Workbook

Sheet Cover
A1: Linde plc — Cover
A2: $ in millions except per-share data | USD | as of 2026-09-15
A4: Linde plc (NYSE: LIN) - Financial Model
A6: Company information
A7: Ticker | B7: LIN
A8: Exchange | B8: NYSE
A9: CIK | B9: 0001707925
A10: Sector / Industry | B10: Materials / Industrial Gases
A11: Reporting currency | B11: USD
A12: Units | B12: $ in millions, except per-share data
A13: Reporting framework | B13: US GAAP
A14: Consolidation scope | B14: Consolidated (Linde plc and subsidiaries)
A15: Fiscal year end | B15: December 31
A16: Periods covered | B16: FY2018 - FY2025 (annual, 8 fiscal years)
A17: Model date | B17: 2026-09-15
A18: Data source | B18: SEC Form 10-K filings, Tier 2 primary source (source.html / prepared/document.md)
A20: Color legend
A21: Blue | B21: Hardcoded reported value (input, traces to a 10-K)
A22: Black | B22: Formula / calculation (subtotal, calc, check)
A23: Green | B23: Cross-sheet link
A24: Grey italic | B24: Memo / commentary (margins, ratios, growth rates)
A26: Sheet directory
A27: Income Statement | B27: IS tab
A28: Balance Sheet | B28: BS tab
A29: Cash Flow Statement | B29: CF tab
A30: Segments | B30: SEG tab
A31: Operating Metrics | B31: OM tab
A32: Derived Metrics | B32: DM tab
A33: Sources | B33: Sources tab
A35: Comparability notes
A36: 1. Segment redefinition (FY2018 -> FY2019) | B36: FY2018 reflects legacy Praxair geographic segments (North America / Europe / South America / Asia / Surface Technologies) plus a separate Linde AG stub, because a 2018 FTC hold-separate order delayed full merger integration. From FY2019, Linde reports on the Americas / EMEA / APAC / Engineering / Other framework, retrospectively recast. The Segments sheet models both structures with min/max period tags; segment totals tie exactly to consolidated Sales and Operating Profit in every year (see SEG tab checks).
A37: 2. Retained earnings / treasury stock discontinuity (FY2022 -> FY2023) | B37: Retained earnings fell from $20,541mm (FY2022) to $8,845mm (FY2023) and treasury stock fell from $(14,737)mm to $(3,133)mm. This is not a restatement or error: the FY2023 Statement of Equity (as shown comparatively in the FY2024 and FY2025 10-Ks) discloses an 'Intercompany reorganization (Note 14)' retiring 61.2 million treasury shares (cost basis $15,300mm) against retained earnings. Total balance sheet equity and Total Assets = Total Liabilities + Equity tie out in every year.
A38: 3. Scope: Geography, Note Schedules, and BS Detail sheets not built separately | B38: The bundle-only collector output classified most non-statement source tables (planned Geography, Note Schedules, and Balance Sheet Detail content) under generic, uninformative block titles that could not be reliably attributed to a specific disclosure without extensive per-table manual inspection. Rather than populate these sheets with low-confidence or unlabeled data, geography content was folded into the Segments sheet (Linde's segments are themselves geographic) and Note Schedules / Balance Sheet Detail were omitted. Segment capital expenditures ('expenditures for long-lived assets') are disclosed on a consistent basis only for FY2023-FY2025 in the companies' own 10-Ks (FY2018-FY2019 used a different, combined 'capex and acquisitions' basis; FY2020-FY2022 10-Ks did not disclose segment capex at all) - the Segments tab shows only the three consistent years rather than mixing bases or estimating. Sales-by-major-country is disclosed for FY2018-FY2019 and FY2023-FY2025 (6 of 8 years, with a FY2020-FY2022 gap in that specific disclosure) and was not incorporated as a separate block given the gap and the already-broad scope of the Segments sheet.

Sheet Income Statement
A1: Linde plc — Income Statement
A2: $ in millions except per-share data | USD | as of 2026-09-15
C3: FY2018 | D3: FY2019 | E3: FY2020 | F3: FY2021 | G3: FY2022 | H3: FY2023 | I3: FY2024 | J3: FY2025
A6: CONTENTS
A7: =HYPERLINK("#'Income Statement'!A9","1. Consolidated Income Statement") -> 1. Consolidated Income Statement
A9: 1. Consolidated Income Statement | K9: 19-25 cagr
A10: Sales | C10: 14900 | D10: 28228 | E10: 27243 | F10: 30793 | G10: 33364 | H10: 32854 | I10: 33005 | J10: 33986 | K10: =POWER(J10/D10,1/6)-1 -> 0.031422634
A11: Sales growth % | D11: =IF(N(C10)=0,"",D10/C10-1) -> 0.89449664 | E11: =IF(N(D10)=0,"",E10/D10-1) -> -0.034894431 | F11: =IF(N(E10)=0,"",F10/E10-1) -> 0.1303087 | G11: =IF(N(F10)=0,"",G10/F10-1) -> 0.083493002 | H11: =IF(N(G10)=0,"",H10/G10-1) -> -0.015285937 | I11: =IF(N(H10)=0,"",I10/H10-1) -> 0.0045960918 | J11: =IF(N(I10)=0,"",J10/I10-1) -> 0.029722769
A13: Cost of sales (excl. D&A) | C13: 9084 | D13: 16644 | E13: 15383 | F13: 17543 | G13: 19450 | H13: 17492 | I13: 17143 | J13: 17389 | K13: =POWER(J13/D13,1/6)-1 -> 0.0073247006
A14: Gross Profit | C14: =C10-C13 -> 5816 | D14: =D10-D13 -> 11584 | E14: =E10-E13 -> 11860 | F14: =F10-F13 -> 13250 | G14: =G10-G13 -> 13914 | H14: =H10-H13 -> 15362 | I14: =I10-I13 -> 15862 | J14: =J10-J13 -> 16597 | K14: =POWER(J14/D14,1/6)-1 -> 0.06176525
A15: Gross margin % | C15: =C14/C10 -> 0.39033557 | D15: =D14/D10 -> 0.41037268 | E15: =E14/E10 -> 0.43534119 | F15: =F14/F10 -> 0.4302926 | G15: =G14/G10 -> 0.41703633 | H15: =H14/H10 -> 0.46758386 | I15: =I14/I10 -> 0.48059385 | J15: =J14/J10 -> 0.48834814
A17: Selling, general and administrative expenses | C17: 1629 | D17: 3457 | E17: 3193 | F17: 3189 | G17: 3107 | H17: 3295 | I17: 3337 | J17: 3433 | K17: =POWER(J17/D17,1/6)-1 -> -0.0011604339
A18: Research and development | C18: 113 | D18: 184 | E18: 152 | F18: 143 | G18: 143 | H18: 146 | I18: 150 | J18: 147
A19: Depreciation and amortization | C19: 1830 | D19: 4675 | E19: 4626 | F19: 4635 | G19: 4204 | H19: 3816 | I19: 3780 | J19: 3763 | K19: =POWER(J19/D19,1/6)-1 -> -0.0355225
A20: Cost reduction / restructuring / transaction charges (Note 3) | B20: Label varies by year: Transaction/merger costs (2018), Cost reduction programs and other charges (2019-2021, 2023-2025), Russia-Ukraine related charges (2022). | C20: 309 | D20: 567 | E20: 506 | F20: 273 | G20: 1029 | H20: 40 | I20: 145 | J20: 273
A21: Net gain on sale of businesses | B21: Gains from divestitures required by FTC merger-clearance order; material only FY2018-FY2019. | C21: -3294 | D21: -164
A22: Other (income) expense - net | C22: -18 | D22: -68 | E22: 61 | F22: 26 | G22: 62 | H22: 41 | I22: -185 | J22: 58
A23: Operating Profit | C23: =C14-C17-C18-C19-C20-C21-C22 -> 5247 | D23: =D14-D17-D18-D19-D20-D21-D22 -> 2933 | E23: =E14-E17-E18-E19-E20-E21-E22 -> 3322 | F23: =F14-F17-F18-F19-F20-F21-F22 -> 4984 | G23: =G14-G17-G18-G19-G20-G21-G22 -> 5369 | H23: =H14-H17-H18-H19-H20-H21-H22 -> 8024 | I23: =I14-I17-I18-I19-I20-I21-I22 -> 8635 | J23: =J14-J17-J18-J19-J20-J21-J22 -> 8923 | K23: =POWER(J23/D23,1/6)-1 -> 0.20374124
A24: Operating margin % | C24: =C23/C10 -> 0.35214765 | D24: =D23/D10 -> 0.10390393 | E24: =E23/E10 -> 0.12193958 | F24: =F23/F10 -> 0.16185497 | G24: =G23/G10 -> 0.16092195 | H24: =H23/H10 -> 0.24423206 | I24: =I23/I10 -> 0.26162703 | J24: =J23/J10 -> 0.26254928
A26: Interest expense - net | C26: 202 | D26: 38 | E26: 115 | F26: 77 | G26: 63 | H26: 200 | I26: 256 | J26: 255
A27: Net pension/OPEB (benefit) cost, excl. service cost | C27: -4 | D27: -32 | E27: -177 | F27: -192 | G27: -237 | H27: -164 | I27: -190 | J27: -229
A28: Income Before Income Taxes and Equity Investments | C28: =C23-C26-C27 -> 5049 | D28: =D23-D26-D27 -> 2927 | E28: =E23-E26-E27 -> 3384 | F28: =F23-F26-F27 -> 5099 | G28: =G23-G26-G27 -> 5543 | H28: =H23-H26-H27 -> 7988 | I28: =I23-I26-I27 -> 8569 | J28: =J23-J26-J27 -> 8897
A29: Income taxes | C29: 817 | D29: 769 | E29: 847 | F29: 1262 | G29: 1434 | H29: 1814 | I29: 2002 | J29: 1989 | K29: =POWER(J29/D29,1/6)-1 -> 0.17161451
A30: Effective tax rate % | C30: =C29/C28 -> 0.16181422 | D30: =D29/D28 -> 0.26272634 | E30: =E29/E28 -> 0.25029551 | F30: =F29/F28 -> 0.24749951 | G30: =G29/G28 -> 0.25870467 | H30: =H29/H28 -> 0.22709064 | I30: =I29/I28 -> 0.23363286 | J30: =J29/J28 -> 0.2235585
A31: Income Before Equity Investments | C31: =C28-C29 -> 4232 | D31: =D28-D29 -> 2158 | E31: =E28-E29 -> 2537 | F31: =F28-F29 -> 3837 | G31: =G28-G29 -> 4109 | H31: =H28-H29 -> 6174 | I31: =I28-I29 -> 6567 | J31: =J28-J29 -> 6908
A32: Income from equity investments | C32: 56 | D32: 114 | E32: 85 | F32: 119 | G32: 172 | H32: 167 | I32: 170 | J32: 150
A33: Income from discontinued operations, net of tax | B33: Material only FY2018-FY2021; nil/not presented thereafter. | C33: 117 | D33: 109 | E33: 4 | F33: 5
A34: Net Income (Including Noncontrolling Interests) | C34: =C31+C32+C33 -> 4405 | D34: =D31+D32+D33 -> 2381 | E34: =E31+E32+E33 -> 2626 | F34: =F31+F32+F33 -> 3961 | G34: =G31+G32+G33 -> 4281 | H34: =H31+H32+H33 -> 6341 | I34: =I31+I32+I33 -> 6737 | J34: =J31+J32+J33 -> 7058
A35: Less: noncontrolling interests | C35: -15 | D35: -89 | E35: -125 | F35: -135 | G35: -134 | H35: -142 | I35: -172 | J35: -160
A36: Less: noncontrolling interests from discontinued operations | C36: -9 | D36: -7
A37: Net Income - Linde plc | C37: =C34+C35+C36 -> 4381 | D37: =D34+D35+D36 -> 2285 | E37: =E34+E35+E36 -> 2501 | F37: =F34+F35+F36 -> 3826 | G37: =G34+G35+G36 -> 4147 | H37: =H34+H35+H36 -> 6199 | I37: =I34+I35+I36 -> 6565 | J37: =J34+J35+J36 -> 6898
A38: Net margin % | C38: =C37/C10 -> 0.29402685 | D38: =D37/D10 -> 0.080947995 | E38: =E37/E10 -> 0.091803399 | F38: =F37/F10 -> 0.12424902 | G38: =G37/G10 -> 0.12429565 | H38: =H37/H10 -> 0.18868327 | I38: =I37/I10 -> 0.19890926 | J38: =J37/J10 -> 0.20296593
A39: Net income growth % | D39: =IF(N(C37)=0,"",D37/C37-1) -> -0.47842958 | E39: =IF(N(D37)=0,"",E37/D37-1) -> 0.09452954 | F39: =IF(N(E37)=0,"",F37/E37-1) -> 0.52978808 | G39: =IF(N(F37)=0,"",G37/F37-1) -> 0.083899634 | H39: =IF(N(G37)=0,"",H37/G37-1) -> 0.49481553 | I39: =IF(N(H37)=0,"",I37/H37-1) -> 0.059041781 | J39: =IF(N(I37)=0,"",J37/I37-1) -> 0.050723534
A41: Check: computed Net Income - Linde plc vs. reported | C41: =C37-C37 -> 0 | D41: =D37-D37 -> 0 | E41: =E37-E37 -> 0 | F41: =F37-F37 -> 0 | G41: =G37-G37 -> 0 | H41: =H37-H37 -> 0 | I41: =I37-I37 -> 0 | J41: =J37-J37 -> 0
A43: Basic earnings per share | C43: 13.26 | D43: 4.22 | E43: 4.75 | F43: 7.4 | G43: 8.3 | H43: 12.7 | I43: 13.71 | J43: 14.69 | K43: =POWER(J43/D43,1/6)-1 -> 0.23107607
A44: Basic EPS growth % | D44: =IF(N(C43)=0,"",D43/C43-1) -> -0.68174962 | E44: =IF(N(D43)=0,"",E43/D43-1) -> 0.12559242 | F44: =IF(N(E43)=0,"",F43/E43-1) -> 0.55789474 | G44: =IF(N(F43)=0,"",G43/F43-1) -> 0.12162162 | H44: =IF(N(G43)=0,"",H43/G43-1) -> 0.53012048 | I44: =IF(N(H43)=0,"",I43/H43-1) -> 0.079527559 | J44: =IF(N(I43)=0,"",J43/I43-1) -> 0.071480671
A45: Diluted earnings per share | C45: 13.11 | D45: 4.19 | E45: 4.71 | F45: 7.33 | G45: 8.23 | H45: 12.59 | I45: 13.62 | J45: 14.61 | K45: =POWER(J45/D45,1/6)-1 -> 0.23141952
A46: Diluted EPS growth % | D46: =IF(N(C45)=0,"",D45/C45-1) -> -0.68039664 | E46: =IF(N(D45)=0,"",E45/D45-1) -> 0.12410501 | F46: =IF(N(E45)=0,"",F45/E45-1) -> 0.55626327 | G46: =IF(N(F45)=0,"",G45/F45-1) -> 0.12278308 | H46: =IF(N(G45)=0,"",H45/G45-1) -> 0.52976914 | I46: =IF(N(H45)=0,"",I45/H45-1) -> 0.081810961 | J46: =IF(N(I45)=0,"",J45/I45-1) -> 0.072687225
A47: Weighted average shares - basic (thousands) | C47: 330401 | D47: 541094 | E47: 526736 | F47: 516896 | G47: 499736 | H47: 488191 | I47: 478773 | J47: 469488 | K47: =POWER(J47/D47,1/6)-1 -> -0.023380714
A48: Weighted average shares - diluted (thousands) | C48: 334127 | D48: 545170 | E48: 531157 | F48: 521875 | G48: 504038 | H48: 492290 | I48: 482092 | J48: 472195 | K48: =POWER(J48/D48,1/6)-1 -> -0.023666392

Sheet Balance Sheet
A1: Linde plc — Balance Sheet
A2: $ in millions except per-share data | USD | as of 2026-09-15
C3: FY2018 | D3: FY2019 | E3: FY2020 | F3: FY2021 | G3: FY2022 | H3: FY2023 | I3: FY2024 | J3: FY2025
A6: CONTENTS
A7: =HYPERLINK("#'Balance Sheet'!A9","1. Consolidated Balance Sheet") -> 1. Consolidated Balance Sheet
A9: 1. Consolidated Balance Sheet
A10: Cash and cash equivalents | C10: 4466 | D10: 2700 | E10: 3754 | F10: 2823 | G10: 5436 | H10: 4664 | I10: 4850 | J10: 5056
A11: Trade accounts receivable - net | C11: 4297 | D11: 4322 | E11: 4167 | F11: 4499 | G11: 4559 | H11: 4718 | I11: 4622 | J11: 4966
A12: Contract assets | C12: 283 | D12: 368 | E12: 162 | F12: 134 | G12: 124 | H12: 196 | I12: 263 | J12: 269
A13: Inventories | C13: 1651 | D13: 1697 | E13: 1729 | F13: 1733 | G13: 1978 | H13: 2115 | I13: 1946 | J13: 2055
A14: Assets held for sale | B14: Businesses divested to satisfy FTC merger-clearance order; resolved by FY2020. | C14: 5498 | D14: 125
A15: Prepaid and other current assets | C15: 1077 | D15: 1140 | E15: 1112 | F15: 970 | G15: 950 | H15: 927 | I15: 1264 | J15: 979
A16: Total Current Assets | C16: =C10+C11+C12+C13+C14+C15 -> 17272 | D16: =D10+D11+D12+D13+D14+D15 -> 10352 | E16: =E10+E11+E12+E13+E14+E15 -> 10924 | F16: =F10+F11+F12+F13+F14+F15 -> 10159 | G16: =G10+G11+G12+G13+G14+G15 -> 13047 | H16: =H10+H11+H12+H13+H14+H15 -> 12620 | I16: =I10+I11+I12+I13+I14+I15 -> 12945 | J16: =J10+J11+J12+J13+J14+J15 -> 13325
A18: Property, plant and equipment - net | C18: 29717 | D18: 29064 | E18: 28711 | F18: 26003 | G18: 23548 | H18: 24552 | I18: 24775 | J18: 28260
A19: Equity investments | C19: 1838 | D19: 2027 | E19: 2061 | F19: 2619 | G19: 2350 | H19: 2190 | I19: 2130 | J19: 2015
A20: Goodwill | C20: 26874 | D20: 27019 | E20: 28201 | F20: 27038 | G20: 25817 | H20: 26751 | I20: 25937 | J20: 27927
A21: Other intangible assets - net | C21: 16223 | D21: 16137 | E21: 16184 | F21: 13802 | G21: 12420 | H21: 12399 | I21: 11330 | J21: 11871
A22: Other long-term assets | C22: 1462 | D22: 2013 | E22: 2148 | F22: 1984 | G22: 2476 | H22: 2299 | I22: 3030 | J22: 3419
A23: Total Assets | C23: =C16+C18+C19+C20+C21+C22 -> 93386 | D23: =D16+D18+D19+D20+D21+D22 -> 86612 | E23: =E16+E18+E19+E20+E21+E22 -> 88229 | F23: =F16+F18+F19+F20+F21+F22 -> 81605 | G23: =G16+G18+G19+G20+G21+G22 -> 79658 | H23: =H16+H18+H19+H20+H21+H22 -> 80811 | I23: =I16+I18+I19+I20+I21+I22 -> 80147 | J23: =J16+J18+J19+J20+J21+J22 -> 86817
A25: Trade accounts payable | C25: 3219 | D25: 3266 | E25: 3095 | F25: 3503 | G25: 2995 | H25: 3020 | I25: 2507 | J25: 2810
A26: Short-term debt | C26: 1485 | D26: 1732 | E26: 3251 | F26: 1163 | G26: 4117 | H26: 4713 | I26: 4223 | J26: 4510
A27: Current portion of long-term debt | C27: 1523 | D27: 1531 | E27: 751 | F27: 1709 | G27: 1599 | H27: 1263 | I27: 2057 | J27: 1796
A28: Contract liabilities | C28: 1546 | D28: 1758 | E28: 1769 | F28: 2940 | G28: 3073 | H28: 1901 | I28: 1194 | J28: 1231
A29: Accrued taxes | C29: 657 | D29: 370 | E29: 542 | F29: 429 | G29: 613 | H29: 664 | I29: 637 | J29: 680
A30: Liabilities held for sale | C30: 768 | D30: 2
A31: Other current liabilities | C31: 3758 | D31: 3501 | E31: 4332 | F31: 3899 | G31: 4082 | H31: 4156 | I31: 3926 | J31: 4171
A32: Total Current Liabilities | C32: =C25+C26+C27+C28+C29+C30+C31 -> 12956 | D32: =D25+D26+D27+D28+D29+D30+D31 -> 12160 | E32: =E25+E26+E27+E28+E29+E30+E31 -> 13740 | F32: =F25+F26+F27+F28+F29+F30+F31 -> 13643 | G32: =G25+G26+G27+G28+G29+G30+G31 -> 16479 | H32: =H25+H26+H27+H28+H29+H30+H31 -> 15717 | I32: =I25+I26+I27+I28+I29+I30+I31 -> 14544 | J32: =J25+J26+J27+J28+J29+J30+J31 -> 15198
A34: Long-term debt | C34: 12288 | D34: 10693 | E34: 12152 | F34: 11335 | G34: 12198 | H34: 13397 | I34: 15343 | J34: 20683
A35: Other long-term liabilities | C35: 3435 | D35: 4888 | E35: 5519 | F35: 4188 | G35: 2795 | H35: 3804 | I35: 4015 | J35: 4355
A36: Deferred credits | C36: 7611 | D36: 7236 | E36: 7236 | F36: 6998 | G36: 6799 | H36: 6798 | I36: 6757 | J36: 6840
A37: Total Liabilities | C37: =C32+C34+C35+C36 -> 36290 | D37: =D32+D34+D35+D36 -> 34977 | E37: =E32+E34+E35+E36 -> 38647 | F37: =F32+F34+F35+F36 -> 36164 | G37: =G32+G34+G35+G36 -> 38271 | H37: =H32+H34+H35+H36 -> 39716 | I37: =I32+I34+I35+I36 -> 40659 | J37: =J32+J34+J35+J36 -> 47076
A39: Redeemable noncontrolling interests | C39: 16 | D39: 113 | E39: 13 | F39: 13 | G39: 13 | H39: 13 | I39: 13 | J39: 13
A41: Ordinary shares (par value) | C41: 1 | D41: 1 | E41: 1 | F41: 1 | G41: 1 | H41: 1 | I41: 1 | J41: 1
A42: Additional paid-in capital | C42: 40151 | D42: 40201 | E42: 40202 | F42: 40180 | G42: 40005 | H42: 39812 | I42: 39603 | J42: 39430
A43: Retained earnings | B43: FY2023 drop vs FY2022 reflects an intercompany reorganization (Note 14): retirement of treasury shares against retained earnings, not a restatement or error. | C43: 16529 | D43: 16842 | E43: 17178 | F43: 18710 | G43: 20541 | H43: 8845 | I43: 12634 | J43: 16608
A44: Accumulated other comprehensive income (loss) | C44: -4456 | D44: -4814 | E44: -4690 | F44: -5048 | G44: -5782 | H44: -5805 | I44: -6894 | J44: -6233
A45: Treasury stock, at cost | B45: FY2023 drop vs FY2022 reflects the same intercompany reorganization (Note 14) treasury-share retirement. | C45: -629 | D45: -3156 | E45: -5374 | F45: -9808 | G45: -14737 | H45: -3133 | I45: -7252 | J45: -11561
A46: Total Linde plc Shareholders' Equity | C46: =C41+C42+C43+C44+C45 -> 51596 | D46: =D41+D42+D43+D44+D45 -> 49074 | E46: =E41+E42+E43+E44+E45 -> 47317 | F46: =F41+F42+F43+F44+F45 -> 44035 | G46: =G41+G42+G43+G44+G45 -> 40028 | H46: =H41+H42+H43+H44+H45 -> 39720 | I46: =I41+I42+I43+I44+I45 -> 38092 | J46: =J41+J42+J43+J44+J45 -> 38245
A47: Noncontrolling interests | C47: 5484 | D47: 2448 | E47: 2252 | F47: 1393 | G47: 1346 | H47: 1362 | I47: 1383 | J47: 1483
A48: Total Equity | C48: =C46+C47 -> 57080 | D48: =D46+D47 -> 51522 | E48: =E46+E47 -> 49569 | F48: =F46+F47 -> 45428 | G48: =G46+G47 -> 41374 | H48: =H46+H47 -> 41082 | I48: =I46+I47 -> 39475 | J48: =J46+J47 -> 39728
A50: Check: Total Assets - Total Liabilities - Redeemable NCI - Total Equity | C50: =C23-C37-C39-C48 -> 0 | D50: =D23-D37-D39-D48 -> 0 | E50: =E23-E37-E39-E48 -> 0 | F50: =F23-F37-F39-F48 -> 0 | G50: =G23-G37-G39-G48 -> 0 | H50: =H23-H37-H39-H48 -> 0 | I50: =I23-I37-I39-I48 -> 0 | J50: =J23-J37-J39-J48 -> 0
A52: Days Sales Outstanding (DSO) | C52: =C11/'Income Statement'!C10*365 -> 105.26208 | D52: =D11/'Income Statement'!D10*365 -> 55.885291 | E52: =E11/'Income Statement'!E10*365 -> 55.829204 | F52: =F11/'Income Statement'!F10*365 -> 53.328191 | G52: =G11/'Income Statement'!G10*365 -> 49.875165 | H52: =H11/'Income Statement'!H10*365 -> 52.41584 | I52: =I11/'Income Statement'!I10*365 -> 51.114377 | J52: =J11/'Income Statement'!J10*365 -> 53.333431
A53: Days Inventory Outstanding (DIO) | C53: =C13/'Income Statement'!C13*365 -> 66.338067 | D53: =D13/'Income Statement'!D13*365 -> 37.214912 | E53: =E13/'Income Statement'!E13*365 -> 41.024833 | F53: =F13/'Income Statement'!F13*365 -> 36.056832 | G53: =G13/'Income Statement'!G13*365 -> 37.11928 | H53: =H13/'Income Statement'!H13*365 -> 44.133032 | I53: =I13/'Income Statement'!I13*365 -> 41.433238 | J53: =J13/'Income Statement'!J13*365 -> 43.135028
A54: Days Payable Outstanding (DPO) | C54: =C25/'Income Statement'!C13*365 -> 129.34115 | D54: =D25/'Income Statement'!D13*365 -> 71.622807 | E54: =E25/'Income Statement'!E13*365 -> 73.436586 | F54: =F25/'Income Statement'!F13*365 -> 72.883486 | G54: =G25/'Income Statement'!G13*365 -> 56.20437 | H54: =H25/'Income Statement'!H13*365 -> 63.017379 | I54: =I25/'Income Statement'!I13*365 -> 53.377764 | J54: =J25/'Income Statement'!J13*365 -> 58.98269
A55: Cash Conversion Cycle (CCC) | C55: =C52+C53-C54 -> 42.258998 | D55: =D52+D53-D54 -> 21.477396 | E55: =E52+E53-E54 -> 23.417451 | F55: =F52+F53-F54 -> 16.501537 | G55: =G52+G53-G54 -> 30.790075 | H55: =H52+H53-H54 -> 33.531493 | I55: =I52+I53-I54 -> 39.169851 | J55: =J52+J53-J54 -> 37.485769

Sheet Cash Flow Statement
A1: Linde plc — Cash Flow Statement
A2: $ in millions except per-share data | USD | as of 2026-09-15
C3: FY2018 | D3: FY2019 | E3: FY2020 | F3: FY2021 | G3: FY2022 | H3: FY2023 | I3: FY2024 | J3: FY2025
A6: CONTENTS
A7: =HYPERLINK("#'Cash Flow Statement'!A9","1. Consolidated Statement of Cash Flows") -> 1. Consolidated Statement of Cash Flows
A9: 1. Consolidated Statement of Cash Flows
A10: Net income - Linde plc | C10: ='Income Statement'!C37 -> 4381 | D10: ='Income Statement'!D37 -> 2285 | E10: ='Income Statement'!E37 -> 2501 | F10: ='Income Statement'!F37 -> 3826 | G10: ='Income Statement'!G37 -> 4147 | H10: ='Income Statement'!H37 -> 6199 | I10: ='Income Statement'!I37 -> 6565 | J10: ='Income Statement'!J37 -> 6898
A11: Less: income from discontinued operations, net of tax and NCI | C11: -108 | D11: -102 | E11: -4 | F11: -5
A12: Add: noncontrolling interests | C12: 15 | D12: 89 | E12: 125 | F12: 135 | G12: 134 | H12: 142 | I12: 172 | J12: 160
A13: Net Income (Including Noncontrolling Interests) | C13: =C10+C11+C12 -> 4288 | D13: =D10+D11+D12 -> 2272 | E13: =E10+E11+E12 -> 2622 | F13: =F10+F11+F12 -> 3956 | G13: =G10+G11+G12 -> 4281 | H13: =H10+H11+H12 -> 6341 | I13: =I10+I11+I12 -> 6737 | J13: =J10+J11+J12 -> 7058
A15: Cost reduction / restructuring / geopolitical charges, net of payments | C15: 40 | D15: -236 | E15: 258 | F15: 98 | G15: 902 | H15: -118 | I15: 31 | J15: 139
A16: Amortization of inventory step-up | C16: 368 | D16: 12
A17: U.S. Tax Act re-measurement charge | C17: -61
A18: Depreciation and amortization | C18: ='Income Statement'!C19 -> 1830 | D18: ='Income Statement'!D19 -> 4675 | E18: ='Income Statement'!E19 -> 4626 | F18: ='Income Statement'!F19 -> 4635 | G18: ='Income Statement'!G19 -> 4204 | H18: ='Income Statement'!H19 -> 3816 | I18: ='Income Statement'!I19 -> 3780 | J18: ='Income Statement'!J19 -> 3763
A19: Deferred income taxes | C19: -187 | D19: -303 | E19: -369 | F19: -254 | G19: -383 | H19: -84 | I19: -142 | J19: -465
A20: Share-based compensation | C20: 62 | D20: 95 | E20: 133 | F20: 128 | G20: 107 | H20: 141 | I20: 160 | J20: 164
A21: Net gain on sale of businesses, net of tax | C21: -2923 | D21: -108
A22: Other non-cash items | C22: 175 | D22: -127 | E22: 152 | F22: -19 | G22: -49 | H22: 43 | I22: -72 | J22: 23
A23: (Increase) decrease in accounts receivable | C23: -124 | D23: 80 | E23: 19 | F23: -553 | G23: -423 | H23: -86 | I23: -160 | J23: -122
A24: Contract assets and liabilities, net | D24: 87 | E24: 90 | F24: 1307 | G24: 310 | H24: -168 | I24: -409 | J24: -72
A25: (Increase) decrease in inventories | C25: -4 | D25: -81 | E25: 18 | F25: -129 | G25: -347 | H25: -127 | I25: 56 | J25: 47
A26: (Increase) decrease in prepaid and other current assets | C26: 43 | D26: -72 | E26: 128 | F26: 76 | G26: -157 | H26: 66 | I26: -55 | J26: 55
A27: Increase (decrease) in accounts payable | C27: 287 | D27: -174 | E27: 109 | F27: 447 | G27: 307 | H27: -168 | I27: -277 | J27: -148
A28: Pension and OPEB contributions | C28: -87 | D28: -94 | E28: -91 | F28: -42 | G28: -51 | H28: -46 | I28: -35 | J28: -25
A29: Other long-term assets and liabilities, net | C29: -53 | D29: 93 | E29: -266 | F29: 75 | G29: 163 | H29: -305 | I29: -191 | J29: -67
A30: Net Cash Provided by Operating Activities | C30: =C13+C15+C16+C17+C18+C19+C20+C21+C22+C23+C24+C25+C26+C27+C28+C29 -> 3654 | D30: =D13+D15+D16+D17+D18+D19+D20+D21+D22+D23+D24+D25+D26+D27+D28+D29 -> 6119 | E30: =E13+E15+E16+E17+E18+E19+E20+E21+E22+E23+E24+E25+E26+E27+E28+E29 -> 7429 | F30: =F13+F15+F16+F17+F18+F19+F20+F21+F22+F23+F24+F25+F26+F27+F28+F29 -> 9725 | G30: =G13+G15+G16+G17+G18+G19+G20+G21+G22+G23+G24+G25+G26+G27+G28+G29 -> 8864 | H30: =H13+H15+H16+H17+H18+H19+H20+H21+H22+H23+H24+H25+H26+H27+H28+H29 -> 9305 | I30: =I13+I15+I16+I17+I18+I19+I20+I21+I22+I23+I24+I25+I26+I27+I28+I29 -> 9423 | J30: =J13+J15+J16+J17+J18+J19+J20+J21+J22+J23+J24+J25+J26+J27+J28+J29 -> 10350
A31: CFO margin % | C31: =C30/'Income Statement'!C10 -> 0.2452349 | D31: =D30/'Income Statement'!D10 -> 0.21677058 | E31: =E30/'Income Statement'!E10 -> 0.2726939 | F31: =F30/'Income Statement'!F10 -> 0.31581853 | G31: =G30/'Income Statement'!G10 -> 0.26567558 | H31: =H30/'Income Statement'!H10 -> 0.28322274 | I31: =I30/'Income Statement'!I10 -> 0.2855022 | J31: =J30/'Income Statement'!J10 -> 0.30453716
A33: Capital expenditures | C33: -1883 | D33: -3682 | E33: -3400 | F33: -3086 | G33: -3173 | H33: -3787 | I33: -4497 | J33: -5261
A34: Acquisitions, net of cash acquired | C34: -25 | D34: -225 | E34: -68 | F34: -88 | G34: -110 | H34: -953 | I34: -317 | J34: -412
A35: Divestitures / proceeds from sale of assets | C35: 5908 | D35: 5096 | E35: 482 | F35: 167 | G35: 195 | H35: 70 | I35: 170 | J35: 42
A36: Cash acquired in Linde AG / Praxair merger | C36: 1363
A37: Other investing activities, net | J37: -90
A38: Net Cash (Used in) Provided by Investing Activities | C38: =C33+C34+C35+C36+C37 -> 5363 | D38: =D33+D34+D35+D36+D37 -> 1189 | E38: =E33+E34+E35+E36+E37 -> -2986 | F38: =F33+F34+F35+F36+F37 -> -3007 | G38: =G33+G34+G35+G36+G37 -> -3088 | H38: =H33+H34+H35+H36+H37 -> -4670 | I38: =I33+I34+I35+I36+I37 -> -4644 | J38: =J33+J34+J35+J36+J37 -> -5721
A40: Net change in short-term debt | C40: 208 | D40: 224 | E40: 1198 | F40: -1329 | G40: 3050 | H40: 554 | I40: -372 | J40: 41
A41: Long-term debt borrowings | C41: 8 | D41: 99 | E41: 2796 | F41: 2283 | G41: 3210 | H41: 2188 | I41: 4844 | J41: 5148
A42: Long-term debt repayments | C42: -3124 | D42: -1583 | E42: -2681 | F42: -1468 | G42: -1785 | H42: -1682 | I42: -1305 | J42: -2278
A43: Proceeds from issuance of ordinary shares | C43: 77 | D43: 72 | E43: 47 | F43: 50 | G43: 36 | H43: 33 | I43: 31 | J43: 23
A44: Purchases of ordinary shares (buybacks) | C44: -599 | D44: -2658 | E44: -2457 | F44: -4612 | G44: -5168 | H44: -3958 | I44: -4482 | J44: -4601
A45: Cash dividends paid | C45: -1166 | D45: -1891 | E45: -2028 | F45: -2189 | G45: -2344 | H45: -2482 | I45: -2655 | J45: -2811
A46: NCI transactions and other financing activities, net | C46: -402 | D46: -3260 | E46: -220 | F46: -323 | G46: -88 | H46: -53 | I46: -420 | J46: -76
A47: Net Cash Used in Financing Activities | C47: =C40+C41+C42+C43+C44+C45+C46 -> -4998 | D47: =D40+D41+D42+D43+D44+D45+D46 -> -8997 | E47: =E40+E41+E42+E43+E44+E45+E46 -> -3345 | F47: =F40+F41+F42+F43+F44+F45+F46 -> -7588 | G47: =G40+G41+G42+G43+G44+G45+G46 -> -3089 | H47: =H40+H41+H42+H43+H44+H45+H46 -> -5400 | I47: =I40+I41+I42+I43+I44+I45+I46 -> -4359 | J47: =J40+J41+J42+J43+J44+J45+J46 -> -4554
A49: Discontinued operations - operating activities | C49: 48 | D49: 69
A50: Discontinued operations - investing activities | C50: -23 | D50: -60
A51: Discontinued operations - financing activities | C51: 2 | D51: 5
A52: Net Cash Flows of Discontinued Operations | C52: =C49+C50+C51 -> 27 | D52: =D49+D50+D51 -> 14 | E52: =E49+E50+E51 -> 0 | F52: =F49+F50+F51 -> 0 | G52: =G49+G50+G51 -> 0 | H52: =H49+H50+H51 -> 0 | I52: =I49+I50+I51 -> 0 | J52: =J49+J50+J51 -> 0
A54: Effect of exchange rate changes on cash | C54: -60 | D54: -77 | E54: -44 | F54: -61 | G54: -74 | H54: -7 | I54: -234 | J54: 131
A55: Change in Cash and Cash Equivalents | C55: =C30+C38+C47+C52+C54 -> 3986 | D55: =D30+D38+D47+D52+D54 -> -1752 | E55: =E30+E38+E47+E52+E54 -> 1054 | F55: =F30+F38+F47+F52+F54 -> -931 | G55: =G30+G38+G47+G52+G54 -> 2613 | H55: =H30+H38+H47+H52+H54 -> -772 | I55: =I30+I38+I47+I52+I54 -> 186 | J55: =J30+J38+J47+J52+J54 -> 206
A56: Cash of discontinued operations, reclassification | C56: -137 | D56: -14
A57: Cash and cash equivalents, beginning of period | C57: 617 | D57: 4466 | E57: 2700 | F57: 3754 | G57: 2823 | H57: 5436 | I57: 4664 | J57: 4850
A58: Cash and Cash Equivalents, End of Period | C58: =C57+C55+C56 -> 4466 | D58: =D57+D55+D56 -> 2700 | E58: =E57+E55+E56 -> 3754 | F58: =F57+F55+F56 -> 2823 | G58: =G57+G55+G56 -> 5436 | H58: =H57+H55+H56 -> 4664 | I58: =I57+I55+I56 -> 4850 | J58: =J57+J55+J56 -> 5056
A60: Check: CF-derived ending cash vs. Balance Sheet cash | C60: =C58-'Balance Sheet'!C10 -> 0 | D60: =D58-'Balance Sheet'!D10 -> 0 | E60: =E58-'Balance Sheet'!E10 -> 0 | F60: =F58-'Balance Sheet'!F10 -> 0 | G60: =G58-'Balance Sheet'!G10 -> 0 | H60: =H58-'Balance Sheet'!H10 -> 0 | I60: =I58-'Balance Sheet'!I10 -> 0 | J60: =J58-'Balance Sheet'!J10 -> 0
A62: Free Cash Flow (CFO + Capex) | C62: =C30+C33 -> 1771 | D62: =D30+D33 -> 2437 | E62: =E30+E33 -> 4029 | F62: =F30+F33 -> 6639 | G62: =G30+G33 -> 5691 | H62: =H30+H33 -> 5518 | I62: =I30+I33 -> 4926 | J62: =J30+J33 -> 5089
A63: FCF growth % | D63: =IF(N(C62)=0,"",D62/C62-1) -> 0.37605872 | E63: =IF(N(D62)=0,"",E62/D62-1) -> 0.65326221 | F63: =IF(N(E62)=0,"",F62/E62-1) -> 0.64780343 | G63: =IF(N(F62)=0,"",G62/F62-1) -> -0.14279259 | H63: =IF(N(G62)=0,"",H62/G62-1) -> -0.030398875 | I63: =IF(N(H62)=0,"",I62/H62-1) -> -0.10728525 | J63: =IF(N(I62)=0,"",J62/I62-1) -> 0.033089728
A64: Capex % of sales | C64: =0-C33/'Income Statement'!C10 -> 0.12637584 | D64: =0-D33/'Income Statement'!D10 -> 0.13043786 | E64: =0-E33/'Income Statement'!E10 -> 0.1248027 | F64: =0-F33/'Income Statement'!F10 -> 0.10021758 | G64: =0-G33/'Income Statement'!G10 -> 0.095102506 | H64: =0-H33/'Income Statement'!H10 -> 0.11526755 | I64: =0-I33/'Income Statement'!I10 -> 0.13625208 | J64: =0-J33/'Income Statement'!J10 -> 0.15479903
A65: FCF margin % | C65: =C62/'Income Statement'!C10 -> 0.11885906 | D65: =D62/'Income Statement'!D10 -> 0.086332719 | E65: =E62/'Income Statement'!E10 -> 0.1478912 | F65: =F62/'Income Statement'!F10 -> 0.21560095 | G65: =G62/'Income Statement'!G10 -> 0.17057307 | H65: =H62/'Income Statement'!H10 -> 0.1679552 | I65: =I62/'Income Statement'!I10 -> 0.14925011 | J65: =J62/'Income Statement'!J10 -> 0.14973813
A66: FCF conversion (FCF / Net Income) | C66: =C62/'Income Statement'!C37 -> 0.40424561 | D66: =D62/'Income Statement'!D37 -> 1.0665208 | E66: =E62/'Income Statement'!E37 -> 1.6109556 | F66: =F62/'Income Statement'!F37 -> 1.7352326 | G66: =G62/'Income Statement'!G37 -> 1.3723173 | H66: =H62/'Income Statement'!H37 -> 0.89014357 | I66: =I62/'Income Statement'!I37 -> 0.75034273 | J66: =J62/'Income Statement'!J37 -> 0.73775007
A68: Supplemental: income taxes paid | C68: 757 | D68: 1357 | E68: 1066 | F68: 1710 | G68: 1735 | H68: 1955 | I68: 2216
A69: Supplemental: interest paid, net of capitalized interest | C69: 214 | D69: 275 | E69: 322 | F69: 233 | G69: 170 | H69: 451 | I69: 443 | J69: 548

Sheet Segments
A1: Linde plc — Segments
A2: $ in millions except per-share data | USD | as of 2026-09-15
C3: FY2018 | D3: FY2019 | E3: FY2020 | F3: FY2021 | G3: FY2022 | H3: FY2023 | I3: FY2024 | J3: FY2025
A6: CONTENTS
A7: =HYPERLINK("#'Segments'!A9","1. Segment Information (Note - Segment Reporting)") -> 1. Segment Information (Note - Segment Reporting)
A9: 1. Segment Information (Note - Segment Reporting)
A11: North America | C11: 6420
A12: Europe (legacy) | C12: 1592
A13: South America (legacy) | C13: 1369
A14: Asia (legacy) | C14: 1964
A15: Surface Technologies (legacy) | C15: 682
A16: Linde AG (legacy stub) | C16: 2873
A17: Americas | D17: 10993 | E17: 10459 | F17: 12103 | G17: 13874 | H17: 14304 | I17: 14442 | J17: 15208
A18: EMEA | D18: 6643 | E18: 6449 | F18: 7643 | G18: 8443 | H18: 8542 | I18: 8352 | J18: 8549
A19: APAC | D19: 5839 | E19: 5687 | F19: 6133 | G19: 6480 | H19: 6559 | I19: 6632 | J19: 6661
A20: Engineering | D20: 2799 | E20: 2851 | F20: 2867 | G20: 2762 | H20: 2160 | I20: 2322 | J20: 2250
A21: Other | D21: 1954 | E21: 1797 | F21: 2047 | G21: 1805 | H21: 1289 | I21: 1257 | J21: 1318
A22: Total Segment Sales | C22: =C11+C12+C13+C14+C15+C16+C17+C18+C19+C20+C21 -> 14900 | D22: =D11+D12+D13+D14+D15+D16+D17+D18+D19+D20+D21 -> 28228 | E22: =E11+E12+E13+E14+E15+E16+E17+E18+E19+E20+E21 -> 27243 | F22: =F11+F12+F13+F14+F15+F16+F17+F18+F19+F20+F21 -> 30793 | G22: =G11+G12+G13+G14+G15+G16+G17+G18+G19+G20+G21 -> 33364 | H22: =H11+H12+H13+H14+H15+H16+H17+H18+H19+H20+H21 -> 32854 | I22: =I11+I12+I13+I14+I15+I16+I17+I18+I19+I20+I21 -> 33005 | J22: =J11+J12+J13+J14+J15+J16+J17+J18+J19+J20+J21 -> 33986
A23: Check: Total Segment Sales vs. IS Sales | C23: =C22-'Income Statement'!C10 -> 0 | D23: =D22-'Income Statement'!D10 -> 0 | E23: =E22-'Income Statement'!E10 -> 0 | F23: =F22-'Income Statement'!F10 -> 0 | G23: =G22-'Income Statement'!G10 -> 0 | H23: =H22-'Income Statement'!H10 -> 0 | I23: =I22-'Income Statement'!I10 -> 0 | J23: =J22-'Income Statement'!J10 -> 0
A26: North America | C26: 1648
A27: Europe (legacy) | C27: 316
A28: South America (legacy) | C28: 215
A29: Asia (legacy) | C29: 427
A30: Surface Technologies (legacy) | C30: 118
A31: Linde AG (legacy stub) | C31: 252
A32: Americas | D32: 2578 | E32: 2773 | F32: 3368 | G32: 3732 | H32: 4244 | I32: 4550 | J32: 4747
A33: EMEA | D33: 1367 | E33: 1465 | F33: 1889 | G33: 2013 | H33: 2486 | I33: 2780 | J33: 3055
A34: APAC | D34: 1198 | E34: 1277 | F34: 1502 | G34: 1670 | H34: 1806 | I34: 1918 | J34: 1933
A35: Engineering | D35: 390 | E35: 435 | F35: 473 | G35: 555 | H35: 491 | I35: 410 | J35: 408
A36: Other / corporate | D36: -245 | E36: -153 | F36: -56 | G36: -66 | H36: 43 | I36: 62 | J36: -6
A37: Total Segment Operating Profit | C37: =C26+C27+C28+C29+C30+C31+C32+C33+C34+C35+C36 -> 2976 | D37: =D26+D27+D28+D29+D30+D31+D32+D33+D34+D35+D36 -> 5288 | E37: =E26+E27+E28+E29+E30+E31+E32+E33+E34+E35+E36 -> 5797 | F37: =F26+F27+F28+F29+F30+F31+F32+F33+F34+F35+F36 -> 7176 | G37: =G26+G27+G28+G29+G30+G31+G32+G33+G34+G35+G36 -> 7904 | H37: =H26+H27+H28+H29+H30+H31+H32+H33+H34+H35+H36 -> 9070 | I37: =I26+I27+I28+I29+I30+I31+I32+I33+I34+I35+I36 -> 9720 | J37: =J26+J27+J28+J29+J30+J31+J32+J33+J34+J35+J36 -> 10137
A38: Less: special / restructuring / transaction charges (Note 3) | C38: -309 | D38: -567 | E38: -506 | F38: -273 | G38: -1029 | H38: -40 | I38: -145 | J38: -273
A39: Add: net gain on sale of businesses | C39: 3294 | D39: 164
A40: Less: purchase accounting impacts - Linde AG merger | C40: -714 | D40: -1952 | E40: -1969 | F40: -1919 | G40: -1506 | H40: -1006 | I40: -940 | J40: -941
A41: Total Operating Profit (reconciled) | C41: =C37+C38+C39+C40 -> 5247 | D41: =D37+D38+D39+D40 -> 2933 | E41: =E37+E38+E39+E40 -> 3322 | F41: =F37+F38+F39+F40 -> 4984 | G41: =G37+G38+G39+G40 -> 5369 | H41: =H37+H38+H39+H40 -> 8024 | I41: =I37+I38+I39+I40 -> 8635 | J41: =J37+J38+J39+J40 -> 8923
A42: Check: Segment Operating Profit (reconciled) vs. IS Operating Profit | C42: =C41-'Income Statement'!C23 -> 0 | D42: =D41-'Income Statement'!D23 -> 0 | E42: =E41-'Income Statement'!E23 -> 0 | F42: =F41-'Income Statement'!F23 -> 0 | G42: =G41-'Income Statement'!G23 -> 0 | H42: =H41-'Income Statement'!H23 -> 0 | I42: =I41-'Income Statement'!I23 -> 0 | J42: =J41-'Income Statement'!J23 -> 0
A45: North America | C45: 660
A46: EMEA (legacy: Europe) | C46: 146
A47: South America (legacy) | C47: 148
A48: Asia/South Pacific (legacy) | C48: 204
A49: Surface Technologies (legacy) | C49: 44
A50: Linde AG (legacy stub) | C50: 282
A51: Americas | D51: 1195 | E51: 1196 | F51: 1243 | G51: 1320 | H51: 1423 | I51: 1450 | J51: 1504
A52: EMEA | D52: 749 | E52: 723 | F52: 752 | G52: 661 | H52: 640 | I52: 640 | J52: 681
A53: APAC | D53: 613 | E53: 619 | F53: 611 | G53: 593 | H53: 633 | I53: 641 | J53: 674
A54: Engineering | D54: 35 | E54: 36 | F54: 39 | G54: 33 | H54: 33 | I54: 33 | J54: 32
A55: Other | D55: 143 | E55: 132 | F55: 127 | G55: 116 | H55: 96 | I55: 93 | J55: 95
A56: Total Segment D&A | C56: =C45+C46+C47+C48+C49+C50+C51+C52+C53+C54+C55 -> 1484 | D56: =D45+D46+D47+D48+D49+D50+D51+D52+D53+D54+D55 -> 2735 | E56: =E45+E46+E47+E48+E49+E50+E51+E52+E53+E54+E55 -> 2706 | F56: =F45+F46+F47+F48+F49+F50+F51+F52+F53+F54+F55 -> 2772 | G56: =G45+G46+G47+G48+G49+G50+G51+G52+G53+G54+G55 -> 2723 | H56: =H45+H46+H47+H48+H49+H50+H51+H52+H53+H54+H55 -> 2825 | I56: =I45+I46+I47+I48+I49+I50+I51+I52+I53+I54+I55 -> 2857 | J56: =J45+J46+J47+J48+J49+J50+J51+J52+J53+J54+J55 -> 2986
A57: Add: purchase accounting impacts - Linde AG merger (D&A) | C57: 346 | D57: 1940 | E57: 1920 | F57: 1863 | G57: 1481 | H57: 991 | I57: 923 | J57: 777
A58: Total D&A (reconciled) | C58: =C56+C57 -> 1830 | D58: =D56+D57 -> 4675 | E58: =E56+E57 -> 4626 | F58: =F56+F57 -> 4635 | G58: =G56+G57 -> 4204 | H58: =H56+H57 -> 3816 | I58: =I56+I57 -> 3780 | J58: =J56+J57 -> 3763
A59: Check: Segment D&A (reconciled) vs. IS D&A | C59: =C58-'Income Statement'!C19 -> 0 | D59: =D58-'Income Statement'!D19 -> 0 | E59: =E58-'Income Statement'!E19 -> 0 | F59: =F58-'Income Statement'!F19 -> 0 | G59: =G58-'Income Statement'!G19 -> 0 | H59: =H58-'Income Statement'!H19 -> 0 | I59: =I58-'Income Statement'!I19 -> 0 | J59: =J58-'Income Statement'!J19 -> 0
A62: Americas | B62: Only FY2023-FY2025 shown: those years' 10-Ks disclose pure 'expenditures for long-lived assets' by segment. FY2018-FY2019 10-Ks disclosed a 'Capital Expenditures and Acquisitions' combined figure on a different basis and are excluded here to avoid mixing bases; FY2020-FY2022 10-Ks did not disclose segment capex at all. | H62: 2999 | I62: 2805 | J62: 3428
A63: EMEA | H63: 635 | I63: 702 | J63: 729
A64: APAC | H64: 975 | I64: 1059 | J64: 1177
A65: Engineering | H65: 24 | I65: 25 | J65: 35
A66: Other | H66: 107 | I66: 223 | J66: 304
A67: Total Segment Capex (FY2023-FY2025 only) | C67: =C62+C63+C64+C65+C66 -> 0 | D67: =D62+D63+D64+D65+D66 -> 0 | E67: =E62+E63+E64+E65+E66 -> 0 | F67: =F62+F63+F64+F65+F66 -> 0 | G67: =G62+G63+G64+G65+G66 -> 0 | H67: =H62+H63+H64+H65+H66 -> 4740 | I67: =I62+I63+I64+I65+I66 -> 4814 | J67: =J62+J63+J64+J65+J66 -> 5673

Sheet Operating Metrics
A1: Linde plc — Operating Metrics
A2: $ in millions except per-share data | USD | as of 2026-09-15
C3: FY2018 | D3: FY2019 | E3: FY2020 | F3: FY2021 | G3: FY2022 | H3: FY2023 | I3: FY2024 | J3: FY2025
A6: CONTENTS
A7: =HYPERLINK("#'Operating Metrics'!A9","1. Segment-Based Operating Metrics") -> 1. Segment-Based Operating Metrics
A9: 1. Segment-Based Operating Metrics
A10: Total Segment Operating Profit | C10: =Segments!C37 -> 2976 | D10: =Segments!D37 -> 5288 | E10: =Segments!E37 -> 5797 | F10: =Segments!F37 -> 7176 | G10: =Segments!G37 -> 7904 | H10: =Segments!H37 -> 9070 | I10: =Segments!I37 -> 9720 | J10: =Segments!J37 -> 10137
A11: Segment operating margin % | C11: =C10/'Income Statement'!C10 -> 0.19973154 | D11: =D10/'Income Statement'!D10 -> 0.18733173 | E11: =E10/'Income Statement'!E10 -> 0.21278861 | F11: =F10/'Income Statement'!F10 -> 0.23303998 | G11: =G10/'Income Statement'!G10 -> 0.23690205 | H11: =H10/'Income Statement'!H10 -> 0.27606988 | I11: =I10/'Income Statement'!I10 -> 0.29450083 | J11: =J10/'Income Statement'!J10 -> 0.29826988
A14: Americas % of sales | D14: =Segments!D17/'Income Statement'!D10 -> 0.38943602 | E14: =Segments!E17/'Income Statement'!E10 -> 0.38391513 | F14: =Segments!F17/'Income Statement'!F10 -> 0.39304387 | G14: =Segments!G17/'Income Statement'!G10 -> 0.41583743 | H14: =Segments!H17/'Income Statement'!H10 -> 0.43538078 | I14: =Segments!I17/'Income Statement'!I10 -> 0.43757007 | J14: =Segments!J17/'Income Statement'!J10 -> 0.44747837
A15: EMEA % of sales | D15: =Segments!D18/'Income Statement'!D10 -> 0.23533371 | E15: =Segments!E18/'Income Statement'!E10 -> 0.23672136 | F15: =Segments!F18/'Income Statement'!F10 -> 0.24820576 | G15: =Segments!G18/'Income Statement'!G10 -> 0.25305719 | H15: =Segments!H18/'Income Statement'!H10 -> 0.25999878 | I15: =Segments!I18/'Income Statement'!I10 -> 0.25305257 | J15: =Segments!J18/'Income Statement'!J10 -> 0.25154475
A16: APAC % of sales | D16: =Segments!D19/'Income Statement'!D10 -> 0.20685135 | E16: =Segments!E19/'Income Statement'!E10 -> 0.20875087 | F16: =Segments!F19/'Income Statement'!F10 -> 0.19916864 | G16: =Segments!G19/'Income Statement'!G10 -> 0.19422132 | H16: =Segments!H19/'Income Statement'!H10 -> 0.19964084 | I16: =Segments!I19/'Income Statement'!I10 -> 0.20093925 | J16: =Segments!J19/'Income Statement'!J10 -> 0.19599247
A17: Engineering % of sales | D17: =Segments!D20/'Income Statement'!D10 -> 0.099156866 | E17: =Segments!E20/'Income Statement'!E10 -> 0.10465074 | F17: =Segments!F20/'Income Statement'!F10 -> 0.093105576 | G17: =Segments!G20/'Income Statement'!G10 -> 0.082783839 | H17: =Segments!H20/'Income Statement'!H10 -> 0.065745419 | I17: =Segments!I20/'Income Statement'!I10 -> 0.070352977 | J17: =Segments!J20/'Income Statement'!J10 -> 0.066203731
A18: Other % of sales | D18: =Segments!D21/'Income Statement'!D10 -> 0.069222049 | E18: =Segments!E21/'Income Statement'!E10 -> 0.065961898 | F18: =Segments!F21/'Income Statement'!F10 -> 0.066476147 | G18: =Segments!G21/'Income Statement'!G10 -> 0.054100228 | H18: =Segments!H21/'Income Statement'!H10 -> 0.039234188 | I18: =Segments!I21/'Income Statement'!I10 -> 0.038085139 | J18: =Segments!J21/'Income Statement'!J10 -> 0.038780674
A21: Americas operating margin % | D21: =Segments!D32/Segments!D17 -> 0.23451287 | E21: =Segments!E32/Segments!E17 -> 0.26513051 | F21: =Segments!F32/Segments!F17 -> 0.27827811 | G21: =Segments!G32/Segments!G17 -> 0.26899236 | H21: =Segments!H32/Segments!H17 -> 0.29670022 | I21: =Segments!I32/Segments!I17 -> 0.31505332 | J21: =Segments!J32/Segments!J17 -> 0.31213835
A22: EMEA operating margin % | D22: =Segments!D33/Segments!D18 -> 0.20578052 | E22: =Segments!E33/Segments!E18 -> 0.227167 | F22: =Segments!F33/Segments!F18 -> 0.24715426 | G22: =Segments!G33/Segments!G18 -> 0.23842236 | H22: =Segments!H33/Segments!H18 -> 0.29103255 | I22: =Segments!I33/Segments!I18 -> 0.33285441 | J22: =Segments!J33/Segments!J18 -> 0.35735174
A23: APAC operating margin % | D23: =Segments!D34/Segments!D19 -> 0.20517212 | E23: =Segments!E34/Segments!E19 -> 0.22454721 | F23: =Segments!F34/Segments!F19 -> 0.24490461 | G23: =Segments!G34/Segments!G19 -> 0.25771605 | H23: =Segments!H34/Segments!H19 -> 0.27534685 | I23: =Segments!I34/Segments!I19 -> 0.28920386 | J23: =Segments!J34/Segments!J19 -> 0.29019667
A24: Engineering operating margin % | D24: =Segments!D35/Segments!D20 -> 0.13933548 | E24: =Segments!E35/Segments!E20 -> 0.15257804 | F24: =Segments!F35/Segments!F20 -> 0.16498082 | G24: =Segments!G35/Segments!G20 -> 0.20094135 | H24: =Segments!H35/Segments!H20 -> 0.22731481 | I24: =Segments!I35/Segments!I20 -> 0.17657192 | J24: =Segments!J35/Segments!J20 -> 0.18133333

Sheet Derived Metrics
A1: Linde plc — Derived Metrics
A2: $ in millions except per-share data | USD | as of 2026-09-15
C3: FY2018 | D3: FY2019 | E3: FY2020 | F3: FY2021 | G3: FY2022 | H3: FY2023 | I3: FY2024 | J3: FY2025
A6: CONTENTS
A7: =HYPERLINK("#'Derived Metrics'!A9","1. Derived / Ratio Analysis") -> 1. Derived / Ratio Analysis
A9: 1. Derived / Ratio Analysis
A11: Gross margin % | C11: ='Income Statement'!C14/'Income Statement'!C10 -> 0.39033557 | D11: ='Income Statement'!D14/'Income Statement'!D10 -> 0.41037268 | E11: ='Income Statement'!E14/'Income Statement'!E10 -> 0.43534119 | F11: ='Income Statement'!F14/'Income Statement'!F10 -> 0.4302926 | G11: ='Income Statement'!G14/'Income Statement'!G10 -> 0.41703633 | H11: ='Income Statement'!H14/'Income Statement'!H10 -> 0.46758386 | I11: ='Income Statement'!I14/'Income Statement'!I10 -> 0.48059385 | J11: ='Income Statement'!J14/'Income Statement'!J10 -> 0.48834814
A12: Operating margin % | C12: ='Income Statement'!C23/'Income Statement'!C10 -> 0.35214765 | D12: ='Income Statement'!D23/'Income Statement'!D10 -> 0.10390393 | E12: ='Income Statement'!E23/'Income Statement'!E10 -> 0.12193958 | F12: ='Income Statement'!F23/'Income Statement'!F10 -> 0.16185497 | G12: ='Income Statement'!G23/'Income Statement'!G10 -> 0.16092195 | H12: ='Income Statement'!H23/'Income Statement'!H10 -> 0.24423206 | I12: ='Income Statement'!I23/'Income Statement'!I10 -> 0.26162703 | J12: ='Income Statement'!J23/'Income Statement'!J10 -> 0.26254928
A13: EBITDA margin % | C13: =('Income Statement'!C23+'Income Statement'!C19)/'Income Statement'!C10 -> 0.47496644 | D13: =('Income Statement'!D23+'Income Statement'!D19)/'Income Statement'!D10 -> 0.26951963 | E13: =('Income Statement'!E23+'Income Statement'!E19)/'Income Statement'!E10 -> 0.29174467 | F13: =('Income Statement'!F23+'Income Statement'!F19)/'Income Statement'!F10 -> 0.31237619 | G13: =('Income Statement'!G23+'Income Statement'!G19)/'Income Statement'!G10 -> 0.28692603 | H13: =('Income Statement'!H23+'Income Statement'!H19)/'Income Statement'!H10 -> 0.3603823 | I13: =('Income Statement'!I23+'Income Statement'!I19)/'Income Statement'!I10 -> 0.37615513 | J13: =('Income Statement'!J23+'Income Statement'!J19)/'Income Statement'!J10 -> 0.37327135
A14: Net margin % | C14: ='Income Statement'!C37/'Income Statement'!C10 -> 0.29402685 | D14: ='Income Statement'!D37/'Income Statement'!D10 -> 0.080947995 | E14: ='Income Statement'!E37/'Income Statement'!E10 -> 0.091803399 | F14: ='Income Statement'!F37/'Income Statement'!F10 -> 0.12424902 | G14: ='Income Statement'!G37/'Income Statement'!G10 -> 0.12429565 | H14: ='Income Statement'!H37/'Income Statement'!H10 -> 0.18868327 | I14: ='Income Statement'!I37/'Income Statement'!I10 -> 0.19890926 | J14: ='Income Statement'!J37/'Income Statement'!J10 -> 0.20296593
A15: Effective tax rate % | C15: ='Income Statement'!C29/'Income Statement'!C28 -> 0.16181422 | D15: ='Income Statement'!D29/'Income Statement'!D28 -> 0.26272634 | E15: ='Income Statement'!E29/'Income Statement'!E28 -> 0.25029551 | F15: ='Income Statement'!F29/'Income Statement'!F28 -> 0.24749951 | G15: ='Income Statement'!G29/'Income Statement'!G28 -> 0.25870467 | H15: ='Income Statement'!H29/'Income Statement'!H28 -> 0.22709064 | I15: ='Income Statement'!I29/'Income Statement'!I28 -> 0.23363286 | J15: ='Income Statement'!J29/'Income Statement'!J28 -> 0.2235585
A18: Return on Assets (avg) | C18: ='Income Statement'!C37/(('Balance Sheet'!C23+'Balance Sheet'!B23)/2) -> 0.093825627 | D18: ='Income Statement'!D37/(('Balance Sheet'!D23+'Balance Sheet'!C23)/2) -> 0.025389171 | E18: ='Income Statement'!E37/(('Balance Sheet'!E23+'Balance Sheet'!D23)/2) -> 0.02860885 | F18: ='Income Statement'!F37/(('Balance Sheet'!F23+'Balance Sheet'!E23)/2) -> 0.04505576 | G18: ='Income Statement'!G37/(('Balance Sheet'!G23+'Balance Sheet'!F23)/2) -> 0.051431512 | H18: ='Income Statement'!H37/(('Balance Sheet'!H23+'Balance Sheet'!G23)/2) -> 0.077261029 | I18: ='Income Statement'!I37/(('Balance Sheet'!I23+'Balance Sheet'!H23)/2) -> 0.081574075 | J18: ='Income Statement'!J37/(('Balance Sheet'!J23+'Balance Sheet'!I23)/2) -> 0.082628591
A19: Return on Equity (avg) | C19: ='Income Statement'!C37/(('Balance Sheet'!C46+'Balance Sheet'!B46)/2) -> 0.16981937 | D19: ='Income Statement'!D37/(('Balance Sheet'!D46+'Balance Sheet'!C46)/2) -> 0.045395848 | E19: ='Income Statement'!E37/(('Balance Sheet'!E46+'Balance Sheet'!D46)/2) -> 0.051892812 | F19: ='Income Statement'!F37/(('Balance Sheet'!F46+'Balance Sheet'!E46)/2) -> 0.083763902 | G19: ='Income Statement'!G37/(('Balance Sheet'!G46+'Balance Sheet'!F46)/2) -> 0.098664097 | H19: ='Income Statement'!H37/(('Balance Sheet'!H46+'Balance Sheet'!G46)/2) -> 0.15546471 | I19: ='Income Statement'!I37/(('Balance Sheet'!I46+'Balance Sheet'!H46)/2) -> 0.16874004 | J19: ='Income Statement'!J37/(('Balance Sheet'!J46+'Balance Sheet'!I46)/2) -> 0.18072494
A20: Return on Invested Capital (avg) | C20: ='Income Statement'!C23*(1-'Income Statement'!C30)/(('Balance Sheet'!C46+'Balance Sheet'!C34+'Balance Sheet'!B46+'Balance Sheet'!B34)/2) -> 0.13768583 | D20: ='Income Statement'!D23*(1-'Income Statement'!D30)/(('Balance Sheet'!D46+'Balance Sheet'!D34+'Balance Sheet'!C46+'Balance Sheet'!C34)/2) -> 0.034976242 | E20: ='Income Statement'!E23*(1-'Income Statement'!E30)/(('Balance Sheet'!E46+'Balance Sheet'!E34+'Balance Sheet'!D46+'Balance Sheet'!D34)/2) -> 0.041774604 | F20: ='Income Statement'!F23*(1-'Income Statement'!F30)/(('Balance Sheet'!F46+'Balance Sheet'!F34+'Balance Sheet'!E46+'Balance Sheet'!E34)/2) -> 0.065316877 | G20: ='Income Statement'!G23*(1-'Income Statement'!G30)/(('Balance Sheet'!G46+'Balance Sheet'!G34+'Balance Sheet'!F46+'Balance Sheet'!F34)/2) -> 0.073980717 | H20: ='Income Statement'!H23*(1-'Income Statement'!H30)/(('Balance Sheet'!H46+'Balance Sheet'!H34+'Balance Sheet'!G46+'Balance Sheet'!G34)/2) -> 0.11774536 | I20: ='Income Statement'!I23*(1-'Income Statement'!I30)/(('Balance Sheet'!I46+'Balance Sheet'!I34+'Balance Sheet'!H46+'Balance Sheet'!H34)/2) -> 0.12421316 | J20: ='Income Statement'!J23*(1-'Income Statement'!J30)/(('Balance Sheet'!J46+'Balance Sheet'!J34+'Balance Sheet'!I46+'Balance Sheet'!I34)/2) -> 0.12331795
A21: Asset turnover (x, avg) | C21: ='Income Statement'!C10/(('Balance Sheet'!C23+'Balance Sheet'!B23)/2) -> 0.31910565 | D21: ='Income Statement'!D10/(('Balance Sheet'!D23+'Balance Sheet'!C23)/2) -> 0.31364793 | E21: ='Income Statement'!E10/(('Balance Sheet'!E23+'Balance Sheet'!D23)/2) -> 0.31163171 | F21: ='Income Statement'!F10/(('Balance Sheet'!F23+'Balance Sheet'!E23)/2) -> 0.36262468 | G21: ='Income Statement'!G10/(('Balance Sheet'!G23+'Balance Sheet'!F23)/2) -> 0.41378369 | H21: ='Income Statement'!H10/(('Balance Sheet'!H23+'Balance Sheet'!G23)/2) -> 0.40947473 | I21: ='Income Statement'!I10/(('Balance Sheet'!I23+'Balance Sheet'!H23)/2) -> 0.41010698 | J21: ='Income Statement'!J10/(('Balance Sheet'!J23+'Balance Sheet'!I23)/2) -> 0.40710572
A24: Net debt ($mm) | C24: ='Balance Sheet'!C34+'Balance Sheet'!C26+'Balance Sheet'!C27-'Balance Sheet'!C10 -> 10830 | D24: ='Balance Sheet'!D34+'Balance Sheet'!D26+'Balance Sheet'!D27-'Balance Sheet'!D10 -> 11256 | E24: ='Balance Sheet'!E34+'Balance Sheet'!E26+'Balance Sheet'!E27-'Balance Sheet'!E10 -> 12400 | F24: ='Balance Sheet'!F34+'Balance Sheet'!F26+'Balance Sheet'!F27-'Balance Sheet'!F10 -> 11384 | G24: ='Balance Sheet'!G34+'Balance Sheet'!G26+'Balance Sheet'!G27-'Balance Sheet'!G10 -> 12478 | H24: ='Balance Sheet'!H34+'Balance Sheet'!H26+'Balance Sheet'!H27-'Balance Sheet'!H10 -> 14709 | I24: ='Balance Sheet'!I34+'Balance Sheet'!I26+'Balance Sheet'!I27-'Balance Sheet'!I10 -> 16773 | J24: ='Balance Sheet'!J34+'Balance Sheet'!J26+'Balance Sheet'!J27-'Balance Sheet'!J10 -> 21933
A25: Net debt / EBITDA (x) | C25: =C24/('Income Statement'!C23+'Income Statement'!C19) -> 1.5303095 | D25: =D24/('Income Statement'!D23+'Income Statement'!D19) -> 1.4794953 | E25: =E24/('Income Statement'!E23+'Income Statement'!E19) -> 1.5601409 | F25: =F24/('Income Statement'!F23+'Income Statement'!F19) -> 1.183491 | G25: =G24/('Income Statement'!G23+'Income Statement'!G19) -> 1.3034576 | H25: =H24/('Income Statement'!H23+'Income Statement'!H19) -> 1.2423142 | I25: =I24/('Income Statement'!I23+'Income Statement'!I19) -> 1.351027 | J25: =J24/('Income Statement'!J23+'Income Statement'!J19) -> 1.7289138
A26: Debt / Equity (x) | C26: =('Balance Sheet'!C34+'Balance Sheet'!C26+'Balance Sheet'!C27)/'Balance Sheet'!C46 -> 0.29645709 | D26: =('Balance Sheet'!D34+'Balance Sheet'!D26+'Balance Sheet'!D27)/'Balance Sheet'!D46 -> 0.28438684 | E26: =('Balance Sheet'!E34+'Balance Sheet'!E26+'Balance Sheet'!E27)/'Balance Sheet'!E46 -> 0.3413995 | F26: =('Balance Sheet'!F34+'Balance Sheet'!F26+'Balance Sheet'!F27)/'Balance Sheet'!F46 -> 0.32262973 | G26: =('Balance Sheet'!G34+'Balance Sheet'!G26+'Balance Sheet'!G27)/'Balance Sheet'!G46 -> 0.44753672 | H26: =('Balance Sheet'!H34+'Balance Sheet'!H26+'Balance Sheet'!H27)/'Balance Sheet'!H46 -> 0.48773917 | I26: =('Balance Sheet'!I34+'Balance Sheet'!I26+'Balance Sheet'!I27)/'Balance Sheet'!I46 -> 0.567652 | J26: =('Balance Sheet'!J34+'Balance Sheet'!J26+'Balance Sheet'!J27)/'Balance Sheet'!J46 -> 0.70568702
A29: Equity ratio (Equity / Assets) | C29: ='Balance Sheet'!C48/'Balance Sheet'!C23 -> 0.61122652 | D29: ='Balance Sheet'!D48/'Balance Sheet'!D23 -> 0.59485983 | E29: ='Balance Sheet'!E48/'Balance Sheet'!E23 -> 0.56182208 | F29: ='Balance Sheet'!F48/'Balance Sheet'!F23 -> 0.55668158 | G29: ='Balance Sheet'!G48/'Balance Sheet'!G23 -> 0.51939542 | H29: ='Balance Sheet'!H48/'Balance Sheet'!H23 -> 0.50837139 | I29: ='Balance Sheet'!I48/'Balance Sheet'!I23 -> 0.49253247 | J29: ='Balance Sheet'!J48/'Balance Sheet'!J23 -> 0.45760623
A30: Debt / Assets | C30: =('Balance Sheet'!C34+'Balance Sheet'!C26+'Balance Sheet'!C27)/'Balance Sheet'!C23 -> 0.16379329 | D30: =('Balance Sheet'!D34+'Balance Sheet'!D26+'Balance Sheet'!D27)/'Balance Sheet'!D23 -> 0.16113241 | E30: =('Balance Sheet'!E34+'Balance Sheet'!E26+'Balance Sheet'!E27)/'Balance Sheet'!E23 -> 0.18309173 | F30: =('Balance Sheet'!F34+'Balance Sheet'!F26+'Balance Sheet'!F27)/'Balance Sheet'!F23 -> 0.17409472 | G30: =('Balance Sheet'!G34+'Balance Sheet'!G26+'Balance Sheet'!G27)/'Balance Sheet'!G23 -> 0.22488639 | H30: =('Balance Sheet'!H34+'Balance Sheet'!H26+'Balance Sheet'!H27)/'Balance Sheet'!H23 -> 0.23973221 | I30: =('Balance Sheet'!I34+'Balance Sheet'!I26+'Balance Sheet'!I27)/'Balance Sheet'!I23 -> 0.26979176 | J30: =('Balance Sheet'!J34+'Balance Sheet'!J26+'Balance Sheet'!J27)/'Balance Sheet'!J23 -> 0.31087229
A33: Current ratio (x) | C33: ='Balance Sheet'!C16/'Balance Sheet'!C32 -> 1.3331275 | D33: ='Balance Sheet'!D16/'Balance Sheet'!D32 -> 0.85131579 | E33: ='Balance Sheet'!E16/'Balance Sheet'!E32 -> 0.79505095 | F33: ='Balance Sheet'!F16/'Balance Sheet'!F32 -> 0.74463095 | G33: ='Balance Sheet'!G16/'Balance Sheet'!G32 -> 0.79173494 | H33: ='Balance Sheet'!H16/'Balance Sheet'!H32 -> 0.80295222 | I33: ='Balance Sheet'!I16/'Balance Sheet'!I32 -> 0.89005776 | J33: ='Balance Sheet'!J16/'Balance Sheet'!J32 -> 0.8767601
A34: Quick ratio (x) | C34: =('Balance Sheet'!C10+'Balance Sheet'!C11)/'Balance Sheet'!C32 -> 0.67636616 | D34: =('Balance Sheet'!D10+'Balance Sheet'!D11)/'Balance Sheet'!D32 -> 0.57746711 | E34: =('Balance Sheet'!E10+'Balance Sheet'!E11)/'Balance Sheet'!E32 -> 0.57649199 | F34: =('Balance Sheet'!F10+'Balance Sheet'!F11)/'Balance Sheet'!F32 -> 0.53668548 | G34: =('Balance Sheet'!G10+'Balance Sheet'!G11)/'Balance Sheet'!G32 -> 0.60652952 | H34: =('Balance Sheet'!H10+'Balance Sheet'!H11)/'Balance Sheet'!H32 -> 0.59693326 | I34: =('Balance Sheet'!I10+'Balance Sheet'!I11)/'Balance Sheet'!I32 -> 0.65126513 | J34: =('Balance Sheet'!J10+'Balance Sheet'!J11)/'Balance Sheet'!J32 -> 0.65942887
A35: Cash ratio (x) | C35: ='Balance Sheet'!C10/'Balance Sheet'!C32 -> 0.34470516 | D35: ='Balance Sheet'!D10/'Balance Sheet'!D32 -> 0.22203947 | E35: ='Balance Sheet'!E10/'Balance Sheet'!E32 -> 0.27321689 | F35: ='Balance Sheet'!F10/'Balance Sheet'!F32 -> 0.2069193 | G35: ='Balance Sheet'!G10/'Balance Sheet'!G32 -> 0.32987439 | H35: ='Balance Sheet'!H10/'Balance Sheet'!H32 -> 0.29674874 | I35: ='Balance Sheet'!I10/'Balance Sheet'!I32 -> 0.33347085 | J35: ='Balance Sheet'!J10/'Balance Sheet'!J32 -> 0.33267535
A38: Interest coverage (EBIT / Interest, x) | C38: ='Income Statement'!C23/'Income Statement'!C26 -> 25.975248 | D38: ='Income Statement'!D23/'Income Statement'!D26 -> 77.184211 | E38: ='Income Statement'!E23/'Income Statement'!E26 -> 28.886957 | F38: ='Income Statement'!F23/'Income Statement'!F26 -> 64.727273 | G38: ='Income Statement'!G23/'Income Statement'!G26 -> 85.222222 | H38: ='Income Statement'!H23/'Income Statement'!H26 -> 40.12 | I38: ='Income Statement'!I23/'Income Statement'!I26 -> 33.730469 | J38: ='Income Statement'!J23/'Income Statement'!J26 -> 34.992157
A39: CFO / Interest expense (x) | C39: ='Cash Flow Statement'!C30/'Income Statement'!C26 -> 18.089109 | D39: ='Cash Flow Statement'!D30/'Income Statement'!D26 -> 161.02632 | E39: ='Cash Flow Statement'!E30/'Income Statement'!E26 -> 64.6 | F39: ='Cash Flow Statement'!F30/'Income Statement'!F26 -> 126.2987 | G39: ='Cash Flow Statement'!G30/'Income Statement'!G26 -> 140.69841 | H39: ='Cash Flow Statement'!H30/'Income Statement'!H26 -> 46.525 | I39: ='Cash Flow Statement'!I30/'Income Statement'!I26 -> 36.808594 | J39: ='Cash Flow Statement'!J30/'Income Statement'!J26 -> 40.588235
A42: CFO margin % | C42: ='Cash Flow Statement'!C30/'Income Statement'!C10 -> 0.2452349 | D42: ='Cash Flow Statement'!D30/'Income Statement'!D10 -> 0.21677058 | E42: ='Cash Flow Statement'!E30/'Income Statement'!E10 -> 0.2726939 | F42: ='Cash Flow Statement'!F30/'Income Statement'!F10 -> 0.31581853 | G42: ='Cash Flow Statement'!G30/'Income Statement'!G10 -> 0.26567558 | H42: ='Cash Flow Statement'!H30/'Income Statement'!H10 -> 0.28322274 | I42: ='Cash Flow Statement'!I30/'Income Statement'!I10 -> 0.2855022 | J42: ='Cash Flow Statement'!J30/'Income Statement'!J10 -> 0.30453716
A43: CFO / EBITDA (x) | C43: ='Cash Flow Statement'!C30/('Income Statement'!C23+'Income Statement'!C19) -> 0.51632047 | D43: ='Cash Flow Statement'!D30/('Income Statement'!D23+'Income Statement'!D19) -> 0.80428496 | E43: ='Cash Flow Statement'!E30/('Income Statement'!E23+'Income Statement'!E19) -> 0.93470055 | F43: ='Cash Flow Statement'!F30/('Income Statement'!F23+'Income Statement'!F19) -> 1.0110199 | G43: ='Cash Flow Statement'!G30/('Income Statement'!G23+'Income Statement'!G19) -> 0.92593753 | H43: ='Cash Flow Statement'!H30/('Income Statement'!H23+'Income Statement'!H19) -> 0.78589527 | I43: ='Cash Flow Statement'!I30/('Income Statement'!I23+'Income Statement'!I19) -> 0.75900121 | J43: ='Cash Flow Statement'!J30/('Income Statement'!J23+'Income Statement'!J19) -> 0.81586
A44: Capex intensity (Capex / Sales) | C44: =0-'Cash Flow Statement'!C33/'Income Statement'!C10 -> 0.12637584 | D44: =0-'Cash Flow Statement'!D33/'Income Statement'!D10 -> 0.13043786 | E44: =0-'Cash Flow Statement'!E33/'Income Statement'!E10 -> 0.1248027 | F44: =0-'Cash Flow Statement'!F33/'Income Statement'!F10 -> 0.10021758 | G44: =0-'Cash Flow Statement'!G33/'Income Statement'!G10 -> 0.095102506 | H44: =0-'Cash Flow Statement'!H33/'Income Statement'!H10 -> 0.11526755 | I44: =0-'Cash Flow Statement'!I33/'Income Statement'!I10 -> 0.13625208 | J44: =0-'Cash Flow Statement'!J33/'Income Statement'!J10 -> 0.15479903
A45: FCF margin % | C45: ='Cash Flow Statement'!C62/'Income Statement'!C10 -> 0.11885906 | D45: ='Cash Flow Statement'!D62/'Income Statement'!D10 -> 0.086332719 | E45: ='Cash Flow Statement'!E62/'Income Statement'!E10 -> 0.1478912 | F45: ='Cash Flow Statement'!F62/'Income Statement'!F10 -> 0.21560095 | G45: ='Cash Flow Statement'!G62/'Income Statement'!G10 -> 0.17057307 | H45: ='Cash Flow Statement'!H62/'Income Statement'!H10 -> 0.1679552 | I45: ='Cash Flow Statement'!I62/'Income Statement'!I10 -> 0.14925011 | J45: ='Cash Flow Statement'!J62/'Income Statement'!J10 -> 0.14973813
A46: FCF / Net Income (x) | C46: ='Cash Flow Statement'!C62/'Income Statement'!C37 -> 0.40424561 | D46: ='Cash Flow Statement'!D62/'Income Statement'!D37 -> 1.0665208 | E46: ='Cash Flow Statement'!E62/'Income Statement'!E37 -> 1.6109556 | F46: ='Cash Flow Statement'!F62/'Income Statement'!F37 -> 1.7352326 | G46: ='Cash Flow Statement'!G62/'Income Statement'!G37 -> 1.3723173 | H46: ='Cash Flow Statement'!H62/'Income Statement'!H37 -> 0.89014357 | I46: ='Cash Flow Statement'!I62/'Income Statement'!I37 -> 0.75034273 | J46: ='Cash Flow Statement'!J62/'Income Statement'!J37 -> 0.73775007
A47: D&A / Capex (x) | C47: ='Income Statement'!C19/(0-'Cash Flow Statement'!C33) -> 0.97185343 | D47: ='Income Statement'!D19/(0-'Cash Flow Statement'!D33) -> 1.2696904 | E47: ='Income Statement'!E19/(0-'Cash Flow Statement'!E33) -> 1.3605882 | F47: ='Income Statement'!F19/(0-'Cash Flow Statement'!F33) -> 1.5019443 | G47: ='Income Statement'!G19/(0-'Cash Flow Statement'!G33) -> 1.3249291 | H47: ='Income Statement'!H19/(0-'Cash Flow Statement'!H33) -> 1.0076578 | I47: ='Income Statement'!I19/(0-'Cash Flow Statement'!I33) -> 0.84056037 | J47: ='Income Statement'!J19/(0-'Cash Flow Statement'!J33) -> 0.71526326
A50: CFO / Net Income (x) | C50: ='Cash Flow Statement'!C30/'Income Statement'!C37 -> 0.83405615 | D50: ='Cash Flow Statement'!D30/'Income Statement'!D37 -> 2.6778993 | E50: ='Cash Flow Statement'!E30/'Income Statement'!E37 -> 2.9704118 | F50: ='Cash Flow Statement'!F30/'Income Statement'!F37 -> 2.5418191 | G50: ='Cash Flow Statement'!G30/'Income Statement'!G37 -> 2.1374488 | H50: ='Cash Flow Statement'!H30/'Income Statement'!H37 -> 1.5010486 | I50: ='Cash Flow Statement'!I30/'Income Statement'!I37 -> 1.4353389 | J50: ='Cash Flow Statement'!J30/'Income Statement'!J37 -> 1.5004349
A51: Accrual ratio ((NI - CFO) / Assets) | C51: =('Income Statement'!C37-'Cash Flow Statement'!C30)/'Balance Sheet'!C23 -> 0.0077848928 | D51: =('Income Statement'!D37-'Cash Flow Statement'!D30)/'Balance Sheet'!D23 -> -0.044266383 | E51: =('Income Statement'!E37-'Cash Flow Statement'!E30)/'Balance Sheet'!E23 -> -0.055854651 | F51: =('Income Statement'!F37-'Cash Flow Statement'!F30)/'Balance Sheet'!F23 -> -0.072287237 | G51: =('Income Statement'!G37-'Cash Flow Statement'!G30)/'Balance Sheet'!G23 -> -0.059215647 | H51: =('Income Statement'!H37-'Cash Flow Statement'!H30)/'Balance Sheet'!H23 -> -0.038435362 | I51: =('Income Statement'!I37-'Cash Flow Statement'!I30)/'Balance Sheet'!I23 -> -0.035659476 | J51: =('Income Statement'!J37-'Cash Flow Statement'!J30)/'Balance Sheet'!J23 -> -0.039761798
A54: Revenue growth % | C54: ='Income Statement'!C10/'Income Statement'!B10-1 -> #DIV/0! | D54: ='Income Statement'!D10/'Income Statement'!C10-1 -> 0.89449664 | E54: ='Income Statement'!E10/'Income Statement'!D10-1 -> -0.034894431 | F54: ='Income Statement'!F10/'Income Statement'!E10-1 -> 0.1303087 | G54: ='Income Statement'!G10/'Income Statement'!F10-1 -> 0.083493002 | H54: ='Income Statement'!H10/'Income Statement'!G10-1 -> -0.015285937 | I54: ='Income Statement'!I10/'Income Statement'!H10-1 -> 0.0045960918 | J54: ='Income Statement'!J10/'Income Statement'!I10-1 -> 0.029722769
A55: Net income growth % | C55: ='Income Statement'!C37/'Income Statement'!B37-1 -> #DIV/0! | D55: ='Income Statement'!D37/'Income Statement'!C37-1 -> -0.47842958 | E55: ='Income Statement'!E37/'Income Statement'!D37-1 -> 0.09452954 | F55: ='Income Statement'!F37/'Income Statement'!E37-1 -> 0.52978808 | G55: ='Income Statement'!G37/'Income Statement'!F37-1 -> 0.083899634 | H55: ='Income Statement'!H37/'Income Statement'!G37-1 -> 0.49481553 | I55: ='Income Statement'!I37/'Income Statement'!H37-1 -> 0.059041781 | J55: ='Income Statement'!J37/'Income Statement'!I37-1 -> 0.050723534
A56: CFO growth % | C56: ='Cash Flow Statement'!C30/'Cash Flow Statement'!B30-1 -> #DIV/0! | D56: ='Cash Flow Statement'!D30/'Cash Flow Statement'!C30-1 -> 0.67460317 | E56: ='Cash Flow Statement'!E30/'Cash Flow Statement'!D30-1 -> 0.21408727 | F56: ='Cash Flow Statement'!F30/'Cash Flow Statement'!E30-1 -> 0.30905909 | G56: ='Cash Flow Statement'!G30/'Cash Flow Statement'!F30-1 -> -0.088534704 | H56: ='Cash Flow Statement'!H30/'Cash Flow Statement'!G30-1 -> 0.049751805 | I56: ='Cash Flow Statement'!I30/'Cash Flow Statement'!H30-1 -> 0.012681354 | J56: ='Cash Flow Statement'!J30/'Cash Flow Statement'!I30-1 -> 0.098376313
A59: Days Sales Outstanding | C59: ='Balance Sheet'!C52 -> 105.26208 | D59: ='Balance Sheet'!D52 -> 55.885291 | E59: ='Balance Sheet'!E52 -> 55.829204 | F59: ='Balance Sheet'!F52 -> 53.328191 | G59: ='Balance Sheet'!G52 -> 49.875165 | H59: ='Balance Sheet'!H52 -> 52.41584 | I59: ='Balance Sheet'!I52 -> 51.114377 | J59: ='Balance Sheet'!J52 -> 53.333431
A60: Days Inventory Outstanding | C60: ='Balance Sheet'!C53 -> 66.338067 | D60: ='Balance Sheet'!D53 -> 37.214912 | E60: ='Balance Sheet'!E53 -> 41.024833 | F60: ='Balance Sheet'!F53 -> 36.056832 | G60: ='Balance Sheet'!G53 -> 37.11928 | H60: ='Balance Sheet'!H53 -> 44.133032 | I60: ='Balance Sheet'!I53 -> 41.433238 | J60: ='Balance Sheet'!J53 -> 43.135028
A61: Days Payable Outstanding | C61: ='Balance Sheet'!C54 -> 129.34115 | D61: ='Balance Sheet'!D54 -> 71.622807 | E61: ='Balance Sheet'!E54 -> 73.436586 | F61: ='Balance Sheet'!F54 -> 72.883486 | G61: ='Balance Sheet'!G54 -> 56.20437 | H61: ='Balance Sheet'!H54 -> 63.017379 | I61: ='Balance Sheet'!I54 -> 53.377764 | J61: ='Balance Sheet'!J54 -> 58.98269
A62: Cash Conversion Cycle | C62: ='Balance Sheet'!C55 -> 42.258998 | D62: ='Balance Sheet'!D55 -> 21.477396 | E62: ='Balance Sheet'!E55 -> 23.417451 | F62: ='Balance Sheet'!F55 -> 16.501537 | G62: ='Balance Sheet'!G55 -> 30.790075 | H62: ='Balance Sheet'!H55 -> 33.531493 | I62: ='Balance Sheet'!I55 -> 39.169851 | J62: ='Balance Sheet'!J55 -> 37.485769

Sheet Consolidated
A1: Linde plc — Quarterly Consolidated Results
A3: Metric ($MM) | B3: 3Q 2025 | C3: 4Q 2025 | D3: 1Q 2026 | E3: 2Q 2026 | F3: FY 2025
A4: Sales | B4: 8615 | C4: 8764 | D4: 8781 | E4: 9289 | F4: 33986
A5: YoY Growth | B5: +3% | C5: +6% | D5: +8% | E5: +9% | F5: +3%
A6: Seq. Growth | B6: +1% | C6: +2% | D6: 0% | E6: +6% | F6: —
A7: Operating Profit | B7: 2558 | C7: 2585 | D7: 2630 | E7: 2744 | F7: 10137
A8: OP Margin | B8: 29.7% | C8: 29.5% | D8: 30.0% | E8: 29.5% | F8: 29.8%
A9: Net Income | B9: 1987 | C9: 1968 | D9: 2019 | E9: 2089 | F9: 7772
A10: Diluted EPS | B10: 4.21 | C10: 4.2 | D10: 4.33 | E10: 4.5 | F10: 16.46
A11: EPS YoY | B11: +7% | C11: +6% | D11: +10% | E11: +10% | F11: +6%
A12: Op. Cash Flow | B12: 2948 | C12: 3030 | D12: 2240 | E12: 2271 | F12: 10350
A13: OCF YoY | B13: +8% | C13: +8% | D13: +4% | E13: +3% | F13: +10%
A14: Capex | B14: 1276 | C14: 1458 | D14: 1342 | E14: 1438 | F14: 5261
A15: Base Capex | B15: 640 | C15: 698 | D15: 689 | E15: 658 | F15: 2618
A16: Project Capex | B16: 636 | C16: 760 | D16: 653 | E16: 780 | F16: 2643
A17: After-Tax ROC | B17: 24.6% | C17: 24.2% | D17: 23.8% | E17: 23.5% | F17: 24.2%
A19: Sales Growth Bridge (YoY)
A20: Component | B20: 3Q 2025 | C20: 4Q 2025 | D20: 1Q 2026 | E20: 2Q 2026
A21: Volume | B21: 0% | C21: +1% | D21: +1% | E21: +2%
A22: Price / Mix | B22: +2% | C22: +2% | D22: +2% | E22: +2%
A23: Cost Pass-thru | B23: 0% | C23: 0% | D23: 0% | E23: +1%
A24: Currency | B24: +1% | C24: +3% | D24: +5% | E24: +2%
A25: Acq / Div | B25: +1% | C25: +1% | D25: +1% | E25: +1%
A26: Engineering | B26: -1% | C26: -1% | D26: -1% | E26: +1%
A27: Total | B27: +3% | C27: +6% | D27: +8% | E27: +9%

Sheet End Markets
A1: Global End Market Trends — % of Sales & YoY Growth
A2: Excludes currency, cost pass-through, acquisitions/divestitures, non-recurring equipment sales
A4: End Market | B4: 3Q'25 Share | C4: 4Q'25 Share | D4: 1Q'26 Share | E4: 2Q'26 Share | F4: 3Q'25 YoY | G4: 4Q'25 YoY | H4: 1Q'26 YoY | I4: 2Q'26 YoY
A5: Consumer Related (~1/3, More Resilient)
A6: Healthcare | B6: 16% | C6: 16% | D6: 16% | E6: 16% | F6: +1% | G6: +1% | H6: +1% | I6: +2%
A7: Food & Beverage | B7: 10% | C7: 9% | D7: 9% | E7: 9% | F7: +3% | G7: +5% | H7: +5% | I7: +3%
A8: Electronics | B8: 9% | C8: 10% | D8: 10% | E8: 10% | F8: +6% | G8: +7% | H8: +10% | I8: +18%
A9: Industrial Related (~2/3, More Cyclical)
A10: Manufacturing | B10: 21% | C10: 21% | D10: 21% | E10: 21% | F10: +3% | G10: +2% | H10: +5% | I10: +5%
A11: Chemicals & Energy | B11: 20% | C11: 21% | D11: 22% | E11: 21% | F11: +1% | G11: +2% | H11: +3% | I11: +2%
A12: Metals & Mining | B12: 13% | C12: 13% | D12: 13% | E12: 13% | F12: +1% | G12: +1% | H12: +3% | I12: +4%
A14: Sequential Sales Growth by End Market
A15: End Market | B15: 3Q'25 Seq. | C15: 4Q'25 Seq. | D15: 1Q'26 Seq. | E15: 2Q'26 Seq.
A16: Healthcare | B16: +1% | C16: +1% | D16: 0% | E16: +1%
A17: Food & Beverage | B17: +3% | C17: -3% | D17: -1% | E17: +5%
A18: Electronics | B18: +4% | C18: +5% | D18: +1% | E18: +7%
A19: Manufacturing | B19: +2% | C19: 0% | D19: 0% | E19: +4%
A20: Chemicals & Energy | B20: -5% | C20: +2% | D20: +1% | E20: +4%
A21: Metals & Mining | B21: 0% | C21: -2% | D21: +1% | E21: +3%

Sheet Regional Segments
A1: Regional Segment Performance
A3: Americas
A4: Metric | B4: 3Q 2025 | C4: 4Q 2025 | D4: 1Q 2026 | E4: 2Q 2026
A5: Sales ($MM) | B5: 3846 | C5: 3884 | D5: 4025 | E5: 4083
A6: Operating Profit ($MM) | B6: 1199 | C6: 1202 | D6: 1272 | E6: 1272
A7: OP Margin | B7: 31.2% | C7: 30.9% | D7: 31.6% | E7: 31.2%
A8: Sales YoY | B8: +6% | C8: +8% | D8: +10% | E8: +7%
A9: Volume | B9: +1% | C9: +1% | D9: +2% | E9: +2%
A10: Price / Mix | B10: +3% | C10: +3% | D10: +4% | E10: +2%
A11: Cost Pass-thru | B11: +2% | C11: +2% | D11: +2% | E11: 0%
A12: Currency | B12: 0% | C12: +1% | D12: +2% | E12: +2%
A13: Acq / Div | B13: 0% | C13: +1% | D13: 0% | E13: +1%
A14: End Market Mix (Q4'25): Healthcare 24%, Manufacturing 19%, C&E 23%, M&M 11%, F&B 11%, Electronics 5%, Others 7%
A16: APAC
A17: Metric | B17: 3Q 2025 | C17: 4Q 2025 | D17: 1Q 2026 | E17: 2Q 2026
A18: Sales ($MM) | B18: 1741 | C18: 1726 | D18: 1701 | E18: 1870
A19: Operating Profit ($MM) | B19: 490 | C19: 502 | D19: 477 | E19: 531
A20: OP Margin | B20: 28.1% | C20: 29.1% | D20: 28.0% | E20: 28.4%
A21: Sales YoY | B21: +1% | C21: +3% | D21: +11% | E21: +13%
A22: Volume | B22: 0% | C22: +2% | D22: +6% | E22: +6%
A23: Price / Mix | B23: -1% | C23: 0% | D23: 0% | E23: +2%
A24: Cost Pass-thru | B24: 0% | C24: -1% | D24: -1% | E24: +2%
A25: Currency | B25: -1% | C25: 0% | D25: +4% | E25: +3%
A26: Acq / Div | B26: +3% | C26: +2% | D26: +2% | E26: 0%
A27: End Market Mix (Q4'25): C&E 28%, Electronics 23%, Manufacturing 16%, Healthcare 14%, M&M 10%, F&B 5%, Others 4%
A29: EMEA
A30: Metric | B30: 3Q 2025 | C30: 4Q 2025 | D30: 1Q 2026 | E30: 2Q 2026
A31: Sales ($MM) | B31: 2178 | C31: 2178 | D31: 2171 | E31: 2303
A32: Operating Profit ($MM) | B32: 781 | C32: 772 | D32: 784 | E32: 823
A33: OP Margin | B33: 35.9% | C33: 35.4% | D33: 36.1% | E33: 35.7%
A34: Sales YoY | B34: +3% | C34: +6% | D34: +7% | E34: +7%
A35: Volume | B35: -3% | C35: -3% | D35: -3% | E35: -1%
A36: Price / Mix | B36: +2% | C36: +1% | D36: +1% | E36: +2%
A37: Cost Pass-thru | B37: -1% | C37: -1% | D37: -2% | E37: +2%
A38: Currency | B38: +5% | C38: +8% | D38: +10% | E38: +3%
A39: Acq / Div | B39: 0% | C39: +1% | D39: +1% | E39: +1%
A40: End Market Mix (Q4'25): C&E 25%, Manufacturing 23%, Healthcare 18%, M&M 17%, F&B 12%, Electronics 3%, Others 2%

Sheet Engineering & Other
A1: Engineering Segment & Global Other
A3: Engineering
A4: Metric | B4: 3Q 2025 | C4: 4Q 2025 | D4: 1Q 2026 | E4: 2Q 2026
A5: Sales ($MM) | B5: 519 | C5: 615 | D5: 517 | E5: 625
A6: Operating Profit ($MM) | B6: 101 | C6: 103 | D6: 101 | E6: 100
A7: OP Margin | B7: 19.5% | C7: 16.7% | D7: 19.5% | E7: 16.0%
A8: Order Intake ($MM) | B8: 269 | C8: 434 | D8: 640 | E8: 871
A9: SOP Backlog ($MM) | B9: 2907 | C9: 2719 | D9: 2802 | E9: 3016
A11: Global Other
A12: Metric | B12: 3Q 2025 | C12: 4Q 2025 | D12: 1Q 2026 | E12: 2Q 2026
A13: Sales ($MM) | B13: 331 | C13: 361 | D13: 367 | E13: 408
A14: Operating Profit ($MM) | B14: -13 | C14: 6 | D14: -4 | E14: 18
A15: OP Margin | B15: -3.9% | C15: 1.7% | D15: -1.1% | E15: 4.4%
A16: Key Driver | B16: Helium drag | C16: Helium drag | D16: Coatings growth | E16: Adv. materials↑

Sheet Backlog & Capital
A1: Project Backlog & Capital Management
A3: Project Backlog
A4: Metric | B4: 3Q 2025 | C4: 4Q 2025 | D4: 1Q 2026 | E4: 2Q 2026
A5: Total Backlog ($B) | B5: 10 | C5: 10 | D5: 9.9 | E5: 11.1
A6: SOG Backlog ($B) | B6: 7.1 | C6: 7.3 | D6: 7.1 | E6: 8.1
A7: SOP Backlog ($B) | B7: 2.9 | C7: 2.7 | D7: 2.8 | E7: 3
A8: SOG Clean Energy % | B8: ~65% | C8: ~65% | D8: — | E8: —
A10: Capital Allocation (Cumulative YTD)
A11: Metric | B11: YTD Q3'25 | C11: FY 2025 | D11: YTD Q1'26 | E11: YTD H1'26
A12: Business Investments ($B) | B12: 4.2 | C12: 5.7 | D12: 1.5 | E12: 3.2
A13: Secured Growth ($B) | B13: 2.3 | C13: 3.1 | D13: 0.8 | E13: 1.9
A14: Base Capex ($B) | B14: 1.9 | C14: 2.6 | D14: 0.7 | E14: 1.3
A15: Return to Shareholders ($B) | B15: 5.3 | C15: 7.4 | D15: 1.5 | E15: 3.1
A16: Net Share Buybacks ($B) | B16: 3.2 | C16: 4.6 | D16: 0.8 | E16: 1.7
A17: Dividends ($B) | B17: 2.1 | C17: 2.8 | D17: 0.7 | E17: 1.4
A19: Quarterly Operating Cash Flow ($B)
A20: Metric | B20: 3Q 2025 | C20: 4Q 2025 | D20: 1Q 2026 | E20: 2Q 2026
A21: Op. Cash Flow | B21: 2.9 | C21: 3 | D21: 2.2 | E21: 2.3
A22: Base Capex | B22: -0.6 | C22: -0.7 | D22: -0.7 | E22: -0.7
A23: Available OCF | B23: 2.3 | C23: 2.3 | D23: 1.5 | E23: 1.6

Sheet Guidance
A1: EPS Guidance Evolution
A3: Guidance Given At | B3: Next-Q EPS Range | C3: Next-Q YoY | D3: Full-Year EPS Range | E3: Full-Year YoY | F3: FX Assumption
A4: Q3'25 (Oct 31, 2025) | B4: $4.10–$4.20 | C4: +3% to +6% | D4: $16.35–$16.45 | E4: +5% to +6% | F4: FY: flat
A5: Q4'25 (Feb 5, 2026) | B5: $4.20–$4.30 | C5: +6% to +9% | D5: $17.40–$17.90 | E5: +6% to +9% | F5: FY: +1%
A6: Q1'26 (May 1, 2026) | B6: $4.40–$4.50 | C6: +8% to +10% | D6: $17.60–$17.90 | E6: +7% to +9% | F6: FY: +1%
A7: Q2'26 (Jul 31, 2026) | B7: $4.45–$4.55 | C7: +6% to +8% | D7: $17.70–$17.90 | E7: +8% to +9% | F7: FY: +1%
A9: Actual EPS vs. Guidance
A10: Quarter | B10: Guidance Range | C10: Actual EPS | D10: vs. Midpoint | E10: Beat/Miss
A11: 3Q 2025 | B11: $4.07–$4.17 (prev.) | C11: $4.21 | D11: +$0.09 | E11: Beat
A12: 4Q 2025 | B12: $4.10–$4.20 | C12: $4.20 | D12: +$0.05 | E12: Beat (top)
A13: 1Q 2026 | B13: $4.20–$4.30 | C13: $4.33 | D13: +$0.08 | E13: Beat
A14: 2Q 2026 | B14: $4.40–$4.50 | C14: $4.50 | D14: +$0.05 | E14: Beat (top)
A16: Capex Guidance Evolution
A17: Given At | B17: Full-Year Capex Guidance
A18: Q3'25 (FY2025) | B18: $5.0B–$5.5B
A19: Q4'25 (FY2026) | B19: $5.0B–$5.5B
A20: Q1'26 (FY2026) | B20: $5.0B–$5.5B
A21: Q2'26 (FY2026) | B21: $5.5B–$6.0B ↑

Sheet Electronics Deep Dive
A1: Electronics End Market — Revenue Derivation
A2: Based on % of Sales from official Linde investor slides + total reported revenue
A4: Metric | B4: 3Q 2025 | C4: 4Q 2025 | D4: 1Q 2026 | E4: 2Q 2026
A5: Total Revenue ($MM) | B5: 8615 | C5: 8764 | D5: 8781 | E5: 9289
A6: Electronics % of Sales | B6: 9% | C6: 10% | D6: 10% | E6: 10%
A7: Est. Electronics Rev ($MM) | B7: 775 | C7: 876 | D7: 878 | E7: 929
A8: YoY Growth | B8: +6% | C8: +7% | D8: +10% | E8: +18%
A9: Seq. Growth | B9: +4% | C9: +5% | D9: +1% | E9: +7%
A11: Taiwan JV (non-consol.) | B11: ~+2% add'l | C11: ~+2% add'l | D11: ~+2% add'l | E11: ~+2% add'l
A12: Adj. Electronics Exposure | B12: ~11% | C12: ~12% | D12: ~12% | E12: ~12%
A14: SOG Backlog ($B) | B14: 7.1 | C14: 7.3 | D14: 7.1 | E14: 8.1
A15: QoQ Change | B15: — | C15: +$0.2B | D15: -$0.2B | E15: +$1.0B
A16: Key Events | B16: Backlog $10B total | C16: Record backlog | D16: 10 projects started | E16: +$1B US electronics

Sheet Sources
A1: Linde plc — Sources
A2: $ in millions except per-share data | USD | as of 2026-09-15
A4: Sources and data provenance
A6: Period | B6: Source document | C6: Path
A7: FY2018 | B7: Linde plc Form 10-K (FY2018) | C7: sources/companies/US/LIN-linde/artifacts/ten_k/LIN-linde/FY2018/psp_2ebae6876662453e850a71097e970a0c/
A8: FY2019 | B8: Linde plc Form 10-K (FY2019) | C8: sources/companies/US/LIN-linde/artifacts/ten_k/LIN-linde/FY2019/psp_17c00f60b08b453fae28219102907da2/
A9: FY2020 | B9: Linde plc Form 10-K (FY2020) | C9: sources/companies/US/LIN-linde/artifacts/ten_k/LIN-linde/FY2020/psp_26319e151ba249dea1137948aedfa245/
A10: FY2021 | B10: Linde plc Form 10-K (FY2021) | C10: sources/companies/US/LIN-linde/artifacts/ten_k/LIN-linde/FY2021/psp_b2b8c0f9a8374dca86d6ba61612f5ea8/
A11: FY2022 | B11: Linde plc Form 10-K (FY2022) | C11: sources/companies/US/LIN-linde/artifacts/ten_k/LIN-linde/FY2022/psp_12a4ea550bc340fa82af491fa19c65cc/
A12: FY2023 | B12: Linde plc Form 10-K (FY2023) | C12: sources/companies/US/LIN-linde/artifacts/ten_k/LIN-linde/FY2023/psp_962cb7e58b0a4448ae507427a5c3a749/
A13: FY2024 | B13: Linde plc Form 10-K (FY2024) | C13: sources/companies/US/LIN-linde/artifacts/ten_k/LIN-linde/FY2024/psp_871627ce04e94c8897932a75dbc7c38b/
A14: FY2025 | B14: Linde plc Form 10-K (FY2025) | C14: sources/companies/US/LIN-linde/artifacts/ten_k/LIN-linde/FY2025/psp_ddce53d5cc49476d894d1511e805bb4a/
A16: Note | B16: All figures hand-extracted and cross-checked from each fiscal year's own 10-K (prepared/document.md), not from tables.json (which misclassified statement tables under unrelated topic_hints and mis-parsed parenthesized negative values) and not from any deep-research markdown report.

Sheet Valuation Driver Build
A1: Linde plc — Valuation Driver Build
A2: 年结日估值口径：FY2026 Q1/Q2 为已披露实际，Q3/Q4 为估计；预测区在左，完整年度与近期季度历史在右。单位：$ in millions except per-share data.
A4: 经营驱动与现金股东回报推导
A5: 指标 | B5: 单位 | C5: 2026 Q1A | D5: 2026 Q2A | E5: 2026 Q3E | F5: 2026 Q4E | G5: FY2026E | H5: FY2027E | I5: FY2028E | J5: FY2029E | K5: FY2030E | L5: FY2031E | N5: FY2018 | O5: FY2019 | P5: FY2020 | Q5: FY2021 | R5: FY2022 | S5: FY2023 | T5: FY2024 | U5: FY2025 | V5: 3Q 2025 | W5: 4Q 2025 | X5: 1Q 2026 | Y5: 2Q 2026
A6: 销售增速 | B6: % | C6: 0.08 | D6: 0.09 | E6: 0.06 | F6: 0.06 | G6: =G7/T7-1 -> 0.10564278 | H6: 0.055 | I6: 0.055 | J6: 0.05 | K6: 0.05 | L6: 0.05 | N6: ='Income Statement'!C11 -> 0 | O6: ='Income Statement'!D11 -> 0.89449664 | P6: ='Income Statement'!E11 -> -0.034894431 | Q6: ='Income Statement'!F11 -> 0.1303087 | R6: ='Income Statement'!G11 -> 0.083493002 | S6: ='Income Statement'!H11 -> -0.015285937 | T6: ='Income Statement'!I11 -> 0.0045960918 | U6: ='Income Statement'!J11 -> 0.029722769 | V6: 0.03 | W6: 0.06 | X6: 0.08 | Y6: 0.09
A7: 销售额 | B7: $mm | C7: =Consolidated!D4 -> 8781 | D7: =Consolidated!E4 -> 9289 | E7: =Consolidated!B4*(1+E6) -> 9131.9 | F7: =Consolidated!C4*(1+F6) -> 9289.84 | G7: =SUM(C7:F7) -> 36491.74 | H7: =G7*(1+H6) -> 38498.786 | I7: =H7*(1+I6) -> 40616.219 | J7: =I7*(1+J6) -> 42647.03 | K7: =J7*(1+K6) -> 44779.381 | L7: =K7*(1+L6) -> 47018.35 | N7: ='Income Statement'!C10 -> 14900 | O7: ='Income Statement'!D10 -> 28228 | P7: ='Income Statement'!E10 -> 27243 | Q7: ='Income Statement'!F10 -> 30793 | R7: ='Income Statement'!G10 -> 33364 | S7: ='Income Statement'!H10 -> 32854 | T7: ='Income Statement'!I10 -> 33005 | U7: ='Income Statement'!J10 -> 33986 | V7: =Consolidated!B4 -> 8615 | W7: =Consolidated!C4 -> 8764 | X7: =Consolidated!D4 -> 8781 | Y7: =Consolidated!E4 -> 9289
A8: 经营利润 | B8: $mm | C8: =Consolidated!D7 -> 2630 | D8: =Consolidated!E7 -> 2744 | E8: =E7*E9 -> 2739.57 | F8: =F7*F9 -> 2805.5317 | G8: =SUM(C8:F8) -> 10919.102 | H8: =H7*H9 -> 11742.13 | I8: =I7*I9 -> 12509.795 | J8: =J7*J9 -> 13263.226 | K8: =K7*K9 -> 14060.726 | L8: =L7*L9 -> 14904.817 | N8: ='Income Statement'!C23 -> 5247 | O8: ='Income Statement'!D23 -> 2933 | P8: ='Income Statement'!E23 -> 3322 | Q8: ='Income Statement'!F23 -> 4984 | R8: ='Income Statement'!G23 -> 5369 | S8: ='Income Statement'!H23 -> 8024 | T8: ='Income Statement'!I23 -> 8635 | U8: ='Income Statement'!J23 -> 8923 | V8: =Consolidated!B7 -> 2558 | W8: =Consolidated!C7 -> 2585 | X8: =Consolidated!D7 -> 2630 | Y8: =Consolidated!E7 -> 2744
A9: 经营利润率 | B9: % | C9: =Consolidated!D8 -> 30.0% | D9: =Consolidated!E8 -> 29.5% | E9: 0.3 | F9: 0.302 | G9: =G8/G7 -> 0.29922118 | H9: 0.305 | I9: 0.308 | J9: 0.311 | K9: 0.314 | L9: 0.317 | N9: ='Income Statement'!C24 -> 0.35214765 | O9: ='Income Statement'!D24 -> 0.10390393 | P9: ='Income Statement'!E24 -> 0.12193958 | Q9: ='Income Statement'!F24 -> 0.16185497 | R9: ='Income Statement'!G24 -> 0.16092195 | S9: ='Income Statement'!H24 -> 0.24423206 | T9: ='Income Statement'!I24 -> 0.26162703 | U9: ='Income Statement'!J24 -> 0.26254928 | V9: =Consolidated!B8 -> 29.7% | W9: =Consolidated!C8 -> 29.5% | X9: =Consolidated!D8 -> 30.0% | Y9: =Consolidated!E8 -> 29.5%
A10: 调整后净利润 / 管理层净利润 | B10: $mm | C10: =Consolidated!D9 -> 2019 | D10: =Consolidated!E9 -> 2089 | E10: =E13*E12 -> 2126.0257 | F10: =F13*F12 -> 2111.8522 | G10: =SUM(C10:F10) -> 8345.8779 | H10: =H7*H11 -> 8777.7231 | I10: =I7*I11 -> 9341.7304 | J10: =J7*J11 -> 9894.1109 | K10: =K7*K11 -> 10478.375 | L10: =L7*L11 -> 11096.331 | N10: ='Income Statement'!C37 -> 4381 | O10: ='Income Statement'!D37 -> 2285 | P10: ='Income Statement'!E37 -> 2501 | Q10: ='Income Statement'!F37 -> 3826 | R10: ='Income Statement'!G37 -> 4147 | S10: ='Income Statement'!H37 -> 6199 | T10: ='Income Statement'!I37 -> 6565 | U10: ='Income Statement'!J37 -> 6898 | V10: =Consolidated!B9 -> 1987 | W10: =Consolidated!C9 -> 1968 | X10: =Consolidated!D9 -> 2019 | Y10: =Consolidated!E9 -> 2089
A11: 净利润率 | B11: % | C11: =C10/C7 -> 0.22992825 | D11: =D10/D7 -> 0.22488965 | E11: =E10/E7 -> 0.23281308 | F11: =F10/F7 -> 0.22732923 | G11: =G10/G7 -> 0.22870595 | H11: 0.228 | I11: 0.23 | J11: 0.232 | K11: 0.234 | L11: 0.236 | N11: =N10/N7 -> 0.29402685 | O11: =O10/O7 -> 0.080947995 | P11: =P10/P7 -> 0.091803399 | Q11: =Q10/Q7 -> 0.12424902 | R11: =R10/R7 -> 0.12429565 | S11: =S10/S7 -> 0.18868327 | T11: =T10/T7 -> 0.19890926 | U11: =U10/U7 -> 0.20296593 | ... Y11: =Y10/Y7 -> 0.22488965
A12: 稀释后股数 | B12: mm | C12: ='Income Statement'!J48/1000 -> 472.195 | D12: ='Income Statement'!J48/1000 -> 472.195 | E12: =G12 -> 472.45016 | F12: =G12 -> 472.45016 | G12: =T12*(1-G14) -> 472.45016 | H12: =G12*(1-H14) -> 463.00116 | I12: =H12*(1-I14) -> 453.74113 | J12: =I12*(1-J14) -> 444.66631 | K12: =J12*(1-K14) -> 435.77298 | L12: =K12*(1-L14) -> 427.05753 | N12: ='Income Statement'!C48/1000 -> 334.127 | O12: ='Income Statement'!D48/1000 -> 545.17 | P12: ='Income Statement'!E48/1000 -> 531.157 | Q12: ='Income Statement'!F48/1000 -> 521.875 | R12: ='Income Statement'!G48/1000 -> 504.038 | S12: ='Income Statement'!H48/1000 -> 492.29 | T12: ='Income Statement'!I48/1000 -> 482.092 | U12: ='Income Statement'!J48/1000 -> 472.195 | V12: ="n.a." -> n.a. | W12: ="n.a." -> n.a. | X12: ="n.a." -> n.a. | Y12: ="n.a." -> n.a.
A13: 调整后稀释 EPS | B13: $ / share | C13: =Consolidated!D10 -> 4.33 | D13: =Consolidated!E10 -> 4.5 | E13: 4.5 | F13: =G13-C13-D13-E13 -> 4.47 | G13: 17.8 | H13: =H10/H12 -> 18.958318 | I13: =I10/I12 -> 20.588238 | J13: =J10/J12 -> 22.250642 | K13: =K10/K12 -> 24.045491 | L13: =L10/L12 -> 25.983223 | N13: ='Income Statement'!C45 -> 13.11 | O13: ='Income Statement'!D45 -> 4.19 | P13: ='Income Statement'!E45 -> 4.71 | Q13: ='Income Statement'!F45 -> 7.33 | R13: ='Income Statement'!G45 -> 8.23 | S13: ='Income Statement'!H45 -> 12.59 | T13: ='Income Statement'!I45 -> 13.62 | U13: ='Income Statement'!J45 -> 14.61 | V13: =Consolidated!B10 -> 4.21 | W13: =Consolidated!C10 -> 4.2 | X13: =Consolidated!D10 -> 4.33 | Y13: =Consolidated!E10 -> 4.5
A14: 净缩股速率 | B14: % | G14: 0.02 | H14: 0.02 | I14: 0.02 | J14: 0.02 | K14: 0.02 | L14: 0.02 | O14: =1-O12/N12 -> -0.6316251 | P14: =1-P12/O12 -> 0.025703909 | Q14: =1-Q12/P12 -> 0.017475059 | R14: =1-R12/Q12 -> 0.034178683 | S14: =1-S12/R12 -> 0.023307766 | T14: =1-T12/S12 -> 0.020715432 | U14: =1-U12/T12 -> 0.020529277 | V14: ="n.a." -> n.a. | W14: ="n.a." -> n.a. | X14: ="n.a." -> n.a. | Y14: ="n.a." -> n.a.
A15: 资本开支 | B15: $mm | C15: =Consolidated!D14 -> 1342 | D15: =Consolidated!E14 -> 1438 | E15: 1450 | F15: =G15-C15-D15-E15 -> 1520 | G15: 5750 | H15: =H7*H16 -> 5967.3118 | I15: =I7*I16 -> 6092.4328 | J15: =J7*J16 -> 6183.8193 | K15: =K7*K16 -> 6493.0103 | L15: =L7*L16 -> 6817.6608 | N15: =-'Cash Flow Statement'!C33 -> 1883 | O15: =-'Cash Flow Statement'!D33 -> 3682 | P15: =-'Cash Flow Statement'!E33 -> 3400 | Q15: =-'Cash Flow Statement'!F33 -> 3086 | R15: =-'Cash Flow Statement'!G33 -> 3173 | S15: =-'Cash Flow Statement'!H33 -> 3787 | T15: =-'Cash Flow Statement'!I33 -> 4497 | U15: =-'Cash Flow Statement'!J33 -> 5261 | V15: =Consolidated!B14 -> 1276 | W15: =Consolidated!C14 -> 1458 | X15: =Consolidated!D14 -> 1342 | Y15: =Consolidated!E14 -> 1438
A16: 资本开支 / 销售额 | B16: % | C16: =C15/C7 -> 0.15282997 | D16: =D15/D7 -> 0.15480676 | E16: =E15/E7 -> 0.15878404 | F16: =F15/F7 -> 0.16361961 | G16: =G15/G7 -> 0.1575699 | H16: 0.155 | I16: 0.15 | J16: 0.145 | K16: 0.145 | L16: 0.145 | N16: =-'Cash Flow Statement'!C33/'Income Statement'!C10 -> 0.12637584 | O16: =-'Cash Flow Statement'!D33/'Income Statement'!D10 -> 0.13043786 | P16: =-'Cash Flow Statement'!E33/'Income Statement'!E10 -> 0.1248027 | Q16: =-'Cash Flow Statement'!F33/'Income Statement'!F10 -> 0.10021758 | R16: =-'Cash Flow Statement'!G33/'Income Statement'!G10 -> 0.095102506 | S16: =-'Cash Flow Statement'!H33/'Income Statement'!H10 -> 0.11526755 | T16: =-'Cash Flow Statement'!I33/'Income Statement'!I10 -> 0.13625208 | U16: =-'Cash Flow Statement'!J33/'Income Statement'!J10 -> 0.15479903 | V16: =Consolidated!B14/Consolidated!B4 -> 0.14811376 | W16: =Consolidated!C14/Consolidated!C4 -> 0.16636239 | X16: =Consolidated!D14/Consolidated!D4 -> 0.15282997 | Y16: =Consolidated!E14/Consolidated!E4 -> 0.15480676
A17: FCF 转换率 | B17: % | C17: =(Consolidated!D12-Consolidated!D14)/Consolidated!D9 -> 0.44477464 | D17: =(Consolidated!E12-Consolidated!E14)/Consolidated!E9 -> 0.39875539 | G17: 0.7 | H17: 0.75 | I17: 0.77 | J17: 0.78 | K17: 0.78 | L17: 0.78 | N17: ='Cash Flow Statement'!C66 -> 0.40424561 | O17: ='Cash Flow Statement'!D66 -> 1.0665208 | P17: ='Cash Flow Statement'!E66 -> 1.6109556 | Q17: ='Cash Flow Statement'!F66 -> 1.7352326 | R17: ='Cash Flow Statement'!G66 -> 1.3723173 | S17: ='Cash Flow Statement'!H66 -> 0.89014357 | T17: ='Cash Flow Statement'!I66 -> 0.75034273 | U17: ='Cash Flow Statement'!J66 -> 0.73775007 | V17: =(Consolidated!B12-Consolidated!B14)/Consolidated!B9 -> 0.84146955 | W17: =(Consolidated!C12-Consolidated!C14)/Consolidated!C9 -> 0.79878049 | X17: =(Consolidated!D12-Consolidated!D14)/Consolidated!D9 -> 0.44477464 | Y17: =(Consolidated!E12-Consolidated!E14)/Consolidated!E9 -> 0.39875539
A18: FCF | B18: $mm | C18: =Consolidated!D12-Consolidated!D14 -> 898 | D18: =Consolidated!E12-Consolidated!E14 -> 833 | G18: =G10*G17 -> 5842.1146 | H18: =H10*H17 -> 6583.2924 | I18: =I10*I17 -> 7193.1324 | J18: =J10*J17 -> 7717.4065 | K18: =K10*K17 -> 8173.1327 | L18: =L10*L17 -> 8655.1379 | N18: ='Cash Flow Statement'!C62 -> 1771 | O18: ='Cash Flow Statement'!D62 -> 2437 | P18: ='Cash Flow Statement'!E62 -> 4029 | Q18: ='Cash Flow Statement'!F62 -> 6639 | R18: ='Cash Flow Statement'!G62 -> 5691 | S18: ='Cash Flow Statement'!H62 -> 5518 | T18: ='Cash Flow Statement'!I62 -> 4926 | U18: ='Cash Flow Statement'!J62 -> 5089 | V18: =Consolidated!B12-Consolidated!B14 -> 1672 | W18: =Consolidated!C12-Consolidated!C14 -> 1572 | X18: =Consolidated!D12-Consolidated!D14 -> 898 | Y18: =Consolidated!E12-Consolidated!E14 -> 833
A19: 现金分红支付率 | B19: % | G19: 0.4 | H19: 0.4 | I19: 0.4 | J19: 0.4 | K19: 0.4 | L19: 0.4 | N19: =-'Cash Flow Statement'!C45/'Income Statement'!C37 -> 0.26614928 | O19: =-'Cash Flow Statement'!D45/'Income Statement'!D37 -> 0.82757112 | P19: =-'Cash Flow Statement'!E45/'Income Statement'!E37 -> 0.81087565 | Q19: =-'Cash Flow Statement'!F45/'Income Statement'!F37 -> 0.572138 | R19: =-'Cash Flow Statement'!G45/'Income Statement'!G37 -> 0.56522788 | S19: =-'Cash Flow Statement'!H45/'Income Statement'!H37 -> 0.40038716 | T19: =-'Cash Flow Statement'!I45/'Income Statement'!I37 -> 0.40441736 | U19: =-'Cash Flow Statement'!J45/'Income Statement'!J37 -> 0.40750942 | V19: ="n.a." -> n.a. | W19: ="n.a." -> n.a. | X19: ="n.a." -> n.a. | Y19: ="n.a." -> n.a.
A20: 每股现金分红 | B20: $ / share | G20: =G13*G19 -> 7.12 | H20: =H13*H19 -> 7.5833272 | I20: =I13*I19 -> 8.2352951 | J20: =J13*J19 -> 8.9002568 | K20: =K13*K19 -> 9.6181963 | L20: =L13*L19 -> 10.393289 | N20: ='Income Statement'!C45*(-'Cash Flow Statement'!C45/'Income Statement'!C37) -> 3.4892171 | O20: ='Income Statement'!D45*(-'Cash Flow Statement'!D45/'Income Statement'!D37) -> 3.467523 | P20: ='Income Statement'!E45*(-'Cash Flow Statement'!E45/'Income Statement'!E37) -> 3.8192243 | Q20: ='Income Statement'!F45*(-'Cash Flow Statement'!F45/'Income Statement'!F37) -> 4.1937716 | R20: ='Income Statement'!G45*(-'Cash Flow Statement'!G45/'Income Statement'!G37) -> 4.6518254 | S20: ='Income Statement'!H45*(-'Cash Flow Statement'!H45/'Income Statement'!H37) -> 5.0408743 | T20: ='Income Statement'!I45*(-'Cash Flow Statement'!I45/'Income Statement'!I37) -> 5.5081645 | U20: ='Income Statement'!J45*(-'Cash Flow Statement'!J45/'Income Statement'!J37) -> 5.9537127 | V20: ="n.a." -> n.a. | W20: ="n.a." -> n.a. | X20: ="n.a." -> n.a. | Y20: ="n.a." -> n.a.
A23: 口径与推导说明
A24: 1. FY2026 基期采用年结日口径：Q1/Q2 为当前底稿已披露实际，Q3 采用最新季度指引 EPS 中值 $4.50，Q4 为全年指引中值 $17.80 减前三季度实际/预测。
A25: 2. FY2026 销售额按 Q3/Q4 同比 +6% 估计；资本开支采用管理层 Q2 纪要给出的 FY2026 $5.5–6.0B 中值 $5.75B。
A26: 3. FY2027–FY2031 销售增速、利润率、缩股、FCF 转换率和分红支付率为可编辑基准假设，均应在新财报发布后与实际和指引逐项复核。
A27: 4. FY2018–FY2025 右侧历史主要为 10-K GAAP 数据；FY2025及近期季度的 EPS/净利润历史区块同时参考管理层调整后口径，已在标签中明确，不能与 GAAP 直接混比。
A28: 5. 预测区右侧强制保留完整年度与连续近期季度历史，更新时先以新披露替换预测，再重算全年、现金流、股数与估值。

Sheet Year-End Valuation
A1: Linde plc — Year-End Valuation
A2: 直接退出 PE + 现金分红 + 净缩股；以 FY2026E 完整财年为估值基期，预测至 FY2031E。
A4: 估值起点与控制项
A5: 估值日期 | B5: 2026-09-15 | D5: 说明
A6: 当前股价（输入） | C6: $ / share | D6: 需由用户按估值日补充；未填时 IRR 保持空白
A7: 当前稀释后股数 | B7: ='Valuation Driver Build'!G12 -> 472.45016 | C7: mm | D7: 链接 FY2026E 估计；用于市值换算
A8: 当前总市值 | B8: =IF(B6="","",B6*B7) | C8: $mm | D8: 当前股价 × 当前稀释后股数
A9: 要求年化股东回报率 | B9: 0.1 | C9: % | D9: 可编辑目标回报率
A10: 退出 PE | B10: 25 | C10: 倍 | D10: 直接输入；净缩股通过 EPS/股数路径单独体现
A11: 模型状态 | B11: =IF(AND(B6>0,B9>0,B10>0),"可计算","待补充当前股价或检查输入") -> 待补充当前股价或检查输入 | D11: 需要当前股价后才可计算 IRR
A13: 年结日预测与每股价值路径
A14: 指标 | B14: FY2026E | C14: FY2027E | D14: FY2028E | E14: FY2029E | F14: FY2030E | G14: FY2031E
A15: 调整后稀释 EPS | B15: ='Valuation Driver Build'!G13 -> 17.8 | C15: ='Valuation Driver Build'!H13 -> 18.958318 | D15: ='Valuation Driver Build'!I13 -> 20.588238 | E15: ='Valuation Driver Build'!J13 -> 22.250642 | F15: ='Valuation Driver Build'!K13 -> 24.045491 | G15: ='Valuation Driver Build'!L13 -> 25.983223
A16: 净缩股速率 | B16: ='Valuation Driver Build'!G14 -> 0.02 | C16: ='Valuation Driver Build'!H14 -> 0.02 | D16: ='Valuation Driver Build'!I14 -> 0.02 | E16: ='Valuation Driver Build'!J14 -> 0.02 | F16: ='Valuation Driver Build'!K14 -> 0.02 | G16: ='Valuation Driver Build'!L14 -> 0.02
A17: 股数指数 | B17: =1 -> 1 | C17: =B17*(1-C16) -> 0.98 | D17: =C17*(1-D16) -> 0.9604 | E17: =D17*(1-E16) -> 0.941192 | F17: =E17*(1-F16) -> 0.92236816 | G17: =F17*(1-G16) -> 0.9039208
A18: 现金分红支付率 | B18: ='Valuation Driver Build'!G19 -> 0.4 | C18: ='Valuation Driver Build'!H19 -> 0.4 | D18: ='Valuation Driver Build'!I19 -> 0.4 | E18: ='Valuation Driver Build'!J19 -> 0.4 | F18: ='Valuation Driver Build'!K19 -> 0.4 | G18: ='Valuation Driver Build'!L19 -> 0.4
A19: 每股现金分红 | B19: =B15*B18 -> 7.12 | C19: =C15*C18 -> 7.5833272 | D19: =D15*D18 -> 8.2352951 | E19: =E15*E18 -> 8.9002568 | F19: =F15*F18 -> 9.6181963 | G19: =G15*G18 -> 10.393289
A20: 退出 PE | B20: =$B$10 -> 25 | C20: =$B$10 -> 25 | D20: =$B$10 -> 25 | E20: =$B$10 -> 25 | F20: =$B$10 -> 25 | G20: =$B$10 -> 25
A21: 退出价值 / 每股 | B21: =B15*B20 -> 445 | C21: =C15*C20 -> 473.95795 | D21: =D15*D20 -> 514.70594 | E21: =E15*E20 -> 556.26605 | F21: =F15*F20 -> 601.13727 | G21: =G15*G20 -> 649.58056
A22: FCF 转换率 | B22: ='Valuation Driver Build'!G17 -> 0.7 | C22: ='Valuation Driver Build'!H17 -> 0.75 | D22: ='Valuation Driver Build'!I17 -> 0.77 | E22: ='Valuation Driver Build'!J17 -> 0.78 | F22: ='Valuation Driver Build'!K17 -> 0.78 | G22: ='Valuation Driver Build'!L17 -> 0.78
A23: FCF | B23: ='Valuation Driver Build'!G18 -> 5842.1146 | C23: ='Valuation Driver Build'!H18 -> 6583.2924 | D23: ='Valuation Driver Build'!I18 -> 7193.1324 | E23: ='Valuation Driver Build'!J18 -> 7717.4065 | F23: ='Valuation Driver Build'!K18 -> 8173.1327 | G23: ='Valuation Driver Build'!L18 -> 8655.1379
A24: 调整后净利润 | B24: ='Valuation Driver Build'!G10 -> 8345.8779 | C24: ='Valuation Driver Build'!H10 -> 8777.7231 | D24: ='Valuation Driver Build'!I10 -> 9341.7304 | E24: ='Valuation Driver Build'!J10 -> 9894.1109 | F24: ='Valuation Driver Build'!K10 -> 10478.375 | G24: ='Valuation Driver Build'!L10 -> 11096.331
A27: 估值结果
A28: 指标 | B28: 2 年持有 | C28: 5 年持有 | D28: 说明
A29: 退出年度 | B29: FY2028E | C29: FY2031E | D29: 估值基期为 FY2026E 年结日
A30: 退出 EPS | B30: =D15 -> 20.588238 | C30: =G15 -> 25.983223
A31: 退出 PE | B31: =D20 -> 25 | C31: =G20 -> 25 | D31: 直接输入
A32: 退出价值 / 每股 | B32: =D21 -> 514.70594 | C32: =G21 -> 649.58056
A33: 持有期现金分红 / 每股 | B33: =C19+D19 -> 15.818622 | C33: =C19+D19+E19+F19+G19 -> 44.730364 | D33: 仅含 FY2027E 起的现金分红
A34: 目标买入价 / 每股 | B34: =C19/(1+$B$9)+(D19+D21)/(1+$B$9)^2 -> 439.07678 | C34: =C19/(1+$B$9)+D19/(1+$B$9)^2+E19/(1+$B$9)^3+F19/(1+$B$9)^4+(G19+G21)/(1+$B$9)^5 -> 436.74805 | D34: 按要求回报率折现终值和分红
A35: 当前股价 | B35: =$B$6 -> 0 | C35: =$B$6 -> 0 | D35: 链接估值输入
A36: 股东回报 IRR | B36: =IF($B$6="","",IRR(B42:D42)) | C36: =IF($B$6="","",IRR(B41:G41)) | D36: 当前股价填入后自动计算
A39: IRR 现金流核对
A40: 期间 | B40: 起点 | C40: FY2027E | D40: FY2028E | E40: FY2029E | F40: FY2030E | G40: FY2031E
A41: 5 年 | B41: =-$B$6 -> 0 | C41: =C19 -> 7.5833272 | D41: =D19 -> 8.2352951 | E41: =E19 -> 8.9002568 | F41: =F19 -> 9.6181963 | G41: =G19+G21 -> 659.97385
A42: 2 年 | B42: =-$B$6 -> 0 | C42: =C19 -> 7.5833272 | D42: =D19+D21 -> 522.94124
A45: 使用说明与限制
A46: 1. 该模型采用直接退出 PE 的股东回报方法。退出 PE 是直接输入值，不再乘以缩股参数；缩股通过稀释后股数和 EPS 路径单独体现。
A47: 2. FCF = OCF - Capex。FY2026 资本开支使用管理层 $5.5–6.0B 指引中值；FCF 转换率为预测参数，需在实际现金流披露后复核。
A48: 3. FY2025及近期季度的 EPS/净利润为管理层调整后口径；历史 GAAP 指标保留在 Valuation Driver Build 右侧作为校准，不得混用。
A49: 4. 当前股价为唯一必须由用户按估值日补充的外部市场输入；未填时目标买入价仍可计算，但 IRR 和当前市值状态显示为待补充。
