Workbook

Sheet Cover
A1: Broadcom Inc. — Cover
A2: $ in millions except per-share data | USD | as of 2026-09-22
A4: Broadcom Inc. (NASDAQ: AVGO) — Financial Model
A6: Company Overview
A7: Legal name | B7: Broadcom Inc. (Delaware; formerly Broadcom Limited, a Singapore public company, through the April 2018 redomiciliation)
A8: Ticker | B8: AVGO (NASDAQ)
A9: Reporting currency / units | B9: USD, $ in millions except per-share data
A10: Reporting framework | B10: US GAAP
A11: Fiscal year end | B11: Last Sunday of October or first Sunday of November (52/53-week fiscal year)
A12: Fiscal years covered | B12: FY2016 (ended 2016-10-30) through FY2025 (ended 2025-11-02), plus 3Q FY2026 (13 weeks ended 2026-08-02)
A13: As-of date | B13: 2025-11-02 (FY2025 fiscal year end); interim data through 2026-08-02
A14: Model date | B14: 2026-09-22
A15: Consolidation scope | B15: Consolidated (includes VMware, Inc. from November 22, 2023)
A17: Color Legend
A18: Hardcoded reported value | B18: Blue font — taken directly from a source filing
A19: Formula / calculation | B19: Black font — computed from other cells in this workbook
A20: Cross-sheet link | B20: Green font — pulled from another sheet
A21: Memo / commentary | B21: Grey italic — margin, growth, or annotation row
A23: Sheet Directory
A24: IS — Income Statement | B24: As-reported revenue through net income, EPS, margins, YoY growth
A25: BS — Balance Sheet | B25: As-reported assets/liabilities/equity, balance check, working-capital analytics (DSO/DIO/DPO/CCC)
A26: CF — Cash Flow Statement | B26: As-reported operating/investing/financing detail, cash walk check, FCF analytics
A27: SEG — Segments | B27: Segment revenue & operating income across three successive segment structures (4-seg / 3-seg / 2-seg), tie-out checks
A28: DM — Derived Metrics | B28: Profitability, returns, leverage, solvency, liquidity, coverage, cash conversion, earnings quality, growth, working capital
A29: Sources | B29: Filing-level source index and key comparability notes
A31: Key Comparability Caveats — read before using this model
A32: 1. VMware scale jump (FY2023 -> FY2024) | B32: VMware, Inc. acquisition closed Nov 22, 2023 (day 1 of FY2024), for $86,290M total consideration (~$54.2B in Broadcom stock, remainder cash). Goodwill $43.7B->$97.9B, intangibles $3.9B->$40.6B, total assets $72.9B->$165.6B, revenue $35.8B->$51.6B. FY2023 and prior are pre-VMware; treat FY2023->FY2024 as a structural break, not organic growth.
A33: 2. FY2025 revenue reclassification | B33: Per FY2025 10-K Note 3: 'we included upfront license revenue of $7,800 million within products revenue... we reclassified $4,601 million and $1,058 million of upfront license revenue from subscriptions and services revenue to products revenue for fiscal years 2024 and 2023, respectively.' This model uses each fiscal year's OWN as-filed Products/Subscriptions split (i.e., FY2024 and FY2023 columns are NOT reclassified/recast) — a pure historical series. Do not compare Products vs. Subscriptions growth rates across the FY2023/FY2024/FY2025 boundary without adjusting for this.
A34: 3. 10-for-1 forward stock split (July 2024) | B34: Effective July 15, 2024 (within FY2024). FY2016-FY2023 EPS/share-count columns are each year's own pre-split as-filed figures; FY2024 onward are post-split. WASO basic jumps from 415M (FY2023) to 4,624M (FY2024) — roughly 11.1x, reflecting both the 10:1 split and real new share issuance for the VMware deal. Do not compute raw EPS/share-count YoY growth across this boundary.
A35: 4. 2018 CIK change / redomiciliation | B35: Broadcom redomiciled from Singapore (Broadcom Limited, CIK 0001649338) to Delaware (Broadcom Inc., CIK 0001730168) on April 4, 2018, accounted for as a common-control transaction (historical financials carried over on the same basis, no restatement). Treated as continuous in this model. Noncontrolling interest (exchangeable LP units) existed FY2016-FY2018 and was eliminated at the redomiciliation.
A36: 5. Segment redefinition | B36: FY2016-FY2018: 4 segments (Wired Infrastructure, Wireless Communications, Enterprise Storage, Industrial & Other). FY2019 only: 3 segments (Semiconductor Solutions, Infrastructure Software, IP Licensing) following the Nov 2018 CA Technologies acquisition. FY2020-present: 2 segments (Semiconductor Solutions, Infrastructure Software). The SEG sheet presents each structure as a separate block (not stitched together) per the source-hierarchy rule against mixing segment definitions.
A37: 6. FY2020-FY2022 segment data sourced from MD&A, not a formal Note | B37: Broadcom's FY2020, FY2021 and FY2022 10-Ks do not include a numeric segment table in the Segment Information note (narrative only in some years); the segment revenue/operating income figures for those years are sourced from each year's MD&A 'Results of Operations' table instead (still Tier-2 SEC-filing sourced, just a different section of the same document).
A38: 7. FY2024 discontinued operations | B38: Broadcom sold the VMware End-User Computing (EUC) business to KKR on July 1, 2024 for $3.5B cash. FY2024's own as-filed income statement includes a 'Loss from discontinued operations, net of income taxes' line of $(273)M; FY2023 and earlier show no such line since EUC was only acquired as part of VMware at the start of FY2024 (no retroactive restatement was required or made).
A39: 8. 3Q FY2026 (10-Q) presentation basis | B39: Income Statement and Segment quarterly columns show the single 13-week quarter ended 2026-08-02. Balance Sheet quarterly column is the point-in-time balance as of 2026-08-02. Cash Flow Statement quarterly column is the cumulative 9-month year-to-date figure as filed (Broadcom's 10-Q does not present single-quarter cash flows) — this is a different grain than the IS/BS quarterly column and is explicitly noted on the CF sheet.

Sheet Income Statement
A1: Broadcom Inc. — Income Statement
A2: $ in millions except per-share data | USD | as of 2026-09-22
C3: FY2016 | D3: FY2017 | E3: FY2018 | F3: FY2019 | G3: FY2020 | H3: FY2021 | I3: FY2022 | J3: FY2023 | K3: FY2024 | L3: FY2025 | M3: · | N3: · | O3: 2Q FY2024 | P3: 3Q FY2024 | Q3: 1Q FY2025 | R3: 2Q FY2025 | S3: 3Q FY2025 | T3: 1Q FY2026 | U3: 2Q FY2026 | V3: 3Q FY2026
C4: 2016-10-30 | D4: 2017-10-29 | E4: 2018-11-04 | F4: 2019-11-03 | G4: 2020-11-01 | H4: 2021-10-31 | I4: 2022-10-30 | J4: 2023-10-29 | K4: 2024-11-03 | L4: 2025-11-02 | O4: 2024-05-05 | P4: 2024-08-04 | Q4: 2025-02-02 | R4: 2025-05-04 | S4: 2025-08-03 | T4: 2026-02-01 | U4: 2026-05-03 | V4: 2026-08-02
A6: CONTENTS
A7: =HYPERLINK("#'Income Statement'!A13","1. REVENUE") -> 1. REVENUE
A8: =HYPERLINK("#'Income Statement'!A20","2. COST OF REVENUE") -> 2. COST OF REVENUE
A9: =HYPERLINK("#'Income Statement'!A30","3. OPERATING EXPENSES") -> 3. OPERATING EXPENSES
A10: =HYPERLINK("#'Income Statement'!A41","4. NON-OPERATING ITEMS AND TAXES") -> 4. NON-OPERATING ITEMS AND TAXES
A11: =HYPERLINK("#'Income Statement'!A57","5. EPS & SHARE COUNT") -> 5. EPS & SHARE COUNT
A13: 1. REVENUE
A14: Net revenue | C14: 13240 | D14: 17636 | E14: 20848 | F14: 22597 | G14: 23888 | H14: 27450 | I14: 33203 | J14: 35819 | K14: 51574 | L14: 63887 | O14: 12487 | P14: 13072 | Q14: 14916 | R14: 15004 | S14: 15952 | T14: 19311 | U14: 22187 | V14: 29591
A15: YoY Growth | D15: =IF(N(C14)=0,"",D14/C14-1) -> 0.33202417 | E15: =IF(N(D14)=0,"",E14/D14-1) -> 0.18212747 | F15: =IF(N(E14)=0,"",F14/E14-1) -> 0.083892939 | G15: =IF(N(F14)=0,"",G14/F14-1) -> 0.057131478 | H15: =IF(N(G14)=0,"",H14/G14-1) -> 0.14911253 | I15: =IF(N(H14)=0,"",I14/H14-1) -> 0.20958106 | J15: =IF(N(I14)=0,"",J14/I14-1) -> 0.078788061 | K15: =IF(N(J14)=0,"",K14/J14-1) -> 0.43985036 | L15: =IF(N(K14)=0,"",L14/K14-1) -> 0.23874433 | S15: =IF(N(O14)=0,"",S14/O14-1) -> 0.27748859 | T15: =IF(N(P14)=0,"",T14/P14-1) -> 0.47727968 | U15: =IF(N(Q14)=0,"",U14/Q14-1) -> 0.48746313 | V15: =IF(N(R14)=0,"",V14/R14-1) -> 0.97220741
A16: Products revenue | B16: Products/Subscriptions split first disclosed in FY2019 10-K; not presented separately for FY2016-FY2018 in their own filings. SEPARATELY: starting with the FY2026 Q1 10-Q, Broadcom reclassified 'upfront license revenue' from Subscriptions/services into Products (applied retrospectively to that filing's own FY2025 Q1 comparative column only). The 1Q/2Q/3Q FY2025 quarterly columns in this model are each shown on that quarter's OWN as-originally-filed (pre-reclassification) basis, consistent with the own-quarter/no-restatement rule used throughout this workbook — they are therefore NOT directly comparable, line-for-line, to the FY2025 annual column (which uses the FY2025 10-K's post-reclassification presentation) or to the 1Q/2Q FY2026 columns (also post-reclassification). Total revenue is unaffected in all cases — only the Products/Subscriptions split shifts. | F16: 18117 | G16: 17435 | H16: 20886 | I16: 26277 | J16: 27891 | K16: 30359 | L16: 44847 | O16: 7192 | P16: 7439 | Q16: 8171 | R16: 8506 | S16: 9257 | T16: 14130 | U16: 16892 | V16: 24279
A17: Subscriptions and services revenue | F17: 4480 | G17: 6453 | H17: 6564 | I17: 6926 | J17: 7928 | K17: 21215 | L17: 19040 | O17: 5295 | P17: 5633 | Q17: 6745 | R17: 6498 | S17: 6695 | T17: 5181 | U17: 5295 | V17: 5312
A18: Split vs Total Revenue (should be ~0) | F18: =F16+F17-F14 -> 0 | G18: =G16+G17-G14 -> 0 | H18: =H16+H17-H14 -> 0 | I18: =I16+I17-I14 -> 0 | J18: =J16+J17-J14 -> 0 | K18: =K16+K17-K14 -> 0 | L18: =L16+L17-L14 -> 0 | O18: =O16+O17-O14 -> 0 | P18: =P16+P17-P14 -> 0 | Q18: =Q16+Q17-Q14 -> 0 | R18: =R16+R17-R14 -> 0 | S18: =S16+S17-S14 -> 0 | T18: =T16+T17-T14 -> 0 | U18: =U16+U17-U14 -> 0 | V18: =V16+V17-V14 -> 0
A20: 2. COST OF REVENUE
A21: Cost of products sold | C21: 5295 | D21: 6593 | E21: 7021 | F21: 6208 | G21: 5892 | H21: 6555 | I21: 7629 | J21: 8636 | K21: 9797 | L21: 12115 | O21: 2429 | P21: 2434 | Q21: 2693 | R21: 2720 | S21: 3096 | T21: 4041 | U21: 4665 | V21: 6983
A22: Cost of subscriptions and services | F22: 515 | G22: 626 | H22: 607 | I22: 627 | J22: 636 | K22: 2991 | L22: 2371 | O22: 713 | P22: 699 | Q22: 580 | R22: 576 | S22: 608 | T22: 638 | U22: 636 | V22: 641
A23: Purchase accounting effect on inventory | C23: 1185 | D23: 4 | E23: 70
A24: Amortization of acquisition-related intangible assets | C24: 763 | D24: 2511 | E24: 3004 | F24: 3314 | G24: 3819 | H24: 3427 | I24: 2847 | J24: 1853 | K24: 6023 | L24: 6031 | O24: 1516 | P24: 1525 | Q24: 1484 | R24: 1483 | S24: 1519 | T24: 1462 | U24: 1461 | V24: 1499
A25: Restructuring charges | C25: 57 | D25: 19 | E25: 20 | F25: 77 | G25: 35 | H25: 17 | I25: 5 | J25: 4 | K25: 254 | L25: 76 | O25: 53 | P25: 58 | Q25: 14 | R25: 28 | S25: 26 | T25: 13 | U25: 10 | V25: 12
A26: Total cost of revenue | C26: =C21+C22+C23+C24+C25 -> 7300 | D26: =D21+D22+D23+D24+D25 -> 9127 | E26: =E21+E22+E23+E24+E25 -> 10115 | F26: =F21+F22+F23+F24+F25 -> 10114 | G26: =G21+G22+G23+G24+G25 -> 10372 | H26: =H21+H22+H23+H24+H25 -> 10606 | I26: =I21+I22+I23+I24+I25 -> 11108 | J26: =J21+J22+J23+J24+J25 -> 11129 | ... L26: =L21+L22+L23+L24+L25 -> 20593 | O26: =O21+O22+O23+O24+O25 -> 4711 | P26: =P21+P22+P23+P24+P25 -> 4716 | Q26: =Q21+Q22+Q23+Q24+Q25 -> 4771 | R26: =R21+R22+R23+R24+R25 -> 4807 | S26: =S21+S22+S23+S24+S25 -> 5249 | T26: =T21+T22+T23+T24+T25 -> 6154 | U26: =U21+U22+U23+U24+U25 -> 6772 | V26: =V21+V22+V23+V24+V25 -> 9135
A27: Gross margin | C27: =C14-C26 -> 5940 | D27: =D14-D26 -> 8509 | E27: =E14-E26 -> 10733 | F27: =F14-F26 -> 12483 | G27: =G14-G26 -> 13516 | H27: =H14-H26 -> 16844 | I27: =I14-I26 -> 22095 | J27: =J14-J26 -> 24690 | ... L27: =L14-L26 -> 43294 | O27: =O14-O26 -> 7776 | P27: =P14-P26 -> 8356 | Q27: =Q14-Q26 -> 10145 | R27: =R14-R26 -> 10197 | S27: =S14-S26 -> 10703 | T27: =T14-T26 -> 13157 | U27: =U14-U26 -> 15415 | V27: =V14-V26 -> 20456
A28: Gross Margin % | C28: =C27/C14 -> 0.44864048 | D28: =D27/D14 -> 0.48247902 | E28: =E27/E14 -> 0.51482157 | F28: =F27/F14 -> 0.55241846 | G28: =G27/G14 -> 0.5658071 | H28: =H27/H14 -> 0.61362477 | I28: =I27/I14 -> 0.66545192 | J28: =J27/J14 -> 0.68929898 | ... L28: =L27/L14 -> 0.67766525 | O28: =O27/O14 -> 0.62272764 | P28: =P27/P14 -> 0.63922889 | Q28: =Q27/Q14 -> 0.68014213 | R28: =R27/R14 -> 0.67961877 | S28: =S27/S14 -> 0.67095035 | T28: =T27/T14 -> 0.68132153 | U28: =U27/U14 -> 0.69477622 | V28: =V27/V14 -> 0.69129127
A30: 3. OPERATING EXPENSES
A31: Research and development | C31: 2674 | D31: 3292 | E31: 3768 | F31: 4696 | G31: 4968 | H31: 4854 | I31: 4919 | J31: 5253 | K31: 9310 | L31: 10977 | O31: 2415 | P31: 2353 | Q31: 2253 | R31: 2693 | S31: 3050 | T31: 2965 | U31: 2995 | V31: 2895
A32: Selling, general and administrative | C32: 806 | D32: 787 | E32: 1056 | F32: 1709 | G32: 1935 | H32: 1347 | I32: 1382 | J32: 1592 | K32: 4959 | L32: 4211 | O32: 1277 | P32: 1100 | Q32: 949 | R32: 1083 | S32: 1072 | T32: 1019 | U32: 1055 | V32: 996
A33: Amortization of acquisition-related intangible assets | C33: 1873 | D33: 1764 | E33: 541 | F33: 1898 | G33: 2401 | H33: 1976 | I33: 1512 | J33: 1394 | K33: 3244 | L33: 2031 | O33: 827 | P33: 812 | Q33: 511 | R33: 506 | S33: 507 | T33: 507 | U33: 506 | V33: 507
A34: Restructuring, impairment and other charges | C34: 996 | D34: 161 | E34: 219 | F34: 736 | G34: 198 | H34: 148 | I34: 57 | J34: 244 | K34: 1533 | L34: 591 | O34: 292 | P34: 303 | Q34: 172 | R34: 86 | S34: 187 | T34: 103 | U34: 71 | V34: 103
A35: Litigation settlements | D35: 122 | E35: 14
A36: Total operating expenses | C36: =C31+C32+C33+C34+C35 -> 6349 | D36: =D31+D32+D33+D34+D35 -> 6126 | E36: =E31+E32+E33+E34+E35 -> 5598 | F36: =F31+F32+F33+F34+F35 -> 9039 | G36: =G31+G32+G33+G34+G35 -> 9502 | H36: =H31+H32+H33+H34+H35 -> 8325 | I36: =I31+I32+I33+I34+I35 -> 7870 | J36: =J31+J32+J33+J34+J35 -> 8483 | ... L36: =L31+L32+L33+L34+L35 -> 17810 | O36: =O31+O32+O33+O34+O35 -> 4811 | P36: =P31+P32+P33+P34+P35 -> 4568 | Q36: =Q31+Q32+Q33+Q34+Q35 -> 3885 | R36: =R31+R32+R33+R34+R35 -> 4368 | S36: =S31+S32+S33+S34+S35 -> 4816 | T36: =T31+T32+T33+T34+T35 -> 4594 | U36: =U31+U32+U33+U34+U35 -> 4627 | V36: =V31+V32+V33+V34+V35 -> 4501
A37: Operating income (loss) | C37: =C27-C36 -> -409 | D37: =D27-D36 -> 2383 | E37: =E27-E36 -> 5135 | F37: =F27-F36 -> 3444 | G37: =G27-G36 -> 4014 | H37: =H27-H36 -> 8519 | I37: =I27-I36 -> 14225 | J37: =J27-J36 -> 16207 | ... L37: =L27-L36 -> 25484 | O37: =O27-O36 -> 2965 | P37: =P27-P36 -> 3788 | Q37: =Q27-Q36 -> 6260 | R37: =R27-R36 -> 5829 | S37: =S27-S36 -> 5887 | T37: =T27-T36 -> 8563 | U37: =U27-U36 -> 10788 | V37: =V27-V36 -> 15955
A38: Operating Margin % | C38: =C37/C14 -> -0.030891239 | D38: =D37/D14 -> 0.13512134 | E38: =E37/E14 -> 0.2463066 | F38: =F37/F14 -> 0.15240961 | G38: =G37/G14 -> 0.16803416 | H38: =H37/H14 -> 0.31034608 | I38: =I37/I14 -> 0.42842514 | J38: =J37/J14 -> 0.45246936 | ... L38: =L37/L14 -> 0.39889179 | O38: =O37/O14 -> 0.23744694 | P38: =P37/P14 -> 0.28977968 | Q38: =Q37/Q14 -> 0.41968356 | R38: =R37/R14 -> 0.3884964 | S38: =S37/S14 -> 0.36904463 | T38: =T37/T14 -> 0.44342603 | U38: =U37/U14 -> 0.48623068 | V38: =V37/V14 -> 0.53918421
A39: YoY Growth | D39: =IF(N(C37)=0,"",D37/C37-1) -> -6.8264059 | E39: =IF(N(D37)=0,"",E37/D37-1) -> 1.1548468 | F39: =IF(N(E37)=0,"",F37/E37-1) -> -0.32930867 | G39: =IF(N(F37)=0,"",G37/F37-1) -> 0.16550523 | H39: =IF(N(G37)=0,"",H37/G37-1) -> 1.1223219 | I39: =IF(N(H37)=0,"",I37/H37-1) -> 0.66979692 | J39: =IF(N(I37)=0,"",J37/I37-1) -> 0.13933216 | K39: =IF(N(J37)=0,"",K37/J37-1) -> -0.16930956 | L39: =IF(N(K37)=0,"",L37/K37-1) -> 0.89289163 | S39: =IF(N(O37)=0,"",S37/O37-1) -> 0.98549747 | T39: =IF(N(P37)=0,"",T37/P37-1) -> 1.2605597 | U39: =IF(N(Q37)=0,"",U37/Q37-1) -> 0.72332268 | V39: =IF(N(R37)=0,"",V37/R37-1) -> 1.7371762
A41: 4. NON-OPERATING ITEMS AND TAXES
A42: Interest expense | C42: -585 | D42: -454 | E42: -628 | F42: -1444 | G42: -1777 | H42: -1885 | I42: -1737 | J42: -1622 | K42: -3953 | L42: -3210 | O42: -1047 | P42: -1064 | Q42: -873 | R42: -769 | S42: -807 | T42: -801 | U42: -776 | V42: -778
A43: Loss on extinguishment of debt | B43: Not broken out separately on the IS face after FY2017; folded into Other income (expense), net in later years (see CF addback for later years' non-cash portion). | C43: -123 | D43: -166
A44: Impairment on investment | E44: -106
A45: Other income (expense), net | C45: 10 | D45: 62 | E45: 144 | F45: 226 | G45: 206 | H45: 131 | I45: -54 | J45: 512 | K45: 406 | L45: 455 | O45: 87 | P45: 82 | Q45: 103 | R45: 25 | S45: 205 | T45: 433 | U45: 118 | V45: 98
A46: Income from continuing operations before income taxes | C46: =C37+C42+C43+C44+C45 -> -1107 | D46: =D37+D42+D43+D44+D45 -> 1825 | E46: =E37+E42+E43+E44+E45 -> 4545 | F46: =F37+F42+F43+F44+F45 -> 2226 | G46: =G37+G42+G43+G44+G45 -> 2443 | H46: =H37+H42+H43+H44+H45 -> 6765 | I46: =I37+I42+I43+I44+I45 -> 12434 | J46: =J37+J42+J43+J44+J45 -> 15097 | ... L46: =L37+L42+L43+L44+L45 -> 22729 | O46: =O37+O42+O43+O44+O45 -> 2005 | P46: =P37+P42+P43+P44+P45 -> 2806 | Q46: =Q37+Q42+Q43+Q44+Q45 -> 5490 | R46: =R37+R42+R43+R44+R45 -> 5085 | S46: =S37+S42+S43+S44+S45 -> 5285 | T46: =T37+T42+T43+T44+T45 -> 8195 | U46: =U37+U42+U43+U44+U45 -> 10130 | V46: =V37+V42+V43+V44+V45 -> 15275
A47: Provision for (benefit from) income taxes | C47: 642 | D47: 35 | E47: -8084 | F47: -510 | G47: -518 | H47: 29 | I47: 939 | J47: 1015 | K47: 3748 | L47: -397 | O47: -116 | P47: 4238 | Q47: -13 | R47: 120 | S47: 1145 | T47: 846 | U47: 820 | V47: 2187
A48: Income from continuing operations | C48: =C46-C47 -> -1749 | D48: =D46-D47 -> 1790 | E48: =E46-E47 -> 12629 | F48: =F46-F47 -> 2736 | G48: =G46-G47 -> 2961 | H48: =H46-H47 -> 6736 | I48: =I46-I47 -> 11495 | J48: =J46-J47 -> 14082 | ... L48: =L46-L47 -> 23126 | O48: =O46-O47 -> 2121 | P48: =P46-P47 -> -1432 | Q48: =Q46-Q47 -> 5503 | R48: =R46-R47 -> 4965 | S48: =S46-S47 -> 4140 | T48: =T46-T47 -> 7349 | U48: =U46-U47 -> 9310 | V48: =V46-V47 -> 13088
A49: Loss from discontinued operations, net of income taxes | B49: FY2024: $(273)M — EUC business (part of VMware) sold to KKR for $3.5B, July 1, 2024. Not restated into other years since EUC was only acquired as part of VMware at the start of FY2024. | C49: -112 | D49: -6 | E49: -19 | F49: -12 | G49: -1 | K49: -273 | P49: -443
A50: Net income (loss) | C50: =C48+C49 -> -1861 | D50: =D48+D49 -> 1784 | E50: =E48+E49 -> 12610 | F50: =F48+F49 -> 2724 | G50: =G48+G49 -> 2960 | H50: =H48+H49 -> 6736 | I50: =I48+I49 -> 11495 | J50: =J48+J49 -> 14082 | ... L50: =L48+L49 -> 23126 | O50: =O48+O49 -> 2121 | P50: =P48+P49 -> -1875 | Q50: =Q48+Q49 -> 5503 | R50: =R48+R49 -> 4965 | S50: =S48+S49 -> 4140 | T50: =T48+T49 -> 7349 | U50: =U48+U49 -> 9310 | V50: =V48+V49 -> 13088
A51: Net Margin % | C51: =C50/C14 -> -0.14055891 | D51: =D50/D14 -> 0.10115672 | E51: =E50/E14 -> 0.60485418 | F51: =F50/F14 -> 0.12054698 | G51: =G50/G14 -> 0.12391159 | H51: =H50/H14 -> 0.24539162 | I51: =I50/I14 -> 0.34620366 | J51: =J50/J14 -> 0.3931433 | ... L51: =L50/L14 -> 0.36198288 | O51: =O50/O14 -> 0.16985665 | P51: =P50/P14 -> -0.14343635 | Q51: =Q50/Q14 -> 0.36893269 | R51: =R50/R14 -> 0.33091176 | S51: =S50/S14 -> 0.25952859 | T51: =T50/T14 -> 0.3805603 | U51: =U50/U14 -> 0.41961509 | V51: =V50/V14 -> 0.44229664
A52: YoY Growth | D52: =IF(N(C50)=0,"",D50/C50-1) -> -1.9586244 | E52: =IF(N(D50)=0,"",E50/D50-1) -> 6.0683857 | F52: =IF(N(E50)=0,"",F50/E50-1) -> -0.78398097 | G52: =IF(N(F50)=0,"",G50/F50-1) -> 0.086637298 | H52: =IF(N(G50)=0,"",H50/G50-1) -> 1.2756757 | I52: =IF(N(H50)=0,"",I50/H50-1) -> 0.70650238 | J52: =IF(N(I50)=0,"",J50/I50-1) -> 0.22505437 | K52: =IF(N(J50)=0,"",K50/J50-1) -> -0.58138049 | L52: =IF(N(K50)=0,"",L50/K50-1) -> 2.9229856 | S52: =IF(N(O50)=0,"",S50/O50-1) -> 0.95190948 | T52: =IF(N(P50)=0,"",T50/P50-1) -> -4.9194667 | U52: =IF(N(Q50)=0,"",U50/Q50-1) -> 0.69180447 | V52: =IF(N(R50)=0,"",V50/R50-1) -> 1.6360524
A53: Less: Net (income) loss attributable to noncontrolling interest | B53: NCI relates to exchangeable LP units outstanding prior to the April 2018 redomiciliation; eliminated from FY2018 onward. | C53: -122 | D53: 92 | E53: 351
A54: Less: Dividends on preferred stock | B54: 8.00% Mandatory Convertible Preferred Stock, Series A, issued FY2019, fully converted during FY2022. | F54: 29 | G54: 297 | H54: 299 | I54: 272
A55: Net income (loss) attributable to common stock | C55: =C50-C53-C54 -> -1739 | D55: =D50-D53-D54 -> 1692 | E55: =E50-E53-E54 -> 12259 | F55: =F50-F53-F54 -> 2695 | G55: =G50-G53-G54 -> 2663 | H55: =H50-H53-H54 -> 6437 | I55: =I50-I53-I54 -> 11223 | J55: =J50-J53-J54 -> 14082 | ... L55: =L50-L53-L54 -> 23126 | O55: =O50-O53-O54 -> 2121 | P55: =P50-P53-P54 -> -1875 | Q55: =Q50-Q53-Q54 -> 5503 | R55: =R50-R53-R54 -> 4965 | S55: =S50-S53-S54 -> 4140 | T55: =T50-T53-T54 -> 7349 | U55: =U50-U53-U54 -> 9310 | V55: =V50-V53-V54 -> 13088
A57: 5. EPS & SHARE COUNT
A58: Basic EPS | B58: IS quarterly columns are single-quarter (3-month) figures, not YTD. 2Q FY2024: Broadcom's 10-Q for the quarter ended May 5, 2024 reports EPS/share counts on a PRE-split basis ($4.56 basic / $4.42 diluted; the 10-for-1 forward stock split completed July 12, 2024, after this quarter-end). For comparability with every other period in this model (all of which are post-split), this model uses the filing's own unaudited pro forma POST-split disclosure (Note 13: $0.46 basic / $0.44 diluted; WASO 4,650 / 4,800). 3Q FY2024 onward is already reported post-split on the face of the financial statements. | C58: -4.75 | D58: 4.18 | E58: 29.33 | F58: 6.77 | G58: 6.62 | H58: 15.7 | I58: 27.44 | J58: 33.93 | K58: 1.27 | L58: 4.91 | O58: 0.46 | P58: -0.4 | Q58: 1.17 | R58: 1.05 | S58: 0.88 | T58: 1.55 | U58: 1.96 | V58: 2.75
A59: Diluted EPS | C59: -4.86 | D59: 4.02 | E59: 28.44 | F59: 6.43 | G59: 6.33 | H59: 15 | I59: 26.53 | J59: 32.98 | K59: 1.23 | L59: 4.77 | O59: 0.44 | P59: -0.4 | Q59: 1.14 | R59: 1.03 | S59: 0.85 | T59: 1.5 | U59: 1.91 | V59: 2.68
A60: YoY Growth (Diluted) | D60: =IF(N(C59)=0,"",D59/C59-1) -> -1.8271605 | E60: =IF(N(D59)=0,"",E59/D59-1) -> 6.0746269 | F60: =IF(N(E59)=0,"",F59/E59-1) -> -0.77390999 | G60: =IF(N(F59)=0,"",G59/F59-1) -> -0.0155521 | H60: =IF(N(G59)=0,"",H59/G59-1) -> 1.3696682 | I60: =IF(N(H59)=0,"",I59/H59-1) -> 0.76866667 | J60: =IF(N(I59)=0,"",J59/I59-1) -> 0.243121 | K60: =IF(N(J59)=0,"",K59/J59-1) -> -0.96270467 | L60: =IF(N(K59)=0,"",L59/K59-1) -> 2.8780488 | S60: =IF(N(O59)=0,"",S59/O59-1) -> 0.93181818 | T60: =IF(N(P59)=0,"",T59/P59-1) -> -4.75 | U60: =IF(N(Q59)=0,"",U59/Q59-1) -> 0.6754386 | V60: =IF(N(R59)=0,"",V59/R59-1) -> 1.6019417
A61: Weighted avg shares — Basic | C61: 366 | D61: 405 | E61: 418 | F61: 398 | G61: 402 | H61: 410 | I61: 409 | J61: 415 | K61: 4624 | L61: 4712 | O61: 4650 | P61: 4663 | Q61: 4695 | R61: 4707 | S61: 4714 | T61: 4741 | U61: 4747 | V61: 4766
A62: Weighted avg shares — Diluted | C62: 383 | D62: 421 | E62: 431 | F62: 419 | G62: 421 | H62: 429 | I62: 423 | J62: 427 | K62: 4778 | L62: 4853 | O62: 4800 | P62: 4663 | Q62: 4836 | R62: 4826 | S62: 4860 | T62: 4888 | U62: 4876 | V62: 4887

Sheet Balance Sheet
A1: Broadcom Inc. — Balance Sheet
A2: $ in millions except per-share data | USD | as of 2026-09-22
C3: FY2016 | D3: FY2017 | E3: FY2018 | F3: FY2019 | G3: FY2020 | H3: FY2021 | I3: FY2022 | J3: FY2023 | K3: FY2024 | L3: FY2025 | M3: · | N3: · | O3: 2Q FY2024 | P3: 3Q FY2024 | Q3: 1Q FY2025 | R3: 2Q FY2025 | S3: 3Q FY2025 | T3: 1Q FY2026 | U3: 2Q FY2026 | V3: 3Q FY2026
C4: 2016-10-30 | D4: 2017-10-29 | E4: 2018-11-04 | F4: 2019-11-03 | G4: 2020-11-01 | H4: 2021-10-31 | I4: 2022-10-30 | J4: 2023-10-29 | K4: 2024-11-03 | L4: 2025-11-02 | O4: 2024-05-05 | P4: 2024-08-04 | Q4: 2025-02-02 | R4: 2025-05-04 | S4: 2025-08-03 | T4: 2026-02-01 | U4: 2026-05-03 | V4: 2026-08-02
A6: CONTENTS
A7: =HYPERLINK("#'Balance Sheet'!A14","1. CURRENT ASSETS") -> 1. CURRENT ASSETS
A8: =HYPERLINK("#'Balance Sheet'!A21","2. LONG-TERM ASSETS") -> 2. LONG-TERM ASSETS
A9: =HYPERLINK("#'Balance Sheet'!A28","3. CURRENT LIABILITIES") -> 3. CURRENT LIABILITIES
A10: =HYPERLINK("#'Balance Sheet'!A35","4. LONG-TERM LIABILITIES") -> 4. LONG-TERM LIABILITIES
A11: =HYPERLINK("#'Balance Sheet'!A41","5. MEZZANINE AND EQUITY") -> 5. MEZZANINE AND EQUITY
A12: =HYPERLINK("#'Balance Sheet'!A51","6. WORKING CAPITAL ANALYTICS") -> 6. WORKING CAPITAL ANALYTICS
A14: 1. CURRENT ASSETS
A15: Cash and cash equivalents | C15: 3097 | D15: 11204 | E15: 4292 | F15: 5055 | G15: 7618 | H15: 12163 | I15: 12416 | J15: 14189 | K15: 9348 | L15: 16178 | O15: 9809 | P15: 9952 | Q15: 9307 | R15: 9472 | S15: 10718 | T15: 14174 | U15: 19628 | V15: 23975
A16: Trade accounts receivable, net | C16: 2181 | D16: 2448 | E16: 3325 | F16: 3259 | G16: 2297 | H16: 2071 | I16: 2958 | J16: 3154 | K16: 4416 | L16: 7145 | O16: 5500 | P16: 4665 | Q16: 4955 | R16: 5563 | S16: 6494 | T16: 8460 | U16: 10830 | V16: 13707
A17: Inventory | C17: 1400 | D17: 1447 | E17: 1124 | F17: 874 | G17: 1003 | H17: 1297 | I17: 1925 | J17: 1898 | K17: 1760 | L17: 2270 | O17: 1842 | P17: 1894 | Q17: 1908 | R17: 2017 | S17: 2180 | T17: 2962 | U17: 4328 | V17: 4523
A18: Other current assets | C18: 447 | D18: 724 | E18: 366 | F18: 729 | G18: 977 | H18: 1055 | I18: 1205 | J18: 1606 | K18: 4071 | L18: 5980 | O18: 8151 | P18: 3436 | Q18: 4820 | R18: 5129 | S18: 5606 | T18: 6466 | U18: 7427 | V18: 9968
A19: Total current assets | C19: =C15+C16+C17+C18 -> 7125 | D19: =D15+D16+D17+D18 -> 15823 | E19: =E15+E16+E17+E18 -> 9107 | F19: =F15+F16+F17+F18 -> 9917 | G19: =G15+G16+G17+G18 -> 11895 | H19: =H15+H16+H17+H18 -> 16586 | I19: =I15+I16+I17+I18 -> 18504 | J19: =J15+J16+J17+J18 -> 20847 | ... L19: =L15+L16+L17+L18 -> 31573 | O19: =O15+O16+O17+O18 -> 25302 | P19: =P15+P16+P17+P18 -> 19947 | Q19: =Q15+Q16+Q17+Q18 -> 20990 | R19: =R15+R16+R17+R18 -> 22181 | S19: =S15+S16+S17+S18 -> 24998 | T19: =T15+T16+T17+T18 -> 32062 | U19: =U15+U16+U17+U18 -> 42213 | V19: =V15+V16+V17+V18 -> 52173
A21: 2. LONG-TERM ASSETS
A22: Property, plant and equipment, net | C22: 2509 | D22: 2599 | E22: 2635 | F22: 2565 | G22: 2509 | H22: 2348 | I22: 2223 | J22: 2154 | K22: 2521 | L22: 2530 | O22: 2668 | P22: 2602 | Q22: 2465 | R22: 2462 | S22: 2451 | T22: 2599 | U22: 2788 | V22: 3144
A23: Goodwill | C23: 24732 | D23: 24706 | E23: 26913 | F23: 36714 | G23: 43447 | H23: 43450 | I23: 43614 | J23: 43653 | K23: 97873 | L23: 97801 | O23: 97873 | P23: 97873 | Q23: 97871 | R23: 97801 | S23: 97801 | T23: 97801 | U23: 97801 | V23: 97801
A24: Intangible assets, net | C24: 15068 | D24: 10832 | E24: 10762 | F24: 17554 | G24: 16782 | H24: 11374 | I24: 7111 | J24: 3867 | K24: 40583 | L24: 32273 | O24: 45407 | P24: 43034 | Q24: 38583 | R24: 36393 | S24: 34344 | T24: 30302 | U24: 28333 | V24: 26325
A25: Other long-term assets | C25: 532 | D25: 458 | E25: 707 | F25: 743 | G25: 1300 | H25: 1812 | I25: 1797 | J25: 2340 | K25: 5073 | L25: 6915 | O25: 3961 | P25: 4510 | Q25: 5449 | R25: 5793 | S25: 6027 | T25: 7139 | U25: 8023 | V25: 8705
A26: Total assets | C26: =C19+C22+C23+C24+C25 -> 49966 | D26: =D19+D22+D23+D24+D25 -> 54418 | E26: =E19+E22+E23+E24+E25 -> 50124 | F26: =F19+F22+F23+F24+F25 -> 67493 | G26: =G19+G22+G23+G24+G25 -> 75933 | H26: =H19+H22+H23+H24+H25 -> 75570 | I26: =I19+I22+I23+I24+I25 -> 73249 | J26: =J19+J22+J23+J24+J25 -> 72861 | ... L26: =L19+L22+L23+L24+L25 -> 171092 | O26: =O19+O22+O23+O24+O25 -> 175211 | P26: =P19+P22+P23+P24+P25 -> 167966 | Q26: =Q19+Q22+Q23+Q24+Q25 -> 165358 | R26: =R19+R22+R23+R24+R25 -> 164630 | S26: =S19+S22+S23+S24+S25 -> 165621 | T26: =T19+T22+T23+T24+T25 -> 169903 | U26: =U19+U22+U23+U24+U25 -> 179158 | V26: =V19+V22+V23+V24+V25 -> 188148
A28: 3. CURRENT LIABILITIES
A29: Accounts payable | C29: 1261 | D29: 1105 | E29: 811 | F29: 855 | G29: 836 | H29: 1086 | I29: 998 | J29: 1210 | K29: 1662 | L29: 1560 | O29: 1441 | P29: 1757 | Q29: 1905 | R29: 1297 | S29: 1432 | T29: 2112 | U29: 2337 | V29: 4000
A30: Employee compensation and benefits | C30: 517 | D30: 626 | E30: 715 | F30: 641 | G30: 877 | H30: 1066 | I30: 1202 | J30: 935 | K30: 1971 | L30: 2129 | O30: 1385 | P30: 1725 | Q30: 922 | R30: 1266 | S30: 1719 | T30: 864 | U30: 1134 | V30: 1506
A31: Current portion of long-term debt / short-term debt | C31: 454 | D31: 117 | F31: 2787 | G31: 827 | H31: 290 | I31: 440 | J31: 1608 | K31: 1271 | L31: 3152 | O31: 2426 | P31: 3161 | Q31: 5653 | R31: 5531 | S31: 1399 | T31: 2252 | U31: 2252 | V31: 2252
A32: Other current liabilities | C32: 846 | D32: 681 | E32: 812 | F32: 2616 | G32: 3831 | H32: 3839 | I32: 4412 | J32: 3652 | K32: 11793 | L32: 11673 | O32: 14919 | P32: 12578 | Q32: 12430 | R32: 12503 | S32: 12154 | T32: 11631 | U32: 13139 | V32: 13080
A33: Total current liabilities | C33: =C29+C30+C31+C32 -> 3078 | D33: =D29+D30+D31+D32 -> 2529 | E33: =E29+E30+E31+E32 -> 2338 | F33: =F29+F30+F31+F32 -> 6899 | G33: =G29+G30+G31+G32 -> 6371 | H33: =H29+H30+H31+H32 -> 6281 | I33: =I29+I30+I31+I32 -> 7052 | J33: =J29+J30+J31+J32 -> 7405 | ... L33: =L29+L30+L31+L32 -> 18514 | O33: =O29+O30+O31+O32 -> 20171 | P33: =P29+P30+P31+P32 -> 19221 | Q33: =Q29+Q30+Q31+Q32 -> 20910 | R33: =R29+R30+R31+R32 -> 20597 | S33: =S29+S30+S31+S32 -> 16704 | T33: =T29+T30+T31+T32 -> 16859 | U33: =U29+U30+U31+U32 -> 18862 | V33: =V29+V30+V31+V32 -> 20838
A35: 4. LONG-TERM LIABILITIES
A36: Long-term debt | C36: 13188 | D36: 17431 | E36: 17493 | F36: 30011 | G36: 40235 | H36: 39440 | I36: 39075 | J36: 37621 | K36: 66295 | L36: 61984 | O36: 71590 | P36: 66798 | Q36: 60926 | R36: 61751 | S36: 62830 | T36: 63805 | U36: 62655 | V36: 57167
A37: Pension and postretirement obligations | B37: Separately disclosed only in FY2016-FY2017; folded into Other long-term liabilities thereafter. | C37: 531 | D37: 112
A38: Other long-term liabilities | C38: 11293 | D38: 11160 | E38: 3636 | F38: 5613 | G38: 5426 | H38: 4860 | I38: 4413 | J38: 3847 | K38: 14975 | L38: 9302 | O38: 13489 | P38: 16296 | Q38: 13733 | R38: 12696 | S38: 12810 | T38: 9367 | U38: 9950 | V38: 10453
A39: Total liabilities | C39: =C33+C36+C37+C38 -> 28090 | D39: =D33+D36+D37+D38 -> 31232 | E39: =E33+E36+E37+E38 -> 23467 | F39: =F33+F36+F37+F38 -> 42523 | G39: =G33+G36+G37+G38 -> 52032 | H39: =H33+H36+H37+H38 -> 50581 | I39: =I33+I36+I37+I38 -> 50540 | J39: =J33+J36+J37+J38 -> 48873 | ... L39: =L33+L36+L37+L38 -> 89800 | O39: =O33+O36+O37+O38 -> 105250 | P39: =P33+P36+P37+P38 -> 102315 | Q39: =Q33+Q36+Q37+Q38 -> 95569 | R39: =R33+R36+R37+R38 -> 95044 | S39: =S33+S36+S37+S38 -> 92344 | T39: =T33+T36+T37+T38 -> 90031 | U39: =U33+U36+U37+U38 -> 91467 | V39: =V33+V36+V37+V38 -> 88458
A41: 5. MEZZANINE AND EQUITY
A42: Preferred stock dividend obligation (mezzanine) | B42: 8.00% Mandatory Convertible Preferred Stock, Series A — issued FY2019, fully converted FY2022. | F42: 29 | G42: 27 | H42: 27
A43: Common stock and additional paid-in capital | C43: 19241 | D43: 20505 | E43: 23285 | F43: 25081 | G43: 23982 | H43: 24330 | I43: 21159 | J43: 21099 | K43: 67471 | L43: 71313 | O43: 69754 | P43: 67318 | Q43: 66853 | R43: 66694 | S43: 69016 | T43: 73140 | U43: 75317 | V43: 77335
A44: Retained earnings (accumulated deficit) | C44: -215 | D44: -129 | E44: 3487 | F44: 0 | G44: 0 | H44: 748 | I44: 1604 | J44: 2682 | K44: 0 | L44: 9761 | O44: 0 | P44: -1875 | Q44: 2729 | R44: 2686 | S44: 4040 | T44: 6520 | U44: 12166 | V44: 22151
A45: Accumulated other comprehensive income (loss) | C45: -134 | D45: -91 | E45: -115 | F45: -140 | G45: -108 | H45: -116 | I45: -54 | J45: 207 | K45: 207 | L45: 218 | O45: 207 | P45: 208 | Q45: 207 | R45: 206 | S45: 221 | T45: 212 | U45: 208 | V45: 204
A46: Total Broadcom stockholders' equity | C46: =C43+C44+C45 -> 18892 | D46: =D43+D44+D45 -> 20285 | E46: =E43+E44+E45 -> 26657 | F46: =F43+F44+F45 -> 24941 | G46: =G43+G44+G45 -> 23874 | H46: =H43+H44+H45 -> 24962 | I46: =I43+I44+I45 -> 22709 | J46: =J43+J44+J45 -> 23988 | ... L46: =L43+L44+L45 -> 81292 | O46: =O43+O44+O45 -> 69961 | P46: =P43+P44+P45 -> 65651 | Q46: =Q43+Q44+Q45 -> 69789 | R46: =R43+R44+R45 -> 69586 | S46: =S43+S44+S45 -> 73277 | T46: =T43+T44+T45 -> 79872 | U46: =U43+U44+U45 -> 87691 | V46: =V43+V44+V45 -> 99690
A47: Noncontrolling interest | B47: Eliminated FY2018 via exchange of exchangeable LP units for common stock at the redomiciliation. | C47: 2984 | D47: 2901
A48: Total equity | C48: =C46+C47 -> 21876 | D48: =D46+D47 -> 23186 | E48: =E46+E47 -> 26657 | F48: =F46+F47 -> 24941 | G48: =G46+G47 -> 23874 | H48: =H46+H47 -> 24962 | I48: =I46+I47 -> 22709 | J48: =J46+J47 -> 23988 | ... L48: =L46+L47 -> 81292 | O48: =O46+O47 -> 69961 | P48: =P46+P47 -> 65651 | Q48: =Q46+Q47 -> 69789 | R48: =R46+R47 -> 69586 | S48: =S46+S47 -> 73277 | T48: =T46+T47 -> 79872 | U48: =U46+U47 -> 87691 | V48: =V46+V47 -> 99690
A49: Balance Check: Assets - Liabilities - Mezzanine - Equity (should be ~0) | C49: =C26-C39-C42-C48 -> 0 | D49: =D26-D39-D42-D48 -> 0 | E49: =E26-E39-E42-E48 -> 0 | F49: =F26-F39-F42-F48 -> 0 | G49: =G26-G39-G42-G48 -> 0 | H49: =H26-H39-H42-H48 -> 0 | I49: =I26-I39-I42-I48 -> 0 | J49: =J26-J39-J42-J48 -> 0 | ... L49: =L26-L39-L42-L48 -> 0 | O49: =O26-O39-O42-O48 -> 0 | P49: =P26-P39-P42-P48 -> 0 | Q49: =Q26-Q39-Q42-Q48 -> 0 | R49: =R26-R39-R42-R48 -> 0 | S49: =S26-S39-S42-S48 -> 0 | T49: =T26-T39-T42-T48 -> 0 | U49: =U26-U39-U42-U48 -> 0 | V49: =V26-V39-V42-V48 -> 0
A51: 6. WORKING CAPITAL ANALYTICS
A52: Days Sales Outstanding | C52: =C16/'Income Statement'!C14*365 -> 60.125755 | D52: =D16/'Income Statement'!D14*365 -> 50.66455 | E52: =E16/'Income Statement'!E14*365 -> 58.213018 | F52: =F16/'Income Statement'!F14*365 -> 52.64128 | G52: =G16/'Income Statement'!G14*365 -> 35.097329 | H52: =H16/'Income Statement'!H14*365 -> 27.537887 | I52: =I16/'Income Statement'!I14*365 -> 32.517242 | J52: =J16/'Income Statement'!J14*365 -> 32.139647 | ... L52: =L16/'Income Statement'!L14*365 -> 40.820903 | O52: =O16/'Income Statement'!O14*91 -> 40.081685 | P52: =P16/'Income Statement'!P14*91 -> 32.475138 | Q52: =Q16/'Income Statement'!Q14*91 -> 30.229619 | R52: =R16/'Income Statement'!R14*91 -> 33.739869 | S52: =S16/'Income Statement'!S14*91 -> 37.045762 | T52: =T16/'Income Statement'!T14*91 -> 39.866397 | U52: =U16/'Income Statement'!U14*91 -> 44.419255 | V52: =V16/'Income Statement'!V14*91 -> 42.15258
A53: Days Inventory Outstanding | C53: =C17/'Income Statement'!C26*365 -> 70 | D53: =D17/'Income Statement'!D26*365 -> 57.867317 | E53: =E17/'Income Statement'!E26*365 -> 40.559565 | F53: =F17/'Income Statement'!F26*365 -> 31.541428 | G53: =G17/'Income Statement'!G26*365 -> 35.296471 | H53: =H17/'Income Statement'!H26*365 -> 44.635584 | I53: =I17/'Income Statement'!I26*365 -> 63.253961 | J53: =J17/'Income Statement'!J26*365 -> 62.249079 | ... L53: =L17/'Income Statement'!L26*365 -> 40.234546 | O53: =O17/'Income Statement'!O26*91 -> 35.580981 | P53: =P17/'Income Statement'!P26*91 -> 36.54665 | Q53: =Q17/'Income Statement'!Q26*91 -> 36.392371 | R53: =R17/'Income Statement'!R26*91 -> 38.183274 | S53: =S17/'Income Statement'!S26*91 -> 37.793865 | T53: =T17/'Income Statement'!T26*91 -> 43.79948 | U53: =U17/'Income Statement'!U26*91 -> 58.158299 | V53: =V17/'Income Statement'!V26*91 -> 45.056705
A54: Days Payable Outstanding | C54: =C29/'Income Statement'!C26*365 -> 63.05 | D54: =D29/'Income Statement'!D26*365 -> 44.190314 | E54: =E29/'Income Statement'!E26*365 -> 29.264953 | F54: =F29/'Income Statement'!F26*365 -> 30.855745 | G54: =G29/'Income Statement'!G26*365 -> 29.419591 | H54: =H29/'Income Statement'!H26*365 -> 37.374128 | I54: =I29/'Income Statement'!I26*365 -> 32.793482 | J54: =J29/'Income Statement'!J26*365 -> 39.684608 | ... L54: =L29/'Income Statement'!L26*365 -> 27.650172 | O54: =O29/'Income Statement'!O26*91 -> 27.835067 | P54: =P29/'Income Statement'!P26*91 -> 33.903096 | Q54: =Q29/'Income Statement'!Q26*91 -> 36.33515 | R54: =R29/'Income Statement'!R26*91 -> 24.553152 | S54: =S29/'Income Statement'!S26*91 -> 24.826062 | T54: =T29/'Income Statement'!T26*91 -> 31.230419 | U54: =U29/'Income Statement'!U26*91 -> 31.403869 | V54: =V29/'Income Statement'!V26*91 -> 39.846743
A55: Cash Conversion Cycle | C55: =C52+C53-C54 -> 67.075755 | D55: =D52+D53-D54 -> 64.341552 | E55: =E52+E53-E54 -> 69.50763 | F55: =F52+F53-F54 -> 53.326963 | G55: =G52+G53-G54 -> 40.974209 | H55: =H52+H53-H54 -> 34.799343 | I55: =I52+I53-I54 -> 62.977721 | J55: =J52+J53-J54 -> 54.704118 | ... L55: =L52+L53-L54 -> 53.405276 | O55: =O52+O53-O54 -> 47.827599 | P55: =P52+P53-P54 -> 35.118692 | Q55: =Q52+Q53-Q54 -> 30.28684 | R55: =R52+R53-R54 -> 47.369992 | S55: =S52+S53-S54 -> 50.013566 | T55: =T52+T53-T54 -> 52.435458 | U55: =U52+U53-U54 -> 71.173685 | V55: =V52+V53-V54 -> 47.362542

Sheet Cash Flow Statement
A1: Broadcom Inc. — Cash Flow Statement
A2: $ in millions except per-share data | USD | as of 2026-09-22
C3: FY2016 | D3: FY2017 | E3: FY2018 | F3: FY2019 | G3: FY2020 | H3: FY2021 | I3: FY2022 | J3: FY2023 | K3: FY2024 | L3: FY2025 | M3: · | N3: · | O3: 2Q FY2024 | P3: 3Q FY2024 | Q3: 1Q FY2025 | R3: 2Q FY2025 | S3: 3Q FY2025 | T3: 1Q FY2026 | U3: 2Q FY2026 | V3: 3Q FY2026
C4: 2016-10-30 | D4: 2017-10-29 | E4: 2018-11-04 | F4: 2019-11-03 | G4: 2020-11-01 | H4: 2021-10-31 | I4: 2022-10-30 | J4: 2023-10-29 | K4: 2024-11-03 | L4: 2025-11-02 | O4: 2024-05-05 | P4: 2024-08-04 | Q4: 2025-02-02 | R4: 2025-05-04 | S4: 2025-08-03 | T4: 2026-02-01 | U4: 2026-05-03 | V4: 2026-08-02
A6: CONTENTS
A7: =HYPERLINK("#'Cash Flow Statement'!A13","1. OPERATING ACTIVITIES") -> 1. OPERATING ACTIVITIES
A8: =HYPERLINK("#'Cash Flow Statement'!A35","2. INVESTING ACTIVITIES") -> 2. INVESTING ACTIVITIES
A9: =HYPERLINK("#'Cash Flow Statement'!A45","3. FINANCING ACTIVITIES") -> 3. FINANCING ACTIVITIES
A10: =HYPERLINK("#'Cash Flow Statement'!A61","4. NET CHANGE IN CASH") -> 4. NET CHANGE IN CASH
A11: =HYPERLINK("#'Cash Flow Statement'!A67","5. FREE CASH FLOW ANALYTICS") -> 5. FREE CASH FLOW ANALYTICS
A13: 1. OPERATING ACTIVITIES
A14: Net income (loss) | B14: All quarterly columns are cumulative fiscal-year-to-date figures exactly as filed in each quarter's own 10-Q (1Q columns = single quarter, since Q1 YTD = Q1 alone; 2Q columns = 6-month YTD; 3Q columns = 9-month YTD) — Broadcom's 10-Qs do not present a discrete single-quarter cash flow statement. All other CF quarterly-column figures below are likewise fiscal-YTD, consistent with this line. (IS and SEG quarterly columns, by contrast, are single-quarter, not YTD — see IS note.) | C14: -1861 | D14: 1784 | E14: 12610 | F14: 2724 | G14: 2960 | H14: 6736 | I14: 11495 | J14: 14082 | K14: 5895 | L14: 23126 | O14: 3446 | P14: 1571 | Q14: 5503 | R14: 10468 | S14: 14608 | T14: 7349 | U14: 16659 | V14: 29747
A15: Ties to IS Net Income (annual only, should be ~0) | C15: =C14-'Income Statement'!C50 -> 0 | D15: =D14-'Income Statement'!D50 -> 0 | E15: =E14-'Income Statement'!E50 -> 0 | F15: =F14-'Income Statement'!F50 -> 0 | G15: =G14-'Income Statement'!G50 -> 0 | H15: =H14-'Income Statement'!H50 -> 0 | I15: =I14-'Income Statement'!I50 -> 0 | J15: =J14-'Income Statement'!J50 -> 0 | ... L15: =L14-'Income Statement'!L50 -> 0
A16: Amortization of intangible assets (and ROU assets, later years) | B16: FY2016-FY2017: combined depreciation & amortization total (not split on face of CF). | C16: 3042 | D16: 4737 | E16: 3566 | F16: 5239 | G16: 6335 | H16: 5502 | I16: 4455 | J16: 3333 | K16: 9417 | L16: 8201 | O16: 4587 | P16: 6962 | Q16: 2032 | R16: 4056 | S16: 6116 | T16: 2003 | U16: 4005 | V16: 6047
A17: Depreciation | E17: 515 | F17: 569 | G17: 570 | H17: 539 | I17: 529 | J17: 502 | K17: 593 | L17: 574 | O17: 288 | P17: 437 | Q17: 142 | R17: 284 | S17: 426 | T17: 150 | U17: 313 | V17: 484
A18: Stock-based compensation expense | C18: 679 | D18: 921 | E18: 1227 | F18: 2185 | G18: 1976 | H18: 1704 | I18: 1533 | J18: 2171 | K18: 5741 | L18: 7568 | O18: 3039 | P18: 4427 | Q18: 1280 | R18: 3051 | S18: 5373 | T18: 2176 | U18: 4268 | V18: 6287
A19: Excess tax benefits from stock-based compensation | C19: -89
A20: Deferred income taxes and other non-cash taxes | C20: 365 | D20: -173 | E20: -8270 | F20: -934 | G20: -1142 | H20: -809 | I20: -34 | J20: -501 | K20: 1965 | L20: -4008 | O20: -805 | P20: 2833 | Q20: -696 | R20: -1267 | S20: -983 | T20: -455 | U20: -1058 | V20: -1051
A21: Impairment on investment | E21: 106
A22: Non-cash portion of loss on debt extinguishment | C22: 100 | D22: 166 | G22: 169 | H22: 198 | I22: 100 | K22: 157 | L22: 138 | P22: 105 | Q22: 65 | R22: 65 | S22: 118 | T22: 55 | U22: 86 | V22: 161
A23: Non-cash restructuring, impairment and disposal charges | C23: 662 | D23: 71 | E23: 21 | F23: 133 | G23: 44 | H23: 38 | I23: 13
A24: Non-cash interest expense / debt issuance cost amortization | C24: 36 | D24: 24 | E24: 24 | F24: 90 | G24: 108 | H24: 96 | I24: 129 | J24: 132 | K24: 427 | L24: 344 | O24: 221 | P24: 336 | Q24: 97 | R24: 191 | S24: 273 | T24: 72 | U24: 139 | V24: 204
A25: Other | C25: -6 | D25: 7 | E25: 37 | F25: -125 | G25: -52 | H25: -113 | I25: 170 | J25: 9 | K25: 404 | L25: 94 | O25: 130 | P25: 266 | Q25: 41 | R25: 81 | S25: 58 | T25: 15 | U25: 18 | V25: 31
A26: (Increase) decrease in trade accounts receivable, net | C26: -491 | D26: -267 | E26: -652 | F26: 486 | G26: 981 | H26: 210 | I26: -870 | J26: -187 | K26: 2327 | L26: -2717 | O26: 1243 | P26: 2078 | Q26: -539 | R26: -1129 | S26: -2066 | T26: -1315 | U26: -3685 | V26: -6544
A27: (Increase) decrease in inventory | C27: 996 | D27: -39 | E27: 417 | F27: 250 | G27: -31 | H27: -294 | I27: -627 | J27: 27 | K27: 150 | L27: -510 | O27: 68 | P27: 16 | Q27: -148 | R27: -257 | S27: -420 | T27: -692 | U27: -2058 | V27: -2253
A28: Increase (decrease) in accounts payable | C28: 33 | D28: -97 | E28: -325 | F28: -42 | G28: -3 | H28: 243 | I28: -79 | J28: 209 | K28: 121 | L28: -118 | O28: -167 | P28: 206 | Q28: 241 | R28: -372 | S28: -236 | T28: 534 | U28: 683 | V28: 2313
A29: Increase (decrease) in employee compensation and benefits | C29: 163 | D29: 109 | E29: 6 | F29: -294 | G29: 217 | H29: 186 | I29: 136 | J29: -279 | K29: 78 | L29: 300 | O29: -409 | P29: -118 | Q29: -908 | R29: -621 | S29: -110 | T29: -1261 | U29: -991 | V29: -619
A30: Contributions to defined benefit pension plans | D30: -361 | E30: -130
A31: Change in other current assets and current liabilities | C31: -98 | D31: -490 | E31: 369 | F31: -283 | G31: 331 | H31: -177 | I31: 222 | J31: -628 | K31: -5323 | L31: -1837 | O31: -2568 | P31: -3913 | Q31: 26 | R31: -29 | S31: -1028 | T31: -692 | U31: -218 | V31: -2893
A32: Change in other long-term assets and long-term liabilities | C32: -120 | D32: 159 | E32: -641 | F32: -301 | G32: -402 | H32: -295 | I32: -436 | J32: -785 | K32: -1990 | L32: -3618 | O32: 322 | P32: -848 | Q32: -1023 | R32: -1853 | S32: -2295 | T32: 321 | U32: 592 | V32: 1036
A33: Net cash provided by operating activities | C33: =C14+C16+C17+C18+C19+C20+C21+C22+C23+C24+C25+C26+C27+C28+C29+C30+C31+C32 -> 3411 | D33: =D14+D16+D17+D18+D19+D20+D21+D22+D23+D24+D25+D26+D27+D28+D29+D30+D31+D32 -> 6551 | E33: =E14+E16+E17+E18+E19+E20+E21+E22+E23+E24+E25+E26+E27+E28+E29+E30+E31+E32 -> 8880 | F33: =F14+F16+F17+F18+F19+F20+F21+F22+F23+F24+F25+F26+F27+F28+F29+F30+F31+F32 -> 9697 | G33: =G14+G16+G17+G18+G19+G20+G21+G22+G23+G24+G25+G26+G27+G28+G29+G30+G31+G32 -> 12061 | H33: =H14+H16+H17+H18+H19+H20+H21+H22+H23+H24+H25+H26+H27+H28+H29+H30+H31+H32 -> 13764 | I33: =I14+I16+I17+I18+I19+I20+I21+I22+I23+I24+I25+I26+I27+I28+I29+I30+I31+I32 -> 16736 | J33: =J14+J16+J17+J18+J19+J20+J21+J22+J23+J24+J25+J26+J27+J28+J29+J30+J31+J32 -> 18085 | ... L33: =L14+L16+L17+L18+L19+L20+L21+L22+L23+L24+L25+L26+L27+L28+L29+L30+L31+L32 -> 27537 | O33: =O14+O16+O17+O18+O19+O20+O21+O22+O23+O24+O25+O26+O27+O28+O29+O30+O31+O32 -> 9395 | P33: =P14+P16+P17+P18+P19+P20+P21+P22+P23+P24+P25+P26+P27+P28+P29+P30+P31+P32 -> 14358 | Q33: =Q14+Q16+Q17+Q18+Q19+Q20+Q21+Q22+Q23+Q24+Q25+Q26+Q27+Q28+Q29+Q30+Q31+Q32 -> 6113 | R33: =R14+R16+R17+R18+R19+R20+R21+R22+R23+R24+R25+R26+R27+R28+R29+R30+R31+R32 -> 12668 | S33: =S14+S16+S17+S18+S19+S20+S21+S22+S23+S24+S25+S26+S27+S28+S29+S30+S31+S32 -> 19834 | T33: =T14+T16+T17+T18+T19+T20+T21+T22+T23+T24+T25+T26+T27+T28+T29+T30+T31+T32 -> 8260 | U33: =U14+U16+U17+U18+U19+U20+U21+U22+U23+U24+U25+U26+U27+U28+U29+U30+U31+U32 -> 18753 | V33: =V14+V16+V17+V18+V19+V20+V21+V22+V23+V24+V25+V26+V27+V28+V29+V30+V31+V32 -> 32950
A35: 2. INVESTING ACTIVITIES
A36: Purchases of property, plant and equipment | C36: -723 | D36: -1069 | E36: -635 | F36: -432 | G36: -463 | H36: -443 | I36: -424 | J36: -452 | K36: -548 | L36: -623 | O36: -254 | P36: -426 | Q36: -100 | R36: -244 | S36: -386 | T36: -250 | U36: -481 | V36: -1013
A37: Proceeds from disposals of property, plant and equipment | C37: 5 | D37: 441 | E37: 239 | F37: 88 | G37: 12 | H37: 4
A38: Acquisitions of businesses, net of cash acquired | B38: FY2024: VMware acquisition (closed Nov 22, 2023). Cash outflow of $25,978M reflects only the cash-consideration portion, net of ~$6,642M cash acquired; total deal value was $86,290M, ~$54.2B of which was Broadcom stock (non-cash). | C38: -10055 | D38: -40 | E38: -4800 | F38: -16033 | G38: -10872 | H38: -8 | I38: -246 | J38: -53 | K38: -25978 | O38: -25976 | P38: -25978
A39: Proceeds from sales of businesses | B39: FY2024: $3,485M — sale of the VMware End-User Computing (EUC) business to KKR. | C39: 898 | D39: 10 | E39: 773 | F39: 957 | G39: 218 | H39: 45 | K39: 3485 | L39: 300 | P39: 3485 | S39: 300
A40: Purchases of investments | C40: -58 | D40: -207 | E40: -249 | F40: -5 | I40: -200 | J40: -346 | K40: -175 | L40: -597 | O40: -72 | P40: -145 | Q40: -105 | R40: -162 | S40: -261 | T40: -114 | U40: -137 | V40: -756
A41: Proceeds from sales/maturities of investments | C41: 104 | D41: 200 | E41: 54 | F41: 5 | H41: 169 | I41: 200 | J41: 228 | K41: 156 | L41: 248 | O41: 131 | P41: 136 | Q41: 18 | R41: 96 | S41: 147 | T41: 244 | U41: 283 | V41: 320
A42: Other | C42: -11 | D42: -9 | E42: -56 | F42: -2 | G42: -4 | H42: -12 | I42: 3 | J42: -66 | K42: -10 | L42: 92 | O42: -12 | P42: -10 | Q42: 13 | R42: 3 | S42: -13 | T42: 5 | U42: 12 | V42: 13
A43: Net cash used in investing activities | C43: =C36+C37+C38+C39+C40+C41+C42 -> -9840 | D43: =D36+D37+D38+D39+D40+D41+D42 -> -674 | E43: =E36+E37+E38+E39+E40+E41+E42 -> -4674 | F43: =F36+F37+F38+F39+F40+F41+F42 -> -15422 | G43: =G36+G37+G38+G39+G40+G41+G42 -> -11109 | H43: =H36+H37+H38+H39+H40+H41+H42 -> -245 | I43: =I36+I37+I38+I39+I40+I41+I42 -> -667 | J43: =J36+J37+J38+J39+J40+J41+J42 -> -689 | ... L43: =L36+L37+L38+L39+L40+L41+L42 -> -580 | O43: =O36+O37+O38+O39+O40+O41+O42 -> -26183 | P43: =P36+P37+P38+P39+P40+P41+P42 -> -22938 | Q43: =Q36+Q37+Q38+Q39+Q40+Q41+Q42 -> -174 | R43: =R36+R37+R38+R39+R40+R41+R42 -> -307 | S43: =S36+S37+S38+S39+S40+S41+S42 -> -213 | T43: =T36+T37+T38+T39+T40+T41+T42 -> -115 | U43: =U36+U37+U38+U39+U40+U41+U42 -> -323 | V43: =V36+V37+V38+V39+V40+V41+V42 -> -1436
A45: 3. FINANCING ACTIVITIES
A46: Proceeds from long-term borrowings | C46: 19510 | D46: 17426 | F46: 28793 | G46: 27802 | H46: 9904 | I46: 1935 | K46: 39954 | L46: 15666 | O46: 30010 | P46: 34985 | Q46: 2986 | R46: 3735 | S46: 10695 | T46: 4474 | U46: 4474 | V46: 4474
A47: Repayment of debt | C47: -9842 | D47: -13668 | E47: -973 | F47: -16800 | G47: -18814 | H47: -11495 | I47: -2361 | J47: -403 | K47: -19608 | L47: -18478 | O47: -2934 | P47: -12136 | Q47: -8090 | R47: -8090 | S47: -14840 | T47: -3650 | U47: -4900 | V47: -10528
A48: Payments on assumed debt | C48: -1475
A49: Debt issuance costs | C49: -123 | D49: -24
A50: Other borrowings, net | B50: FY2019/FY2020: other net borrowing activity not separately itemized in this model. FY2025 quarterly columns (1Q/2Q/3Q FY2025): this row holds 'Proceeds from commercial paper, net' as disclosed in each quarter's own 10-Q (fiscal-YTD cumulative, consistent with the rest of the CF quarterly columns). | F50: 1241 | G50: -1285 | Q50: 3980 | R50: 3861 | S50: 488
A51: Excess tax benefits from stock-based compensation | B51: FY2016: offsetting reclassification of the $89M excess tax benefit deducted within operating activities (see CFO section) — required by the cash-basis presentation used that year. | C51: 89
A52: Dividends and distributions paid on common stock | C52: -750 | D52: -1745 | E52: -2998 | F52: -4235 | G52: -5534 | H52: -6212 | I52: -7032 | J52: -7645 | K52: -9814 | L52: -11142 | O52: -4878 | P52: -7330 | Q52: -2774 | R52: -5559 | S52: -8345 | T52: -3086 | U52: -6178 | V52: -9281
A53: Repurchases of common stock | E53: -7258 | F53: -5435 | I53: -7000 | J53: -5824 | K53: -7176 | L53: -2450 | O53: -7176 | P53: -7176 | R53: -2450 | S53: -2450 | T53: -7850 | U53: -8450 | V53: -8450
A54: Shares repurchased for tax withholdings on vesting of equity awards | F54: -972 | G54: -765 | H54: -1299 | I54: -1455 | J54: -1861 | K54: -5216 | L54: -3860 | O54: -2662 | P54: -4012 | Q54: -2036 | R54: -3802 | S54: -3860
A55: Issuance of preferred stock, net | F55: 3679
A56: Issuance of common stock | C56: 295 | D56: 257 | E56: 156 | F56: 253 | G56: 276 | H56: 170 | I56: 114 | J56: 122 | K56: 190 | L56: 221 | O56: 64 | P56: 64 | R56: 118 | S56: 118 | U56: 113 | V56: 113
A57: Payments of capital lease obligations | D57: -16 | E57: -21
A58: Other | E58: -24 | F58: -36 | G58: -69 | H58: -42 | I58: -17 | J58: -12 | K58: -63 | L58: -84 | O58: -16 | P58: -52 | Q58: -46 | R58: -50 | S58: -57 | T58: -37 | U58: -39 | V58: -45
A59: Net cash provided by (used in) financing activities | C59: =C46+C47+C48+C49+C50+C51+C52+C53+C54+C55+C56+C57+C58 -> 7704 | D59: =D46+D47+D48+D49+D50+D51+D52+D53+D54+D55+D56+D57+D58 -> 2230 | E59: =E46+E47+E48+E49+E50+E51+E52+E53+E54+E55+E56+E57+E58 -> -11118 | F59: =F46+F47+F48+F49+F50+F51+F52+F53+F54+F55+F56+F57+F58 -> 6488 | G59: =G46+G47+G48+G49+G50+G51+G52+G53+G54+G55+G56+G57+G58 -> 1611 | H59: =H46+H47+H48+H49+H50+H51+H52+H53+H54+H55+H56+H57+H58 -> -8974 | I59: =I46+I47+I48+I49+I50+I51+I52+I53+I54+I55+I56+I57+I58 -> -15816 | J59: =J46+J47+J48+J49+J50+J51+J52+J53+J54+J55+J56+J57+J58 -> -15623 | ... L59: =L46+L47+L48+L49+L50+L51+L52+L53+L54+L55+L56+L57+L58 -> -20127 | O59: =O46+O47+O48+O49+O50+O51+O52+O53+O54+O55+O56+O57+O58 -> 12408 | P59: =P46+P47+P48+P49+P50+P51+P52+P53+P54+P55+P56+P57+P58 -> 4343 | Q59: =Q46+Q47+Q48+Q49+Q50+Q51+Q52+Q53+Q54+Q55+Q56+Q57+Q58 -> -5980 | R59: =R46+R47+R48+R49+R50+R51+R52+R53+R54+R55+R56+R57+R58 -> -12237 | S59: =S46+S47+S48+S49+S50+S51+S52+S53+S54+S55+S56+S57+S58 -> -18251 | T59: =T46+T47+T48+T49+T50+T51+T52+T53+T54+T55+T56+T57+T58 -> -10149 | U59: =U46+U47+U48+U49+U50+U51+U52+U53+U54+U55+U56+U57+U58 -> -14980 | V59: =V46+V47+V48+V49+V50+V51+V52+V53+V54+V55+V56+V57+V58 -> -23717
A61: 4. NET CHANGE IN CASH
A62: Net change in cash and cash equivalents | B62: No separate FX-translation line is presented in any year of Broadcom's cash flow statement. | C62: =C33+C43+C59 -> 1275 | D62: =D33+D43+D59 -> 8107 | E62: =E33+E43+E59 -> -6912 | F62: =F33+F43+F59 -> 763 | G62: =G33+G43+G59 -> 2563 | H62: =H33+H43+H59 -> 4545 | I62: =I33+I43+I59 -> 253 | J62: =J33+J43+J59 -> 1773 | ... L62: =L33+L43+L59 -> 6830 | O62: =O33+O43+O59 -> -4380 | P62: =P33+P43+P59 -> -4237 | Q62: =Q33+Q43+Q59 -> -41 | R62: =R33+R43+R59 -> 124 | S62: =S33+S43+S59 -> 1370 | T62: =T33+T43+T59 -> -2004 | U62: =U33+U43+U59 -> 3450 | V62: =V33+V43+V59 -> 7797
A63: Cash and cash equivalents, beginning of period | C63: 1822 | D63: 3097 | E63: 11204 | F63: 4292 | G63: 5055 | H63: 7618 | I63: 12163 | J63: 12416 | K63: 14189 | L63: 9348 | O63: 14189 | P63: 14189 | Q63: 9348 | R63: 9348 | S63: 9348 | T63: 16178 | U63: 16178 | V63: 16178
A64: Cash and cash equivalents, end of period | C64: 3097 | D64: 11204 | E64: 4292 | F64: 5055 | G64: 7618 | H64: 12163 | I64: 12416 | J64: 14189 | K64: 9348 | L64: 16178 | O64: 9809 | P64: 9952 | Q64: 9307 | R64: 9472 | S64: 10718 | T64: 14174 | U64: 19628 | V64: 23975
A65: Cash Walk Check (should be ~0) | C65: =C63+C62-C64 -> 0 | D65: =D63+D62-D64 -> 0 | E65: =E63+E62-E64 -> 0 | F65: =F63+F62-F64 -> 0 | G65: =G63+G62-G64 -> 0 | H65: =H63+H62-H64 -> 0 | I65: =I63+I62-I64 -> 0 | J65: =J63+J62-J64 -> 0 | ... L65: =L63+L62-L64 -> 0 | O65: =O63+O62-O64 -> 0 | P65: =P63+P62-P64 -> 0 | Q65: =Q63+Q62-Q64 -> 0 | R65: =R63+R62-R64 -> 0 | S65: =S63+S62-S64 -> 0 | T65: =T63+T62-T64 -> 0 | U65: =U63+U62-U64 -> 0 | V65: =V63+V62-V64 -> 0
A67: 5. FREE CASH FLOW ANALYTICS
A68: Free Cash Flow | C68: =C33+C36 -> 2688 | D68: =D33+D36 -> 5482 | E68: =E33+E36 -> 8245 | F68: =F33+F36 -> 9265 | G68: =G33+G36 -> 11598 | H68: =H33+H36 -> 13321 | I68: =I33+I36 -> 16312 | J68: =J33+J36 -> 17633 | ... L68: =L33+L36 -> 26914 | O68: =O33+O36 -> 9141 | P68: =P33+P36 -> 13932 | Q68: =Q33+Q36 -> 6013 | R68: =R33+R36 -> 12424 | S68: =S33+S36 -> 19448 | T68: =T33+T36 -> 8010 | U68: =U33+U36 -> 18272 | V68: =V33+V36 -> 31937
A69: YoY Growth | D69: =IF(N(C68)=0,"",D68/C68-1) -> 1.0394345 | E69: =IF(N(D68)=0,"",E68/D68-1) -> 0.50401313 | F69: =IF(N(E68)=0,"",F68/E68-1) -> 0.12371134 | G69: =IF(N(F68)=0,"",G68/F68-1) -> 0.25180788 | H69: =IF(N(G68)=0,"",H68/G68-1) -> 0.1485601 | I69: =IF(N(H68)=0,"",I68/H68-1) -> 0.22453269 | J69: =IF(N(I68)=0,"",J68/I68-1) -> 0.080983325 | K69: =IF(N(J68)=0,"",K68/J68-1) -> 0.1010038 | L69: =IF(N(K68)=0,"",L68/K68-1) -> 0.38631915 | S69: =IF(N(O68)=0,"",S68/O68-1) -> 1.1275572 | T69: =IF(N(P68)=0,"",T68/P68-1) -> -0.4250646 | U69: =IF(N(Q68)=0,"",U68/Q68-1) -> 2.0387494 | V69: =IF(N(R68)=0,"",V68/R68-1) -> 1.5705892
A70: Capex % of Revenue | C70: =0-C36/'Income Statement'!C14 -> 0.054607251 | D70: =0-D36/'Income Statement'!D14 -> 0.060614652 | E70: =0-E36/'Income Statement'!E14 -> 0.030458557 | F70: =0-F36/'Income Statement'!F14 -> 0.019117582 | G70: =0-G36/'Income Statement'!G14 -> 0.019382117 | H70: =0-H36/'Income Statement'!H14 -> 0.016138434 | I70: =0-I36/'Income Statement'!I14 -> 0.01276993 | J70: =0-J36/'Income Statement'!J14 -> 0.012619001 | ... L70: =0-L36/'Income Statement'!L14 -> 0.0097515927 | O70: =0-O36/'Income Statement'!O14 -> 0.020341155 | P70: =0-P36/'Income Statement'!P14 -> 0.032588739 | Q70: =0-Q36/'Income Statement'!Q14 -> 0.0067042102 | R70: =0-R36/'Income Statement'!R14 -> 0.01626233 | S70: =0-S36/'Income Statement'!S14 -> 0.024197593 | T70: =0-T36/'Income Statement'!T14 -> 0.012945989 | U70: =0-U36/'Income Statement'!U14 -> 0.021679362 | V70: =0-V36/'Income Statement'!V14 -> 0.034233382
A71: FCF Margin | C71: =C68/'Income Statement'!C14 -> 0.20302115 | D71: =D68/'Income Statement'!D14 -> 0.31084146 | E71: =E68/'Income Statement'!E14 -> 0.39548158 | F71: =F68/'Income Statement'!F14 -> 0.41001018 | G71: =G68/'Income Statement'!G14 -> 0.48551574 | H71: =H68/'Income Statement'!H14 -> 0.48528233 | I71: =I68/'Income Statement'!I14 -> 0.49128091 | J71: =J68/'Income Statement'!J14 -> 0.49228063 | ... L71: =L68/'Income Statement'!L14 -> 0.42127506 | O71: =O68/'Income Statement'!O14 -> 0.73204132 | P71: =P68/'Income Statement'!P14 -> 1.0657895 | Q71: =Q68/'Income Statement'!Q14 -> 0.40312416 | R71: =R68/'Income Statement'!R14 -> 0.82804585 | S71: =S68/'Income Statement'!S14 -> 1.2191575 | T71: =T68/'Income Statement'!T14 -> 0.4147895 | U71: =U68/'Income Statement'!U14 -> 0.82354532 | V71: =V68/'Income Statement'!V14 -> 1.0792809
A72: FCF Conversion (FCF / Net Income) | C72: =C68/'Income Statement'!C50 -> -1.4443847 | D72: =D68/'Income Statement'!D50 -> 3.07287 | E72: =E68/'Income Statement'!E50 -> 0.65384615 | F72: =F68/'Income Statement'!F50 -> 3.4012482 | G72: =G68/'Income Statement'!G50 -> 3.9182432 | H72: =H68/'Income Statement'!H50 -> 1.9775831 | I72: =I68/'Income Statement'!I50 -> 1.4190518 | J72: =J68/'Income Statement'!J50 -> 1.2521659 | ... L72: =L68/'Income Statement'!L50 -> 1.1637983 | O72: =O68/'Income Statement'!O50 -> 4.3097595 | P72: =P68/'Income Statement'!P50 -> -7.4304 | Q72: =Q68/'Income Statement'!Q50 -> 1.0926767 | R72: =R68/'Income Statement'!R50 -> 2.5023162 | S72: =S68/'Income Statement'!S50 -> 4.6975845 | T72: =T68/'Income Statement'!T50 -> 1.0899442 | U72: =U68/'Income Statement'!U50 -> 1.9626208 | V72: =V68/'Income Statement'!V50 -> 2.4401742

Sheet Segments
A1: Broadcom Inc. — Segments
A2: $ in millions except per-share data | USD | as of 2026-09-22
C3: FY2016 | D3: FY2017 | E3: FY2018 | F3: FY2019 | G3: FY2020 | H3: FY2021 | I3: FY2022 | J3: FY2023 | K3: FY2024 | L3: FY2025 | M3: · | N3: · | O3: 2Q FY2024 | P3: 3Q FY2024 | Q3: 1Q FY2025 | R3: 2Q FY2025 | S3: 3Q FY2025 | T3: 1Q FY2026 | U3: 2Q FY2026 | V3: 3Q FY2026
C4: 2016-10-30 | D4: 2017-10-29 | E4: 2018-11-04 | F4: 2019-11-03 | G4: 2020-11-01 | H4: 2021-10-31 | I4: 2022-10-30 | J4: 2023-10-29 | K4: 2024-11-03 | L4: 2025-11-02 | O4: 2024-05-05 | P4: 2024-08-04 | Q4: 2025-02-02 | R4: 2025-05-04 | S4: 2025-08-03 | T4: 2026-02-01 | U4: 2026-05-03 | V4: 2026-08-02
A6: CONTENTS
A7: =HYPERLINK("#'Segments'!A11","1. LEGACY 4-SEGMENT STRUCTURE (FY2016-FY2018)") -> 1. LEGACY 4-SEGMENT STRUCTURE (FY2016-FY2018)
A8: =HYPERLINK("#'Segments'!A27","2. 3-SEGMENT STRUCTURE (FY2019 ONLY — CA Technologies year)") -> 2. 3-SEGMENT STRUCTURE (FY2019 ONLY — CA Technologies year)
A9: =HYPERLINK("#'Segments'!A41","3. 2-SEGMENT STRUCTURE (FY2020-PRESENT)") -> 3. 2-SEGMENT STRUCTURE (FY2020-PRESENT)
A11: 1. LEGACY 4-SEGMENT STRUCTURE (FY2016-FY2018)
A12: Wired Infrastructure — Revenue | C12: 6582 | D12: 8549 | E12: 8674
A13: Wireless Communications — Revenue | C13: 3724 | D13: 5404 | E13: 6490
A14: Enterprise Storage — Revenue | C14: 2291 | D14: 2799 | E14: 4673
A15: Industrial & Other — Revenue | C15: 643 | D15: 884 | E15: 1011
A16: Total segment revenue | C16: =C12+C13+C14+C15 -> 13240 | D16: =D12+D13+D14+D15 -> 17636 | E16: =E12+E13+E14+E15 -> 20848
A17: vs IS Revenue (should be ~0) | C17: =C16-'Income Statement'!C14 -> 0 | D17: =D16-'Income Statement'!D14 -> 0 | E17: =E16-'Income Statement'!E14 -> 0
A19: Wired Infrastructure — Operating income | C19: 2664 | D19: 3853 | E19: 4093
A20: Wireless Communications — Operating income | C20: 1282 | D20: 2155 | E20: 2840
A21: Enterprise Storage — Operating income | C21: 995 | D21: 1527 | E21: 2906
A22: Industrial & Other — Operating income | C22: 327 | D22: 447 | E22: 571
A23: Segment operating income before unallocated | C23: =C19+C20+C21+C22 -> 5268 | D23: =D19+D20+D21+D22 -> 7982 | E23: =E19+E20+E21+E22 -> 10410
A24: Unallocated corporate expenses (plug to consolidated OI) | C24: ='Income Statement'!C37-C23 -> -5677 | D24: ='Income Statement'!D37-D23 -> -5599 | E24: ='Income Statement'!E37-E23 -> -5275
A25: Total operating income (= IS operating income) | C25: ='Income Statement'!C37 -> -409 | D25: ='Income Statement'!D37 -> 2383 | E25: ='Income Statement'!E37 -> 5135
A27: 2. 3-SEGMENT STRUCTURE (FY2019 ONLY — CA Technologies year)
A28: Semiconductor solutions — Revenue | F28: 17368
A29: Infrastructure software — Revenue | F29: 5156
A30: IP licensing — Revenue | F30: 73
A31: Total segment revenue | F31: =F28+F29+F30 -> 22597
A32: vs IS Revenue (should be ~0) | F32: =F31-'Income Statement'!F14 -> 0
A34: Semiconductor solutions — Operating income | F34: 8150
A35: Infrastructure software — Operating income | F35: 3781
A36: IP licensing — Operating income (loss) | F36: -2
A37: Segment operating income before unallocated | F37: =F34+F35+F36 -> 11929
A38: Unallocated corporate expenses (plug to consolidated OI) | F38: ='Income Statement'!F37-F37 -> -8485
A39: Total operating income (= IS operating income) | F39: ='Income Statement'!F37 -> 3444
A41: 3. 2-SEGMENT STRUCTURE (FY2020-PRESENT)
A42: Semiconductor Solutions — Revenue | G42: 17267 | H42: 20383 | I42: 25818 | J42: 28182 | K42: 30096 | L42: 36858 | O42: 7202 | P42: 7274 | Q42: 8212 | R42: 8408 | S42: 9166 | T42: 12515 | U42: 15009 | V42: 20839
A43: yoy | H43: =H42/G42-1 -> 0.18045984 | I43: =I42/H42-1 -> 0.26664377 | J43: =J42/I42-1 -> 0.091564025 | K43: =K42/J42-1 -> 0.067915691 | L43: =L42/K42-1 -> 0.22468102 | R43: =R42/O42-1 -> 0.16745349 | S43: =S42/P42-1 -> 0.26010448 | T43: =T42/Q42-1 -> 0.52398928 | U43: =U42/R42-1 -> 0.78508563 | V43: =V42/S42-1 -> 1.2735108
A44: Infrastructure Software — Revenue | G44: 6621 | H44: 7067 | I44: 7385 | J44: 7637 | K44: 21478 | L44: 27029 | O44: 5285 | P44: 5798 | Q44: 6704 | R44: 6596 | S44: 6786 | T44: 6796 | U44: 7178 | V44: 8752
A45: yoy | H45: =H44/G44-1 -> 0.067361426 | I45: =I44/H44-1 -> 0.044997877 | J45: =J44/I44-1 -> 0.034123223 | K45: =K44/J44-1 -> 1.8123609 | L45: =L44/K44-1 -> 0.25845051 | R45: =R44/O44-1 -> 0.24806055 | S45: =S44/P44-1 -> 0.17040359 | T45: =T44/Q44-1 -> 0.01372315 | U45: =U44/R44-1 -> 0.088235294 | V45: =V44/S44-1 -> 0.28971412
A46: Total segment revenue | G46: =G42+G44 -> 23888 | H46: =H42+H44 -> 27450 | I46: =I42+I44 -> 33203 | J46: =J42+J44 -> 35819 | K46: =K42+K44 -> 51574 | L46: =L42+L44 -> 63887 | O46: =O42+O44 -> 12487 | P46: =P42+P44 -> 13072 | Q46: =Q42+Q44 -> 14916 | R46: =R42+R44 -> 15004 | S46: =S42+S44 -> 15952 | T46: =T42+T44 -> 19311 | U46: =U42+U44 -> 22187 | V46: =V42+V44 -> 29591
A47: vs IS Revenue (should be ~0) | G47: =G46-'Income Statement'!G14 -> 0 | H47: =H46-'Income Statement'!H14 -> 0 | I47: =I46-'Income Statement'!I14 -> 0 | J47: =J46-'Income Statement'!J14 -> 0 | K47: =K46-'Income Statement'!K14 -> 0 | L47: =L46-'Income Statement'!L14 -> 0 | O47: =O46-'Income Statement'!O14 -> 0 | P47: =P46-'Income Statement'!P14 -> 0 | Q47: =Q46-'Income Statement'!Q14 -> 0 | R47: =R46-'Income Statement'!R14 -> 0 | S47: =S46-'Income Statement'!S14 -> 0 | T47: =T46-'Income Statement'!T14 -> 0 | U47: =U46-'Income Statement'!U14 -> 0 | V47: =V46-'Income Statement'!V14 -> 0
A48: yoy | H48: =H46/G46-1 -> 0.14911253 | I48: =I46/H46-1 -> 0.20958106 | J48: =J46/I46-1 -> 0.078788061 | K48: =K46/J46-1 -> 0.43985036 | L48: =L46/K46-1 -> 0.23874433 | R48: =R46/O46-1 -> 0.20156963 | S48: =S46/P46-1 -> 0.22031824 | T48: =T46/Q46-1 -> 0.29465004 | U48: =U46/R46-1 -> 0.478739 | V48: =V46/S46-1 -> 0.85500251
A51: Semiconductor Solutions — Operating income | G51: 8576 | H51: 10976 | I51: 15075 | J51: 16486 | K51: 16759 | L51: 21232 | O51: 3978 | P51: 4042 | Q51: 4706 | R51: 4806 | S51: 5217 | T51: 7503 | U51: 9281 | V51: 12770
A52: yoy | H52: =H51/G51-1 -> 0.27985075 | I52: =I51/H51-1 -> 0.37345117 | J52: =J51/I51-1 -> 0.093598673 | K52: =K51/J51-1 -> 0.016559505 | L52: =L51/K51-1 -> 0.26690137 | R52: =R51/O51-1 -> 0.2081448 | S52: =S51/P51-1 -> 0.29069767 | T52: =T51/Q51-1 -> 0.59434764 | U52: =U51/R51-1 -> 0.93112776 | V52: =V51/S51-1 -> 1.4477669
A53: Infrastructure Software — Operating income | G53: 4363 | H53: 4936 | I53: 5219 | J53: 5639 | K53: 13977 | L53: 20765 | O53: 3168 | P53: 3906 | Q53: 5122 | R53: 4987 | S53: 5238 | T53: 5323 | U53: 5647 | V53: 7325
A54: yoy | H54: =H53/G53-1 -> 0.13133165 | I54: =I53/H53-1 -> 0.057333874 | J54: =J53/I53-1 -> 0.080475187 | K54: =K53/J53-1 -> 1.478631 | L54: =L53/K53-1 -> 0.485655 | R54: =R53/O53-1 -> 0.57417929 | S54: =S53/P53-1 -> 0.34101382 | T54: =T53/Q53-1 -> 0.039242483 | U54: =U53/R53-1 -> 0.13234409 | V54: =V53/S53-1 -> 0.39843452
A55: Semiconductor Solutions —— Margin | G55: =G51/G42 -> 0.49666995 | H55: =H51/H42 -> 0.53848796 | I55: =I51/I42 -> 0.58389496 | J55: =J51/J42 -> 0.58498332 | K55: =K51/K42 -> 0.55685141 | L55: =L51/L42 -> 0.57604862 | O55: =O51/O42 -> 0.55234657 | P55: =P51/P42 -> 0.55567776 | Q55: =Q51/Q42 -> 0.57306381 | R55: =R51/R42 -> 0.57159848 | S55: =S51/S42 -> 0.56916867 | T55: =T51/T42 -> 0.59952058 | U55: =U51/U42 -> 0.61836232 | V55: =V51/V42 -> 0.61279332
A56: Infrastructure Software — Margin | G56: =G53/G44 -> 0.6589639 | H56: =H53/H44 -> 0.69845762 | I56: =I53/I44 -> 0.70670278 | J56: =J53/J44 -> 0.73837894 | K56: =K53/K44 -> 0.65075892 | L56: =L53/L44 -> 0.76824892 | O56: =O53/O44 -> 0.59943236 | P56: =P53/P44 -> 0.67368058 | Q56: =Q53/Q44 -> 0.76402148 | R56: =R53/R44 -> 0.75606428 | S56: =S53/S44 -> 0.77188329 | T56: =T53/T44 -> 0.78325486 | U56: =U53/U44 -> 0.78670939 | V56: =V53/V44 -> 0.83695155
A57: Segment operating income before unallocated | G57: =G51+G53 -> 12939 | H57: =H51+H53 -> 15912 | I57: =I51+I53 -> 20294 | J57: =J51+J53 -> 22125 | K57: =K51+K53 -> 30736 | L57: =L51+L53 -> 41997 | O57: =O51+O53 -> 7146 | P57: =P51+P53 -> 7948 | Q57: =Q51+Q53 -> 9828 | R57: =R51+R53 -> 9793 | S57: =S51+S53 -> 10455 | T57: =T51+T53 -> 12826 | U57: =U51+U53 -> 14928 | V57: =V51+V53 -> 20095
A58: Unallocated corporate expenses (plug to consolidated OI) | B58: Includes amortization of acquisition-related intangibles, stock-based compensation, restructuring/other charges, and acquisition-related costs — not allocated to segments per the CODM's reporting basis. | G58: ='Income Statement'!G37-G57 -> -8925 | H58: ='Income Statement'!H37-H57 -> -7393 | I58: ='Income Statement'!I37-I57 -> -6069 | J58: ='Income Statement'!J37-J57 -> -5918 | K58: ='Income Statement'!K37-K57 -> -17273 | L58: ='Income Statement'!L37-L57 -> -16513 | O58: ='Income Statement'!O37-O57 -> -4181 | P58: ='Income Statement'!P37-P57 -> -4160 | Q58: ='Income Statement'!Q37-Q57 -> -3568 | R58: ='Income Statement'!R37-R57 -> -3964 | S58: ='Income Statement'!S37-S57 -> -4568 | T58: ='Income Statement'!T37-T57 -> -4263 | U58: ='Income Statement'!U37-U57 -> -4140 | V58: ='Income Statement'!V37-V57 -> -4140
A59: Total operating income (= IS operating income) | G59: ='Income Statement'!G37 -> 4014 | H59: ='Income Statement'!H37 -> 8519 | I59: ='Income Statement'!I37 -> 14225 | J59: ='Income Statement'!J37 -> 16207 | K59: ='Income Statement'!K37 -> 13463 | L59: ='Income Statement'!L37 -> 25484 | O59: ='Income Statement'!O37 -> 2965 | P59: ='Income Statement'!P37 -> 3788 | Q59: ='Income Statement'!Q37 -> 6260 | R59: ='Income Statement'!R37 -> 5829 | S59: ='Income Statement'!S37 -> 5887 | T59: ='Income Statement'!T37 -> 8563 | U59: ='Income Statement'!U37 -> 10788 | V59: ='Income Statement'!V37 -> 15955
A60: yoy | H60: =H59/G59-1 -> 1.1223219 | I60: =I59/H59-1 -> 0.66979692 | J60: =J59/I59-1 -> 0.13933216 | K60: =K59/J59-1 -> -0.16930956 | L60: =L59/K59-1 -> 0.89289163 | R60: =R59/O59-1 -> 0.96593592 | S60: =S59/P59-1 -> 0.55411827 | T60: =T59/Q59-1 -> 0.36789137 | U60: =U59/R59-1 -> 0.85074627 | V60: =V59/S59-1 -> 1.7102089
A61: OPM（GAAP） | G61: =G59/G46 -> 0.16803416 | H61: =H59/H46 -> 0.31034608 | I61: =I59/I46 -> 0.42842514 | J61: =J59/J46 -> 0.45246936 | K61: =K59/K46 -> 0.26104239 | L61: =L59/L46 -> 0.39889179 | O61: =O59/O46 -> 0.23744694 | P61: =P59/P46 -> 0.28977968 | Q61: =Q59/Q46 -> 0.41968356 | R61: =R59/R46 -> 0.3884964 | S61: =S59/S46 -> 0.36904463 | T61: =T59/T46 -> 0.44342603 | U61: =U59/U46 -> 0.48623068 | V61: =V59/V46 -> 0.53918421

Sheet Geography & Products
A1: Broadcom Inc. — Geography & Products
A2: $ in millions except per-share data | USD | as of 2026-09-22
C3: FY2016 | D3: FY2017 | E3: FY2018 | F3: FY2019 | G3: FY2020 | H3: FY2021 | I3: FY2022 | J3: FY2023 | K3: FY2024 | L3: FY2025 | M3: · | N3: · | O3: 2Q FY2024 | P3: 3Q FY2024 | Q3: 1Q FY2025 | R3: 2Q FY2025 | S3: 3Q FY2025 | T3: 1Q FY2026 | U3: 2Q FY2026 | V3: 3Q FY2026
C4: 2016-10-30 | D4: 2017-10-29 | E4: 2018-11-04 | F4: 2019-11-03 | G4: 2020-11-01 | H4: 2021-10-31 | I4: 2022-10-30 | J4: 2023-10-29 | K4: 2024-11-03 | L4: 2025-11-02 | O4: 2024-05-05 | P4: 2024-08-04 | Q4: 2025-02-02 | R4: 2025-05-04 | S4: 2025-08-03 | T4: 2026-02-01 | U4: 2026-05-03 | V4: 2026-08-02
A6: CONTENTS
A7: =HYPERLINK("#'Geography & Products'!A10","1. REVENUE BY GEOGRAPHIC REGION (FY2019 10-K Note onward; own-period figures, not restated comparatives)") -> 1. REVENUE BY GEOGRAPHIC REGION (FY2019 10-K Note onward; own-period figures, not restated comparatives)
A8: =HYPERLINK("#'Geography & Products'!A33","2. LONG-LIVED ASSETS BY GEOGRAPHY (Annual only — disclosed in the 10-K only, not in 10-Qs)") -> 2. LONG-LIVED ASSETS BY GEOGRAPHY (Annual only — disclosed in the 10-K only, not in 10-Qs)
A10: 1. REVENUE BY GEOGRAPHIC REGION (FY2019 10-K Note onward; own-period figures, not restated comparatives)
A11: Products — Americas | B11: Own-period figures as filed in each 10-K/10-Q's own geographic revenue Note (never a later filing's restated comparative column). Not disclosed for FY2016-FY2018. See IS:rev_products note re: the FY2026 Q1 upfront-license reclassification, which also affects how Products/Subscriptions are split by region starting with the 1Q/2Q FY2026 and FY2025-annual columns (post-reclass) vs the 1Q/2Q/3Q FY2025 quarterly columns (pre-reclass, as originally filed). | F11: 2023 | G11: 1775 | H11: 1809 | I11: 2371 | J11: 2601 | K11: 2244 | L11: 7908 | O11: 473 | P11: 582 | Q11: 490 | R11: 635 | S11: 662 | T11: 2164 | U11: 2187 | V11: 2642
A12: Products — Asia Pacific | F12: 14857 | G12: 14442 | H12: 17258 | I12: 21761 | J12: 23263 | K12: 26219 | L12: 33596 | O12: 6267 | P12: 6411 | Q12: 7269 | R12: 7454 | S12: 8181 | T12: 10950 | U12: 13956 | V12: 20199
A13: Products — Europe, Middle East & Africa | F13: 1237 | G13: 1218 | H13: 1819 | I13: 2145 | J13: 2027 | K13: 1896 | L13: 3343 | O13: 452 | P13: 446 | Q13: 412 | R13: 417 | S13: 414 | T13: 1016 | U13: 749 | V13: 1438
A14: Total Products revenue | F14: =F11+F12+F13 -> 18117 | G14: =G11+G12+G13 -> 17435 | H14: =H11+H12+H13 -> 20886 | I14: =I11+I12+I13 -> 26277 | J14: =J11+J12+J13 -> 27891 | K14: =K11+K12+K13 -> 30359 | L14: =L11+L12+L13 -> 44847 | O14: =O11+O12+O13 -> 7192 | P14: =P11+P12+P13 -> 7439 | Q14: =Q11+Q12+Q13 -> 8171 | R14: =R11+R12+R13 -> 8506 | S14: =S11+S12+S13 -> 9257 | T14: =T11+T12+T13 -> 14130 | U14: =U11+U12+U13 -> 16892 | V14: =V11+V12+V13 -> 24279
A15: vs IS Products Revenue (should be ~0) | F15: =F14-'Income Statement'!F16 -> 0 | G15: =G14-'Income Statement'!G16 -> 0 | H15: =H14-'Income Statement'!H16 -> 0 | I15: =I14-'Income Statement'!I16 -> 0 | J15: =J14-'Income Statement'!J16 -> 0 | K15: =K14-'Income Statement'!K16 -> 0 | L15: =L14-'Income Statement'!L16 -> 0 | O15: =O14-'Income Statement'!O16 -> 0 | P15: =P14-'Income Statement'!P16 -> 0 | Q15: =Q14-'Income Statement'!Q16 -> 0 | R15: =R14-'Income Statement'!R16 -> 0 | S15: =S14-'Income Statement'!S16 -> 0 | T15: =T14-'Income Statement'!T16 -> 0 | U15: =U14-'Income Statement'!U16 -> 0 | V15: =V14-'Income Statement'!V16 -> 0
A17: Subscriptions & Services — Americas | F17: 3126 | G17: 4059 | H17: 4290 | I17: 4573 | J17: 5678 | K17: 12726 | L17: 11031 | O17: 3401 | P17: 3409 | Q17: 4142 | R17: 4071 | S17: 4062 | T17: 2917 | U17: 3015 | V17: 2871
A18: Subscriptions & Services — Asia Pacific | F18: 374 | G18: 881 | H18: 720 | I18: 744 | J18: 657 | K18: 2203 | L18: 2300 | O18: 487 | P18: 630 | Q18: 763 | R18: 646 | S18: 779 | T18: 665 | U18: 579 | V18: 745
A19: Subscriptions & Services — Europe, Middle East & Africa | F19: 980 | G19: 1513 | H19: 1554 | I19: 1609 | J19: 1593 | K19: 6286 | L19: 5709 | O19: 1407 | P19: 1594 | Q19: 1840 | R19: 1781 | S19: 1854 | T19: 1599 | U19: 1701 | V19: 1696
A20: Total Subscriptions & Services revenue | F20: =F17+F18+F19 -> 4480 | G20: =G17+G18+G19 -> 6453 | H20: =H17+H18+H19 -> 6564 | I20: =I17+I18+I19 -> 6926 | J20: =J17+J18+J19 -> 7928 | K20: =K17+K18+K19 -> 21215 | L20: =L17+L18+L19 -> 19040 | O20: =O17+O18+O19 -> 5295 | P20: =P17+P18+P19 -> 5633 | Q20: =Q17+Q18+Q19 -> 6745 | R20: =R17+R18+R19 -> 6498 | S20: =S17+S18+S19 -> 6695 | T20: =T17+T18+T19 -> 5181 | U20: =U17+U18+U19 -> 5295 | V20: =V17+V18+V19 -> 5312
A21: vs IS Subscriptions Revenue (should be ~0) | F21: =F20-'Income Statement'!F17 -> 0 | G21: =G20-'Income Statement'!G17 -> 0 | H21: =H20-'Income Statement'!H17 -> 0 | I21: =I20-'Income Statement'!I17 -> 0 | J21: =J20-'Income Statement'!J17 -> 0 | K21: =K20-'Income Statement'!K17 -> 0 | L21: =L20-'Income Statement'!L17 -> 0 | O21: =O20-'Income Statement'!O17 -> 0 | P21: =P20-'Income Statement'!P17 -> 0 | Q21: =Q20-'Income Statement'!Q17 -> 0 | R21: =R20-'Income Statement'!R17 -> 0 | S21: =S20-'Income Statement'!S17 -> 0 | T21: =T20-'Income Statement'!T17 -> 0 | U21: =U20-'Income Statement'!U17 -> 0 | V21: =V20-'Income Statement'!V17 -> 0
A23: Total revenue — Americas | F23: =F11+F17 -> 5149 | G23: =G11+G17 -> 5834 | H23: =H11+H17 -> 6099 | I23: =I11+I17 -> 6944 | J23: =J11+J17 -> 8279 | K23: =K11+K17 -> 14970 | L23: =L11+L17 -> 18939 | O23: =O11+O17 -> 3874 | P23: =P11+P17 -> 3991 | Q23: =Q11+Q17 -> 4632 | R23: =R11+R17 -> 4706 | S23: =S11+S17 -> 4724 | T23: =T11+T17 -> 5081 | U23: =U11+U17 -> 5202 | V23: =V11+V17 -> 5513
A24: Total revenue — Asia Pacific | F24: =F12+F18 -> 15231 | G24: =G12+G18 -> 15323 | H24: =H12+H18 -> 17978 | I24: =I12+I18 -> 22505 | J24: =J12+J18 -> 23920 | K24: =K12+K18 -> 28422 | L24: =L12+L18 -> 35896 | O24: =O12+O18 -> 6754 | P24: =P12+P18 -> 7041 | Q24: =Q12+Q18 -> 8032 | R24: =R12+R18 -> 8100 | S24: =S12+S18 -> 8960 | T24: =T12+T18 -> 11615 | U24: =U12+U18 -> 14535 | V24: =V12+V18 -> 20944
A25: Total revenue — Europe, Middle East & Africa | F25: =F13+F19 -> 2217 | G25: =G13+G19 -> 2731 | H25: =H13+H19 -> 3373 | I25: =I13+I19 -> 3754 | J25: =J13+J19 -> 3620 | K25: =K13+K19 -> 8182 | L25: =L13+L19 -> 9052 | O25: =O13+O19 -> 1859 | P25: =P13+P19 -> 2040 | Q25: =Q13+Q19 -> 2252 | R25: =R13+R19 -> 2198 | S25: =S13+S19 -> 2268 | T25: =T13+T19 -> 2615 | U25: =U13+U19 -> 2450 | V25: =V13+V19 -> 3134
A26: Total revenue — All regions | F26: =F23+F24+F25 -> 22597 | G26: =G23+G24+G25 -> 23888 | H26: =H23+H24+H25 -> 27450 | I26: =I23+I24+I25 -> 33203 | J26: =J23+J24+J25 -> 35819 | K26: =K23+K24+K25 -> 51574 | L26: =L23+L24+L25 -> 63887 | O26: =O23+O24+O25 -> 12487 | P26: =P23+P24+P25 -> 13072 | Q26: =Q23+Q24+Q25 -> 14916 | R26: =R23+R24+R25 -> 15004 | S26: =S23+S24+S25 -> 15952 | T26: =T23+T24+T25 -> 19311 | U26: =U23+U24+U25 -> 22187 | V26: =V23+V24+V25 -> 29591
A27: vs IS Total Revenue (should be ~0) | F27: =F26-'Income Statement'!F14 -> 0 | G27: =G26-'Income Statement'!G14 -> 0 | H27: =H26-'Income Statement'!H14 -> 0 | I27: =I26-'Income Statement'!I14 -> 0 | J27: =J26-'Income Statement'!J14 -> 0 | K27: =K26-'Income Statement'!K14 -> 0 | L27: =L26-'Income Statement'!L14 -> 0 | O27: =O26-'Income Statement'!O14 -> 0 | P27: =P26-'Income Statement'!P14 -> 0 | Q27: =Q26-'Income Statement'!Q14 -> 0 | R27: =R26-'Income Statement'!R14 -> 0 | S27: =S26-'Income Statement'!S14 -> 0 | T27: =T26-'Income Statement'!T14 -> 0 | U27: =U26-'Income Statement'!U14 -> 0 | V27: =V26-'Income Statement'!V14 -> 0
A29: Mix % — Americas | F29: =F23/F26 -> 0.22786211 | G29: =G23/G26 -> 0.24422304 | H29: =H23/H26 -> 0.22218579 | I29: =I23/I26 -> 0.20913773 | J29: =J23/J26 -> 0.23113431 | K29: =K23/K26 -> 0.29026254 | L29: =L23/L26 -> 0.29644529 | O29: =O23/O26 -> 0.31024265 | P29: =P23/P26 -> 0.30530906 | Q29: =Q23/Q26 -> 0.31053902 | R29: =R23/R26 -> 0.31364969 | S29: =S23/S26 -> 0.29613842 | T29: =T23/T26 -> 0.26311429 | U29: =U23/U26 -> 0.23446162 | V29: =V23/V26 -> 0.18630665
A30: Mix % — Asia Pacific | F30: =F24/F26 -> 0.67402753 | G30: =G24/G26 -> 0.64145177 | H30: =H24/H26 -> 0.65493625 | I30: =I24/I26 -> 0.6778002 | J30: =J24/J26 -> 0.667802 | K30: =K24/K26 -> 0.55109164 | L30: =L24/L26 -> 0.56186705 | O30: =O24/O26 -> 0.54088252 | P30: =P24/P26 -> 0.53863219 | Q30: =Q24/Q26 -> 0.53848217 | R30: =R24/R26 -> 0.53985604 | S30: =S24/S26 -> 0.56168506 | T30: =T24/T26 -> 0.60147066 | U30: =U24/U26 -> 0.65511335 | V30: =V24/V26 -> 0.70778277
A31: Mix % — Europe, Middle East & Africa | F31: =F25/F26 -> 0.098110369 | G31: =G25/G26 -> 0.11432518 | H31: =H25/H26 -> 0.12287796 | I31: =I25/I26 -> 0.11306207 | J31: =J25/J26 -> 0.10106368 | K31: =K25/K26 -> 0.15864583 | L31: =L25/L26 -> 0.14168767 | O31: =O25/O26 -> 0.14887483 | P31: =P25/P26 -> 0.15605875 | Q31: =Q25/Q26 -> 0.15097881 | R31: =R25/R26 -> 0.14649427 | S31: =S25/S26 -> 0.14217653 | T31: =T25/T26 -> 0.13541505 | U31: =U25/U26 -> 0.11042502 | V31: =V25/V26 -> 0.10591058
A33: 2. LONG-LIVED ASSETS BY GEOGRAPHY (Annual only — disclosed in the 10-K only, not in 10-Qs)
A34: United States | B34: This Note (long-lived assets by geographic location) is disclosed only in Broadcom's annual 10-K, not in its 10-Qs -- quarterly columns are intentionally blank by the nature of the disclosure, not a dropped extraction. Own fiscal-year-end figures each time (never a later filing's restated comparative column). | C34: 1917 | D34: 1822 | E34: 1859 | F34: 1763 | G34: 1659 | H34: 1540 | I34: 1441 | J34: 1371 | K34: 1685 | L34: 1697
A35: Malaysia | C35: 153
A36: Singapore | C36: 78 | D36: 79
A37: Taiwan | D37: 268 | E37: 264 | F37: 258 | G37: 285 | H37: 313 | I37: 318 | J37: 341 | K37: 365 | L37: 446
A38: Other | C38: 361 | D38: 430 | E38: 512 | F38: 544 | G38: 565 | H38: 495 | I38: 464 | J38: 442 | K38: 471 | L38: 387
A39: Total long-lived assets (computed) | C39: =C34+C35+C36+C37+C38 -> 2509 | D39: =D34+D35+D36+D37+D38 -> 2599 | E39: =E34+E35+E36+E37+E38 -> 2635 | F39: =F34+F35+F36+F37+F38 -> 2565 | G39: =G34+G35+G36+G37+G38 -> 2509 | H39: =H34+H35+H36+H37+H38 -> 2348 | I39: =I34+I35+I36+I37+I38 -> 2223 | J39: =J34+J35+J36+J37+J38 -> 2154 | ... L39: =L34+L35+L36+L37+L38 -> 2530
A40: Total long-lived assets (as reported) | C40: 2509 | D40: 2599 | E40: 2635 | F40: 2565 | G40: 2509 | H40: 2348 | I40: 2223 | J40: 2154 | K40: 2521 | L40: 2530
A41: Computed vs Reported (should be ~0) | C41: =C39-C40 -> 0 | D41: =D39-D40 -> 0 | E41: =E39-E40 -> 0 | F41: =F39-F40 -> 0 | G41: =G39-G40 -> 0 | H41: =H39-H40 -> 0 | I41: =I39-I40 -> 0 | J41: =J39-J40 -> 0 | ... L41: =L39-L40 -> 0

Sheet Derived Metrics
A1: Broadcom Inc. — Derived Metrics
A2: $ in millions except per-share data | USD | as of 2026-09-22
C3: FY2016 | D3: FY2017 | E3: FY2018 | F3: FY2019 | G3: FY2020 | H3: FY2021 | I3: FY2022 | J3: FY2023 | K3: FY2024 | L3: FY2025 | M3: · | N3: · | O3: 2Q FY2024 | P3: 3Q FY2024 | Q3: 1Q FY2025 | R3: 2Q FY2025 | S3: 3Q FY2025 | T3: 1Q FY2026 | U3: 2Q FY2026 | V3: 3Q FY2026
C4: 2016-10-30 | D4: 2017-10-29 | E4: 2018-11-04 | F4: 2019-11-03 | G4: 2020-11-01 | H4: 2021-10-31 | I4: 2022-10-30 | J4: 2023-10-29 | K4: 2024-11-03 | L4: 2025-11-02 | O4: 2024-05-05 | P4: 2024-08-04 | Q4: 2025-02-02 | R4: 2025-05-04 | S4: 2025-08-03 | T4: 2026-02-01 | U4: 2026-05-03 | V4: 2026-08-02
A6: CONTENTS
A7: =HYPERLINK("#'Derived Metrics'!A18","1. PROFITABILITY") -> 1. PROFITABILITY
A8: =HYPERLINK("#'Derived Metrics'!A25","2. RETURNS") -> 2. RETURNS
A9: =HYPERLINK("#'Derived Metrics'!A30","3. LEVERAGE") -> 3. LEVERAGE
A10: =HYPERLINK("#'Derived Metrics'!A35","4. SOLVENCY") -> 4. SOLVENCY
A11: =HYPERLINK("#'Derived Metrics'!A39","5. LIQUIDITY") -> 5. LIQUIDITY
A12: =HYPERLINK("#'Derived Metrics'!A43","6. COVERAGE") -> 6. COVERAGE
A13: =HYPERLINK("#'Derived Metrics'!A46","7. CASH CONVERSION") -> 7. CASH CONVERSION
A14: =HYPERLINK("#'Derived Metrics'!A51","8. EARNINGS QUALITY") -> 8. EARNINGS QUALITY
A15: =HYPERLINK("#'Derived Metrics'!A54","9. GROWTH") -> 9. GROWTH
A16: =HYPERLINK("#'Derived Metrics'!A60","10. WORKING CAPITAL") -> 10. WORKING CAPITAL
A18: 1. PROFITABILITY
A19: Gross Margin % | C19: ='Income Statement'!C28 -> 0.44864048 | D19: ='Income Statement'!D28 -> 0.48247902 | E19: ='Income Statement'!E28 -> 0.51482157 | F19: ='Income Statement'!F28 -> 0.55241846 | G19: ='Income Statement'!G28 -> 0.5658071 | H19: ='Income Statement'!H28 -> 0.61362477 | I19: ='Income Statement'!I28 -> 0.66545192 | J19: ='Income Statement'!J28 -> 0.68929898 | ... L19: ='Income Statement'!L28 -> 0.67766525 | O19: ='Income Statement'!O28 -> 0.62272764 | P19: ='Income Statement'!P28 -> 0.63922889 | Q19: ='Income Statement'!Q28 -> 0.68014213 | R19: ='Income Statement'!R28 -> 0.67961877 | S19: ='Income Statement'!S28 -> 0.67095035 | T19: ='Income Statement'!T28 -> 0.68132153 | U19: ='Income Statement'!U28 -> 0.69477622 | V19: ='Income Statement'!V28 -> 0.69129127
A20: Operating Margin % | C20: ='Income Statement'!C38 -> -0.030891239 | D20: ='Income Statement'!D38 -> 0.13512134 | E20: ='Income Statement'!E38 -> 0.2463066 | F20: ='Income Statement'!F38 -> 0.15240961 | G20: ='Income Statement'!G38 -> 0.16803416 | H20: ='Income Statement'!H38 -> 0.31034608 | I20: ='Income Statement'!I38 -> 0.42842514 | J20: ='Income Statement'!J38 -> 0.45246936 | ... L20: ='Income Statement'!L38 -> 0.39889179 | O20: ='Income Statement'!O38 -> 0.23744694 | P20: ='Income Statement'!P38 -> 0.28977968 | Q20: ='Income Statement'!Q38 -> 0.41968356 | R20: ='Income Statement'!R38 -> 0.3884964 | S20: ='Income Statement'!S38 -> 0.36904463 | T20: ='Income Statement'!T38 -> 0.44342603 | U20: ='Income Statement'!U38 -> 0.48623068 | V20: ='Income Statement'!V38 -> 0.53918421
A21: Net Margin % | C21: ='Income Statement'!C51 -> -0.14055891 | D21: ='Income Statement'!D51 -> 0.10115672 | E21: ='Income Statement'!E51 -> 0.60485418 | F21: ='Income Statement'!F51 -> 0.12054698 | G21: ='Income Statement'!G51 -> 0.12391159 | H21: ='Income Statement'!H51 -> 0.24539162 | I21: ='Income Statement'!I51 -> 0.34620366 | J21: ='Income Statement'!J51 -> 0.3931433 | ... L21: ='Income Statement'!L51 -> 0.36198288 | O21: ='Income Statement'!O51 -> 0.16985665 | P21: ='Income Statement'!P51 -> -0.14343635 | Q21: ='Income Statement'!Q51 -> 0.36893269 | R21: ='Income Statement'!R51 -> 0.33091176 | S21: ='Income Statement'!S51 -> 0.25952859 | T21: ='Income Statement'!T51 -> 0.3805603 | U21: ='Income Statement'!U51 -> 0.41961509 | V21: ='Income Statement'!V51 -> 0.44229664
A22: EBITDA | C22: ='Income Statement'!C37+'Cash Flow Statement'!C16+'Cash Flow Statement'!C17 -> 2633 | D22: ='Income Statement'!D37+'Cash Flow Statement'!D16+'Cash Flow Statement'!D17 -> 7120 | E22: ='Income Statement'!E37+'Cash Flow Statement'!E16+'Cash Flow Statement'!E17 -> 9216 | F22: ='Income Statement'!F37+'Cash Flow Statement'!F16+'Cash Flow Statement'!F17 -> 9252 | G22: ='Income Statement'!G37+'Cash Flow Statement'!G16+'Cash Flow Statement'!G17 -> 10919 | H22: ='Income Statement'!H37+'Cash Flow Statement'!H16+'Cash Flow Statement'!H17 -> 14560 | I22: ='Income Statement'!I37+'Cash Flow Statement'!I16+'Cash Flow Statement'!I17 -> 19209 | J22: ='Income Statement'!J37+'Cash Flow Statement'!J16+'Cash Flow Statement'!J17 -> 20042 | ... L22: ='Income Statement'!L37+'Cash Flow Statement'!L16+'Cash Flow Statement'!L17 -> 34259 | O22: ='Income Statement'!O37+'Cash Flow Statement'!O16+'Cash Flow Statement'!O17 -> 7840 | P22: ='Income Statement'!P37+'Cash Flow Statement'!P16+'Cash Flow Statement'!P17 -> 11187 | Q22: ='Income Statement'!Q37+'Cash Flow Statement'!Q16+'Cash Flow Statement'!Q17 -> 8434 | R22: ='Income Statement'!R37+'Cash Flow Statement'!R16+'Cash Flow Statement'!R17 -> 10169 | S22: ='Income Statement'!S37+'Cash Flow Statement'!S16+'Cash Flow Statement'!S17 -> 12429 | T22: ='Income Statement'!T37+'Cash Flow Statement'!T16+'Cash Flow Statement'!T17 -> 10716 | U22: ='Income Statement'!U37+'Cash Flow Statement'!U16+'Cash Flow Statement'!U17 -> 15106 | V22: ='Income Statement'!V37+'Cash Flow Statement'!V16+'Cash Flow Statement'!V17 -> 22486
A23: EBITDA Margin % | C23: =C22/'Income Statement'!C14 -> 0.19886707 | D23: =D22/'Income Statement'!D14 -> 0.40371966 | E23: =E22/'Income Statement'!E14 -> 0.44205679 | F23: =F22/'Income Statement'!F14 -> 0.40943488 | G23: =G22/'Income Statement'!G14 -> 0.45709143 | H23: =H22/'Income Statement'!H14 -> 0.53041894 | I23: =I22/'Income Statement'!I14 -> 0.57853206 | J23: =J22/'Income Statement'!J14 -> 0.55953544 | ... L23: =L22/'Income Statement'!L14 -> 0.53624368 | O23: =O22/'Income Statement'!O14 -> 0.62785297 | P23: =P22/'Income Statement'!P14 -> 0.85579865 | Q23: =Q22/'Income Statement'!Q14 -> 0.56543309 | R23: =R22/'Income Statement'!R14 -> 0.6777526 | S23: =S22/'Income Statement'!S14 -> 0.77914995 | T23: =T22/'Income Statement'!T14 -> 0.55491689 | U23: =U22/'Income Statement'!U14 -> 0.68084915 | V23: =V22/'Income Statement'!V14 -> 0.75989321
A25: 2. RETURNS
A26: Return on Equity (avg) | D26: ='Income Statement'!D50/(('Balance Sheet'!D48+'Balance Sheet'!C48)/2) -> 0.079179797 | E26: ='Income Statement'!E50/(('Balance Sheet'!E48+'Balance Sheet'!D48)/2) -> 0.5059888 | F26: ='Income Statement'!F50/(('Balance Sheet'!F48+'Balance Sheet'!E48)/2) -> 0.10558549 | G26: ='Income Statement'!G50/(('Balance Sheet'!G48+'Balance Sheet'!F48)/2) -> 0.1212742 | H26: ='Income Statement'!H50/(('Balance Sheet'!H48+'Balance Sheet'!G48)/2) -> 0.27586207 | I26: ='Income Statement'!I50/(('Balance Sheet'!I48+'Balance Sheet'!H48)/2) -> 0.48226385 | J26: ='Income Statement'!J50/(('Balance Sheet'!J48+'Balance Sheet'!I48)/2) -> 0.60312226 | K26: ='Income Statement'!K50/(('Balance Sheet'!K48+'Balance Sheet'!J48)/2) -> 0.12861912 | L26: ='Income Statement'!L50/(('Balance Sheet'!L48+'Balance Sheet'!K48)/2) -> 0.31047862
A27: Return on Assets (avg) | D27: ='Income Statement'!D50/(('Balance Sheet'!D26+'Balance Sheet'!C26)/2) -> 0.034181484 | E27: ='Income Statement'!E50/(('Balance Sheet'!E26+'Balance Sheet'!D26)/2) -> 0.24124275 | F27: ='Income Statement'!F50/(('Balance Sheet'!F26+'Balance Sheet'!E26)/2) -> 0.046319835 | G27: ='Income Statement'!G50/(('Balance Sheet'!G26+'Balance Sheet'!F26)/2) -> 0.04127564 | H27: ='Income Statement'!H50/(('Balance Sheet'!H26+'Balance Sheet'!G26)/2) -> 0.088922332 | I27: ='Income Statement'!I50/(('Balance Sheet'!I26+'Balance Sheet'!H26)/2) -> 0.15448296 | J27: ='Income Statement'!J50/(('Balance Sheet'!J26+'Balance Sheet'!I26)/2) -> 0.19275888 | K27: ='Income Statement'!K50/(('Balance Sheet'!K26+'Balance Sheet'!J26)/2) -> 0.049432719 | L27: ='Income Statement'!L50/(('Balance Sheet'!L26+'Balance Sheet'!K26)/2) -> 0.13735348
A28: Return on Invested Capital (approx.) | B28: NOPAT = operating income - as-reported income tax provision (Income Statement row 47); invested capital = total debt + total equity - cash. No assumed or normalized tax rate is applied. | C28: =('Income Statement'!C37-'Income Statement'!C47)/('Balance Sheet'!C36+'Balance Sheet'!C31+'Balance Sheet'!C48-'Balance Sheet'!C15) -> -0.03241726 | D28: =('Income Statement'!D37-'Income Statement'!D47)/('Balance Sheet'!D36+'Balance Sheet'!D31+'Balance Sheet'!D48-'Balance Sheet'!D15) -> 0.07951236 | E28: =('Income Statement'!E37-'Income Statement'!E47)/('Balance Sheet'!E36+'Balance Sheet'!E31+'Balance Sheet'!E48-'Balance Sheet'!E15) -> 0.33165237 | F28: =('Income Statement'!F37-'Income Statement'!F47)/('Balance Sheet'!F36+'Balance Sheet'!F31+'Balance Sheet'!F48-'Balance Sheet'!F15) -> 0.075051249 | G28: =('Income Statement'!G37-'Income Statement'!G47)/('Balance Sheet'!G36+'Balance Sheet'!G31+'Balance Sheet'!G48-'Balance Sheet'!G15) -> 0.079067658 | H28: =('Income Statement'!H37-'Income Statement'!H47)/('Balance Sheet'!H36+'Balance Sheet'!H31+'Balance Sheet'!H48-'Balance Sheet'!H15) -> 0.16162501 | I28: =('Income Statement'!I37-'Income Statement'!I47)/('Balance Sheet'!I36+'Balance Sheet'!I31+'Balance Sheet'!I48-'Balance Sheet'!I15) -> 0.2667443 | J28: =('Income Statement'!J37-'Income Statement'!J47)/('Balance Sheet'!J36+'Balance Sheet'!J31+'Balance Sheet'!J48-'Balance Sheet'!J15) -> 0.30986375 | ... L28: =('Income Statement'!L37-'Income Statement'!L47)/('Balance Sheet'!L36+'Balance Sheet'!L31+'Balance Sheet'!L48-'Balance Sheet'!L15) -> 0.1987025 | O28: =('Income Statement'!O37-'Income Statement'!O47)/('Balance Sheet'!O36+'Balance Sheet'!O31+'Balance Sheet'!O48-'Balance Sheet'!O15) -> 0.022963747 | P28: =('Income Statement'!P37-'Income Statement'!P47)/('Balance Sheet'!P36+'Balance Sheet'!P31+'Balance Sheet'!P48-'Balance Sheet'!P15) -> -0.0035811488 | Q28: =('Income Statement'!Q37-'Income Statement'!Q47)/('Balance Sheet'!Q36+'Balance Sheet'!Q31+'Balance Sheet'!Q48-'Balance Sheet'!Q15) -> 0.049369988 | R28: =('Income Statement'!R37-'Income Statement'!R47)/('Balance Sheet'!R36+'Balance Sheet'!R31+'Balance Sheet'!R48-'Balance Sheet'!R15) -> 0.044813024 | S28: =('Income Statement'!S37-'Income Statement'!S47)/('Balance Sheet'!S36+'Balance Sheet'!S31+'Balance Sheet'!S48-'Balance Sheet'!S15) -> 0.037401016 | T28: =('Income Statement'!T37-'Income Statement'!T47)/('Balance Sheet'!T36+'Balance Sheet'!T31+'Balance Sheet'!T48-'Balance Sheet'!T15) -> 0.058570832 | U28: =('Income Statement'!U37-'Income Statement'!U47)/('Balance Sheet'!U36+'Balance Sheet'!U31+'Balance Sheet'!U48-'Balance Sheet'!U15) -> 0.074964278 | V28: =('Income Statement'!V37-'Income Statement'!V47)/('Balance Sheet'!V36+'Balance Sheet'!V31+'Balance Sheet'!V48-'Balance Sheet'!V15) -> 0.10188406
A30: 3. LEVERAGE
A31: Total Debt / Equity | C31: =('Balance Sheet'!C36+'Balance Sheet'!C31)/'Balance Sheet'!C48 -> 0.62360578 | D31: =('Balance Sheet'!D36+'Balance Sheet'!D31)/'Balance Sheet'!D48 -> 0.75683602 | E31: =('Balance Sheet'!E36+'Balance Sheet'!E31)/'Balance Sheet'!E48 -> 0.65622538 | F31: =('Balance Sheet'!F36+'Balance Sheet'!F31)/'Balance Sheet'!F48 -> 1.3150235 | G31: =('Balance Sheet'!G36+'Balance Sheet'!G31)/'Balance Sheet'!G48 -> 1.7199464 | H31: =('Balance Sheet'!H36+'Balance Sheet'!H31)/'Balance Sheet'!H48 -> 1.5916193 | I31: =('Balance Sheet'!I36+'Balance Sheet'!I31)/'Balance Sheet'!I48 -> 1.740059 | J31: =('Balance Sheet'!J36+'Balance Sheet'!J31)/'Balance Sheet'!J48 -> 1.6353593 | ... L31: =('Balance Sheet'!L36+'Balance Sheet'!L31)/'Balance Sheet'!L48 -> 0.80125966 | O31: =('Balance Sheet'!O36+'Balance Sheet'!O31)/'Balance Sheet'!O48 -> 1.0579609 | P31: =('Balance Sheet'!P36+'Balance Sheet'!P31)/'Balance Sheet'!P48 -> 1.0656197 | Q31: =('Balance Sheet'!Q36+'Balance Sheet'!Q31)/'Balance Sheet'!Q48 -> 0.95400421 | R31: =('Balance Sheet'!R36+'Balance Sheet'!R31)/'Balance Sheet'!R48 -> 0.96688989 | S31: =('Balance Sheet'!S36+'Balance Sheet'!S31)/'Balance Sheet'!S48 -> 0.87652333 | T31: =('Balance Sheet'!T36+'Balance Sheet'!T31)/'Balance Sheet'!T48 -> 0.82703576 | U31: =('Balance Sheet'!U36+'Balance Sheet'!U31)/'Balance Sheet'!U48 -> 0.74017858 | V31: =('Balance Sheet'!V36+'Balance Sheet'!V31)/'Balance Sheet'!V48 -> 0.59603772
A32: Total Debt / EBITDA | C32: =('Balance Sheet'!C36+'Balance Sheet'!C31)/C22 -> 5.1811622 | D32: =('Balance Sheet'!D36+'Balance Sheet'!D31)/D22 -> 2.4646067 | E32: =('Balance Sheet'!E36+'Balance Sheet'!E31)/E22 -> 1.898112 | F32: =('Balance Sheet'!F36+'Balance Sheet'!F31)/F22 -> 3.5449633 | G32: =('Balance Sheet'!G36+'Balance Sheet'!G31)/G22 -> 3.7606008 | H32: =('Balance Sheet'!H36+'Balance Sheet'!H31)/H22 -> 2.7287088 | I32: =('Balance Sheet'!I36+'Balance Sheet'!I31)/I22 -> 2.0571086 | J32: =('Balance Sheet'!J36+'Balance Sheet'!J31)/J22 -> 1.9573396 | ... L32: =('Balance Sheet'!L36+'Balance Sheet'!L31)/L22 -> 1.9012814 | O32: =('Balance Sheet'!O36+'Balance Sheet'!O31)/O22 -> 9.4408163 | P32: =('Balance Sheet'!P36+'Balance Sheet'!P31)/P22 -> 6.2535979 | Q32: =('Balance Sheet'!Q36+'Balance Sheet'!Q31)/Q22 -> 7.894119 | R32: =('Balance Sheet'!R36+'Balance Sheet'!R31)/R22 -> 6.6163831 | S32: =('Balance Sheet'!S36+'Balance Sheet'!S31)/S22 -> 5.1676724 | T32: =('Balance Sheet'!T36+'Balance Sheet'!T31)/T22 -> 6.1643337 | U32: =('Balance Sheet'!U36+'Balance Sheet'!U31)/U22 -> 4.2967695 | V32: =('Balance Sheet'!V36+'Balance Sheet'!V31)/V22 -> 2.6424887
A33: Net Debt / EBITDA | C33: =('Balance Sheet'!C36+'Balance Sheet'!C31-'Balance Sheet'!C15)/C22 -> 4.0049373 | D33: =('Balance Sheet'!D36+'Balance Sheet'!D31-'Balance Sheet'!D15)/D22 -> 0.89101124 | E33: =('Balance Sheet'!E36+'Balance Sheet'!E31-'Balance Sheet'!E15)/E22 -> 1.4324002 | F33: =('Balance Sheet'!F36+'Balance Sheet'!F31-'Balance Sheet'!F15)/F22 -> 2.9985949 | G33: =('Balance Sheet'!G36+'Balance Sheet'!G31-'Balance Sheet'!G15)/G22 -> 3.0629178 | H33: =('Balance Sheet'!H36+'Balance Sheet'!H31-'Balance Sheet'!H15)/H22 -> 1.8933379 | I33: =('Balance Sheet'!I36+'Balance Sheet'!I31-'Balance Sheet'!I15)/I22 -> 1.410745 | J33: =('Balance Sheet'!J36+'Balance Sheet'!J31-'Balance Sheet'!J15)/J22 -> 1.2493763 | ... L33: =('Balance Sheet'!L36+'Balance Sheet'!L31-'Balance Sheet'!L15)/L22 -> 1.4290551 | O33: =('Balance Sheet'!O36+'Balance Sheet'!O31-'Balance Sheet'!O15)/O22 -> 8.1896684 | P33: =('Balance Sheet'!P36+'Balance Sheet'!P31-'Balance Sheet'!P15)/P22 -> 5.3639939 | Q33: =('Balance Sheet'!Q36+'Balance Sheet'!Q31-'Balance Sheet'!Q15)/Q22 -> 6.7906094 | R33: =('Balance Sheet'!R36+'Balance Sheet'!R31-'Balance Sheet'!R15)/R22 -> 5.6849248 | S33: =('Balance Sheet'!S36+'Balance Sheet'!S31-'Balance Sheet'!S15)/S22 -> 4.3053343 | T33: =('Balance Sheet'!T36+'Balance Sheet'!T31-'Balance Sheet'!T15)/T22 -> 4.8416387 | U33: =('Balance Sheet'!U36+'Balance Sheet'!U31-'Balance Sheet'!U15)/U22 -> 2.9974182 | V33: =('Balance Sheet'!V36+'Balance Sheet'!V31-'Balance Sheet'!V15)/V22 -> 1.5762697
A35: 4. SOLVENCY
A36: Total Liabilities / Total Assets | C36: ='Balance Sheet'!C39/'Balance Sheet'!C26 -> 0.56218228 | D36: ='Balance Sheet'!D39/'Balance Sheet'!D26 -> 0.57392774 | E36: ='Balance Sheet'!E39/'Balance Sheet'!E26 -> 0.46817892 | F36: ='Balance Sheet'!F39/'Balance Sheet'!F26 -> 0.63003571 | G36: ='Balance Sheet'!G39/'Balance Sheet'!G26 -> 0.68523567 | H36: ='Balance Sheet'!H39/'Balance Sheet'!H26 -> 0.66932645 | I36: ='Balance Sheet'!I39/'Balance Sheet'!I26 -> 0.68997529 | J36: ='Balance Sheet'!J39/'Balance Sheet'!J26 -> 0.67077037 | ... L36: ='Balance Sheet'!L39/'Balance Sheet'!L26 -> 0.52486382 | O36: ='Balance Sheet'!O39/'Balance Sheet'!O26 -> 0.60070429 | P36: ='Balance Sheet'!P39/'Balance Sheet'!P26 -> 0.60914114 | Q36: ='Balance Sheet'!Q39/'Balance Sheet'!Q26 -> 0.57795208 | R36: ='Balance Sheet'!R39/'Balance Sheet'!R26 -> 0.57731884 | S36: ='Balance Sheet'!S39/'Balance Sheet'!S26 -> 0.55756214 | T36: ='Balance Sheet'!T39/'Balance Sheet'!T26 -> 0.52989647 | U36: ='Balance Sheet'!U39/'Balance Sheet'!U26 -> 0.51053818 | V36: ='Balance Sheet'!V39/'Balance Sheet'!V26 -> 0.47015116
A37: Total Equity / Total Assets | C37: ='Balance Sheet'!C48/'Balance Sheet'!C26 -> 0.43781772 | D37: ='Balance Sheet'!D48/'Balance Sheet'!D26 -> 0.42607226 | E37: ='Balance Sheet'!E48/'Balance Sheet'!E26 -> 0.53182108 | F37: ='Balance Sheet'!F48/'Balance Sheet'!F26 -> 0.36953462 | G37: ='Balance Sheet'!G48/'Balance Sheet'!G26 -> 0.31440876 | H37: ='Balance Sheet'!H48/'Balance Sheet'!H26 -> 0.33031626 | I37: ='Balance Sheet'!I48/'Balance Sheet'!I26 -> 0.31002471 | J37: ='Balance Sheet'!J48/'Balance Sheet'!J26 -> 0.32922963 | ... L37: ='Balance Sheet'!L48/'Balance Sheet'!L26 -> 0.47513618 | O37: ='Balance Sheet'!O48/'Balance Sheet'!O26 -> 0.39929571 | P37: ='Balance Sheet'!P48/'Balance Sheet'!P26 -> 0.39085886 | Q37: ='Balance Sheet'!Q48/'Balance Sheet'!Q26 -> 0.42204792 | R37: ='Balance Sheet'!R48/'Balance Sheet'!R26 -> 0.42268116 | S37: ='Balance Sheet'!S48/'Balance Sheet'!S26 -> 0.44243786 | T37: ='Balance Sheet'!T48/'Balance Sheet'!T26 -> 0.47010353 | U37: ='Balance Sheet'!U48/'Balance Sheet'!U26 -> 0.48946182 | V37: ='Balance Sheet'!V48/'Balance Sheet'!V26 -> 0.52984884
A39: 5. LIQUIDITY
A40: Current Ratio | C40: ='Balance Sheet'!C19/'Balance Sheet'!C33 -> 2.3148148 | D40: ='Balance Sheet'!D19/'Balance Sheet'!D33 -> 6.2566232 | E40: ='Balance Sheet'!E19/'Balance Sheet'!E33 -> 3.8952096 | F40: ='Balance Sheet'!F19/'Balance Sheet'!F33 -> 1.4374547 | G40: ='Balance Sheet'!G19/'Balance Sheet'!G33 -> 1.8670538 | H40: ='Balance Sheet'!H19/'Balance Sheet'!H33 -> 2.6406623 | I40: ='Balance Sheet'!I19/'Balance Sheet'!I33 -> 2.6239365 | J40: ='Balance Sheet'!J19/'Balance Sheet'!J33 -> 2.81526 | ... L40: ='Balance Sheet'!L19/'Balance Sheet'!L33 -> 1.7053581 | O40: ='Balance Sheet'!O19/'Balance Sheet'!O33 -> 1.2543751 | P40: ='Balance Sheet'!P19/'Balance Sheet'!P33 -> 1.0377712 | Q40: ='Balance Sheet'!Q19/'Balance Sheet'!Q33 -> 1.0038259 | R40: ='Balance Sheet'!R19/'Balance Sheet'!R33 -> 1.0769044 | S40: ='Balance Sheet'!S19/'Balance Sheet'!S33 -> 1.4965278 | T40: ='Balance Sheet'!T19/'Balance Sheet'!T33 -> 1.9017735 | U40: ='Balance Sheet'!U19/'Balance Sheet'!U33 -> 2.2379917 | V40: ='Balance Sheet'!V19/'Balance Sheet'!V33 -> 2.5037432
A41: Quick Ratio | C41: =('Balance Sheet'!C19-'Balance Sheet'!C17)/'Balance Sheet'!C33 -> 1.859974 | D41: =('Balance Sheet'!D19-'Balance Sheet'!D17)/'Balance Sheet'!D33 -> 5.6844603 | E41: =('Balance Sheet'!E19-'Balance Sheet'!E17)/'Balance Sheet'!E33 -> 3.4144568 | F41: =('Balance Sheet'!F19-'Balance Sheet'!F17)/'Balance Sheet'!F33 -> 1.3107697 | G41: =('Balance Sheet'!G19-'Balance Sheet'!G17)/'Balance Sheet'!G33 -> 1.7096217 | H41: =('Balance Sheet'!H19-'Balance Sheet'!H17)/'Balance Sheet'!H33 -> 2.4341665 | I41: =('Balance Sheet'!I19-'Balance Sheet'!I17)/'Balance Sheet'!I33 -> 2.3509643 | J41: =('Balance Sheet'!J19-'Balance Sheet'!J17)/'Balance Sheet'!J33 -> 2.5589467 | ... L41: =('Balance Sheet'!L19-'Balance Sheet'!L17)/'Balance Sheet'!L33 -> 1.5827482 | O41: =('Balance Sheet'!O19-'Balance Sheet'!O17)/'Balance Sheet'!O33 -> 1.1630559 | P41: =('Balance Sheet'!P19-'Balance Sheet'!P17)/'Balance Sheet'!P33 -> 0.93923313 | Q41: =('Balance Sheet'!Q19-'Balance Sheet'!Q17)/'Balance Sheet'!Q33 -> 0.91257771 | R41: =('Balance Sheet'!R19-'Balance Sheet'!R17)/'Balance Sheet'!R33 -> 0.97897752 | S41: =('Balance Sheet'!S19-'Balance Sheet'!S17)/'Balance Sheet'!S33 -> 1.3660201 | T41: =('Balance Sheet'!T19-'Balance Sheet'!T17)/'Balance Sheet'!T33 -> 1.726081 | U41: =('Balance Sheet'!U19-'Balance Sheet'!U17)/'Balance Sheet'!U33 -> 2.0085357 | V41: =('Balance Sheet'!V19-'Balance Sheet'!V17)/'Balance Sheet'!V33 -> 2.2866878
A43: 6. COVERAGE
A44: Interest Coverage (Operating Income / Interest Expense) | C44: ='Income Statement'!C37/(0-'Income Statement'!C42) -> -0.6991453 | D44: ='Income Statement'!D37/(0-'Income Statement'!D42) -> 5.2488987 | E44: ='Income Statement'!E37/(0-'Income Statement'!E42) -> 8.1767516 | F44: ='Income Statement'!F37/(0-'Income Statement'!F42) -> 2.3850416 | G44: ='Income Statement'!G37/(0-'Income Statement'!G42) -> 2.2588633 | H44: ='Income Statement'!H37/(0-'Income Statement'!H42) -> 4.5193634 | I44: ='Income Statement'!I37/(0-'Income Statement'!I42) -> 8.189407 | J44: ='Income Statement'!J37/(0-'Income Statement'!J42) -> 9.9919852 | ... L44: ='Income Statement'!L37/(0-'Income Statement'!L42) -> 7.9389408 | O44: ='Income Statement'!O37/(0-'Income Statement'!O42) -> 2.8319007 | P44: ='Income Statement'!P37/(0-'Income Statement'!P42) -> 3.5601504 | Q44: ='Income Statement'!Q37/(0-'Income Statement'!Q42) -> 7.1706758 | R44: ='Income Statement'!R37/(0-'Income Statement'!R42) -> 7.579974 | S44: ='Income Statement'!S37/(0-'Income Statement'!S42) -> 7.2949195 | T44: ='Income Statement'!T37/(0-'Income Statement'!T42) -> 10.690387 | U44: ='Income Statement'!U37/(0-'Income Statement'!U42) -> 13.902062 | V44: ='Income Statement'!V37/(0-'Income Statement'!V42) -> 20.507712
A46: 7. CASH CONVERSION
A47: FCF Margin % | C47: ='Cash Flow Statement'!C71 -> 0.20302115 | D47: ='Cash Flow Statement'!D71 -> 0.31084146 | E47: ='Cash Flow Statement'!E71 -> 0.39548158 | F47: ='Cash Flow Statement'!F71 -> 0.41001018 | G47: ='Cash Flow Statement'!G71 -> 0.48551574 | H47: ='Cash Flow Statement'!H71 -> 0.48528233 | I47: ='Cash Flow Statement'!I71 -> 0.49128091 | J47: ='Cash Flow Statement'!J71 -> 0.49228063 | ... L47: ='Cash Flow Statement'!L71 -> 0.42127506 | O47: ='Cash Flow Statement'!O71 -> 0.73204132 | P47: ='Cash Flow Statement'!P71 -> 1.0657895 | Q47: ='Cash Flow Statement'!Q71 -> 0.40312416 | R47: ='Cash Flow Statement'!R71 -> 0.82804585 | S47: ='Cash Flow Statement'!S71 -> 1.2191575 | T47: ='Cash Flow Statement'!T71 -> 0.4147895 | U47: ='Cash Flow Statement'!U71 -> 0.82354532 | V47: ='Cash Flow Statement'!V71 -> 1.0792809
A48: FCF Conversion (FCF / Net Income) | C48: ='Cash Flow Statement'!C72 -> -1.4443847 | D48: ='Cash Flow Statement'!D72 -> 3.07287 | E48: ='Cash Flow Statement'!E72 -> 0.65384615 | F48: ='Cash Flow Statement'!F72 -> 3.4012482 | G48: ='Cash Flow Statement'!G72 -> 3.9182432 | H48: ='Cash Flow Statement'!H72 -> 1.9775831 | I48: ='Cash Flow Statement'!I72 -> 1.4190518 | J48: ='Cash Flow Statement'!J72 -> 1.2521659 | ... L48: ='Cash Flow Statement'!L72 -> 1.1637983 | O48: ='Cash Flow Statement'!O72 -> 4.3097595 | P48: ='Cash Flow Statement'!P72 -> -7.4304 | Q48: ='Cash Flow Statement'!Q72 -> 1.0926767 | R48: ='Cash Flow Statement'!R72 -> 2.5023162 | S48: ='Cash Flow Statement'!S72 -> 4.6975845 | T48: ='Cash Flow Statement'!T72 -> 1.0899442 | U48: ='Cash Flow Statement'!U72 -> 1.9626208 | V48: ='Cash Flow Statement'!V72 -> 2.4401742
A49: CFO / Net Income | C49: ='Cash Flow Statement'!C33/'Income Statement'!C50 -> -1.8328855 | D49: ='Cash Flow Statement'!D33/'Income Statement'!D50 -> 3.6720852 | E49: ='Cash Flow Statement'!E33/'Income Statement'!E50 -> 0.70420301 | F49: ='Cash Flow Statement'!F33/'Income Statement'!F50 -> 3.5598385 | G49: ='Cash Flow Statement'!G33/'Income Statement'!G50 -> 4.0746622 | H49: ='Cash Flow Statement'!H33/'Income Statement'!H50 -> 2.0433492 | I49: ='Cash Flow Statement'!I33/'Income Statement'!I50 -> 1.4559374 | J49: ='Cash Flow Statement'!J33/'Income Statement'!J50 -> 1.2842636 | ... L49: ='Cash Flow Statement'!L33/'Income Statement'!L50 -> 1.1907377 | O49: ='Cash Flow Statement'!O33/'Income Statement'!O50 -> 4.4295144 | P49: ='Cash Flow Statement'!P33/'Income Statement'!P50 -> -7.6576 | Q49: ='Cash Flow Statement'!Q33/'Income Statement'!Q50 -> 1.1108486 | R49: ='Cash Flow Statement'!R33/'Income Statement'!R50 -> 2.5514602 | S49: ='Cash Flow Statement'!S33/'Income Statement'!S50 -> 4.7908213 | T49: ='Cash Flow Statement'!T33/'Income Statement'!T50 -> 1.1239624 | U49: ='Cash Flow Statement'!U33/'Income Statement'!U50 -> 2.0142857 | V49: ='Cash Flow Statement'!V33/'Income Statement'!V50 -> 2.5175733
A51: 8. EARNINGS QUALITY
A52: Accruals Ratio ((NI - CFO) / Avg Total Assets) | D52: =('Income Statement'!D50-'Cash Flow Statement'!D33)/(('Balance Sheet'!D26+'Balance Sheet'!C26)/2) -> -0.091335837 | E52: =('Income Statement'!E50-'Cash Flow Statement'!E33)/(('Balance Sheet'!E26+'Balance Sheet'!D26)/2) -> 0.07135888 | F52: =('Income Statement'!F50-'Cash Flow Statement'!F33)/(('Balance Sheet'!F26+'Balance Sheet'!E26)/2) -> -0.11857129 | G52: =('Income Statement'!G50-'Cash Flow Statement'!G33)/(('Balance Sheet'!G26+'Balance Sheet'!F26)/2) -> -0.12690865 | H52: =('Income Statement'!H50-'Cash Flow Statement'!H33)/(('Balance Sheet'!H26+'Balance Sheet'!G26)/2) -> -0.092777041 | I52: =('Income Statement'!I50-'Cash Flow Statement'!I33)/(('Balance Sheet'!I26+'Balance Sheet'!H26)/2) -> -0.070434555 | J52: =('Income Statement'!J50-'Cash Flow Statement'!J33)/(('Balance Sheet'!J26+'Balance Sheet'!I26)/2) -> -0.054794333 | K52: =('Income Statement'!K50-'Cash Flow Statement'!K33)/(('Balance Sheet'!K26+'Balance Sheet'!J26)/2) -> -0.1179593 | L52: =('Income Statement'!L50-'Cash Flow Statement'!L33)/(('Balance Sheet'!L26+'Balance Sheet'!K26)/2) -> -0.026198487
A54: 9. GROWTH
A55: Revenue YoY Growth | C55: ='Income Statement'!C15 -> 0 | D55: ='Income Statement'!D15 -> 0.33202417 | E55: ='Income Statement'!E15 -> 0.18212747 | F55: ='Income Statement'!F15 -> 0.083892939 | G55: ='Income Statement'!G15 -> 0.057131478 | H55: ='Income Statement'!H15 -> 0.14911253 | I55: ='Income Statement'!I15 -> 0.20958106 | J55: ='Income Statement'!J15 -> 0.078788061 | ... L55: ='Income Statement'!L15 -> 0.23874433 | O55: ='Income Statement'!O15 -> 0 | P55: ='Income Statement'!P15 -> 0 | Q55: ='Income Statement'!Q15 -> 0 | R55: ='Income Statement'!R15 -> 0 | S55: ='Income Statement'!S15 -> 0.27748859 | T55: ='Income Statement'!T15 -> 0.47727968 | U55: ='Income Statement'!U15 -> 0.48746313 | V55: ='Income Statement'!V15 -> 0.97220741
A56: Operating Income YoY Growth | C56: ='Income Statement'!C39 -> 0 | D56: ='Income Statement'!D39 -> -6.8264059 | E56: ='Income Statement'!E39 -> 1.1548468 | F56: ='Income Statement'!F39 -> -0.32930867 | G56: ='Income Statement'!G39 -> 0.16550523 | H56: ='Income Statement'!H39 -> 1.1223219 | I56: ='Income Statement'!I39 -> 0.66979692 | J56: ='Income Statement'!J39 -> 0.13933216 | ... L56: ='Income Statement'!L39 -> 0.89289163 | O56: ='Income Statement'!O39 -> 0 | P56: ='Income Statement'!P39 -> 0 | Q56: ='Income Statement'!Q39 -> 0 | R56: ='Income Statement'!R39 -> 0 | S56: ='Income Statement'!S39 -> 0.98549747 | T56: ='Income Statement'!T39 -> 1.2605597 | U56: ='Income Statement'!U39 -> 0.72332268 | V56: ='Income Statement'!V39 -> 1.7371762
A57: Net Income YoY Growth | C57: ='Income Statement'!C52 -> 0 | D57: ='Income Statement'!D52 -> -1.9586244 | E57: ='Income Statement'!E52 -> 6.0683857 | F57: ='Income Statement'!F52 -> -0.78398097 | G57: ='Income Statement'!G52 -> 0.086637298 | H57: ='Income Statement'!H52 -> 1.2756757 | I57: ='Income Statement'!I52 -> 0.70650238 | J57: ='Income Statement'!J52 -> 0.22505437 | ... L57: ='Income Statement'!L52 -> 2.9229856 | O57: ='Income Statement'!O52 -> 0 | P57: ='Income Statement'!P52 -> 0 | Q57: ='Income Statement'!Q52 -> 0 | R57: ='Income Statement'!R52 -> 0 | S57: ='Income Statement'!S52 -> 0.95190948 | T57: ='Income Statement'!T52 -> -4.9194667 | U57: ='Income Statement'!U52 -> 0.69180447 | V57: ='Income Statement'!V52 -> 1.6360524
A58: EBITDA YoY Growth | D58: =IF(N(C22)=0,"",D22/C22-1) -> 1.7041398 | E58: =IF(N(D22)=0,"",E22/D22-1) -> 0.29438202 | F58: =IF(N(E22)=0,"",F22/E22-1) -> 0.00390625 | G58: =IF(N(F22)=0,"",G22/F22-1) -> 0.18017726 | H58: =IF(N(G22)=0,"",H22/G22-1) -> 0.33345544 | I58: =IF(N(H22)=0,"",I22/H22-1) -> 0.31929945 | J58: =IF(N(I22)=0,"",J22/I22-1) -> 0.043365089 | K58: =IF(N(J22)=0,"",K22/J22-1) -> 0.1711905 | L58: =IF(N(K22)=0,"",L22/K22-1) -> 0.45950667 | S58: =IF(N(O22)=0,"",S22/O22-1) -> 0.58533163 | T58: =IF(N(P22)=0,"",T22/P22-1) -> -0.04210244 | U58: =IF(N(Q22)=0,"",U22/Q22-1) -> 0.79108371 | V58: =IF(N(R22)=0,"",V22/R22-1) -> 1.2112302
A60: 10. WORKING CAPITAL
A61: Days Sales Outstanding | C61: ='Balance Sheet'!C52 -> 60.125755 | D61: ='Balance Sheet'!D52 -> 50.66455 | E61: ='Balance Sheet'!E52 -> 58.213018 | F61: ='Balance Sheet'!F52 -> 52.64128 | G61: ='Balance Sheet'!G52 -> 35.097329 | H61: ='Balance Sheet'!H52 -> 27.537887 | I61: ='Balance Sheet'!I52 -> 32.517242 | J61: ='Balance Sheet'!J52 -> 32.139647 | ... L61: ='Balance Sheet'!L52 -> 40.820903 | O61: ='Balance Sheet'!O52 -> 40.081685 | P61: ='Balance Sheet'!P52 -> 32.475138 | Q61: ='Balance Sheet'!Q52 -> 30.229619 | R61: ='Balance Sheet'!R52 -> 33.739869 | S61: ='Balance Sheet'!S52 -> 37.045762 | T61: ='Balance Sheet'!T52 -> 39.866397 | U61: ='Balance Sheet'!U52 -> 44.419255 | V61: ='Balance Sheet'!V52 -> 42.15258
A62: Days Inventory Outstanding | C62: ='Balance Sheet'!C53 -> 70 | D62: ='Balance Sheet'!D53 -> 57.867317 | E62: ='Balance Sheet'!E53 -> 40.559565 | F62: ='Balance Sheet'!F53 -> 31.541428 | G62: ='Balance Sheet'!G53 -> 35.296471 | H62: ='Balance Sheet'!H53 -> 44.635584 | I62: ='Balance Sheet'!I53 -> 63.253961 | J62: ='Balance Sheet'!J53 -> 62.249079 | ... L62: ='Balance Sheet'!L53 -> 40.234546 | O62: ='Balance Sheet'!O53 -> 35.580981 | P62: ='Balance Sheet'!P53 -> 36.54665 | Q62: ='Balance Sheet'!Q53 -> 36.392371 | R62: ='Balance Sheet'!R53 -> 38.183274 | S62: ='Balance Sheet'!S53 -> 37.793865 | T62: ='Balance Sheet'!T53 -> 43.79948 | U62: ='Balance Sheet'!U53 -> 58.158299 | V62: ='Balance Sheet'!V53 -> 45.056705
A63: Days Payable Outstanding | C63: ='Balance Sheet'!C54 -> 63.05 | D63: ='Balance Sheet'!D54 -> 44.190314 | E63: ='Balance Sheet'!E54 -> 29.264953 | F63: ='Balance Sheet'!F54 -> 30.855745 | G63: ='Balance Sheet'!G54 -> 29.419591 | H63: ='Balance Sheet'!H54 -> 37.374128 | I63: ='Balance Sheet'!I54 -> 32.793482 | J63: ='Balance Sheet'!J54 -> 39.684608 | ... L63: ='Balance Sheet'!L54 -> 27.650172 | O63: ='Balance Sheet'!O54 -> 27.835067 | P63: ='Balance Sheet'!P54 -> 33.903096 | Q63: ='Balance Sheet'!Q54 -> 36.33515 | R63: ='Balance Sheet'!R54 -> 24.553152 | S63: ='Balance Sheet'!S54 -> 24.826062 | T63: ='Balance Sheet'!T54 -> 31.230419 | U63: ='Balance Sheet'!U54 -> 31.403869 | V63: ='Balance Sheet'!V54 -> 39.846743
A64: Cash Conversion Cycle | C64: ='Balance Sheet'!C55 -> 67.075755 | D64: ='Balance Sheet'!D55 -> 64.341552 | E64: ='Balance Sheet'!E55 -> 69.50763 | F64: ='Balance Sheet'!F55 -> 53.326963 | G64: ='Balance Sheet'!G55 -> 40.974209 | H64: ='Balance Sheet'!H55 -> 34.799343 | I64: ='Balance Sheet'!I55 -> 62.977721 | J64: ='Balance Sheet'!J55 -> 54.704118 | ... L64: ='Balance Sheet'!L55 -> 53.405276 | O64: ='Balance Sheet'!O55 -> 47.827599 | P64: ='Balance Sheet'!P55 -> 35.118692 | Q64: ='Balance Sheet'!Q55 -> 30.28684 | R64: ='Balance Sheet'!R55 -> 47.369992 | S64: ='Balance Sheet'!S55 -> 50.013566 | T64: ='Balance Sheet'!T55 -> 52.435458 | U64: ='Balance Sheet'!U55 -> 71.173685 | V64: ='Balance Sheet'!V55 -> 47.362542

Sheet Sources
A1: Broadcom Inc. — Sources
A2: $ in millions except per-share data | USD | as of 2026-09-22
A4: Sources
A6: Filing | B6: Repository path | C6: Period
A7: FY2016 10-K | B7: sources/companies/US/AVGO-broadcom/artifacts/ten_k/AVGO-broadcom/FY2016/psp_666734a663ef49d3864df1c8a3620cbf/prepared/document.md | C7: FYE 2016-10-30
A8: FY2017 10-K | B8: sources/companies/US/AVGO-broadcom/artifacts/ten_k/AVGO-broadcom/FY2017/psp_6e35f35ab0da48268dfd27dc6687451c/prepared/document.md | C8: FYE 2017-10-29
A9: FY2018 10-K | B9: sources/companies/US/AVGO-broadcom/artifacts/ten_k/AVGO-broadcom/FY2018/psp_0946b31c90c341fcb89c814a56e680a6/prepared/document.md | C9: FYE 2018-11-04
A10: FY2019 10-K | B10: sources/companies/US/AVGO-broadcom/artifacts/ten_k/AVGO-broadcom/FY2019/psp_6349fca9546c40c1a68e5c6a793e32a5/prepared/document.md | C10: FYE 2019-11-03
A11: FY2020 10-K | B11: sources/companies/US/AVGO-broadcom/artifacts/ten_k/AVGO-broadcom/FY2020/psp_c7f4d090d8164b04a169c631fb75c79a/prepared/document.md | C11: FYE 2020-11-01
A12: FY2021 10-K | B12: sources/companies/US/AVGO-broadcom/artifacts/ten_k/AVGO-broadcom/FY2021/psp_10972accbf6d40a0a03d224474584f54/prepared/document.md | C12: FYE 2021-10-31
A13: FY2022 10-K | B13: sources/companies/US/AVGO-broadcom/artifacts/ten_k/AVGO-broadcom/FY2022/psp_0690231d201142e0952366ddb7520e5e/prepared/document.md | C13: FYE 2022-10-30
A14: FY2023 10-K | B14: sources/companies/US/AVGO-broadcom/artifacts/ten_k/AVGO-broadcom/FY2023/psp_4d19f918a1a24df8aab06c837a36fcc3/prepared/document.md | C14: FYE 2023-10-29
A15: FY2024 10-K | B15: sources/companies/US/AVGO-broadcom/artifacts/ten_k/AVGO-broadcom/FY2024/psp_de98d67093094a79895aa84d04f3f0ee/prepared/document.md | C15: FYE 2024-11-03
A16: FY2025 10-K | B16: sources/companies/US/AVGO-broadcom/artifacts/ten_k/AVGO-broadcom/FY2025/psp_13e4c5dfa72a4c7ead9d52bf95ea70fd/prepared/document.md | C16: FYE 2025-11-02
A17: 3Q FY2026 10-Q | B17: sources/companies/US/AVGO-broadcom/artifacts/ten_k/AVGO-broadcom/FY20263/psp_c9981a970e024215b090a916e6857b69/prepared/document.md | C17: Quarter ended 2026-08-02
A19: Methodology notes
A20: Source tier | B20: All figures on IS/BS/CF/SEG are Tier-2 (hand-extracted directly from each fiscal year's own SEC 10-K or 10-Q, sourced from the prepared/document.md filing text above). No Tier-1 financial_input.json existed for this company; tables.json (Tier-2 bundle collector output, 994 tables) was reviewed but not used directly for IS/BS/CF because its period-normalization regex did not match full-date column headers (e.g. 'November 2, 2025'), so it produced no usable Income Statement / Balance Sheet / Cash Flow / Segment sheets — see model.draft-bundle.json.bak in this directory for the discarded draft.
A21: Own-year rule | B21: Every annual column uses that fiscal year's OWN as-filed figures from its own 10-K, not a later filing's restated/recast comparative column. This preserves a pure historical series but means some comparability breaks are real disclosure changes, not modeling errors — see Cover sheet for the full list (VMware, revenue reclassification, stock split, segment redefinition, discontinued operations).
A22: Supplementary topic sheets | B22: The original draft model.json (Phase 3 auto-assembly) grouped tables into 7 heuristic topic sheets (Other Notes, Tax & Shares, Products & Geography, Debt & Liquidity, Capital Returns, Assets & Intangibles, Operating KPIs) from unverified bundle data. These were dropped in this rebuild rather than carried forward unverified; the core financial statements (IS/BS/CF/SEG) together with Derived Metrics (DM) are the verified, source-traced deliverable.

Sheet Asset Structure
A1: Broadcom Inc. — Asset Structure
A2: $ in millions except per-share data | USD | FY2016-FY2025 annual | as of 2026-09-22
C3: FY2016 | D3: FY2017 | E3: FY2018 | F3: FY2019 | G3: FY2020 | H3: FY2021 | I3: FY2022 | J3: FY2023 | K3: FY2024 | L3: FY2025
C4: 2016-10-30 | D4: 2017-10-29 | E4: 2018-11-04 | F4: 2019-11-03 | G4: 2020-11-01 | H4: 2021-10-31 | I4: 2022-10-30 | J4: 2023-10-29 | K4: 2024-11-03 | L4: 2025-11-02
A6: 1. ASSET STRUCTURE — $ MILLIONS
A7: Source: Balance Sheet (linked). Each bucket reconciles exactly to reported Total assets — see check row below.
A8: Cash and cash equivalents | C8: ='Balance Sheet'!C15 -> 3097 | D8: ='Balance Sheet'!D15 -> 11204 | E8: ='Balance Sheet'!E15 -> 4292 | F8: ='Balance Sheet'!F15 -> 5055 | G8: ='Balance Sheet'!G15 -> 7618 | H8: ='Balance Sheet'!H15 -> 12163 | I8: ='Balance Sheet'!I15 -> 12416 | J8: ='Balance Sheet'!J15 -> 14189 | ... L8: ='Balance Sheet'!L15 -> 16178
A9: Trade receivables, net | C9: ='Balance Sheet'!C16 -> 2181 | D9: ='Balance Sheet'!D16 -> 2448 | E9: ='Balance Sheet'!E16 -> 3325 | F9: ='Balance Sheet'!F16 -> 3259 | G9: ='Balance Sheet'!G16 -> 2297 | H9: ='Balance Sheet'!H16 -> 2071 | I9: ='Balance Sheet'!I16 -> 2958 | J9: ='Balance Sheet'!J16 -> 3154 | ... L9: ='Balance Sheet'!L16 -> 7145
A10: Inventory | C10: ='Balance Sheet'!C17 -> 1400 | D10: ='Balance Sheet'!D17 -> 1447 | E10: ='Balance Sheet'!E17 -> 1124 | F10: ='Balance Sheet'!F17 -> 874 | G10: ='Balance Sheet'!G17 -> 1003 | H10: ='Balance Sheet'!H17 -> 1297 | I10: ='Balance Sheet'!I17 -> 1925 | J10: ='Balance Sheet'!J17 -> 1898 | ... L10: ='Balance Sheet'!L17 -> 2270
A11: Other current assets | C11: ='Balance Sheet'!C18 -> 447 | D11: ='Balance Sheet'!D18 -> 724 | E11: ='Balance Sheet'!E18 -> 366 | F11: ='Balance Sheet'!F18 -> 729 | G11: ='Balance Sheet'!G18 -> 977 | H11: ='Balance Sheet'!H18 -> 1055 | I11: ='Balance Sheet'!I18 -> 1205 | J11: ='Balance Sheet'!J18 -> 1606 | ... L11: ='Balance Sheet'!L18 -> 5980
A12: Total current assets | C12: =SUM(C8:C11) -> 7125 | D12: =SUM(D8:D11) -> 15823 | E12: =SUM(E8:E11) -> 9107 | F12: =SUM(F8:F11) -> 9917 | G12: =SUM(G8:G11) -> 11895 | H12: =SUM(H8:H11) -> 16586 | I12: =SUM(I8:I11) -> 18504 | J12: =SUM(J8:J11) -> 20847 | ... L12: =SUM(L8:L11) -> 31573
A14: Property, plant & equipment, net | C14: ='Balance Sheet'!C22 -> 2509 | D14: ='Balance Sheet'!D22 -> 2599 | E14: ='Balance Sheet'!E22 -> 2635 | F14: ='Balance Sheet'!F22 -> 2565 | G14: ='Balance Sheet'!G22 -> 2509 | H14: ='Balance Sheet'!H22 -> 2348 | I14: ='Balance Sheet'!I22 -> 2223 | J14: ='Balance Sheet'!J22 -> 2154 | ... L14: ='Balance Sheet'!L22 -> 2530
A15: Goodwill | C15: ='Balance Sheet'!C23 -> 24732 | D15: ='Balance Sheet'!D23 -> 24706 | E15: ='Balance Sheet'!E23 -> 26913 | F15: ='Balance Sheet'!F23 -> 36714 | G15: ='Balance Sheet'!G23 -> 43447 | H15: ='Balance Sheet'!H23 -> 43450 | I15: ='Balance Sheet'!I23 -> 43614 | J15: ='Balance Sheet'!J23 -> 43653 | ... L15: ='Balance Sheet'!L23 -> 97801
A16: Intangible assets, net | C16: ='Balance Sheet'!C24 -> 15068 | D16: ='Balance Sheet'!D24 -> 10832 | E16: ='Balance Sheet'!E24 -> 10762 | F16: ='Balance Sheet'!F24 -> 17554 | G16: ='Balance Sheet'!G24 -> 16782 | H16: ='Balance Sheet'!H24 -> 11374 | I16: ='Balance Sheet'!I24 -> 7111 | J16: ='Balance Sheet'!J24 -> 3867 | ... L16: ='Balance Sheet'!L24 -> 32273
A17: Other long-term assets | C17: ='Balance Sheet'!C25 -> 532 | D17: ='Balance Sheet'!D25 -> 458 | E17: ='Balance Sheet'!E25 -> 707 | F17: ='Balance Sheet'!F25 -> 743 | G17: ='Balance Sheet'!G25 -> 1300 | H17: ='Balance Sheet'!H25 -> 1812 | I17: ='Balance Sheet'!I25 -> 1797 | J17: ='Balance Sheet'!J25 -> 2340 | ... L17: ='Balance Sheet'!L25 -> 6915
A18: Total long-term assets | C18: =SUM(C14:C17) -> 42841 | D18: =SUM(D14:D17) -> 38595 | E18: =SUM(E14:E17) -> 41017 | F18: =SUM(F14:F17) -> 57576 | G18: =SUM(G14:G17) -> 64038 | H18: =SUM(H14:H17) -> 58984 | I18: =SUM(I14:I17) -> 54745 | J18: =SUM(J14:J17) -> 52014 | ... L18: =SUM(L14:L17) -> 139519
A20: Total assets (sum of buckets) | C20: =C12+C18 -> 49966 | D20: =D12+D18 -> 54418 | E20: =E12+E18 -> 50124 | F20: =F12+F18 -> 67493 | G20: =G12+G18 -> 75933 | H20: =H12+H18 -> 75570 | I20: =I12+I18 -> 73249 | J20: =J12+J18 -> 72861 | ... L20: =L12+L18 -> 171092
A21: Total assets (as reported, linked) | C21: ='Balance Sheet'!C26 -> 49966 | D21: ='Balance Sheet'!D26 -> 54418 | E21: ='Balance Sheet'!E26 -> 50124 | F21: ='Balance Sheet'!F26 -> 67493 | G21: ='Balance Sheet'!G26 -> 75933 | H21: ='Balance Sheet'!H26 -> 75570 | I21: ='Balance Sheet'!I26 -> 73249 | J21: ='Balance Sheet'!J26 -> 72861 | ... L21: ='Balance Sheet'!L26 -> 171092
A22: Reconciliation check (should be ~0) | C22: =C20-C21 -> 0 | D22: =D20-D21 -> 0 | E22: =E20-E21 -> 0 | F22: =F20-F21 -> 0 | G22: =G20-G21 -> 0 | H22: =H20-H21 -> 0 | I22: =I20-I21 -> 0 | J22: =J20-J21 -> 0 | ... L22: =L20-L21 -> 0
A24: 2. ASSET STRUCTURE — % OF TOTAL ASSETS
A25: Each bucket $ (Section 1, this sheet) divided by Total assets as reported (row above).
A26: Cash and cash equivalents | C26: =C8/C21 -> 0.061982148 | D26: =D8/D21 -> 0.20588776 | E26: =E8/E21 -> 0.085627643 | F26: =F8/F21 -> 0.074896656 | G26: =G8/G21 -> 0.10032529 | H26: =H8/H21 -> 0.16095011 | I26: =I8/I21 -> 0.16950402 | J26: =J8/J21 -> 0.19474067 | ... L26: =L8/L21 -> 0.094557314
A27: Trade receivables, net | C27: =C9/C21 -> 0.043649682 | D27: =D9/D21 -> 0.044985115 | E27: =E9/E21 -> 0.066335488 | F27: =F9/F21 -> 0.048286489 | G27: =G9/G21 -> 0.030250352 | H27: =H9/H21 -> 0.027405055 | I27: =I9/I21 -> 0.040382804 | J27: =J9/J21 -> 0.043287904 | ... L27: =L9/L21 -> 0.041761158
A28: Inventory | C28: =C10/C21 -> 0.028019053 | D28: =D10/D21 -> 0.026590466 | E28: =E10/E21 -> 0.022424388 | F28: =F10/F21 -> 0.012949491 | G28: =G10/G21 -> 0.013209013 | H28: =H10/H21 -> 0.017162895 | I28: =I10/I21 -> 0.026280222 | J28: =J10/J21 -> 0.026049601 | ... L28: =L10/L21 -> 0.013267716
A29: Other current assets | C29: =C11/C21 -> 0.0089460833 | D29: =D11/D21 -> 0.013304421 | E29: =E11/E21 -> 0.0073018913 | F29: =F11/F21 -> 0.01080112 | G29: =G11/G21 -> 0.012866606 | H29: =H11/H21 -> 0.013960566 | I29: =I11/I21 -> 0.016450737 | J29: =J11/J21 -> 0.02204197 | ... L29: =L11/L21 -> 0.034951956
A30: Property, plant & equipment, net | C30: =C14/C21 -> 0.050214146 | D30: =D14/D21 -> 0.047759932 | E30: =E14/E21 -> 0.052569627 | F30: =F14/F21 -> 0.038003941 | G30: =G14/G21 -> 0.033042287 | H30: =H14/H21 -> 0.031070531 | I30: =I14/I21 -> 0.030348537 | J30: =J14/J21 -> 0.029563141 | ... L30: =L14/L21 -> 0.014787366
A31: Goodwill | C31: =C15/C21 -> 0.49497658 | D31: =D15/D21 -> 0.45400419 | E31: =E15/E21 -> 0.53692842 | F31: =F15/F21 -> 0.54396752 | G31: =G15/G21 -> 0.57217547 | H31: =H15/H21 -> 0.57496361 | I31: =I15/I21 -> 0.5954211 | J31: =J15/J21 -> 0.59912711 | ... L31: =L15/L21 -> 0.57162813
A32: Intangible assets, net | C32: =C16/C21 -> 0.30156506 | D32: =D16/D21 -> 0.19905178 | E32: =E16/E21 -> 0.21470753 | F32: =F16/F21 -> 0.26008623 | G32: =G16/G21 -> 0.22101063 | H32: =H16/H21 -> 0.15050946 | I32: =I16/I21 -> 0.097079824 | J32: =J16/J21 -> 0.053073661 | ... L32: =L16/L21 -> 0.18862951
A33: Other long-term assets | C33: =C17/C21 -> 0.01064724 | D33: =D17/D21 -> 0.0084163328 | E33: =E17/E21 -> 0.01410502 | F33: =F17/F21 -> 0.011008549 | G33: =G17/G21 -> 0.017120356 | H33: =H17/H21 -> 0.023977769 | I33: =I17/I21 -> 0.024532758 | J33: =J17/J21 -> 0.032115947 | ... L33: =L17/L21 -> 0.040416852
A34: Total | C34: =SUM(C26:C33) -> 1 | D34: =SUM(D26:D33) -> 1 | E34: =SUM(E26:E33) -> 1 | F34: =SUM(F26:F33) -> 1 | G34: =SUM(G26:G33) -> 1 | H34: =SUM(H26:H33) -> 1 | I34: =SUM(I26:I33) -> 1 | J34: =SUM(J26:J33) -> 1 | ... L34: =SUM(L26:L33) -> 1
A36: Notes: buckets follow Balance Sheet as-disclosed line items; no separate short-term investments line is disclosed by Broadcom in this model, so cash-like assets = cash & equivalents only.
A37: FY2024+ reflects the VMware acquisition (closed 2023-11-22) — Goodwill/Intangibles step up structurally; mix % is not organic growth. See Cover sheet comparability caveats.

Sheet Net Cash
A1: Broadcom Inc. — Net Cash
A2: $ in millions except per-share data | USD | FY2016-FY2025 annual | as of 2026-09-22
C3: FY2016 | D3: FY2017 | E3: FY2018 | F3: FY2019 | G3: FY2020 | H3: FY2021 | I3: FY2022 | J3: FY2023 | K3: FY2024 | L3: FY2025
C4: 2016-10-30 | D4: 2017-10-29 | E4: 2018-11-04 | F4: 2019-11-03 | G4: 2020-11-01 | H4: 2021-10-31 | I4: 2022-10-30 | J4: 2023-10-29 | K4: 2024-11-03 | L4: 2025-11-02
A6: NET CASH / (NET DEBT)
A7: Source: Balance Sheet (linked). Broadcom does not disclose a separate short-term investments line, so cash-like assets = cash & equivalents.
A8: Cash and cash equivalents | C8: ='Balance Sheet'!C15 -> 3097 | D8: ='Balance Sheet'!D15 -> 11204 | E8: ='Balance Sheet'!E15 -> 4292 | F8: ='Balance Sheet'!F15 -> 5055 | G8: ='Balance Sheet'!G15 -> 7618 | H8: ='Balance Sheet'!H15 -> 12163 | I8: ='Balance Sheet'!I15 -> 12416 | J8: ='Balance Sheet'!J15 -> 14189 | ... L8: ='Balance Sheet'!L15 -> 16178
A9: Current portion of long-term debt / short-term debt | C9: ='Balance Sheet'!C31 -> 454 | D9: ='Balance Sheet'!D31 -> 117 | E9: ='Balance Sheet'!E31 -> 0 | F9: ='Balance Sheet'!F31 -> 2787 | G9: ='Balance Sheet'!G31 -> 827 | H9: ='Balance Sheet'!H31 -> 290 | I9: ='Balance Sheet'!I31 -> 440 | J9: ='Balance Sheet'!J31 -> 1608 | ... L9: ='Balance Sheet'!L31 -> 3152
A10: Long-term debt | C10: ='Balance Sheet'!C36 -> 13188 | D10: ='Balance Sheet'!D36 -> 17431 | E10: ='Balance Sheet'!E36 -> 17493 | F10: ='Balance Sheet'!F36 -> 30011 | G10: ='Balance Sheet'!G36 -> 40235 | H10: ='Balance Sheet'!H36 -> 39440 | I10: ='Balance Sheet'!I36 -> 39075 | J10: ='Balance Sheet'!J36 -> 37621 | ... L10: ='Balance Sheet'!L36 -> 61984
A11: Total debt | C11: =C9+C10 -> 13642 | D11: =D9+D10 -> 17548 | E11: =E9+E10 -> 17493 | F11: =F9+F10 -> 32798 | G11: =G9+G10 -> 41062 | H11: =H9+H10 -> 39730 | I11: =I9+I10 -> 39515 | J11: =J9+J10 -> 39229 | ... L11: =L9+L10 -> 65136
A13: Net cash / (net debt) | C13: =C8-C11 -> -10545 | D13: =D8-D11 -> -6344 | E13: =E8-E11 -> -13201 | F13: =F8-F11 -> -27743 | G13: =G8-G11 -> -33444 | H13: =H8-H11 -> -27567 | I13: =I8-I11 -> -27099 | J13: =J8-J11 -> -25040 | ... L13: =L8-L11 -> -48958
A15: Positive = net cash position; negative = net debt position. Broadcom has been net-debt since the FY2016 IPO-era Avago/Broadcom combination and remained net-debt through FY2025 due to the VMware-financed debt raised in FY2024.

Sheet Working Capital
A1: Broadcom Inc. — Working Capital
A2: $ in millions except per-share data | USD | FY2016-FY2025 annual | as of 2026-09-22
C3: FY2016 | D3: FY2017 | E3: FY2018 | F3: FY2019 | G3: FY2020 | H3: FY2021 | I3: FY2022 | J3: FY2023 | K3: FY2024 | L3: FY2025
C4: 2016-10-30 | D4: 2017-10-29 | E4: 2018-11-04 | F4: 2019-11-03 | G4: 2020-11-01 | H4: 2021-10-31 | I4: 2022-10-30 | J4: 2023-10-29 | K4: 2024-11-03 | L4: 2025-11-02
A6: OPERATING WORKING CAPITAL
A7: Source: Balance Sheet (linked) and Income Statement (revenue, linked). Trade receivables and inventory are material for Broadcom (semiconductor + software mix) — this table is meaningful, not omitted.
A8: Trade receivables, net | C8: ='Balance Sheet'!C16 -> 2181 | D8: ='Balance Sheet'!D16 -> 2448 | E8: ='Balance Sheet'!E16 -> 3325 | F8: ='Balance Sheet'!F16 -> 3259 | G8: ='Balance Sheet'!G16 -> 2297 | H8: ='Balance Sheet'!H16 -> 2071 | I8: ='Balance Sheet'!I16 -> 2958 | J8: ='Balance Sheet'!J16 -> 3154 | ... L8: ='Balance Sheet'!L16 -> 7145
A9: Inventory | C9: ='Balance Sheet'!C17 -> 1400 | D9: ='Balance Sheet'!D17 -> 1447 | E9: ='Balance Sheet'!E17 -> 1124 | F9: ='Balance Sheet'!F17 -> 874 | G9: ='Balance Sheet'!G17 -> 1003 | H9: ='Balance Sheet'!H17 -> 1297 | I9: ='Balance Sheet'!I17 -> 1925 | J9: ='Balance Sheet'!J17 -> 1898 | ... L9: ='Balance Sheet'!L17 -> 2270
A10: Other current assets | C10: ='Balance Sheet'!C18 -> 447 | D10: ='Balance Sheet'!D18 -> 724 | E10: ='Balance Sheet'!E18 -> 366 | F10: ='Balance Sheet'!F18 -> 729 | G10: ='Balance Sheet'!G18 -> 977 | H10: ='Balance Sheet'!H18 -> 1055 | I10: ='Balance Sheet'!I18 -> 1205 | J10: ='Balance Sheet'!J18 -> 1606 | ... L10: ='Balance Sheet'!L18 -> 5980
A11: Operating current assets | C11: =SUM(C8:C10) -> 4028 | D11: =SUM(D8:D10) -> 4619 | E11: =SUM(E8:E10) -> 4815 | F11: =SUM(F8:F10) -> 4862 | G11: =SUM(G8:G10) -> 4277 | H11: =SUM(H8:H10) -> 4423 | I11: =SUM(I8:I10) -> 6088 | J11: =SUM(J8:J10) -> 6658 | ... L11: =SUM(L8:L10) -> 15395
A13: Accounts payable | C13: ='Balance Sheet'!C29 -> 1261 | D13: ='Balance Sheet'!D29 -> 1105 | E13: ='Balance Sheet'!E29 -> 811 | F13: ='Balance Sheet'!F29 -> 855 | G13: ='Balance Sheet'!G29 -> 836 | H13: ='Balance Sheet'!H29 -> 1086 | I13: ='Balance Sheet'!I29 -> 998 | J13: ='Balance Sheet'!J29 -> 1210 | ... L13: ='Balance Sheet'!L29 -> 1560
A14: Employee compensation and benefits | C14: ='Balance Sheet'!C30 -> 517 | D14: ='Balance Sheet'!D30 -> 626 | E14: ='Balance Sheet'!E30 -> 715 | F14: ='Balance Sheet'!F30 -> 641 | G14: ='Balance Sheet'!G30 -> 877 | H14: ='Balance Sheet'!H30 -> 1066 | I14: ='Balance Sheet'!I30 -> 1202 | J14: ='Balance Sheet'!J30 -> 935 | ... L14: ='Balance Sheet'!L30 -> 2129
A15: Other current liabilities | C15: ='Balance Sheet'!C32 -> 846 | D15: ='Balance Sheet'!D32 -> 681 | E15: ='Balance Sheet'!E32 -> 812 | F15: ='Balance Sheet'!F32 -> 2616 | G15: ='Balance Sheet'!G32 -> 3831 | H15: ='Balance Sheet'!H32 -> 3839 | I15: ='Balance Sheet'!I32 -> 4412 | J15: ='Balance Sheet'!J32 -> 3652 | ... L15: ='Balance Sheet'!L32 -> 11673
A16: Operating current liabilities | C16: =SUM(C13:C15) -> 2624 | D16: =SUM(D13:D15) -> 2412 | E16: =SUM(E13:E15) -> 2338 | F16: =SUM(F13:F15) -> 4112 | G16: =SUM(G13:G15) -> 5544 | H16: =SUM(H13:H15) -> 5991 | I16: =SUM(I13:I15) -> 6612 | J16: =SUM(J13:J15) -> 5797 | ... L16: =SUM(L13:L15) -> 15362
A18: Net working capital | C18: =C11-C16 -> 1404 | D18: =D11-D16 -> 2207 | E18: =E11-E16 -> 2477 | F18: =F11-F16 -> 750 | G18: =G11-G16 -> -1267 | H18: =H11-H16 -> -1568 | I18: =I11-I16 -> -524 | J18: =J11-J16 -> 861 | ... L18: =L11-L16 -> 33
A19: Total revenue (linked, for reference) | C19: ='Income Statement'!C14 -> 13240 | D19: ='Income Statement'!D14 -> 17636 | E19: ='Income Statement'!E14 -> 20848 | F19: ='Income Statement'!F14 -> 22597 | G19: ='Income Statement'!G14 -> 23888 | H19: ='Income Statement'!H14 -> 27450 | I19: ='Income Statement'!I14 -> 33203 | J19: ='Income Statement'!J14 -> 35819 | ... L19: ='Income Statement'!L14 -> 63887
A20: NWC as % of revenue | C20: =C18/C19 -> 0.1060423 | D20: =D18/D19 -> 0.12514176 | E20: =E18/E19 -> 0.11881236 | F20: =F18/F19 -> 0.033190246 | G20: =G18/G19 -> -0.053039183 | H20: =H18/H19 -> -0.05712204 | I20: =I18/I19 -> -0.015781706 | J20: =J18/J19 -> 0.024037522 | ... L20: =L18/L19 -> 0.00051653701
A22: OCA excludes cash & equivalents (no separate ST-investments line disclosed). OCL excludes current portion of long-term/short-term debt. FY2024+ step-up reflects VMware consolidation, not organic working-capital growth.

Sheet Cash-Flow Attribution
A1: Broadcom Inc. — Cash-Flow Attribution
A2: $ in millions except per-share data | USD | FY2016-FY2025 annual | as of 2026-09-22 | quarterly CF (not shown here) is fiscal-YTD; this sheet is annual, discrete-year figures only
C3: FY2016 | D3: FY2017 | E3: FY2018 | F3: FY2019 | G3: FY2020 | H3: FY2021 | I3: FY2022 | J3: FY2023 | K3: FY2024 | L3: FY2025
C4: 2016-10-30 | D4: 2017-10-29 | E4: 2018-11-04 | F4: 2019-11-03 | G4: 2020-11-01 | H4: 2021-10-31 | I4: 2022-10-30 | J4: 2023-10-29 | K4: 2024-11-03 | L4: 2025-11-02
A6: CASH-FLOW ATTRIBUTION BRIDGE — NET INCOME TO NET CHANGE IN CASH
A7: Source: Cash Flow Statement (linked). Bridge nets exactly to reported net change in cash — see hard-reconciliation check row at bottom.
A8: Net income (loss) | C8: ='Cash Flow Statement'!C14 -> -1861 | D8: ='Cash Flow Statement'!D14 -> 1784 | E8: ='Cash Flow Statement'!E14 -> 12610 | F8: ='Cash Flow Statement'!F14 -> 2724 | G8: ='Cash Flow Statement'!G14 -> 2960 | H8: ='Cash Flow Statement'!H14 -> 6736 | I8: ='Cash Flow Statement'!I14 -> 11495 | J8: ='Cash Flow Statement'!J14 -> 14082 | ... L8: ='Cash Flow Statement'!L14 -> 23126
A9: Depreciation & amortization | C9: ='Cash Flow Statement'!C16+'Cash Flow Statement'!C17 -> 3042 | D9: ='Cash Flow Statement'!D16+'Cash Flow Statement'!D17 -> 4737 | E9: ='Cash Flow Statement'!E16+'Cash Flow Statement'!E17 -> 4081 | F9: ='Cash Flow Statement'!F16+'Cash Flow Statement'!F17 -> 5808 | G9: ='Cash Flow Statement'!G16+'Cash Flow Statement'!G17 -> 6905 | H9: ='Cash Flow Statement'!H16+'Cash Flow Statement'!H17 -> 6041 | I9: ='Cash Flow Statement'!I16+'Cash Flow Statement'!I17 -> 4984 | J9: ='Cash Flow Statement'!J16+'Cash Flow Statement'!J17 -> 3835 | ... L9: ='Cash Flow Statement'!L16+'Cash Flow Statement'!L17 -> 8775
A10: Stock-based compensation expense | C10: ='Cash Flow Statement'!C18 -> 679 | D10: ='Cash Flow Statement'!D18 -> 921 | E10: ='Cash Flow Statement'!E18 -> 1227 | F10: ='Cash Flow Statement'!F18 -> 2185 | G10: ='Cash Flow Statement'!G18 -> 1976 | H10: ='Cash Flow Statement'!H18 -> 1704 | I10: ='Cash Flow Statement'!I18 -> 1533 | J10: ='Cash Flow Statement'!J18 -> 2171 | ... L10: ='Cash Flow Statement'!L18 -> 7568
A11: Deferred income taxes and other non-cash taxes | C11: ='Cash Flow Statement'!C20 -> 365 | D11: ='Cash Flow Statement'!D20 -> -173 | E11: ='Cash Flow Statement'!E20 -> -8270 | F11: ='Cash Flow Statement'!F20 -> -934 | G11: ='Cash Flow Statement'!G20 -> -1142 | H11: ='Cash Flow Statement'!H20 -> -809 | I11: ='Cash Flow Statement'!I20 -> -34 | J11: ='Cash Flow Statement'!J20 -> -501 | ... L11: ='Cash Flow Statement'!L20 -> -4008
A12: Other non-cash operating items | C12: ='Cash Flow Statement'!C19+'Cash Flow Statement'!C21+'Cash Flow Statement'!C22+'Cash Flow Statement'!C23+'Cash Flow Statement'!C24+'Cash Flow Statement'!C25 -> 703 | D12: ='Cash Flow Statement'!D19+'Cash Flow Statement'!D21+'Cash Flow Statement'!D22+'Cash Flow Statement'!D23+'Cash Flow Statement'!D24+'Cash Flow Statement'!D25 -> 268 | E12: ='Cash Flow Statement'!E19+'Cash Flow Statement'!E21+'Cash Flow Statement'!E22+'Cash Flow Statement'!E23+'Cash Flow Statement'!E24+'Cash Flow Statement'!E25 -> 188 | F12: ='Cash Flow Statement'!F19+'Cash Flow Statement'!F21+'Cash Flow Statement'!F22+'Cash Flow Statement'!F23+'Cash Flow Statement'!F24+'Cash Flow Statement'!F25 -> 98 | G12: ='Cash Flow Statement'!G19+'Cash Flow Statement'!G21+'Cash Flow Statement'!G22+'Cash Flow Statement'!G23+'Cash Flow Statement'!G24+'Cash Flow Statement'!G25 -> 269 | H12: ='Cash Flow Statement'!H19+'Cash Flow Statement'!H21+'Cash Flow Statement'!H22+'Cash Flow Statement'!H23+'Cash Flow Statement'!H24+'Cash Flow Statement'!H25 -> 219 | I12: ='Cash Flow Statement'!I19+'Cash Flow Statement'!I21+'Cash Flow Statement'!I22+'Cash Flow Statement'!I23+'Cash Flow Statement'!I24+'Cash Flow Statement'!I25 -> 412 | J12: ='Cash Flow Statement'!J19+'Cash Flow Statement'!J21+'Cash Flow Statement'!J22+'Cash Flow Statement'!J23+'Cash Flow Statement'!J24+'Cash Flow Statement'!J25 -> 141 | ... L12: ='Cash Flow Statement'!L19+'Cash Flow Statement'!L21+'Cash Flow Statement'!L22+'Cash Flow Statement'!L23+'Cash Flow Statement'!L24+'Cash Flow Statement'!L25 -> 576
A13: Working capital change (net) | C13: ='Cash Flow Statement'!C26+'Cash Flow Statement'!C27+'Cash Flow Statement'!C28+'Cash Flow Statement'!C29+'Cash Flow Statement'!C30+'Cash Flow Statement'!C31+'Cash Flow Statement'!C32 -> 483 | D13: ='Cash Flow Statement'!D26+'Cash Flow Statement'!D27+'Cash Flow Statement'!D28+'Cash Flow Statement'!D29+'Cash Flow Statement'!D30+'Cash Flow Statement'!D31+'Cash Flow Statement'!D32 -> -986 | E13: ='Cash Flow Statement'!E26+'Cash Flow Statement'!E27+'Cash Flow Statement'!E28+'Cash Flow Statement'!E29+'Cash Flow Statement'!E30+'Cash Flow Statement'!E31+'Cash Flow Statement'!E32 -> -956 | F13: ='Cash Flow Statement'!F26+'Cash Flow Statement'!F27+'Cash Flow Statement'!F28+'Cash Flow Statement'!F29+'Cash Flow Statement'!F30+'Cash Flow Statement'!F31+'Cash Flow Statement'!F32 -> -184 | G13: ='Cash Flow Statement'!G26+'Cash Flow Statement'!G27+'Cash Flow Statement'!G28+'Cash Flow Statement'!G29+'Cash Flow Statement'!G30+'Cash Flow Statement'!G31+'Cash Flow Statement'!G32 -> 1093 | H13: ='Cash Flow Statement'!H26+'Cash Flow Statement'!H27+'Cash Flow Statement'!H28+'Cash Flow Statement'!H29+'Cash Flow Statement'!H30+'Cash Flow Statement'!H31+'Cash Flow Statement'!H32 -> -127 | I13: ='Cash Flow Statement'!I26+'Cash Flow Statement'!I27+'Cash Flow Statement'!I28+'Cash Flow Statement'!I29+'Cash Flow Statement'!I30+'Cash Flow Statement'!I31+'Cash Flow Statement'!I32 -> -1654 | J13: ='Cash Flow Statement'!J26+'Cash Flow Statement'!J27+'Cash Flow Statement'!J28+'Cash Flow Statement'!J29+'Cash Flow Statement'!J30+'Cash Flow Statement'!J31+'Cash Flow Statement'!J32 -> -1643 | ... L13: ='Cash Flow Statement'!L26+'Cash Flow Statement'!L27+'Cash Flow Statement'!L28+'Cash Flow Statement'!L29+'Cash Flow Statement'!L30+'Cash Flow Statement'!L31+'Cash Flow Statement'!L32 -> -8500
A14: Cash flow from operations (calc, = sum above) | C14: =SUM(C8:C13) -> 3411 | D14: =SUM(D8:D13) -> 6551 | E14: =SUM(E8:E13) -> 8880 | F14: =SUM(F8:F13) -> 9697 | G14: =SUM(G8:G13) -> 12061 | H14: =SUM(H8:H13) -> 13764 | I14: =SUM(I8:I13) -> 16736 | J14: =SUM(J8:J13) -> 18085 | ... L14: =SUM(L8:L13) -> 27537
A15: Cash flow from operations (as reported, linked) | C15: ='Cash Flow Statement'!C33 -> 3411 | D15: ='Cash Flow Statement'!D33 -> 6551 | E15: ='Cash Flow Statement'!E33 -> 8880 | F15: ='Cash Flow Statement'!F33 -> 9697 | G15: ='Cash Flow Statement'!G33 -> 12061 | H15: ='Cash Flow Statement'!H33 -> 13764 | I15: ='Cash Flow Statement'!I33 -> 16736 | J15: ='Cash Flow Statement'!J33 -> 18085 | ... L15: ='Cash Flow Statement'!L33 -> 27537
A17: Capital expenditures (PP&E) | C17: ='Cash Flow Statement'!C36 -> -723 | D17: ='Cash Flow Statement'!D36 -> -1069 | E17: ='Cash Flow Statement'!E36 -> -635 | F17: ='Cash Flow Statement'!F36 -> -432 | G17: ='Cash Flow Statement'!G36 -> -463 | H17: ='Cash Flow Statement'!H36 -> -443 | I17: ='Cash Flow Statement'!I36 -> -424 | J17: ='Cash Flow Statement'!J36 -> -452 | ... L17: ='Cash Flow Statement'!L36 -> -623
A18: Free cash flow (CFO as reported + capex) | C18: =C15+C17 -> 2688 | D18: =D15+D17 -> 5482 | E18: =E15+E17 -> 8245 | F18: =F15+F17 -> 9265 | G18: =G15+G17 -> 11598 | H18: =H15+H17 -> 13321 | I18: =I15+I17 -> 16312 | J18: =J15+J17 -> 17633 | ... L18: =L15+L17 -> 26914
A20: Dividends paid | C20: ='Cash Flow Statement'!C52 -> -750 | D20: ='Cash Flow Statement'!D52 -> -1745 | E20: ='Cash Flow Statement'!E52 -> -2998 | F20: ='Cash Flow Statement'!F52 -> -4235 | G20: ='Cash Flow Statement'!G52 -> -5534 | H20: ='Cash Flow Statement'!H52 -> -6212 | I20: ='Cash Flow Statement'!I52 -> -7032 | J20: ='Cash Flow Statement'!J52 -> -7645 | ... L20: ='Cash Flow Statement'!L52 -> -11142
A21: Repurchases of common stock (open-market buybacks) | C21: ='Cash Flow Statement'!C53 -> 0 | D21: ='Cash Flow Statement'!D53 -> 0 | E21: ='Cash Flow Statement'!E53 -> -7258 | F21: ='Cash Flow Statement'!F53 -> -5435 | G21: ='Cash Flow Statement'!G53 -> 0 | H21: ='Cash Flow Statement'!H53 -> 0 | I21: ='Cash Flow Statement'!I53 -> -7000 | J21: ='Cash Flow Statement'!J53 -> -5824 | ... L21: ='Cash Flow Statement'!L53 -> -2450
A22: Shares repurchased for tax withholding on vesting | C22: ='Cash Flow Statement'!C54 -> 0 | D22: ='Cash Flow Statement'!D54 -> 0 | E22: ='Cash Flow Statement'!E54 -> 0 | F22: ='Cash Flow Statement'!F54 -> -972 | G22: ='Cash Flow Statement'!G54 -> -765 | H22: ='Cash Flow Statement'!H54 -> -1299 | I22: ='Cash Flow Statement'!I54 -> -1455 | J22: ='Cash Flow Statement'!J54 -> -1861 | ... L22: ='Cash Flow Statement'!L54 -> -3860
A23: Net debt issuance / (repayment) | C23: ='Cash Flow Statement'!C46+'Cash Flow Statement'!C47+'Cash Flow Statement'!C48+'Cash Flow Statement'!C49+'Cash Flow Statement'!C50+'Cash Flow Statement'!C57 -> 8070 | D23: ='Cash Flow Statement'!D46+'Cash Flow Statement'!D47+'Cash Flow Statement'!D48+'Cash Flow Statement'!D49+'Cash Flow Statement'!D50+'Cash Flow Statement'!D57 -> 3718 | E23: ='Cash Flow Statement'!E46+'Cash Flow Statement'!E47+'Cash Flow Statement'!E48+'Cash Flow Statement'!E49+'Cash Flow Statement'!E50+'Cash Flow Statement'!E57 -> -994 | F23: ='Cash Flow Statement'!F46+'Cash Flow Statement'!F47+'Cash Flow Statement'!F48+'Cash Flow Statement'!F49+'Cash Flow Statement'!F50+'Cash Flow Statement'!F57 -> 13234 | G23: ='Cash Flow Statement'!G46+'Cash Flow Statement'!G47+'Cash Flow Statement'!G48+'Cash Flow Statement'!G49+'Cash Flow Statement'!G50+'Cash Flow Statement'!G57 -> 7703 | H23: ='Cash Flow Statement'!H46+'Cash Flow Statement'!H47+'Cash Flow Statement'!H48+'Cash Flow Statement'!H49+'Cash Flow Statement'!H50+'Cash Flow Statement'!H57 -> -1591 | I23: ='Cash Flow Statement'!I46+'Cash Flow Statement'!I47+'Cash Flow Statement'!I48+'Cash Flow Statement'!I49+'Cash Flow Statement'!I50+'Cash Flow Statement'!I57 -> -426 | J23: ='Cash Flow Statement'!J46+'Cash Flow Statement'!J47+'Cash Flow Statement'!J48+'Cash Flow Statement'!J49+'Cash Flow Statement'!J50+'Cash Flow Statement'!J57 -> -403 | ... L23: ='Cash Flow Statement'!L46+'Cash Flow Statement'!L47+'Cash Flow Statement'!L48+'Cash Flow Statement'!L49+'Cash Flow Statement'!L50+'Cash Flow Statement'!L57 -> -2812
A24: Acquisitions of businesses, net of cash acquired | C24: ='Cash Flow Statement'!C38 -> -10055 | D24: ='Cash Flow Statement'!D38 -> -40 | E24: ='Cash Flow Statement'!E38 -> -4800 | F24: ='Cash Flow Statement'!F38 -> -16033 | G24: ='Cash Flow Statement'!G38 -> -10872 | H24: ='Cash Flow Statement'!H38 -> -8 | I24: ='Cash Flow Statement'!I38 -> -246 | J24: ='Cash Flow Statement'!J38 -> -53 | ... L24: ='Cash Flow Statement'!L38 -> 0
A25: Proceeds from sales of businesses | C25: ='Cash Flow Statement'!C39 -> 898 | D25: ='Cash Flow Statement'!D39 -> 10 | E25: ='Cash Flow Statement'!E39 -> 773 | F25: ='Cash Flow Statement'!F39 -> 957 | G25: ='Cash Flow Statement'!G39 -> 218 | H25: ='Cash Flow Statement'!H39 -> 45 | I25: ='Cash Flow Statement'!I39 -> 0 | J25: ='Cash Flow Statement'!J39 -> 0 | ... L25: ='Cash Flow Statement'!L39 -> 300
A26: Other investing items (net) | C26: ='Cash Flow Statement'!C37+'Cash Flow Statement'!C40+'Cash Flow Statement'!C41+'Cash Flow Statement'!C42 -> 40 | D26: ='Cash Flow Statement'!D37+'Cash Flow Statement'!D40+'Cash Flow Statement'!D41+'Cash Flow Statement'!D42 -> 425 | E26: ='Cash Flow Statement'!E37+'Cash Flow Statement'!E40+'Cash Flow Statement'!E41+'Cash Flow Statement'!E42 -> -12 | F26: ='Cash Flow Statement'!F37+'Cash Flow Statement'!F40+'Cash Flow Statement'!F41+'Cash Flow Statement'!F42 -> 86 | G26: ='Cash Flow Statement'!G37+'Cash Flow Statement'!G40+'Cash Flow Statement'!G41+'Cash Flow Statement'!G42 -> 8 | H26: ='Cash Flow Statement'!H37+'Cash Flow Statement'!H40+'Cash Flow Statement'!H41+'Cash Flow Statement'!H42 -> 161 | I26: ='Cash Flow Statement'!I37+'Cash Flow Statement'!I40+'Cash Flow Statement'!I41+'Cash Flow Statement'!I42 -> 3 | J26: ='Cash Flow Statement'!J37+'Cash Flow Statement'!J40+'Cash Flow Statement'!J41+'Cash Flow Statement'!J42 -> -184 | ... L26: ='Cash Flow Statement'!L37+'Cash Flow Statement'!L40+'Cash Flow Statement'!L41+'Cash Flow Statement'!L42 -> -257
A27: Other financing items (net) | C27: ='Cash Flow Statement'!C51+'Cash Flow Statement'!C55+'Cash Flow Statement'!C56+'Cash Flow Statement'!C58 -> 384 | D27: ='Cash Flow Statement'!D51+'Cash Flow Statement'!D55+'Cash Flow Statement'!D56+'Cash Flow Statement'!D58 -> 257 | E27: ='Cash Flow Statement'!E51+'Cash Flow Statement'!E55+'Cash Flow Statement'!E56+'Cash Flow Statement'!E58 -> 132 | F27: ='Cash Flow Statement'!F51+'Cash Flow Statement'!F55+'Cash Flow Statement'!F56+'Cash Flow Statement'!F58 -> 3896 | G27: ='Cash Flow Statement'!G51+'Cash Flow Statement'!G55+'Cash Flow Statement'!G56+'Cash Flow Statement'!G58 -> 207 | H27: ='Cash Flow Statement'!H51+'Cash Flow Statement'!H55+'Cash Flow Statement'!H56+'Cash Flow Statement'!H58 -> 128 | I27: ='Cash Flow Statement'!I51+'Cash Flow Statement'!I55+'Cash Flow Statement'!I56+'Cash Flow Statement'!I58 -> 97 | J27: ='Cash Flow Statement'!J51+'Cash Flow Statement'!J55+'Cash Flow Statement'!J56+'Cash Flow Statement'!J58 -> 110 | ... L27: ='Cash Flow Statement'!L51+'Cash Flow Statement'!L55+'Cash Flow Statement'!L56+'Cash Flow Statement'!L58 -> 137
A28: Net change in cash (calc, = full bridge) | C28: =C8+C9+C10+C11+C12+C13+C17+C20+C21+C22+C23+C24+C25+C26+C27 -> 1275 | D28: =D8+D9+D10+D11+D12+D13+D17+D20+D21+D22+D23+D24+D25+D26+D27 -> 8107 | E28: =E8+E9+E10+E11+E12+E13+E17+E20+E21+E22+E23+E24+E25+E26+E27 -> -6912 | F28: =F8+F9+F10+F11+F12+F13+F17+F20+F21+F22+F23+F24+F25+F26+F27 -> 763 | G28: =G8+G9+G10+G11+G12+G13+G17+G20+G21+G22+G23+G24+G25+G26+G27 -> 2563 | H28: =H8+H9+H10+H11+H12+H13+H17+H20+H21+H22+H23+H24+H25+H26+H27 -> 4545 | I28: =I8+I9+I10+I11+I12+I13+I17+I20+I21+I22+I23+I24+I25+I26+I27 -> 253 | J28: =J8+J9+J10+J11+J12+J13+J17+J20+J21+J22+J23+J24+J25+J26+J27 -> 1773 | ... L28: =L8+L9+L10+L11+L12+L13+L17+L20+L21+L22+L23+L24+L25+L26+L27 -> 6830
A29: Net change in cash (as reported, linked) | C29: ='Cash Flow Statement'!C62 -> 1275 | D29: ='Cash Flow Statement'!D62 -> 8107 | E29: ='Cash Flow Statement'!E62 -> -6912 | F29: ='Cash Flow Statement'!F62 -> 763 | G29: ='Cash Flow Statement'!G62 -> 2563 | H29: ='Cash Flow Statement'!H62 -> 4545 | I29: ='Cash Flow Statement'!I62 -> 253 | J29: ='Cash Flow Statement'!J62 -> 1773 | ... L29: ='Cash Flow Statement'!L62 -> 6830
A30: Reconciliation check (should be ~0) | C30: =C28-C29 -> 0 | D30: =D28-D29 -> 0 | E30: =E28-E29 -> 0 | F30: =F28-F29 -> 0 | G30: =G28-G29 -> 0 | H30: =H28-H29 -> 0 | I30: =I28-I29 -> 0 | J30: =J28-J29 -> 0 | ... L30: =L28-L29 -> 0
A32: Bridge line items follow Broadcom's as-filed CF statement; capex sign is negative (outflow). "Other non-cash operating items" = impairment on investments, non-cash debt-extinguishment loss, non-cash restructuring, non-cash interest, excess tax benefit from SBC, and residual "Other".
A33: FY2024 net debt issuance reflects the VMware-acquisition financing; FY2024+ dividend/buyback $ amounts are on a post-10-for-1-split share count (July 2024) vs FY2016-FY2023 pre-split.
A34: FY2025 WATERFALL CHART DATA (base + delta helper, for chart only)
A35: Component | B35: Base (invisible) | C35: Delta (visible)
A36: Net income | B36: 0 | C36: 23126
A37: D&A | B37: 23126 | C37: 8775
A38: SBC | B38: 31901 | C38: 7568
A39: Deferred tax | B39: 35461 | C39: -4008
A40: Other non-cash | B40: 35461 | C40: 576
A41: Working capital chg | B41: 27537 | C41: -8500
A42: Capex | B42: 26914 | C42: -623
A43: Dividends | B43: 15772 | C43: -11142
A44: Buybacks | B44: 13322 | C44: -2450
A45: Tax w/h buyback | B45: 9462 | C45: -3860
A46: Net debt issuance/(repay) | B46: 6650 | C46: -2812
A47: Acquisitions | B47: 6650 | C47: 0
... A51: Net change in cash (total) | B51: 0 | C51: 6830

Sheet Yearly Factor Table
A1: Broadcom Inc. — Yearly Factor Table
A2: $ in millions except per-share data | USD | FY2016-FY2025 annual | as of 2026-09-22
C3: FY2016 | D3: FY2017 | E3: FY2018 | F3: FY2019 | G3: FY2020 | H3: FY2021 | I3: FY2022 | J3: FY2023 | K3: FY2024 | L3: FY2025
C4: 2016-10-30 | D4: 2017-10-29 | E4: 2018-11-04 | F4: 2019-11-03 | G4: 2020-11-01 | H4: 2021-10-31 | I4: 2022-10-30 | J4: 2023-10-29 | K4: 2024-11-03 | L4: 2025-11-02
A6: YEARLY FACTOR TABLE — ONE COLUMN PER FISCAL YEAR
A7: Green = linked from IS/BS/CF. Black = calculated in this sheet. NOPAT = operating income less the period's as-reported income tax provision ('Income Statement' row 47) — no assumed or normalized tax rate is applied.
A8: Revenue | C8: ='Income Statement'!C14 -> 13240 | D8: ='Income Statement'!D14 -> 17636 | E8: ='Income Statement'!E14 -> 20848 | F8: ='Income Statement'!F14 -> 22597 | G8: ='Income Statement'!G14 -> 23888 | H8: ='Income Statement'!H14 -> 27450 | I8: ='Income Statement'!I14 -> 33203 | J8: ='Income Statement'!J14 -> 35819 | ... L8: ='Income Statement'!L14 -> 63887
A9: Revenue growth (YoY) | C9: n/d | D9: =(D8/C8)-1 -> 0.33202417 | E9: =(E8/D8)-1 -> 0.18212747 | F9: =(F8/E8)-1 -> 0.083892939 | G9: =(G8/F8)-1 -> 0.057131478 | H9: =(H8/G8)-1 -> 0.14911253 | I9: =(I8/H8)-1 -> 0.20958106 | J9: =(J8/I8)-1 -> 0.078788061 | K9: =(K8/J8)-1 -> 0.43985036 | L9: =(L8/K8)-1 -> 0.23874433
A10: Gross margin % | C10: ='Income Statement'!C27/C8 -> 0.44864048 | D10: ='Income Statement'!D27/D8 -> 0.48247902 | E10: ='Income Statement'!E27/E8 -> 0.51482157 | F10: ='Income Statement'!F27/F8 -> 0.55241846 | G10: ='Income Statement'!G27/G8 -> 0.5658071 | H10: ='Income Statement'!H27/H8 -> 0.61362477 | I10: ='Income Statement'!I27/I8 -> 0.66545192 | J10: ='Income Statement'!J27/J8 -> 0.68929898 | ... L10: ='Income Statement'!L27/L8 -> 0.67766525
A11: Operating margin % | C11: ='Income Statement'!C37/C8 -> -0.030891239 | D11: ='Income Statement'!D37/D8 -> 0.13512134 | E11: ='Income Statement'!E37/E8 -> 0.2463066 | F11: ='Income Statement'!F37/F8 -> 0.15240961 | G11: ='Income Statement'!G37/G8 -> 0.16803416 | H11: ='Income Statement'!H37/H8 -> 0.31034608 | I11: ='Income Statement'!I37/I8 -> 0.42842514 | J11: ='Income Statement'!J37/J8 -> 0.45246936 | ... L11: ='Income Statement'!L37/L8 -> 0.39889179
A12: EBITDA (Operating income + D&A) | C12: ='Income Statement'!C37+'Cash Flow Statement'!C16+'Cash Flow Statement'!C17 -> 2633 | D12: ='Income Statement'!D37+'Cash Flow Statement'!D16+'Cash Flow Statement'!D17 -> 7120 | E12: ='Income Statement'!E37+'Cash Flow Statement'!E16+'Cash Flow Statement'!E17 -> 9216 | F12: ='Income Statement'!F37+'Cash Flow Statement'!F16+'Cash Flow Statement'!F17 -> 9252 | G12: ='Income Statement'!G37+'Cash Flow Statement'!G16+'Cash Flow Statement'!G17 -> 10919 | H12: ='Income Statement'!H37+'Cash Flow Statement'!H16+'Cash Flow Statement'!H17 -> 14560 | I12: ='Income Statement'!I37+'Cash Flow Statement'!I16+'Cash Flow Statement'!I17 -> 19209 | J12: ='Income Statement'!J37+'Cash Flow Statement'!J16+'Cash Flow Statement'!J17 -> 20042 | ... L12: ='Income Statement'!L37+'Cash Flow Statement'!L16+'Cash Flow Statement'!L17 -> 34259
A13: EBITDA margin % | C13: =C12/C8 -> 0.19886707 | D13: =D12/D8 -> 0.40371966 | E13: =E12/E8 -> 0.44205679 | F13: =F12/F8 -> 0.40943488 | G13: =G12/G8 -> 0.45709143 | H13: =H12/H8 -> 0.53041894 | I13: =I12/I8 -> 0.57853206 | J13: =J12/J8 -> 0.55953544 | ... L13: =L12/L8 -> 0.53624368
A14: Effective tax rate (GAAP, as-reported) | C14: ='Income Statement'!C47/'Income Statement'!C46 -> -0.5799458 | D14: ='Income Statement'!D47/'Income Statement'!D46 -> 0.019178082 | E14: ='Income Statement'!E47/'Income Statement'!E46 -> -1.7786579 | F14: ='Income Statement'!F47/'Income Statement'!F46 -> -0.22911051 | G14: ='Income Statement'!G47/'Income Statement'!G46 -> -0.21203438 | H14: ='Income Statement'!H47/'Income Statement'!H46 -> 0.0042867701 | I14: ='Income Statement'!I47/'Income Statement'!I46 -> 0.075518739 | J14: ='Income Statement'!J47/'Income Statement'!J46 -> 0.0672319 | ... L14: ='Income Statement'!L47/'Income Statement'!L46 -> -0.017466673
A15: Note: shown as a memo only. NOPAT below uses the period's as-reported income tax provision (dollar amount), not this rate — Broadcom's GAAP ETR is highly volatile (one-off items incl. FY2018 TCJA remeasurement) and is not a suitable basis for a tax-rate assumption.
A16: Net margin % | C16: ='Income Statement'!C50/C8 -> -0.14055891 | D16: ='Income Statement'!D50/D8 -> 0.10115672 | E16: ='Income Statement'!E50/E8 -> 0.60485418 | F16: ='Income Statement'!F50/F8 -> 0.12054698 | G16: ='Income Statement'!G50/G8 -> 0.12391159 | H16: ='Income Statement'!H50/H8 -> 0.24539162 | I16: ='Income Statement'!I50/I8 -> 0.34620366 | J16: ='Income Statement'!J50/J8 -> 0.3931433 | ... L16: ='Income Statement'!L50/L8 -> 0.36198288
A17: (Normalized cash tax rate assumption removed — NOPAT now uses the period's actual reported income tax expense; see row 18)
A18: NOPAT = Operating income − provision for (benefit from) income taxes (as reported) | C18: ='Income Statement'!C37-'Income Statement'!C47 -> -1051 | D18: ='Income Statement'!D37-'Income Statement'!D47 -> 2348 | E18: ='Income Statement'!E37-'Income Statement'!E47 -> 13219 | F18: ='Income Statement'!F37-'Income Statement'!F47 -> 3954 | G18: ='Income Statement'!G37-'Income Statement'!G47 -> 4532 | H18: ='Income Statement'!H37-'Income Statement'!H47 -> 8490 | I18: ='Income Statement'!I37-'Income Statement'!I47 -> 13286 | J18: ='Income Statement'!J37-'Income Statement'!J47 -> 15192 | ... L18: ='Income Statement'!L37-'Income Statement'!L47 -> 25881
A19: Invested capital (period-end: debt + equity − cash) | C19: ='Balance Sheet'!C31+'Balance Sheet'!C36+'Balance Sheet'!C48-'Balance Sheet'!C15 -> 32421 | D19: ='Balance Sheet'!D31+'Balance Sheet'!D36+'Balance Sheet'!D48-'Balance Sheet'!D15 -> 29530 | E19: ='Balance Sheet'!E31+'Balance Sheet'!E36+'Balance Sheet'!E48-'Balance Sheet'!E15 -> 39858 | F19: ='Balance Sheet'!F31+'Balance Sheet'!F36+'Balance Sheet'!F48-'Balance Sheet'!F15 -> 52684 | G19: ='Balance Sheet'!G31+'Balance Sheet'!G36+'Balance Sheet'!G48-'Balance Sheet'!G15 -> 57318 | H19: ='Balance Sheet'!H31+'Balance Sheet'!H36+'Balance Sheet'!H48-'Balance Sheet'!H15 -> 52529 | I19: ='Balance Sheet'!I31+'Balance Sheet'!I36+'Balance Sheet'!I48-'Balance Sheet'!I15 -> 49808 | J19: ='Balance Sheet'!J31+'Balance Sheet'!J36+'Balance Sheet'!J48-'Balance Sheet'!J15 -> 49028 | ... L19: ='Balance Sheet'!L31+'Balance Sheet'!L36+'Balance Sheet'!L48-'Balance Sheet'!L15 -> 130250
A20: Invested capital, full-capital (debt + equity, no cash netting) | C20: ='Balance Sheet'!C31+'Balance Sheet'!C36+'Balance Sheet'!C48 -> 35518 | D20: ='Balance Sheet'!D31+'Balance Sheet'!D36+'Balance Sheet'!D48 -> 40734 | E20: ='Balance Sheet'!E31+'Balance Sheet'!E36+'Balance Sheet'!E48 -> 44150 | F20: ='Balance Sheet'!F31+'Balance Sheet'!F36+'Balance Sheet'!F48 -> 57739 | G20: ='Balance Sheet'!G31+'Balance Sheet'!G36+'Balance Sheet'!G48 -> 64936 | H20: ='Balance Sheet'!H31+'Balance Sheet'!H36+'Balance Sheet'!H48 -> 64692 | I20: ='Balance Sheet'!I31+'Balance Sheet'!I36+'Balance Sheet'!I48 -> 62224 | J20: ='Balance Sheet'!J31+'Balance Sheet'!J36+'Balance Sheet'!J48 -> 63217 | ... L20: ='Balance Sheet'!L31+'Balance Sheet'!L36+'Balance Sheet'!L48 -> 146428
A21: Operating ROIC = NOPAT / avg. invested capital | C21: n/d | D21: =D18/((D19+C19)/2) -> 0.075801843 | E21: =E18/((E19+D19)/2) -> 0.38101689 | F21: =F18/((F19+E19)/2) -> 0.085453092 | G21: =G18/((G19+F19)/2) -> 0.082398502 | H21: =H18/((H19+G19)/2) -> 0.15457864 | I21: =I18/((I19+H19)/2) -> 0.25965193 | J21: =J18/((J19+I19)/2) -> 0.30741835 | K21: =K18/((K19+J19)/2) -> 0.11107681 | L21: =L18/((L19+K19)/2) -> 0.20208006
A22: Full-capital ROIC = NOPAT / avg. full-capital invested capital | C22: n/d | D22: =D18/((D20+C20)/2) -> 0.06158527 | E22: =E18/((E20+D20)/2) -> 0.31146035 | F22: =F18/((F20+E20)/2) -> 0.077613874 | G22: =G18/((G20+F20)/2) -> 0.073886285 | H22: =H18/((H20+G20)/2) -> 0.13099022 | I22: =I18/((I20+H20)/2) -> 0.20936683 | J22: =J18/((J20+I20)/2) -> 0.24221746 | K22: =K18/((K20+J20)/2) -> 0.097903366 | L22: =L18/((L20+K20)/2) -> 0.18376693
A23: Asset turnover = revenue / avg. total assets | C23: n/d | D23: =D8/(('Balance Sheet'!D26+'Balance Sheet'!C26)/2) -> 0.33790619 | E23: =E8/(('Balance Sheet'!E26+'Balance Sheet'!D26)/2) -> 0.39884448 | F23: =F8/(('Balance Sheet'!F26+'Balance Sheet'!E26)/2) -> 0.38424718 | G23: =G8/(('Balance Sheet'!G26+'Balance Sheet'!F26)/2) -> 0.33310557 | H23: =H8/(('Balance Sheet'!H26+'Balance Sheet'!G26)/2) -> 0.36236906 | I23: =I8/(('Balance Sheet'!I26+'Balance Sheet'!H26)/2) -> 0.4462199 | J23: =J8/(('Balance Sheet'!J26+'Balance Sheet'!I26)/2) -> 0.49030183 | K23: =K8/(('Balance Sheet'!K26+'Balance Sheet'!J26)/2) -> 0.43247549 | L23: =L8/(('Balance Sheet'!L26+'Balance Sheet'!K26)/2) -> 0.37944746
A24: Net cash / (net debt) | C24: ='Balance Sheet'!C15-'Balance Sheet'!C31-'Balance Sheet'!C36 -> -10545 | D24: ='Balance Sheet'!D15-'Balance Sheet'!D31-'Balance Sheet'!D36 -> -6344 | E24: ='Balance Sheet'!E15-'Balance Sheet'!E31-'Balance Sheet'!E36 -> -13201 | F24: ='Balance Sheet'!F15-'Balance Sheet'!F31-'Balance Sheet'!F36 -> -27743 | G24: ='Balance Sheet'!G15-'Balance Sheet'!G31-'Balance Sheet'!G36 -> -33444 | H24: ='Balance Sheet'!H15-'Balance Sheet'!H31-'Balance Sheet'!H36 -> -27567 | I24: ='Balance Sheet'!I15-'Balance Sheet'!I31-'Balance Sheet'!I36 -> -27099 | J24: ='Balance Sheet'!J15-'Balance Sheet'!J31-'Balance Sheet'!J36 -> -25040 | ... L24: ='Balance Sheet'!L15-'Balance Sheet'!L31-'Balance Sheet'!L36 -> -48958
A25: Cash flow from operations (linked) | C25: ='Cash Flow Statement'!C33 -> 3411 | D25: ='Cash Flow Statement'!D33 -> 6551 | E25: ='Cash Flow Statement'!E33 -> 8880 | F25: ='Cash Flow Statement'!F33 -> 9697 | G25: ='Cash Flow Statement'!G33 -> 12061 | H25: ='Cash Flow Statement'!H33 -> 13764 | I25: ='Cash Flow Statement'!I33 -> 16736 | J25: ='Cash Flow Statement'!J33 -> 18085 | ... L25: ='Cash Flow Statement'!L33 -> 27537
A26: Capital expenditures (linked) | C26: ='Cash Flow Statement'!C36 -> -723 | D26: ='Cash Flow Statement'!D36 -> -1069 | E26: ='Cash Flow Statement'!E36 -> -635 | F26: ='Cash Flow Statement'!F36 -> -432 | G26: ='Cash Flow Statement'!G36 -> -463 | H26: ='Cash Flow Statement'!H36 -> -443 | I26: ='Cash Flow Statement'!I36 -> -424 | J26: ='Cash Flow Statement'!J36 -> -452 | ... L26: ='Cash Flow Statement'!L36 -> -623
A27: Free cash flow = CFO + capex | C27: =C25+C26 -> 2688 | D27: =D25+D26 -> 5482 | E27: =E25+E26 -> 8245 | F27: =F25+F26 -> 9265 | G27: =G25+G26 -> 11598 | H27: =H25+H26 -> 13321 | I27: =I25+I26 -> 16312 | J27: =J25+J26 -> 17633 | ... L27: =L25+L26 -> 26914
A28: FCF margin % | C28: =C27/C8 -> 0.20302115 | D28: =D27/D8 -> 0.31084146 | E28: =E27/E8 -> 0.39548158 | F28: =F27/F8 -> 0.41001018 | G28: =G27/G8 -> 0.48551574 | H28: =H27/H8 -> 0.48528233 | I28: =I27/I8 -> 0.49128091 | J28: =J27/J8 -> 0.49228063 | ... L28: =L27/L8 -> 0.42127506
A29: Net income (linked, for conversion ratios) | C29: ='Income Statement'!C50 -> -1861 | D29: ='Income Statement'!D50 -> 1784 | E29: ='Income Statement'!E50 -> 12610 | F29: ='Income Statement'!F50 -> 2724 | G29: ='Income Statement'!G50 -> 2960 | H29: ='Income Statement'!H50 -> 6736 | I29: ='Income Statement'!I50 -> 11495 | J29: ='Income Statement'!J50 -> 14082 | ... L29: ='Income Statement'!L50 -> 23126
A30: OCF conversion = CFO / net income | C30: n/m | D30: =D25/D29 -> 3.6720852 | E30: =E25/E29 -> 0.70420301 | F30: =F25/F29 -> 3.5598385 | G30: =G25/G29 -> 4.0746622 | H30: =H25/H29 -> 2.0433492 | I30: =I25/I29 -> 1.4559374 | J30: =J25/J29 -> 1.2842636 | K30: =K25/K29 -> 3.3862595 | L30: =L25/L29 -> 1.1907377
A31: FCF conversion = FCF / net income | C31: n/m | D31: =D27/D29 -> 3.07287 | E31: =E27/E29 -> 0.65384615 | F31: =F27/F29 -> 3.4012482 | G31: =G27/G29 -> 3.9182432 | H31: =H27/H29 -> 1.9775831 | I31: =I27/I29 -> 1.4190518 | J31: =J27/J29 -> 1.2521659 | K31: =K27/K29 -> 3.2932994 | L31: =L27/L29 -> 1.1637983
A32: Diluted weighted-average shares outstanding (linked) | C32: ='Income Statement'!C62 -> 383 | D32: ='Income Statement'!D62 -> 421 | E32: ='Income Statement'!E62 -> 431 | F32: ='Income Statement'!F62 -> 419 | G32: ='Income Statement'!G62 -> 421 | H32: ='Income Statement'!H62 -> 429 | I32: ='Income Statement'!I62 -> 423 | J32: ='Income Statement'!J62 -> 427 | ... L32: ='Income Statement'!L62 -> 4853
A33: Dividends paid, gross $ (linked, sign-flipped to positive) | C33: =-'Cash Flow Statement'!C52 -> 750 | D33: =-'Cash Flow Statement'!D52 -> 1745 | E33: =-'Cash Flow Statement'!E52 -> 2998 | F33: =-'Cash Flow Statement'!F52 -> 4235 | G33: =-'Cash Flow Statement'!G52 -> 5534 | H33: =-'Cash Flow Statement'!H52 -> 6212 | I33: =-'Cash Flow Statement'!I52 -> 7032 | J33: =-'Cash Flow Statement'!J52 -> 7645 | ... L33: =-'Cash Flow Statement'!L52 -> 11142
A34: Dividend per share (implied = dividends paid / diluted shares) — analyst-calculated | C34: =C33/C32 -> 1.9582245 | D34: =D33/D32 -> 4.1448931 | E34: =E33/E32 -> 6.9559165 | F34: =F33/F32 -> 10.107399 | G34: =G33/G32 -> 13.144893 | H34: =H33/H32 -> 14.480186 | I34: =I33/I32 -> 16.624113 | J34: =J33/J32 -> 17.903981 | ... L34: =L33/L32 -> 2.2958994
A35: Buybacks, gross $ (open-market repurchases, linked, sign-flipped) | C35: =-'Cash Flow Statement'!C53 -> 0 | D35: =-'Cash Flow Statement'!D53 -> 0 | E35: =-'Cash Flow Statement'!E53 -> 7258 | F35: =-'Cash Flow Statement'!F53 -> 5435 | G35: =-'Cash Flow Statement'!G53 -> 0 | H35: =-'Cash Flow Statement'!H53 -> 0 | I35: =-'Cash Flow Statement'!I53 -> 7000 | J35: =-'Cash Flow Statement'!J53 -> 5824 | ... L35: =-'Cash Flow Statement'!L53 -> 2450
A36: Payout ratio = (dividends + buybacks) / net income | C36: n/m | D36: =(D33+D35)/D29 -> 0.97813901 | E36: =(E33+E35)/E29 -> 0.81332276 | F36: =(F33+F35)/F29 -> 3.5499266 | G36: =(G33+G35)/G29 -> 1.8695946 | H36: =(H33+H35)/H29 -> 0.92220903 | I36: =(I33+I35)/I29 -> 1.2207047 | J36: =(J33+J35)/J29 -> 0.95646925 | K36: =(K33+K35)/K29 -> 2.8821035 | L36: =(L33+L35)/L29 -> 0.58773675
A37: Cash earnings = CFO − working-capital change | C37: =C25-('Cash Flow Statement'!C26+'Cash Flow Statement'!C27+'Cash Flow Statement'!C28+'Cash Flow Statement'!C29+'Cash Flow Statement'!C30+'Cash Flow Statement'!C31+'Cash Flow Statement'!C32) -> 2928 | D37: =D25-('Cash Flow Statement'!D26+'Cash Flow Statement'!D27+'Cash Flow Statement'!D28+'Cash Flow Statement'!D29+'Cash Flow Statement'!D30+'Cash Flow Statement'!D31+'Cash Flow Statement'!D32) -> 7537 | E37: =E25-('Cash Flow Statement'!E26+'Cash Flow Statement'!E27+'Cash Flow Statement'!E28+'Cash Flow Statement'!E29+'Cash Flow Statement'!E30+'Cash Flow Statement'!E31+'Cash Flow Statement'!E32) -> 9836 | F37: =F25-('Cash Flow Statement'!F26+'Cash Flow Statement'!F27+'Cash Flow Statement'!F28+'Cash Flow Statement'!F29+'Cash Flow Statement'!F30+'Cash Flow Statement'!F31+'Cash Flow Statement'!F32) -> 9881 | G37: =G25-('Cash Flow Statement'!G26+'Cash Flow Statement'!G27+'Cash Flow Statement'!G28+'Cash Flow Statement'!G29+'Cash Flow Statement'!G30+'Cash Flow Statement'!G31+'Cash Flow Statement'!G32) -> 10968 | H37: =H25-('Cash Flow Statement'!H26+'Cash Flow Statement'!H27+'Cash Flow Statement'!H28+'Cash Flow Statement'!H29+'Cash Flow Statement'!H30+'Cash Flow Statement'!H31+'Cash Flow Statement'!H32) -> 13891 | I37: =I25-('Cash Flow Statement'!I26+'Cash Flow Statement'!I27+'Cash Flow Statement'!I28+'Cash Flow Statement'!I29+'Cash Flow Statement'!I30+'Cash Flow Statement'!I31+'Cash Flow Statement'!I32) -> 18390 | J37: =J25-('Cash Flow Statement'!J26+'Cash Flow Statement'!J27+'Cash Flow Statement'!J28+'Cash Flow Statement'!J29+'Cash Flow Statement'!J30+'Cash Flow Statement'!J31+'Cash Flow Statement'!J32) -> 19728 | ... L37: =L25-('Cash Flow Statement'!L26+'Cash Flow Statement'!L27+'Cash Flow Statement'!L28+'Cash Flow Statement'!L29+'Cash Flow Statement'!L30+'Cash Flow Statement'!L31+'Cash Flow Statement'!L32) -> 36037
A38: Cash earnings per share (diluted) — analyst-calculated | C38: =C37/C32 -> 7.6449086 | D38: =D37/D32 -> 17.902613 | E38: =E37/E32 -> 22.821346 | F38: =F37/F32 -> 23.582339 | G38: =G37/G32 -> 26.052257 | H38: =H37/H32 -> 32.379953 | I38: =I37/I32 -> 43.475177 | J38: =J37/J32 -> 46.201405 | ... L38: =L37/L32 -> 7.4257161
A40: Payout ratio and OCF/FCF conversion marked "n/m" (not meaningful) when net income <= 0 (FY2016), per metric-catalog guidance.
A41: DPS, cash EPS and diluted share count are NOT comparable pre- vs post- the 10-for-1 forward stock split (effective July 2024): FY2016-FY2023 figures are pre-split (~10x fewer, larger-denomination shares).
A42: No Broadcom-defined (issuer) APM figures (e.g. adjusted EBITDA, non-GAAP EPS) are blended into this table — all figures above are either as-reported statutory line items (linked, green) or analyst-calculated (black).

Sheet Interval Factor Table
A1: Broadcom Inc. — Interval Factor Table
A2: $ in millions | USD | cumulative/trailing windows, explicit per column | as of 2026-09-22
C3: Trailing 3-year (FY2023-FY2025, n=3) | D3: Trailing 5-year (FY2021-FY2025, n=5) | E3: Full window (FY2016-FY2025) (FY2016-FY2025, n=10)
A6: CUMULATIVE CONVERSION & DISTRIBUTION METRICS
A7: Each window sums CFO, capex, net income, dividends and buybacks over the labeled fiscal years (as-reported annual figures, linked), then computes the ratio on cumulative $ — not an average of yearly ratios.
A8: Cumulative CFO ($) | C8: 65584 | D8: 96084 | E8: 136684
A9: Cumulative capex ($) | C9: -1623 | D9: -2490 | E9: -5812
A10: Cumulative FCF ($) | C10: 63961 | D10: 93594 | E10: 130872
A11: Cumulative net income ($) | C11: 43103 | D11: 61334 | E11: 79551
A12: Cumulative OCF conversion (CFO / NI) | C12: 1.5215646 | D12: 1.5665699 | E12: 1.7181934
A13: Cumulative FCF conversion (FCF / NI) | C13: 1.4839106 | D13: 1.5259725 | E13: 1.6451333
A14: Cumulative dividends paid ($) | C14: 28601 | D14: 41845 | E14: 57107
A15: Cumulative buybacks ($) | C15: 15450 | D15: 22450 | E15: 35143
A16: Cumulative dividends + buybacks ($) | C16: 44051 | D16: 64295 | E16: 92250
A17: Cumulative payout ratio (div / cumulative NI) | C17: =C14/C11 -> 0.6635501 | D17: =D14/D11 -> 0.68224802 | E17: =E14/E11 -> 0.71786653
A18: Cumulative payout ratio ((div+bb) / cumulative NI) | C18: 1.0219938 | D18: 1.0482766 | E18: 1.1596334
A19: Cumulative (dividends + buybacks) / cumulative FCF | C19: 0.68871656 | D19: 0.68695643 | E19: 0.70488722
A21: Windows chosen: trailing 3-year and trailing 5-year (most decision-relevant recent history) plus the full FY2016-FY2025 window supported by the base workbook. All three windows include FY2024 (VMware acquisition close, 10-for-1 split) — treat cumulative per-year comparisons across the split date with care (dividend/buyback $ totals are unaffected by the split; only per-share figures are).
A22: No issuer-defined APM used; all inputs are as-reported statutory CFO/capex/net income/dividends/buybacks, linked from Cash Flow Statement and Income Statement.

Sheet Growth Factor Table
A1: Broadcom Inc. — Growth Factor Table
A2: $ in millions | USD | CAGR = (ending/beginning)^(1/n)-1, positive endpoints only | as of 2026-09-22
C3: Full/available window CAGR | D3: Shorter window CAGR (FY2020-FY2025, n=5) | E3: Window & notes
A6: GROWTH FACTOR TABLE — CAGR
A7: CAGR requires positive endpoints; FY2016 Operating income (-409) and Net income (-1,861) are negative, so those two rows substitute FY2017 as the full-window start (8-yr CAGR) — see notes column.
A8: Revenue | C8: 0.1910971 | D8: 0.21743712 | E8: FY2016→FY2025 (n=9)
A9: Cost of goods/services (total COGS) | C9: 0.12213235 | D9: 0.14702114 | E9: FY2016→FY2025 (n=9)
A10: Operating profit | C10: 0.34475431 | D10: 0.44723163 | E10: FY2017→FY2025 (n=8) — substituted for FY2016 start (negative base)
A11: Net income | C11: 0.37748922 | D11: 0.50855713 | E11: FY2017→FY2025 (n=8) — substituted for FY2016 start (negative base)
A12: Normalized EBIT (disclosed one-off addbacks only) | C12: 0.34389038 | D12: 0.43840508 | E12: FY2016→FY2025 (n=9)
A13: Cash earnings (CFO − working-capital change) | C13: 0.32169376 | D13: 0.26859863 | E13: FY2016→FY2025 (n=9)
A15: Shorter window FY2020-FY2025 (n=5) chosen: long enough to smooth annual noise, short enough to be decision-relevant, and all six series are positive at FY2020 (no zero-crossing).
A16: Both windows span the VMware acquisition close (2023-11-22, within FY2024) and the FY2024 4-segment→... structural change is not applicable here, but the FY2024 scale jump is structural (M&A), not organic — do not read either CAGR as a pure organic growth rate.
A17: COGS and Products/Subscriptions cost splits: FY2025 10-K reclassified the split (not applied retroactively); "Total COGS" here is the as-filed consolidated total each year, unaffected by the sub-line reclass, so the COGS CAGR is comparability-safe.
