Workbook

Sheet Contents
A1: Intel Corporation — Research workbook | B1: Intel Corporation — Research workbook | C1: Intel Corporation — Research workbook | D1: Intel Corporation — Research workbook | E1: Intel Corporation — Research workbook | F1: Intel Corporation — Research workbook | G1: Intel Corporation — Research workbook | H1: Intel Corporation — Research workbook
A2: USD million unless stated otherwise; annual FY2016–FY2025; latest interim 27 June 2026.
A4: Historical actuals and derived metrics
A6: Segments | C6: Segment revenue, profit and reporting frameworks
A7: Revenue & Operations | C7: Geography, customers, operating drivers and KPIs
A8: Income Statement | C8: Consolidated profit, EPS and reconciliations
A9: Balance Sheet | C9: Assets, liabilities and equity
A10: Cash Flow | C10: YTD cash flows, capital expenditure and free cash flow
A11: Derivate Metrics | C11: Profitability, working capital, net cash and operating ROIC
A12: Assets & Investments | C12: Investments, inventories, PP&E, goodwill and intangibles
A13: Debt & Leases | C13: Borrowings, maturities, interest and lease disclosures
A14: Capital & Shareholders | C14: Equity, dividends, repurchases and share-based compensation
A15: Taxes & Adjustments | C15: Taxes, restructuring and company non-GAAP reconciliations
A18: Scope: FY2016–FY2025 and available quarters through Q2 2026. USD million unless stated. | B18: Scope: FY2016–FY2025 and available quarters through Q2 2026. USD million unless stated. | C18: Scope: FY2016–FY2025 and available quarters through Q2 2026. USD million unless stated. | D18: Scope: FY2016–FY2025 and available quarters through Q2 2026. USD million unless stated. | E18: Scope: FY2016–FY2025 and available quarters through Q2 2026. USD million unless stated. | F18: Scope: FY2016–FY2025 and available quarters through Q2 2026. USD million unless stated. | G18: Scope: FY2016–FY2025 and available quarters through Q2 2026. USD million unless stated. | H18: Scope: FY2016–FY2025 and available quarters through Q2 2026. USD million unless stated.
A19: Cash Flow uses YTD; Derivate Metrics uses TTM flows. Balance-sheet data are period-end amounts. | B19: Cash Flow uses YTD; Derivate Metrics uses TTM flows. Balance-sheet data are period-end amounts. | C19: Cash Flow uses YTD; Derivate Metrics uses TTM flows. Balance-sheet data are period-end amounts. | D19: Cash Flow uses YTD; Derivate Metrics uses TTM flows. Balance-sheet data are period-end amounts. | E19: Cash Flow uses YTD; Derivate Metrics uses TTM flows. Balance-sheet data are period-end amounts. | F19: Cash Flow uses YTD; Derivate Metrics uses TTM flows. Balance-sheet data are period-end amounts. | G19: Cash Flow uses YTD; Derivate Metrics uses TTM flows. Balance-sheet data are period-end amounts. | H19: Cash Flow uses YTD; Derivate Metrics uses TTM flows. Balance-sheet data are period-end amounts.
A20: Unavailable values are blank; n.m. marks rates that are not meaningful. Q1/Q2 2023 balance sheets were not supplied. | B20: Unavailable values are blank; n.m. marks rates that are not meaningful. Q1/Q2 2023 balance sheets were not supplied. | C20: Unavailable values are blank; n.m. marks rates that are not meaningful. Q1/Q2 2023 balance sheets were not supplied. | D20: Unavailable values are blank; n.m. marks rates that are not meaningful. Q1/Q2 2023 balance sheets were not supplied. | E20: Unavailable values are blank; n.m. marks rates that are not meaningful. Q1/Q2 2023 balance sheets were not supplied. | F20: Unavailable values are blank; n.m. marks rates that are not meaningful. Q1/Q2 2023 balance sheets were not supplied. | G20: Unavailable values are blank; n.m. marks rates that are not meaningful. Q1/Q2 2023 balance sheets were not supplied. | H20: Unavailable values are blank; n.m. marks rates that are not meaningful. Q1/Q2 2023 balance sheets were not supplied.
A21: Source mappings and review records are retained outside this workbook. | B21: Source mappings and review records are retained outside this workbook. | C21: Source mappings and review records are retained outside this workbook. | D21: Source mappings and review records are retained outside this workbook. | E21: Source mappings and review records are retained outside this workbook. | F21: Source mappings and review records are retained outside this workbook. | G21: Source mappings and review records are retained outside this workbook. | H21: Source mappings and review records are retained outside this workbook.

Sheet Segments
A1: Intel Corporation — Segments | B1: Intel Corporation — Segments | C1: Intel Corporation — Segments | D1: Intel Corporation — Segments | E1: Intel Corporation — Segments | F1: Intel Corporation — Segments | G1: Intel Corporation — Segments | H1: Intel Corporation — Segments | I1: Intel Corporation — Segments | J1: Intel Corporation — Segments | K1: Intel Corporation — Segments | L1: Intel Corporation — Segments | M1: Intel Corporation — Segments | N1: Intel Corporation — Segments | O1: Intel Corporation — Segments | P1: Intel Corporation — Segments | Q1: Intel Corporation — Segments | R1: Intel Corporation — Segments | S1: Intel Corporation — Segments | T1: Intel Corporation — Segments | U1: Intel Corporation — Segments | V1: Intel Corporation — Segments | W1: Intel Corporation — Segments | X1: Intel Corporation — Segments | Y1: Intel Corporation — Segments | Z1: Intel Corporation — Segments | AA1: Intel Corporation — Segments
A2: USD million unless stated otherwise; annual FY2016–FY2025; latest interim 27 June 2026.
A3: Metric | C3: FY2016 | D3: FY2017 | E3: FY2018 | F3: FY2019 | G3: FY2020 | H3: FY2021 | I3: FY2022 | J3: FY2023 | K3: FY2024 | L3: FY2025 | N3: 1Q2023 | O3: 2Q2023 | P3: 3Q2023 | Q3: 4Q2023 | R3: 1Q2024 | S3: 2Q2024 | T3: 3Q2024 | U3: 4Q2024 | V3: 1Q2025 | W3: 2Q2025 | X3: 3Q2025 | Y3: 4Q2025 | Z3: 1Q2026 | AA3: 2Q2026
C4: 2016-12-31T00:00:00.000Z | D4: 2017-12-30T00:00:00.000Z | E4: 2018-12-29T00:00:00.000Z | F4: 2019-12-28T00:00:00.000Z | G4: 2020-12-26T00:00:00.000Z | H4: 2021-12-25T00:00:00.000Z | I4: 2022-12-31T00:00:00.000Z | J4: 2023-12-30T00:00:00.000Z | K4: 2024-12-28T00:00:00.000Z | L4: 2025-12-27T00:00:00.000Z | N4: 2023-04-01T00:00:00.000Z | O4: 2023-07-01T00:00:00.000Z | P4: 2023-09-30T00:00:00.000Z | Q4: 2023-12-30T00:00:00.000Z | R4: 2024-03-30T00:00:00.000Z | S4: 2024-06-29T00:00:00.000Z | T4: 2024-09-28T00:00:00.000Z | U4: 2024-12-28T00:00:00.000Z | V4: 2025-03-29T00:00:00.000Z | W4: 2025-06-28T00:00:00.000Z | X4: 2025-09-27T00:00:00.000Z | Y4: 2025-12-27T00:00:00.000Z | Z4: 2026-03-28T00:00:00.000Z | AA4: 2026-06-27T00:00:00.000Z
A5: Annual / discrete-quarter / instant as identified | C5: Annual | D5: Annual | E5: Annual | F5: Annual | G5: Annual | H5: Annual | I5: Annual | J5: Annual | K5: Annual | L5: Annual | N5: Quarter / note basis | O5: Quarter / note basis | P5: Quarter / note basis | Q5: Quarter / note basis | R5: Quarter / note basis | S5: Quarter / note basis | T5: Quarter / note basis | U5: Quarter / note basis | V5: Quarter / note basis | W5: Quarter / note basis | X5: Quarter / note basis | Y5: Quarter / note basis | Z5: Quarter / note basis | AA5: Quarter / note basis
A7: 2025 reporting framework: Net revenue | B7: 2025 reporting framework: Net revenue | C7: 2025 reporting framework: Net revenue | D7: 2025 reporting framework: Net revenue | E7: 2025 reporting framework: Net revenue | F7: 2025 reporting framework: Net revenue | G7: 2025 reporting framework: Net revenue | H7: 2025 reporting framework: Net revenue | I7: 2025 reporting framework: Net revenue | J7: 2025 reporting framework: Net revenue | K7: 2025 reporting framework: Net revenue | L7: 2025 reporting framework: Net revenue | M7: 2025 reporting framework: Net revenue | N7: 2025 reporting framework: Net revenue | O7: 2025 reporting framework: Net revenue | P7: 2025 reporting framework: Net revenue | Q7: 2025 reporting framework: Net revenue | R7: 2025 reporting framework: Net revenue | S7: 2025 reporting framework: Net revenue | T7: 2025 reporting framework: Net revenue | U7: 2025 reporting framework: Net revenue | V7: 2025 reporting framework: Net revenue | W7: 2025 reporting framework: Net revenue | X7: 2025 reporting framework: Net revenue | Y7: 2025 reporting framework: Net revenue | Z7: 2025 reporting framework: Net revenue | AA7: 2025 reporting framework: Net revenue
A8: 2023–2025 annuals use the 2025 segment framework. Q2 2026 CCPG is the renamed CCG where source comparatives agree; legacy frameworks below are not spliced into this series. | B8: 2023–2025 annuals use the 2025 segment framework. Q2 2026 CCPG is the renamed CCG where source comparatives agree; legacy frameworks below are not spliced into this series. | C8: 2023–2025 annuals use the 2025 segment framework. Q2 2026 CCPG is the renamed CCG where source comparatives agree; legacy frameworks below are not spliced into this series. | D8: 2023–2025 annuals use the 2025 segment framework. Q2 2026 CCPG is the renamed CCG where source comparatives agree; legacy frameworks below are not spliced into this series. | E8: 2023–2025 annuals use the 2025 segment framework. Q2 2026 CCPG is the renamed CCG where source comparatives agree; legacy frameworks below are not spliced into this series. | F8: 2023–2025 annuals use the 2025 segment framework. Q2 2026 CCPG is the renamed CCG where source comparatives agree; legacy frameworks below are not spliced into this series. | G8: 2023–2025 annuals use the 2025 segment framework. Q2 2026 CCPG is the renamed CCG where source comparatives agree; legacy frameworks below are not spliced into this series. | H8: 2023–2025 annuals use the 2025 segment framework. Q2 2026 CCPG is the renamed CCG where source comparatives agree; legacy frameworks below are not spliced into this series. | I8: 2023–2025 annuals use the 2025 segment framework. Q2 2026 CCPG is the renamed CCG where source comparatives agree; legacy frameworks below are not spliced into this series. | J8: 2023–2025 annuals use the 2025 segment framework. Q2 2026 CCPG is the renamed CCG where source comparatives agree; legacy frameworks below are not spliced into this series. | K8: 2023–2025 annuals use the 2025 segment framework. Q2 2026 CCPG is the renamed CCG where source comparatives agree; legacy frameworks below are not spliced into this series. | L8: 2023–2025 annuals use the 2025 segment framework. Q2 2026 CCPG is the renamed CCG where source comparatives agree; legacy frameworks below are not spliced into this series. | M8: 2023–2025 annuals use the 2025 segment framework. Q2 2026 CCPG is the renamed CCG where source comparatives agree; legacy frameworks below are not spliced into this series. | N8: 2023–2025 annuals use the 2025 segment framework. Q2 2026 CCPG is the renamed CCG where source comparatives agree; legacy frameworks below are not spliced into this series. | O8: 2023–2025 annuals use the 2025 segment framework. Q2 2026 CCPG is the renamed CCG where source comparatives agree; legacy frameworks below are not spliced into this series. | P8: 2023–2025 annuals use the 2025 segment framework. Q2 2026 CCPG is the renamed CCG where source comparatives agree; legacy frameworks below are not spliced into this series. | Q8: 2023–2025 annuals use the 2025 segment framework. Q2 2026 CCPG is the renamed CCG where source comparatives agree; legacy frameworks below are not spliced into this series. | R8: 2023–2025 annuals use the 2025 segment framework. Q2 2026 CCPG is the renamed CCG where source comparatives agree; legacy frameworks below are not spliced into this series. | S8: 2023–2025 annuals use the 2025 segment framework. Q2 2026 CCPG is the renamed CCG where source comparatives agree; legacy frameworks below are not spliced into this series. | T8: 2023–2025 annuals use the 2025 segment framework. Q2 2026 CCPG is the renamed CCG where source comparatives agree; legacy frameworks below are not spliced into this series. | U8: 2023–2025 annuals use the 2025 segment framework. Q2 2026 CCPG is the renamed CCG where source comparatives agree; legacy frameworks below are not spliced into this series. | V8: 2023–2025 annuals use the 2025 segment framework. Q2 2026 CCPG is the renamed CCG where source comparatives agree; legacy frameworks below are not spliced into this series. | W8: 2023–2025 annuals use the 2025 segment framework. Q2 2026 CCPG is the renamed CCG where source comparatives agree; legacy frameworks below are not spliced into this series. | X8: 2023–2025 annuals use the 2025 segment framework. Q2 2026 CCPG is the renamed CCG where source comparatives agree; legacy frameworks below are not spliced into this series. | Y8: 2023–2025 annuals use the 2025 segment framework. Q2 2026 CCPG is the renamed CCG where source comparatives agree; legacy frameworks below are not spliced into this series. | Z8: 2023–2025 annuals use the 2025 segment framework. Q2 2026 CCPG is the renamed CCG where source comparatives agree; legacy frameworks below are not spliced into this series. | AA8: 2023–2025 annuals use the 2025 segment framework. Q2 2026 CCPG is the renamed CCG where source comparatives agree; legacy frameworks below are not spliced into this series.
A9: Revenue - CCG | J9: 32305 | K9: 33346 | L9: 32228 | Q9: =IF(COUNT(J9,N9,O9,P9)=4,J9-N9-O9-P9,"") | R9: 8273 | S9: 8143 | T9: 8161 | U9: =IF(COUNT(K9,R9,S9,T9)=4,K9-R9-S9-T9,"") -> 8769 | V9: 7629 | W9: 7871 | X9: 8535 | Y9: =IF(COUNT(L9,V9,W9,X9)=4,L9-V9-W9-X9,"") -> 8193 | Z9: 7727 | AA9: 8877
A10: Revenue - DCAI | J10: 15980 | K10: 16125 | L10: 16919 | Q10: =IF(COUNT(J10,N10,O10,P10)=4,J10-N10-O10-P10,"") | R10: 3828 | S10: 3805 | T10: 4141 | U10: =IF(COUNT(K10,R10,S10,T10)=4,K10-R10-S10-T10,"") -> 4351 | V10: 4126 | W10: 3939 | X10: 4117 | Y10: =IF(COUNT(L10,V10,W10,X10)=4,L10-V10-W10-X10,"") -> 4737 | Z10: 5052 | AA10: 6262
A11: Revenue - Total Intel Products | J11: 48285 | K11: 49471 | L11: 49147 | Q11: =IF(COUNT(J11,N11,O11,P11)=4,J11-N11-O11-P11,"") | R11: 12101 | S11: 11948 | T11: 12302 | U11: =IF(COUNT(K11,R11,S11,T11)=4,K11-R11-S11-T11,"") -> 13120 | V11: 11755 | W11: 11810 | X11: 12652 | Y11: =IF(COUNT(L11,V11,W11,X11)=4,L11-V11-W11-X11,"") -> 12930 | Z11: 12779 | AA11: 15139
A12: Revenue - Intel Foundry | J12: 18504 | K12: 17317 | L12: 17826 | Q12: =IF(COUNT(J12,N12,O12,P12)=4,J12-N12-O12-P12,"") | R12: 4356 | S12: 4282 | T12: 4339 | U12: =IF(COUNT(K12,R12,S12,T12)=4,K12-R12-S12-T12,"") -> 4340 | V12: 4667 | W12: 4417 | X12: 4235 | Y12: =IF(COUNT(L12,V12,W12,X12)=4,L12-V12-W12-X12,"") -> 4507 | Z12: 5421 | AA12: 5765
A13: Revenue - All Other | J13: 5463 | K13: 3601 | L13: 3563 | Q13: =IF(COUNT(J13,N13,O13,P13)=4,J13-N13-O13-P13,"") | R13: 643 | S13: 881 | T13: 964 | U13: =IF(COUNT(K13,R13,S13,T13)=4,K13-R13-S13-T13,"") -> 1113 | V13: 943 | W13: 1053 | X13: 993 | Y13: =IF(COUNT(L13,V13,W13,X13)=4,L13-V13-W13-X13,"") -> 574 | Z13: 628 | AA13: 701
A14: Revenue - Corporate Unallocated | J14: 0 | K14: 0 | L14: 0 | Q14: =IF(COUNT(J14,N14,O14,P14)=4,J14-N14-O14-P14,"") | R14: 0 | S14: 0 | T14: 0 | U14: =IF(COUNT(K14,R14,S14,T14)=4,K14-R14-S14-T14,"") -> 0 | V14: 0 | W14: 0 | X14: 0 | Y14: =IF(COUNT(L14,V14,W14,X14)=4,L14-V14-W14-X14,"") -> 0 | Z14: 0 | AA14: 0
A15: Revenue - Intersegment Eliminations | J15: -18024 | K15: -17288 | L15: -17683 | Q15: =IF(COUNT(J15,N15,O15,P15)=4,J15-N15-O15-P15,"") | R15: -4376 | S15: -4278 | T15: -4321 | U15: =IF(COUNT(K15,R15,S15,T15)=4,K15-R15-S15-T15,"") -> -4313 | V15: -4698 | W15: -4421 | X15: -4227 | Y15: =IF(COUNT(L15,V15,W15,X15)=4,L15-V15-W15-X15,"") -> -4337 | Z15: -5251 | AA15: -5477
A16: Revenue - Total Consolidated | J16: 54228 | K16: 53101 | L16: 52853 | Q16: =IF(COUNT(J16,N16,O16,P16)=4,J16-N16-O16-P16,"") | R16: 12724 | S16: 12833 | T16: 13284 | U16: =IF(COUNT(K16,R16,S16,T16)=4,K16-R16-S16-T16,"") -> 14260 | V16: 12667 | W16: 12859 | X16: 13653 | Y16: =IF(COUNT(L16,V16,W16,X16)=4,L16-V16-W16-X16,"") -> 13674 | Z16: 13577 | AA16: 16128
A17: Check: segment lines - printed total (should be 0) | J17: =IF(COUNT(J9,J10,J12,J13,J14,J15,J16)=7,J9+J10+J12+J13+J14+J15-J16,"") -> 0 | K17: =IF(COUNT(K9,K10,K12,K13,K14,K15,K16)=7,K9+K10+K12+K13+K14+K15-K16,"") -> 0 | L17: =IF(COUNT(L9,L10,L12,L13,L14,L15,L16)=7,L9+L10+L12+L13+L14+L15-L16,"") -> 0 | Q17: =IF(COUNT(Q9,Q10,Q12,Q13,Q14,Q15,Q16)=7,Q9+Q10+Q12+Q13+Q14+Q15-Q16,"") | R17: =IF(COUNT(R9,R10,R12,R13,R14,R15,R16)=7,R9+R10+R12+R13+R14+R15-R16,"") -> 0 | S17: =IF(COUNT(S9,S10,S12,S13,S14,S15,S16)=7,S9+S10+S12+S13+S14+S15-S16,"") -> 0 | T17: =IF(COUNT(T9,T10,T12,T13,T14,T15,T16)=7,T9+T10+T12+T13+T14+T15-T16,"") -> 0 | U17: =IF(COUNT(U9,U10,U12,U13,U14,U15,U16)=7,U9+U10+U12+U13+U14+U15-U16,"") -> 0 | V17: =IF(COUNT(V9,V10,V12,V13,V14,V15,V16)=7,V9+V10+V12+V13+V14+V15-V16,"") -> 0 | W17: =IF(COUNT(W9,W10,W12,W13,W14,W15,W16)=7,W9+W10+W12+W13+W14+W15-W16,"") -> 0 | X17: =IF(COUNT(X9,X10,X12,X13,X14,X15,X16)=7,X9+X10+X12+X13+X14+X15-X16,"") -> 0 | ... AA17: =IF(COUNT(AA9,AA10,AA12,AA13,AA14,AA15,AA16)=7,AA9+AA10+AA12+AA13+AA14+AA15-AA16,"") -> 0
A19: 2025 reporting framework: Operating income (loss) | B19: 2025 reporting framework: Operating income (loss) | C19: 2025 reporting framework: Operating income (loss) | D19: 2025 reporting framework: Operating income (loss) | E19: 2025 reporting framework: Operating income (loss) | F19: 2025 reporting framework: Operating income (loss) | G19: 2025 reporting framework: Operating income (loss) | H19: 2025 reporting framework: Operating income (loss) | I19: 2025 reporting framework: Operating income (loss) | J19: 2025 reporting framework: Operating income (loss) | K19: 2025 reporting framework: Operating income (loss) | L19: 2025 reporting framework: Operating income (loss) | M19: 2025 reporting framework: Operating income (loss) | N19: 2025 reporting framework: Operating income (loss) | O19: 2025 reporting framework: Operating income (loss) | P19: 2025 reporting framework: Operating income (loss) | Q19: 2025 reporting framework: Operating income (loss) | R19: 2025 reporting framework: Operating income (loss) | S19: 2025 reporting framework: Operating income (loss) | T19: 2025 reporting framework: Operating income (loss) | U19: 2025 reporting framework: Operating income (loss) | V19: 2025 reporting framework: Operating income (loss) | W19: 2025 reporting framework: Operating income (loss) | X19: 2025 reporting framework: Operating income (loss) | Y19: 2025 reporting framework: Operating income (loss) | Z19: 2025 reporting framework: Operating income (loss) | AA19: 2025 reporting framework: Operating income (loss)
A20: 2023–2025 annuals use the 2025 segment framework. Q2 2026 CCPG is the renamed CCG where source comparatives agree; legacy frameworks below are not spliced into this series. | B20: 2023–2025 annuals use the 2025 segment framework. Q2 2026 CCPG is the renamed CCG where source comparatives agree; legacy frameworks below are not spliced into this series. | C20: 2023–2025 annuals use the 2025 segment framework. Q2 2026 CCPG is the renamed CCG where source comparatives agree; legacy frameworks below are not spliced into this series. | D20: 2023–2025 annuals use the 2025 segment framework. Q2 2026 CCPG is the renamed CCG where source comparatives agree; legacy frameworks below are not spliced into this series. | E20: 2023–2025 annuals use the 2025 segment framework. Q2 2026 CCPG is the renamed CCG where source comparatives agree; legacy frameworks below are not spliced into this series. | F20: 2023–2025 annuals use the 2025 segment framework. Q2 2026 CCPG is the renamed CCG where source comparatives agree; legacy frameworks below are not spliced into this series. | G20: 2023–2025 annuals use the 2025 segment framework. Q2 2026 CCPG is the renamed CCG where source comparatives agree; legacy frameworks below are not spliced into this series. | H20: 2023–2025 annuals use the 2025 segment framework. Q2 2026 CCPG is the renamed CCG where source comparatives agree; legacy frameworks below are not spliced into this series. | I20: 2023–2025 annuals use the 2025 segment framework. Q2 2026 CCPG is the renamed CCG where source comparatives agree; legacy frameworks below are not spliced into this series. | J20: 2023–2025 annuals use the 2025 segment framework. Q2 2026 CCPG is the renamed CCG where source comparatives agree; legacy frameworks below are not spliced into this series. | K20: 2023–2025 annuals use the 2025 segment framework. Q2 2026 CCPG is the renamed CCG where source comparatives agree; legacy frameworks below are not spliced into this series. | L20: 2023–2025 annuals use the 2025 segment framework. Q2 2026 CCPG is the renamed CCG where source comparatives agree; legacy frameworks below are not spliced into this series. | M20: 2023–2025 annuals use the 2025 segment framework. Q2 2026 CCPG is the renamed CCG where source comparatives agree; legacy frameworks below are not spliced into this series. | N20: 2023–2025 annuals use the 2025 segment framework. Q2 2026 CCPG is the renamed CCG where source comparatives agree; legacy frameworks below are not spliced into this series. | O20: 2023–2025 annuals use the 2025 segment framework. Q2 2026 CCPG is the renamed CCG where source comparatives agree; legacy frameworks below are not spliced into this series. | P20: 2023–2025 annuals use the 2025 segment framework. Q2 2026 CCPG is the renamed CCG where source comparatives agree; legacy frameworks below are not spliced into this series. | Q20: 2023–2025 annuals use the 2025 segment framework. Q2 2026 CCPG is the renamed CCG where source comparatives agree; legacy frameworks below are not spliced into this series. | R20: 2023–2025 annuals use the 2025 segment framework. Q2 2026 CCPG is the renamed CCG where source comparatives agree; legacy frameworks below are not spliced into this series. | S20: 2023–2025 annuals use the 2025 segment framework. Q2 2026 CCPG is the renamed CCG where source comparatives agree; legacy frameworks below are not spliced into this series. | T20: 2023–2025 annuals use the 2025 segment framework. Q2 2026 CCPG is the renamed CCG where source comparatives agree; legacy frameworks below are not spliced into this series. | U20: 2023–2025 annuals use the 2025 segment framework. Q2 2026 CCPG is the renamed CCG where source comparatives agree; legacy frameworks below are not spliced into this series. | V20: 2023–2025 annuals use the 2025 segment framework. Q2 2026 CCPG is the renamed CCG where source comparatives agree; legacy frameworks below are not spliced into this series. | W20: 2023–2025 annuals use the 2025 segment framework. Q2 2026 CCPG is the renamed CCG where source comparatives agree; legacy frameworks below are not spliced into this series. | X20: 2023–2025 annuals use the 2025 segment framework. Q2 2026 CCPG is the renamed CCG where source comparatives agree; legacy frameworks below are not spliced into this series. | Y20: 2023–2025 annuals use the 2025 segment framework. Q2 2026 CCPG is the renamed CCG where source comparatives agree; legacy frameworks below are not spliced into this series. | Z20: 2023–2025 annuals use the 2025 segment framework. Q2 2026 CCPG is the renamed CCG where source comparatives agree; legacy frameworks below are not spliced into this series. | AA20: 2023–2025 annuals use the 2025 segment framework. Q2 2026 CCPG is the renamed CCG where source comparatives agree; legacy frameworks below are not spliced into this series.
A21: Operating income (loss) - CCG | J21: 10128 | K21: 11594 | L21: 9317 | Q21: =IF(COUNT(J21,N21,O21,P21)=4,J21-N21-O21-P21,"") | R21: 2822 | S21: 2641 | T21: 2937 | U21: =IF(COUNT(K21,R21,S21,T21)=4,K21-R21-S21-T21,"") -> 3194 | V21: 2361 | W21: 2053 | X21: 2694 | Y21: =IF(COUNT(L21,V21,W21,X21)=4,L21-V21-W21-X21,"") -> 2209 | Z21: 2516 | AA21: 2343
A22: Operating income (loss) - DCAI | J22: 945 | K22: 1414 | L22: 3422 | Q22: =IF(COUNT(J22,N22,O22,P22)=4,J22-N22-O22-P22,"") | R22: 417 | S22: 242 | T22: 381 | U22: =IF(COUNT(K22,R22,S22,T22)=4,K22-R22-S22-T22,"") -> 374 | V22: 575 | W22: 633 | X22: 964 | Y22: =IF(COUNT(L22,V22,W22,X22)=4,L22-V22-W22-X22,"") -> 1250 | Z22: 1542 | AA22: 2474
A23: Operating income (loss) - Total Intel Products | J23: 11073 | K23: 13008 | L23: 12739 | Q23: =IF(COUNT(J23,N23,O23,P23)=4,J23-N23-O23-P23,"") | R23: 3239 | S23: 2883 | T23: 3318 | U23: =IF(COUNT(K23,R23,S23,T23)=4,K23-R23-S23-T23,"") -> 3568 | V23: 2936 | W23: 2686 | X23: 3658 | Y23: =IF(COUNT(L23,V23,W23,X23)=4,L23-V23-W23-X23,"") -> 3459 | Z23: 4058 | AA23: 4817
A24: Operating income (loss) - Intel Foundry | J24: -7083 | K24: -13291 | L24: -10318 | Q24: =IF(COUNT(J24,N24,O24,P24)=4,J24-N24-O24-P24,"") | R24: -2441 | S24: -2802 | T24: -5799 | U24: =IF(COUNT(K24,R24,S24,T24)=4,K24-R24-S24-T24,"") -> -2249 | V24: -2320 | W24: -3168 | X24: -2321 | Y24: =IF(COUNT(L24,V24,W24,X24)=4,L24-V24-W24-X24,"") -> -2509 | Z24: -2437 | AA24: -2089
A25: Operating income (loss) - All Other | J25: 1507 | K25: -57 | L25: 264 | Q25: =IF(COUNT(J25,N25,O25,P25)=4,J25-N25-O25-P25,"") | R25: -170 | S25: -46 | T25: 5 | U25: =IF(COUNT(K25,R25,S25,T25)=4,K25-R25-S25-T25,"") -> 154 | V25: 103 | W25: 69 | X25: 100 | Y25: =IF(COUNT(L25,V25,W25,X25)=4,L25-V25-W25-X25,"") -> -8 | Z25: 102 | AA25: 230
A26: Operating income (loss) - Corporate Unallocated | J26: -5199 | K26: -11177 | L26: -5518 | Q26: =IF(COUNT(J26,N26,O26,P26)=4,J26-N26-O26-P26,"") | R26: -2187 | S26: -1708 | T26: -6502 | U26: =IF(COUNT(K26,R26,S26,T26)=4,K26-R26-S26-T26,"") -> -780 | V26: -1260 | W26: -2755 | X26: -782 | Y26: =IF(COUNT(L26,V26,W26,X26)=4,L26-V26-W26-X26,"") -> -721 | Z26: -5080 | AA26: -1416
A27: Operating income (loss) - Intersegment Eliminations | J27: -205 | K27: -161 | L27: 619 | Q27: =IF(COUNT(J27,N27,O27,P27)=4,J27-N27-O27-P27,"") | R27: 490 | S27: -291 | T27: -79 | U27: =IF(COUNT(K27,R27,S27,T27)=4,K27-R27-S27-T27,"") -> -281 | V27: 240 | W27: -8 | X27: 28 | Y27: =IF(COUNT(L27,V27,W27,X27)=4,L27-V27-W27-X27,"") -> 359 | Z27: 221 | AA27: 254
A28: Operating income (loss) - Total Consolidated | J28: 93 | K28: -11678 | L28: -2214 | Q28: =IF(COUNT(J28,N28,O28,P28)=4,J28-N28-O28-P28,"") | R28: -1069 | S28: -1964 | T28: -9057 | U28: =IF(COUNT(K28,R28,S28,T28)=4,K28-R28-S28-T28,"") -> 412 | V28: -301 | W28: -3176 | X28: 683 | Y28: =IF(COUNT(L28,V28,W28,X28)=4,L28-V28-W28-X28,"") -> 580 | Z28: -3136 | AA28: 1796
A29: Check: segment lines - printed total (should be 0) | J29: =IF(COUNT(J21,J22,J24,J25,J26,J27,J28)=7,J21+J22+J24+J25+J26+J27-J28,"") -> 0 | K29: =IF(COUNT(K21,K22,K24,K25,K26,K27,K28)=7,K21+K22+K24+K25+K26+K27-K28,"") -> 0 | L29: =IF(COUNT(L21,L22,L24,L25,L26,L27,L28)=7,L21+L22+L24+L25+L26+L27-L28,"") -> 0 | Q29: =IF(COUNT(Q21,Q22,Q24,Q25,Q26,Q27,Q28)=7,Q21+Q22+Q24+Q25+Q26+Q27-Q28,"") | R29: =IF(COUNT(R21,R22,R24,R25,R26,R27,R28)=7,R21+R22+R24+R25+R26+R27-R28,"") -> 0 | S29: =IF(COUNT(S21,S22,S24,S25,S26,S27,S28)=7,S21+S22+S24+S25+S26+S27-S28,"") -> 0 | T29: =IF(COUNT(T21,T22,T24,T25,T26,T27,T28)=7,T21+T22+T24+T25+T26+T27-T28,"") -> 0 | U29: =IF(COUNT(U21,U22,U24,U25,U26,U27,U28)=7,U21+U22+U24+U25+U26+U27-U28,"") -> 0 | V29: =IF(COUNT(V21,V22,V24,V25,V26,V27,V28)=7,V21+V22+V24+V25+V26+V27-V28,"") -> 0 | W29: =IF(COUNT(W21,W22,W24,W25,W26,W27,W28)=7,W21+W22+W24+W25+W26+W27-W28,"") -> 0 | X29: =IF(COUNT(X21,X22,X24,X25,X26,X27,X28)=7,X21+X22+X24+X25+X26+X27-X28,"") -> 0 | ... AA29: =IF(COUNT(AA21,AA22,AA24,AA25,AA26,AA27,AA28)=7,AA21+AA22+AA24+AA25+AA26+AA27-AA28,"") -> 0
A31: 2025 reporting framework: Cost of sales and operating expenses | B31: 2025 reporting framework: Cost of sales and operating expenses | C31: 2025 reporting framework: Cost of sales and operating expenses | D31: 2025 reporting framework: Cost of sales and operating expenses | E31: 2025 reporting framework: Cost of sales and operating expenses | F31: 2025 reporting framework: Cost of sales and operating expenses | G31: 2025 reporting framework: Cost of sales and operating expenses | H31: 2025 reporting framework: Cost of sales and operating expenses | I31: 2025 reporting framework: Cost of sales and operating expenses | J31: 2025 reporting framework: Cost of sales and operating expenses | K31: 2025 reporting framework: Cost of sales and operating expenses | L31: 2025 reporting framework: Cost of sales and operating expenses | M31: 2025 reporting framework: Cost of sales and operating expenses | N31: 2025 reporting framework: Cost of sales and operating expenses | O31: 2025 reporting framework: Cost of sales and operating expenses | P31: 2025 reporting framework: Cost of sales and operating expenses | Q31: 2025 reporting framework: Cost of sales and operating expenses | R31: 2025 reporting framework: Cost of sales and operating expenses | S31: 2025 reporting framework: Cost of sales and operating expenses | T31: 2025 reporting framework: Cost of sales and operating expenses | U31: 2025 reporting framework: Cost of sales and operating expenses | V31: 2025 reporting framework: Cost of sales and operating expenses | W31: 2025 reporting framework: Cost of sales and operating expenses | X31: 2025 reporting framework: Cost of sales and operating expenses | Y31: 2025 reporting framework: Cost of sales and operating expenses | Z31: 2025 reporting framework: Cost of sales and operating expenses | AA31: 2025 reporting framework: Cost of sales and operating expenses
A32: 2023–2025 annuals use the 2025 segment framework. Q2 2026 CCPG is the renamed CCG where source comparatives agree; legacy frameworks below are not spliced into this series. | B32: 2023–2025 annuals use the 2025 segment framework. Q2 2026 CCPG is the renamed CCG where source comparatives agree; legacy frameworks below are not spliced into this series. | C32: 2023–2025 annuals use the 2025 segment framework. Q2 2026 CCPG is the renamed CCG where source comparatives agree; legacy frameworks below are not spliced into this series. | D32: 2023–2025 annuals use the 2025 segment framework. Q2 2026 CCPG is the renamed CCG where source comparatives agree; legacy frameworks below are not spliced into this series. | E32: 2023–2025 annuals use the 2025 segment framework. Q2 2026 CCPG is the renamed CCG where source comparatives agree; legacy frameworks below are not spliced into this series. | F32: 2023–2025 annuals use the 2025 segment framework. Q2 2026 CCPG is the renamed CCG where source comparatives agree; legacy frameworks below are not spliced into this series. | G32: 2023–2025 annuals use the 2025 segment framework. Q2 2026 CCPG is the renamed CCG where source comparatives agree; legacy frameworks below are not spliced into this series. | H32: 2023–2025 annuals use the 2025 segment framework. Q2 2026 CCPG is the renamed CCG where source comparatives agree; legacy frameworks below are not spliced into this series. | I32: 2023–2025 annuals use the 2025 segment framework. Q2 2026 CCPG is the renamed CCG where source comparatives agree; legacy frameworks below are not spliced into this series. | J32: 2023–2025 annuals use the 2025 segment framework. Q2 2026 CCPG is the renamed CCG where source comparatives agree; legacy frameworks below are not spliced into this series. | K32: 2023–2025 annuals use the 2025 segment framework. Q2 2026 CCPG is the renamed CCG where source comparatives agree; legacy frameworks below are not spliced into this series. | L32: 2023–2025 annuals use the 2025 segment framework. Q2 2026 CCPG is the renamed CCG where source comparatives agree; legacy frameworks below are not spliced into this series. | M32: 2023–2025 annuals use the 2025 segment framework. Q2 2026 CCPG is the renamed CCG where source comparatives agree; legacy frameworks below are not spliced into this series. | N32: 2023–2025 annuals use the 2025 segment framework. Q2 2026 CCPG is the renamed CCG where source comparatives agree; legacy frameworks below are not spliced into this series. | O32: 2023–2025 annuals use the 2025 segment framework. Q2 2026 CCPG is the renamed CCG where source comparatives agree; legacy frameworks below are not spliced into this series. | P32: 2023–2025 annuals use the 2025 segment framework. Q2 2026 CCPG is the renamed CCG where source comparatives agree; legacy frameworks below are not spliced into this series. | Q32: 2023–2025 annuals use the 2025 segment framework. Q2 2026 CCPG is the renamed CCG where source comparatives agree; legacy frameworks below are not spliced into this series. | R32: 2023–2025 annuals use the 2025 segment framework. Q2 2026 CCPG is the renamed CCG where source comparatives agree; legacy frameworks below are not spliced into this series. | S32: 2023–2025 annuals use the 2025 segment framework. Q2 2026 CCPG is the renamed CCG where source comparatives agree; legacy frameworks below are not spliced into this series. | T32: 2023–2025 annuals use the 2025 segment framework. Q2 2026 CCPG is the renamed CCG where source comparatives agree; legacy frameworks below are not spliced into this series. | U32: 2023–2025 annuals use the 2025 segment framework. Q2 2026 CCPG is the renamed CCG where source comparatives agree; legacy frameworks below are not spliced into this series. | V32: 2023–2025 annuals use the 2025 segment framework. Q2 2026 CCPG is the renamed CCG where source comparatives agree; legacy frameworks below are not spliced into this series. | W32: 2023–2025 annuals use the 2025 segment framework. Q2 2026 CCPG is the renamed CCG where source comparatives agree; legacy frameworks below are not spliced into this series. | X32: 2023–2025 annuals use the 2025 segment framework. Q2 2026 CCPG is the renamed CCG where source comparatives agree; legacy frameworks below are not spliced into this series. | Y32: 2023–2025 annuals use the 2025 segment framework. Q2 2026 CCPG is the renamed CCG where source comparatives agree; legacy frameworks below are not spliced into this series. | Z32: 2023–2025 annuals use the 2025 segment framework. Q2 2026 CCPG is the renamed CCG where source comparatives agree; legacy frameworks below are not spliced into this series. | AA32: 2023–2025 annuals use the 2025 segment framework. Q2 2026 CCPG is the renamed CCG where source comparatives agree; legacy frameworks below are not spliced into this series.
A33: Cost of sales and operating expenses - CCG | J33: 22177 | K33: 21752 | L33: 22911 | Q33: =IF(COUNT(J33,N33,O33,P33)=4,J33-N33-O33-P33,"") | S33: 5502 | T33: 5224 | U33: =IF(COUNT(K33,R33,S33,T33)=4,K33-R33-S33-T33,"") | V33: 5268 | W33: 5818 | X33: 5841 | Y33: =IF(COUNT(L33,V33,W33,X33)=4,L33-V33-W33-X33,"") -> 5984 | Z33: 5211 | AA33: 6534
A34: Cost of sales and operating expenses - DCAI | J34: 15035 | K34: 14711 | L34: 13497 | Q34: =IF(COUNT(J34,N34,O34,P34)=4,J34-N34-O34-P34,"") | S34: 3563 | T34: 3760 | U34: =IF(COUNT(K34,R34,S34,T34)=4,K34-R34-S34-T34,"") | V34: 3551 | W34: 3306 | X34: 3153 | Y34: =IF(COUNT(L34,V34,W34,X34)=4,L34-V34-W34-X34,"") -> 3487 | Z34: 3510 | AA34: 3788
A35: Cost of sales and operating expenses - Total Intel Products | J35: 37212 | K35: 36463 | L35: 36408 | Q35: =IF(COUNT(J35,N35,O35,P35)=4,J35-N35-O35-P35,"") | S35: 9065 | T35: 8984 | U35: =IF(COUNT(K35,R35,S35,T35)=4,K35-R35-S35-T35,"") | V35: 8819 | W35: 9124 | X35: 8994 | Y35: =IF(COUNT(L35,V35,W35,X35)=4,L35-V35-W35-X35,"") -> 9471 | Z35: 8721 | AA35: 10322
A36: Cost of sales and operating expenses - Intel Foundry | J36: 25587 | K36: 30608 | L36: 28144 | Q36: =IF(COUNT(J36,N36,O36,P36)=4,J36-N36-O36-P36,"") | S36: 7084 | T36: 10138 | U36: =IF(COUNT(K36,R36,S36,T36)=4,K36-R36-S36-T36,"") | V36: 6987 | W36: 7585 | X36: 6556 | Y36: =IF(COUNT(L36,V36,W36,X36)=4,L36-V36-W36-X36,"") -> 7016 | Z36: 7858 | AA36: 7854
A37: Cost of sales and operating expenses - All Other | J37: 3956 | K37: 3658 | L37: 3299 | Q37: =IF(COUNT(J37,N37,O37,P37)=4,J37-N37-O37-P37,"") | S37: 927 | T37: 959 | U37: =IF(COUNT(K37,R37,S37,T37)=4,K37-R37-S37-T37,"") | V37: 840 | W37: 984 | X37: 893 | Y37: =IF(COUNT(L37,V37,W37,X37)=4,L37-V37-W37-X37,"") -> 582 | Z37: 526 | AA37: 471
A38: Cost of sales and operating expenses - Corporate Unallocated | J38: 5199 | K38: 11177 | L38: 5518 | Q38: =IF(COUNT(J38,N38,O38,P38)=4,J38-N38-O38-P38,"") | S38: 1708 | T38: 6502 | U38: =IF(COUNT(K38,R38,S38,T38)=4,K38-R38-S38-T38,"") | V38: 1260 | W38: 2755 | X38: 782 | Y38: =IF(COUNT(L38,V38,W38,X38)=4,L38-V38-W38-X38,"") -> 721 | Z38: 5080 | AA38: 1416
A39: Cost of sales and operating expenses - Intersegment Eliminations | J39: -17819 | K39: -17127 | L39: -18302 | Q39: =IF(COUNT(J39,N39,O39,P39)=4,J39-N39-O39-P39,"") | S39: -3987 | T39: -4242 | U39: =IF(COUNT(K39,R39,S39,T39)=4,K39-R39-S39-T39,"") | V39: -4938 | W39: -4413 | X39: -4255 | Y39: =IF(COUNT(L39,V39,W39,X39)=4,L39-V39-W39-X39,"") -> -4696 | Z39: -5472 | AA39: -5731
A40: Cost of sales and operating expenses - Total Consolidated | J40: 54135 | K40: 64779 | L40: 55067 | Q40: =IF(COUNT(J40,N40,O40,P40)=4,J40-N40-O40-P40,"") | S40: 14797 | T40: 22341 | U40: =IF(COUNT(K40,R40,S40,T40)=4,K40-R40-S40-T40,"") | V40: 12968 | W40: 16035 | X40: 12970 | Y40: =IF(COUNT(L40,V40,W40,X40)=4,L40-V40-W40-X40,"") -> 13094 | Z40: 16713 | AA40: 14332
A41: Check: segment lines - printed total (should be 0) | J41: =IF(COUNT(J33,J34,J36,J37,J38,J39,J40)=7,J33+J34+J36+J37+J38+J39-J40,"") -> 0 | K41: =IF(COUNT(K33,K34,K36,K37,K38,K39,K40)=7,K33+K34+K36+K37+K38+K39-K40,"") -> 0 | L41: =IF(COUNT(L33,L34,L36,L37,L38,L39,L40)=7,L33+L34+L36+L37+L38+L39-L40,"") -> 0 | Q41: =IF(COUNT(Q33,Q34,Q36,Q37,Q38,Q39,Q40)=7,Q33+Q34+Q36+Q37+Q38+Q39-Q40,"") | S41: =IF(COUNT(S33,S34,S36,S37,S38,S39,S40)=7,S33+S34+S36+S37+S38+S39-S40,"") -> 0 | T41: =IF(COUNT(T33,T34,T36,T37,T38,T39,T40)=7,T33+T34+T36+T37+T38+T39-T40,"") -> 0 | U41: =IF(COUNT(U33,U34,U36,U37,U38,U39,U40)=7,U33+U34+U36+U37+U38+U39-U40,"") | V41: =IF(COUNT(V33,V34,V36,V37,V38,V39,V40)=7,V33+V34+V36+V37+V38+V39-V40,"") -> 0 | W41: =IF(COUNT(W33,W34,W36,W37,W38,W39,W40)=7,W33+W34+W36+W37+W38+W39-W40,"") -> 0 | X41: =IF(COUNT(X33,X34,X36,X37,X38,X39,X40)=7,X33+X34+X36+X37+X38+X39-X40,"") -> 0 | Y41: =IF(COUNT(Y33,Y34,Y36,Y37,Y38,Y39,Y40)=7,Y33+Y34+Y36+Y37+Y38+Y39-Y40,"") -> 0 | Z41: =IF(COUNT(Z33,Z34,Z36,Z37,Z38,Z39,Z40)=7,Z33+Z34+Z36+Z37+Z38+Z39-Z40,"") -> 0 | AA41: =IF(COUNT(AA33,AA34,AA36,AA37,AA38,AA39,AA40)=7,AA33+AA34+AA36+AA37+AA38+AA39-AA40,"") -> 0
A43: 2025 reporting framework: Cost of sales | B43: 2025 reporting framework: Cost of sales | C43: 2025 reporting framework: Cost of sales | D43: 2025 reporting framework: Cost of sales | E43: 2025 reporting framework: Cost of sales | F43: 2025 reporting framework: Cost of sales | G43: 2025 reporting framework: Cost of sales | H43: 2025 reporting framework: Cost of sales | I43: 2025 reporting framework: Cost of sales | J43: 2025 reporting framework: Cost of sales | K43: 2025 reporting framework: Cost of sales | L43: 2025 reporting framework: Cost of sales | M43: 2025 reporting framework: Cost of sales | N43: 2025 reporting framework: Cost of sales | O43: 2025 reporting framework: Cost of sales | P43: 2025 reporting framework: Cost of sales | Q43: 2025 reporting framework: Cost of sales | R43: 2025 reporting framework: Cost of sales | S43: 2025 reporting framework: Cost of sales | T43: 2025 reporting framework: Cost of sales | U43: 2025 reporting framework: Cost of sales | V43: 2025 reporting framework: Cost of sales | W43: 2025 reporting framework: Cost of sales | X43: 2025 reporting framework: Cost of sales | Y43: 2025 reporting framework: Cost of sales | Z43: 2025 reporting framework: Cost of sales | AA43: 2025 reporting framework: Cost of sales
A44: 2023–2025 annuals use the 2025 segment framework. Q2 2026 CCPG is the renamed CCG where source comparatives agree; legacy frameworks below are not spliced into this series. | B44: 2023–2025 annuals use the 2025 segment framework. Q2 2026 CCPG is the renamed CCG where source comparatives agree; legacy frameworks below are not spliced into this series. | C44: 2023–2025 annuals use the 2025 segment framework. Q2 2026 CCPG is the renamed CCG where source comparatives agree; legacy frameworks below are not spliced into this series. | D44: 2023–2025 annuals use the 2025 segment framework. Q2 2026 CCPG is the renamed CCG where source comparatives agree; legacy frameworks below are not spliced into this series. | E44: 2023–2025 annuals use the 2025 segment framework. Q2 2026 CCPG is the renamed CCG where source comparatives agree; legacy frameworks below are not spliced into this series. | F44: 2023–2025 annuals use the 2025 segment framework. Q2 2026 CCPG is the renamed CCG where source comparatives agree; legacy frameworks below are not spliced into this series. | G44: 2023–2025 annuals use the 2025 segment framework. Q2 2026 CCPG is the renamed CCG where source comparatives agree; legacy frameworks below are not spliced into this series. | H44: 2023–2025 annuals use the 2025 segment framework. Q2 2026 CCPG is the renamed CCG where source comparatives agree; legacy frameworks below are not spliced into this series. | I44: 2023–2025 annuals use the 2025 segment framework. Q2 2026 CCPG is the renamed CCG where source comparatives agree; legacy frameworks below are not spliced into this series. | J44: 2023–2025 annuals use the 2025 segment framework. Q2 2026 CCPG is the renamed CCG where source comparatives agree; legacy frameworks below are not spliced into this series. | K44: 2023–2025 annuals use the 2025 segment framework. Q2 2026 CCPG is the renamed CCG where source comparatives agree; legacy frameworks below are not spliced into this series. | L44: 2023–2025 annuals use the 2025 segment framework. Q2 2026 CCPG is the renamed CCG where source comparatives agree; legacy frameworks below are not spliced into this series. | M44: 2023–2025 annuals use the 2025 segment framework. Q2 2026 CCPG is the renamed CCG where source comparatives agree; legacy frameworks below are not spliced into this series. | N44: 2023–2025 annuals use the 2025 segment framework. Q2 2026 CCPG is the renamed CCG where source comparatives agree; legacy frameworks below are not spliced into this series. | O44: 2023–2025 annuals use the 2025 segment framework. Q2 2026 CCPG is the renamed CCG where source comparatives agree; legacy frameworks below are not spliced into this series. | P44: 2023–2025 annuals use the 2025 segment framework. Q2 2026 CCPG is the renamed CCG where source comparatives agree; legacy frameworks below are not spliced into this series. | Q44: 2023–2025 annuals use the 2025 segment framework. Q2 2026 CCPG is the renamed CCG where source comparatives agree; legacy frameworks below are not spliced into this series. | R44: 2023–2025 annuals use the 2025 segment framework. Q2 2026 CCPG is the renamed CCG where source comparatives agree; legacy frameworks below are not spliced into this series. | S44: 2023–2025 annuals use the 2025 segment framework. Q2 2026 CCPG is the renamed CCG where source comparatives agree; legacy frameworks below are not spliced into this series. | T44: 2023–2025 annuals use the 2025 segment framework. Q2 2026 CCPG is the renamed CCG where source comparatives agree; legacy frameworks below are not spliced into this series. | U44: 2023–2025 annuals use the 2025 segment framework. Q2 2026 CCPG is the renamed CCG where source comparatives agree; legacy frameworks below are not spliced into this series. | V44: 2023–2025 annuals use the 2025 segment framework. Q2 2026 CCPG is the renamed CCG where source comparatives agree; legacy frameworks below are not spliced into this series. | W44: 2023–2025 annuals use the 2025 segment framework. Q2 2026 CCPG is the renamed CCG where source comparatives agree; legacy frameworks below are not spliced into this series. | X44: 2023–2025 annuals use the 2025 segment framework. Q2 2026 CCPG is the renamed CCG where source comparatives agree; legacy frameworks below are not spliced into this series. | Y44: 2023–2025 annuals use the 2025 segment framework. Q2 2026 CCPG is the renamed CCG where source comparatives agree; legacy frameworks below are not spliced into this series. | Z44: 2023–2025 annuals use the 2025 segment framework. Q2 2026 CCPG is the renamed CCG where source comparatives agree; legacy frameworks below are not spliced into this series. | AA44: 2023–2025 annuals use the 2025 segment framework. Q2 2026 CCPG is the renamed CCG where source comparatives agree; legacy frameworks below are not spliced into this series.
A45: Cost of sales - CCG | Q45: =IF(COUNT(J45,N45,O45,P45)=4,J45-N45-O45-P45,"") | R45: 4004 | U45: =IF(COUNT(K45,R45,S45,T45)=4,K45-R45-S45-T45,"") | V45: 3984 | Y45: =IF(COUNT(L45,V45,W45,X45)=4,L45-V45-W45-X45,"")
A46: Cost of sales - DCAI | Q46: =IF(COUNT(J46,N46,O46,P46)=4,J46-N46-O46-P46,"") | R46: 1745 | U46: =IF(COUNT(K46,R46,S46,T46)=4,K46-R46-S46-T46,"") | V46: 2359 | Y46: =IF(COUNT(L46,V46,W46,X46)=4,L46-V46-W46-X46,"")
A47: Cost of sales - Total Intel Products | Q47: =IF(COUNT(J47,N47,O47,P47)=4,J47-N47-O47-P47,"") | R47: 5749 | U47: =IF(COUNT(K47,R47,S47,T47)=4,K47-R47-S47-T47,"") | V47: 6343 | Y47: =IF(COUNT(L47,V47,W47,X47)=4,L47-V47-W47-X47,"")
A48: Cost of sales - Intel Foundry | Q48: =IF(COUNT(J48,N48,O48,P48)=4,J48-N48-O48-P48,"") | R48: 5617 | U48: =IF(COUNT(K48,R48,S48,T48)=4,K48-R48-S48-T48,"") | V48: 5946 | Y48: =IF(COUNT(L48,V48,W48,X48)=4,L48-V48-W48-X48,"")
A49: Cost of sales - All Other | Q49: =IF(COUNT(J49,N49,O49,P49)=4,J49-N49-O49-P49,"") | R49: 341 | U49: =IF(COUNT(K49,R49,S49,T49)=4,K49-R49-S49-T49,"") | V49: 396 | Y49: =IF(COUNT(L49,V49,W49,X49)=4,L49-V49-W49-X49,"")
A50: Cost of sales - Corporate Unallocated | Q50: =IF(COUNT(J50,N50,O50,P50)=4,J50-N50-O50-P50,"") | R50: 701 | U50: =IF(COUNT(K50,R50,S50,T50)=4,K50-R50-S50-T50,"") | V50: 377 | Y50: =IF(COUNT(L50,V50,W50,X50)=4,L50-V50-W50-X50,"")
A51: Cost of sales - Intersegment Eliminations | Q51: =IF(COUNT(J51,N51,O51,P51)=4,J51-N51-O51-P51,"") | R51: -4901 | U51: =IF(COUNT(K51,R51,S51,T51)=4,K51-R51-S51-T51,"") | V51: -5067 | Y51: =IF(COUNT(L51,V51,W51,X51)=4,L51-V51-W51-X51,"")
A52: Cost of sales - Total Consolidated | Q52: =IF(COUNT(J52,N52,O52,P52)=4,J52-N52-O52-P52,"") | R52: 7507 | U52: =IF(COUNT(K52,R52,S52,T52)=4,K52-R52-S52-T52,"") | V52: 7995 | Y52: =IF(COUNT(L52,V52,W52,X52)=4,L52-V52-W52-X52,"")
A53: Check: segment lines - printed total (should be 0) | R53: =IF(COUNT(R45,R46,R48,R49,R50,R51,R52)=7,R45+R46+R48+R49+R50+R51-R52,"") -> 0 | V53: =IF(COUNT(V45,V46,V48,V49,V50,V51,V52)=7,V45+V46+V48+V49+V50+V51-V52,"") -> 0
A55: 2025 reporting framework: Operating expenses | B55: 2025 reporting framework: Operating expenses | C55: 2025 reporting framework: Operating expenses | D55: 2025 reporting framework: Operating expenses | E55: 2025 reporting framework: Operating expenses | F55: 2025 reporting framework: Operating expenses | G55: 2025 reporting framework: Operating expenses | H55: 2025 reporting framework: Operating expenses | I55: 2025 reporting framework: Operating expenses | J55: 2025 reporting framework: Operating expenses | K55: 2025 reporting framework: Operating expenses | L55: 2025 reporting framework: Operating expenses | M55: 2025 reporting framework: Operating expenses | N55: 2025 reporting framework: Operating expenses | O55: 2025 reporting framework: Operating expenses | P55: 2025 reporting framework: Operating expenses | Q55: 2025 reporting framework: Operating expenses | R55: 2025 reporting framework: Operating expenses | S55: 2025 reporting framework: Operating expenses | T55: 2025 reporting framework: Operating expenses | U55: 2025 reporting framework: Operating expenses | V55: 2025 reporting framework: Operating expenses | W55: 2025 reporting framework: Operating expenses | X55: 2025 reporting framework: Operating expenses | Y55: 2025 reporting framework: Operating expenses | Z55: 2025 reporting framework: Operating expenses | AA55: 2025 reporting framework: Operating expenses
A56: 2023–2025 annuals use the 2025 segment framework. Q2 2026 CCPG is the renamed CCG where source comparatives agree; legacy frameworks below are not spliced into this series. | B56: 2023–2025 annuals use the 2025 segment framework. Q2 2026 CCPG is the renamed CCG where source comparatives agree; legacy frameworks below are not spliced into this series. | C56: 2023–2025 annuals use the 2025 segment framework. Q2 2026 CCPG is the renamed CCG where source comparatives agree; legacy frameworks below are not spliced into this series. | D56: 2023–2025 annuals use the 2025 segment framework. Q2 2026 CCPG is the renamed CCG where source comparatives agree; legacy frameworks below are not spliced into this series. | E56: 2023–2025 annuals use the 2025 segment framework. Q2 2026 CCPG is the renamed CCG where source comparatives agree; legacy frameworks below are not spliced into this series. | F56: 2023–2025 annuals use the 2025 segment framework. Q2 2026 CCPG is the renamed CCG where source comparatives agree; legacy frameworks below are not spliced into this series. | G56: 2023–2025 annuals use the 2025 segment framework. Q2 2026 CCPG is the renamed CCG where source comparatives agree; legacy frameworks below are not spliced into this series. | H56: 2023–2025 annuals use the 2025 segment framework. Q2 2026 CCPG is the renamed CCG where source comparatives agree; legacy frameworks below are not spliced into this series. | I56: 2023–2025 annuals use the 2025 segment framework. Q2 2026 CCPG is the renamed CCG where source comparatives agree; legacy frameworks below are not spliced into this series. | J56: 2023–2025 annuals use the 2025 segment framework. Q2 2026 CCPG is the renamed CCG where source comparatives agree; legacy frameworks below are not spliced into this series. | K56: 2023–2025 annuals use the 2025 segment framework. Q2 2026 CCPG is the renamed CCG where source comparatives agree; legacy frameworks below are not spliced into this series. | L56: 2023–2025 annuals use the 2025 segment framework. Q2 2026 CCPG is the renamed CCG where source comparatives agree; legacy frameworks below are not spliced into this series. | M56: 2023–2025 annuals use the 2025 segment framework. Q2 2026 CCPG is the renamed CCG where source comparatives agree; legacy frameworks below are not spliced into this series. | N56: 2023–2025 annuals use the 2025 segment framework. Q2 2026 CCPG is the renamed CCG where source comparatives agree; legacy frameworks below are not spliced into this series. | O56: 2023–2025 annuals use the 2025 segment framework. Q2 2026 CCPG is the renamed CCG where source comparatives agree; legacy frameworks below are not spliced into this series. | P56: 2023–2025 annuals use the 2025 segment framework. Q2 2026 CCPG is the renamed CCG where source comparatives agree; legacy frameworks below are not spliced into this series. | Q56: 2023–2025 annuals use the 2025 segment framework. Q2 2026 CCPG is the renamed CCG where source comparatives agree; legacy frameworks below are not spliced into this series. | R56: 2023–2025 annuals use the 2025 segment framework. Q2 2026 CCPG is the renamed CCG where source comparatives agree; legacy frameworks below are not spliced into this series. | S56: 2023–2025 annuals use the 2025 segment framework. Q2 2026 CCPG is the renamed CCG where source comparatives agree; legacy frameworks below are not spliced into this series. | T56: 2023–2025 annuals use the 2025 segment framework. Q2 2026 CCPG is the renamed CCG where source comparatives agree; legacy frameworks below are not spliced into this series. | U56: 2023–2025 annuals use the 2025 segment framework. Q2 2026 CCPG is the renamed CCG where source comparatives agree; legacy frameworks below are not spliced into this series. | V56: 2023–2025 annuals use the 2025 segment framework. Q2 2026 CCPG is the renamed CCG where source comparatives agree; legacy frameworks below are not spliced into this series. | W56: 2023–2025 annuals use the 2025 segment framework. Q2 2026 CCPG is the renamed CCG where source comparatives agree; legacy frameworks below are not spliced into this series. | X56: 2023–2025 annuals use the 2025 segment framework. Q2 2026 CCPG is the renamed CCG where source comparatives agree; legacy frameworks below are not spliced into this series. | Y56: 2023–2025 annuals use the 2025 segment framework. Q2 2026 CCPG is the renamed CCG where source comparatives agree; legacy frameworks below are not spliced into this series. | Z56: 2023–2025 annuals use the 2025 segment framework. Q2 2026 CCPG is the renamed CCG where source comparatives agree; legacy frameworks below are not spliced into this series. | AA56: 2023–2025 annuals use the 2025 segment framework. Q2 2026 CCPG is the renamed CCG where source comparatives agree; legacy frameworks below are not spliced into this series.
A57: Operating expenses - CCG | Q57: =IF(COUNT(J57,N57,O57,P57)=4,J57-N57-O57-P57,"") | R57: 1447 | U57: =IF(COUNT(K57,R57,S57,T57)=4,K57-R57-S57-T57,"") | V57: 1284 | Y57: =IF(COUNT(L57,V57,W57,X57)=4,L57-V57-W57-X57,"")
A58: Operating expenses - DCAI | Q58: =IF(COUNT(J58,N58,O58,P58)=4,J58-N58-O58-P58,"") | R58: 1666 | U58: =IF(COUNT(K58,R58,S58,T58)=4,K58-R58-S58-T58,"") | V58: 1192 | Y58: =IF(COUNT(L58,V58,W58,X58)=4,L58-V58-W58-X58,"")
A59: Operating expenses - Total Intel Products | Q59: =IF(COUNT(J59,N59,O59,P59)=4,J59-N59-O59-P59,"") | R59: 3113 | U59: =IF(COUNT(K59,R59,S59,T59)=4,K59-R59-S59-T59,"") | V59: 2476 | Y59: =IF(COUNT(L59,V59,W59,X59)=4,L59-V59-W59-X59,"")
A60: Operating expenses - Intel Foundry | Q60: =IF(COUNT(J60,N60,O60,P60)=4,J60-N60-O60-P60,"") | R60: 1180 | U60: =IF(COUNT(K60,R60,S60,T60)=4,K60-R60-S60-T60,"") | V60: 1041 | Y60: =IF(COUNT(L60,V60,W60,X60)=4,L60-V60-W60-X60,"")
A61: Operating expenses - All Other | Q61: =IF(COUNT(J61,N61,O61,P61)=4,J61-N61-O61-P61,"") | R61: 472 | U61: =IF(COUNT(K61,R61,S61,T61)=4,K61-R61-S61-T61,"") | V61: 444 | Y61: =IF(COUNT(L61,V61,W61,X61)=4,L61-V61-W61-X61,"")
A62: Operating expenses - Corporate Unallocated | Q62: =IF(COUNT(J62,N62,O62,P62)=4,J62-N62-O62-P62,"") | R62: 1486 | U62: =IF(COUNT(K62,R62,S62,T62)=4,K62-R62-S62-T62,"") | V62: 883 | Y62: =IF(COUNT(L62,V62,W62,X62)=4,L62-V62-W62-X62,"")
A63: Operating expenses - Intersegment Eliminations | Q63: =IF(COUNT(J63,N63,O63,P63)=4,J63-N63-O63-P63,"") | R63: 35 | U63: =IF(COUNT(K63,R63,S63,T63)=4,K63-R63-S63-T63,"") | V63: 129 | Y63: =IF(COUNT(L63,V63,W63,X63)=4,L63-V63-W63-X63,"")
A64: Operating expenses - Total Consolidated | Q64: =IF(COUNT(J64,N64,O64,P64)=4,J64-N64-O64-P64,"") | R64: 6286 | U64: =IF(COUNT(K64,R64,S64,T64)=4,K64-R64-S64-T64,"") | V64: 4973 | Y64: =IF(COUNT(L64,V64,W64,X64)=4,L64-V64-W64-X64,"")
A65: Check: segment lines - printed total (should be 0) | R65: =IF(COUNT(R57,R58,R60,R61,R62,R63,R64)=7,R57+R58+R60+R61+R62+R63-R64,"") -> 0 | V65: =IF(COUNT(V57,V58,V60,V61,V62,V63,V64)=7,V57+V58+V60+V61+V62+V63-V64,"") -> 0
A67: 2025 reporting framework: Corporate unallocated - composition | B67: 2025 reporting framework: Corporate unallocated - composition | C67: 2025 reporting framework: Corporate unallocated - composition | D67: 2025 reporting framework: Corporate unallocated - composition | E67: 2025 reporting framework: Corporate unallocated - composition | F67: 2025 reporting framework: Corporate unallocated - composition | G67: 2025 reporting framework: Corporate unallocated - composition | H67: 2025 reporting framework: Corporate unallocated - composition | I67: 2025 reporting framework: Corporate unallocated - composition | J67: 2025 reporting framework: Corporate unallocated - composition | K67: 2025 reporting framework: Corporate unallocated - composition | L67: 2025 reporting framework: Corporate unallocated - composition | M67: 2025 reporting framework: Corporate unallocated - composition | N67: 2025 reporting framework: Corporate unallocated - composition | O67: 2025 reporting framework: Corporate unallocated - composition | P67: 2025 reporting framework: Corporate unallocated - composition | Q67: 2025 reporting framework: Corporate unallocated - composition | R67: 2025 reporting framework: Corporate unallocated - composition | S67: 2025 reporting framework: Corporate unallocated - composition | T67: 2025 reporting framework: Corporate unallocated - composition | U67: 2025 reporting framework: Corporate unallocated - composition | V67: 2025 reporting framework: Corporate unallocated - composition | W67: 2025 reporting framework: Corporate unallocated - composition | X67: 2025 reporting framework: Corporate unallocated - composition | Y67: 2025 reporting framework: Corporate unallocated - composition | Z67: 2025 reporting framework: Corporate unallocated - composition | AA67: 2025 reporting framework: Corporate unallocated - composition
A68: 2023–2025 annuals use the 2025 segment framework. Q2 2026 CCPG is the renamed CCG where source comparatives agree; legacy frameworks below are not spliced into this series. | B68: 2023–2025 annuals use the 2025 segment framework. Q2 2026 CCPG is the renamed CCG where source comparatives agree; legacy frameworks below are not spliced into this series. | C68: 2023–2025 annuals use the 2025 segment framework. Q2 2026 CCPG is the renamed CCG where source comparatives agree; legacy frameworks below are not spliced into this series. | D68: 2023–2025 annuals use the 2025 segment framework. Q2 2026 CCPG is the renamed CCG where source comparatives agree; legacy frameworks below are not spliced into this series. | E68: 2023–2025 annuals use the 2025 segment framework. Q2 2026 CCPG is the renamed CCG where source comparatives agree; legacy frameworks below are not spliced into this series. | F68: 2023–2025 annuals use the 2025 segment framework. Q2 2026 CCPG is the renamed CCG where source comparatives agree; legacy frameworks below are not spliced into this series. | G68: 2023–2025 annuals use the 2025 segment framework. Q2 2026 CCPG is the renamed CCG where source comparatives agree; legacy frameworks below are not spliced into this series. | H68: 2023–2025 annuals use the 2025 segment framework. Q2 2026 CCPG is the renamed CCG where source comparatives agree; legacy frameworks below are not spliced into this series. | I68: 2023–2025 annuals use the 2025 segment framework. Q2 2026 CCPG is the renamed CCG where source comparatives agree; legacy frameworks below are not spliced into this series. | J68: 2023–2025 annuals use the 2025 segment framework. Q2 2026 CCPG is the renamed CCG where source comparatives agree; legacy frameworks below are not spliced into this series. | K68: 2023–2025 annuals use the 2025 segment framework. Q2 2026 CCPG is the renamed CCG where source comparatives agree; legacy frameworks below are not spliced into this series. | L68: 2023–2025 annuals use the 2025 segment framework. Q2 2026 CCPG is the renamed CCG where source comparatives agree; legacy frameworks below are not spliced into this series. | M68: 2023–2025 annuals use the 2025 segment framework. Q2 2026 CCPG is the renamed CCG where source comparatives agree; legacy frameworks below are not spliced into this series. | N68: 2023–2025 annuals use the 2025 segment framework. Q2 2026 CCPG is the renamed CCG where source comparatives agree; legacy frameworks below are not spliced into this series. | O68: 2023–2025 annuals use the 2025 segment framework. Q2 2026 CCPG is the renamed CCG where source comparatives agree; legacy frameworks below are not spliced into this series. | P68: 2023–2025 annuals use the 2025 segment framework. Q2 2026 CCPG is the renamed CCG where source comparatives agree; legacy frameworks below are not spliced into this series. | Q68: 2023–2025 annuals use the 2025 segment framework. Q2 2026 CCPG is the renamed CCG where source comparatives agree; legacy frameworks below are not spliced into this series. | R68: 2023–2025 annuals use the 2025 segment framework. Q2 2026 CCPG is the renamed CCG where source comparatives agree; legacy frameworks below are not spliced into this series. | S68: 2023–2025 annuals use the 2025 segment framework. Q2 2026 CCPG is the renamed CCG where source comparatives agree; legacy frameworks below are not spliced into this series. | T68: 2023–2025 annuals use the 2025 segment framework. Q2 2026 CCPG is the renamed CCG where source comparatives agree; legacy frameworks below are not spliced into this series. | U68: 2023–2025 annuals use the 2025 segment framework. Q2 2026 CCPG is the renamed CCG where source comparatives agree; legacy frameworks below are not spliced into this series. | V68: 2023–2025 annuals use the 2025 segment framework. Q2 2026 CCPG is the renamed CCG where source comparatives agree; legacy frameworks below are not spliced into this series. | W68: 2023–2025 annuals use the 2025 segment framework. Q2 2026 CCPG is the renamed CCG where source comparatives agree; legacy frameworks below are not spliced into this series. | X68: 2023–2025 annuals use the 2025 segment framework. Q2 2026 CCPG is the renamed CCG where source comparatives agree; legacy frameworks below are not spliced into this series. | Y68: 2023–2025 annuals use the 2025 segment framework. Q2 2026 CCPG is the renamed CCG where source comparatives agree; legacy frameworks below are not spliced into this series. | Z68: 2023–2025 annuals use the 2025 segment framework. Q2 2026 CCPG is the renamed CCG where source comparatives agree; legacy frameworks below are not spliced into this series. | AA68: 2023–2025 annuals use the 2025 segment framework. Q2 2026 CCPG is the renamed CCG where source comparatives agree; legacy frameworks below are not spliced into this series.
A69: Restructuring and other charges | J69: -62 | K69: 6970 | L69: 2191 | Q69: =IF(COUNT(J69,N69,O69,P69)=4,J69-N69-O69-P69,"") | S69: 943 | T69: 5622 | U69: =IF(COUNT(K69,R69,S69,T69)=4,K69-R69-S69-T69,"") | V69: 156 | W69: 1890 | X69: 175 | Y69: =IF(COUNT(L69,V69,W69,X69)=4,L69-V69-W69-X69,"") -> -30 | Z69: 4070
A70: Share-based compensation | J70: 3229 | K70: 3410 | L70: 2434 | Q70: =IF(COUNT(J70,N70,O70,P70)=4,J70-N70-O70-P70,"") | S70: 780 | T70: 800 | U70: =IF(COUNT(K70,R70,S70,T70)=4,K70-R70-S70-T70,"") | V70: 684 | W70: 664 | X70: 548 | Y70: =IF(COUNT(L70,V70,W70,X70)=4,L70-V70-W70-X70,"") -> 538 | Z70: 621
A71: Acquisition-related costs | J71: 1407 | K71: 1044 | L71: 505 | Q71: =IF(COUNT(J71,N71,O71,P71)=4,J71-N71-O71-P71,"") | S71: 265 | T71: 266 | U71: =IF(COUNT(K71,R71,S71,T71)=4,K71-R71-S71-T71,"") | V71: 151 | W71: 119 | X71: 118 | Y71: =IF(COUNT(L71,V71,W71,X71)=4,L71-V71-W71-X71,"") -> 117 | Z71: 113
A72: CORP UNALLOCATED: Other | J72: 625 | K72: -247 | L72: 388 | Q72: =IF(COUNT(J72,N72,O72,P72)=4,J72-N72-O72-P72,"") | S72: -280 | T72: -186 | U72: =IF(COUNT(K72,R72,S72,T72)=4,K72-R72-S72-T72,"") | V72: 269 | W72: 82 | X72: -59 | Y72: =IF(COUNT(L72,V72,W72,X72)=4,L72-V72-W72-X72,"") -> 96 | Z72: 276
A73: Total corporate unallocated expenses | J73: 5199 | K73: 11177 | L73: 5518 | Q73: =IF(COUNT(J73,N73,O73,P73)=4,J73-N73-O73-P73,"") | S73: 1708 | T73: 6502 | U73: =IF(COUNT(K73,R73,S73,T73)=4,K73-R73-S73-T73,"") | V73: 1260 | W73: 2755 | X73: 782 | Y73: =IF(COUNT(L73,V73,W73,X73)=4,L73-V73-W73-X73,"") -> 721 | Z73: 5080
A74: Acquisition-related costs - Cost of Sales | Q74: =IF(COUNT(J74,N74,O74,P74)=4,J74-N74-O74-P74,"") | R74: 224 | U74: =IF(COUNT(K74,R74,S74,T74)=4,K74-R74-S74-T74,"") | V74: 114 | Y74: =IF(COUNT(L74,V74,W74,X74)=4,L74-V74-W74-X74,"")
A75: Acquisition-related costs - Operating Expenses | Q75: =IF(COUNT(J75,N75,O75,P75)=4,J75-N75-O75-P75,"") | R75: 41 | U75: =IF(COUNT(K75,R75,S75,T75)=4,K75-R75-S75-T75,"") | V75: 37 | Y75: =IF(COUNT(L75,V75,W75,X75)=4,L75-V75-W75-X75,"")
A76: Acquisition-related costs - Total | Q76: =IF(COUNT(J76,N76,O76,P76)=4,J76-N76-O76-P76,"") | R76: 265 | U76: =IF(COUNT(K76,R76,S76,T76)=4,K76-R76-S76-T76,"") | V76: 151 | Y76: =IF(COUNT(L76,V76,W76,X76)=4,L76-V76-W76-X76,"")
A77: Share-based compensation - Cost of Sales | Q77: =IF(COUNT(J77,N77,O77,P77)=4,J77-N77-O77-P77,"") | R77: 298 | U77: =IF(COUNT(K77,R77,S77,T77)=4,K77-R77-S77-T77,"") | V77: 175 | Y77: =IF(COUNT(L77,V77,W77,X77)=4,L77-V77-W77-X77,"")
A78: Share-based compensation - Operating Expenses | Q78: =IF(COUNT(J78,N78,O78,P78)=4,J78-N78-O78-P78,"") | R78: 881 | U78: =IF(COUNT(K78,R78,S78,T78)=4,K78-R78-S78-T78,"") | V78: 509 | Y78: =IF(COUNT(L78,V78,W78,X78)=4,L78-V78-W78-X78,"")
A79: Share-based compensation - Total | Q79: =IF(COUNT(J79,N79,O79,P79)=4,J79-N79-O79-P79,"") | R79: 1179 | U79: =IF(COUNT(K79,R79,S79,T79)=4,K79-R79-S79-T79,"") | V79: 684 | Y79: =IF(COUNT(L79,V79,W79,X79)=4,L79-V79-W79-X79,"")
A80: Restructuring and other charges - Cost of Sales | Q80: =IF(COUNT(J80,N80,O80,P80)=4,J80-N80-O80-P80,"") | R80: 0 | U80: =IF(COUNT(K80,R80,S80,T80)=4,K80-R80-S80-T80,"") | V80: 0 | Y80: =IF(COUNT(L80,V80,W80,X80)=4,L80-V80-W80-X80,"")
A81: Restructuring and other charges - Operating Expenses | Q81: =IF(COUNT(J81,N81,O81,P81)=4,J81-N81-O81-P81,"") | R81: 348 | U81: =IF(COUNT(K81,R81,S81,T81)=4,K81-R81-S81-T81,"") | V81: 156 | Y81: =IF(COUNT(L81,V81,W81,X81)=4,L81-V81-W81-X81,"")
A82: Restructuring and other charges - Total | Q82: =IF(COUNT(J82,N82,O82,P82)=4,J82-N82-O82-P82,"") | R82: 348 | U82: =IF(COUNT(K82,R82,S82,T82)=4,K82-R82-S82-T82,"") | V82: 156 | Y82: =IF(COUNT(L82,V82,W82,X82)=4,L82-V82-W82-X82,"")
A83: Other - Cost of Sales | Q83: =IF(COUNT(J83,N83,O83,P83)=4,J83-N83-O83-P83,"") | R83: 179 | U83: =IF(COUNT(K83,R83,S83,T83)=4,K83-R83-S83-T83,"") | V83: 88 | Y83: =IF(COUNT(L83,V83,W83,X83)=4,L83-V83-W83-X83,"")
A84: Other - Operating Expenses | Q84: =IF(COUNT(J84,N84,O84,P84)=4,J84-N84-O84-P84,"") | R84: 216 | U84: =IF(COUNT(K84,R84,S84,T84)=4,K84-R84-S84-T84,"") | V84: 181 | Y84: =IF(COUNT(L84,V84,W84,X84)=4,L84-V84-W84-X84,"")
A85: Other - Total | Q85: =IF(COUNT(J85,N85,O85,P85)=4,J85-N85-O85-P85,"") | R85: 395 | U85: =IF(COUNT(K85,R85,S85,T85)=4,K85-R85-S85-T85,"") | V85: 269 | Y85: =IF(COUNT(L85,V85,W85,X85)=4,L85-V85-W85-X85,"")
... A88: Total corporate unallocated expenses | Q88: =IF(COUNT(J88,N88,O88,P88)=4,J88-N88-O88-P88,"") | R88: 2187 | U88: =IF(COUNT(K88,R88,S88,T88)=4,K88-R88-S88-T88,"") | V88: 1260 | Y88: =IF(COUNT(L88,V88,W88,X88)=4,L88-V88-W88-X88,"")
A90: 2026 supplementary segment detail: Corporate unallocated - composition | B90: 2026 supplementary segment detail: Corporate unallocated - composition | C90: 2026 supplementary segment detail: Corporate unallocated - composition | D90: 2026 supplementary segment detail: Corporate unallocated - composition | E90: 2026 supplementary segment detail: Corporate unallocated - composition | F90: 2026 supplementary segment detail: Corporate unallocated - composition | G90: 2026 supplementary segment detail: Corporate unallocated - composition | H90: 2026 supplementary segment detail: Corporate unallocated - composition | I90: 2026 supplementary segment detail: Corporate unallocated - composition | J90: 2026 supplementary segment detail: Corporate unallocated - composition | K90: 2026 supplementary segment detail: Corporate unallocated - composition | L90: 2026 supplementary segment detail: Corporate unallocated - composition | M90: 2026 supplementary segment detail: Corporate unallocated - composition | N90: 2026 supplementary segment detail: Corporate unallocated - composition | O90: 2026 supplementary segment detail: Corporate unallocated - composition | P90: 2026 supplementary segment detail: Corporate unallocated - composition | Q90: 2026 supplementary segment detail: Corporate unallocated - composition | R90: 2026 supplementary segment detail: Corporate unallocated - composition | S90: 2026 supplementary segment detail: Corporate unallocated - composition | T90: 2026 supplementary segment detail: Corporate unallocated - composition | U90: 2026 supplementary segment detail: Corporate unallocated - composition | V90: 2026 supplementary segment detail: Corporate unallocated - composition | W90: 2026 supplementary segment detail: Corporate unallocated - composition | X90: 2026 supplementary segment detail: Corporate unallocated - composition | Y90: 2026 supplementary segment detail: Corporate unallocated - composition | Z90: 2026 supplementary segment detail: Corporate unallocated - composition | AA90: 2026 supplementary segment detail: Corporate unallocated - composition
A91: Source rows that cannot be matched unambiguously to the 2025 framework are retained separately. | B91: Source rows that cannot be matched unambiguously to the 2025 framework are retained separately. | C91: Source rows that cannot be matched unambiguously to the 2025 framework are retained separately. | D91: Source rows that cannot be matched unambiguously to the 2025 framework are retained separately. | E91: Source rows that cannot be matched unambiguously to the 2025 framework are retained separately. | F91: Source rows that cannot be matched unambiguously to the 2025 framework are retained separately. | G91: Source rows that cannot be matched unambiguously to the 2025 framework are retained separately. | H91: Source rows that cannot be matched unambiguously to the 2025 framework are retained separately. | I91: Source rows that cannot be matched unambiguously to the 2025 framework are retained separately. | J91: Source rows that cannot be matched unambiguously to the 2025 framework are retained separately. | K91: Source rows that cannot be matched unambiguously to the 2025 framework are retained separately. | L91: Source rows that cannot be matched unambiguously to the 2025 framework are retained separately. | M91: Source rows that cannot be matched unambiguously to the 2025 framework are retained separately. | N91: Source rows that cannot be matched unambiguously to the 2025 framework are retained separately. | O91: Source rows that cannot be matched unambiguously to the 2025 framework are retained separately. | P91: Source rows that cannot be matched unambiguously to the 2025 framework are retained separately. | Q91: Source rows that cannot be matched unambiguously to the 2025 framework are retained separately. | R91: Source rows that cannot be matched unambiguously to the 2025 framework are retained separately. | S91: Source rows that cannot be matched unambiguously to the 2025 framework are retained separately. | T91: Source rows that cannot be matched unambiguously to the 2025 framework are retained separately. | U91: Source rows that cannot be matched unambiguously to the 2025 framework are retained separately. | V91: Source rows that cannot be matched unambiguously to the 2025 framework are retained separately. | W91: Source rows that cannot be matched unambiguously to the 2025 framework are retained separately. | X91: Source rows that cannot be matched unambiguously to the 2025 framework are retained separately. | Y91: Source rows that cannot be matched unambiguously to the 2025 framework are retained separately. | Z91: Source rows that cannot be matched unambiguously to the 2025 framework are retained separately. | AA91: Source rows that cannot be matched unambiguously to the 2025 framework are retained separately.
A92: Restructuring and other charges | Q92: =IF(COUNT(J92,N92,O92,P92)=4,J92-N92-O92-P92,"") | U92: =IF(COUNT(K92,R92,S92,T92)=4,K92-R92-S92-T92,"") | W92: 1890 | Y92: =IF(COUNT(L92,V92,W92,X92)=4,L92-V92-W92-X92,"") | AA92: 170
A93: Share-based compensation | Q93: =IF(COUNT(J93,N93,O93,P93)=4,J93-N93-O93-P93,"") | U93: =IF(COUNT(K93,R93,S93,T93)=4,K93-R93-S93-T93,"") | W93: 664 | Y93: =IF(COUNT(L93,V93,W93,X93)=4,L93-V93-W93-X93,"") | AA93: 687
A94: Acquisition-related costs | Q94: =IF(COUNT(J94,N94,O94,P94)=4,J94-N94-O94-P94,"") | U94: =IF(COUNT(K94,R94,S94,T94)=4,K94-R94-S94-T94,"") | W94: 119 | Y94: =IF(COUNT(L94,V94,W94,X94)=4,L94-V94-W94-X94,"") | AA94: 117
A95: CORP UNALLOCATED: Other | Q95: =IF(COUNT(J95,N95,O95,P95)=4,J95-N95-O95-P95,"") | U95: =IF(COUNT(K95,R95,S95,T95)=4,K95-R95-S95-T95,"") | W95: 82 | Y95: =IF(COUNT(L95,V95,W95,X95)=4,L95-V95-W95-X95,"") | AA95: 442
A96: Total corporate unallocated expenses | Q96: =IF(COUNT(J96,N96,O96,P96)=4,J96-N96-O96-P96,"") | U96: =IF(COUNT(K96,R96,S96,T96)=4,K96-R96-S96-T96,"") | W96: 2755 | Y96: =IF(COUNT(L96,V96,W96,X96)=4,L96-V96-W96-X96,"") | AA96: 1416
A98: FY2016 reporting framework: Net revenue | B98: FY2016 reporting framework: Net revenue | C98: FY2016 reporting framework: Net revenue | D98: FY2016 reporting framework: Net revenue | E98: FY2016 reporting framework: Net revenue | F98: FY2016 reporting framework: Net revenue | G98: FY2016 reporting framework: Net revenue | H98: FY2016 reporting framework: Net revenue | I98: FY2016 reporting framework: Net revenue | J98: FY2016 reporting framework: Net revenue | K98: FY2016 reporting framework: Net revenue | L98: FY2016 reporting framework: Net revenue | M98: FY2016 reporting framework: Net revenue | N98: FY2016 reporting framework: Net revenue | O98: FY2016 reporting framework: Net revenue | P98: FY2016 reporting framework: Net revenue | Q98: FY2016 reporting framework: Net revenue | R98: FY2016 reporting framework: Net revenue | S98: FY2016 reporting framework: Net revenue | T98: FY2016 reporting framework: Net revenue | U98: FY2016 reporting framework: Net revenue | V98: FY2016 reporting framework: Net revenue | W98: FY2016 reporting framework: Net revenue | X98: FY2016 reporting framework: Net revenue | Y98: FY2016 reporting framework: Net revenue | Z98: FY2016 reporting framework: Net revenue | AA98: FY2016 reporting framework: Net revenue
A99: Historical segment definitions differ from the current framework; compare within this section only. | B99: Historical segment definitions differ from the current framework; compare within this section only. | C99: Historical segment definitions differ from the current framework; compare within this section only. | D99: Historical segment definitions differ from the current framework; compare within this section only. | E99: Historical segment definitions differ from the current framework; compare within this section only. | F99: Historical segment definitions differ from the current framework; compare within this section only. | G99: Historical segment definitions differ from the current framework; compare within this section only. | H99: Historical segment definitions differ from the current framework; compare within this section only. | I99: Historical segment definitions differ from the current framework; compare within this section only. | J99: Historical segment definitions differ from the current framework; compare within this section only. | K99: Historical segment definitions differ from the current framework; compare within this section only. | L99: Historical segment definitions differ from the current framework; compare within this section only. | M99: Historical segment definitions differ from the current framework; compare within this section only. | N99: Historical segment definitions differ from the current framework; compare within this section only. | O99: Historical segment definitions differ from the current framework; compare within this section only. | P99: Historical segment definitions differ from the current framework; compare within this section only. | Q99: Historical segment definitions differ from the current framework; compare within this section only. | R99: Historical segment definitions differ from the current framework; compare within this section only. | S99: Historical segment definitions differ from the current framework; compare within this section only. | T99: Historical segment definitions differ from the current framework; compare within this section only. | U99: Historical segment definitions differ from the current framework; compare within this section only. | V99: Historical segment definitions differ from the current framework; compare within this section only. | W99: Historical segment definitions differ from the current framework; compare within this section only. | X99: Historical segment definitions differ from the current framework; compare within this section only. | Y99: Historical segment definitions differ from the current framework; compare within this section only. | Z99: Historical segment definitions differ from the current framework; compare within this section only. | AA99: Historical segment definitions differ from the current framework; compare within this section only.
A100: CCG PLATFORM: Platform | C100: 30751 | Q100: =IF(COUNT(J100,N100,O100,P100)=4,J100-N100-O100-P100,"") | U100: =IF(COUNT(K100,R100,S100,T100)=4,K100-R100-S100-T100,"") | Y100: =IF(COUNT(L100,V100,W100,X100)=4,L100-V100-W100-X100,"")
A101: CCG OTHER: Other | C101: 2157 | Q101: =IF(COUNT(J101,N101,O101,P101)=4,J101-N101-O101-P101,"") | U101: =IF(COUNT(K101,R101,S101,T101)=4,K101-R101-S101-T101,"") | Y101: =IF(COUNT(L101,V101,W101,X101)=4,L101-V101-W101-X101,"")
A102: [Client Computing Group total] | C102: 32908 | Q102: =IF(COUNT(J102,N102,O102,P102)=4,J102-N102-O102-P102,"") | U102: =IF(COUNT(K102,R102,S102,T102)=4,K102-R102-S102-T102,"") | Y102: =IF(COUNT(L102,V102,W102,X102)=4,L102-V102-W102-X102,"")
A103: DCG PLATFORM: Platform | C103: 15895 | Q103: =IF(COUNT(J103,N103,O103,P103)=4,J103-N103-O103-P103,"") | U103: =IF(COUNT(K103,R103,S103,T103)=4,K103-R103-S103-T103,"") | Y103: =IF(COUNT(L103,V103,W103,X103)=4,L103-V103-W103-X103,"")
A104: DCG OTHER: Other | C104: 1341 | Q104: =IF(COUNT(J104,N104,O104,P104)=4,J104-N104-O104-P104,"") | U104: =IF(COUNT(K104,R104,S104,T104)=4,K104-R104-S104-T104,"") | Y104: =IF(COUNT(L104,V104,W104,X104)=4,L104-V104-W104-X104,"")
A105: [Data Center Group total] | C105: 17236 | Q105: =IF(COUNT(J105,N105,O105,P105)=4,J105-N105-O105-P105,"") | U105: =IF(COUNT(K105,R105,S105,T105)=4,K105-R105-S105-T105,"") | Y105: =IF(COUNT(L105,V105,W105,X105)=4,L105-V105-W105-X105,"")
A106: IOTG PLATFORM: Platform | C106: 2290 | Q106: =IF(COUNT(J106,N106,O106,P106)=4,J106-N106-O106-P106,"") | U106: =IF(COUNT(K106,R106,S106,T106)=4,K106-R106-S106-T106,"") | Y106: =IF(COUNT(L106,V106,W106,X106)=4,L106-V106-W106-X106,"")
A107: IOTG OTHER: Other | C107: 348 | Q107: =IF(COUNT(J107,N107,O107,P107)=4,J107-N107-O107-P107,"") | U107: =IF(COUNT(K107,R107,S107,T107)=4,K107-R107-S107-T107,"") | Y107: =IF(COUNT(L107,V107,W107,X107)=4,L107-V107-W107-X107,"")
A108: [Internet of Things Group total] | C108: 2638 | Q108: =IF(COUNT(J108,N108,O108,P108)=4,J108-N108-O108-P108,"") | U108: =IF(COUNT(K108,R108,S108,T108)=4,K108-R108-S108-T108,"") | Y108: =IF(COUNT(L108,V108,W108,X108)=4,L108-V108-W108-X108,"")
A109: Non-Volatile Memory Solutions Group | C109: 2576 | Q109: =IF(COUNT(J109,N109,O109,P109)=4,J109-N109-O109-P109,"") | U109: =IF(COUNT(K109,R109,S109,T109)=4,K109-R109-S109-T109,"") | Y109: =IF(COUNT(L109,V109,W109,X109)=4,L109-V109-W109-X109,"")
A110: Intel Security Group | C110: 2161 | Q110: =IF(COUNT(J110,N110,O110,P110)=4,J110-N110-O110-P110,"") | U110: =IF(COUNT(K110,R110,S110,T110)=4,K110-R110-S110-T110,"") | Y110: =IF(COUNT(L110,V110,W110,X110)=4,L110-V110-W110-X110,"")
...

Sheet Revenue & Operations
A1: Intel Corporation — Revenue & Operations | B1: Intel Corporation — Revenue & Operations | C1: Intel Corporation — Revenue & Operations | D1: Intel Corporation — Revenue & Operations | E1: Intel Corporation — Revenue & Operations | F1: Intel Corporation — Revenue & Operations | G1: Intel Corporation — Revenue & Operations | H1: Intel Corporation — Revenue & Operations | I1: Intel Corporation — Revenue & Operations | J1: Intel Corporation — Revenue & Operations | K1: Intel Corporation — Revenue & Operations | L1: Intel Corporation — Revenue & Operations
A2: USD million unless stated otherwise; annual FY2016–FY2025; latest interim 27 June 2026.
A3: Metric | C3: FY2016 | D3: FY2017 | E3: FY2018 | F3: FY2019 | G3: FY2020 | H3: FY2021 | I3: FY2022 | J3: FY2023 | K3: FY2024 | L3: FY2025
C4: 2016-12-31T00:00:00.000Z | D4: 2017-12-30T00:00:00.000Z | E4: 2018-12-29T00:00:00.000Z | F4: 2019-12-28T00:00:00.000Z | G4: 2020-12-26T00:00:00.000Z | H4: 2021-12-25T00:00:00.000Z | I4: 2022-12-31T00:00:00.000Z | J4: 2023-12-30T00:00:00.000Z | K4: 2024-12-28T00:00:00.000Z | L4: 2025-12-27T00:00:00.000Z
A5: Annual / discrete-quarter / instant as identified | C5: Annual | D5: Annual | E5: Annual | F5: Annual | G5: Annual | H5: Annual | I5: Annual | J5: Annual | K5: Annual | L5: Annual
A7: Net revenue by country / region | B7: Net revenue by country / region | C7: Net revenue by country / region | D7: Net revenue by country / region | E7: Net revenue by country / region | F7: Net revenue by country / region | G7: Net revenue by country / region | H7: Net revenue by country / region | I7: Net revenue by country / region | J7: Net revenue by country / region | K7: Net revenue by country / region | L7: Net revenue by country / region
A8: Revenue geography uses customer billing location; it is not end-consumer demand geography. | B8: Revenue geography uses customer billing location; it is not end-consumer demand geography. | C8: Revenue geography uses customer billing location; it is not end-consumer demand geography. | D8: Revenue geography uses customer billing location; it is not end-consumer demand geography. | E8: Revenue geography uses customer billing location; it is not end-consumer demand geography. | F8: Revenue geography uses customer billing location; it is not end-consumer demand geography. | G8: Revenue geography uses customer billing location; it is not end-consumer demand geography. | H8: Revenue geography uses customer billing location; it is not end-consumer demand geography. | I8: Revenue geography uses customer billing location; it is not end-consumer demand geography. | J8: Revenue geography uses customer billing location; it is not end-consumer demand geography. | K8: Revenue geography uses customer billing location; it is not end-consumer demand geography. | L8: Revenue geography uses customer billing location; it is not end-consumer demand geography.
A9: United States | C9: 12957 | D9: 12543 | E9: 14303 | F9: 15617 | G9: 16573 | H9: 14107 | I9: 16529 | J9: 13958 | K9: 12994 | L9: 15757
A10: China | C10: 13977 | D10: 14796 | E10: 18824 | F10: 20026 | G10: 20257 | H10: 21141 | I10: 17125 | J10: 14854 | K10: 15532 | L10: 12694
A11: Singapore | C11: 12780 | D11: 14285 | E11: 15409 | F11: 15650 | G11: 17845 | H11: 14254 | I11: 9664 | J11: 8602 | K11: 10187 | L11: 9535
A12: Taiwan | C12: 9953 | D12: 10518 | E12: 10646 | F12: 10058 | G12: 11605 | H12: 13461 | I12: 8287 | J12: 6867 | K12: 7804 | L12: 7672
A13: Other regions | C13: 9720 | D13: 10619 | E13: 11666 | F13: 10614 | G13: 11587 | H13: 16061 | I13: 11449 | J13: 9947 | K13: 6584 | L13: 7195
A14: Total net revenue | C14: 59387 | D14: 62761 | E14: 70848 | F14: 71965 | G14: 77867 | H14: 79024 | I14: 63054 | J14: 54228 | K14: 53101 | L14: 52853
A15: Check: regions - printed total (should be 0) | C15: =IF(COUNT(C9,C10,C11,C12,C13,C14)=6,C9+C10+C11+C12+C13-C14,"") -> 0 | D15: =IF(COUNT(D9,D10,D11,D12,D13,D14)=6,D9+D10+D11+D12+D13-D14,"") -> 0 | E15: =IF(COUNT(E9,E10,E11,E12,E13,E14)=6,E9+E10+E11+E12+E13-E14,"") -> 0 | F15: =IF(COUNT(F9,F10,F11,F12,F13,F14)=6,F9+F10+F11+F12+F13-F14,"") -> 0 | G15: =IF(COUNT(G9,G10,G11,G12,G13,G14)=6,G9+G10+G11+G12+G13-G14,"") -> 0 | H15: =IF(COUNT(H9,H10,H11,H12,H13,H14)=6,H9+H10+H11+H12+H13-H14,"") -> 0 | I15: =IF(COUNT(I9,I10,I11,I12,I13,I14)=6,I9+I10+I11+I12+I13-I14,"") -> 0 | J15: =IF(COUNT(J9,J10,J11,J12,J13,J14)=6,J9+J10+J11+J12+J13-J14,"") -> 0 | ... L15: =IF(COUNT(L9,L10,L11,L12,L13,L14)=6,L9+L10+L11+L12+L13-L14,"") -> 0
A16: Check: total vs income-statement net revenue (should be 0)
A18: Customer concentration (% of revenue) | B18: Customer concentration (% of revenue) | C18: Customer concentration (% of revenue) | D18: Customer concentration (% of revenue) | E18: Customer concentration (% of revenue) | F18: Customer concentration (% of revenue) | G18: Customer concentration (% of revenue) | H18: Customer concentration (% of revenue) | I18: Customer concentration (% of revenue) | J18: Customer concentration (% of revenue) | K18: Customer concentration (% of revenue) | L18: Customer concentration (% of revenue)
A19: Customer A | I19: 0.19 | J19: 0.19 | K19: 0.19 | L19: 0.19
A20: Customer B | I20: 0.12 | J20: 0.11 | K20: 0.14 | L20: 0.12
A21: Customer C | I21: 0.11 | J21: 0.1 | K21: 0.12 | L21: 0.12
A22: Dell Inc. | H22: 0.21 | I22: 0.19 | J22: 0.19
A23: Lenovo Group Limited | H23: 0.12 | I23: 0.12 | J23: 0.11
A24: HP Inc. | H24: 0.1 | I24: 0.11 | J24: 0.1
A25: Total percentage of net revenue | H25: 0.43 | I25: 0.42 | J25: 0.4 | K25: 0.45 | L25: 0.43
A27: Platform vs Adjacent revenue outside the segment note | B27: Platform vs Adjacent revenue outside the segment note | C27: Platform vs Adjacent revenue outside the segment note | D27: Platform vs Adjacent revenue outside the segment note | E27: Platform vs Adjacent revenue outside the segment note | F27: Platform vs Adjacent revenue outside the segment note | G27: Platform vs Adjacent revenue outside the segment note | H27: Platform vs Adjacent revenue outside the segment note | I27: Platform vs Adjacent revenue outside the segment note | J27: Platform vs Adjacent revenue outside the segment note | K27: Platform vs Adjacent revenue outside the segment note | L27: Platform vs Adjacent revenue outside the segment note
A28: CCG notebook platform | D28: 19414 | E28: 20930 | F28: 20779 | G28: 24903 | H28: 25475
A29: Other platform | C29: 2467 | D29: 2810 | E29: 3149 | F29: 80
A30: CCG desktop platform | D30: 11647 | E30: 12220 | F30: 11822 | G30: 10692 | H30: 11835
A31: CCG other platform1 | E31: 84 | F31: 80 | G31: 47 | H31: 66
A32: Desktop platform | C32: 12371 | D32: 11647 | E32: 12220
A33: Notebook platform | C33: 18203 | D33: 19414 | E33: 20930
A34: DCG platform | C34: 15895 | D34: 17439 | E34: 21155 | F34: 21441 | G34: 23056 | H34: 22703
A35: IOTG platform | D35: 2645 | E35: 3065 | F35: 3440 | G35: 2705 | H35: 3658
A36: [Total platform revenue] | C36: 48936 | D36: 51310 | E36: 57454 | F36: 57562 | G36: 61403 | H36: 63737
A37: Adjacent revenue | C37: 8290 | D37: 10917 | E37: 13394 | F37: 14403
A38: ISecG divested business | C38: 2161 | D38: 534 | E38: 0 | F38: 0
A39: Adjacent revenue2 | E39: 13394 | F39: 14403 | G39: 16464 | H39: 15287
A40: Total revenue | C40: 59387 | D40: 62761 | E40: 70848 | F40: 71965 | G40: 77867 | H40: 79024
A42: Platform sales volumes and average selling prices | B42: Platform sales volumes and average selling prices | C42: Platform sales volumes and average selling prices | D42: Platform sales volumes and average selling prices | E42: Platform sales volumes and average selling prices | F42: Platform sales volumes and average selling prices | G42: Platform sales volumes and average selling prices | H42: Platform sales volumes and average selling prices | I42: Platform sales volumes and average selling prices | J42: Platform sales volumes and average selling prices | K42: Platform sales volumes and average selling prices | L42: Platform sales volumes and average selling prices
A43: Desktop platform volume - CCG: change (%) | E43: -0.06 | F43: -0.06 | G43: -0.11 | H43: 0.08
A44: Desktop platform volume - CCG: revenue contribution (USD million) | E44: -608 | F44: -705 | G44: -1316 | H44: 851
A45: Desktop platform ASP - CCG: change (%) | E45: 0.11 | F45: 0.03 | G45: 0.02 | H45: 0.03
A46: Desktop platform ASP - CCG: revenue contribution (USD million) | E46: 1181 | F46: 307 | G46: 186 | H46: 292
A47: Notebook platform volume - CCG: change (%) | E47: 0.04 | F47: -0.05 | G47: 0.28 | H47: 0.08
A48: Notebook platform volume - CCG: revenue contribution (USD million) | E48: 839 | F48: -1080 | G48: 5770 | H48: 2102
A49: Notebook platform ASP - CCG: change (%) | E49: 0.03 | F49: 0.05 | G49: -0.06 | H49: -0.06
A50: Notebook platform ASP - CCG: revenue contribution (USD million) | E50: 677 | F50: 929 | G50: -1646 | H50: -1530
A51: Adjacent products and other - CCG: revenue contribution (USD million) | E51: 912 | F51: 691 | G51: -83 | H51: -1261
A52: Total change in revenue - CCG: revenue contribution (USD million) | E52: 3001 | F52: 142 | G52: 2911 | H52: 454
A53: Platform ASP - DCG: change (%) | E53: 0.07 | F53: 0.05 | G53: -0.03 | H53: -0.04
A54: Platform ASP - DCG: revenue contribution (USD million) | E54: 1382 | F54: 940 | G54: -701 | H54: -924
A55: Adjacent Products - DCG: change (%) | E55: 0.13
A56: Adjacent Products - DCG: revenue contribution (USD million) | E56: 211
A57: Platform volume - DCG: change (%) | E57: 0.13 | F57: -0.03 | G57: 0.11 | H57: 0.02
A58: Platform volume - DCG: revenue contribution (USD million) | E58: 2334 | F58: -654 | G58: 2316 | H58: 571
A59: Adjacent products - DCG: change (%) | F59: 0.11 | G59: 0.49 | H59: 0.02
A60: Adjacent products - DCG: revenue contribution (USD million) | F60: 204 | G60: 1007 | H60: 71
A61: Total change in revenue - DCG: revenue contribution (USD million) | E61: 3927 | F61: 490 | G61: 2622 | H61: -282
A62: Volume - CCG: change (%) | D62: -0.05
A63: ASP - CCG: change (%) | D63: 0
A64: Volume - CCG: change (%) | D64: 0.05
A65: ASP - CCG: change (%) | D65: 0.02
A66: Revenue - CCG: change (%) | D66: 0.29
A67: Cloud Service Provider - DCG: change (%) | D67: 0.28
A68: Enterprise and Government - DCG: change (%) | D68: -0.03
A69: Communication Service Provider - DCG: change (%) | D69: 0.15
A70: Volume - DCG: change (%) | D70: 0.05
A71: ASP - DCG: change (%) | D71: 0.04
A72: Revenue - DCG: change (%) | D72: 0.21
A73: CCG platform unit sales - CCG: change (%) | C73: -0.1
A74: CCG platform average selling prices - CCG: change (%) | C74: 0.11
A75: DCG platform unit sales - DCG: change (%) | C75: 0.08
A76: DCG platform average selling prices - DCG: change (%) | C76: -0.01
A78: Employees | B78: Employees | C78: Employees | D78: Employees | E78: Employees | F78: Employees | G78: Employees | H78: Employees | I78: Employees | J78: Employees | K78: Employees | L78: Employees
A79: Employees (people) | C79: 106000 | D79: 102700 | E79: 107400 | F79: 110800 | G79: 110600 | H79: 121100 | I79: 131900 | J79: 124800 | K79: 108900 | L79: 85100
A81: Facilities (million square feet) | B81: Facilities (million square feet) | C81: Facilities (million square feet) | D81: Facilities (million square feet) | E81: Facilities (million square feet) | F81: Facilities (million square feet) | G81: Facilities (million square feet) | H81: Facilities (million square feet) | I81: Facilities (million square feet) | J81: Facilities (million square feet) | K81: Facilities (million square feet) | L81: Facilities (million square feet)
A82: Owned facilities [UnitedStates] | C82: 31.5 | D82: 31.3 | E82: 30.5 | F82: 31.3 | G82: 31 | H82: 31 | I82: 34 | J82: 38 | K82: 35 | L82: 35
A83: Owned facilities [OtherCountries] | C83: 19.2 | D83: 17.9 | E83: 22.2 | F83: 22.3 | G83: 23 | H83: 24 | I83: 25 | J83: 28 | K83: 28 | L83: 25
A84: Owned facilities [Total] | C84: 50.7 | D84: 49.2 | E84: 52.7 | F84: 53.6 | G84: 54 | H84: 55 | I84: 59 | J84: 66 | K84: 63 | L84: 60
A85: Leased facilities [UnitedStates] | C85: 2.5 | D85: 1.6 | E85: 1 | F85: 0.8 | G85: 1 | H85: 1 | I85: 1 | J85: 2 | K85: 3 | L85: 2
A86: Leased facilities [OtherCountries] | C86: 7.1 | D86: 6.3 | E86: 6.6 | F86: 5.4 | G86: 5 | H86: 5 | I86: 5 | J86: 5 | K86: 4 | L86: 3
A87: Leased facilities [Total] | C87: 9.6 | D87: 7.9 | E87: 7.6 | F87: 6.2 | G87: 6 | H87: 6 | I87: 6 | J87: 7 | K87: 7 | L87: 5
A88: Total facilities [UnitedStates] | C88: 34 | D88: 32.9 | E88: 31.5 | F88: 32.1 | G88: 32 | H88: 32 | I88: 35 | J88: 40 | K88: 38 | L88: 37
A89: Total facilities [OtherCountries] | C89: 26.3 | D89: 24.2 | E89: 28.8 | F89: 27.7 | G89: 28 | H89: 29 | I89: 30 | J89: 33 | K89: 32 | L89: 28
A90: Total facilities [Total] | C90: 60.3 | D90: 57.1 | E90: 60.3 | F90: 59.8 | G90: 60 | H90: 61 | I90: 65 | J90: 73 | K90: 70 | L90: 65
A92: Other MD&A tables | B92: Other MD&A tables | C92: Other MD&A tables | D92: Other MD&A tables | E92: Other MD&A tables | F92: Other MD&A tables | G92: Other MD&A tables | H92: Other MD&A tables | I92: Other MD&A tables | J92: Other MD&A tables | K92: Other MD&A tables | L92: Other MD&A tables
A93: Research and development (R&D) | C93: 12740
A94: Marketing, general and administrative (MG&A) | C94: 8397
A95: R&D and MG&A as percentage of net revenue | C95: 0.356
A96: Restructuring and other charges | C96: 1886
A97: Amortization of acquisition-related intangibles | C97: 294
A98: Gains (losses) on equity investments, net | C98: 506 | D98: 2651 | E98: -125
A99: Interest and other, net | C99: -444 | D99: -235 | E99: 126
A101: Official growth attribution: Intel consolidated: gross margin bridge | B101: Official growth attribution: Intel consolidated: gross margin bridge | C101: Official growth attribution: Intel consolidated: gross margin bridge | D101: Official growth attribution: Intel consolidated: gross margin bridge | E101: Official growth attribution: Intel consolidated: gross margin bridge | F101: Official growth attribution: Intel consolidated: gross margin bridge | G101: Official growth attribution: Intel consolidated: gross margin bridge | H101: Official growth attribution: Intel consolidated: gross margin bridge | I101: Official growth attribution: Intel consolidated: gross margin bridge | J101: Official growth attribution: Intel consolidated: gross margin bridge | K101: Official growth attribution: Intel consolidated: gross margin bridge | L101: Official growth attribution: Intel consolidated: gross margin bridge
A102: Company-disclosed year-on-year contributions in USD million. Only the filing year’s own comparison is shown; duplicated bridge endpoints remain in source records. | B102: Company-disclosed year-on-year contributions in USD million. Only the filing year’s own comparison is shown; duplicated bridge endpoints remain in source records. | C102: Company-disclosed year-on-year contributions in USD million. Only the filing year’s own comparison is shown; duplicated bridge endpoints remain in source records. | D102: Company-disclosed year-on-year contributions in USD million. Only the filing year’s own comparison is shown; duplicated bridge endpoints remain in source records. | E102: Company-disclosed year-on-year contributions in USD million. Only the filing year’s own comparison is shown; duplicated bridge endpoints remain in source records. | F102: Company-disclosed year-on-year contributions in USD million. Only the filing year’s own comparison is shown; duplicated bridge endpoints remain in source records. | G102: Company-disclosed year-on-year contributions in USD million. Only the filing year’s own comparison is shown; duplicated bridge endpoints remain in source records. | H102: Company-disclosed year-on-year contributions in USD million. Only the filing year’s own comparison is shown; duplicated bridge endpoints remain in source records. | I102: Company-disclosed year-on-year contributions in USD million. Only the filing year’s own comparison is shown; duplicated bridge endpoints remain in source records. | J102: Company-disclosed year-on-year contributions in USD million. Only the filing year’s own comparison is shown; duplicated bridge endpoints remain in source records. | K102: Company-disclosed year-on-year contributions in USD million. Only the filing year’s own comparison is shown; duplicated bridge endpoints remain in source records. | L102: Company-disclosed year-on-year contributions in USD million. Only the filing year’s own comparison is shown; duplicated bridge endpoints remain in source records.
A103: Higher gross margin from platform revenue | C103: 1830 | D103: 2380 | E103: 5810 | F103: 580 | G103: 2360 | H103: 1010
A104: PSG gross margin from acquisition of Altera | C104: 1150
A105: Lower platform unit cost | C105: 935
A106: Altera and other acquisition-related charges | C106: -1045
A107: Lower NSG gross margin | C107: -690
A108: Higher factory start-up costs, primarily driven by the ramp of our 10nm process technology | C108: -645 | D108: -535
...

Sheet Income Statement
A1: Intel Corporation — Income Statement | B1: Intel Corporation — Income Statement | C1: Intel Corporation — Income Statement | D1: Intel Corporation — Income Statement | E1: Intel Corporation — Income Statement | F1: Intel Corporation — Income Statement | G1: Intel Corporation — Income Statement | H1: Intel Corporation — Income Statement | I1: Intel Corporation — Income Statement | J1: Intel Corporation — Income Statement | K1: Intel Corporation — Income Statement | L1: Intel Corporation — Income Statement | M1: Intel Corporation — Income Statement | N1: Intel Corporation — Income Statement | O1: Intel Corporation — Income Statement | P1: Intel Corporation — Income Statement | Q1: Intel Corporation — Income Statement | R1: Intel Corporation — Income Statement | S1: Intel Corporation — Income Statement | T1: Intel Corporation — Income Statement | U1: Intel Corporation — Income Statement | V1: Intel Corporation — Income Statement | W1: Intel Corporation — Income Statement | X1: Intel Corporation — Income Statement | Y1: Intel Corporation — Income Statement | Z1: Intel Corporation — Income Statement | AA1: Intel Corporation — Income Statement
A2: USD million unless stated otherwise; annual FY2016–FY2025; latest interim 27 June 2026.
A3: Metric | C3: FY2016 | D3: FY2017 | E3: FY2018 | F3: FY2019 | G3: FY2020 | H3: FY2021 | I3: FY2022 | J3: FY2023 | K3: FY2024 | L3: FY2025 | N3: 1Q2023 | O3: 2Q2023 | P3: 3Q2023 | Q3: 4Q2023 | R3: 1Q2024 | S3: 2Q2024 | T3: 3Q2024 | U3: 4Q2024 | V3: 1Q2025 | W3: 2Q2025 | X3: 3Q2025 | Y3: 4Q2025 | Z3: 1Q2026 | AA3: 2Q2026
C4: 2016-12-31T00:00:00.000Z | D4: 2017-12-30T00:00:00.000Z | E4: 2018-12-29T00:00:00.000Z | F4: 2019-12-28T00:00:00.000Z | G4: 2020-12-26T00:00:00.000Z | H4: 2021-12-25T00:00:00.000Z | I4: 2022-12-31T00:00:00.000Z | J4: 2023-12-30T00:00:00.000Z | K4: 2024-12-28T00:00:00.000Z | L4: 2025-12-27T00:00:00.000Z | N4: 2023-04-01T00:00:00.000Z | O4: 2023-07-01T00:00:00.000Z | P4: 2023-09-30T00:00:00.000Z | Q4: 2023-12-30T00:00:00.000Z | R4: 2024-03-30T00:00:00.000Z | S4: 2024-06-29T00:00:00.000Z | T4: 2024-09-28T00:00:00.000Z | U4: 2024-12-28T00:00:00.000Z | V4: 2025-03-29T00:00:00.000Z | W4: 2025-06-28T00:00:00.000Z | X4: 2025-09-27T00:00:00.000Z | Y4: 2025-12-27T00:00:00.000Z | Z4: 2026-03-28T00:00:00.000Z | AA4: 2026-06-27T00:00:00.000Z
A5: Annual / discrete-quarter / instant as identified | C5: Annual | D5: Annual | E5: Annual | F5: Annual | G5: Annual | H5: Annual | I5: Annual | J5: Annual | K5: Annual | L5: Annual | N5: Quarter / note basis | O5: Quarter / note basis | P5: Quarter / note basis | Q5: Quarter / note basis | R5: Quarter / note basis | S5: Quarter / note basis | T5: Quarter / note basis | U5: Quarter / note basis | V5: Quarter / note basis | W5: Quarter / note basis | X5: Quarter / note basis | Y5: Quarter / note basis | Z5: Quarter / note basis | AA5: Quarter / note basis
A7: Revenue and gross profit | B7: Revenue and gross profit | C7: Revenue and gross profit | D7: Revenue and gross profit | E7: Revenue and gross profit | F7: Revenue and gross profit | G7: Revenue and gross profit | H7: Revenue and gross profit | I7: Revenue and gross profit | J7: Revenue and gross profit | K7: Revenue and gross profit | L7: Revenue and gross profit | M7: Revenue and gross profit | N7: Revenue and gross profit | O7: Revenue and gross profit | P7: Revenue and gross profit | Q7: Revenue and gross profit | R7: Revenue and gross profit | S7: Revenue and gross profit | T7: Revenue and gross profit | U7: Revenue and gross profit | V7: Revenue and gross profit | W7: Revenue and gross profit | X7: Revenue and gross profit | Y7: Revenue and gross profit | Z7: Revenue and gross profit | AA7: Revenue and gross profit
A8: USD million, except per-share figures and shares (million). Quarterly columns are discrete quarters; Q4 is derived only for additive flows. | B8: USD million, except per-share figures and shares (million). Quarterly columns are discrete quarters; Q4 is derived only for additive flows. | C8: USD million, except per-share figures and shares (million). Quarterly columns are discrete quarters; Q4 is derived only for additive flows. | D8: USD million, except per-share figures and shares (million). Quarterly columns are discrete quarters; Q4 is derived only for additive flows. | E8: USD million, except per-share figures and shares (million). Quarterly columns are discrete quarters; Q4 is derived only for additive flows. | F8: USD million, except per-share figures and shares (million). Quarterly columns are discrete quarters; Q4 is derived only for additive flows. | G8: USD million, except per-share figures and shares (million). Quarterly columns are discrete quarters; Q4 is derived only for additive flows. | H8: USD million, except per-share figures and shares (million). Quarterly columns are discrete quarters; Q4 is derived only for additive flows. | I8: USD million, except per-share figures and shares (million). Quarterly columns are discrete quarters; Q4 is derived only for additive flows. | J8: USD million, except per-share figures and shares (million). Quarterly columns are discrete quarters; Q4 is derived only for additive flows. | K8: USD million, except per-share figures and shares (million). Quarterly columns are discrete quarters; Q4 is derived only for additive flows. | L8: USD million, except per-share figures and shares (million). Quarterly columns are discrete quarters; Q4 is derived only for additive flows. | M8: USD million, except per-share figures and shares (million). Quarterly columns are discrete quarters; Q4 is derived only for additive flows. | N8: USD million, except per-share figures and shares (million). Quarterly columns are discrete quarters; Q4 is derived only for additive flows. | O8: USD million, except per-share figures and shares (million). Quarterly columns are discrete quarters; Q4 is derived only for additive flows. | P8: USD million, except per-share figures and shares (million). Quarterly columns are discrete quarters; Q4 is derived only for additive flows. | Q8: USD million, except per-share figures and shares (million). Quarterly columns are discrete quarters; Q4 is derived only for additive flows. | R8: USD million, except per-share figures and shares (million). Quarterly columns are discrete quarters; Q4 is derived only for additive flows. | S8: USD million, except per-share figures and shares (million). Quarterly columns are discrete quarters; Q4 is derived only for additive flows. | T8: USD million, except per-share figures and shares (million). Quarterly columns are discrete quarters; Q4 is derived only for additive flows. | U8: USD million, except per-share figures and shares (million). Quarterly columns are discrete quarters; Q4 is derived only for additive flows. | V8: USD million, except per-share figures and shares (million). Quarterly columns are discrete quarters; Q4 is derived only for additive flows. | W8: USD million, except per-share figures and shares (million). Quarterly columns are discrete quarters; Q4 is derived only for additive flows. | X8: USD million, except per-share figures and shares (million). Quarterly columns are discrete quarters; Q4 is derived only for additive flows. | Y8: USD million, except per-share figures and shares (million). Quarterly columns are discrete quarters; Q4 is derived only for additive flows. | Z8: USD million, except per-share figures and shares (million). Quarterly columns are discrete quarters; Q4 is derived only for additive flows. | AA8: USD million, except per-share figures and shares (million). Quarterly columns are discrete quarters; Q4 is derived only for additive flows.
A9: Net revenue | C9: 59387 | D9: 62761 | E9: 70848 | F9: 71965 | G9: 77867 | H9: 79024 | I9: 63054 | J9: 54228 | K9: 53101 | L9: 52853 | N9: 11715 | O9: 12949 | P9: 14158 | Q9: =IF(COUNT(J9,N9,O9,P9)=4,J9-N9-O9-P9,"") -> 15406 | R9: 12724 | S9: 12833 | T9: 13284 | U9: =IF(COUNT(K9,R9,S9,T9)=4,K9-R9-S9-T9,"") -> 14260 | V9: 12667 | W9: 12859 | X9: 13653 | Y9: =IF(COUNT(L9,V9,W9,X9)=4,L9-V9-W9-X9,"") -> 13674 | Z9: 13577 | AA9: 16128
A10: YoY growth | D10: =IF(COUNT(D9,C9)=2,IF(C9>0,D9/C9-1,"n.m."),"") -> 0.056813781 | E10: =IF(COUNT(E9,D9)=2,IF(D9>0,E9/D9-1,"n.m."),"") -> 0.12885391 | F10: =IF(COUNT(F9,E9)=2,IF(E9>0,F9/E9-1,"n.m."),"") -> 0.015766147 | G10: =IF(COUNT(G9,F9)=2,IF(F9>0,G9/F9-1,"n.m."),"") -> 0.082012089 | H10: =IF(COUNT(H9,G9)=2,IF(G9>0,H9/G9-1,"n.m."),"") -> 0.014858669 | I10: =IF(COUNT(I9,H9)=2,IF(H9>0,I9/H9-1,"n.m."),"") -> -0.2020905 | J10: =IF(COUNT(J9,I9)=2,IF(I9>0,J9/I9-1,"n.m."),"") -> -0.13997526 | K10: =IF(COUNT(K9,J9)=2,IF(J9>0,K9/J9-1,"n.m."),"") -> -0.020782622 | L10: =IF(COUNT(L9,K9)=2,IF(K9>0,L9/K9-1,"n.m."),"") -> -0.0046703452 | R10: =IF(COUNT(R9,N9)=2,IF(N9>0,R9/N9-1,"n.m."),"") -> 0.086128895 | S10: =IF(COUNT(S9,O9)=2,IF(O9>0,S9/O9-1,"n.m."),"") -> -0.0089582207 | T10: =IF(COUNT(T9,P9)=2,IF(P9>0,T9/P9-1,"n.m."),"") -> -0.061731883 | U10: =IF(COUNT(U9,Q9)=2,IF(Q9>0,U9/Q9-1,"n.m."),"") -> -0.074386603 | V10: =IF(COUNT(V9,R9)=2,IF(R9>0,V9/R9-1,"n.m."),"") -> -0.0044797234 | W10: =IF(COUNT(W9,S9)=2,IF(S9>0,W9/S9-1,"n.m."),"") -> 0.0020260267 | X10: =IF(COUNT(X9,T9)=2,IF(T9>0,X9/T9-1,"n.m."),"") -> 0.027777778 | Y10: =IF(COUNT(Y9,U9)=2,IF(U9>0,Y9/U9-1,"n.m."),"") -> -0.041093969 | ... AA10: =IF(COUNT(AA9,W9)=2,IF(W9>0,AA9/W9-1,"n.m."),"") -> 0.25421884
A11: Cost of sales | C11: 23196 | D11: 23692 | E11: 27111 | F11: 29825 | G11: 34255 | H11: 35209 | I11: 36188 | J11: 32517 | K11: 35756 | L11: 34478 | N11: 7707 | O11: 8311 | P11: 8140 | Q11: =IF(COUNT(J11,N11,O11,P11)=4,J11-N11-O11-P11,"") -> 8359 | R11: 7507 | S11: 8286 | T11: 11287 | U11: =IF(COUNT(K11,R11,S11,T11)=4,K11-R11-S11-T11,"") -> 8676 | V11: 7995 | W11: 9317 | X11: 8435 | Y11: =IF(COUNT(L11,V11,W11,X11)=4,L11-V11-W11-X11,"") -> 8731 | Z11: 8230 | AA11: 9619
A12: Gross profit (earlier captioned 'Gross margin') | C12: 36191 | D12: 39069 | E12: 43737 | F12: 42140 | G12: 43612 | H12: 43815 | I12: 26866 | J12: 21711 | K12: 17345 | L12: 18375 | N12: 4008 | O12: 4638 | P12: 6018 | Q12: =IF(COUNT(J12,N12,O12,P12)=4,J12-N12-O12-P12,"") -> 7047 | R12: 5217 | S12: 4547 | T12: 1997 | U12: =IF(COUNT(K12,R12,S12,T12)=4,K12-R12-S12-T12,"") -> 5584 | V12: 4672 | W12: 3542 | X12: 5218 | Y12: =IF(COUNT(L12,V12,W12,X12)=4,L12-V12-W12-X12,"") -> 4943 | Z12: 5347 | AA12: 6509
A13: Gross margin | C13: =IF(COUNT(C12,C9)=2,C12/C9,"") -> 0.60940947 | D13: =IF(COUNT(D12,D9)=2,D12/D9,"") -> 0.62250442 | E13: =IF(COUNT(E12,E9)=2,E12/E9,"") -> 0.6173357 | F13: =IF(COUNT(F12,F9)=2,F12/F9,"") -> 0.58556243 | G13: =IF(COUNT(G12,G9)=2,G12/G9,"") -> 0.56008322 | H13: =IF(COUNT(H12,H9)=2,H12/H9,"") -> 0.55445181 | I13: =IF(COUNT(I12,I9)=2,I12/I9,"") -> 0.42607923 | J13: =IF(COUNT(J12,J9)=2,J12/J9,"") -> 0.40036513 | ... L13: =IF(COUNT(L12,L9)=2,L12/L9,"") -> 0.34766238 | N13: =IF(COUNT(N12,N9)=2,N12/N9,"") -> 0.34212548 | O13: =IF(COUNT(O12,O9)=2,O12/O9,"") -> 0.35817438 | P13: =IF(COUNT(P12,P9)=2,P12/P9,"") -> 0.42506004 | Q13: =IF(COUNT(Q12,Q9)=2,Q12/Q9,"") -> 0.45741919 | R13: =IF(COUNT(R12,R9)=2,R12/R9,"") -> 0.41001257 | S13: =IF(COUNT(S12,S9)=2,S12/S9,"") -> 0.35432089 | T13: =IF(COUNT(T12,T9)=2,T12/T9,"") -> 0.15033123 | U13: =IF(COUNT(U12,U9)=2,U12/U9,"") -> 0.39158485 | ... AA13: =IF(COUNT(AA12,AA9)=2,AA12/AA9,"") -> 0.40358383
A15: Operating expenses and operating profit | B15: Operating expenses and operating profit | C15: Operating expenses and operating profit | D15: Operating expenses and operating profit | E15: Operating expenses and operating profit | F15: Operating expenses and operating profit | G15: Operating expenses and operating profit | H15: Operating expenses and operating profit | I15: Operating expenses and operating profit | J15: Operating expenses and operating profit | K15: Operating expenses and operating profit | L15: Operating expenses and operating profit | M15: Operating expenses and operating profit | N15: Operating expenses and operating profit | O15: Operating expenses and operating profit | P15: Operating expenses and operating profit | Q15: Operating expenses and operating profit | R15: Operating expenses and operating profit | S15: Operating expenses and operating profit | T15: Operating expenses and operating profit | U15: Operating expenses and operating profit | V15: Operating expenses and operating profit | W15: Operating expenses and operating profit | X15: Operating expenses and operating profit | Y15: Operating expenses and operating profit | Z15: Operating expenses and operating profit | AA15: Operating expenses and operating profit
A16: Historical annual figures are as originally filed. Pension presentation changed in 2018; acquisition amortization moved into functional costs in 2020. See source notes. | B16: Historical annual figures are as originally filed. Pension presentation changed in 2018; acquisition amortization moved into functional costs in 2020. See source notes. | C16: Historical annual figures are as originally filed. Pension presentation changed in 2018; acquisition amortization moved into functional costs in 2020. See source notes. | D16: Historical annual figures are as originally filed. Pension presentation changed in 2018; acquisition amortization moved into functional costs in 2020. See source notes. | E16: Historical annual figures are as originally filed. Pension presentation changed in 2018; acquisition amortization moved into functional costs in 2020. See source notes. | F16: Historical annual figures are as originally filed. Pension presentation changed in 2018; acquisition amortization moved into functional costs in 2020. See source notes. | G16: Historical annual figures are as originally filed. Pension presentation changed in 2018; acquisition amortization moved into functional costs in 2020. See source notes. | H16: Historical annual figures are as originally filed. Pension presentation changed in 2018; acquisition amortization moved into functional costs in 2020. See source notes. | I16: Historical annual figures are as originally filed. Pension presentation changed in 2018; acquisition amortization moved into functional costs in 2020. See source notes. | J16: Historical annual figures are as originally filed. Pension presentation changed in 2018; acquisition amortization moved into functional costs in 2020. See source notes. | K16: Historical annual figures are as originally filed. Pension presentation changed in 2018; acquisition amortization moved into functional costs in 2020. See source notes. | L16: Historical annual figures are as originally filed. Pension presentation changed in 2018; acquisition amortization moved into functional costs in 2020. See source notes. | M16: Historical annual figures are as originally filed. Pension presentation changed in 2018; acquisition amortization moved into functional costs in 2020. See source notes. | N16: Historical annual figures are as originally filed. Pension presentation changed in 2018; acquisition amortization moved into functional costs in 2020. See source notes. | O16: Historical annual figures are as originally filed. Pension presentation changed in 2018; acquisition amortization moved into functional costs in 2020. See source notes. | P16: Historical annual figures are as originally filed. Pension presentation changed in 2018; acquisition amortization moved into functional costs in 2020. See source notes. | Q16: Historical annual figures are as originally filed. Pension presentation changed in 2018; acquisition amortization moved into functional costs in 2020. See source notes. | R16: Historical annual figures are as originally filed. Pension presentation changed in 2018; acquisition amortization moved into functional costs in 2020. See source notes. | S16: Historical annual figures are as originally filed. Pension presentation changed in 2018; acquisition amortization moved into functional costs in 2020. See source notes. | T16: Historical annual figures are as originally filed. Pension presentation changed in 2018; acquisition amortization moved into functional costs in 2020. See source notes. | U16: Historical annual figures are as originally filed. Pension presentation changed in 2018; acquisition amortization moved into functional costs in 2020. See source notes. | V16: Historical annual figures are as originally filed. Pension presentation changed in 2018; acquisition amortization moved into functional costs in 2020. See source notes. | W16: Historical annual figures are as originally filed. Pension presentation changed in 2018; acquisition amortization moved into functional costs in 2020. See source notes. | X16: Historical annual figures are as originally filed. Pension presentation changed in 2018; acquisition amortization moved into functional costs in 2020. See source notes. | Y16: Historical annual figures are as originally filed. Pension presentation changed in 2018; acquisition amortization moved into functional costs in 2020. See source notes. | Z16: Historical annual figures are as originally filed. Pension presentation changed in 2018; acquisition amortization moved into functional costs in 2020. See source notes. | AA16: Historical annual figures are as originally filed. Pension presentation changed in 2018; acquisition amortization moved into functional costs in 2020. See source notes.
A17: Research and development | C17: 12740 | D17: 13098 | E17: 13543 | F17: 13362 | G17: 13556 | H17: 15190 | I17: 17528 | J17: 16046 | K17: 16546 | L17: 13774 | N17: 4109 | O17: 4080 | P17: 3870 | Q17: =IF(COUNT(J17,N17,O17,P17)=4,J17-N17-O17-P17,"") -> 3987 | R17: 4382 | S17: 4239 | T17: 4049 | U17: =IF(COUNT(K17,R17,S17,T17)=4,K17-R17-S17-T17,"") -> 3876 | V17: 3640 | W17: 3684 | X17: 3231 | Y17: =IF(COUNT(L17,V17,W17,X17)=4,L17-V17-W17-X17,"") -> 3219 | Z17: 3375 | AA17: 3368
A18: Marketing, general and administrative | C18: 8397 | D18: 7474 | E18: 6750 | F18: 6150 | G18: 6180 | H18: 6543 | I18: 7002 | J18: 5634 | K18: 5507 | L18: 4624 | N18: 1303 | O18: 1374 | P18: 1340 | Q18: =IF(COUNT(J18,N18,O18,P18)=4,J18-N18-O18-P18,"") -> 1617 | R18: 1556 | S18: 1329 | T18: 1383 | U18: =IF(COUNT(K18,R18,S18,T18)=4,K18-R18-S18-T18,"") -> 1239 | V18: 1177 | W18: 1144 | X18: 1129 | Y18: =IF(COUNT(L18,V18,W18,X18)=4,L18-V18-W18-X18,"") -> 1174 | Z18: 1038 | AA18: 1175
A19: Restructuring and other charges | C19: 1886 | D19: 384 | E19: -72 | F19: 393 | G19: 198 | H19: 2626 | I19: 2 | J19: -62 | K19: 6970 | L19: 2191 | N19: 64 | O19: 200 | P19: 816 | Q19: =IF(COUNT(J19,N19,O19,P19)=4,J19-N19-O19-P19,"") -> -1142 | R19: 348 | S19: 943 | T19: 5622 | U19: =IF(COUNT(K19,R19,S19,T19)=4,K19-R19-S19-T19,"") -> 57 | V19: 156 | W19: 1890 | X19: 175 | Y19: =IF(COUNT(L19,V19,W19,X19)=4,L19-V19-W19-X19,"") -> -30 | Z19: 4070 | AA19: 170
A20: Amortization of acquisition-related intangibles | C20: 294 | D20: 177 | E20: 200 | F20: 200 | Q20: =IF(COUNT(J20,N20,O20,P20)=4,J20-N20-O20-P20,"") | U20: =IF(COUNT(K20,R20,S20,T20)=4,K20-R20-S20-T20,"") | Y20: =IF(COUNT(L20,V20,W20,X20)=4,L20-V20-W20-X20,"")
A21: Operating expenses | C21: 23317 | D21: 21133 | E21: 20421 | F21: 20105 | G21: 19934 | H21: 24359 | I21: 24532 | J21: 21618 | K21: 29023 | L21: 20589 | N21: 5476 | O21: 5654 | P21: 6026 | Q21: =IF(COUNT(J21,N21,O21,P21)=4,J21-N21-O21-P21,"") -> 4462 | R21: 6286 | S21: 6511 | T21: 11054 | U21: =IF(COUNT(K21,R21,S21,T21)=4,K21-R21-S21-T21,"") -> 5172 | V21: 4973 | W21: 6718 | X21: 4535 | Y21: =IF(COUNT(L21,V21,W21,X21)=4,L21-V21-W21-X21,"") -> 4363 | Z21: 8483 | AA21: 4713
A22: Operating income (loss) | C22: 12874 | D22: 17936 | E22: 23316 | F22: 22035 | G22: 23678 | H22: 19456 | I22: 2334 | J22: 93 | K22: -11678 | L22: -2214 | N22: -1468 | O22: -1016 | P22: -8 | Q22: =IF(COUNT(J22,N22,O22,P22)=4,J22-N22-O22-P22,"") -> 2585 | R22: -1069 | S22: -1964 | T22: -9057 | U22: =IF(COUNT(K22,R22,S22,T22)=4,K22-R22-S22-T22,"") -> 412 | V22: -301 | W22: -3176 | X22: 683 | Y22: =IF(COUNT(L22,V22,W22,X22)=4,L22-V22-W22-X22,"") -> 580 | Z22: -3136 | AA22: 1796
A23: Operating income (loss) YoY | D23: =IF(COUNT(D22,C22)=2,IF(C22>0,D22/C22-1,"n.m."),"") -> 0.39319559 | E23: =IF(COUNT(E22,D22)=2,IF(D22>0,E22/D22-1,"n.m."),"") -> 0.2999554 | F23: =IF(COUNT(F22,E22)=2,IF(E22>0,F22/E22-1,"n.m."),"") -> -0.054940813 | G23: =IF(COUNT(G22,F22)=2,IF(F22>0,G22/F22-1,"n.m."),"") -> 0.074563195 | H23: =IF(COUNT(H22,G22)=2,IF(G22>0,H22/G22-1,"n.m."),"") -> -0.17830898 | I23: =IF(COUNT(I22,H22)=2,IF(H22>0,I22/H22-1,"n.m."),"") -> -0.88003701 | J23: =IF(COUNT(J22,I22)=2,IF(I22>0,J22/I22-1,"n.m."),"") -> -0.96015424 | K23: =IF(COUNT(K22,J22)=2,IF(J22>0,K22/J22-1,"n.m."),"") -> -126.56989 | L23: =IF(COUNT(L22,K22)=2,IF(K22>0,L22/K22-1,"n.m."),"") -> n.m. | R23: =IF(COUNT(R22,N22)=2,IF(N22>0,R22/N22-1,"n.m."),"") -> n.m. | S23: =IF(COUNT(S22,O22)=2,IF(O22>0,S22/O22-1,"n.m."),"") -> n.m. | T23: =IF(COUNT(T22,P22)=2,IF(P22>0,T22/P22-1,"n.m."),"") -> n.m. | U23: =IF(COUNT(U22,Q22)=2,IF(Q22>0,U22/Q22-1,"n.m."),"") -> -0.84061896 | V23: =IF(COUNT(V22,R22)=2,IF(R22>0,V22/R22-1,"n.m."),"") -> n.m. | W23: =IF(COUNT(W22,S22)=2,IF(S22>0,W22/S22-1,"n.m."),"") -> n.m. | X23: =IF(COUNT(X22,T22)=2,IF(T22>0,X22/T22-1,"n.m."),"") -> n.m. | Y23: =IF(COUNT(Y22,U22)=2,IF(U22>0,Y22/U22-1,"n.m."),"") -> 0.40776699 | ... AA23: =IF(COUNT(AA22,W22)=2,IF(W22>0,AA22/W22-1,"n.m."),"") -> n.m.
A24: Operating margin | C24: =IF(COUNT(C22,C9)=2,C22/C9,"") -> 0.21678145 | D24: =IF(COUNT(D22,D9)=2,D22/D9,"") -> 0.28578257 | E24: =IF(COUNT(E22,E9)=2,E22/E9,"") -> 0.32909892 | F24: =IF(COUNT(F22,F9)=2,F22/F9,"") -> 0.30619051 | G24: =IF(COUNT(G22,G9)=2,G22/G9,"") -> 0.3040826 | H24: =IF(COUNT(H22,H9)=2,H22/H9,"") -> 0.24620368 | I24: =IF(COUNT(I22,I9)=2,I22/I9,"") -> 0.037015891 | J24: =IF(COUNT(J22,J9)=2,J22/J9,"") -> 0.0017149812 | ... L24: =IF(COUNT(L22,L9)=2,L22/L9,"") -> -0.04188977 | N24: =IF(COUNT(N22,N9)=2,N22/N9,"") -> -0.12530943 | O24: =IF(COUNT(O22,O9)=2,O22/O9,"") -> -0.078461657 | P24: =IF(COUNT(P22,P9)=2,P22/P9,"") -> -0.00056505156 | Q24: =IF(COUNT(Q22,Q9)=2,Q22/Q9,"") -> 0.16779177 | R24: =IF(COUNT(R22,R9)=2,R22/R9,"") -> -0.084014461 | S24: =IF(COUNT(S22,S9)=2,S22/S9,"") -> -0.15304294 | T24: =IF(COUNT(T22,T9)=2,T22/T9,"") -> -0.68179765 | U24: =IF(COUNT(U22,U9)=2,U22/U9,"") -> 0.028892006 | ... AA24: =IF(COUNT(AA22,AA9)=2,AA22/AA9,"") -> 0.11135913
A26: Non-operating items and net income | B26: Non-operating items and net income | C26: Non-operating items and net income | D26: Non-operating items and net income | E26: Non-operating items and net income | F26: Non-operating items and net income | G26: Non-operating items and net income | H26: Non-operating items and net income | I26: Non-operating items and net income | J26: Non-operating items and net income | K26: Non-operating items and net income | L26: Non-operating items and net income | M26: Non-operating items and net income | N26: Non-operating items and net income | O26: Non-operating items and net income | P26: Non-operating items and net income | Q26: Non-operating items and net income | R26: Non-operating items and net income | S26: Non-operating items and net income | T26: Non-operating items and net income | U26: Non-operating items and net income | V26: Non-operating items and net income | W26: Non-operating items and net income | X26: Non-operating items and net income | Y26: Non-operating items and net income | Z26: Non-operating items and net income | AA26: Non-operating items and net income
A27: Gains (losses) on equity investments, net | C27: 506 | D27: 2651 | E27: -125 | F27: 1539 | G27: 1904 | H27: 2729 | I27: 4268 | J27: 40 | K27: 242 | L27: 514 | N27: 169 | O27: -24 | P27: -191 | Q27: =IF(COUNT(J27,N27,O27,P27)=4,J27-N27-O27-P27,"") -> 86 | R27: 205 | S27: -120 | T27: -159 | U27: =IF(COUNT(K27,R27,S27,T27)=4,K27-R27-S27-T27,"") -> 316 | V27: -112 | W27: 502 | X27: 221 | Y27: =IF(COUNT(L27,V27,W27,X27)=4,L27-V27-W27-X27,"") -> -97 | Z27: -72 | AA27: -39
A28: Interest and other, net | C28: -444 | D28: -235 | E28: 126 | F28: 484 | G28: -504 | H28: -482 | I28: 1166 | J28: 629 | K28: 226 | L28: 3257 | N28: 141 | O28: 224 | P28: 147 | Q28: =IF(COUNT(J28,N28,O28,P28)=4,J28-N28-O28-P28,"") -> 117 | R28: 145 | S28: 80 | T28: 130 | U28: =IF(COUNT(K28,R28,S28,T28)=4,K28-R28-S28-T28,"") -> -129 | V28: -173 | W28: -95 | X28: 3670 | Y28: =IF(COUNT(L28,V28,W28,X28)=4,L28-V28-W28-X28,"") -> -145 | Z28: -738 | AA28: -12576
A29: Income (loss) before taxes | C29: 12936 | D29: 20352 | E29: 23317 | F29: 24058 | G29: 25078 | H29: 21703 | I29: 7768 | J29: 762 | K29: -11210 | L29: 1557 | N29: -1158 | O29: -816 | P29: -52 | Q29: =IF(COUNT(J29,N29,O29,P29)=4,J29-N29-O29-P29,"") -> 2788 | R29: -719 | S29: -2004 | T29: -9086 | U29: =IF(COUNT(K29,R29,S29,T29)=4,K29-R29-S29-T29,"") -> 599 | V29: -586 | W29: -2769 | X29: 4574 | Y29: =IF(COUNT(L29,V29,W29,X29)=4,L29-V29-W29-X29,"") -> 338 | Z29: -3946 | AA29: -10819
A30: Provision for (benefit from) taxes | C30: 2620 | D30: 10751 | E30: 2264 | F30: 3010 | G30: 4179 | H30: 1835 | I30: -249 | J30: -913 | K30: 8023 | L30: 1531 | N30: 1610 | O30: -2289 | P30: -362 | Q30: =IF(COUNT(J30,N30,O30,P30)=4,J30-N30-O30-P30,"") -> 128 | R30: -282 | S30: -350 | T30: 7903 | U30: =IF(COUNT(K30,R30,S30,T30)=4,K30-R30-S30-T30,"") -> 752 | V30: 301 | W30: 255 | X30: 304 | Y30: =IF(COUNT(L30,V30,W30,X30)=4,L30-V30-W30-X30,"") -> 671 | Z30: 335 | AA30: 29
A31: Net income (loss) | C31: 10316 | D31: 9601 | E31: 21053 | F31: 21048 | G31: 20899 | H31: 19868 | I31: 8017 | J31: 1675 | K31: -19233 | L31: 26 | N31: -2768 | O31: 1473 | P31: 310 | Q31: =IF(COUNT(J31,N31,O31,P31)=4,J31-N31-O31-P31,"") -> 2660 | R31: -437 | S31: -1654 | T31: -16989 | U31: =IF(COUNT(K31,R31,S31,T31)=4,K31-R31-S31-T31,"") -> -153 | V31: -887 | W31: -3024 | X31: 4270 | Y31: =IF(COUNT(L31,V31,W31,X31)=4,L31-V31-W31-X31,"") -> -333 | Z31: -4281 | AA31: -10848
A32: Net income (loss) YoY | D32: =IF(COUNT(D31,C31)=2,IF(C31>0,D31/C31-1,"n.m."),"") -> -0.06930981 | E32: =IF(COUNT(E31,D31)=2,IF(D31>0,E31/D31-1,"n.m."),"") -> 1.1927924 | F32: =IF(COUNT(F31,E31)=2,IF(E31>0,F31/E31-1,"n.m."),"") -> -0.00023749584 | G32: =IF(COUNT(G31,F31)=2,IF(F31>0,G31/F31-1,"n.m."),"") -> -0.0070790574 | H32: =IF(COUNT(H31,G31)=2,IF(G31>0,H31/G31-1,"n.m."),"") -> -0.049332504 | I32: =IF(COUNT(I31,H31)=2,IF(H31>0,I31/H31-1,"n.m."),"") -> -0.59648681 | J32: =IF(COUNT(J31,I31)=2,IF(I31>0,J31/I31-1,"n.m."),"") -> -0.79106898 | K32: =IF(COUNT(K31,J31)=2,IF(J31>0,K31/J31-1,"n.m."),"") -> -12.482388 | L32: =IF(COUNT(L31,K31)=2,IF(K31>0,L31/K31-1,"n.m."),"") -> n.m. | R32: =IF(COUNT(R31,N31)=2,IF(N31>0,R31/N31-1,"n.m."),"") -> n.m. | S32: =IF(COUNT(S31,O31)=2,IF(O31>0,S31/O31-1,"n.m."),"") -> -2.1228785 | T32: =IF(COUNT(T31,P31)=2,IF(P31>0,T31/P31-1,"n.m."),"") -> -55.803226 | U32: =IF(COUNT(U31,Q31)=2,IF(Q31>0,U31/Q31-1,"n.m."),"") -> -1.0575188 | V32: =IF(COUNT(V31,R31)=2,IF(R31>0,V31/R31-1,"n.m."),"") -> n.m. | W32: =IF(COUNT(W31,S31)=2,IF(S31>0,W31/S31-1,"n.m."),"") -> n.m. | X32: =IF(COUNT(X31,T31)=2,IF(T31>0,X31/T31-1,"n.m."),"") -> n.m. | Y32: =IF(COUNT(Y31,U31)=2,IF(U31>0,Y31/U31-1,"n.m."),"") -> n.m. | ... AA32: =IF(COUNT(AA31,W31)=2,IF(W31>0,AA31/W31-1,"n.m."),"") -> n.m.
A33: Net margin (net income INCLUDING non-controlling interests / net revenue) | C33: =IF(COUNT(C31,C9)=2,C31/C9,"") -> 0.17370805 | D33: =IF(COUNT(D31,D9)=2,D31/D9,"") -> 0.15297717 | E33: =IF(COUNT(E31,E9)=2,E31/E9,"") -> 0.29715729 | F33: =IF(COUNT(F31,F9)=2,F31/F9,"") -> 0.29247551 | G33: =IF(COUNT(G31,G9)=2,G31/G9,"") -> 0.26839354 | H33: =IF(COUNT(H31,H9)=2,H31/H9,"") -> 0.25141729 | I33: =IF(COUNT(I31,I9)=2,I31/I9,"") -> 0.12714499 | J33: =IF(COUNT(J31,J9)=2,J31/J9,"") -> 0.030888102 | ... L33: =IF(COUNT(L31,L9)=2,L31/L9,"") -> 0.00049193045 | N33: =IF(COUNT(N31,N9)=2,N31/N9,"") -> -0.23627828 | O33: =IF(COUNT(O31,O9)=2,O31/O9,"") -> 0.11375396 | P33: =IF(COUNT(P31,P9)=2,P31/P9,"") -> 0.021895748 | Q33: =IF(COUNT(Q31,Q9)=2,Q31/Q9,"") -> 0.17266 | R33: =IF(COUNT(R31,R9)=2,R31/R9,"") -> -0.034344546 | S33: =IF(COUNT(S31,S9)=2,S31/S9,"") -> -0.12888646 | T33: =IF(COUNT(T31,T9)=2,T31/T9,"") -> -1.278907 | U33: =IF(COUNT(U31,U9)=2,U31/U9,"") -> -0.010729313 | ... AA33: =IF(COUNT(AA31,AA9)=2,AA31/AA9,"") -> -0.67261905
A34: Less: net income (loss) attributable to non-controlling interests | I34: 3 | J34: -14 | K34: -477 | L34: 293 | N34: -10 | O34: -8 | P34: 13 | Q34: =IF(COUNT(J34,N34,O34,P34)=4,J34-N34-O34-P34,"") -> -9 | R34: -56 | S34: -44 | T34: -350 | U34: =IF(COUNT(K34,R34,S34,T34)=4,K34-R34-S34-T34,"") -> -27 | V34: -66 | W34: -106 | X34: 207 | Y34: =IF(COUNT(L34,V34,W34,X34)=4,L34-V34-W34-X34,"") -> 258 | Z34: -553 | AA34: 185
A35: Net income (loss) attributable to Intel | I35: 8014 | J35: 1689 | K35: -18756 | L35: -267 | N35: -2758 | O35: 1481 | P35: 297 | Q35: =IF(COUNT(J35,N35,O35,P35)=4,J35-N35-O35-P35,"") -> 2669 | R35: -381 | S35: -1610 | T35: -16639 | U35: =IF(COUNT(K35,R35,S35,T35)=4,K35-R35-S35-T35,"") -> -126 | V35: -821 | W35: -2918 | X35: 4063 | Y35: =IF(COUNT(L35,V35,W35,X35)=4,L35-V35-W35-X35,"") -> -591 | Z35: -3728 | AA35: -11033
A36: Net income (loss) attributable to Intel YoY | D36: =IF(COUNT(D35,C35)=2,IF(C35>0,D35/C35-1,"n.m."),"") | E36: =IF(COUNT(E35,D35)=2,IF(D35>0,E35/D35-1,"n.m."),"") | F36: =IF(COUNT(F35,E35)=2,IF(E35>0,F35/E35-1,"n.m."),"") | G36: =IF(COUNT(G35,F35)=2,IF(F35>0,G35/F35-1,"n.m."),"") | H36: =IF(COUNT(H35,G35)=2,IF(G35>0,H35/G35-1,"n.m."),"") | I36: =IF(COUNT(I35,H35)=2,IF(H35>0,I35/H35-1,"n.m."),"") | J36: =IF(COUNT(J35,I35)=2,IF(I35>0,J35/I35-1,"n.m."),"") -> -0.78924382 | K36: =IF(COUNT(K35,J35)=2,IF(J35>0,K35/J35-1,"n.m."),"") -> -12.104796 | L36: =IF(COUNT(L35,K35)=2,IF(K35>0,L35/K35-1,"n.m."),"") -> n.m. | R36: =IF(COUNT(R35,N35)=2,IF(N35>0,R35/N35-1,"n.m."),"") -> n.m. | S36: =IF(COUNT(S35,O35)=2,IF(O35>0,S35/O35-1,"n.m."),"") -> -2.0871033 | T36: =IF(COUNT(T35,P35)=2,IF(P35>0,T35/P35-1,"n.m."),"") -> -57.023569 | U36: =IF(COUNT(U35,Q35)=2,IF(Q35>0,U35/Q35-1,"n.m."),"") -> -1.0472087 | V36: =IF(COUNT(V35,R35)=2,IF(R35>0,V35/R35-1,"n.m."),"") -> n.m. | W36: =IF(COUNT(W35,S35)=2,IF(S35>0,W35/S35-1,"n.m."),"") -> n.m. | X36: =IF(COUNT(X35,T35)=2,IF(T35>0,X35/T35-1,"n.m."),"") -> n.m. | Y36: =IF(COUNT(Y35,U35)=2,IF(U35>0,Y35/U35-1,"n.m."),"") -> n.m. | ... AA36: =IF(COUNT(AA35,W35)=2,IF(W35>0,AA35/W35-1,"n.m."),"") -> n.m.
A38: Earnings per share and weighted-average shares | B38: Earnings per share and weighted-average shares | C38: Earnings per share and weighted-average shares | D38: Earnings per share and weighted-average shares | E38: Earnings per share and weighted-average shares | F38: Earnings per share and weighted-average shares | G38: Earnings per share and weighted-average shares | H38: Earnings per share and weighted-average shares | I38: Earnings per share and weighted-average shares | J38: Earnings per share and weighted-average shares | K38: Earnings per share and weighted-average shares | L38: Earnings per share and weighted-average shares | M38: Earnings per share and weighted-average shares | N38: Earnings per share and weighted-average shares | O38: Earnings per share and weighted-average shares | P38: Earnings per share and weighted-average shares | Q38: Earnings per share and weighted-average shares | R38: Earnings per share and weighted-average shares | S38: Earnings per share and weighted-average shares | T38: Earnings per share and weighted-average shares | U38: Earnings per share and weighted-average shares | V38: Earnings per share and weighted-average shares | W38: Earnings per share and weighted-average shares | X38: Earnings per share and weighted-average shares | Y38: Earnings per share and weighted-average shares | Z38: Earnings per share and weighted-average shares | AA38: Earnings per share and weighted-average shares
A39: Quarterly EPS and weighted-average shares are not calculated by subtracting annual and YTD figures. | B39: Quarterly EPS and weighted-average shares are not calculated by subtracting annual and YTD figures. | C39: Quarterly EPS and weighted-average shares are not calculated by subtracting annual and YTD figures. | D39: Quarterly EPS and weighted-average shares are not calculated by subtracting annual and YTD figures. | E39: Quarterly EPS and weighted-average shares are not calculated by subtracting annual and YTD figures. | F39: Quarterly EPS and weighted-average shares are not calculated by subtracting annual and YTD figures. | G39: Quarterly EPS and weighted-average shares are not calculated by subtracting annual and YTD figures. | H39: Quarterly EPS and weighted-average shares are not calculated by subtracting annual and YTD figures. | I39: Quarterly EPS and weighted-average shares are not calculated by subtracting annual and YTD figures. | J39: Quarterly EPS and weighted-average shares are not calculated by subtracting annual and YTD figures. | K39: Quarterly EPS and weighted-average shares are not calculated by subtracting annual and YTD figures. | L39: Quarterly EPS and weighted-average shares are not calculated by subtracting annual and YTD figures. | M39: Quarterly EPS and weighted-average shares are not calculated by subtracting annual and YTD figures. | N39: Quarterly EPS and weighted-average shares are not calculated by subtracting annual and YTD figures. | O39: Quarterly EPS and weighted-average shares are not calculated by subtracting annual and YTD figures. | P39: Quarterly EPS and weighted-average shares are not calculated by subtracting annual and YTD figures. | Q39: Quarterly EPS and weighted-average shares are not calculated by subtracting annual and YTD figures. | R39: Quarterly EPS and weighted-average shares are not calculated by subtracting annual and YTD figures. | S39: Quarterly EPS and weighted-average shares are not calculated by subtracting annual and YTD figures. | T39: Quarterly EPS and weighted-average shares are not calculated by subtracting annual and YTD figures. | U39: Quarterly EPS and weighted-average shares are not calculated by subtracting annual and YTD figures. | V39: Quarterly EPS and weighted-average shares are not calculated by subtracting annual and YTD figures. | W39: Quarterly EPS and weighted-average shares are not calculated by subtracting annual and YTD figures. | X39: Quarterly EPS and weighted-average shares are not calculated by subtracting annual and YTD figures. | Y39: Quarterly EPS and weighted-average shares are not calculated by subtracting annual and YTD figures. | Z39: Quarterly EPS and weighted-average shares are not calculated by subtracting annual and YTD figures. | AA39: Quarterly EPS and weighted-average shares are not calculated by subtracting annual and YTD figures.
A40: Earnings (loss) per share - basic | C40: 2.18 | D40: 2.04 | E40: 4.57 | F40: 4.77 | G40: 4.98 | H40: 4.89 | I40: 1.95 | J40: 0.4 | K40: -4.38 | L40: -0.06 | N40: -0.66 | O40: 0.35 | P40: 0.07 | R40: -0.09 | S40: -0.38 | T40: -3.88 | V40: -0.19 | W40: -0.67 | X40: 0.9 | Z40: -0.73 | AA40: -2.16
A41: Earnings (loss) per share - diluted | C41: 2.12 | D41: 1.99 | E41: 4.48 | F41: 4.71 | G41: 4.94 | H41: 4.86 | I41: 1.94 | J41: 0.4 | K41: -4.38 | L41: -0.06 | N41: -0.66 | O41: 0.35 | P41: 0.07 | R41: -0.09 | S41: -0.38 | T41: -3.88 | V41: -0.19 | W41: -0.67 | X41: 0.9 | Z41: -0.73 | AA41: -2.16
A42: Weighted average shares - basic | C42: 4730 | D42: 4701 | E42: 4611 | F42: 4417 | G42: 4199 | H42: 4059 | I42: 4108 | J42: 4190 | K42: 4280 | L42: 4530 | N42: 4154 | O42: 4182 | P42: 4202 | R42: 4242 | S42: 4267 | T42: 4292 | V42: 4343 | W42: 4369 | X42: 4514 | Z42: 5083 | AA42: 5104
A43: Weighted average shares - diluted | C43: 4875 | D43: 4835 | E43: 4701 | F43: 4473 | G43: 4232 | H43: 4090 | I43: 4123 | J43: 4212 | K43: 4280 | L43: 4530 | N43: 4154 | O43: 4196 | P43: 4229 | R43: 4242 | S43: 4267 | T43: 4292 | V43: 4343 | W43: 4369 | X43: 4531 | Z43: 5083 | AA43: 5104
A45: Income-statement reconciliations | B45: Income-statement reconciliations | C45: Income-statement reconciliations | D45: Income-statement reconciliations | E45: Income-statement reconciliations | F45: Income-statement reconciliations | G45: Income-statement reconciliations | H45: Income-statement reconciliations | I45: Income-statement reconciliations | J45: Income-statement reconciliations | K45: Income-statement reconciliations | L45: Income-statement reconciliations | M45: Income-statement reconciliations | N45: Income-statement reconciliations | O45: Income-statement reconciliations | P45: Income-statement reconciliations | Q45: Income-statement reconciliations | R45: Income-statement reconciliations | S45: Income-statement reconciliations | T45: Income-statement reconciliations | U45: Income-statement reconciliations | V45: Income-statement reconciliations | W45: Income-statement reconciliations | X45: Income-statement reconciliations | Y45: Income-statement reconciliations | Z45: Income-statement reconciliations | AA45: Income-statement reconciliations
A46: Check: net revenue - cost of sales - gross profit (should be 0) | C46: =IF(COUNT(C9,C11,C12)=3,C9-C11-C12,"") -> 0 | D46: =IF(COUNT(D9,D11,D12)=3,D9-D11-D12,"") -> 0 | E46: =IF(COUNT(E9,E11,E12)=3,E9-E11-E12,"") -> 0 | F46: =IF(COUNT(F9,F11,F12)=3,F9-F11-F12,"") -> 0 | G46: =IF(COUNT(G9,G11,G12)=3,G9-G11-G12,"") -> 0 | H46: =IF(COUNT(H9,H11,H12)=3,H9-H11-H12,"") -> 0 | I46: =IF(COUNT(I9,I11,I12)=3,I9-I11-I12,"") -> 0 | J46: =IF(COUNT(J9,J11,J12)=3,J9-J11-J12,"") -> 0 | ... L46: =IF(COUNT(L9,L11,L12)=3,L9-L11-L12,"") -> 0 | N46: =IF(COUNT(N9,N11,N12)=3,N9-N11-N12,"") -> 0 | O46: =IF(COUNT(O9,O11,O12)=3,O9-O11-O12,"") -> 0 | P46: =IF(COUNT(P9,P11,P12)=3,P9-P11-P12,"") -> 0 | Q46: =IF(COUNT(Q9,Q11,Q12)=3,Q9-Q11-Q12,"") -> 0 | R46: =IF(COUNT(R9,R11,R12)=3,R9-R11-R12,"") -> 0 | S46: =IF(COUNT(S9,S11,S12)=3,S9-S11-S12,"") -> 0 | T46: =IF(COUNT(T9,T11,T12)=3,T9-T11-T12,"") -> 0 | U46: =IF(COUNT(U9,U11,U12)=3,U9-U11-U12,"") -> 0 | ... AA46: =IF(COUNT(AA9,AA11,AA12)=3,AA9-AA11-AA12,"") -> 0
A47: Check: R&D + MG&A + amortization + restructuring - operating expenses (should be 0) | C47: =IF(COUNT(C17,C18,C20,C19,C21)=5,C17+C18+C20+C19-C21,"") -> 0 | D47: =IF(COUNT(D17,D18,D20,D19,D21)=5,D17+D18+D20+D19-D21,"") -> 0 | E47: =IF(COUNT(E17,E18,E20,E19,E21)=5,E17+E18+E20+E19-E21,"") -> 0 | F47: =IF(COUNT(F17,F18,F20,F19,F21)=5,F17+F18+F20+F19-F21,"") -> 0 | G47: =IF(COUNT(G17,G18,G19,G21)=4,G17+G18+0+G19-G21,"") -> 0 | H47: =IF(COUNT(H17,H18,H19,H21)=4,H17+H18+0+H19-H21,"") -> 0 | I47: =IF(COUNT(I17,I18,I19,I21)=4,I17+I18+0+I19-I21,"") -> 0 | J47: =IF(COUNT(J17,J18,J19,J21)=4,J17+J18+0+J19-J21,"") -> 0 | K47: =IF(COUNT(K17,K18,K19,K21)=4,K17+K18+0+K19-K21,"") -> 0 | L47: =IF(COUNT(L17,L18,L19,L21)=4,L17+L18+0+L19-L21,"") -> 0 | N47: =IF(COUNT(N17,N18,N19,N21)=4,N17+N18+0+N19-N21,"") -> 0 | O47: =IF(COUNT(O17,O18,O19,O21)=4,O17+O18+0+O19-O21,"") -> 0 | P47: =IF(COUNT(P17,P18,P19,P21)=4,P17+P18+0+P19-P21,"") -> 0 | Q47: =IF(COUNT(Q17,Q18,Q19,Q21)=4,Q17+Q18+0+Q19-Q21,"") -> 0 | R47: =IF(COUNT(R17,R18,R19,R21)=4,R17+R18+0+R19-R21,"") -> 0 | S47: =IF(COUNT(S17,S18,S19,S21)=4,S17+S18+0+S19-S21,"") -> 0 | T47: =IF(COUNT(T17,T18,T19,T21)=4,T17+T18+0+T19-T21,"") -> 0 | U47: =IF(COUNT(U17,U18,U19,U21)=4,U17+U18+0+U19-U21,"") -> 0 | ... AA47: =IF(COUNT(AA17,AA18,AA19,AA21)=4,AA17+AA18+0+AA19-AA21,"") -> 0
A48: Check: gross profit - operating expenses - operating income (should be 0) | C48: =IF(COUNT(C12,C21,C22)=3,C12-C21-C22,"") -> 0 | D48: =IF(COUNT(D12,D21,D22)=3,D12-D21-D22,"") -> 0 | E48: =IF(COUNT(E12,E21,E22)=3,E12-E21-E22,"") -> 0 | F48: =IF(COUNT(F12,F21,F22)=3,F12-F21-F22,"") -> 0 | G48: =IF(COUNT(G12,G21,G22)=3,G12-G21-G22,"") -> 0 | H48: =IF(COUNT(H12,H21,H22)=3,H12-H21-H22,"") -> 0 | I48: =IF(COUNT(I12,I21,I22)=3,I12-I21-I22,"") -> 0 | J48: =IF(COUNT(J12,J21,J22)=3,J12-J21-J22,"") -> 0 | ... L48: =IF(COUNT(L12,L21,L22)=3,L12-L21-L22,"") -> 0 | N48: =IF(COUNT(N12,N21,N22)=3,N12-N21-N22,"") -> 0 | O48: =IF(COUNT(O12,O21,O22)=3,O12-O21-O22,"") -> 0 | P48: =IF(COUNT(P12,P21,P22)=3,P12-P21-P22,"") -> 0 | Q48: =IF(COUNT(Q12,Q21,Q22)=3,Q12-Q21-Q22,"") -> 0 | R48: =IF(COUNT(R12,R21,R22)=3,R12-R21-R22,"") -> 0 | S48: =IF(COUNT(S12,S21,S22)=3,S12-S21-S22,"") -> 0 | T48: =IF(COUNT(T12,T21,T22)=3,T12-T21-T22,"") -> 0 | U48: =IF(COUNT(U12,U21,U22)=3,U12-U21-U22,"") -> 0 | ... AA48: =IF(COUNT(AA12,AA21,AA22)=3,AA12-AA21-AA22,"") -> 0
A49: Check: operating income + equity gains + interest and other - pretax income (should be 0) | C49: =IF(COUNT(C22,C27,C28,C29)=4,C22+C27+C28-C29,"") -> 0 | D49: =IF(COUNT(D22,D27,D28,D29)=4,D22+D27+D28-D29,"") -> 0 | E49: =IF(COUNT(E22,E27,E28,E29)=4,E22+E27+E28-E29,"") -> 0 | F49: =IF(COUNT(F22,F27,F28,F29)=4,F22+F27+F28-F29,"") -> 0 | G49: =IF(COUNT(G22,G27,G28,G29)=4,G22+G27+G28-G29,"") -> 0 | H49: =IF(COUNT(H22,H27,H28,H29)=4,H22+H27+H28-H29,"") -> 0 | I49: =IF(COUNT(I22,I27,I28,I29)=4,I22+I27+I28-I29,"") -> 0 | J49: =IF(COUNT(J22,J27,J28,J29)=4,J22+J27+J28-J29,"") -> 0 | ... L49: =IF(COUNT(L22,L27,L28,L29)=4,L22+L27+L28-L29,"") -> 0 | N49: =IF(COUNT(N22,N27,N28,N29)=4,N22+N27+N28-N29,"") -> 0 | O49: =IF(COUNT(O22,O27,O28,O29)=4,O22+O27+O28-O29,"") -> 0 | P49: =IF(COUNT(P22,P27,P28,P29)=4,P22+P27+P28-P29,"") -> 0 | Q49: =IF(COUNT(Q22,Q27,Q28,Q29)=4,Q22+Q27+Q28-Q29,"") -> 0 | R49: =IF(COUNT(R22,R27,R28,R29)=4,R22+R27+R28-R29,"") -> 0 | S49: =IF(COUNT(S22,S27,S28,S29)=4,S22+S27+S28-S29,"") -> 0 | T49: =IF(COUNT(T22,T27,T28,T29)=4,T22+T27+T28-T29,"") -> 0 | U49: =IF(COUNT(U22,U27,U28,U29)=4,U22+U27+U28-U29,"") -> 0 | ... AA49: =IF(COUNT(AA22,AA27,AA28,AA29)=4,AA22+AA27+AA28-AA29,"") -> 0
A50: Check: pretax income - taxes - net income (should be 0) | C50: =IF(COUNT(C29,C30,C31)=3,C29-C30-C31,"") -> 0 | D50: =IF(COUNT(D29,D30,D31)=3,D29-D30-D31,"") -> 0 | E50: =IF(COUNT(E29,E30,E31)=3,E29-E30-E31,"") -> 0 | F50: =IF(COUNT(F29,F30,F31)=3,F29-F30-F31,"") -> 0 | G50: =IF(COUNT(G29,G30,G31)=3,G29-G30-G31,"") -> 0 | H50: =IF(COUNT(H29,H30,H31)=3,H29-H30-H31,"") -> 0 | I50: =IF(COUNT(I29,I30,I31)=3,I29-I30-I31,"") -> 0 | J50: =IF(COUNT(J29,J30,J31)=3,J29-J30-J31,"") -> 0 | ... L50: =IF(COUNT(L29,L30,L31)=3,L29-L30-L31,"") -> 0 | N50: =IF(COUNT(N29,N30,N31)=3,N29-N30-N31,"") -> 0 | O50: =IF(COUNT(O29,O30,O31)=3,O29-O30-O31,"") -> 0 | P50: =IF(COUNT(P29,P30,P31)=3,P29-P30-P31,"") -> 0 | Q50: =IF(COUNT(Q29,Q30,Q31)=3,Q29-Q30-Q31,"") -> 0 | R50: =IF(COUNT(R29,R30,R31)=3,R29-R30-R31,"") -> 0 | S50: =IF(COUNT(S29,S30,S31)=3,S29-S30-S31,"") -> 0 | T50: =IF(COUNT(T29,T30,T31)=3,T29-T30-T31,"") -> 0 | U50: =IF(COUNT(U29,U30,U31)=3,U29-U30-U31,"") -> 0 | ... AA50: =IF(COUNT(AA29,AA30,AA31)=3,AA29-AA30-AA31,"") -> 0
A51: Check: net income - NCI - net income attributable to Intel (should be 0) | I51: =IF(COUNT(I31,I34,I35)=3,I31-I34-I35,"") -> 0 | J51: =IF(COUNT(J31,J34,J35)=3,J31-J34-J35,"") -> 0 | K51: =IF(COUNT(K31,K34,K35)=3,K31-K34-K35,"") -> 0 | L51: =IF(COUNT(L31,L34,L35)=3,L31-L34-L35,"") -> 0 | N51: =IF(COUNT(N31,N34,N35)=3,N31-N34-N35,"") -> 0 | O51: =IF(COUNT(O31,O34,O35)=3,O31-O34-O35,"") -> 0 | P51: =IF(COUNT(P31,P34,P35)=3,P31-P34-P35,"") -> 0 | Q51: =IF(COUNT(Q31,Q34,Q35)=3,Q31-Q34-Q35,"") -> 0 | R51: =IF(COUNT(R31,R34,R35)=3,R31-R34-R35,"") -> 0 | S51: =IF(COUNT(S31,S34,S35)=3,S31-S34-S35,"") -> 0 | T51: =IF(COUNT(T31,T34,T35)=3,T31-T34-T35,"") -> 0 | U51: =IF(COUNT(U31,U34,U35)=3,U31-U34-U35,"") -> 0 | ... AA51: =IF(COUNT(AA31,AA34,AA35)=3,AA31-AA34-AA35,"") -> 0

Sheet Balance Sheet
A1: Intel Corporation — Balance Sheet | B1: Intel Corporation — Balance Sheet | C1: Intel Corporation — Balance Sheet | D1: Intel Corporation — Balance Sheet | E1: Intel Corporation — Balance Sheet | F1: Intel Corporation — Balance Sheet | G1: Intel Corporation — Balance Sheet | H1: Intel Corporation — Balance Sheet | I1: Intel Corporation — Balance Sheet | J1: Intel Corporation — Balance Sheet | K1: Intel Corporation — Balance Sheet | L1: Intel Corporation — Balance Sheet | M1: Intel Corporation — Balance Sheet | N1: Intel Corporation — Balance Sheet | O1: Intel Corporation — Balance Sheet | P1: Intel Corporation — Balance Sheet | Q1: Intel Corporation — Balance Sheet | R1: Intel Corporation — Balance Sheet | S1: Intel Corporation — Balance Sheet | T1: Intel Corporation — Balance Sheet | U1: Intel Corporation — Balance Sheet | V1: Intel Corporation — Balance Sheet | W1: Intel Corporation — Balance Sheet | X1: Intel Corporation — Balance Sheet | Y1: Intel Corporation — Balance Sheet | Z1: Intel Corporation — Balance Sheet | AA1: Intel Corporation — Balance Sheet
A2: USD million unless stated otherwise; annual FY2016–FY2025; latest interim 27 June 2026.
A3: Metric | C3: FY2016 | D3: FY2017 | E3: FY2018 | F3: FY2019 | G3: FY2020 | H3: FY2021 | I3: FY2022 | J3: FY2023 | K3: FY2024 | L3: FY2025 | N3: 1Q2023 | O3: 2Q2023 | P3: 3Q2023 | Q3: 4Q2023 | R3: 1Q2024 | S3: 2Q2024 | T3: 3Q2024 | U3: 4Q2024 | V3: 1Q2025 | W3: 2Q2025 | X3: 3Q2025 | Y3: 4Q2025 | Z3: 1Q2026 | AA3: 2Q2026
C4: 2016-12-31T00:00:00.000Z | D4: 2017-12-30T00:00:00.000Z | E4: 2018-12-29T00:00:00.000Z | F4: 2019-12-28T00:00:00.000Z | G4: 2020-12-26T00:00:00.000Z | H4: 2021-12-25T00:00:00.000Z | I4: 2022-12-31T00:00:00.000Z | J4: 2023-12-30T00:00:00.000Z | K4: 2024-12-28T00:00:00.000Z | L4: 2025-12-27T00:00:00.000Z | N4: 2023-04-01T00:00:00.000Z | O4: 2023-07-01T00:00:00.000Z | P4: 2023-09-30T00:00:00.000Z | Q4: 2023-12-30T00:00:00.000Z | R4: 2024-03-30T00:00:00.000Z | S4: 2024-06-29T00:00:00.000Z | T4: 2024-09-28T00:00:00.000Z | U4: 2024-12-28T00:00:00.000Z | V4: 2025-03-29T00:00:00.000Z | W4: 2025-06-28T00:00:00.000Z | X4: 2025-09-27T00:00:00.000Z | Y4: 2025-12-27T00:00:00.000Z | Z4: 2026-03-28T00:00:00.000Z | AA4: 2026-06-27T00:00:00.000Z
A5: Annual / discrete-quarter / instant as identified | C5: Annual | D5: Annual | E5: Annual | F5: Annual | G5: Annual | H5: Annual | I5: Annual | J5: Annual | K5: Annual | L5: Annual | N5: Instant | O5: Instant | P5: Instant | Q5: Instant | R5: Instant | S5: Instant | T5: Instant | U5: Instant | V5: Instant | W5: Instant | X5: Instant | Y5: Instant | Z5: Instant | AA5: Instant
A7: Current assets | B7: Current assets | C7: Current assets | D7: Current assets | E7: Current assets | F7: Current assets | G7: Current assets | H7: Current assets | I7: Current assets | J7: Current assets | K7: Current assets | L7: Current assets | M7: Current assets | N7: Current assets | O7: Current assets | P7: Current assets | Q7: Current assets | R7: Current assets | S7: Current assets | T7: Current assets | U7: Current assets | V7: Current assets | W7: Current assets | X7: Current assets | Y7: Current assets | Z7: Current assets | AA7: Current assets
A8: Cash and cash equivalents | C8: 5560 | D8: 3433 | E8: 3019 | F8: 4194 | G8: 5865 | H8: 4827 | I8: 11144 | J8: 7079 | K8: 8249 | L8: 14265 | P8: 7621 | Q8: =IF(COUNT(J8)=1,J8,"") -> 7079 | R8: 6923 | S8: 11287 | T8: 8785 | U8: =IF(COUNT(K8)=1,K8,"") -> 8249 | V8: 8947 | W8: 9643 | X8: 11141 | Y8: =IF(COUNT(L8)=1,L8,"") -> 14265 | Z8: 17247 | AA8: 12874
A9: Short-term investments | C9: 3225 | D9: 1814 | E9: 2788 | F9: 1082 | G9: 2292 | H9: 2103 | I9: 17194 | J9: 17955 | K9: 13813 | L9: 23151 | P9: 17409 | Q9: =IF(COUNT(J9)=1,J9,"") -> 17955 | R9: 14388 | S9: 17986 | T9: 15301 | U9: =IF(COUNT(K9)=1,K9,"") -> 13813 | V9: 12101 | W9: 11563 | X9: 19794 | Y9: =IF(COUNT(L9)=1,L9,"") -> 23151 | Z9: 15542 | AA9: 16853
A10: Trading assets | C10: 8314 | D10: 8755 | E10: 5843 | F10: 7847 | G10: 15738 | H10: 21483 | Q10: =IF(COUNT(J10)=1,J10,"") | U10: =IF(COUNT(K10)=1,K10,"") | Y10: =IF(COUNT(L10)=1,L10,"")
A11: Accounts receivable, net | C11: 4690 | D11: 5607 | E11: 6722 | F11: 7659 | G11: 6782 | H11: 9457 | I11: 4133 | J11: 3402 | K11: 3478 | L11: 3839 | P11: 2843 | Q11: =IF(COUNT(J11)=1,J11,"") -> 3402 | R11: 3323 | S11: 3131 | T11: 3121 | U11: =IF(COUNT(K11)=1,K11,"") -> 3478 | V11: 3064 | W11: 2360 | X11: 3202 | Y11: =IF(COUNT(L11)=1,L11,"") -> 3839 | Z11: 4066 | AA11: 4033
A12: Inventories | C12: 5553 | D12: 6983 | E12: 7253 | F12: 8744 | G12: 8427 | H12: 10776 | I12: 13224 | J12: 11127 | K12: 12198 | L12: 11618 | P12: 11466 | Q12: =IF(COUNT(J12)=1,J12,"") -> 11127 | R12: 11494 | S12: 11244 | T12: 12062 | U12: =IF(COUNT(K12)=1,K12,"") -> 12198 | V12: 12281 | W12: 11377 | X12: 11489 | Y12: =IF(COUNT(L12)=1,L12,"") -> 11618 | Z12: 12426 | AA12: 12492
A13: Assets held for sale | C13: 5210 | D13: 0 | G13: 5400 | H13: 6942 | I13: 45 | Q13: =IF(COUNT(J13)=1,J13,"") | U13: =IF(COUNT(K13)=1,K13,"") | Y13: =IF(COUNT(L13)=1,L13,"")
A14: Other current assets | C14: 2956 | D14: 2908 | E14: 3162 | F14: 1713 | G14: 2745 | H14: 2130 | I14: 4667 | J14: 3706 | K14: 9586 | L14: 10815 | P14: 4472 | Q14: =IF(COUNT(J14)=1,J14,"") -> 3706 | R14: 6480 | S14: 7181 | T14: 6868 | U14: =IF(COUNT(K14)=1,K14,"") -> 9586 | V14: 5741 | W14: 8432 | X14: 6105 | Y14: =IF(COUNT(L14)=1,L14,"") -> 10815 | Z14: 12876 | AA14: 10961
A15: Total current assets | C15: 35508 | D15: 29500 | E15: 28787 | F15: 31239 | G15: 47249 | H15: 57718 | I15: 50407 | J15: 43269 | K15: 47324 | L15: 63688 | P15: 43811 | Q15: =IF(COUNT(J15)=1,J15,"") -> 43269 | R15: 42608 | S15: 50829 | T15: 46137 | U15: =IF(COUNT(K15)=1,K15,"") -> 47324 | V15: 42134 | W15: 43375 | X15: 51731 | Y15: =IF(COUNT(L15)=1,L15,"") -> 63688 | Z15: 62157 | AA15: 57213
A17: Non-current assets | B17: Non-current assets | C17: Non-current assets | D17: Non-current assets | E17: Non-current assets | F17: Non-current assets | G17: Non-current assets | H17: Non-current assets | I17: Non-current assets | J17: Non-current assets | K17: Non-current assets | L17: Non-current assets | M17: Non-current assets | N17: Non-current assets | O17: Non-current assets | P17: Non-current assets | Q17: Non-current assets | R17: Non-current assets | S17: Non-current assets | T17: Non-current assets | U17: Non-current assets | V17: Non-current assets | W17: Non-current assets | X17: Non-current assets | Y17: Non-current assets | Z17: Non-current assets | AA17: Non-current assets
A18: Property, plant and equipment, net | C18: 36171 | D18: 41109 | E18: 48976 | F18: 55386 | G18: 56584 | H18: 63245 | I18: 80860 | J18: 96647 | K18: 107919 | L18: 105414 | P18: 93352 | Q18: =IF(COUNT(J18)=1,J18,"") -> 96647 | R18: 99924 | S18: 103398 | T18: 104248 | U18: =IF(COUNT(K18)=1,K18,"") -> 107919 | V18: 109763 | W18: 109510 | X18: 105047 | Y18: =IF(COUNT(L18)=1,L18,"") -> 105414 | Z18: 104458 | AA18: 105741
A19: Marketable equity securities | C19: 6180 | D19: 4192 | Q19: =IF(COUNT(J19)=1,J19,"") | U19: =IF(COUNT(K19)=1,K19,"") | Y19: =IF(COUNT(L19)=1,L19,"")
A20: Equity investments | E20: 6042 | F20: 3967 | G20: 5152 | H20: 6298 | I20: 5912 | J20: 5829 | K20: 5383 | L20: 8512 | P20: 5700 | Q20: =IF(COUNT(J20)=1,J20,"") -> 5829 | R20: 6139 | S20: 5824 | T20: 5496 | U20: =IF(COUNT(K20)=1,K20,"") -> 5383 | V20: 5027 | W20: 5383 | X20: 8667 | Y20: =IF(COUNT(L20)=1,L20,"") -> 8512 | Z20: 8481 | AA20: 8410
A21: Other long-term investments | C21: 4716 | D21: 3712 | E21: 3388 | F21: 3276 | G21: 2192 | H21: 840 | Q21: =IF(COUNT(J21)=1,J21,"") | U21: =IF(COUNT(K21)=1,K21,"") | Y21: =IF(COUNT(L21)=1,L21,"")
A22: Goodwill | C22: 14099 | D22: 24389 | E22: 24513 | F22: 26276 | G22: 26971 | H22: 26963 | I22: 27591 | J22: 27591 | K22: 24693 | L22: 23912 | P22: 27591 | Q22: =IF(COUNT(J22)=1,J22,"") -> 27591 | R22: 27440 | S22: 27442 | T22: 24680 | U22: =IF(COUNT(K22)=1,K22,"") -> 24693 | V22: 24693 | W22: 23912 | X22: 23912 | Y22: =IF(COUNT(L22)=1,L22,"") -> 23912 | Z22: 20465 | AA22: 20465
A23: Identified intangible assets, net | C23: 9494 | D23: 12745 | E23: 11836 | F23: 10827 | G23: 9026 | H23: 7270 | I23: 6018 | J23: 4589 | K23: 3691 | L23: 2772 | P23: 4970 | Q23: =IF(COUNT(J23)=1,J23,"") -> 4589 | R23: 4675 | S23: 4383 | T23: 3975 | U23: =IF(COUNT(K23)=1,K23,"") -> 3691 | V23: 3568 | W23: 3057 | X23: 2877 | Y23: =IF(COUNT(L23)=1,L23,"") -> 2772 | Z23: 2722 | AA23: 2545
A24: Other long-term assets | C24: 7159 | D24: 7602 | E24: 4421 | F24: 5553 | G24: 5917 | H24: 6072 | I24: 11315 | J24: 13647 | K24: 7475 | L24: 7131 | P24: 13413 | Q24: =IF(COUNT(J24)=1,J24,"") -> 13647 | R24: 11947 | S24: 14329 | T24: 9006 | U24: =IF(COUNT(K24)=1,K24,"") -> 7475 | V24: 7057 | W24: 7283 | X24: 12280 | Y24: =IF(COUNT(L24)=1,L24,"") -> 7131 | Z24: 7049 | AA24: 8065
A25: Total assets | C25: 113327 | D25: 123249 | E25: 127963 | F25: 136524 | G25: 153091 | H25: 168406 | I25: 182103 | J25: 191572 | K25: 196485 | L25: 211429 | P25: 188837 | Q25: =IF(COUNT(J25)=1,J25,"") -> 191572 | R25: 192733 | S25: 206205 | T25: 193542 | U25: =IF(COUNT(K25)=1,K25,"") -> 196485 | V25: 192242 | W25: 192520 | X25: 204514 | Y25: =IF(COUNT(L25)=1,L25,"") -> 211429 | Z25: 205332 | AA25: 202439
A27: Liabilities and temporary equity | B27: Liabilities and temporary equity | C27: Liabilities and temporary equity | D27: Liabilities and temporary equity | E27: Liabilities and temporary equity | F27: Liabilities and temporary equity | G27: Liabilities and temporary equity | H27: Liabilities and temporary equity | I27: Liabilities and temporary equity | J27: Liabilities and temporary equity | K27: Liabilities and temporary equity | L27: Liabilities and temporary equity | M27: Liabilities and temporary equity | N27: Liabilities and temporary equity | O27: Liabilities and temporary equity | P27: Liabilities and temporary equity | Q27: Liabilities and temporary equity | R27: Liabilities and temporary equity | S27: Liabilities and temporary equity | T27: Liabilities and temporary equity | U27: Liabilities and temporary equity | V27: Liabilities and temporary equity | W27: Liabilities and temporary equity | X27: Liabilities and temporary equity | Y27: Liabilities and temporary equity | Z27: Liabilities and temporary equity | AA27: Liabilities and temporary equity
A28: Accounts payable | C28: 2475 | D28: 2928 | E28: 3824 | F28: 4128 | G28: 5581 | H28: 5747 | I28: 9595 | J28: 8578 | K28: 12556 | L28: 9882 | P28: 8669 | Q28: =IF(COUNT(J28)=1,J28,"") -> 8578 | R28: 8559 | S28: 9618 | T28: 11074 | U28: =IF(COUNT(K28)=1,K28,"") -> 12556 | V28: 10896 | W28: 10666 | X28: 10268 | Y28: =IF(COUNT(L28)=1,L28,"") -> 9882 | Z28: 7159 | AA28: 8756
A29: Accrued compensation and benefits | C29: 3465 | D29: 3526 | E29: 3622 | F29: 3853 | G29: 3999 | H29: 4535 | I29: 4084 | J29: 3655 | K29: 3343 | L29: 3990 | P29: 3115 | Q29: =IF(COUNT(J29)=1,J29,"") -> 3655 | R29: 2506 | S29: 2651 | T29: 5015 | U29: =IF(COUNT(K29)=1,K29,"") -> 3343 | V29: 2652 | W29: 4249 | X29: 3756 | Y29: =IF(COUNT(L29)=1,L29,"") -> 3990 | Z29: 2824 | AA29: 3748
A30: Accrued advertising | C30: 810 | Q30: =IF(COUNT(J30)=1,J30,"") | U30: =IF(COUNT(K30)=1,K30,"") | Y30: =IF(COUNT(L30)=1,L30,"")
A31: Deferred income | C31: 1718 | D31: 1656 | E31: 0 | Q31: =IF(COUNT(J31)=1,J31,"") | U31: =IF(COUNT(K31)=1,K31,"") | Y31: =IF(COUNT(L31)=1,L31,"")
A32: Liabilities held for sale | C32: 1920 | D32: 0 | Q32: =IF(COUNT(J32)=1,J32,"") | U32: =IF(COUNT(K32)=1,K32,"") | Y32: =IF(COUNT(L32)=1,L32,"")
A33: Short-term debt | C33: 4634 | D33: 1776 | E33: 1261 | F33: 3693 | G33: 2504 | H33: 4591 | I33: 4367 | J33: 2288 | K33: 3729 | L33: 2499 | P33: 2288 | Q33: =IF(COUNT(J33)=1,J33,"") -> 2288 | R33: 4581 | S33: 4695 | T33: 3765 | U33: =IF(COUNT(K33)=1,K33,"") -> 3729 | V33: 5240 | W33: 6731 | X33: 2496 | Y33: =IF(COUNT(L33)=1,L33,"") -> 2499 | Z33: 2004 | AA33: 1988
A34: Income taxes payable (current) | I34: 2251 | J34: 1107 | K34: 1756 | L34: 604 | P34: 2112 | Q34: =IF(COUNT(J34)=1,J34,"") -> 1107 | R34: 346 | S34: 1856 | T34: 2440 | U34: =IF(COUNT(K34)=1,K34,"") -> 1756 | V34: 1873 | W34: 887 | X34: 825 | Y34: =IF(COUNT(L34)=1,L34,"") -> 604
A35: Other accrued liabilities | C35: 5280 | D35: 7535 | E35: 7919 | F35: 10636 | G35: 12670 | H35: 12589 | I35: 11858 | J35: 12425 | K35: 14282 | L35: 14600 | P35: 12430 | Q35: =IF(COUNT(J35)=1,J35,"") -> 12425 | R35: 11221 | S35: 13207 | T35: 12865 | U35: =IF(COUNT(K35)=1,K35,"") -> 14282 | V35: 11513 | W35: 12433 | X35: 14952 | Y35: =IF(COUNT(L35)=1,L35,"") -> 14600 | Z35: 14898 | AA35: 21178
A36: Total current liabilities | C36: 20302 | D36: 17421 | E36: 16626 | F36: 22310 | G36: 24754 | H36: 27462 | I36: 32155 | J36: 28053 | K36: 35666 | L36: 31575 | P36: 28614 | Q36: =IF(COUNT(J36)=1,J36,"") -> 28053 | R36: 27213 | S36: 32027 | T36: 35159 | U36: =IF(COUNT(K36)=1,K36,"") -> 35666 | V36: 32174 | W36: 34966 | X36: 32297 | Y36: =IF(COUNT(L36)=1,L36,"") -> 31575 | Z36: 26885 | AA36: 35670
A37: Debt (long-term; captioned 'Long-term debt' in FY2016-FY2017) | C37: 20649 | D37: 25037 | E37: 25098 | F37: 25308 | G37: 33897 | H37: 33510 | I37: 37684 | J37: 46978 | K37: 46282 | L37: 44086 | P37: 46591 | Q37: =IF(COUNT(J37)=1,J37,"") -> 46978 | R37: 47869 | S37: 48334 | T37: 46471 | U37: =IF(COUNT(K37)=1,K37,"") -> 46282 | V37: 44911 | W37: 44026 | X37: 44057 | Y37: =IF(COUNT(L37)=1,L37,"") -> 44086 | Z37: 43027 | AA37: 48549
A38: Contract liabilities (non-current; presented after total current liabilities FY2018-FY2021) | E38: 2049 | F38: 1368 | G38: 1367 | H38: 185 | Q38: =IF(COUNT(J38)=1,J38,"") | U38: =IF(COUNT(K38)=1,K38,"") | Y38: =IF(COUNT(L38)=1,L38,"")
A39: Long-term income taxes payable (FY2020-FY2021 captioned 'Income taxes payable', non-current) | E39: 4897 | F39: 4919 | G39: 4578 | H39: 4305 | I39: 3796 | Q39: =IF(COUNT(J39)=1,J39,"") | U39: =IF(COUNT(K39)=1,K39,"") | Y39: =IF(COUNT(L39)=1,L39,"")
A40: Deferred income taxes (liability) | C40: 1730 | D40: 3046 | E40: 1665 | F40: 2044 | G40: 3843 | H40: 2667 | I40: 202 | Q40: =IF(COUNT(J40)=1,J40,"") | U40: =IF(COUNT(K40)=1,K40,"") | Y40: =IF(COUNT(L40)=1,L40,"")
A41: Other long-term liabilities | C41: 3538 | D41: 7860 | E41: 2646 | F41: 2916 | G41: 3614 | H41: 4886 | I41: 4980 | J41: 6576 | K41: 9505 | L41: 9408 | P41: 7946 | Q41: =IF(COUNT(J41)=1,J41,"") -> 6576 | R41: 6895 | S41: 5410 | T41: 7048 | U41: =IF(COUNT(K41)=1,K41,"") -> 9505 | V41: 8744 | W41: 7777 | X41: 11430 | Y41: =IF(COUNT(L41)=1,L41,"") -> 9408 | Z41: 10431 | AA41: 15077
A42: Temporary equity | C42: 882 | D42: 866 | E42: 419 | F42: 155 | G42: 0 | Q42: =IF(COUNT(J42)=1,J42,"") | U42: =IF(COUNT(K42)=1,K42,"") | Y42: =IF(COUNT(L42)=1,L42,"")
A44: Equity | B44: Equity | C44: Equity | D44: Equity | E44: Equity | F44: Equity | G44: Equity | H44: Equity | I44: Equity | J44: Equity | K44: Equity | L44: Equity | M44: Equity | N44: Equity | O44: Equity | P44: Equity | Q44: Equity | R44: Equity | S44: Equity | T44: Equity | U44: Equity | V44: Equity | W44: Equity | X44: Equity | Y44: Equity | Z44: Equity | AA44: Equity
A45: Preferred stock | C45: 0 | D45: 0 | E45: 0 | F45: 0 | G45: 0 | H45: 0 | I45: 0 | J45: 0 | K45: 0 | L45: 0 | Q45: =IF(COUNT(J45)=1,J45,"") -> 0 | U45: =IF(COUNT(K45)=1,K45,"") -> 0 | Y45: =IF(COUNT(L45)=1,L45,"") -> 0
A46: Common stock and capital in excess of par value | C46: 25373 | D46: 26074 | E46: 25365 | F46: 25261 | G46: 25556 | H46: 28006 | I46: 31580 | J46: 36649 | K46: 50949 | L46: 65185 | P46: 35653 | Q46: =IF(COUNT(J46)=1,J46,"") -> 36649 | R46: 38291 | S46: 49763 | T46: 50665 | U46: =IF(COUNT(K46)=1,K46,"") -> 50949 | V46: 51920 | W46: 52334 | X46: 56755 | Y46: =IF(COUNT(L46)=1,L46,"") -> 65185 | Z46: 66259 | AA46: 53780
A47: Accumulated other comprehensive income (loss) | C47: 106 | D47: 862 | E47: -974 | F47: -1280 | G47: -751 | H47: -880 | I47: -562 | J47: -215 | K47: -711 | L47: 113 | P47: -861 | Q47: =IF(COUNT(J47)=1,J47,"") -> -215 | R47: -542 | S47: -696 | T47: -185 | U47: =IF(COUNT(K47)=1,K47,"") -> -711 | V47: -486 | W47: 65 | X47: 19 | Y47: =IF(COUNT(L47)=1,L47,"") -> 113 | Z47: -44 | AA47: -80
A48: Retained earnings | C48: 40747 | D48: 42083 | E48: 50172 | F48: 53523 | G48: 56233 | H48: 68265 | I48: 70405 | J48: 69156 | K48: 49032 | L48: 48983 | P48: 67021 | Q48: =IF(COUNT(J48)=1,J48,"") -> 69156 | R48: 68224 | S48: 66162 | T48: 49052 | U48: =IF(COUNT(K48)=1,K48,"") -> 49032 | V48: 48322 | W48: 45484 | X48: 49602 | Y48: =IF(COUNT(L48)=1,L48,"") -> 48983 | Z48: 45179 | AA48: 33842
A49: Total Intel stockholders' equity | I49: 101423 | J49: 105590 | K49: 99270 | L49: 114281 | P49: 101813 | Q49: =IF(COUNT(J49)=1,J49,"") -> 105590 | R49: 105973 | S49: 115229 | T49: 99532 | U49: =IF(COUNT(K49)=1,K49,"") -> 99270 | V49: 99756 | W49: 97883 | X49: 106376 | Y49: =IF(COUNT(L49)=1,L49,"") -> 114281 | Z49: 111394 | AA49: 87542
A50: Non-controlling interests | I50: 1863 | J50: 4375 | K50: 5762 | L50: 12079 | P50: 3873 | Q50: =IF(COUNT(J50)=1,J50,"") -> 4375 | R50: 4783 | S50: 5205 | T50: 5332 | U50: =IF(COUNT(K50)=1,K50,"") -> 5762 | V50: 6657 | W50: 7868 | X50: 10354 | Y50: =IF(COUNT(L50)=1,L50,"") -> 12079 | Z50: 13595 | AA50: 15601
A51: Total stockholders' equity | C51: 66226 | D51: 69019 | E51: 74563 | F51: 77504 | G51: 81038 | H51: 95391 | I51: 103286 | J51: 109965 | K51: 105032 | L51: 126360 | P51: 105686 | Q51: =IF(COUNT(J51)=1,J51,"") -> 109965 | R51: 110756 | S51: 120434 | T51: 104864 | U51: =IF(COUNT(K51)=1,K51,"") -> 105032 | V51: 106413 | W51: 105751 | X51: 116730 | Y51: =IF(COUNT(L51)=1,L51,"") -> 126360 | Z51: 124989 | AA51: 103143
A52: Total liabilities and stockholders' equity | C52: 113327 | D52: 123249 | E52: 127963 | F52: 136524 | G52: 153091 | H52: 168406 | I52: 182103 | J52: 191572 | K52: 196485 | L52: 211429 | P52: 188837 | Q52: =IF(COUNT(J52)=1,J52,"") -> 191572 | R52: 192733 | S52: 206205 | T52: 193542 | U52: =IF(COUNT(K52)=1,K52,"") -> 196485 | V52: 192242 | W52: 192520 | X52: 204514 | Y52: =IF(COUNT(L52)=1,L52,"") -> 211429 | Z52: 205332 | AA52: 202439
A54: Balance-sheet reconciliations | B54: Balance-sheet reconciliations | C54: Balance-sheet reconciliations | D54: Balance-sheet reconciliations | E54: Balance-sheet reconciliations | F54: Balance-sheet reconciliations | G54: Balance-sheet reconciliations | H54: Balance-sheet reconciliations | I54: Balance-sheet reconciliations | J54: Balance-sheet reconciliations | K54: Balance-sheet reconciliations | L54: Balance-sheet reconciliations | M54: Balance-sheet reconciliations | N54: Balance-sheet reconciliations | O54: Balance-sheet reconciliations | P54: Balance-sheet reconciliations | Q54: Balance-sheet reconciliations | R54: Balance-sheet reconciliations | S54: Balance-sheet reconciliations | T54: Balance-sheet reconciliations | U54: Balance-sheet reconciliations | V54: Balance-sheet reconciliations | W54: Balance-sheet reconciliations | X54: Balance-sheet reconciliations | Y54: Balance-sheet reconciliations | Z54: Balance-sheet reconciliations | AA54: Balance-sheet reconciliations
A55: Quarterly balances are period-end amounts; Q4 links the fiscal year end. Q1/Q2 2023 balance sheets are outside the supplied original filing set. | B55: Quarterly balances are period-end amounts; Q4 links the fiscal year end. Q1/Q2 2023 balance sheets are outside the supplied original filing set. | C55: Quarterly balances are period-end amounts; Q4 links the fiscal year end. Q1/Q2 2023 balance sheets are outside the supplied original filing set. | D55: Quarterly balances are period-end amounts; Q4 links the fiscal year end. Q1/Q2 2023 balance sheets are outside the supplied original filing set. | E55: Quarterly balances are period-end amounts; Q4 links the fiscal year end. Q1/Q2 2023 balance sheets are outside the supplied original filing set. | F55: Quarterly balances are period-end amounts; Q4 links the fiscal year end. Q1/Q2 2023 balance sheets are outside the supplied original filing set. | G55: Quarterly balances are period-end amounts; Q4 links the fiscal year end. Q1/Q2 2023 balance sheets are outside the supplied original filing set. | H55: Quarterly balances are period-end amounts; Q4 links the fiscal year end. Q1/Q2 2023 balance sheets are outside the supplied original filing set. | I55: Quarterly balances are period-end amounts; Q4 links the fiscal year end. Q1/Q2 2023 balance sheets are outside the supplied original filing set. | J55: Quarterly balances are period-end amounts; Q4 links the fiscal year end. Q1/Q2 2023 balance sheets are outside the supplied original filing set. | K55: Quarterly balances are period-end amounts; Q4 links the fiscal year end. Q1/Q2 2023 balance sheets are outside the supplied original filing set. | L55: Quarterly balances are period-end amounts; Q4 links the fiscal year end. Q1/Q2 2023 balance sheets are outside the supplied original filing set. | M55: Quarterly balances are period-end amounts; Q4 links the fiscal year end. Q1/Q2 2023 balance sheets are outside the supplied original filing set. | N55: Quarterly balances are period-end amounts; Q4 links the fiscal year end. Q1/Q2 2023 balance sheets are outside the supplied original filing set. | O55: Quarterly balances are period-end amounts; Q4 links the fiscal year end. Q1/Q2 2023 balance sheets are outside the supplied original filing set. | P55: Quarterly balances are period-end amounts; Q4 links the fiscal year end. Q1/Q2 2023 balance sheets are outside the supplied original filing set. | Q55: Quarterly balances are period-end amounts; Q4 links the fiscal year end. Q1/Q2 2023 balance sheets are outside the supplied original filing set. | R55: Quarterly balances are period-end amounts; Q4 links the fiscal year end. Q1/Q2 2023 balance sheets are outside the supplied original filing set. | S55: Quarterly balances are period-end amounts; Q4 links the fiscal year end. Q1/Q2 2023 balance sheets are outside the supplied original filing set. | T55: Quarterly balances are period-end amounts; Q4 links the fiscal year end. Q1/Q2 2023 balance sheets are outside the supplied original filing set. | U55: Quarterly balances are period-end amounts; Q4 links the fiscal year end. Q1/Q2 2023 balance sheets are outside the supplied original filing set. | V55: Quarterly balances are period-end amounts; Q4 links the fiscal year end. Q1/Q2 2023 balance sheets are outside the supplied original filing set. | W55: Quarterly balances are period-end amounts; Q4 links the fiscal year end. Q1/Q2 2023 balance sheets are outside the supplied original filing set. | X55: Quarterly balances are period-end amounts; Q4 links the fiscal year end. Q1/Q2 2023 balance sheets are outside the supplied original filing set. | Y55: Quarterly balances are period-end amounts; Q4 links the fiscal year end. Q1/Q2 2023 balance sheets are outside the supplied original filing set. | Z55: Quarterly balances are period-end amounts; Q4 links the fiscal year end. Q1/Q2 2023 balance sheets are outside the supplied original filing set. | AA55: Quarterly balances are period-end amounts; Q4 links the fiscal year end. Q1/Q2 2023 balance sheets are outside the supplied original filing set.
A56: Check: current asset lines - total current assets (should be 0) | C56: =IF(COUNT(C8,C9,C10,C11,C12,C13,C14,C15)=8,C8+C9+C10+C11+C12+C13+C14-C15,"") -> 0 | D56: =IF(COUNT(D8,D9,D10,D11,D12,D13,D14,D15)=8,D8+D9+D10+D11+D12+D13+D14-D15,"") -> 0 | E56: =IF(COUNT(E8,E9,E10,E11,E12,E14,E15)=7,E8+E9+E10+E11+E12+0+E14-E15,"") -> 0 | F56: =IF(COUNT(F8,F9,F10,F11,F12,F14,F15)=7,F8+F9+F10+F11+F12+0+F14-F15,"") -> 0 | G56: =IF(COUNT(G8,G9,G10,G11,G12,G13,G14,G15)=8,G8+G9+G10+G11+G12+G13+G14-G15,"") -> 0 | H56: =IF(COUNT(H8,H9,H10,H11,H12,H13,H14,H15)=8,H8+H9+H10+H11+H12+H13+H14-H15,"") -> 0 | I56: =IF(COUNT(I8,I9,I11,I12,I13,I14,I15)=7,I8+I9+0+I11+I12+I13+I14-I15,"") -> 0 | J56: =IF(COUNT(J8,J9,J11,J12,J14,J15)=6,J8+J9+0+J11+J12+0+J14-J15,"") -> 0 | K56: =IF(COUNT(K8,K9,K11,K12,K14,K15)=6,K8+K9+0+K11+K12+0+K14-K15,"") -> 0 | L56: =IF(COUNT(L8,L9,L11,L12,L14,L15)=6,L8+L9+0+L11+L12+0+L14-L15,"") -> 0 | P56: =IF(COUNT(P8,P9,P11,P12,P14,P15)=6,P8+P9+0+P11+P12+0+P14-P15,"") -> 0 | Q56: =IF(COUNT(Q8,Q9,Q11,Q12,Q14,Q15)=6,Q8+Q9+0+Q11+Q12+0+Q14-Q15,"") -> 0 | R56: =IF(COUNT(R8,R9,R11,R12,R14,R15)=6,R8+R9+0+R11+R12+0+R14-R15,"") -> 0 | S56: =IF(COUNT(S8,S9,S11,S12,S14,S15)=6,S8+S9+0+S11+S12+0+S14-S15,"") -> 0 | T56: =IF(COUNT(T8,T9,T11,T12,T14,T15)=6,T8+T9+0+T11+T12+0+T14-T15,"") -> 0 | U56: =IF(COUNT(U8,U9,U11,U12,U14,U15)=6,U8+U9+0+U11+U12+0+U14-U15,"") -> 0 | V56: =IF(COUNT(V8,V9,V11,V12,V14,V15)=6,V8+V9+0+V11+V12+0+V14-V15,"") -> 0 | W56: =IF(COUNT(W8,W9,W11,W12,W14,W15)=6,W8+W9+0+W11+W12+0+W14-W15,"") -> 0 | ... AA56: =IF(COUNT(AA8,AA9,AA11,AA12,AA14,AA15)=6,AA8+AA9+0+AA11+AA12+0+AA14-AA15,"") -> 0
A57: Check: asset lines - total assets (should be 0) | C57: =IF(COUNT(C15,C18,C19,C21,C22,C23,C24,C25)=8,C15+C18+C19+C21+0+C22+C23+C24-C25,"") -> 0 | D57: =IF(COUNT(D15,D18,D19,D21,D22,D23,D24,D25)=8,D15+D18+D19+D21+0+D22+D23+D24-D25,"") -> 0 | E57: =IF(COUNT(E15,E18,E21,E20,E22,E23,E24,E25)=8,E15+E18+0+E21+E20+E22+E23+E24-E25,"") -> 0 | F57: =IF(COUNT(F15,F18,F21,F20,F22,F23,F24,F25)=8,F15+F18+0+F21+F20+F22+F23+F24-F25,"") -> 0 | G57: =IF(COUNT(G15,G18,G21,G20,G22,G23,G24,G25)=8,G15+G18+0+G21+G20+G22+G23+G24-G25,"") -> 0 | H57: =IF(COUNT(H15,H18,H21,H20,H22,H23,H24,H25)=8,H15+H18+0+H21+H20+H22+H23+H24-H25,"") -> 0 | I57: =IF(COUNT(I15,I18,I20,I22,I23,I24,I25)=7,I15+I18+0+0+I20+I22+I23+I24-I25,"") -> 0 | J57: =IF(COUNT(J15,J18,J20,J22,J23,J24,J25)=7,J15+J18+0+0+J20+J22+J23+J24-J25,"") -> 0 | K57: =IF(COUNT(K15,K18,K20,K22,K23,K24,K25)=7,K15+K18+0+0+K20+K22+K23+K24-K25,"") -> 0 | L57: =IF(COUNT(L15,L18,L20,L22,L23,L24,L25)=7,L15+L18+0+0+L20+L22+L23+L24-L25,"") -> 0 | P57: =IF(COUNT(P15,P18,P20,P22,P23,P24,P25)=7,P15+P18+0+0+P20+P22+P23+P24-P25,"") -> 0 | Q57: =IF(COUNT(Q15,Q18,Q20,Q22,Q23,Q24,Q25)=7,Q15+Q18+0+0+Q20+Q22+Q23+Q24-Q25,"") -> 0 | R57: =IF(COUNT(R15,R18,R20,R22,R23,R24,R25)=7,R15+R18+0+0+R20+R22+R23+R24-R25,"") -> 0 | S57: =IF(COUNT(S15,S18,S20,S22,S23,S24,S25)=7,S15+S18+0+0+S20+S22+S23+S24-S25,"") -> 0 | T57: =IF(COUNT(T15,T18,T20,T22,T23,T24,T25)=7,T15+T18+0+0+T20+T22+T23+T24-T25,"") -> 0 | U57: =IF(COUNT(U15,U18,U20,U22,U23,U24,U25)=7,U15+U18+0+0+U20+U22+U23+U24-U25,"") -> 0 | V57: =IF(COUNT(V15,V18,V20,V22,V23,V24,V25)=7,V15+V18+0+0+V20+V22+V23+V24-V25,"") -> 0 | W57: =IF(COUNT(W15,W18,W20,W22,W23,W24,W25)=7,W15+W18+0+0+W20+W22+W23+W24-W25,"") -> 0 | ... AA57: =IF(COUNT(AA15,AA18,AA20,AA22,AA23,AA24,AA25)=7,AA15+AA18+0+0+AA20+AA22+AA23+AA24-AA25,"") -> 0
A58: Check: current liability lines - total current liabilities (should be 0) | C58: =IF(COUNT(C33,C28,C29,C30,C31,C32,C35,C36)=8,C33+C28+C29+C30+C31+C32+0+C35-C36,"") -> 0 | D58: =IF(COUNT(D33,D28,D29,D31,D32,D35,D36)=7,D33+D28+D29+0+D31+D32+0+D35-D36,"") -> 0 | E58: =IF(COUNT(E33,E28,E29,E31,E35,E36)=6,E33+E28+E29+0+E31+0+0+E35-E36,"") -> 0 | F58: =IF(COUNT(F33,F28,F29,F35,F36)=5,F33+F28+F29+0+0+0+0+F35-F36,"") -> 0 | G58: =IF(COUNT(G33,G28,G29,G35,G36)=5,G33+G28+G29+0+0+0+0+G35-G36,"") -> 0 | H58: =IF(COUNT(H33,H28,H29,H35,H36)=5,H33+H28+H29+0+0+0+0+H35-H36,"") -> 0 | I58: =IF(COUNT(I33,I28,I29,I34,I35,I36)=6,I33+I28+I29+0+0+0+I34+I35-I36,"") -> 0 | J58: =IF(COUNT(J33,J28,J29,J34,J35,J36)=6,J33+J28+J29+0+0+0+J34+J35-J36,"") -> 0 | K58: =IF(COUNT(K33,K28,K29,K34,K35,K36)=6,K33+K28+K29+0+0+0+K34+K35-K36,"") -> 0 | L58: =IF(COUNT(L33,L28,L29,L34,L35,L36)=6,L33+L28+L29+0+0+0+L34+L35-L36,"") -> 0 | P58: =IF(COUNT(P33,P28,P29,P34,P35,P36)=6,P33+P28+P29+0+0+0+P34+P35-P36,"") -> 0 | Q58: =IF(COUNT(Q33,Q28,Q29,Q34,Q35,Q36)=6,Q33+Q28+Q29+0+0+0+Q34+Q35-Q36,"") -> 0 | R58: =IF(COUNT(R33,R28,R29,R34,R35,R36)=6,R33+R28+R29+0+0+0+R34+R35-R36,"") -> 0 | S58: =IF(COUNT(S33,S28,S29,S34,S35,S36)=6,S33+S28+S29+0+0+0+S34+S35-S36,"") -> 0 | T58: =IF(COUNT(T33,T28,T29,T34,T35,T36)=6,T33+T28+T29+0+0+0+T34+T35-T36,"") -> 0 | U58: =IF(COUNT(U33,U28,U29,U34,U35,U36)=6,U33+U28+U29+0+0+0+U34+U35-U36,"") -> 0 | V58: =IF(COUNT(V33,V28,V29,V34,V35,V36)=6,V33+V28+V29+0+0+0+V34+V35-V36,"") -> 0 | W58: =IF(COUNT(W33,W28,W29,W34,W35,W36)=6,W33+W28+W29+0+0+0+W34+W35-W36,"") -> 0 | ... Y58: =IF(COUNT(Y33,Y28,Y29,Y34,Y35,Y36)=6,Y33+Y28+Y29+0+0+0+Y34+Y35-Y36,"") -> 0 | Z58: =IF(COUNT(Z33,Z28,Z29,Z35,Z36)=5,Z33+Z28+Z29+0+0+0+0+Z35-Z36,"") -> 0 | AA58: =IF(COUNT(AA33,AA28,AA29,AA35,AA36)=5,AA33+AA28+AA29+0+0+0+0+AA35-AA36,"") -> 0
A59: Check: liabilities, temporary equity and equity lines - total (should be 0) | C59: =IF(COUNT(C36,C37,C40,C41,C42,C51,C52)=7,C36+C37+0+0+C40+C41+C42+C51-C52,"") -> 0 | D59: =IF(COUNT(D36,D37,D40,D41,D42,D51,D52)=7,D36+D37+0+0+D40+D41+D42+D51-D52,"") -> 0 | E59: =IF(COUNT(E36,E37,E38,E39,E40,E41,E42,E51,E52)=9,E36+E37+E38+E39+E40+E41+E42+E51-E52,"") -> 0 | F59: =IF(COUNT(F36,F37,F38,F39,F40,F41,F42,F51,F52)=9,F36+F37+F38+F39+F40+F41+F42+F51-F52,"") -> 0 | G59: =IF(COUNT(G36,G37,G38,G39,G40,G41,G42,G51,G52)=9,G36+G37+G38+G39+G40+G41+G42+G51-G52,"") -> 0 | H59: =IF(COUNT(H36,H37,H38,H39,H40,H41,H51,H52)=8,H36+H37+H38+H39+H40+H41+0+H51-H52,"") -> 0 | I59: =IF(COUNT(I36,I37,I39,I40,I41,I51,I52)=7,I36+I37+0+I39+I40+I41+0+I51-I52,"") -> 0 | J59: =IF(COUNT(J36,J37,J41,J51,J52)=5,J36+J37+0+0+0+J41+0+J51-J52,"") -> 0 | K59: =IF(COUNT(K36,K37,K41,K51,K52)=5,K36+K37+0+0+0+K41+0+K51-K52,"") -> 0 | L59: =IF(COUNT(L36,L37,L41,L51,L52)=5,L36+L37+0+0+0+L41+0+L51-L52,"") -> 0 | P59: =IF(COUNT(P36,P37,P41,P51,P52)=5,P36+P37+0+0+0+P41+0+P51-P52,"") -> 0 | Q59: =IF(COUNT(Q36,Q37,Q41,Q51,Q52)=5,Q36+Q37+0+0+0+Q41+0+Q51-Q52,"") -> 0 | R59: =IF(COUNT(R36,R37,R41,R51,R52)=5,R36+R37+0+0+0+R41+0+R51-R52,"") -> 0 | S59: =IF(COUNT(S36,S37,S41,S51,S52)=5,S36+S37+0+0+0+S41+0+S51-S52,"") -> 0 | T59: =IF(COUNT(T36,T37,T41,T51,T52)=5,T36+T37+0+0+0+T41+0+T51-T52,"") -> 0 | U59: =IF(COUNT(U36,U37,U41,U51,U52)=5,U36+U37+0+0+0+U41+0+U51-U52,"") -> 0 | V59: =IF(COUNT(V36,V37,V41,V51,V52)=5,V36+V37+0+0+0+V41+0+V51-V52,"") -> 0 | W59: =IF(COUNT(W36,W37,W41,W51,W52)=5,W36+W37+0+0+0+W41+0+W51-W52,"") -> 0 | ... AA59: =IF(COUNT(AA36,AA37,AA41,AA51,AA52)=5,AA36+AA37+0+0+0+AA41+0+AA51-AA52,"") -> 0
A60: Check: Intel equity components - Intel stockholders' equity (should be 0; FY2022+ presentation) | I60: =IF(COUNT(I45,I46,I47,I48,I49)=5,I45+I46+I47+I48-I49,"") -> 0 | J60: =IF(COUNT(J45,J46,J47,J48,J49)=5,J45+J46+J47+J48-J49,"") -> 0 | K60: =IF(COUNT(K45,K46,K47,K48,K49)=5,K45+K46+K47+K48-K49,"") -> 0 | L60: =IF(COUNT(L45,L46,L47,L48,L49)=5,L45+L46+L47+L48-L49,"") -> 0 | P60: =IF(COUNT(P46,P47,P48,P49)=4,0+P46+P47+P48-P49,"") -> 0 | Q60: =IF(COUNT(Q45,Q46,Q47,Q48,Q49)=5,Q45+Q46+Q47+Q48-Q49,"") -> 0 | R60: =IF(COUNT(R46,R47,R48,R49)=4,0+R46+R47+R48-R49,"") -> 0 | S60: =IF(COUNT(S46,S47,S48,S49)=4,0+S46+S47+S48-S49,"") -> 0 | T60: =IF(COUNT(T46,T47,T48,T49)=4,0+T46+T47+T48-T49,"") -> 0 | U60: =IF(COUNT(U45,U46,U47,U48,U49)=5,U45+U46+U47+U48-U49,"") -> 0 | V60: =IF(COUNT(V46,V47,V48,V49)=4,0+V46+V47+V48-V49,"") -> 0 | W60: =IF(COUNT(W46,W47,W48,W49)=4,0+W46+W47+W48-W49,"") -> 0 | X60: =IF(COUNT(X46,X47,X48,X49)=4,0+X46+X47+X48-X49,"") -> 0 | Y60: =IF(COUNT(Y45,Y46,Y47,Y48,Y49)=5,Y45+Y46+Y47+Y48-Y49,"") -> 0 | Z60: =IF(COUNT(Z46,Z47,Z48,Z49)=4,0+Z46+Z47+Z48-Z49,"") -> 0 | AA60: =IF(COUNT(AA46,AA47,AA48,AA49)=4,0+AA46+AA47+AA48-AA49,"") -> 0
A61: Check: Intel equity + NCI - total equity (should be 0; FY2022+) | I61: =IF(COUNT(I49,I50,I51)=3,I49+I50-I51,"") -> 0 | J61: =IF(COUNT(J49,J50,J51)=3,J49+J50-J51,"") -> 0 | K61: =IF(COUNT(K49,K50,K51)=3,K49+K50-K51,"") -> 0 | L61: =IF(COUNT(L49,L50,L51)=3,L49+L50-L51,"") -> 0 | P61: =IF(COUNT(P49,P50,P51)=3,P49+P50-P51,"") -> 0 | Q61: =IF(COUNT(Q49,Q50,Q51)=3,Q49+Q50-Q51,"") -> 0 | R61: =IF(COUNT(R49,R50,R51)=3,R49+R50-R51,"") -> 0 | S61: =IF(COUNT(S49,S50,S51)=3,S49+S50-S51,"") -> 0 | T61: =IF(COUNT(T49,T50,T51)=3,T49+T50-T51,"") -> 0 | U61: =IF(COUNT(U49,U50,U51)=3,U49+U50-U51,"") -> 0 | V61: =IF(COUNT(V49,V50,V51)=3,V49+V50-V51,"") -> 0 | W61: =IF(COUNT(W49,W50,W51)=3,W49+W50-W51,"") -> 0 | ... AA61: =IF(COUNT(AA49,AA50,AA51)=3,AA49+AA50-AA51,"") -> 0
A62: Check: total assets - total liabilities and equity (should be 0) | C62: =IF(COUNT(C25,C52)=2,C25-C52,"") -> 0 | D62: =IF(COUNT(D25,D52)=2,D25-D52,"") -> 0 | E62: =IF(COUNT(E25,E52)=2,E25-E52,"") -> 0 | F62: =IF(COUNT(F25,F52)=2,F25-F52,"") -> 0 | G62: =IF(COUNT(G25,G52)=2,G25-G52,"") -> 0 | H62: =IF(COUNT(H25,H52)=2,H25-H52,"") -> 0 | I62: =IF(COUNT(I25,I52)=2,I25-I52,"") -> 0 | J62: =IF(COUNT(J25,J52)=2,J25-J52,"") -> 0 | ... L62: =IF(COUNT(L25,L52)=2,L25-L52,"") -> 0 | P62: =IF(COUNT(P25,P52)=2,P25-P52,"") -> 0 | Q62: =IF(COUNT(Q25,Q52)=2,Q25-Q52,"") -> 0 | R62: =IF(COUNT(R25,R52)=2,R25-R52,"") -> 0 | S62: =IF(COUNT(S25,S52)=2,S25-S52,"") -> 0 | T62: =IF(COUNT(T25,T52)=2,T25-T52,"") -> 0 | U62: =IF(COUNT(U25,U52)=2,U25-U52,"") -> 0 | V62: =IF(COUNT(V25,V52)=2,V25-V52,"") -> 0 | W62: =IF(COUNT(W25,W52)=2,W25-W52,"") -> 0 | ... AA62: =IF(COUNT(AA25,AA52)=2,AA25-AA52,"") -> 0
A64: Opening-balance inputs: 26 December 2015 | B64: Opening-balance inputs: 26 December 2015 | C64: Opening-balance inputs: 26 December 2015 | D64: Opening-balance inputs: 26 December 2015 | E64: Opening-balance inputs: 26 December 2015 | F64: Opening-balance inputs: 26 December 2015 | G64: Opening-balance inputs: 26 December 2015 | H64: Opening-balance inputs: 26 December 2015 | I64: Opening-balance inputs: 26 December 2015 | J64: Opening-balance inputs: 26 December 2015 | K64: Opening-balance inputs: 26 December 2015 | L64: Opening-balance inputs: 26 December 2015 | M64: Opening-balance inputs: 26 December 2015 | N64: Opening-balance inputs: 26 December 2015 | O64: Opening-balance inputs: 26 December 2015 | P64: Opening-balance inputs: 26 December 2015 | Q64: Opening-balance inputs: 26 December 2015 | R64: Opening-balance inputs: 26 December 2015 | S64: Opening-balance inputs: 26 December 2015 | T64: Opening-balance inputs: 26 December 2015 | U64: Opening-balance inputs: 26 December 2015 | V64: Opening-balance inputs: 26 December 2015 | W64: Opening-balance inputs: 26 December 2015 | X64: Opening-balance inputs: 26 December 2015 | Y64: Opening-balance inputs: 26 December 2015 | Z64: Opening-balance inputs: 26 December 2015 | AA64: Opening-balance inputs: 26 December 2015
A65: These explicitly dated opening inputs appear in the FY2016 column only; they are 26 December 2015 balances, not FY2016 closing values. | B65: These explicitly dated opening inputs appear in the FY2016 column only; they are 26 December 2015 balances, not FY2016 closing values. | C65: These explicitly dated opening inputs appear in the FY2016 column only; they are 26 December 2015 balances, not FY2016 closing values. | D65: These explicitly dated opening inputs appear in the FY2016 column only; they are 26 December 2015 balances, not FY2016 closing values. | E65: These explicitly dated opening inputs appear in the FY2016 column only; they are 26 December 2015 balances, not FY2016 closing values. | F65: These explicitly dated opening inputs appear in the FY2016 column only; they are 26 December 2015 balances, not FY2016 closing values. | G65: These explicitly dated opening inputs appear in the FY2016 column only; they are 26 December 2015 balances, not FY2016 closing values. | H65: These explicitly dated opening inputs appear in the FY2016 column only; they are 26 December 2015 balances, not FY2016 closing values. | I65: These explicitly dated opening inputs appear in the FY2016 column only; they are 26 December 2015 balances, not FY2016 closing values. | J65: These explicitly dated opening inputs appear in the FY2016 column only; they are 26 December 2015 balances, not FY2016 closing values. | K65: These explicitly dated opening inputs appear in the FY2016 column only; they are 26 December 2015 balances, not FY2016 closing values. | L65: These explicitly dated opening inputs appear in the FY2016 column only; they are 26 December 2015 balances, not FY2016 closing values. | M65: These explicitly dated opening inputs appear in the FY2016 column only; they are 26 December 2015 balances, not FY2016 closing values. | N65: These explicitly dated opening inputs appear in the FY2016 column only; they are 26 December 2015 balances, not FY2016 closing values. | O65: These explicitly dated opening inputs appear in the FY2016 column only; they are 26 December 2015 balances, not FY2016 closing values. | P65: These explicitly dated opening inputs appear in the FY2016 column only; they are 26 December 2015 balances, not FY2016 closing values. | Q65: These explicitly dated opening inputs appear in the FY2016 column only; they are 26 December 2015 balances, not FY2016 closing values. | R65: These explicitly dated opening inputs appear in the FY2016 column only; they are 26 December 2015 balances, not FY2016 closing values. | S65: These explicitly dated opening inputs appear in the FY2016 column only; they are 26 December 2015 balances, not FY2016 closing values. | T65: These explicitly dated opening inputs appear in the FY2016 column only; they are 26 December 2015 balances, not FY2016 closing values. | U65: These explicitly dated opening inputs appear in the FY2016 column only; they are 26 December 2015 balances, not FY2016 closing values. | V65: These explicitly dated opening inputs appear in the FY2016 column only; they are 26 December 2015 balances, not FY2016 closing values. | W65: These explicitly dated opening inputs appear in the FY2016 column only; they are 26 December 2015 balances, not FY2016 closing values. | X65: These explicitly dated opening inputs appear in the FY2016 column only; they are 26 December 2015 balances, not FY2016 closing values. | Y65: These explicitly dated opening inputs appear in the FY2016 column only; they are 26 December 2015 balances, not FY2016 closing values. | Z65: These explicitly dated opening inputs appear in the FY2016 column only; they are 26 December 2015 balances, not FY2016 closing values. | AA65: These explicitly dated opening inputs appear in the FY2016 column only; they are 26 December 2015 balances, not FY2016 closing values.
A66: Opening 2016: Cash and cash equivalents | C66: 15308
A67: Opening 2016: Short-term investments | C67: 2682
A68: Opening 2016: Trading assets | C68: 7323
A69: Opening 2016: Accounts receivable | C69: 4787
A70: Opening 2016: Inventories | C70: 5167
A71: Opening 2016: Total assets | C71: 101459
A72: Opening 2016: Marketable equity securities | C72: 5960
A73: Opening 2016: Other long-term investments | C73: 1891
A75: Opening financial-note inputs: 26 December 2015 | B75: Opening financial-note inputs: 26 December 2015 | C75: Opening financial-note inputs: 26 December 2015 | D75: Opening financial-note inputs: 26 December 2015 | E75: Opening financial-note inputs: 26 December 2015 | F75: Opening financial-note inputs: 26 December 2015 | G75: Opening financial-note inputs: 26 December 2015 | H75: Opening financial-note inputs: 26 December 2015 | I75: Opening financial-note inputs: 26 December 2015 | J75: Opening financial-note inputs: 26 December 2015 | K75: Opening financial-note inputs: 26 December 2015 | L75: Opening financial-note inputs: 26 December 2015 | M75: Opening financial-note inputs: 26 December 2015 | N75: Opening financial-note inputs: 26 December 2015 | O75: Opening financial-note inputs: 26 December 2015 | P75: Opening financial-note inputs: 26 December 2015 | Q75: Opening financial-note inputs: 26 December 2015 | R75: Opening financial-note inputs: 26 December 2015 | S75: Opening financial-note inputs: 26 December 2015 | T75: Opening financial-note inputs: 26 December 2015 | U75: Opening financial-note inputs: 26 December 2015 | V75: Opening financial-note inputs: 26 December 2015 | W75: Opening financial-note inputs: 26 December 2015 | X75: Opening financial-note inputs: 26 December 2015 | Y75: Opening financial-note inputs: 26 December 2015 | Z75: Opening financial-note inputs: 26 December 2015 | AA75: Opening financial-note inputs: 26 December 2015
A76: Explicitly dated opening stocks, displayed in FY2016 column only. Operating hedges remain in IC; marketable equity is not counted again. | B76: Explicitly dated opening stocks, displayed in FY2016 column only. Operating hedges remain in IC; marketable equity is not counted again. | C76: Explicitly dated opening stocks, displayed in FY2016 column only. Operating hedges remain in IC; marketable equity is not counted again. | D76: Explicitly dated opening stocks, displayed in FY2016 column only. Operating hedges remain in IC; marketable equity is not counted again. | E76: Explicitly dated opening stocks, displayed in FY2016 column only. Operating hedges remain in IC; marketable equity is not counted again. | F76: Explicitly dated opening stocks, displayed in FY2016 column only. Operating hedges remain in IC; marketable equity is not counted again. | G76: Explicitly dated opening stocks, displayed in FY2016 column only. Operating hedges remain in IC; marketable equity is not counted again. | H76: Explicitly dated opening stocks, displayed in FY2016 column only. Operating hedges remain in IC; marketable equity is not counted again. | I76: Explicitly dated opening stocks, displayed in FY2016 column only. Operating hedges remain in IC; marketable equity is not counted again. | J76: Explicitly dated opening stocks, displayed in FY2016 column only. Operating hedges remain in IC; marketable equity is not counted again. | K76: Explicitly dated opening stocks, displayed in FY2016 column only. Operating hedges remain in IC; marketable equity is not counted again. | L76: Explicitly dated opening stocks, displayed in FY2016 column only. Operating hedges remain in IC; marketable equity is not counted again. | M76: Explicitly dated opening stocks, displayed in FY2016 column only. Operating hedges remain in IC; marketable equity is not counted again. | N76: Explicitly dated opening stocks, displayed in FY2016 column only. Operating hedges remain in IC; marketable equity is not counted again. | O76: Explicitly dated opening stocks, displayed in FY2016 column only. Operating hedges remain in IC; marketable equity is not counted again. | P76: Explicitly dated opening stocks, displayed in FY2016 column only. Operating hedges remain in IC; marketable equity is not counted again. | Q76: Explicitly dated opening stocks, displayed in FY2016 column only. Operating hedges remain in IC; marketable equity is not counted again. | R76: Explicitly dated opening stocks, displayed in FY2016 column only. Operating hedges remain in IC; marketable equity is not counted again. | S76: Explicitly dated opening stocks, displayed in FY2016 column only. Operating hedges remain in IC; marketable equity is not counted again. | T76: Explicitly dated opening stocks, displayed in FY2016 column only. Operating hedges remain in IC; marketable equity is not counted again. | U76: Explicitly dated opening stocks, displayed in FY2016 column only. Operating hedges remain in IC; marketable equity is not counted again. | V76: Explicitly dated opening stocks, displayed in FY2016 column only. Operating hedges remain in IC; marketable equity is not counted again. | W76: Explicitly dated opening stocks, displayed in FY2016 column only. Operating hedges remain in IC; marketable equity is not counted again. | X76: Explicitly dated opening stocks, displayed in FY2016 column only. Operating hedges remain in IC; marketable equity is not counted again. | Y76: Explicitly dated opening stocks, displayed in FY2016 column only. Operating hedges remain in IC; marketable equity is not counted again. | Z76: Explicitly dated opening stocks, displayed in FY2016 column only. Operating hedges remain in IC; marketable equity is not counted again. | AA76: Explicitly dated opening stocks, displayed in FY2016 column only. Operating hedges remain in IC; marketable equity is not counted again.
A77: Opening 2016: Derivative assets: current | C77: 445
A78: Opening 2016: Loans receivable: current | C78: 137
A79: Opening 2016: Derivative assets: long-term | C79: 40
A80: Opening 2016: Loans receivable: long-term | C80: 342
A81: Opening 2016: Equity method investments within other long-term assets | C81: 1590
A82: Opening 2016: Non-marketable cost method investments within other long-term assets | C82: 2933
A83: Opening 2016: Loans at cost: total (FV loans excluded) | C83: 315
A84: Opening 2016: Reverse repos >3 months | C84: 1000

Sheet Cash Flow
A1: Intel Corporation — Cash Flow | B1: Intel Corporation — Cash Flow | C1: Intel Corporation — Cash Flow | D1: Intel Corporation — Cash Flow | E1: Intel Corporation — Cash Flow | F1: Intel Corporation — Cash Flow | G1: Intel Corporation — Cash Flow | H1: Intel Corporation — Cash Flow | I1: Intel Corporation — Cash Flow | J1: Intel Corporation — Cash Flow | K1: Intel Corporation — Cash Flow | L1: Intel Corporation — Cash Flow | M1: Intel Corporation — Cash Flow | N1: Intel Corporation — Cash Flow | O1: Intel Corporation — Cash Flow | P1: Intel Corporation — Cash Flow | Q1: Intel Corporation — Cash Flow | R1: Intel Corporation — Cash Flow | S1: Intel Corporation — Cash Flow | T1: Intel Corporation — Cash Flow | U1: Intel Corporation — Cash Flow | V1: Intel Corporation — Cash Flow | W1: Intel Corporation — Cash Flow | X1: Intel Corporation — Cash Flow | Y1: Intel Corporation — Cash Flow | Z1: Intel Corporation — Cash Flow | AA1: Intel Corporation — Cash Flow
A2: USD million unless stated otherwise; annual FY2016–FY2025; latest interim 27 June 2026.
A3: Metric | C3: FY2016 | D3: FY2017 | E3: FY2018 | F3: FY2019 | G3: FY2020 | H3: FY2021 | I3: FY2022 | J3: FY2023 | K3: FY2024 | L3: FY2025 | N3: 1Q2023 | O3: 2Q2023 | P3: 3Q2023 | Q3: 4Q2023 | R3: 1Q2024 | S3: 2Q2024 | T3: 3Q2024 | U3: 4Q2024 | V3: 1Q2025 | W3: 2Q2025 | X3: 3Q2025 | Y3: 4Q2025 | Z3: 1Q2026 | AA3: 2Q2026
C4: 2016-12-31T00:00:00.000Z | D4: 2017-12-30T00:00:00.000Z | E4: 2018-12-29T00:00:00.000Z | F4: 2019-12-28T00:00:00.000Z | G4: 2020-12-26T00:00:00.000Z | H4: 2021-12-25T00:00:00.000Z | I4: 2022-12-31T00:00:00.000Z | J4: 2023-12-30T00:00:00.000Z | K4: 2024-12-28T00:00:00.000Z | L4: 2025-12-27T00:00:00.000Z | N4: 2023-04-01T00:00:00.000Z | O4: 2023-07-01T00:00:00.000Z | P4: 2023-09-30T00:00:00.000Z | Q4: 2023-12-30T00:00:00.000Z | R4: 2024-03-30T00:00:00.000Z | S4: 2024-06-29T00:00:00.000Z | T4: 2024-09-28T00:00:00.000Z | U4: 2024-12-28T00:00:00.000Z | V4: 2025-03-29T00:00:00.000Z | W4: 2025-06-28T00:00:00.000Z | X4: 2025-09-27T00:00:00.000Z | Y4: 2025-12-27T00:00:00.000Z | Z4: 2026-03-28T00:00:00.000Z | AA4: 2026-06-27T00:00:00.000Z
A5: Quarter columns: source YTD; see discrete section | C5: Annual | D5: Annual | E5: Annual | F5: Annual | G5: Annual | H5: Annual | I5: Annual | J5: Annual | K5: Annual | L5: Annual | N5: YTD | O5: YTD | P5: YTD | Q5: YTD | R5: YTD | S5: YTD | T5: YTD | U5: YTD | V5: YTD | W5: YTD | X5: YTD | Y5: YTD | Z5: YTD | AA5: YTD
A7: Operating cash flow | B7: Operating cash flow | C7: Operating cash flow | D7: Operating cash flow | E7: Operating cash flow | F7: Operating cash flow | G7: Operating cash flow | H7: Operating cash flow | I7: Operating cash flow | J7: Operating cash flow | K7: Operating cash flow | L7: Operating cash flow | M7: Operating cash flow | N7: Operating cash flow | O7: Operating cash flow | P7: Operating cash flow | Q7: Operating cash flow | R7: Operating cash flow | S7: Operating cash flow | T7: Operating cash flow | U7: Operating cash flow | V7: Operating cash flow | W7: Operating cash flow | X7: Operating cash flow | Y7: Operating cash flow | Z7: Operating cash flow | AA7: Operating cash flow
A8: Quarterly columns are YTD: Q1=3 months, Q2=6 months, Q3=9 months, Q4=full year. Cash balances are instant amounts. | B8: Quarterly columns are YTD: Q1=3 months, Q2=6 months, Q3=9 months, Q4=full year. Cash balances are instant amounts. | C8: Quarterly columns are YTD: Q1=3 months, Q2=6 months, Q3=9 months, Q4=full year. Cash balances are instant amounts. | D8: Quarterly columns are YTD: Q1=3 months, Q2=6 months, Q3=9 months, Q4=full year. Cash balances are instant amounts. | E8: Quarterly columns are YTD: Q1=3 months, Q2=6 months, Q3=9 months, Q4=full year. Cash balances are instant amounts. | F8: Quarterly columns are YTD: Q1=3 months, Q2=6 months, Q3=9 months, Q4=full year. Cash balances are instant amounts. | G8: Quarterly columns are YTD: Q1=3 months, Q2=6 months, Q3=9 months, Q4=full year. Cash balances are instant amounts. | H8: Quarterly columns are YTD: Q1=3 months, Q2=6 months, Q3=9 months, Q4=full year. Cash balances are instant amounts. | I8: Quarterly columns are YTD: Q1=3 months, Q2=6 months, Q3=9 months, Q4=full year. Cash balances are instant amounts. | J8: Quarterly columns are YTD: Q1=3 months, Q2=6 months, Q3=9 months, Q4=full year. Cash balances are instant amounts. | K8: Quarterly columns are YTD: Q1=3 months, Q2=6 months, Q3=9 months, Q4=full year. Cash balances are instant amounts. | L8: Quarterly columns are YTD: Q1=3 months, Q2=6 months, Q3=9 months, Q4=full year. Cash balances are instant amounts. | M8: Quarterly columns are YTD: Q1=3 months, Q2=6 months, Q3=9 months, Q4=full year. Cash balances are instant amounts. | N8: Quarterly columns are YTD: Q1=3 months, Q2=6 months, Q3=9 months, Q4=full year. Cash balances are instant amounts. | O8: Quarterly columns are YTD: Q1=3 months, Q2=6 months, Q3=9 months, Q4=full year. Cash balances are instant amounts. | P8: Quarterly columns are YTD: Q1=3 months, Q2=6 months, Q3=9 months, Q4=full year. Cash balances are instant amounts. | Q8: Quarterly columns are YTD: Q1=3 months, Q2=6 months, Q3=9 months, Q4=full year. Cash balances are instant amounts. | R8: Quarterly columns are YTD: Q1=3 months, Q2=6 months, Q3=9 months, Q4=full year. Cash balances are instant amounts. | S8: Quarterly columns are YTD: Q1=3 months, Q2=6 months, Q3=9 months, Q4=full year. Cash balances are instant amounts. | T8: Quarterly columns are YTD: Q1=3 months, Q2=6 months, Q3=9 months, Q4=full year. Cash balances are instant amounts. | U8: Quarterly columns are YTD: Q1=3 months, Q2=6 months, Q3=9 months, Q4=full year. Cash balances are instant amounts. | V8: Quarterly columns are YTD: Q1=3 months, Q2=6 months, Q3=9 months, Q4=full year. Cash balances are instant amounts. | W8: Quarterly columns are YTD: Q1=3 months, Q2=6 months, Q3=9 months, Q4=full year. Cash balances are instant amounts. | X8: Quarterly columns are YTD: Q1=3 months, Q2=6 months, Q3=9 months, Q4=full year. Cash balances are instant amounts. | Y8: Quarterly columns are YTD: Q1=3 months, Q2=6 months, Q3=9 months, Q4=full year. Cash balances are instant amounts. | Z8: Quarterly columns are YTD: Q1=3 months, Q2=6 months, Q3=9 months, Q4=full year. Cash balances are instant amounts. | AA8: Quarterly columns are YTD: Q1=3 months, Q2=6 months, Q3=9 months, Q4=full year. Cash balances are instant amounts.
A9: Net income (loss) | C9: 10316 | D9: 9601 | E9: 21053 | F9: 21048 | G9: 20899 | H9: 19868 | I9: 8017 | J9: 1675 | K9: -19233 | L9: 26 | N9: -2768 | O9: -1295 | P9: -985 | Q9: =IF(COUNT(J9)=1,J9,"") -> 1675 | R9: -437 | S9: -2091 | T9: -19080 | U9: =IF(COUNT(K9)=1,K9,"") -> -19233 | V9: -887 | W9: -3911 | X9: 359 | Y9: =IF(COUNT(L9)=1,L9,"") -> 26 | Z9: -4281 | AA9: -15129
A10: Depreciation | C10: 6266 | D10: 6752 | E10: 7520 | F10: 9204 | G10: 10482 | H10: 9953 | I10: 11128 | J10: 7847 | K10: 9951 | L10: 10757 | N10: 1901 | O10: 3733 | P10: 5753 | Q10: =IF(COUNT(J10)=1,J10,"") -> 7847 | R10: 2200 | S10: 4403 | T10: 7651 | U10: =IF(COUNT(K10)=1,K10,"") -> 9951 | V10: 2425 | W10: 5213 | X10: 7971 | Y10: =IF(COUNT(L10)=1,L10,"") -> 10757 | Z10: 2902 | AA10: 5891
A11: Share-based compensation | C11: 1444 | D11: 1358 | E11: 1546 | F11: 1705 | G11: 1854 | H11: 2036 | I11: 3128 | J11: 3229 | K11: 3410 | L11: 2434 | N11: 739 | O11: 1661 | P11: 2433 | Q11: =IF(COUNT(J11)=1,J11,"") -> 3229 | R11: 1179 | S11: 1959 | T11: 2759 | U11: =IF(COUNT(K11)=1,K11,"") -> 3410 | V11: 684 | W11: 1348 | X11: 1896 | Y11: =IF(COUNT(L11)=1,L11,"") -> 2434 | Z11: 621 | AA11: 1307
A12: Excess tax benefit from share-based payment arrangements (operating section) | C12: -121 | Q12: =IF(COUNT(J12)=1,J12,"") | U12: =IF(COUNT(K12)=1,K12,"") | Y12: =IF(COUNT(L12)=1,L12,"")
A13: Restructuring and other charges | C13: 1886 | D13: 384 | H13: 2626 | I13: 1074 | J13: -424 | K13: 3491 | L13: 476 | N13: 55 | O13: 255 | P13: 718 | Q13: =IF(COUNT(J13)=1,J13,"") -> -424 | R13: 348 | S13: 1291 | T13: 3626 | U13: =IF(COUNT(K13)=1,K13,"") -> 3491 | W13: 382 | X13: 372 | Y13: =IF(COUNT(L13)=1,L13,"") -> 476 | Z13: 3965 | AA13: 3967
A14: Amortization of intangibles | C14: 1524 | D14: 1377 | E14: 1565 | F14: 1622 | G14: 1757 | H14: 1839 | I14: 1907 | J14: 1755 | K14: 1428 | L14: 949 | N14: 465 | O14: 909 | P14: 1336 | Q14: =IF(COUNT(J14)=1,J14,"") -> 1755 | R14: 351 | S14: 717 | T14: 1081 | U14: =IF(COUNT(K14)=1,K14,"") -> 1428 | V14: 249 | W14: 474 | X14: 708 | Y14: =IF(COUNT(L14)=1,L14,"") -> 949 | Z14: 234 | AA14: 469
A15: (Gains) losses on equity investments, net | C15: -432 | D15: -2583 | E15: 155 | F15: -892 | G15: -1757 | H15: -1458 | I15: -4254 | J15: -42 | K15: -246 | L15: -514 | N15: -167 | O15: -146 | P15: 47 | Q15: =IF(COUNT(J15)=1,J15,"") -> -42 | R15: -208 | S15: -84 | T15: 75 | U15: =IF(COUNT(K15)=1,K15,"") -> -246 | V15: 112 | W15: -390 | X15: -611 | Y15: =IF(COUNT(L15)=1,L15,"") -> -514 | Z15: 72 | AA15: 111
A16: Loss on debt conversion and extinguishment | D16: 476 | E16: 260 | Q16: =IF(COUNT(J16)=1,J16,"") | U16: =IF(COUNT(K16)=1,K16,"") | Y16: =IF(COUNT(L16)=1,L16,"")
A17: Mark-to-market (gains) losses on Escrowed Shares / obligation to issue Escrowed Shares | L17: 1796 | Q17: =IF(COUNT(J17)=1,J17,"") | U17: =IF(COUNT(K17)=1,K17,"") | X17: 1687 | Y17: =IF(COUNT(L17)=1,L17,"") -> 1796 | Z17: 1090 | AA17: 13619
A18: (Gains) losses on divestitures | D18: -387 | E18: -497 | F18: -690 | G18: -30 | I18: -1059 | J18: 0 | K18: 0 | L18: -5323 | P18: 0 | Q18: =IF(COUNT(J18)=1,J18,"") -> 0 | U18: =IF(COUNT(K18)=1,K18,"") -> 0 | X18: -5355 | Y18: =IF(COUNT(L18)=1,L18,"") -> -5323
A19: Deferred taxes | C19: 257 | D19: 1548 | E19: -1749 | K19: 6132 | L19: 328 | Q19: =IF(COUNT(J19)=1,J19,"") | T19: 6368 | U19: =IF(COUNT(K19)=1,K19,"") -> 6132 | V19: 19 | W19: 106 | X19: 123 | Y19: =IF(COUNT(L19)=1,L19,"") -> 328 | Z19: -9 | AA19: -27
A20: Impairments and net (gain) loss on retirement of property, plant and equipment | K20: 2252 | L20: 515 | Q20: =IF(COUNT(J20)=1,J20,"") | T20: 2290 | U20: =IF(COUNT(K20)=1,K20,"") -> 2252 | W20: 482 | X20: 465 | Y20: =IF(COUNT(L20)=1,L20,"") -> 515 | AA20: 165
A21: Accounts receivable | C21: 65 | D21: -781 | E21: -1714 | F21: -935 | G21: 883 | H21: -2674 | I21: 5327 | J21: 731 | K21: -75 | L21: -449 | N21: 286 | O21: 1137 | P21: 1290 | Q21: =IF(COUNT(J21)=1,J21,"") -> 731 | R21: 80 | S21: 272 | T21: 282 | U21: =IF(COUNT(K21)=1,K21,"") -> -75 | V21: 414 | W21: 1004 | X21: 162 | Y21: =IF(COUNT(L21)=1,L21,"") -> -449 | Z21: -217 | AA21: -221
A22: Inventories | C22: 119 | D22: -1300 | E22: -214 | F22: -1481 | G22: -687 | H22: -2339 | I22: -2436 | J22: 2097 | K22: -1105 | L22: -138 | N22: 231 | O22: 1240 | P22: 1758 | Q22: =IF(COUNT(J22)=1,J22,"") -> 2097 | R22: -366 | S22: -116 | T22: -969 | U22: =IF(COUNT(K22)=1,K22,"") -> -1105 | V22: -83 | W22: 99 | X22: -9 | Y22: =IF(COUNT(L22)=1,L22,"") -> -138 | Z22: -808 | AA22: -874
A23: Accounts payable | C23: 182 | D23: 191 | E23: 211 | F23: 696 | G23: 412 | H23: 1190 | I23: -29 | J23: -801 | K23: 634 | L23: 297 | N23: -771 | O23: -1102 | P23: -1082 | Q23: =IF(COUNT(J23)=1,J23,"") -> -801 | R23: -386 | S23: 184 | T23: 566 | U23: =IF(COUNT(K23)=1,K23,"") -> 634 | V23: -240 | W23: 114 | X23: -281 | Y23: =IF(COUNT(L23)=1,L23,"") -> 297 | Z23: -142 | AA23: 310
A24: Accrued compensation and benefits | C24: -1595 | D24: -73 | E24: -260 | F24: 91 | G24: 463 | H24: 515 | I24: -1533 | J24: -614 | K24: -218 | L24: 788 | N24: -1560 | O24: -1340 | P24: -1171 | Q24: =IF(COUNT(J24)=1,J24,"") -> -614 | R24: -1289 | S24: -1309 | T24: 1384 | U24: =IF(COUNT(K24)=1,K24,"") -> -218 | V24: -741 | W24: 1022 | X24: 541 | Y24: =IF(COUNT(L24)=1,L24,"") -> 788 | Z24: -1175 | AA24: -372
A25: Prepaid supply agreements (FY2018-19 captioned: Customer deposits and prepaid supply agreements; FY2021-23: Prepaid customer supply agreements) | E25: 1367 | F25: -782 | G25: -181 | H25: -1583 | I25: -24 | J25: 0 | Q25: =IF(COUNT(J25)=1,J25,"") -> 0 | U25: =IF(COUNT(K25)=1,K25,"") | Y25: =IF(COUNT(L25)=1,L25,"")
A26: Income taxes payable and receivable / Income taxes | C26: 1382 | D26: 5230 | E26: 148 | F26: 885 | G26: 1620 | H26: -441 | I26: -4535 | J26: -3531 | K26: -356 | L26: -995 | N26: 1344 | O26: -2186 | P26: -2676 | Q26: =IF(COUNT(J26)=1,J26,"") -> -3531 | R26: -591 | S26: -2174 | T26: -930 | U26: =IF(COUNT(K26)=1,K26,"") -> -356 | V26: 67 | W26: -1338 | X26: -1196 | Y26: =IF(COUNT(L26)=1,L26,"") -> -995 | Z26: 169 | AA26: -477
A27: Other assets and liabilities | C27: 515 | D27: 317 | E27: 41 | F27: 2674 | G27: -331 | H27: 459 | I27: -1278 | J27: -451 | K27: 2223 | L27: -1250 | N27: -1540 | O27: -1843 | P27: -574 | Q27: =IF(COUNT(J27)=1,J27,"") -> -451 | R27: -2104 | S27: -1983 | T27: 20 | U27: =IF(COUNT(K27)=1,K27,"") -> 2223 | V27: -1206 | W27: -1742 | X27: -1423 | Y27: =IF(COUNT(L27)=1,L27,"") -> -1250 | Z27: -1325 | AA27: -637
A28: Total adjustments | C28: 11492 | D28: 12509 | E28: 8379 | F28: 12097 | G28: 14485 | H28: 10123 | I28: 7416 | J28: 9796 | K28: 27521 | L28: 9671 | N28: 983 | O28: 2318 | P28: 7832 | Q28: =IF(COUNT(J28)=1,J28,"") -> 9796 | R28: -786 | S28: 3160 | T28: 24203 | U28: =IF(COUNT(K28)=1,K28,"") -> 27521 | V28: 1700 | W28: 6774 | X28: 5050 | Y28: =IF(COUNT(L28)=1,L28,"") -> 9671 | Z28: 5377 | AA28: 23231
A29: Net cash provided by (used for) operating activities | C29: 21808 | D29: 22110 | E29: 29432 | F29: 33145 | G29: 35384 | H29: 29991 | I29: 15433 | J29: 11471 | K29: 8288 | L29: 9697 | N29: -1785 | O29: 1023 | P29: 6847 | Q29: =IF(COUNT(J29)=1,J29,"") -> 11471 | R29: -1223 | S29: 1069 | T29: 5123 | U29: =IF(COUNT(K29)=1,K29,"") -> 8288 | V29: 813 | W29: 2863 | X29: 5409 | Y29: =IF(COUNT(L29)=1,L29,"") -> 9697 | Z29: 1096 | AA29: 8102
A31: Investing cash flow | B31: Investing cash flow | C31: Investing cash flow | D31: Investing cash flow | E31: Investing cash flow | F31: Investing cash flow | G31: Investing cash flow | H31: Investing cash flow | I31: Investing cash flow | J31: Investing cash flow | K31: Investing cash flow | L31: Investing cash flow | M31: Investing cash flow | N31: Investing cash flow | O31: Investing cash flow | P31: Investing cash flow | Q31: Investing cash flow | R31: Investing cash flow | S31: Investing cash flow | T31: Investing cash flow | U31: Investing cash flow | V31: Investing cash flow | W31: Investing cash flow | X31: Investing cash flow | Y31: Investing cash flow | Z31: Investing cash flow | AA31: Investing cash flow
A32: Additions to property, plant and equipment | C32: -9625 | D32: -11778 | E32: -15181 | F32: -16213 | G32: -14259 | H32: -18733 | I32: -24844 | J32: -25750 | K32: -23944 | L32: -14646 | N32: -7413 | O32: -13301 | P32: -19054 | Q32: =IF(COUNT(J32)=1,J32,"") -> -25750 | R32: -5970 | S32: -11652 | T32: -18110 | U32: =IF(COUNT(K32)=1,K32,"") -> -23944 | V32: -5183 | W32: -8733 | X32: -11158 | Y32: =IF(COUNT(L32)=1,L32,"") -> -14646 | Z32: -3636 | AA32: -6192
A33: Additions to held for sale NAND property, plant and equipment | G33: -194 | H33: -1596 | I33: -206 | J33: 0 | Q33: =IF(COUNT(J33)=1,J33,"") -> 0 | U33: =IF(COUNT(K33)=1,K33,"") | Y33: =IF(COUNT(L33)=1,L33,"")
A34: Proceeds from capital-related government incentives | J34: 1011 | K34: 1936 | L34: 1577 | N34: 0 | O34: 49 | Q34: =IF(COUNT(J34)=1,J34,"") -> 1011 | R34: 592 | S34: 699 | T34: 725 | U34: =IF(COUNT(K34)=1,K34,"") -> 1936 | V34: 803 | W34: 964 | X34: 1018 | Y34: =IF(COUNT(L34)=1,L34,"") -> 1577 | Z34: 107 | AA34: 167
A35: Acquisitions, net of cash acquired | C35: -15470 | D35: -14499 | E35: -190 | F35: -1958 | G35: -837 | H35: -209 | K35: -82 | Q35: =IF(COUNT(J35)=1,J35,"") | U35: =IF(COUNT(K35)=1,K35,"") -> -82 | Y35: =IF(COUNT(L35)=1,L35,"") | Z35: -596 | AA35: -596
A36: Purchases of available-for-sale investments / debt investments | C36: -9269 | D36: -2764 | E36: -3843 | F36: -2268 | G36: -6862 | H36: -5051 | Q36: =IF(COUNT(J36)=1,J36,"") | U36: =IF(COUNT(K36)=1,K36,"") | Y36: =IF(COUNT(L36)=1,L36,"")
A37: Sales of available-for-sale investments / debt investments | C37: 3852 | D37: 6978 | E37: 195 | F37: 238 | Q37: =IF(COUNT(J37)=1,J37,"") | U37: =IF(COUNT(K37)=1,K37,"") | Y37: =IF(COUNT(L37)=1,L37,"")
A38: Maturities of available-for-sale investments / debt investments | C38: 5654 | D38: 3687 | E38: 2968 | F38: 3988 | Q38: =IF(COUNT(J38)=1,J38,"") | U38: =IF(COUNT(K38)=1,K38,"") | Y38: =IF(COUNT(L38)=1,L38,"")
A39: Maturities and sales of available-for-sale debt investments | G39: 6781 | H39: 6467 | Q39: =IF(COUNT(J39)=1,J39,"") | U39: =IF(COUNT(K39)=1,K39,"") | Y39: =IF(COUNT(L39)=1,L39,"")
