Workbook

Sheet Cover
A1: Guidewire Software, Inc. — Cover
A2: $ in thousands except per-share data | USD | as of 2026-09-17
A4: Guidewire Software, Inc.
A6: Ticker | B6: GWRE
A7: Exchange | B7: NYSE
A8: Currency | B8: USD
A9: Units | B9: In thousands except per-share data
A10: Reporting Framework | B10: US GAAP
A11: Fiscal Year End | B11: July 31
A12: SIC Code | B12: 7372 — Prepackaged Software
A14: Model Date | B14: 2026-09-17
A15: As-of Date | B15: 2026-07-31
A16: Annual Periods | B16: FY2017 – FY2026 (10 years)
A17: Quarterly Periods | B17: 1Q2024 – 3Q2026 (9 quarters)
A19: Sheet Directory
A20: IS | B20: Income Statement — as-reported with margins, growth, EPS
A21: BS | B21: Balance Sheet — full detail with balance check
A22: CF | B22: Cash Flow — all line items with FCF analytics
A23: DM | B23: Derived Metrics — profitability, returns, leverage, quality
A24: SEG | B24: Segments — geographic revenue breakdown
A25: NS | B25: Note Schedules — debt, intangibles, leases, revenue contracts
A27: Color Legend
A28: Blue | B28: Input values from SEC filings
A29: Black | B29: Formulas / Calculations
A30: Green | B30: Cross-sheet links
A31: Grey Italic | B31: Memo / analytical annotations

Sheet Income Statement
A1: Guidewire Software, Inc. — Income Statement
A2: $ in thousands except per-share data | USD | as of 2026-09-17
C3: FY2017 | D3: FY2018 | E3: FY2019 | F3: FY2020 | G3: FY2021 | H3: FY2022 | I3: FY2023 | J3: FY2024 | K3: FY2025 | L3: FY2026 | M3: · | N3: · | O3: · | P3: · | Q3: · | R3: 1Q2024 | S3: 2Q2024 | T3: 3Q2024 | U3: 1Q2025 | V3: 2Q2025 | W3: 3Q2025 | X3: 1Q2026 | Y3: 2Q2026 | Z3: 3Q2026
A6: 1. INCOME STATEMENT
A7: Subscription and Support Revenue | C7: 68643 | D7: 110738 | E7: 150474 | F7: 203473 | G7: 252358 | H7: 343708 | I7: 429667 | J7: 549087 | K7: 731296 | L7: 970885 | R7: 127627 | S7: 131642 | T7: 137970 | U7: 169742 | V7: 177838 | W7: 181823 | X7: 222203 | Y7: 237209 | Z7: 244738
A8: yoy | D8: =D7/C7-1 -> 0.61324534 | E8: =E7/D7-1 -> 0.35882895 | F8: =F7/E7-1 -> 0.35221367 | G8: =G7/F7-1 -> 0.24025301 | H8: =H7/G7-1 -> 0.36198575 | I8: =I7/H7-1 -> 0.2500931 | J8: =J7/I7-1 -> 0.27793617 | K8: =K7/J7-1 -> 0.33183995 | L8: =L7/K7-1 -> 0.32762247
A9: License Revenue | C9: 271462 | D9: 275606 | E9: 320272 | F9: 331554 | G9: 303792 | H9: 258631 | I9: 265593 | J9: 250176 | K9: 251935 | L9: 234578 | R9: 34025 | S9: 71083 | T9: 56210 | U9: 37370 | V9: 63694 | W9: 57233 | X9: 41967 | Y9: 59528 | Z9: 55996
A10: yoy | D10: =D9/C9-1 -> 0.015265488 | E10: =E9/D9-1 -> 0.16206469 | F10: =F9/E9-1 -> 0.035226308 | G10: =G9/F9-1 -> -0.083732967 | H10: =H9/G9-1 -> -0.14865763 | I10: =I9/H9-1 -> 0.02691866 | J10: =J9/I9-1 -> -0.058047464 | K10: =K9/J9-1 -> 0.0070310501 | L10: =L9/K9-1 -> -0.068894755
A11: Services Revenue | C11: 174179 | D11: 266505 | E11: 248768 | F11: 207280 | G11: 187117 | H11: 210275 | I11: 210081 | J11: 181234 | K11: 219228 | L11: 269900 | R11: 45755 | S11: 38172 | T11: 46498 | U11: 55789 | V11: 47948 | W11: 54452 | X11: 68469 | Y11: 62358 | Z11: 71807
A12: yoy | D12: =D11/C11-1 -> 0.5300639 | E12: =E11/D11-1 -> -0.066554098 | F12: =F11/E11-1 -> -0.16677386 | G12: =G11/F11-1 -> -0.097274218 | H12: =H11/G11-1 -> 0.12376214 | I12: =I11/H11-1 -> -0.00092260136 | J12: =J11/I11-1 -> -0.1373137 | K12: =K11/J11-1 -> 0.20964058 | L12: =L11/K11-1 -> 0.23113836
A13: Total Revenue | C13: 509533 | D13: 652849 | E13: 719514 | F13: 742307 | G13: 743267 | H13: 812614 | I13: 905341 | J13: 980497 | K13: 1202459 | L13: 1475363 | R13: 207407 | S13: 240897 | T13: 240678 | U13: 262901 | V13: 289480 | W13: 293508 | X13: 332639 | Y13: 359095 | Z13: 372541
A14: Revenue Growth YoY | D14: =IF(N(C13)=0,"",D13/C13-1) -> 0.28126932 | E14: =IF(N(D13)=0,"",E13/D13-1) -> 0.10211397 | F14: =IF(N(E13)=0,"",F13/E13-1) -> 0.031678327 | G14: =IF(N(F13)=0,"",G13/F13-1) -> 0.0012932655 | H14: =IF(N(G13)=0,"",H13/G13-1) -> 0.093300254 | I14: =IF(N(H13)=0,"",I13/H13-1) -> 0.11410953 | J14: =IF(N(I13)=0,"",J13/I13-1) -> 0.083014025 | K14: =IF(N(J13)=0,"",K13/J13-1) -> 0.22637703 | L14: =IF(N(K13)=0,"",L13/K13-1) -> 0.22695493 | V14: =IF(N(R13)=0,"",V13/R13-1) -> 0.39570988 | W14: =IF(N(S13)=0,"",W13/S13-1) -> 0.21839624 | X14: =IF(N(T13)=0,"",X13/T13-1) -> 0.38209143 | Y14: =IF(N(U13)=0,"",Y13/U13-1) -> 0.36589439 | Z14: =IF(N(V13)=0,"",Z13/V13-1) -> 0.28693174
A16: Cost of Revenue - Subscription and Support | C16: 13397 | D16: 45134 | E16: 73597 | F16: 117158 | G16: 157488 | H16: 202832 | I16: 210507 | J16: 204794 | K16: 235106 | L16: 265203 | R16: 48054 | S16: 49934 | T16: 51185 | U16: 54024 | V16: 59096 | W16: 57411 | X16: 63927 | Y16: 63928 | Z16: 67882
A17: yoy | D17: =D16/C16-1 -> 2.3689632 | E17: =E16/D16-1 -> 0.63063323 | F17: =F16/E16-1 -> 0.59188554 | G17: =G16/F16-1 -> 0.34423599 | H17: =H16/G16-1 -> 0.28792035 | I17: =I16/H16-1 -> 0.037839197 | J17: =J16/I16-1 -> -0.02713924 | K17: =K16/J16-1 -> 0.14801215 | L17: =L16/K16-1 -> 0.1280146
A18: Cost of Revenue - License | C18: 17046 | D18: 5101 | E18: 7700 | F18: 11566 | G18: 10569 | H18: 8754 | I18: 6488 | J18: 4536 | K18: 3624 | L18: 1982 | R18: 1219 | S18: 1483 | T18: 837 | U18: 881 | V18: 942 | W18: 892 | X18: 644 | Y18: 442 | Z18: 374
A19: yoy | D19: =D18/C18-1 -> -0.70075091 | E19: =E18/D18-1 -> 0.50950794 | F19: =F18/E18-1 -> 0.50207792 | G19: =G18/F18-1 -> -0.086200934 | H19: =H18/G18-1 -> -0.17172864 | I19: =I18/H18-1 -> -0.2588531 | J19: =J18/I18-1 -> -0.30086313 | K19: =K18/J18-1 -> -0.2010582 | L19: =L18/K18-1 -> -0.45309051
A20: Cost of Revenue - Services | C20: 161116 | D20: 246548 | E20: 243053 | F20: 209291 | G20: 185650 | H20: 223852 | I20: 230135 | J20: 187806 | K20: 211676 | L20: 260810 | R20: 45842 | S20: 47074 | T20: 46429 | U20: 49604 | V20: 50290 | W20: 52507 | X20: 58546 | Y20: 63205 | Z20: 67639
A21: yoy | D21: =D20/C20-1 -> 0.5302515 | E21: =E20/D20-1 -> -0.014175739 | F21: =F20/E20-1 -> -0.13890797 | G21: =G20/F20-1 -> -0.11295756 | H21: =H20/G20-1 -> 0.20577431 | I21: =I20/H20-1 -> 0.028067652 | J21: =J20/I20-1 -> -0.18393117 | K21: =K20/J20-1 -> 0.12709924 | L21: =L20/K20-1 -> 0.2321189
A22: Total Cost of Revenue | C22: 191559 | D22: 296783 | E22: 324350 | F22: 338015 | G22: 353707 | H22: 435438 | I22: 447130 | J22: 397136 | K22: 450406 | L22: 527995 | R22: 95115 | S22: 98491 | T22: 98451 | U22: 104509 | V22: 110328 | W22: 110810 | X22: 123117 | Y22: 127574 | Z22: 135896
A24: Gross Profit - Subscription and Support | C24: 55246 | D24: 65604 | E24: 76877 | F24: 86315 | G24: 94870 | H24: 140876 | I24: 219160 | J24: 344293 | K24: 496190 | L24: 705682 | R24: 79573 | S24: 81708 | T24: 86785 | U24: 115718 | V24: 118742 | W24: 124412 | X24: 158276 | Y24: 173281 | Z24: 176856
A25: yoy | D25: =D24/C24-1 -> 0.18748869 | E25: =E24/D24-1 -> 0.17183403 | F25: =F24/E24-1 -> 0.12276754 | G25: =G24/F24-1 -> 0.099113711 | H25: =H24/G24-1 -> 0.48493728 | I25: =I24/H24-1 -> 0.55569437 | J25: =J24/I24-1 -> 0.57096642 | K25: =K24/J24-1 -> 0.44118527 | L25: =L24/K24-1 -> 0.42220117
A26: Gross Profit - License | C26: 254416 | D26: 270505 | E26: 312572 | F26: 319988 | G26: 293223 | H26: 249877 | I26: 259105 | J26: 245640 | K26: 248311 | L26: 232596 | R26: 32806 | S26: 69600 | T26: 55373 | U26: 36489 | V26: 62752 | W26: 56341 | X26: 41323 | Y26: 59086 | Z26: 55622
A27: yoy | D27: =D26/C26-1 -> 0.063238947 | E27: =E26/D26-1 -> 0.15551284 | F27: =F26/E26-1 -> 0.023725734 | G27: =G26/F26-1 -> -0.083643762 | H27: =H26/G26-1 -> -0.14782606 | I27: =I26/H26-1 -> 0.03693017 | J27: =J26/I26-1 -> -0.051967349 | K27: =K26/J26-1 -> 0.010873636 | L27: =L26/K26-1 -> -0.063287571
A28: Gross Profit - Services | C28: 13063 | D28: 19957 | E28: 5715 | F28: -2011 | G28: 1467 | H28: -13577 | I28: -20054 | J28: -6572 | K28: 7552 | L28: 9090 | R28: -87 | S28: -8902 | T28: 69 | U28: 6185 | V28: -2342 | W28: 1945 | X28: 9923 | Y28: -847 | Z28: 4167
A29: yoy | D29: =D28/C28-1 -> 0.52775013 | E29: =E28/D28-1 -> -0.71363431 | F29: =F28/E28-1 -> -1.351881 | G29: =G28/F28-1 -> -1.7294878 | H29: =H28/G28-1 -> -10.254942 | I29: =I28/H28-1 -> 0.47705679 | J29: =J28/I28-1 -> -0.67228483 | K29: =K28/J28-1 -> -2.1491175 | L29: =L28/K28-1 -> 0.20365466
A30: Total Gross Profit | C30: 317974 | D30: 356066 | E30: 395164 | F30: 404292 | G30: 389560 | H30: 377176 | I30: 458211 | J30: 583361 | K30: 752053 | L30: 947368 | R30: 112292 | S30: 142406 | T30: 142227 | U30: 158392 | V30: 179152 | W30: 182698 | X30: 209522 | Y30: 231521 | Z30: 236645
A31: Gross Margin | C31: =C30/C13 -> 0.62404987 | D31: =D30/D13 -> 0.5454033 | E31: =E30/E13 -> 0.54920961 | F31: =F30/F13 -> 0.54464258 | G31: =G30/G13 -> 0.52411852 | H31: =H30/H13 -> 0.46415149 | I31: =I30/I13 -> 0.50611979 | J31: =J30/J13 -> 0.59496459 | ... L31: =L30/L13 -> 0.64212536 | R31: =R30/R13 -> 0.54140892 | S31: =S30/S13 -> 0.59114891 | T31: =T30/T13 -> 0.59094309 | U31: =U30/U13 -> 0.60247774 | V31: =V30/V13 -> 0.61887522 | W31: =W30/W13 -> 0.62246344 | X31: =X30/X13 -> 0.62987804 | Y31: =Y30/Y13 -> 0.64473468 | Z31: =Z30/Z13 -> 0.63521867
A33: Research and Development | C33: 130323 | D33: 171657 | E33: 188541 | F33: 200575 | G33: 201465 | H33: 229230 | I33: 249746 | J33: 269381 | K33: 296160 | L33: 340097 | R33: 62469 | S33: 65458 | T33: 66134 | U33: 68880 | V33: 70268 | W33: 72915 | X33: 78317 | Y33: 83324 | Z33: 87868
A34: Sales and Marketing | C34: 109239 | D34: 124117 | E34: 130751 | F34: 142420 | G34: 150521 | H34: 182620 | I34: 188224 | J34: 199033 | K34: 230346 | L34: 258937 | R34: 44581 | S34: 49181 | T34: 50487 | U34: 51478 | V34: 55452 | W34: 57768 | X34: 64258 | Y34: 61475 | Z34: 68201
A35: General and Administrative | C35: 56551 | D35: 75916 | E35: 74401 | F35: 85183 | G35: 143158 | H35: 164773 | I35: 169731 | J35: 167520 | K35: 184479 | L35: 198460 | R35: 39023 | S35: 40177 | T35: 42302 | U35: 42754 | V35: 41709 | W35: 47547 | X35: 48469 | Y35: 48281 | Z35: 49939
A36: Total Operating Expenses | C36: 296113 | D36: 371690 | E36: 393693 | F36: 428178 | G36: 495144 | H36: 576623 | I36: 607701 | J36: 635934 | K36: 710985 | L36: 797494 | R36: 146073 | S36: 154816 | T36: 158923 | U36: 163112 | V36: 167429 | W36: 178230 | X36: 191044 | Y36: 193080 | Z36: 206008
A38: Income (Loss) from Operations | C38: 21861 | D38: -15624 | E38: 1471 | F38: -23886 | G38: -105584 | H38: -199447 | I38: -149490 | J38: -52573 | K38: 41068 | L38: 149874 | R38: -33781 | S38: -12410 | T38: -16696 | U38: -4720 | V38: 11723 | W38: 4468 | X38: 18478 | Y38: 38441 | Z38: 30637
A39: Operating Margin | C39: =C38/C13 -> 0.042903992 | D39: =D38/D13 -> -0.023932027 | E39: =E38/E13 -> 0.0020444355 | F39: =F38/F13 -> -0.032178061 | G39: =G38/G13 -> -0.14205393 | H39: =H38/H13 -> -0.24543879 | I39: =I38/I13 -> -0.1651201 | J39: =J38/J13 -> -0.053618726 | ... L39: =L38/L13 -> 0.10158449 | R39: =R38/R13 -> -0.162873 | S39: =S38/S13 -> -0.051515793 | T39: =T38/T13 -> -0.069370694 | U39: =U38/U13 -> -0.017953526 | V39: =V38/V13 -> 0.040496753 | W39: =W38/W13 -> 0.015222754 | X39: =X38/X13 -> 0.05554971 | Y39: =Y38/Y13 -> 0.10704967 | Z39: =Z38/Z13 -> 0.082237928
A41: Interest Income | C41: 5867 | D41: 13281 | E41: 30182 | F41: 24705 | G41: 7395 | H41: 6277 | I41: 24389 | J41: 43478 | K41: 56625 | L41: 48564 | R41: 10613 | S41: 10290 | T41: 10824 | U41: 13606 | V41: 15722 | W41: 13794 | X41: 14650 | Y41: 12487 | Z41: 11295
A42: Interest Expense | C42: -13 | D42: -6442 | E42: -17334 | F42: -17945 | G42: -18711 | H42: -19446 | I42: -6716 | J42: -6738 | K42: -13211 | L42: -13324 | R42: -1683 | S42: -1692 | T42: -1686 | U42: -2062 | V42: -4183 | W42: -3668 | X42: -3312 | Y42: -3334 | Z42: -3318
A43: Other Income (Expense), Net | C43: 811 | D43: 509 | E43: -1867 | F43: -7205 | G43: 12619 | H43: -17099 | I43: -2277 | J43: -11005 | K43: -35087 | L43: -20997 | R43: -13742 | S43: 10776 | T43: -6535 | U43: -4055 | V43: -66289 | W43: 34074 | X43: -5314 | Y43: 26958 | Z43: -18854
A44: Income (Loss) Before Income Taxes | C44: 28526 | D44: -8276 | E44: 12452 | F44: -24331 | G44: -104281 | H44: -229715 | I44: -134094 | J44: -26838 | K44: 49395 | L44: 164117 | R44: -38593 | S44: 6964 | T44: -14093 | U44: 2769 | V44: -43027 | W44: 48668 | X44: 24502 | Y44: 74552 | Z44: 19760
A45: Provision for (Benefit from) Income Taxes | C45: 10454 | D45: 18467 | E45: -8280 | F45: 2867 | G45: -37774 | H45: -49284 | I45: -22239 | J45: -20735 | K45: -20409 | L45: 24834 | R45: -11522 | S45: -2723 | T45: -8615 | U45: -6370 | V45: -5750 | W45: 2677 | X45: -6806 | Y45: 14442 | Z45: 3289
A46: Net Income (Loss) | C46: 18072 | D46: -26743 | E46: 20732 | F46: -27198 | G46: -66507 | H46: -180431 | I46: -111855 | J46: -6103 | K46: 69804 | L46: 139283 | R46: -27071 | S46: 9687 | T46: -5478 | U46: 9139 | V46: -37277 | W46: 45991 | X46: 31308 | Y46: 60110 | Z46: 16471
A47: Net Margin | C47: =C46/C13 -> 0.035467771 | D47: =D46/D13 -> -0.040963531 | E47: =E46/E13 -> 0.028813894 | F47: =F46/F13 -> -0.036639827 | G47: =G46/G13 -> -0.089479285 | H47: =H46/H13 -> -0.22203777 | I47: =I46/I13 -> -0.12355013 | J47: =J46/J13 -> -0.0062243944 | ... L47: =L46/L13 -> 0.094405919 | R47: =R46/R13 -> -0.13052115 | S47: =S46/S13 -> 0.040212207 | T47: =T46/T13 -> -0.022760701 | U47: =U46/U13 -> 0.034762135 | V47: =V46/V13 -> -0.12877228 | W47: =W46/W13 -> 0.1566942 | X47: =X46/X13 -> 0.094120052 | Y47: =Y46/Y13 -> 0.16739303 | Z47: =Z46/Z13 -> 0.044212583
A48: Net Income Growth YoY | D48: =IF(N(C46)=0,"",D46/C46-1) -> -2.479803 | E48: =IF(N(D46)=0,"",E46/D46-1) -> -1.7752309 | F48: =IF(N(E46)=0,"",F46/E46-1) -> -2.311885 | G48: =IF(N(F46)=0,"",G46/F46-1) -> 1.4452901 | H48: =IF(N(G46)=0,"",H46/G46-1) -> 1.7129625 | I48: =IF(N(H46)=0,"",I46/H46-1) -> -0.38006773 | J48: =IF(N(I46)=0,"",J46/I46-1) -> -0.94543829 | K48: =IF(N(J46)=0,"",K46/J46-1) -> -12.437654 | L48: =IF(N(K46)=0,"",L46/K46-1) -> 0.99534411 | V48: =IF(N(R46)=0,"",V46/R46-1) -> 0.37700861 | W48: =IF(N(S46)=0,"",W46/S46-1) -> 3.7477031 | X48: =IF(N(T46)=0,"",X46/T46-1) -> -6.7152245 | Y48: =IF(N(U46)=0,"",Y46/U46-1) -> 5.5773061 | Z48: =IF(N(V46)=0,"",Z46/V46-1) -> -1.4418542
A50: 2. EPS & SHARE COUNT
A51: Basic EPS | C51: 0.24 | D51: -0.34 | E51: 0.25 | F51: -0.33 | G51: -0.79 | H51: -2.16 | I51: -1.36 | J51: -0.07 | K51: 0.83 | L51: 1.65 | R51: -0.33 | S51: 0.12 | T51: -0.07 | U51: 0.11 | V51: -0.45 | W51: 0.55 | X51: 0.37 | Y51: 0.71 | Z51: 0.2
A52: Diluted EPS | C52: 0.24 | D52: -0.34 | E52: 0.25 | F52: -0.33 | G52: -0.79 | H52: -2.16 | I52: -1.36 | J52: -0.07 | K52: 0.81 | L52: 1.63 | R52: -0.33 | S52: 0.12 | T52: -0.07 | U52: 0.11 | V52: -0.45 | W52: 0.54 | X52: 0.36 | Y52: 0.7 | Z52: 0.19
A53: Weighted Avg Shares - Basic | C53: 73994577 | D53: 77709592 | E53: 81447998 | F53: 82855392 | G53: 83577375 | H53: 83569517 | I53: 82176629 | J53: 82291483 | K53: 83846793 | L53: 84186951 | R53: 81690912 | S53: 82133632 | T53: 82500109 | U53: 83276236 | V53: 83705700 | W53: 84044661 | X53: 84780201 | Y53: 84858179 | Z53: 84241069
A54: Weighted Avg Shares - Diluted | C54: 75328343 | D54: 77709592 | E54: 82681214 | F54: 82855392 | G54: 83577375 | H54: 83569517 | I54: 82176629 | J54: 82291483 | K54: 85911653 | L54: 85405177 | R54: 81690912 | S54: 83305080 | T54: 82500109 | U54: 85960868 | V54: 83705700 | W54: 85880643 | X54: 86451737 | Y54: 86116567 | Z54: 85065999
A56: 3. MARGINS & GROWTH
A57: Subscription & Support % of Revenue | C57: =C7/C13 -> 0.13471748 | D57: =D7/D13 -> 0.16962268 | E57: =E7/E13 -> 0.20913283 | F57: =F7/F13 -> 0.27410896 | G57: =G7/G13 -> 0.33952537 | H57: =H7/H13 -> 0.42296589 | I57: =I7/I13 -> 0.47459134 | J57: =J7/J13 -> 0.56000885 | ... L57: =L7/L13 -> 0.65806517 | R57: =R7/R13 -> 0.61534567 | S57: =S7/S13 -> 0.54646592 | T57: =T7/T13 -> 0.57325555 | U57: =U7/U13 -> 0.64564988 | V57: =V7/V13 -> 0.61433605 | W57: =W7/W13 -> 0.61948226 | X57: =X7/X13 -> 0.66800044 | Y57: =Y7/Y13 -> 0.6605745 | Z57: =Z7/Z13 -> 0.65694246
A58: License % of Revenue | C58: =C9/C13 -> 0.53276628 | D58: =D9/D13 -> 0.42215888 | E58: =E9/E13 -> 0.44512268 | F58: =F9/F13 -> 0.44665347 | G58: =G9/G13 -> 0.40872526 | H58: =H9/H13 -> 0.31827042 | I58: =I9/I13 -> 0.29336239 | J58: =J9/J13 -> 0.25515223 | ... L58: =L9/L13 -> 0.1589968 | R58: =R9/R13 -> 0.16404943 | S58: =S9/S13 -> 0.29507632 | T58: =T9/T13 -> 0.23354856 | U58: =U9/U13 -> 0.14214476 | V58: =V9/V13 -> 0.22002902 | W58: =W9/W13 -> 0.19499639 | X58: =X9/X13 -> 0.1261638 | Y58: =Y9/Y13 -> 0.16577229 | Z58: =Z9/Z13 -> 0.15030829
A59: Services % of Revenue | C59: =C11/C13 -> 0.34184047 | D59: =D11/D13 -> 0.40821844 | E59: =E11/E13 -> 0.34574449 | F59: =F11/F13 -> 0.27923757 | G59: =G11/G13 -> 0.25174937 | H59: =H11/H13 -> 0.25876369 | I59: =I11/I13 -> 0.23204627 | J59: =J11/J13 -> 0.18483891 | ... L59: =L11/L13 -> 0.18293803 | R59: =R11/R13 -> 0.2206049 | S59: =S11/S13 -> 0.15845776 | T59: =T11/T13 -> 0.19319589 | U59: =U11/U13 -> 0.21220535 | V59: =V11/V13 -> 0.16563493 | W59: =W11/W13 -> 0.18552135 | X59: =X11/X13 -> 0.20583576 | Y59: =Y11/Y13 -> 0.17365321 | Z59: =Z11/Z13 -> 0.19274925
A60: Subscription & Support Gross Margin | C60: =C24/C7 -> 0.80483079 | D60: =D24/D7 -> 0.59242536 | E60: =E24/E7 -> 0.51089889 | F60: =F24/F7 -> 0.42420862 | G60: =G24/G7 -> 0.37593419 | H60: =H24/H7 -> 0.40987117 | I60: =I24/I7 -> 0.51006943 | J60: =J24/J7 -> 0.62702814 | ... L60: =L24/L7 -> 0.72684406 | R60: =R24/R7 -> 0.62348092 | S60: =S24/S7 -> 0.62068337 | T60: =T24/T7 -> 0.62901355 | U60: =U24/U7 -> 0.68172874 | V60: =V24/V7 -> 0.66769757 | W60: =W24/W7 -> 0.68424787 | X60: =X24/X7 -> 0.71230361 | Y60: =Y24/Y7 -> 0.73049926 | Z60: =Z24/Z7 -> 0.722634
A61: License Gross Margin | C61: =C26/C9 -> 0.93720668 | D61: =D26/D9 -> 0.98149169 | E61: =E26/E9 -> 0.97595794 | F61: =F26/F9 -> 0.96511579 | G61: =G26/G9 -> 0.96520975 | H61: =H26/H9 -> 0.96615255 | I61: =I26/I9 -> 0.97557165 | J61: =J26/J9 -> 0.98186876 | ... L61: =L26/L9 -> 0.99155078 | R61: =R26/R9 -> 0.9641734 | S61: =S26/S9 -> 0.97913707 | T61: =T26/T9 -> 0.98510941 | U61: =U26/U9 -> 0.97642494 | V61: =V26/V9 -> 0.98521054 | W61: =W26/W9 -> 0.98441459 | X61: =X26/X9 -> 0.98465461 | Y61: =Y26/Y9 -> 0.99257492 | Z61: =Z26/Z9 -> 0.99332095
A62: Services Gross Margin | C62: =C28/C11 -> 0.07499756 | D62: =D28/D11 -> 0.074884149 | E62: =E28/E11 -> 0.022973212 | F62: =F28/F11 -> -0.0097018526 | G62: =G28/G11 -> 0.0078400145 | H62: =H28/H11 -> -0.064567828 | I62: =I28/I11 -> -0.095458418 | J62: =J28/J11 -> -0.036262511 | ... L62: =L28/L11 -> 0.03367914 | R62: =R28/R11 -> -0.0019014315 | S62: =S28/S11 -> -0.23320759 | T62: =T28/T11 -> 0.0014839348 | U62: =U28/U11 -> 0.11086415 | V62: =V28/V11 -> -0.048844582 | W62: =W28/W11 -> 0.035719533 | X62: =X28/X11 -> 0.1449269 | Y62: =Y28/Y11 -> -0.01358286 | Z62: =Z28/Z11 -> 0.058030554
A63: R&D % of Revenue | C63: =C33/C13 -> 0.2557695 | D63: =D33/D13 -> 0.26293523 | E63: =E33/E13 -> 0.26203938 | F63: =F33/F13 -> 0.27020492 | G63: =G33/G13 -> 0.27105334 | H63: =H33/H13 -> 0.28208965 | I63: =I33/I13 -> 0.27585849 | J63: =J33/J13 -> 0.27473924 | ... L63: =L33/L13 -> 0.23051751 | R63: =R33/R13 -> 0.30119041 | S63: =S33/S13 -> 0.27172609 | T63: =T33/T13 -> 0.27478207 | U63: =U33/U13 -> 0.26199976 | V63: =V33/V13 -> 0.2427387 | W63: =W33/W13 -> 0.24842594 | X63: =X33/X13 -> 0.23544142 | Y63: =Y33/Y13 -> 0.23203888 | Z63: =Z33/Z13 -> 0.23586129
A64: S&M % of Revenue | C64: =C34/C13 -> 0.21439043 | D64: =D34/D13 -> 0.19011594 | E64: =E34/E13 -> 0.18172127 | F64: =F34/F13 -> 0.19186132 | G64: =G34/G13 -> 0.20251269 | H64: =H34/H13 -> 0.22473155 | I64: =I34/I13 -> 0.20790398 | J64: =J34/J13 -> 0.20299195 | ... L64: =L34/L13 -> 0.17550732 | R64: =R34/R13 -> 0.21494453 | S64: =S34/S13 -> 0.20415779 | T64: =T34/T13 -> 0.2097699 | U64: =U34/U13 -> 0.19580755 | V64: =V34/V13 -> 0.19155728 | W64: =W34/W13 -> 0.19681917 | X64: =X34/X13 -> 0.19317639 | Y64: =Y34/Y13 -> 0.17119425 | Z64: =Z34/Z13 -> 0.18306978
A65: G&A % of Revenue | C65: =C35/C13 -> 0.11098594 | D65: =D35/D13 -> 0.11628416 | E65: =E35/E13 -> 0.10340452 | F65: =F35/F13 -> 0.11475441 | G65: =G35/G13 -> 0.19260643 | H65: =H35/H13 -> 0.20276909 | I65: =I35/I13 -> 0.18747743 | J65: =J35/J13 -> 0.17085213 | ... L65: =L35/L13 -> 0.13451605 | R65: =R35/R13 -> 0.18814698 | S65: =S35/S13 -> 0.16678082 | T65: =T35/T13 -> 0.17576181 | U65: =U35/U13 -> 0.16262395 | V65: =V35/V13 -> 0.14408249 | W65: =W35/W13 -> 0.16199558 | X65: =X35/X13 -> 0.14571052 | Y65: =Y35/Y13 -> 0.13445189 | Z65: =Z35/Z13 -> 0.13404968
A66: Total Opex % of Revenue | C66: =C36/C13 -> 0.58114587 | D66: =D36/D13 -> 0.56933533 | E66: =E36/E13 -> 0.54716517 | F66: =F36/F13 -> 0.57682064 | G66: =G36/G13 -> 0.66617245 | H66: =H36/H13 -> 0.70959029 | I66: =I36/I13 -> 0.6712399 | J66: =J36/J13 -> 0.64858332 | ... L66: =L36/L13 -> 0.54054087 | R66: =R36/R13 -> 0.70428192 | S66: =S36/S13 -> 0.64266471 | T66: =T36/T13 -> 0.66031378 | U66: =U36/U13 -> 0.62043127 | V66: =V36/V13 -> 0.57837847 | W66: =W36/W13 -> 0.60724069 | X66: =X36/X13 -> 0.57432833 | Y66: =Y36/Y13 -> 0.53768501 | Z66: =Z36/Z13 -> 0.55298075
A67: Sub & Support Revenue Growth YoY | D67: =IF(N(C7)=0,"",D7/C7-1) -> 0.61324534 | E67: =IF(N(D7)=0,"",E7/D7-1) -> 0.35882895 | F67: =IF(N(E7)=0,"",F7/E7-1) -> 0.35221367 | G67: =IF(N(F7)=0,"",G7/F7-1) -> 0.24025301 | H67: =IF(N(G7)=0,"",H7/G7-1) -> 0.36198575 | I67: =IF(N(H7)=0,"",I7/H7-1) -> 0.2500931 | J67: =IF(N(I7)=0,"",J7/I7-1) -> 0.27793617 | K67: =IF(N(J7)=0,"",K7/J7-1) -> 0.33183995 | L67: =IF(N(K7)=0,"",L7/K7-1) -> 0.32762247 | V67: =IF(N(R7)=0,"",V7/R7-1) -> 0.39341989 | W67: =IF(N(S7)=0,"",W7/S7-1) -> 0.38119293 | X67: =IF(N(T7)=0,"",X7/T7-1) -> 0.61051678 | Y67: =IF(N(U7)=0,"",Y7/U7-1) -> 0.39746792 | Z67: =IF(N(V7)=0,"",Z7/V7-1) -> 0.37618507
A68: License Revenue Growth YoY | D68: =IF(N(C9)=0,"",D9/C9-1) -> 0.015265488 | E68: =IF(N(D9)=0,"",E9/D9-1) -> 0.16206469 | F68: =IF(N(E9)=0,"",F9/E9-1) -> 0.035226308 | G68: =IF(N(F9)=0,"",G9/F9-1) -> -0.083732967 | H68: =IF(N(G9)=0,"",H9/G9-1) -> -0.14865763 | I68: =IF(N(H9)=0,"",I9/H9-1) -> 0.02691866 | J68: =IF(N(I9)=0,"",J9/I9-1) -> -0.058047464 | K68: =IF(N(J9)=0,"",K9/J9-1) -> 0.0070310501 | L68: =IF(N(K9)=0,"",L9/K9-1) -> -0.068894755 | V68: =IF(N(R9)=0,"",V9/R9-1) -> 0.87197649 | W68: =IF(N(S9)=0,"",W9/S9-1) -> -0.19484265 | X68: =IF(N(T9)=0,"",X9/T9-1) -> -0.25338908 | Y68: =IF(N(U9)=0,"",Y9/U9-1) -> 0.59293551 | Z68: =IF(N(V9)=0,"",Z9/V9-1) -> -0.12085911
A69: Services Revenue Growth YoY | D69: =IF(N(C11)=0,"",D11/C11-1) -> 0.5300639 | E69: =IF(N(D11)=0,"",E11/D11-1) -> -0.066554098 | F69: =IF(N(E11)=0,"",F11/E11-1) -> -0.16677386 | G69: =IF(N(F11)=0,"",G11/F11-1) -> -0.097274218 | H69: =IF(N(G11)=0,"",H11/G11-1) -> 0.12376214 | I69: =IF(N(H11)=0,"",I11/H11-1) -> -0.00092260136 | J69: =IF(N(I11)=0,"",J11/I11-1) -> -0.1373137 | K69: =IF(N(J11)=0,"",K11/J11-1) -> 0.20964058 | L69: =IF(N(K11)=0,"",L11/K11-1) -> 0.23113836 | V69: =IF(N(R11)=0,"",V11/R11-1) -> 0.047929188 | W69: =IF(N(S11)=0,"",W11/S11-1) -> 0.42649062 | X69: =IF(N(T11)=0,"",X11/T11-1) -> 0.47251495 | Y69: =IF(N(U11)=0,"",Y11/U11-1) -> 0.11774723 | Z69: =IF(N(V11)=0,"",Z11/V11-1) -> 0.49760157
A70: Effective Tax Rate | C70: =C45/C44 -> 0.36647269 | D70: =D45/D44 -> -2.231392 | E70: =E45/E44 -> -0.66495342 | F70: =F45/F44 -> -0.11783322 | G70: =G45/G44 -> 0.36223281 | H70: =H45/H44 -> 0.21454411 | I70: =I45/I44 -> 0.16584635 | J70: =J45/J44 -> 0.77259855 | ... L70: =L45/L44 -> 0.15131888 | R70: =R45/R44 -> 0.29855155 | S70: =S45/S44 -> -0.39101091 | T70: =T45/T44 -> 0.61129639 | U70: =U45/U44 -> -2.3004695 | V70: =V45/V44 -> 0.13363702 | W70: =W45/W44 -> 0.055005342 | X70: =X45/X44 -> -0.27777324 | Y70: =Y45/Y44 -> 0.19371714 | Z70: =Z45/Z44 -> 0.16644737
A72: 4. IS CHECK
A73: IS Check (should be 0) | C73: =C13-C22-C36-C38 -> 0 | D73: =D13-D22-D36-D38 -> 0 | E73: =E13-E22-E36-E38 -> 0 | F73: =F13-F22-F36-F38 -> 0 | G73: =G13-G22-G36-G38 -> 0 | H73: =H13-H22-H36-H38 -> 0 | I73: =I13-I22-I36-I38 -> 0 | J73: =J13-J22-J36-J38 -> 0 | ... L73: =L13-L22-L36-L38 -> 0 | R73: =R13-R22-R36-R38 -> 0 | S73: =S13-S22-S36-S38 -> 0 | T73: =T13-T22-T36-T38 -> 0 | U73: =U13-U22-U36-U38 -> 0 | V73: =V13-V22-V36-V38 -> 0 | W73: =W13-W22-W36-W38 -> 0 | X73: =X13-X22-X36-X38 -> 0 | Y73: =Y13-Y22-Y36-Y38 -> 0 | Z73: =Z13-Z22-Z36-Z38 -> 0

Sheet Balance Sheet
A1: Guidewire Software, Inc. — Balance Sheet
A2: $ in thousands except per-share data | USD | as of 2026-09-17
C3: FY2017 | D3: FY2018 | E3: FY2019 | F3: FY2020 | G3: FY2021 | H3: FY2022 | I3: FY2023 | J3: FY2024 | K3: FY2025 | L3: FY2026 | M3: · | N3: · | O3: · | P3: · | Q3: · | R3: 1Q2024 | S3: 2Q2024 | T3: 3Q2024 | U3: 1Q2025 | V3: 2Q2025 | W3: 3Q2025 | X3: 1Q2026 | Y3: 2Q2026 | Z3: 3Q2026
A6: 1. BALANCE SHEET
A7: Cash and Cash Equivalents | C7: 263176 | D7: 437140 | E7: 254101 | F7: 366969 | G7: 384910 | H7: 606303 | I7: 401813 | J7: 547992 | K7: 697902 | L7: 372887 | R7: 301419 | S7: 349989 | T7: 359600 | U7: 823562 | V7: 697488 | W7: 510321 | X7: 492038 | Y7: 407946 | Z7: 294634
A8: Short-term Investments | C8: 310027 | D8: 630008 | E8: 870136 | F8: 766527 | G8: 734517 | H8: 369865 | I8: 396872 | J8: 455576 | K8: 451541 | L8: 380175 | R8: 411528 | S8: 427634 | T8: 422691 | U8: 514767 | V8: 471473 | W8: 410116 | X8: 519861 | Y8: 511221 | Z8: 454900
A9: Accounts Receivable, Net | C9: 79433 | D9: 124849 | E9: 138443 | F9: 114242 | G9: 104068 | H9: 143797 | I9: 151034 | J9: 137339 | K9: 140639 | L9: 193720 | R9: 93083 | S9: 128242 | T9: 104344 | U9: 97475 | V9: 123001 | W9: 147296 | X9: 94600 | Y9: 162937 | Z9: 138853
A10: Unbilled Accounts Receivable, Net (Current) | C10: 0 | D10: 0 | E10: 36728 | F10: 49491 | G10: 79061 | H10: 71515 | I10: 87752 | J10: 87031 | K10: 130959 | L10: 140832 | R10: 6883 | S10: 6796 | T10: 7288 | U10: 648 | V10: 801 | W10: 791 | X10: 83 | Y10: 83 | Z10: 83
A11: Prepaid Expenses and Other Current Assets | C11: 26604 | D11: 30464 | E11: 35566 | F11: 45989 | G11: 52729 | H11: 61223 | I11: 62132 | J11: 67596 | K11: 86374 | L11: 99363 | R11: 61537 | S11: 63799 | T11: 69345 | U11: 72059 | V11: 71683 | W11: 78311 | X11: 87509 | Y11: 89434 | Z11: 102255
A12: Total Current Assets | C12: 679240 | D12: 1222461 | E12: 1334974 | F12: 1343218 | G12: 1355285 | H12: 1252703 | I12: 1099603 | J12: 1295534 | K12: 1507415 | L12: 1186977 | R12: 976798 | S12: 1060630 | T12: 1081511 | U12: 1637292 | V12: 1478126 | W12: 1312969 | X12: 1357024 | Y12: 1346188 | Z12: 1215410
A13: Unbilled Accounts Receivable, Net (Non-current) | C13: 0 | D13: 0 | E13: 9375 | F13: 34737 | G13: 24361 | H13: 13914 | I13: 11112 | J13: 4157 | K13: 670 | L13: 0
A14: Long-term Investments | C14: 114585 | D14: 190952 | E14: 213524 | F14: 300771 | G14: 227164 | H14: 187507 | I14: 128782 | J14: 125885 | K14: 333754 | L14: 462223 | R14: 140644 | S14: 155061 | T14: 151891 | U14: 142119 | V14: 243473 | W14: 323305 | X14: 397365 | Y14: 432255 | Z14: 397267
A15: Property and Equipment, Net | C15: 14376 | D15: 18595 | E15: 65809 | F15: 65235 | G15: 80061 | H15: 80740 | I15: 54499 | J15: 55409 | K15: 60436 | L15: 67800 | R15: 55280 | S15: 55109 | T15: 55025 | U15: 55215 | V15: 54079 | W15: 55561 | X15: 65199 | Y15: 65315 | Z15: 66647
A16: Operating Lease Assets | F16: 103797 | G16: 97447 | H16: 90287 | I16: 52373 | J16: 43750 | K16: 39309 | L16: 34404 | R16: 50402 | S16: 48327 | T16: 46267 | U16: 41993 | V16: 43142 | W16: 41767 | X16: 37636 | Y16: 37430 | Z16: 36443
A17: Intangible Assets, Net | C17: 71315 | D17: 95654 | E17: 66542 | F17: 39708 | G17: 19743 | H17: 21361 | I17: 14473 | J17: 9005 | K17: 12042 | L17: 16406 | R17: 13106 | S17: 11739 | T17: 10372 | U17: 7638 | V17: 6360 | W17: 13482 | X17: 10704 | Y17: 19833 | Z17: 17727
A18: Goodwill | C18: 141851 | D18: 340877 | E18: 340877 | F18: 340877 | G18: 340877 | H18: 372192 | I18: 372214 | J18: 372214 | K18: 393978 | L18: 423267 | R18: 372214 | S18: 372214 | T18: 372214 | U18: 372214 | V18: 372214 | W18: 393592 | X18: 394300 | Y18: 422113 | Z18: 421111
A19: Deferred Tax Assets, Net | C19: 37430 | D19: 90369 | E19: 90308 | F19: 101565 | G19: 138428 | H19: 191461 | I19: 226875 | J19: 253085 | K19: 297234 | L19: 286585 | R19: 239822 | S19: 243424 | T19: 255547 | U19: 274875 | V19: 281034 | W19: 281344 | X19: 305494 | Y19: 292842 | Z19: 293911
A20: Other Assets | C20: 20104 | D20: 22525 | E20: 45554 | F20: 34944 | G20: 38479 | H20: 56732 | I20: 67957 | J20: 67255 | K20: 76261 | L20: 99283 | R20: 64448 | S20: 60220 | T20: 59910 | U20: 64703 | V20: 63560 | W20: 65260 | X20: 71526 | Y20: 75686 | Z20: 86533
A21: TOTAL ASSETS | C21: 1078901 | D21: 1981433 | E21: 2166963 | F21: 2364852 | G21: 2321845 | H21: 2266897 | I21: 2027888 | J21: 2226294 | K21: 2721099 | L21: 2576946 | R21: 1919597 | S21: 2013520 | T21: 2040025 | U21: 2596697 | V21: 2542789 | W21: 2488071 | X21: 2639331 | Y21: 2691745 | Z21: 2535132
A23: Accounts Payable | C23: 13416 | D23: 30635 | E23: 34255 | F23: 22634 | G23: 27830 | H23: 40440 | I23: 34627 | J23: 15209 | K23: 28797 | L23: 38074 | R23: 19210 | S23: 21999 | T23: 23514 | U23: 31394 | V23: 24921 | W23: 28952 | X23: 33557 | Y23: 28946 | Z23: 34972
A24: Accrued Employee Compensation | C24: 48882 | D24: 60135 | E24: 73365 | F24: 58547 | G24: 102137 | H24: 90962 | I24: 103980 | J24: 109084 | K24: 140613 | L24: 146331 | R24: 46686 | S24: 62669 | T24: 76538 | U24: 51860 | V24: 60601 | W24: 89230 | X24: 70300 | Y24: 84697 | Z24: 117531
A25: Deferred Revenue (Current) | C25: 91243 | D25: 127107 | E25: 108304 | F25: 118311 | G25: 138699 | H25: 170776 | I25: 206923 | J25: 281855 | K25: 340253 | L25: 437181 | R25: 3915 | S25: 4072 | T25: 3210 | U25: 3187 | V25: 3109 | W25: 4937 | X25: 2464 | Y25: 4977 | Z25: 3718
A26: Other Current Liabilities | C26: 10075 | D26: 20280 | E26: 16348 | F26: 25706 | G26: 31648 | H26: 35340 | I26: 27731 | J26: 32584 | K26: 35139 | L26: 42911 | R26: 25376 | S26: 27325 | T26: 24599 | U26: 29199 | V26: 29341 | W26: 28946 | X26: 32464 | Y26: 37694 | Z26: 44032
A27: Total Current Liabilities | C27: 163616 | D27: 238157 | E27: 232272 | F27: 225198 | G27: 300314 | H27: 337518 | I27: 373261 | J27: 837635 | K27: 544802 | L27: 664497 | R27: 262375 | S27: 307076 | T27: 704807 | U27: 615237 | V27: 558681 | W27: 405914 | X27: 389858 | Y27: 458983 | Z27: 497175
A28: Convertible Senior Notes, Net (Current) | C28: 0 | D28: 0 | E28: 0 | F28: 0 | G28: 0 | H28: 0 | I28: 0 | J28: 398903 | K28: 0 | L28: 0
A29: Lease Liabilities (Non-current) | F29: 119408 | G29: 115374 | H29: 105123 | I29: 42972 | J29: 34721 | K29: 30687 | L29: 25206 | R29: 40872 | S29: 39074 | T29: 37120 | U29: 32934 | V29: 33983 | W29: 33013 | X29: 29057 | Y29: 28673 | Z29: 27031
A30: Convertible Senior Notes, Net (Non-current) | D30: 305128 | E30: 317322 | F30: 330208 | G30: 343825 | H30: 358216 | I30: 397171 | J30: 0 | K30: 674568 | L30: 678094 | R30: 397601 | S30: 398033 | T30: 398467 | U30: 671820 | V30: 672828 | W30: 673696 | X30: 675443 | Y30: 676323 | Z30: 677206
A31: Deferred Revenue (Non-current) | C31: 19892 | D31: 23758 | E31: 23527 | F31: 14685 | G31: 7237 | H31: 7500 | I31: 5988 | J31: 3628 | K31: 4533 | L31: 1633
A32: Other Liabilities | C32: 2112 | D32: 774 | E32: 19641 | F32: 18585 | G32: 10201 | H32: 6883 | I32: 9030 | J32: 7578 | K32: 9279 | L32: 13828 | R32: 9185 | S32: 9152 | T32: 9522 | U32: 5490 | V32: 5452 | W32: 7936 | X32: 9091 | Y32: 12171 | Z32: 12858
A33: Total Liabilities | C33: 185620 | D33: 567817 | E33: 592762 | F33: 708084 | G33: 776951 | H33: 815240 | I33: 828422 | J33: 883562 | K33: 1263869 | L33: 1383258 | R33: 713948 | S33: 757407 | T33: 754659 | U33: 1328668 | V33: 1274053 | W33: 1125496 | X33: 1105913 | Y33: 1181127 | Z33: 1217987
A35: Common Stock | C35: 8 | D35: 8 | E35: 8 | F35: 8 | G35: 8 | H35: 8 | I35: 8 | J35: 8 | K35: 8 | L35: 8 | R35: 8 | S35: 8 | T35: 8 | U35: 8 | V35: 8 | W35: 8 | X35: 9 | Y35: 8 | Z35: 8
A36: Additional Paid-in Capital | C36: 830014 | D36: 1296380 | E36: 1391904 | F36: 1499050 | G36: 1617204 | H36: 1755476 | I36: 1831267 | J36: 1979021 | K36: 2020393 | L36: 2230308 | R36: 1867467 | S36: 1903873 | T36: 1940691 | U36: 1894904 | V36: 1936293 | W36: 1977364 | X36: 2064255 | Y36: 2124589 | Z36: 2169769
A37: Accumulated Other Comprehensive Income (Loss) | C37: -5796 | D37: -7748 | E37: -7758 | F37: -5246 | G37: -6218 | H37: -19845 | I37: -13859 | J37: -12244 | K37: -8922 | L37: -12233 | R37: -16805 | S37: -12434 | T37: -14521 | U37: -11969 | V37: -15374 | W37: -8597 | X37: -7905 | Y37: -2959 | Z37: -7105
A38: Retained Earnings (Accumulated Deficit) | C38: 69055 | D38: 124976 | E38: 190047 | F38: 162956 | G38: -66100 | H38: -283982 | I38: -617950 | J38: -624053 | K38: -554249 | L38: -1024396 | R38: -645021 | S38: -635334 | T38: -640812 | U38: -614914 | V38: -652191 | W38: -606200 | X38: -522941 | Y38: -611021 | Z38: -845527
A39: Total Stockholders' Equity | C39: 893281 | D39: 1413616 | E39: 1574201 | F39: 1656768 | G39: 1544894 | H39: 1451657 | I39: 1199466 | J39: 1342732 | K39: 1457230 | L39: 1193687 | R39: 1205649 | S39: 1256113 | T39: 1285366 | U39: 1268029 | V39: 1268736 | W39: 1362575 | X39: 1533418 | Y39: 1510618 | Z39: 1317145
A40: TOTAL LIABILITIES AND STOCKHOLDERS' EQUITY | C40: 1078901 | D40: 1981433 | E40: 2166963 | F40: 2364852 | G40: 2321845 | H40: 2266897 | I40: 2027888 | J40: 2226294 | K40: 2721099 | L40: 2576946
A42: 2. BS CHECK
A43: BS Check (should be 0) | C43: =C21-C33-C39 -> 0 | D43: =D21-D33-D39 -> 0 | E43: =E21-E33-E39 -> 0 | F43: =F21-F33-F39 -> 0 | G43: =G21-G33-G39 -> 0 | H43: =H21-H33-H39 -> 0 | I43: =I21-I33-I39 -> 0 | J43: =J21-J33-J39 -> 0 | ... L43: =L21-L33-L39 -> 1 | R43: =R21-R33-R39 -> 0 | S43: =S21-S33-S39 -> 0 | T43: =T21-T33-T39 -> 0 | U43: =U21-U33-U39 -> 0 | V43: =V21-V33-V39 -> 0 | W43: =W21-W33-W39 -> 0 | X43: =X21-X33-X39 -> 0 | Y43: =Y21-Y33-Y39 -> 0 | Z43: =Z21-Z33-Z39 -> 0

Sheet Cash Flow Statement
A1: Guidewire Software, Inc. — Cash Flow Statement
A2: $ in thousands except per-share data | USD | as of 2026-09-17
C3: FY2017 | D3: FY2018 | E3: FY2019 | F3: FY2020 | G3: FY2021 | H3: FY2022 | I3: FY2023 | J3: FY2024 | K3: FY2025 | L3: FY2026 | M3: · | N3: · | O3: · | P3: · | Q3: · | R3: 1Q2024 | S3: 2Q2024 | T3: 3Q2024 | U3: 1Q2025 | V3: 2Q2025 | W3: 3Q2025 | X3: 1Q2026 | Y3: 2Q2026 | Z3: 3Q2026
A6: 1. CASH FLOW STATEMENT
A7: Net Income (Loss) | C7: 18072 | D7: -26743 | E7: 20732 | F7: -27198 | G7: -66507 | H7: -180431 | I7: -111855 | J7: -6103 | K7: 69804 | L7: 139283 | R7: -27071 | S7: -17384 | T7: -22862 | U7: 9139 | V7: -28138 | W7: 17853 | X7: 31308 | Y7: 91418 | Z7: 107888
A9: Depreciation and Amortization | C9: 18725 | D9: 35611 | E9: 39953 | F9: 42641 | G9: 36955 | H9: 33540 | I9: 24838 | J9: 22309 | K9: 23758 | L9: 27952 | R9: 5442 | S9: 10934 | T9: 16525 | U9: 5845 | V9: 11573 | W9: 17538 | X9: 6362 | Y9: 13402 | Z9: 20632
A10: Amortization of Debt Issuance Costs | D10: 4512 | E10: 12194 | F10: 12886 | G10: 13617 | H10: 14391 | I10: 1703 | J10: 1732 | K10: 3758 | L10: 3939 | R10: 430 | S10: 862 | T10: 1296 | U10: 545 | V10: 1724 | W10: 2782 | X10: 980 | Y10: 1964 | Z10: 2947
A11: Amortization of Contract Costs | E11: 5515 | F11: 9892 | G11: 11442 | H11: 14456 | I11: 17966 | J11: 28413 | K11: 30893 | L11: 35011 | R11: 4064 | S11: 8745 | T11: 12869 | U11: 7780 | V11: 15233 | W11: 22518 | X11: 8802 | Y11: 17304 | Z11: 25812
A12: Stock-based Compensation | C12: 71794 | D12: 89614 | E12: 91516 | F12: 101817 | G12: 115009 | H12: 137011 | I12: 142842 | J12: 146460 | K12: 161556 | L12: 181799 | R12: 36097 | S12: 72524 | T12: 109174 | U12: 38060 | V12: 79008 | W12: 119365 | X12: 43316 | Y12: 90074 | Z12: 135015
A13: Changes to Allowances / Credit Losses | D13: 1062 | E13: 670 | F13: 367 | G13: 226 | H13: 2597 | I13: -131 | J13: 526 | K13: 526 | L13: 2516 | R13: 128 | S13: -194 | T13: -142 | U13: 1257 | V13: 1090 | W13: 1107 | X13: 2358 | Y13: 2337 | Z13: 2542
A14: Deferred Income Tax | C14: -1227 | D14: 14150 | E14: -13998 | F14: -11859 | G14: -35789 | H14: -54115 | I14: -27516 | J14: -26847 | K14: -31780 | L14: 8981 | R14: -13220 | S14: -17390 | T14: -29294 | U14: -7955 | V14: -14159 | W14: -15851 | X14: -8527 | Y14: 1466 | Z14: 922
A15: Amortization of Premium on Securities | C15: 1462 | D15: -1418 | E15: -7757 | F15: -1882 | G15: 6567 | H15: 5498 | I15: -4858 | J15: -12894 | K15: -10326 | L15: -6254 | R15: -2927 | S15: -6223 | T15: -9492 | U15: -3228 | V15: -6549 | W15: -8613 | X15: -1948 | Y15: -4008 | Z15: -5377
A16: Gains/Losses on Strategic Investments | J16: -1803 | K16: -3671 | L16: -632 | S16: -1758 | T16: -1758 | V16: -3671 | W16: -3671 | Z16: -632
A17: Changes in Fair Value of Strategic Investments | F17: 10672 | H17: -1545 | I17: 802 | J17: 1957 | K17: 2130 | L17: -489 | T17: -298 | U17: -53 | V17: 238 | W17: 341 | X17: 60 | Y17: 45 | Z17: -554
A18: Loss on Retirement of Debt | K18: 53565 | V18: 53565 | W18: 53565
A19: Accelerated Depreciation (Lease) | I19: 26921
A20: Gain from Lease Assignment | I20: -18419
A21: Excess Tax Benefit from Stock Options/RSUs | C21: -9067
A22: Other Non-cash Items | C22: 49 | E22: 189 | F22: 739 | G22: 863 | H22: 63 | I22: 164 | J22: -74 | K22: 186 | L22: -88 | R22: -29 | S22: -46 | T22: -74 | U22: 286 | V22: 3 | W22: 56 | X22: 17 | Y22: 7 | Z22: 18
A24: Change in Accounts Receivable | C24: -9750 | D24: -40832 | E24: -15057 | F24: 23878 | G24: 10820 | H24: -42545 | I24: -7301 | J24: 12631 | K24: -3348 | L24: -54868 | R24: 57193 | S24: 22547 | T24: 46276 | U24: 38609 | V24: 12817 | W24: -10609 | X24: 43676 | Y24: -23665 | Z24: 276
A25: Change in Unbilled Accounts Receivable | E25: -17341 | F25: -38125 | G25: -19194 | H25: 18106 | I25: -13435 | J25: 7676 | K25: -38930 | L25: -9193 | R25: -17250 | S25: 1102 | T25: -33955 | U25: -38889 | V25: -24094 | W25: -74471 | X25: -31470 | Y25: -43095 | Z25: -93214
A26: Change in Prepaid Expenses and Other Assets | C26: -9463 | D26: -2737 | E26: -21766 | F26: -18564 | G26: -16764 | H26: -23390 | I26: -22613 | J26: -44131 | K26: -58054 | L26: -55354 | R26: -6560 | S26: -12531 | T26: -22082 | U26: -8932 | V26: -17207 | W26: -29305 | X26: -4710 | Y26: -14281 | Z26: -33815
A27: Change in Operating Lease Assets | F27: -10784 | G27: 6350 | H27: 7160 | I27: -19000 | J27: 8623 | K27: 4441 | L27: 4905 | R27: 1971 | S27: 4046 | T27: 6106 | U27: 1757 | V27: 608 | W27: 1983 | X27: 1673 | Y27: 1879 | Z27: 2866
A28: Change in Accounts Payable | C28: 1311 | D28: 16794 | E28: -5521 | F28: -1209 | G28: 3627 | H28: 13580 | I28: -6080 | J28: -18933 | K28: 11399 | L28: 11712 | R28: -16982 | S28: -12212 | T28: -10538 | U28: 16206 | V28: 10150 | W28: 13589 | X28: 4264 | Y28: 1813 | Z28: 7910
A29: Change in Accrued Employee Compensation | C29: 7138 | D29: 9230 | E29: 13825 | F29: -15624 | G29: 41526 | H29: -8942 | I29: 12440 | J29: 6453 | K29: 30090 | L29: 6196 | R29: -54576 | S29: -39657 | T29: -25604 | U29: -56545 | V29: -46878 | W29: -20600 | X29: -69630 | Y29: -57657 | Z29: -23578
A30: Change in Deferred Revenue | C30: 41553 | D30: 32358 | E30: -9628 | F30: 1165 | G30: 12940 | H30: 31564 | I30: 34635 | J30: 72572 | K30: 56617 | L30: 93675 | R30: -37893 | S30: -13756 | T30: -28012 | U30: -58107 | V30: -17522 | W30: -24876 | X30: -88785 | Y30: -32515 | Z30: -40781
A31: Change in Lease Liabilities | F31: 18678 | G31: -3346 | H31: -9637 | I31: 9548 | J31: -7389 | K31: -2891 | L31: -4232 | R31: -1601 | S31: -3245 | T31: -5136 | U31: -1685 | V31: -151 | W31: -1121 | X31: -1537 | Y31: -1330 | Z31: -3572
A32: Change in Other Liabilities | C32: 6612 | D32: 8858 | E32: 22600 | F32: 15576 | G32: -6755 | H32: 4699 | I32: -2256 | J32: 4570 | K32: 1144 | L32: 4857 | R32: 701 | S32: 804 | T32: -1028 | U32: -6395 | V32: -3954 | W32: -5544 | X32: -3607 | Y32: -510 | Z32: 525
A33: Net Cash from Operating Activities | C33: 138759 | D33: 140459 | E33: 116126 | F33: 113066 | G33: 111587 | H33: -37940 | I33: 38395 | J33: 195748 | K33: 300867 | L33: 389716 | R33: -72083 | S33: -2832 | T33: 1971 | U33: -62305 | V33: 23686 | W33: 56036 | X33: -67398 | Y33: 44648 | Z33: 105830
A35: Purchases of Available-for-Sale Securities | C35: -462035 | D35: -859657 | E35: -1209312 | F35: -1280755 | G35: -1033095 | H35: -519536 | I35: -506115 | J35: -615935 | K35: -858571 | L35: -859150 | R35: -160239 | S35: -314846 | T35: -453441 | U35: -211649 | V35: -429742 | W35: -672330 | X35: -318525 | Y35: -535549 | Z35: -644915
A36: Maturities and Sales of AFS Securities | C36: 547630 | D36: 390025 | E36: 879532 | F36: 1168720 | G36: 1128524 | H36: 908914 | I36: 547094 | J36: 576886 | K36: 665012 | L36: 806049 | R36: 137386 | S36: 267416 | T36: 416299 | U36: 139896 | V36: 303111 | W36: 529887 | X36: 189726 | Y36: 382943 | Z36: 582638
A37: Purchases of Property and Equipment | C37: -5886 | D37: -9398 | E37: -44921 | F37: -21377 | G37: -19008 | H37: -9510 | I37: -5821 | J37: -6362 | K37: -5741 | L37: -12056 | R37: -998 | S37: -3990 | T37: -4668 | U37: -843 | V37: -1633 | W37: -2336 | X37: -4878 | Y37: -8162 | Z37: -9934
A38: Capitalized Software Development Costs | C38: -784 | D38: -2613 | E38: -3936 | F38: -4283 | G38: -9846 | H38: -12266 | I38: -11606 | J38: -12165 | K38: -14714 | L38: -19003 | R38: -3692 | S38: -6058 | T38: -9429 | U38: -4233 | V38: -7156 | W38: -10972 | X38: -5088 | Y38: -8192 | Z38: -13939
A39: Acquisition of Strategic Investments | C39: -4677 | F39: -2156 | G39: -2384 | H39: -11560 | I39: -10840 | J39: -1336 | K39: -1772 | L39: -14646 | R39: -250 | S39: -250 | T39: -336 | U39: -772 | V39: -772 | W39: -1772 | Y39: -2348 | Z39: -14590
A40: Sale of Strategic Investments | S40: 6508 | T40: 6508 | V40: 5671 | W40: 5671 | Z40: 781
A41: Acquisitions, Net of Cash | C41: -187590 | D41: -130059 | H41: -43830 | K41: -26850 | L41: -37953 | W41: -26724 | Y41: -33252 | Z41: -33453
A42: Net Cash from Investing Activities | C42: -113342 | D42: -537584 | E42: -301433 | F42: -5801 | G42: 64191 | H42: 312212 | I42: 12712 | J42: -52359 | K42: -236965 | L42: -135977 | R42: -27793 | S42: -51220 | T42: -45067 | U42: -77601 | V42: -130521 | W42: -178576 | X42: -138765 | Y42: -204560 | Z42: -133412
A44: Proceeds from Convertible Notes | D44: 387239 | K44: 671840 | U44: 672750 | V44: 671840 | W44: 671840
A45: Payment for Retirement of Convertible Notes | K45: -353535 | U45: -200394 | V45: -353535 | W45: -353535
A46: Payment for Maturity of Convertible Notes | K46: -179061 | W46: -179061
A47: Purchase of Capped Calls | D47: -37200 | K47: -58788 | U47: -58788 | V47: -58788 | W47: -58788
A48: Payment of Revolving Credit Facility Costs | K48: -2065 | V48: -2065 | W48: -2065
A49: Proceeds from Common Stock, Net | D49: 220948
A50: Proceeds from ESPP | L50: 26603 | Y50: 13364 | Z50: 13364
A51: Proceeds from Stock Option Exercises | C51: 5563 | D51: 2013 | E51: 3954 | F51: 4955 | G51: 1932 | H51: 116 | I51: 228 | J51: 1055 | K51: 3902 | L51: 729 | S51: 4 | T51: 14 | U51: 1939 | V51: 2464 | W51: 3174 | X51: 413 | Y51: 531 | Z51: 539
A52: Repurchase and Retirement of Common Stock | G52: -161319 | H52: -37451 | I52: -261807 | L52: -606309 | Y52: -148192 | Z52: -392447
A53: Excess Tax Benefit (Financing) | C53: 7468
A54: Net Cash from Financing Activities | C54: 13031 | D54: 573000 | E54: 3954 | F54: 4955 | G54: -159387 | H54: -37335 | I54: -261579 | J54: 1055 | K54: 82293 | L54: -578977 | S54: 4 | T54: 14 | U54: 415507 | V54: 259916 | W54: 81565 | X54: 413 | Y54: -134297 | Z54: -378544
A56: Effect of Foreign Exchange on Cash | C56: 1146 | D56: -1911 | E56: -1686 | F56: 648 | G56: 1550 | H56: -7161 | I56: 2576 | J56: -2050 | K56: 3715 | L56: -969 | R56: -4303 | S56: -1561 | T56: -2915 | U56: -31 | V56: -3585 | W56: 3303 | X56: -114 | Y56: 3061
A57: Net Change in Cash | C57: 39594 | D57: 173964 | E57: -183039 | F57: 112868 | G57: 17941 | H57: 229776 | I57: -207896 | J57: 142394 | K57: 149910 | L57: -326207 | R57: -104179 | S57: -55609 | T57: -45997 | U57: 275570 | V57: 149496 | X57: -205864
A58: Cash, Beginning of Period | C58: 223582 | D58: 263176 | E58: 437140 | F58: 254101 | G58: 366969 | H58: 384910 | I58: 614686 | J58: 406790 | K58: 549184 | L58: 699094 | R58: 406790 | S58: 406790 | T58: 406790 | U58: 549184 | V58: 549184 | X58: 699094
A59: Cash, End of Period | C59: 263176 | D59: 437140 | E59: 254101 | F59: 366969 | G59: 384910 | H59: 614686 | I59: 406790 | J59: 549184 | K59: 699094 | L59: 372887 | R59: 302611 | S59: 351181 | T59: 360793 | U59: 824754 | V59: 698680 | X59: 493230
A61: 2. FCF ANALYTICS
A62: Free Cash Flow | C62: =C33+C37+C38 -> 132089 | D62: =D33+D37+D38 -> 128448 | E62: =E33+E37+E38 -> 67269 | F62: =F33+F37+F38 -> 87406 | G62: =G33+G37+G38 -> 82733 | H62: =H33+H37+H38 -> -59716 | I62: =I33+I37+I38 -> 20968 | J62: =J33+J37+J38 -> 177221 | ... L62: =L33+L37+L38 -> 358657 | R62: =R33+R37+R38 -> -76773 | S62: =S33+S37+S38 -> -12880 | T62: =T33+T37+T38 -> -12126 | U62: =U33+U37+U38 -> -67381 | V62: =V33+V37+V38 -> 14897 | W62: =W33+W37+W38 -> 42728 | X62: =X33+X37+X38 -> -77364 | Y62: =Y33+Y37+Y38 -> 28294 | Z62: =Z33+Z37+Z38 -> 81957
A63: FCF Growth YoY | D63: =IF(N(C62)=0,"",D62/C62-1) -> -0.027564748 | E63: =IF(N(D62)=0,"",E62/D62-1) -> -0.47629391 | F63: =IF(N(E62)=0,"",F62/E62-1) -> 0.29935037 | G63: =IF(N(F62)=0,"",G62/F62-1) -> -0.053463149 | H63: =IF(N(G62)=0,"",H62/G62-1) -> -1.7217918 | I63: =IF(N(H62)=0,"",I62/H62-1) -> -1.3511287 | J63: =IF(N(I62)=0,"",J62/I62-1) -> 7.4519744 | K63: =IF(N(J62)=0,"",K62/J62-1) -> 0.58227298 | L63: =IF(N(K62)=0,"",L62/K62-1) -> 0.27903585 | V63: =IF(N(R62)=0,"",V62/R62-1) -> -1.1940396 | W63: =IF(N(S62)=0,"",W62/S62-1) -> -4.3173913 | X63: =IF(N(T62)=0,"",X62/T62-1) -> 5.3800099 | Y63: =IF(N(U62)=0,"",Y62/U62-1) -> -1.4199107 | Z63: =IF(N(V62)=0,"",Z62/V62-1) -> 4.5015775
A64: Total Capex | C64: =C37+C38 -> -6670 | D64: =D37+D38 -> -12011 | E64: =E37+E38 -> -48857 | F64: =F37+F38 -> -25660 | G64: =G37+G38 -> -28854 | H64: =H37+H38 -> -21776 | I64: =I37+I38 -> -17427 | J64: =J37+J38 -> -18527 | ... L64: =L37+L38 -> -31059 | R64: =R37+R38 -> -4690 | S64: =S37+S38 -> -10048 | T64: =T37+T38 -> -14097 | U64: =U37+U38 -> -5076 | V64: =V37+V38 -> -8789 | W64: =W37+W38 -> -13308 | X64: =X37+X38 -> -9966 | Y64: =Y37+Y38 -> -16354 | Z64: =Z37+Z38 -> -23873
A65: Capex % of Revenue | C65: =(C37+C38)/'Income Statement'!C13*-1 -> 0.013090418 | D65: =(D37+D38)/'Income Statement'!D13*-1 -> 0.018397822 | E65: =(E37+E38)/'Income Statement'!E13*-1 -> 0.067902779 | F65: =(F37+F38)/'Income Statement'!F13*-1 -> 0.034567908 | G65: =(G37+G38)/'Income Statement'!G13*-1 -> 0.038820505 | H65: =(H37+H38)/'Income Statement'!H13*-1 -> 0.026797471 | I65: =(I37+I38)/'Income Statement'!I13*-1 -> 0.019249101 | J65: =(J37+J38)/'Income Statement'!J13*-1 -> 0.018895519 | ... L65: =(L37+L38)/'Income Statement'!L13*-1 -> 0.021051768 | R65: =(R37+R38)/'Income Statement'!R13*-1 -> 0.022612544 | S65: =(S37+S38)/'Income Statement'!S13*-1 -> 0.041710773 | T65: =(T37+T38)/'Income Statement'!T13*-1 -> 0.058572034 | U65: =(U37+U38)/'Income Statement'!U13*-1 -> 0.019307648 | V65: =(V37+V38)/'Income Statement'!V13*-1 -> 0.030361338 | W65: =(W37+W38)/'Income Statement'!W13*-1 -> 0.045341183 | X65: =(X37+X38)/'Income Statement'!X13*-1 -> 0.029960408 | Y65: =(Y37+Y38)/'Income Statement'!Y13*-1 -> 0.045542266 | Z65: =(Z37+Z38)/'Income Statement'!Z13*-1 -> 0.064081537
A66: FCF Margin | C66: =(C33+C37+C38)/'Income Statement'!C13 -> 0.25923542 | D66: =(D33+D37+D38)/'Income Statement'!D13 -> 0.19674994 | E66: =(E33+E37+E38)/'Income Statement'!E13 -> 0.093492274 | F66: =(F33+F37+F38)/'Income Statement'!F13 -> 0.11774913 | G66: =(G33+G37+G38)/'Income Statement'!G13 -> 0.11130993 | H66: =(H33+H37+H38)/'Income Statement'!H13 -> -0.073486305 | I66: =(I33+I37+I38)/'Income Statement'!I13 -> 0.023160334 | J66: =(J33+J37+J38)/'Income Statement'!J13 -> 0.18074609 | ... L66: =(L33+L37+L38)/'Income Statement'!L13 -> 0.24309746 | R66: =(R33+R37+R38)/'Income Statement'!R13 -> -0.37015626 | S66: =(S33+S37+S38)/'Income Statement'!S13 -> -0.053466834 | T66: =(T33+T37+T38)/'Income Statement'!T13 -> -0.050382669 | U66: =(U33+U37+U38)/'Income Statement'!U13 -> -0.256298 | V66: =(V33+V37+V38)/'Income Statement'!V13 -> 0.051461241 | W66: =(W33+W37+W38)/'Income Statement'!W13 -> 0.14557695 | X66: =(X33+X37+X38)/'Income Statement'!X13 -> -0.23257646 | Y66: =(Y33+Y37+Y38)/'Income Statement'!Y13 -> 0.07879252 | Z66: =(Z33+Z37+Z38)/'Income Statement'!Z13 -> 0.21999458
A67: FCF Conversion (FCF/Net Income) | C67: =(C33+C37+C38)/'Income Statement'!C46 -> 7.3090416 | D67: =(D33+D37+D38)/'Income Statement'!D46 -> -4.8030513 | E67: =(E33+E37+E38)/'Income Statement'!E46 -> 3.2446942 | F67: =(F33+F37+F38)/'Income Statement'!F46 -> -3.2136922 | G67: =(G33+G37+G38)/'Income Statement'!G46 -> -1.2439743 | H67: =(H33+H37+H38)/'Income Statement'!H46 -> 0.33096308 | I67: =(I33+I37+I38)/'Income Statement'!I46 -> -0.18745698 | J67: =(J33+J37+J38)/'Income Statement'!J46 -> -29.038342 | ... L67: =(L33+L37+L38)/'Income Statement'!L46 -> 2.5750235 | R67: =(R33+R37+R38)/'Income Statement'!R46 -> 2.8359868 | S67: =(S33+S37+S38)/'Income Statement'!S46 -> -1.329617 | T67: =(T33+T37+T38)/'Income Statement'!T46 -> 2.2135816 | U67: =(U33+U37+U38)/'Income Statement'!U46 -> -7.3729073 | V67: =(V33+V37+V38)/'Income Statement'!V46 -> -0.3996298 | W67: =(W33+W37+W38)/'Income Statement'!W46 -> 0.92905134 | X67: =(X33+X37+X38)/'Income Statement'!X46 -> -2.4710617 | Y67: =(Y33+Y37+Y38)/'Income Statement'!Y46 -> 0.47070371 | Z67: =(Z33+Z37+Z38)/'Income Statement'!Z46 -> 4.9758363
A69: 3. CF CHECK
A70: CF Check (should be 0) | C70: =C33+C42+C54+C56-C57 -> 0 | D70: =D33+D42+D54+D56-D57 -> 0 | E70: =E33+E42+E54+E56-E57 -> 0 | F70: =F33+F42+F54+F56-F57 -> 0 | G70: =G33+G42+G54+G56-G57 -> 0 | H70: =H33+H42+H54+H56-H57 -> 0 | I70: =I33+I42+I54+I56-I57 -> 0 | J70: =J33+J42+J54+J56-J57 -> 0 | ... L70: =L33+L42+L54+L56-L57 -> 0

Sheet Derived Metrics
A1: Guidewire Software, Inc. — Derived Metrics
A2: $ in thousands except per-share data | USD | as of 2026-09-17
C3: FY2017 | D3: FY2018 | E3: FY2019 | F3: FY2020 | G3: FY2021 | H3: FY2022 | I3: FY2023 | J3: FY2024 | K3: FY2025 | L3: FY2026 | M3: · | N3: · | O3: · | P3: · | Q3: · | R3: 1Q2024 | S3: 2Q2024 | T3: 3Q2024 | U3: 1Q2025 | V3: 2Q2025 | W3: 3Q2025 | X3: 1Q2026 | Y3: 2Q2026 | Z3: 3Q2026
A6: 1. PROFITABILITY
A7: Gross Margin | C7: ='Income Statement'!C30/'Income Statement'!C13 -> 0.62404987 | D7: ='Income Statement'!D30/'Income Statement'!D13 -> 0.5454033 | E7: ='Income Statement'!E30/'Income Statement'!E13 -> 0.54920961 | F7: ='Income Statement'!F30/'Income Statement'!F13 -> 0.54464258 | G7: ='Income Statement'!G30/'Income Statement'!G13 -> 0.52411852 | H7: ='Income Statement'!H30/'Income Statement'!H13 -> 0.46415149 | I7: ='Income Statement'!I30/'Income Statement'!I13 -> 0.50611979 | J7: ='Income Statement'!J30/'Income Statement'!J13 -> 0.59496459 | ... L7: ='Income Statement'!L30/'Income Statement'!L13 -> 0.64212536 | R7: ='Income Statement'!R30/'Income Statement'!R13 -> 0.54140892 | S7: ='Income Statement'!S30/'Income Statement'!S13 -> 0.59114891 | T7: ='Income Statement'!T30/'Income Statement'!T13 -> 0.59094309 | U7: ='Income Statement'!U30/'Income Statement'!U13 -> 0.60247774 | V7: ='Income Statement'!V30/'Income Statement'!V13 -> 0.61887522 | W7: ='Income Statement'!W30/'Income Statement'!W13 -> 0.62246344 | X7: ='Income Statement'!X30/'Income Statement'!X13 -> 0.62987804 | Y7: ='Income Statement'!Y30/'Income Statement'!Y13 -> 0.64473468 | Z7: ='Income Statement'!Z30/'Income Statement'!Z13 -> 0.63521867
A8: Operating Margin | C8: ='Income Statement'!C38/'Income Statement'!C13 -> 0.042903992 | D8: ='Income Statement'!D38/'Income Statement'!D13 -> -0.023932027 | E8: ='Income Statement'!E38/'Income Statement'!E13 -> 0.0020444355 | F8: ='Income Statement'!F38/'Income Statement'!F13 -> -0.032178061 | G8: ='Income Statement'!G38/'Income Statement'!G13 -> -0.14205393 | H8: ='Income Statement'!H38/'Income Statement'!H13 -> -0.24543879 | I8: ='Income Statement'!I38/'Income Statement'!I13 -> -0.1651201 | J8: ='Income Statement'!J38/'Income Statement'!J13 -> -0.053618726 | ... L8: ='Income Statement'!L38/'Income Statement'!L13 -> 0.10158449 | R8: ='Income Statement'!R38/'Income Statement'!R13 -> -0.162873 | S8: ='Income Statement'!S38/'Income Statement'!S13 -> -0.051515793 | T8: ='Income Statement'!T38/'Income Statement'!T13 -> -0.069370694 | U8: ='Income Statement'!U38/'Income Statement'!U13 -> -0.017953526 | V8: ='Income Statement'!V38/'Income Statement'!V13 -> 0.040496753 | W8: ='Income Statement'!W38/'Income Statement'!W13 -> 0.015222754 | X8: ='Income Statement'!X38/'Income Statement'!X13 -> 0.05554971 | Y8: ='Income Statement'!Y38/'Income Statement'!Y13 -> 0.10704967 | Z8: ='Income Statement'!Z38/'Income Statement'!Z13 -> 0.082237928
A9: Net Margin | C9: ='Income Statement'!C46/'Income Statement'!C13 -> 0.035467771 | D9: ='Income Statement'!D46/'Income Statement'!D13 -> -0.040963531 | E9: ='Income Statement'!E46/'Income Statement'!E13 -> 0.028813894 | F9: ='Income Statement'!F46/'Income Statement'!F13 -> -0.036639827 | G9: ='Income Statement'!G46/'Income Statement'!G13 -> -0.089479285 | H9: ='Income Statement'!H46/'Income Statement'!H13 -> -0.22203777 | I9: ='Income Statement'!I46/'Income Statement'!I13 -> -0.12355013 | J9: ='Income Statement'!J46/'Income Statement'!J13 -> -0.0062243944 | ... L9: ='Income Statement'!L46/'Income Statement'!L13 -> 0.094405919 | R9: ='Income Statement'!R46/'Income Statement'!R13 -> -0.13052115 | S9: ='Income Statement'!S46/'Income Statement'!S13 -> 0.040212207 | T9: ='Income Statement'!T46/'Income Statement'!T13 -> -0.022760701 | U9: ='Income Statement'!U46/'Income Statement'!U13 -> 0.034762135 | V9: ='Income Statement'!V46/'Income Statement'!V13 -> -0.12877228 | W9: ='Income Statement'!W46/'Income Statement'!W13 -> 0.1566942 | X9: ='Income Statement'!X46/'Income Statement'!X13 -> 0.094120052 | Y9: ='Income Statement'!Y46/'Income Statement'!Y13 -> 0.16739303 | Z9: ='Income Statement'!Z46/'Income Statement'!Z13 -> 0.044212583
A10: Effective Tax Rate | C10: ='Income Statement'!C45/'Income Statement'!C44 -> 0.36647269 | D10: ='Income Statement'!D45/'Income Statement'!D44 -> -2.231392 | E10: ='Income Statement'!E45/'Income Statement'!E44 -> -0.66495342 | F10: ='Income Statement'!F45/'Income Statement'!F44 -> -0.11783322 | G10: ='Income Statement'!G45/'Income Statement'!G44 -> 0.36223281 | H10: ='Income Statement'!H45/'Income Statement'!H44 -> 0.21454411 | I10: ='Income Statement'!I45/'Income Statement'!I44 -> 0.16584635 | J10: ='Income Statement'!J45/'Income Statement'!J44 -> 0.77259855 | ... L10: ='Income Statement'!L45/'Income Statement'!L44 -> 0.15131888 | R10: ='Income Statement'!R45/'Income Statement'!R44 -> 0.29855155 | S10: ='Income Statement'!S45/'Income Statement'!S44 -> -0.39101091 | T10: ='Income Statement'!T45/'Income Statement'!T44 -> 0.61129639 | U10: ='Income Statement'!U45/'Income Statement'!U44 -> -2.3004695 | V10: ='Income Statement'!V45/'Income Statement'!V44 -> 0.13363702 | W10: ='Income Statement'!W45/'Income Statement'!W44 -> 0.055005342 | X10: ='Income Statement'!X45/'Income Statement'!X44 -> -0.27777324 | Y10: ='Income Statement'!Y45/'Income Statement'!Y44 -> 0.19371714 | Z10: ='Income Statement'!Z45/'Income Statement'!Z44 -> 0.16644737
A11: Subscription & Support Gross Margin | C11: ='Income Statement'!C24/'Income Statement'!C7 -> 0.80483079 | D11: ='Income Statement'!D24/'Income Statement'!D7 -> 0.59242536 | E11: ='Income Statement'!E24/'Income Statement'!E7 -> 0.51089889 | F11: ='Income Statement'!F24/'Income Statement'!F7 -> 0.42420862 | G11: ='Income Statement'!G24/'Income Statement'!G7 -> 0.37593419 | H11: ='Income Statement'!H24/'Income Statement'!H7 -> 0.40987117 | I11: ='Income Statement'!I24/'Income Statement'!I7 -> 0.51006943 | J11: ='Income Statement'!J24/'Income Statement'!J7 -> 0.62702814 | ... L11: ='Income Statement'!L24/'Income Statement'!L7 -> 0.72684406 | R11: ='Income Statement'!R24/'Income Statement'!R7 -> 0.62348092 | S11: ='Income Statement'!S24/'Income Statement'!S7 -> 0.62068337 | T11: ='Income Statement'!T24/'Income Statement'!T7 -> 0.62901355 | U11: ='Income Statement'!U24/'Income Statement'!U7 -> 0.68172874 | V11: ='Income Statement'!V24/'Income Statement'!V7 -> 0.66769757 | W11: ='Income Statement'!W24/'Income Statement'!W7 -> 0.68424787 | X11: ='Income Statement'!X24/'Income Statement'!X7 -> 0.71230361 | Y11: ='Income Statement'!Y24/'Income Statement'!Y7 -> 0.73049926 | Z11: ='Income Statement'!Z24/'Income Statement'!Z7 -> 0.722634
A13: 2. RETURNS
A14: Return on Assets (ROA) | C14: ='Income Statement'!C46/'Balance Sheet'!C21 -> 0.016750378 | D14: ='Income Statement'!D46/'Balance Sheet'!D21 -> -0.013496798 | E14: ='Income Statement'!E46/'Balance Sheet'!E21 -> 0.0095673069 | F14: ='Income Statement'!F46/'Balance Sheet'!F21 -> -0.011500931 | G14: ='Income Statement'!G46/'Balance Sheet'!G21 -> -0.028644031 | H14: ='Income Statement'!H46/'Balance Sheet'!H21 -> -0.079593824 | I14: ='Income Statement'!I46/'Balance Sheet'!I21 -> -0.055158372 | J14: ='Income Statement'!J46/'Balance Sheet'!J21 -> -0.0027413271 | ... L14: ='Income Statement'!L46/'Balance Sheet'!L21 -> 0.054049639 | R14: ='Income Statement'!R46/'Balance Sheet'!R21 -> -0.014102439 | S14: ='Income Statement'!S46/'Balance Sheet'!S21 -> 0.0048109778 | T14: ='Income Statement'!T46/'Balance Sheet'!T21 -> -0.0026852612 | U14: ='Income Statement'!U46/'Balance Sheet'!U21 -> 0.0035194711 | V14: ='Income Statement'!V46/'Balance Sheet'!V21 -> -0.014659887 | W14: ='Income Statement'!W46/'Balance Sheet'!W21 -> 0.018484601 | X14: ='Income Statement'!X46/'Balance Sheet'!X21 -> 0.011862097 | Y14: ='Income Statement'!Y46/'Balance Sheet'!Y21 -> 0.022331239 | Z14: ='Income Statement'!Z46/'Balance Sheet'!Z21 -> 0.0064970976
A15: Return on Equity (ROE) | C15: ='Income Statement'!C46/'Balance Sheet'!C39 -> 0.020231036 | D15: ='Income Statement'!D46/'Balance Sheet'!D39 -> -0.01891815 | E15: ='Income Statement'!E46/'Balance Sheet'!E39 -> 0.013169856 | F15: ='Income Statement'!F46/'Balance Sheet'!F39 -> -0.0164163 | G15: ='Income Statement'!G46/'Balance Sheet'!G39 -> -0.043049556 | H15: ='Income Statement'!H46/'Balance Sheet'!H39 -> -0.12429314 | I15: ='Income Statement'!I46/'Balance Sheet'!I39 -> -0.093253998 | J15: ='Income Statement'!J46/'Balance Sheet'!J39 -> -0.0045452108 | ... L15: ='Income Statement'!L46/'Balance Sheet'!L39 -> 0.11668302 | R15: ='Income Statement'!R46/'Balance Sheet'!R39 -> -0.022453467 | S15: ='Income Statement'!S46/'Balance Sheet'!S39 -> 0.0077118858 | T15: ='Income Statement'!T46/'Balance Sheet'!T39 -> -0.0042618211 | U15: ='Income Statement'!U46/'Balance Sheet'!U39 -> 0.0072072484 | V15: ='Income Statement'!V46/'Balance Sheet'!V39 -> -0.029381211 | W15: ='Income Statement'!W46/'Balance Sheet'!W39 -> 0.033753004 | X15: ='Income Statement'!X46/'Balance Sheet'!X39 -> 0.020417133 | Y15: ='Income Statement'!Y46/'Balance Sheet'!Y39 -> 0.039791661 | Z15: ='Income Statement'!Z46/'Balance Sheet'!Z39 -> 0.012505077
A16: Asset Turnover | C16: ='Income Statement'!C13/'Balance Sheet'!C21 -> 0.47227039 | D16: ='Income Statement'!D13/'Balance Sheet'!D21 -> 0.32948326 | E16: ='Income Statement'!E13/'Balance Sheet'!E21 -> 0.33203797 | F16: ='Income Statement'!F13/'Balance Sheet'!F21 -> 0.31389152 | G16: ='Income Statement'!G13/'Balance Sheet'!G21 -> 0.32011913 | H16: ='Income Statement'!H13/'Balance Sheet'!H21 -> 0.35846975 | I16: ='Income Statement'!I13/'Balance Sheet'!I21 -> 0.44644527 | J16: ='Income Statement'!J13/'Balance Sheet'!J21 -> 0.44041667 | ... L16: ='Income Statement'!L13/'Balance Sheet'!L21 -> 0.57252383 | R16: ='Income Statement'!R13/'Balance Sheet'!R21 -> 0.10804716 | S16: ='Income Statement'!S13/'Balance Sheet'!S21 -> 0.11963974 | T16: ='Income Statement'!T13/'Balance Sheet'!T21 -> 0.11797797 | U16: ='Income Statement'!U13/'Balance Sheet'!U21 -> 0.10124439 | V16: ='Income Statement'!V13/'Balance Sheet'!V21 -> 0.1138435 | W16: ='Income Statement'!W13/'Balance Sheet'!W21 -> 0.11796609 | X16: ='Income Statement'!X13/'Balance Sheet'!X21 -> 0.12603156 | Y16: ='Income Statement'!Y13/'Balance Sheet'!Y21 -> 0.13340602 | Z16: ='Income Statement'!Z13/'Balance Sheet'!Z21 -> 0.14695132
A18: 3. SOLVENCY
A19: Equity Ratio | C19: ='Balance Sheet'!C39/'Balance Sheet'!C21 -> 0.82795456 | D19: ='Balance Sheet'!D39/'Balance Sheet'!D21 -> 0.71343114 | E19: ='Balance Sheet'!E39/'Balance Sheet'!E21 -> 0.72645495 | F19: ='Balance Sheet'!F39/'Balance Sheet'!F21 -> 0.70057999 | G19: ='Balance Sheet'!G39/'Balance Sheet'!G21 -> 0.66537344 | H19: ='Balance Sheet'!H39/'Balance Sheet'!H21 -> 0.64037184 | I19: ='Balance Sheet'!I39/'Balance Sheet'!I21 -> 0.59148533 | J19: ='Balance Sheet'!J39/'Balance Sheet'!J21 -> 0.6031243 | ... L19: ='Balance Sheet'!L39/'Balance Sheet'!L21 -> 0.4632177 | R19: ='Balance Sheet'!R39/'Balance Sheet'!R21 -> 0.62807402 | S19: ='Balance Sheet'!S39/'Balance Sheet'!S21 -> 0.62383935 | T19: ='Balance Sheet'!T39/'Balance Sheet'!T21 -> 0.63007365 | U19: ='Balance Sheet'!U39/'Balance Sheet'!U21 -> 0.48832382 | V19: ='Balance Sheet'!V39/'Balance Sheet'!V21 -> 0.49895449 | W19: ='Balance Sheet'!W39/'Balance Sheet'!W21 -> 0.54764313 | X19: ='Balance Sheet'!X39/'Balance Sheet'!X21 -> 0.58098738 | Y19: ='Balance Sheet'!Y39/'Balance Sheet'!Y21 -> 0.56120398 | Z19: ='Balance Sheet'!Z39/'Balance Sheet'!Z21 -> 0.51955677
A20: Debt to Assets | C20: ='Balance Sheet'!C30/'Balance Sheet'!C21 -> 0 | D20: ='Balance Sheet'!D30/'Balance Sheet'!D21 -> 0.1539936 | E20: ='Balance Sheet'!E30/'Balance Sheet'!E21 -> 0.14643628 | F20: ='Balance Sheet'!F30/'Balance Sheet'!F21 -> 0.13963157 | G20: ='Balance Sheet'!G30/'Balance Sheet'!G21 -> 0.14808267 | H20: ='Balance Sheet'!H30/'Balance Sheet'!H21 -> 0.15802041 | I20: ='Balance Sheet'!I30/'Balance Sheet'!I21 -> 0.1958545 | J20: ='Balance Sheet'!J30/'Balance Sheet'!J21 -> 0 | ... L20: ='Balance Sheet'!L30/'Balance Sheet'!L21 -> 0.26313861 | R20: ='Balance Sheet'!R30/'Balance Sheet'!R21 -> 0.20712733 | S20: ='Balance Sheet'!S30/'Balance Sheet'!S21 -> 0.19768018 | T20: ='Balance Sheet'!T30/'Balance Sheet'!T21 -> 0.19532457 | U20: ='Balance Sheet'!U30/'Balance Sheet'!U21 -> 0.25872098 | V20: ='Balance Sheet'!V30/'Balance Sheet'!V21 -> 0.26460237 | W20: ='Balance Sheet'!W30/'Balance Sheet'!W21 -> 0.27077041 | X20: ='Balance Sheet'!X30/'Balance Sheet'!X21 -> 0.25591447 | Y20: ='Balance Sheet'!Y30/'Balance Sheet'!Y21 -> 0.2512582 | Z20: ='Balance Sheet'!Z30/'Balance Sheet'!Z21 -> 0.2671285
A22: 4. LIQUIDITY
A23: Current Ratio | C23: ='Balance Sheet'!C12/'Balance Sheet'!C27 -> 4.1514277 | D23: ='Balance Sheet'!D12/'Balance Sheet'!D27 -> 5.1330047 | E23: ='Balance Sheet'!E12/'Balance Sheet'!E27 -> 5.7474599 | F23: ='Balance Sheet'!F12/'Balance Sheet'!F27 -> 5.9646089 | G23: ='Balance Sheet'!G12/'Balance Sheet'!G27 -> 4.5128932 | H23: ='Balance Sheet'!H12/'Balance Sheet'!H27 -> 3.7115146 | I23: ='Balance Sheet'!I12/'Balance Sheet'!I27 -> 2.945936 | J23: ='Balance Sheet'!J12/'Balance Sheet'!J27 -> 1.546657 | ... L23: ='Balance Sheet'!L12/'Balance Sheet'!L27 -> 1.7862789 | R23: ='Balance Sheet'!R12/'Balance Sheet'!R27 -> 3.7229081 | S23: ='Balance Sheet'!S12/'Balance Sheet'!S27 -> 3.4539658 | T23: ='Balance Sheet'!T12/'Balance Sheet'!T27 -> 1.5344782 | U23: ='Balance Sheet'!U12/'Balance Sheet'!U27 -> 2.6612379 | V23: ='Balance Sheet'!V12/'Balance Sheet'!V27 -> 2.6457424 | W23: ='Balance Sheet'!W12/'Balance Sheet'!W27 -> 3.234599 | X23: ='Balance Sheet'!X12/'Balance Sheet'!X27 -> 3.4808161 | Y23: ='Balance Sheet'!Y12/'Balance Sheet'!Y27 -> 2.9329801 | Z23: ='Balance Sheet'!Z12/'Balance Sheet'!Z27 -> 2.4446322
A24: Cash Ratio | C24: =('Balance Sheet'!C7+'Balance Sheet'!C8)/'Balance Sheet'!C27 -> 3.5033432 | D24: =('Balance Sheet'!D7+'Balance Sheet'!D8)/'Balance Sheet'!D27 -> 4.4808593 | E24: =('Balance Sheet'!E7+'Balance Sheet'!E8)/'Balance Sheet'!E27 -> 4.8401745 | F24: =('Balance Sheet'!F7+'Balance Sheet'!F8)/'Balance Sheet'!F27 -> 5.0333307 | G24: =('Balance Sheet'!G7+'Balance Sheet'!G8)/'Balance Sheet'!G27 -> 3.7275219 | H24: =('Balance Sheet'!H7+'Balance Sheet'!H8)/'Balance Sheet'!H27 -> 2.8921954 | I24: =('Balance Sheet'!I7+'Balance Sheet'!I8)/'Balance Sheet'!I27 -> 2.1397494 | J24: =('Balance Sheet'!J7+'Balance Sheet'!J8)/'Balance Sheet'!J27 -> 1.198097 | ... L24: =('Balance Sheet'!L7+'Balance Sheet'!L8)/'Balance Sheet'!L27 -> 1.1332813 | R24: =('Balance Sheet'!R7+'Balance Sheet'!R8)/'Balance Sheet'!R27 -> 2.7172825 | S24: =('Balance Sheet'!S7+'Balance Sheet'!S8)/'Balance Sheet'!S27 -> 2.532347 | T24: =('Balance Sheet'!T7+'Balance Sheet'!T8)/'Balance Sheet'!T27 -> 1.1099365 | U24: =('Balance Sheet'!U7+'Balance Sheet'!U8)/'Balance Sheet'!U27 -> 2.1753064 | V24: =('Balance Sheet'!V7+'Balance Sheet'!V8)/'Balance Sheet'!V27 -> 2.0923586 | W24: =('Balance Sheet'!W7+'Balance Sheet'!W8)/'Balance Sheet'!W27 -> 2.2675665 | X24: =('Balance Sheet'!X7+'Balance Sheet'!X8)/'Balance Sheet'!X27 -> 2.5955579 | Y24: =('Balance Sheet'!Y7+'Balance Sheet'!Y8)/'Balance Sheet'!Y27 -> 2.0026167 | Z24: =('Balance Sheet'!Z7+'Balance Sheet'!Z8)/'Balance Sheet'!Z27 -> 1.5075859
A26: 5. COVERAGE
A27: Interest Coverage | C27: ='Income Statement'!C38/'Income Statement'!C42*-1 -> 1681.6154 | D27: ='Income Statement'!D38/'Income Statement'!D42*-1 -> -2.4253337 | E27: ='Income Statement'!E38/'Income Statement'!E42*-1 -> 0.084862121 | F27: ='Income Statement'!F38/'Income Statement'!F42*-1 -> -1.3310671 | G27: ='Income Statement'!G38/'Income Statement'!G42*-1 -> -5.6428839 | H27: ='Income Statement'!H38/'Income Statement'!H42*-1 -> -10.256454 | I27: ='Income Statement'!I38/'Income Statement'!I42*-1 -> -22.258785 | J27: ='Income Statement'!J38/'Income Statement'!J42*-1 -> -7.8024636 | ... L27: ='Income Statement'!L38/'Income Statement'!L42*-1 -> 11.248424 | R27: ='Income Statement'!R38/'Income Statement'!R42*-1 -> -20.071895 | S27: ='Income Statement'!S38/'Income Statement'!S42*-1 -> -7.3345154 | T27: ='Income Statement'!T38/'Income Statement'!T42*-1 -> -9.9027284 | U27: ='Income Statement'!U38/'Income Statement'!U42*-1 -> -2.2890398 | V27: ='Income Statement'!V38/'Income Statement'!V42*-1 -> 2.8025341 | W27: ='Income Statement'!W38/'Income Statement'!W42*-1 -> 1.2181025 | X27: ='Income Statement'!X38/'Income Statement'!X42*-1 -> 5.5791063 | Y27: ='Income Statement'!Y38/'Income Statement'!Y42*-1 -> 11.529994 | Z27: ='Income Statement'!Z38/'Income Statement'!Z42*-1 -> 9.2335744
A29: 6. CASH CONVERSION
A30: CFO Margin | C30: ='Cash Flow Statement'!C33/'Income Statement'!C13 -> 0.27232584 | D30: ='Cash Flow Statement'!D33/'Income Statement'!D13 -> 0.21514776 | E30: ='Cash Flow Statement'!E33/'Income Statement'!E13 -> 0.16139505 | F30: ='Cash Flow Statement'!F33/'Income Statement'!F13 -> 0.15231703 | G30: ='Cash Flow Statement'!G33/'Income Statement'!G13 -> 0.15013044 | H30: ='Cash Flow Statement'!H33/'Income Statement'!H13 -> -0.046688834 | I30: ='Cash Flow Statement'!I33/'Income Statement'!I13 -> 0.042409435 | J30: ='Cash Flow Statement'!J33/'Income Statement'!J13 -> 0.19964161 | ... L30: ='Cash Flow Statement'!L33/'Income Statement'!L13 -> 0.26414923 | R30: ='Cash Flow Statement'!R33/'Income Statement'!R13 -> -0.34754372 | S30: ='Cash Flow Statement'!S33/'Income Statement'!S13 -> -0.011756062 | T30: ='Cash Flow Statement'!T33/'Income Statement'!T13 -> 0.008189365 | U30: ='Cash Flow Statement'!U33/'Income Statement'!U13 -> -0.23699035 | V30: ='Cash Flow Statement'!V33/'Income Statement'!V13 -> 0.081822578 | W30: ='Cash Flow Statement'!W33/'Income Statement'!W13 -> 0.19091814 | X30: ='Cash Flow Statement'!X33/'Income Statement'!X13 -> -0.20261605 | Y30: ='Cash Flow Statement'!Y33/'Income Statement'!Y13 -> 0.12433479 | Z30: ='Cash Flow Statement'!Z33/'Income Statement'!Z13 -> 0.28407612
A31: Capex Intensity | C31: =('Cash Flow Statement'!C37+'Cash Flow Statement'!C38)/'Income Statement'!C13*-1 -> 0.013090418 | D31: =('Cash Flow Statement'!D37+'Cash Flow Statement'!D38)/'Income Statement'!D13*-1 -> 0.018397822 | E31: =('Cash Flow Statement'!E37+'Cash Flow Statement'!E38)/'Income Statement'!E13*-1 -> 0.067902779 | F31: =('Cash Flow Statement'!F37+'Cash Flow Statement'!F38)/'Income Statement'!F13*-1 -> 0.034567908 | G31: =('Cash Flow Statement'!G37+'Cash Flow Statement'!G38)/'Income Statement'!G13*-1 -> 0.038820505 | H31: =('Cash Flow Statement'!H37+'Cash Flow Statement'!H38)/'Income Statement'!H13*-1 -> 0.026797471 | I31: =('Cash Flow Statement'!I37+'Cash Flow Statement'!I38)/'Income Statement'!I13*-1 -> 0.019249101 | J31: =('Cash Flow Statement'!J37+'Cash Flow Statement'!J38)/'Income Statement'!J13*-1 -> 0.018895519 | ... L31: =('Cash Flow Statement'!L37+'Cash Flow Statement'!L38)/'Income Statement'!L13*-1 -> 0.021051768 | R31: =('Cash Flow Statement'!R37+'Cash Flow Statement'!R38)/'Income Statement'!R13*-1 -> 0.022612544 | S31: =('Cash Flow Statement'!S37+'Cash Flow Statement'!S38)/'Income Statement'!S13*-1 -> 0.041710773 | T31: =('Cash Flow Statement'!T37+'Cash Flow Statement'!T38)/'Income Statement'!T13*-1 -> 0.058572034 | U31: =('Cash Flow Statement'!U37+'Cash Flow Statement'!U38)/'Income Statement'!U13*-1 -> 0.019307648 | V31: =('Cash Flow Statement'!V37+'Cash Flow Statement'!V38)/'Income Statement'!V13*-1 -> 0.030361338 | W31: =('Cash Flow Statement'!W37+'Cash Flow Statement'!W38)/'Income Statement'!W13*-1 -> 0.045341183 | X31: =('Cash Flow Statement'!X37+'Cash Flow Statement'!X38)/'Income Statement'!X13*-1 -> 0.029960408 | Y31: =('Cash Flow Statement'!Y37+'Cash Flow Statement'!Y38)/'Income Statement'!Y13*-1 -> 0.045542266 | Z31: =('Cash Flow Statement'!Z37+'Cash Flow Statement'!Z38)/'Income Statement'!Z13*-1 -> 0.064081537
A32: FCF Margin | C32: =('Cash Flow Statement'!C33+'Cash Flow Statement'!C37+'Cash Flow Statement'!C38)/'Income Statement'!C13 -> 0.25923542 | D32: =('Cash Flow Statement'!D33+'Cash Flow Statement'!D37+'Cash Flow Statement'!D38)/'Income Statement'!D13 -> 0.19674994 | E32: =('Cash Flow Statement'!E33+'Cash Flow Statement'!E37+'Cash Flow Statement'!E38)/'Income Statement'!E13 -> 0.093492274 | F32: =('Cash Flow Statement'!F33+'Cash Flow Statement'!F37+'Cash Flow Statement'!F38)/'Income Statement'!F13 -> 0.11774913 | G32: =('Cash Flow Statement'!G33+'Cash Flow Statement'!G37+'Cash Flow Statement'!G38)/'Income Statement'!G13 -> 0.11130993 | H32: =('Cash Flow Statement'!H33+'Cash Flow Statement'!H37+'Cash Flow Statement'!H38)/'Income Statement'!H13 -> -0.073486305 | I32: =('Cash Flow Statement'!I33+'Cash Flow Statement'!I37+'Cash Flow Statement'!I38)/'Income Statement'!I13 -> 0.023160334 | J32: =('Cash Flow Statement'!J33+'Cash Flow Statement'!J37+'Cash Flow Statement'!J38)/'Income Statement'!J13 -> 0.18074609 | ... L32: =('Cash Flow Statement'!L33+'Cash Flow Statement'!L37+'Cash Flow Statement'!L38)/'Income Statement'!L13 -> 0.24309746 | R32: =('Cash Flow Statement'!R33+'Cash Flow Statement'!R37+'Cash Flow Statement'!R38)/'Income Statement'!R13 -> -0.37015626 | S32: =('Cash Flow Statement'!S33+'Cash Flow Statement'!S37+'Cash Flow Statement'!S38)/'Income Statement'!S13 -> -0.053466834 | T32: =('Cash Flow Statement'!T33+'Cash Flow Statement'!T37+'Cash Flow Statement'!T38)/'Income Statement'!T13 -> -0.050382669 | U32: =('Cash Flow Statement'!U33+'Cash Flow Statement'!U37+'Cash Flow Statement'!U38)/'Income Statement'!U13 -> -0.256298 | V32: =('Cash Flow Statement'!V33+'Cash Flow Statement'!V37+'Cash Flow Statement'!V38)/'Income Statement'!V13 -> 0.051461241 | W32: =('Cash Flow Statement'!W33+'Cash Flow Statement'!W37+'Cash Flow Statement'!W38)/'Income Statement'!W13 -> 0.14557695 | X32: =('Cash Flow Statement'!X33+'Cash Flow Statement'!X37+'Cash Flow Statement'!X38)/'Income Statement'!X13 -> -0.23257646 | Y32: =('Cash Flow Statement'!Y33+'Cash Flow Statement'!Y37+'Cash Flow Statement'!Y38)/'Income Statement'!Y13 -> 0.07879252 | Z32: =('Cash Flow Statement'!Z33+'Cash Flow Statement'!Z37+'Cash Flow Statement'!Z38)/'Income Statement'!Z13 -> 0.21999458
A33: FCF Conversion (FCF/Net Income) | C33: =('Cash Flow Statement'!C33+'Cash Flow Statement'!C37+'Cash Flow Statement'!C38)/'Income Statement'!C46 -> 7.3090416 | D33: =('Cash Flow Statement'!D33+'Cash Flow Statement'!D37+'Cash Flow Statement'!D38)/'Income Statement'!D46 -> -4.8030513 | E33: =('Cash Flow Statement'!E33+'Cash Flow Statement'!E37+'Cash Flow Statement'!E38)/'Income Statement'!E46 -> 3.2446942 | F33: =('Cash Flow Statement'!F33+'Cash Flow Statement'!F37+'Cash Flow Statement'!F38)/'Income Statement'!F46 -> -3.2136922 | G33: =('Cash Flow Statement'!G33+'Cash Flow Statement'!G37+'Cash Flow Statement'!G38)/'Income Statement'!G46 -> -1.2439743 | H33: =('Cash Flow Statement'!H33+'Cash Flow Statement'!H37+'Cash Flow Statement'!H38)/'Income Statement'!H46 -> 0.33096308 | I33: =('Cash Flow Statement'!I33+'Cash Flow Statement'!I37+'Cash Flow Statement'!I38)/'Income Statement'!I46 -> -0.18745698 | J33: =('Cash Flow Statement'!J33+'Cash Flow Statement'!J37+'Cash Flow Statement'!J38)/'Income Statement'!J46 -> -29.038342 | ... L33: =('Cash Flow Statement'!L33+'Cash Flow Statement'!L37+'Cash Flow Statement'!L38)/'Income Statement'!L46 -> 2.5750235 | R33: =('Cash Flow Statement'!R33+'Cash Flow Statement'!R37+'Cash Flow Statement'!R38)/'Income Statement'!R46 -> 2.8359868 | S33: =('Cash Flow Statement'!S33+'Cash Flow Statement'!S37+'Cash Flow Statement'!S38)/'Income Statement'!S46 -> -1.329617 | T33: =('Cash Flow Statement'!T33+'Cash Flow Statement'!T37+'Cash Flow Statement'!T38)/'Income Statement'!T46 -> 2.2135816 | U33: =('Cash Flow Statement'!U33+'Cash Flow Statement'!U37+'Cash Flow Statement'!U38)/'Income Statement'!U46 -> -7.3729073 | V33: =('Cash Flow Statement'!V33+'Cash Flow Statement'!V37+'Cash Flow Statement'!V38)/'Income Statement'!V46 -> -0.3996298 | W33: =('Cash Flow Statement'!W33+'Cash Flow Statement'!W37+'Cash Flow Statement'!W38)/'Income Statement'!W46 -> 0.92905134 | X33: =('Cash Flow Statement'!X33+'Cash Flow Statement'!X37+'Cash Flow Statement'!X38)/'Income Statement'!X46 -> -2.4710617 | Y33: =('Cash Flow Statement'!Y33+'Cash Flow Statement'!Y37+'Cash Flow Statement'!Y38)/'Income Statement'!Y46 -> 0.47070371 | Z33: =('Cash Flow Statement'!Z33+'Cash Flow Statement'!Z37+'Cash Flow Statement'!Z38)/'Income Statement'!Z46 -> 4.9758363
A34: D&A / Capex | C34: ='Cash Flow Statement'!C9/('Cash Flow Statement'!C37+'Cash Flow Statement'!C38)*-1 -> 2.8073463 | D34: ='Cash Flow Statement'!D9/('Cash Flow Statement'!D37+'Cash Flow Statement'!D38)*-1 -> 2.9648655 | E34: ='Cash Flow Statement'!E9/('Cash Flow Statement'!E37+'Cash Flow Statement'!E38)*-1 -> 0.81775385 | F34: ='Cash Flow Statement'!F9/('Cash Flow Statement'!F37+'Cash Flow Statement'!F38)*-1 -> 1.6617693 | G34: ='Cash Flow Statement'!G9/('Cash Flow Statement'!G37+'Cash Flow Statement'!G38)*-1 -> 1.2807583 | H34: ='Cash Flow Statement'!H9/('Cash Flow Statement'!H37+'Cash Flow Statement'!H38)*-1 -> 1.5402278 | I34: ='Cash Flow Statement'!I9/('Cash Flow Statement'!I37+'Cash Flow Statement'!I38)*-1 -> 1.4252597 | J34: ='Cash Flow Statement'!J9/('Cash Flow Statement'!J37+'Cash Flow Statement'!J38)*-1 -> 1.2041345 | ... L34: ='Cash Flow Statement'!L9/('Cash Flow Statement'!L37+'Cash Flow Statement'!L38)*-1 -> 0.89996458 | R34: ='Cash Flow Statement'!R9/('Cash Flow Statement'!R37+'Cash Flow Statement'!R38)*-1 -> 1.1603412 | S34: ='Cash Flow Statement'!S9/('Cash Flow Statement'!S37+'Cash Flow Statement'!S38)*-1 -> 1.0881768 | T34: ='Cash Flow Statement'!T9/('Cash Flow Statement'!T37+'Cash Flow Statement'!T38)*-1 -> 1.1722352 | U34: ='Cash Flow Statement'!U9/('Cash Flow Statement'!U37+'Cash Flow Statement'!U38)*-1 -> 1.1514972 | V34: ='Cash Flow Statement'!V9/('Cash Flow Statement'!V37+'Cash Flow Statement'!V38)*-1 -> 1.3167596 | W34: ='Cash Flow Statement'!W9/('Cash Flow Statement'!W37+'Cash Flow Statement'!W38)*-1 -> 1.3178539 | X34: ='Cash Flow Statement'!X9/('Cash Flow Statement'!X37+'Cash Flow Statement'!X38)*-1 -> 0.63837046 | Y34: ='Cash Flow Statement'!Y9/('Cash Flow Statement'!Y37+'Cash Flow Statement'!Y38)*-1 -> 0.8194937 | Z34: ='Cash Flow Statement'!Z9/('Cash Flow Statement'!Z37+'Cash Flow Statement'!Z38)*-1 -> 0.86423994
A36: 7. EARNINGS QUALITY
A37: CFO / Net Income | C37: ='Cash Flow Statement'!C33/'Income Statement'!C46 -> 7.6781208 | D37: ='Cash Flow Statement'!D33/'Income Statement'!D46 -> -5.2521781 | E37: ='Cash Flow Statement'!E33/'Income Statement'!E46 -> 5.6012927 | F37: ='Cash Flow Statement'!F33/'Income Statement'!F46 -> -4.1571439 | G37: ='Cash Flow Statement'!G33/'Income Statement'!G46 -> -1.6778234 | H37: ='Cash Flow Statement'!H33/'Income Statement'!H46 -> 0.21027429 | I37: ='Cash Flow Statement'!I33/'Income Statement'!I46 -> -0.3432569 | J37: ='Cash Flow Statement'!J33/'Income Statement'!J46 -> -32.074062 | ... L37: ='Cash Flow Statement'!L33/'Income Statement'!L46 -> 2.7980156 | R37: ='Cash Flow Statement'!R33/'Income Statement'!R46 -> 2.6627387 | S37: ='Cash Flow Statement'!S33/'Income Statement'!S46 -> -0.29235057 | T37: ='Cash Flow Statement'!T33/'Income Statement'!T46 -> -0.35980285 | U37: ='Cash Flow Statement'!U33/'Income Statement'!U46 -> -6.8174855 | V37: ='Cash Flow Statement'!V33/'Income Statement'!V46 -> -0.63540521 | W37: ='Cash Flow Statement'!W33/'Income Statement'!W46 -> 1.2184123 | X37: ='Cash Flow Statement'!X33/'Income Statement'!X46 -> -2.1527405 | Y37: ='Cash Flow Statement'!Y33/'Income Statement'!Y46 -> 0.74277159 | Z37: ='Cash Flow Statement'!Z33/'Income Statement'!Z46 -> 6.4252322
A38: Accrual Ratio | C38: =('Income Statement'!C46-'Cash Flow Statement'!C33)/'Balance Sheet'!C21 -> -0.11186105 | D38: =('Income Statement'!D46-'Cash Flow Statement'!D33)/'Balance Sheet'!D21 -> -0.084384382 | E38: =('Income Statement'!E46-'Cash Flow Statement'!E33)/'Balance Sheet'!E21 -> -0.044021979 | F38: =('Income Statement'!F46-'Cash Flow Statement'!F33)/'Balance Sheet'!F21 -> -0.059311957 | G38: =('Income Statement'!G46-'Cash Flow Statement'!G33)/'Balance Sheet'!G21 -> -0.076703656 | H38: =('Income Statement'!H46-'Cash Flow Statement'!H33)/'Balance Sheet'!H21 -> -0.062857289 | I38: =('Income Statement'!I46-'Cash Flow Statement'!I33)/'Balance Sheet'!I21 -> -0.074091863 | J38: =('Income Statement'!J46-'Cash Flow Statement'!J33)/'Balance Sheet'!J21 -> -0.090666821 | ... L38: =('Income Statement'!L46-'Cash Flow Statement'!L33)/'Balance Sheet'!L21 -> -0.097182091 | R38: =('Income Statement'!R46-'Cash Flow Statement'!R33)/'Balance Sheet'!R21 -> 0.023448672 | S38: =('Income Statement'!S46-'Cash Flow Statement'!S33)/'Balance Sheet'!S21 -> 0.0062174699 | T38: =('Income Statement'!T46-'Cash Flow Statement'!T33)/'Balance Sheet'!T21 -> -0.0036514258 | U38: =('Income Statement'!U46-'Cash Flow Statement'!U33)/'Balance Sheet'!U21 -> 0.027513414 | V38: =('Income Statement'!V46-'Cash Flow Statement'!V33)/'Balance Sheet'!V21 -> -0.023974856 | W38: =('Income Statement'!W46-'Cash Flow Statement'!W33)/'Balance Sheet'!W21 -> -0.0040372642 | X38: =('Income Statement'!X46-'Cash Flow Statement'!X33)/'Balance Sheet'!X21 -> 0.037398113 | Y38: =('Income Statement'!Y46-'Cash Flow Statement'!Y33)/'Balance Sheet'!Y21 -> 0.0057442291 | Z38: =('Income Statement'!Z46-'Cash Flow Statement'!Z33)/'Balance Sheet'!Z21 -> -0.035248263
A40: 8. GROWTH
A41: Revenue Growth YoY | C41: ='Income Statement'!C13/'Income Statement'!B13-1 -> #DIV/0! | D41: ='Income Statement'!D13/'Income Statement'!C13-1 -> 0.28126932 | E41: ='Income Statement'!E13/'Income Statement'!D13-1 -> 0.10211397 | F41: ='Income Statement'!F13/'Income Statement'!E13-1 -> 0.031678327 | G41: ='Income Statement'!G13/'Income Statement'!F13-1 -> 0.0012932655 | H41: ='Income Statement'!H13/'Income Statement'!G13-1 -> 0.093300254 | I41: ='Income Statement'!I13/'Income Statement'!H13-1 -> 0.11410953 | J41: ='Income Statement'!J13/'Income Statement'!I13-1 -> 0.083014025 | ... L41: ='Income Statement'!L13/'Income Statement'!K13-1 -> 0.22695493 | R41: ='Income Statement'!R13/'Income Statement'!Q13-1 -> #DIV/0! | S41: ='Income Statement'!S13/'Income Statement'!R13-1 -> 0.16146996 | T41: ='Income Statement'!T13/'Income Statement'!S13-1 -> -0.00090910223 | U41: ='Income Statement'!U13/'Income Statement'!T13-1 -> 0.092334987 | V41: ='Income Statement'!V13/'Income Statement'!U13-1 -> 0.10109889 | W41: ='Income Statement'!W13/'Income Statement'!V13-1 -> 0.013914605 | X41: ='Income Statement'!X13/'Income Statement'!W13-1 -> 0.13332175 | Y41: ='Income Statement'!Y13/'Income Statement'!X13-1 -> 0.079533669 | Z41: ='Income Statement'!Z13/'Income Statement'!Y13-1 -> 0.03744413
A42: Net Income Growth YoY | C42: ='Income Statement'!C46/'Income Statement'!B46-1 -> #DIV/0! | D42: ='Income Statement'!D46/'Income Statement'!C46-1 -> -2.479803 | E42: ='Income Statement'!E46/'Income Statement'!D46-1 -> -1.7752309 | F42: ='Income Statement'!F46/'Income Statement'!E46-1 -> -2.311885 | G42: ='Income Statement'!G46/'Income Statement'!F46-1 -> 1.4452901 | H42: ='Income Statement'!H46/'Income Statement'!G46-1 -> 1.7129625 | I42: ='Income Statement'!I46/'Income Statement'!H46-1 -> -0.38006773 | J42: ='Income Statement'!J46/'Income Statement'!I46-1 -> -0.94543829 | ... L42: ='Income Statement'!L46/'Income Statement'!K46-1 -> 0.99534411 | R42: ='Income Statement'!R46/'Income Statement'!Q46-1 -> #DIV/0! | S42: ='Income Statement'!S46/'Income Statement'!R46-1 -> -1.3578368 | T42: ='Income Statement'!T46/'Income Statement'!S46-1 -> -1.5655002 | U42: ='Income Statement'!U46/'Income Statement'!T46-1 -> -2.6683096 | V42: ='Income Statement'!V46/'Income Statement'!U46-1 -> -5.0788927 | W42: ='Income Statement'!W46/'Income Statement'!V46-1 -> -2.2337634 | X42: ='Income Statement'!X46/'Income Statement'!W46-1 -> -0.31925812 | Y42: ='Income Statement'!Y46/'Income Statement'!X46-1 -> 0.91995656 | Z42: ='Income Statement'!Z46/'Income Statement'!Y46-1 -> -0.72598569
A43: CFO Growth YoY | C43: ='Cash Flow Statement'!C33/'Cash Flow Statement'!B33-1 -> #DIV/0! | D43: ='Cash Flow Statement'!D33/'Cash Flow Statement'!C33-1 -> 0.012251458 | E43: ='Cash Flow Statement'!E33/'Cash Flow Statement'!D33-1 -> -0.17323917 | F43: ='Cash Flow Statement'!F33/'Cash Flow Statement'!E33-1 -> -0.026350688 | G43: ='Cash Flow Statement'!G33/'Cash Flow Statement'!F33-1 -> -0.013080855 | H43: ='Cash Flow Statement'!H33/'Cash Flow Statement'!G33-1 -> -1.3400038 | I43: ='Cash Flow Statement'!I33/'Cash Flow Statement'!H33-1 -> -2.0119926 | J43: ='Cash Flow Statement'!J33/'Cash Flow Statement'!I33-1 -> 4.098268 | ... L43: ='Cash Flow Statement'!L33/'Cash Flow Statement'!K33-1 -> 0.29530989 | R43: ='Cash Flow Statement'!R33/'Cash Flow Statement'!Q33-1 -> #DIV/0! | S43: ='Cash Flow Statement'!S33/'Cash Flow Statement'!R33-1 -> -0.96071196 | T43: ='Cash Flow Statement'!T33/'Cash Flow Statement'!S33-1 -> -1.6959746 | U43: ='Cash Flow Statement'!U33/'Cash Flow Statement'!T33-1 -> -32.610857 | V43: ='Cash Flow Statement'!V33/'Cash Flow Statement'!U33-1 -> -1.3801621 | W43: ='Cash Flow Statement'!W33/'Cash Flow Statement'!V33-1 -> 1.3657857 | X43: ='Cash Flow Statement'!X33/'Cash Flow Statement'!W33-1 -> -2.2027625 | Y43: ='Cash Flow Statement'!Y33/'Cash Flow Statement'!X33-1 -> -1.6624529 | Z43: ='Cash Flow Statement'!Z33/'Cash Flow Statement'!Y33-1 -> 1.3703189
A45: 9. WORKING CAPITAL
A46: Days Sales Outstanding (DSO) | C46: ='Balance Sheet'!C9/'Income Statement'!C13*365 -> 56.901212 | D46: ='Balance Sheet'!D9/'Income Statement'!D13*365 -> 69.80157 | E46: ='Balance Sheet'!E9/'Income Statement'!E13*365 -> 70.230315 | F46: ='Balance Sheet'!F9/'Income Statement'!F13*365 -> 56.173968 | G46: ='Balance Sheet'!G9/'Income Statement'!G13*365 -> 51.105215 | H46: ='Balance Sheet'!H9/'Income Statement'!H13*365 -> 64.588975 | I46: ='Balance Sheet'!I9/'Income Statement'!I13*365 -> 60.891322 | J46: ='Balance Sheet'!J9/'Income Statement'!J13*365 -> 51.125842 | ... L46: ='Balance Sheet'!L9/'Income Statement'!L13*365 -> 47.925697 | R46: ='Balance Sheet'!R9/'Income Statement'!R13*365 -> 163.80978 | S46: ='Balance Sheet'!S9/'Income Statement'!S13*365 -> 194.30848 | T46: ='Balance Sheet'!T9/'Income Statement'!T13*365 -> 158.2428 | U46: ='Balance Sheet'!U9/'Income Statement'!U13*365 -> 135.32993 | V46: ='Balance Sheet'!V9/'Income Statement'!V13*365 -> 155.0897 | W46: ='Balance Sheet'!W9/'Income Statement'!W13*365 -> 183.17402 | X46: ='Balance Sheet'!X9/'Income Statement'!X13*365 -> 103.80322 | Y46: ='Balance Sheet'!Y9/'Income Statement'!Y13*365 -> 165.61636 | Z46: ='Balance Sheet'!Z9/'Income Statement'!Z13*365 -> 136.04233
A49: 10. CASH FLOW DIRECTION (SOURCES & USES OF CFO)
A50: Operating Cash Flow (Source, $K) | C50: ='Cash Flow Statement'!C33 -> 138759 | D50: ='Cash Flow Statement'!D33 -> 140459 | E50: ='Cash Flow Statement'!E33 -> 116126 | F50: ='Cash Flow Statement'!F33 -> 113066 | G50: ='Cash Flow Statement'!G33 -> 111587 | H50: ='Cash Flow Statement'!H33 -> -37940 | I50: ='Cash Flow Statement'!I33 -> 38395 | J50: ='Cash Flow Statement'!J33 -> 195748 | ... L50: ='Cash Flow Statement'!L33 -> 389716 | R50: ='Cash Flow Statement'!R33 -> -72083 | S50: ='Cash Flow Statement'!S33 -> -2832 | T50: ='Cash Flow Statement'!T33 -> 1971 | U50: ='Cash Flow Statement'!U33 -> -62305 | V50: ='Cash Flow Statement'!V33 -> 23686 | W50: ='Cash Flow Statement'!W33 -> 56036 | X50: ='Cash Flow Statement'!X33 -> -67398 | Y50: ='Cash Flow Statement'!Y33 -> 44648 | Z50: ='Cash Flow Statement'!Z33 -> 105830
A51: Capex Deployed (Uses, $K) | C51: ='Cash Flow Statement'!C37+'Cash Flow Statement'!C38 -> -6670 | D51: ='Cash Flow Statement'!D37+'Cash Flow Statement'!D38 -> -12011 | E51: ='Cash Flow Statement'!E37+'Cash Flow Statement'!E38 -> -48857 | F51: ='Cash Flow Statement'!F37+'Cash Flow Statement'!F38 -> -25660 | G51: ='Cash Flow Statement'!G37+'Cash Flow Statement'!G38 -> -28854 | H51: ='Cash Flow Statement'!H37+'Cash Flow Statement'!H38 -> -21776 | I51: ='Cash Flow Statement'!I37+'Cash Flow Statement'!I38 -> -17427 | J51: ='Cash Flow Statement'!J37+'Cash Flow Statement'!J38 -> -18527 | ... L51: ='Cash Flow Statement'!L37+'Cash Flow Statement'!L38 -> -31059 | R51: ='Cash Flow Statement'!R37+'Cash Flow Statement'!R38 -> -4690 | S51: ='Cash Flow Statement'!S37+'Cash Flow Statement'!S38 -> -10048 | T51: ='Cash Flow Statement'!T37+'Cash Flow Statement'!T38 -> -14097 | U51: ='Cash Flow Statement'!U37+'Cash Flow Statement'!U38 -> -5076 | V51: ='Cash Flow Statement'!V37+'Cash Flow Statement'!V38 -> -8789 | W51: ='Cash Flow Statement'!W37+'Cash Flow Statement'!W38 -> -13308 | X51: ='Cash Flow Statement'!X37+'Cash Flow Statement'!X38 -> -9966 | Y51: ='Cash Flow Statement'!Y37+'Cash Flow Statement'!Y38 -> -16354 | Z51: ='Cash Flow Statement'!Z37+'Cash Flow Statement'!Z38 -> -23873
A52: M&A Deployed (Uses, $K) | C52: ='Cash Flow Statement'!C41 -> -187590 | D52: ='Cash Flow Statement'!D41 -> -130059 | E52: ='Cash Flow Statement'!E41 -> 0 | F52: ='Cash Flow Statement'!F41 -> 0 | G52: ='Cash Flow Statement'!G41 -> 0 | H52: ='Cash Flow Statement'!H41 -> -43830 | I52: ='Cash Flow Statement'!I41 -> 0 | J52: ='Cash Flow Statement'!J41 -> 0 | ... L52: ='Cash Flow Statement'!L41 -> -37953 | R52: ='Cash Flow Statement'!R41 -> 0 | S52: ='Cash Flow Statement'!S41 -> 0 | T52: ='Cash Flow Statement'!T41 -> 0 | U52: ='Cash Flow Statement'!U41 -> 0 | V52: ='Cash Flow Statement'!V41 -> 0 | W52: ='Cash Flow Statement'!W41 -> -26724 | X52: ='Cash Flow Statement'!X41 -> 0 | Y52: ='Cash Flow Statement'!Y41 -> -33252 | Z52: ='Cash Flow Statement'!Z41 -> -33453
A53: Net Debt Service (Uses, $K) | C53: ='Cash Flow Statement'!C44+'Cash Flow Statement'!C45+'Cash Flow Statement'!C46 -> 0 | D53: ='Cash Flow Statement'!D44+'Cash Flow Statement'!D45+'Cash Flow Statement'!D46 -> 387239 | E53: ='Cash Flow Statement'!E44+'Cash Flow Statement'!E45+'Cash Flow Statement'!E46 -> 0 | F53: ='Cash Flow Statement'!F44+'Cash Flow Statement'!F45+'Cash Flow Statement'!F46 -> 0 | G53: ='Cash Flow Statement'!G44+'Cash Flow Statement'!G45+'Cash Flow Statement'!G46 -> 0 | H53: ='Cash Flow Statement'!H44+'Cash Flow Statement'!H45+'Cash Flow Statement'!H46 -> 0 | I53: ='Cash Flow Statement'!I44+'Cash Flow Statement'!I45+'Cash Flow Statement'!I46 -> 0 | J53: ='Cash Flow Statement'!J44+'Cash Flow Statement'!J45+'Cash Flow Statement'!J46 -> 0 | ... L53: ='Cash Flow Statement'!L44+'Cash Flow Statement'!L45+'Cash Flow Statement'!L46 -> 0 | R53: ='Cash Flow Statement'!R44+'Cash Flow Statement'!R45+'Cash Flow Statement'!R46 -> 0 | S53: ='Cash Flow Statement'!S44+'Cash Flow Statement'!S45+'Cash Flow Statement'!S46 -> 0 | T53: ='Cash Flow Statement'!T44+'Cash Flow Statement'!T45+'Cash Flow Statement'!T46 -> 0 | U53: ='Cash Flow Statement'!U44+'Cash Flow Statement'!U45+'Cash Flow Statement'!U46 -> 472356 | V53: ='Cash Flow Statement'!V44+'Cash Flow Statement'!V45+'Cash Flow Statement'!V46 -> 318305 | W53: ='Cash Flow Statement'!W44+'Cash Flow Statement'!W45+'Cash Flow Statement'!W46 -> 139244 | X53: ='Cash Flow Statement'!X44+'Cash Flow Statement'!X45+'Cash Flow Statement'!X46 -> 0 | Y53: ='Cash Flow Statement'!Y44+'Cash Flow Statement'!Y45+'Cash Flow Statement'!Y46 -> 0 | Z53: ='Cash Flow Statement'!Z44+'Cash Flow Statement'!Z45+'Cash Flow Statement'!Z46 -> 0
A54: Buybacks Deployed (Uses, $K) | C54: ='Cash Flow Statement'!C52 -> 0 | D54: ='Cash Flow Statement'!D52 -> 0 | E54: ='Cash Flow Statement'!E52 -> 0 | F54: ='Cash Flow Statement'!F52 -> 0 | G54: ='Cash Flow Statement'!G52 -> -161319 | H54: ='Cash Flow Statement'!H52 -> -37451 | I54: ='Cash Flow Statement'!I52 -> -261807 | J54: ='Cash Flow Statement'!J52 -> 0 | ... L54: ='Cash Flow Statement'!L52 -> -606309 | R54: ='Cash Flow Statement'!R52 -> 0 | S54: ='Cash Flow Statement'!S52 -> 0 | T54: ='Cash Flow Statement'!T52 -> 0 | U54: ='Cash Flow Statement'!U52 -> 0 | V54: ='Cash Flow Statement'!V52 -> 0 | W54: ='Cash Flow Statement'!W52 -> 0 | X54: ='Cash Flow Statement'!X52 -> 0 | Y54: ='Cash Flow Statement'!Y52 -> -148192 | Z54: ='Cash Flow Statement'!Z52 -> -392447
A55: Capex % of CFO | C55: =-C51/C50 -> 0.048068954 | D55: =-D51/D50 -> 0.085512498 | E55: =-E51/E50 -> 0.42072404 | F55: =-F51/F50 -> 0.22694709 | G55: =-G51/G50 -> 0.25857851 | H55: =-H51/H50 -> -0.57395888 | I55: =-I51/I50 -> 0.45388722 | J55: =-J51/J50 -> 0.094647199 | ... L55: =-L51/L50 -> 0.079696497 | R55: =-R51/R50 -> -0.065063885 | S55: =-S51/S50 -> -3.5480226 | T55: =-T51/T50 -> 7.152207 | U55: =-U51/U50 -> -0.081470187 | V55: =-V51/V50 -> 0.37106308 | W55: =-W51/W50 -> 0.23749018 | X55: =-X51/X50 -> -0.14786789 | Y55: =-Y51/Y50 -> 0.3662874 | Z55: =-Z51/Z50 -> 0.22557876
A56: M&A % of CFO | C56: =-C52/C50 -> 1.3519123 | D56: =-D52/D50 -> 0.92595704 | E56: =-E52/E50 -> 0 | F56: =-F52/F50 -> 0 | G56: =-G52/G50 -> 0 | H56: =-H52/H50 -> -1.1552451 | I56: =-I52/I50 -> 0 | J56: =-J52/J50 -> 0 | ... L56: =-L52/L50 -> 0.097386302 | R56: =-R52/R50 -> 0 | S56: =-S52/S50 -> 0 | T56: =-T52/T50 -> 0 | U56: =-U52/U50 -> 0 | V56: =-V52/V50 -> 0 | W56: =-W52/W50 -> 0.4769077 | X56: =-X52/X50 -> 0 | Y56: =-Y52/Y50 -> 0.744759 | Z56: =-Z52/Z50 -> 0.31610129
A57: Buybacks % of CFO | C57: =-C54/C50 -> 0 | D57: =-D54/D50 -> 0 | E57: =-E54/E50 -> 0 | F57: =-F54/F50 -> 0 | G57: =-G54/G50 -> 1.4456792 | H57: =-H54/H50 -> -0.98711123 | I57: =-I54/I50 -> 6.8187785 | J57: =-J54/J50 -> 0 | ... L57: =-L54/L50 -> 1.5557714 | R57: =-R54/R50 -> 0 | S57: =-S54/S50 -> 0 | T57: =-T54/T50 -> 0 | U57: =-U54/U50 -> 0 | V57: =-V54/V50 -> 0 | W57: =-W54/W50 -> 0 | X57: =-X54/X50 -> 0 | Y57: =-Y54/Y50 -> 3.3191184 | Z57: =-Z54/Z50 -> 3.7082774
A58: Residual Cash After Capex/M&A/Debt/Buybacks ($K) | C58: =C50+C51+C52+C53+C54 -> -55501 | D58: =D50+D51+D52+D53+D54 -> 385628 | E58: =E50+E51+E52+E53+E54 -> 67269 | F58: =F50+F51+F52+F53+F54 -> 87406 | G58: =G50+G51+G52+G53+G54 -> -78586 | H58: =H50+H51+H52+H53+H54 -> -140997 | I58: =I50+I51+I52+I53+I54 -> -240839 | J58: =J50+J51+J52+J53+J54 -> 177221 | ... L58: =L50+L51+L52+L53+L54 -> -285605 | R58: =R50+R51+R52+R53+R54 -> -76773 | S58: =S50+S51+S52+S53+S54 -> -12880 | T58: =T50+T51+T52+T53+T54 -> -12126 | U58: =U50+U51+U52+U53+U54 -> 404975 | V58: =V50+V51+V52+V53+V54 -> 333202 | W58: =W50+W51+W52+W53+W54 -> 155248 | X58: =X50+X51+X52+X53+X54 -> -77364 | Y58: =Y50+Y51+Y52+Y53+Y54 -> -153150 | Z58: =Z50+Z51+Z52+Z53+Z54 -> -343943
A59: SBC (Non-cash Comp) % of CFO | C59: ='Cash Flow Statement'!C12/'Cash Flow Statement'!C33 -> 0.51740067 | D59: ='Cash Flow Statement'!D12/'Cash Flow Statement'!D33 -> 0.63800824 | E59: ='Cash Flow Statement'!E12/'Cash Flow Statement'!E33 -> 0.78807502 | F59: ='Cash Flow Statement'!F12/'Cash Flow Statement'!F33 -> 0.90050944 | G59: ='Cash Flow Statement'!G12/'Cash Flow Statement'!G33 -> 1.0306667 | H59: ='Cash Flow Statement'!H12/'Cash Flow Statement'!H33 -> -3.6112546 | I59: ='Cash Flow Statement'!I12/'Cash Flow Statement'!I33 -> 3.7203282 | J59: ='Cash Flow Statement'!J12/'Cash Flow Statement'!J33 -> 0.74820688 | ... L59: ='Cash Flow Statement'!L12/'Cash Flow Statement'!L33 -> 0.46649098 | R59: ='Cash Flow Statement'!R12/'Cash Flow Statement'!R33 -> -0.50076995 | S59: ='Cash Flow Statement'!S12/'Cash Flow Statement'!S33 -> -25.608757 | T59: ='Cash Flow Statement'!T12/'Cash Flow Statement'!T33 -> 55.390157 | U59: ='Cash Flow Statement'!U12/'Cash Flow Statement'!U33 -> -0.6108659 | V59: ='Cash Flow Statement'!V12/'Cash Flow Statement'!V33 -> 3.3356413 | W59: ='Cash Flow Statement'!W12/'Cash Flow Statement'!W33 -> 2.1301485 | X59: ='Cash Flow Statement'!X12/'Cash Flow Statement'!X33 -> -0.64268969 | Y59: ='Cash Flow Statement'!Y12/'Cash Flow Statement'!Y33 -> 2.0174252 | Z59: ='Cash Flow Statement'!Z12/'Cash Flow Statement'!Z33 -> 1.2757725
A60: Weighted Avg Diluted Shares (thousands) | C60: ='Income Statement'!C54/1000 -> 75328.343 | D60: ='Income Statement'!D54/1000 -> 77709.592 | E60: ='Income Statement'!E54/1000 -> 82681.214 | F60: ='Income Statement'!F54/1000 -> 82855.392 | G60: ='Income Statement'!G54/1000 -> 83577.375 | H60: ='Income Statement'!H54/1000 -> 83569.517 | I60: ='Income Statement'!I54/1000 -> 82176.629 | J60: ='Income Statement'!J54/1000 -> 82291.483 | ... L60: ='Income Statement'!L54/1000 -> 85405.177 | R60: ='Income Statement'!R54/1000 -> 81690.912 | S60: ='Income Statement'!S54/1000 -> 83305.08 | T60: ='Income Statement'!T54/1000 -> 82500.109 | U60: ='Income Statement'!U54/1000 -> 85960.868 | V60: ='Income Statement'!V54/1000 -> 83705.7 | W60: ='Income Statement'!W54/1000 -> 85880.643 | X60: ='Income Statement'!X54/1000 -> 86451.737 | Y60: ='Income Statement'!Y54/1000 -> 86116.567 | Z60: ='Income Statement'!Z54/1000 -> 85065.999
A61: Diluted Shares Change vs. Prior Period (%) | D61: ='Income Statement'!D54/'Income Statement'!C54-1 -> 0.031611594 | E61: ='Income Statement'!E54/'Income Statement'!D54-1 -> 0.063976941 | F61: ='Income Statement'!F54/'Income Statement'!E54-1 -> 0.0021066212 | G61: ='Income Statement'!G54/'Income Statement'!F54-1 -> 0.0087137721 | H61: ='Income Statement'!H54/'Income Statement'!G54-1 -> -9.402066e-05 | I61: ='Income Statement'!I54/'Income Statement'!H54-1 -> -0.016667417 | J61: ='Income Statement'!J54/'Income Statement'!I54-1 -> 0.001397648 | K61: ='Income Statement'!K54/'Income Statement'!J54-1 -> 0.043992037 | L61: ='Income Statement'!L54/'Income Statement'!K54-1 -> -0.005895312 | S61: ='Income Statement'!S54/'Income Statement'!R54-1 -> 0.019759456 | T61: ='Income Statement'!T54/'Income Statement'!S54-1 -> -0.0096629281 | U61: ='Income Statement'!U54/'Income Statement'!T54-1 -> 0.041948539 | V61: ='Income Statement'!V54/'Income Statement'!U54-1 -> -0.026234821 | W61: ='Income Statement'!W54/'Income Statement'!V54-1 -> 0.025983213 | X61: ='Income Statement'!X54/'Income Statement'!W54-1 -> 0.0066498571 | Y61: ='Income Statement'!Y54/'Income Statement'!X54-1 -> -0.0038769609 | Z61: ='Income Statement'!Z54/'Income Statement'!Y54-1 -> -0.012199372
A62: Net Change in Diluted Shares (thousands) -- Buyback vs. SBC Dilution | D62: =('Income Statement'!D54-'Income Statement'!C54)/1000 -> 2381.249 | E62: =('Income Statement'!E54-'Income Statement'!D54)/1000 -> 4971.622 | F62: =('Income Statement'!F54-'Income Statement'!E54)/1000 -> 174.178 | G62: =('Income Statement'!G54-'Income Statement'!F54)/1000 -> 721.983 | H62: =('Income Statement'!H54-'Income Statement'!G54)/1000 -> -7.858 | I62: =('Income Statement'!I54-'Income Statement'!H54)/1000 -> -1392.888 | J62: =('Income Statement'!J54-'Income Statement'!I54)/1000 -> 114.854 | K62: =('Income Statement'!K54-'Income Statement'!J54)/1000 -> 3620.17 | L62: =('Income Statement'!L54-'Income Statement'!K54)/1000 -> -506.476 | S62: =('Income Statement'!S54-'Income Statement'!R54)/1000 -> 1614.168 | T62: =('Income Statement'!T54-'Income Statement'!S54)/1000 -> -804.971 | U62: =('Income Statement'!U54-'Income Statement'!T54)/1000 -> 3460.759 | V62: =('Income Statement'!V54-'Income Statement'!U54)/1000 -> -2255.168 | W62: =('Income Statement'!W54-'Income Statement'!V54)/1000 -> 2174.943 | X62: =('Income Statement'!X54-'Income Statement'!W54)/1000 -> 571.094 | Y62: =('Income Statement'!Y54-'Income Statement'!X54)/1000 -> -335.17 | Z62: =('Income Statement'!Z54-'Income Statement'!Y54)/1000 -> -1050.568

Sheet Operating Metrics
A1: Guidewire Software, Inc. — Operating Metrics
A2: $ in thousands except per-share data | USD | as of 2026-09-17
C3: FY2017 | D3: FY2018 | E3: FY2019 | F3: FY2020 | G3: FY2021 | H3: FY2022 | I3: FY2023 | J3: FY2024 | K3: FY2025 | L3: FY2026 | M3: · | N3: · | O3: · | P3: · | Q3: · | R3: 1Q2024 | S3: 2Q2024 | T3: 3Q2024 | U3: 1Q2025 | V3: 2Q2025 | W3: 3Q2025 | X3: 1Q2026 | Y3: 2Q2026 | Z3: 3Q2026
A6: CONTENTS
A7: =HYPERLINK("#'Operating Metrics'!A13","1. ANNUAL RECURRING REVENUE (ARR)") -> 1. ANNUAL RECURRING REVENUE (ARR)
A8: =HYPERLINK("#'Operating Metrics'!A21","2. CUSTOMERS & EMPLOYEES") -> 2. CUSTOMERS & EMPLOYEES
A9: =HYPERLINK("#'Operating Metrics'!A30","3. BUSINESS MIX & CONCENTRATION") -> 3. BUSINESS MIX & CONCENTRATION
A10: =HYPERLINK("#'Operating Metrics'!A34","4. SBC & EFFICIENCY") -> 4. SBC & EFFICIENCY
A13: 1. ANNUAL RECURRING REVENUE (ARR)
A14: Annual Recurring Revenue (ARR) | B14: Per company disclosure, non-GAAP | D14: 412000 | E14: 460000 | F14: 514000 | G14: 582000 | H14: 664000 | I14: 763000 | J14: 864000 | K14: 1041000 | L14: 1237000 | R14: 770000 | S14: 800000 | T14: 828000 | U14: 874000 | V14: 918000 | W14: 960000 | X14: 1063000 | Y14: 1121000 | Z14: 1147000
A15: ARR YoY Growth | D15: =IF(N(C14)=0,"",D14/C14-1) | E15: =IF(N(D14)=0,"",E14/D14-1) -> 0.11650485 | F15: =IF(N(E14)=0,"",F14/E14-1) -> 0.1173913 | G15: =IF(N(F14)=0,"",G14/F14-1) -> 0.13229572 | H15: =IF(N(G14)=0,"",H14/G14-1) -> 0.14089347 | I15: =IF(N(H14)=0,"",I14/H14-1) -> 0.14909639 | J15: =IF(N(I14)=0,"",J14/I14-1) -> 0.13237221 | K15: =IF(N(J14)=0,"",K14/J14-1) -> 0.20486111 | L15: =IF(N(K14)=0,"",L14/K14-1) -> 0.1882805 | V15: =IF(N(S14)=0,"",V14/S14-1) -> 0.1475 | W15: =IF(N(T14)=0,"",W14/T14-1) -> 0.15942029 | X15: =IF(N(U14)=0,"",X14/U14-1) -> 0.21624714 | Y15: =IF(N(V14)=0,"",Y14/V14-1) -> 0.2211329 | Z15: =IF(N(W14)=0,"",Z14/W14-1) -> 0.19479167
A16: ARR as % of Revenue | D16: =D14/'Income Statement'!D13 -> 0.63108008 | E16: =E14/'Income Statement'!E13 -> 0.63932043 | F16: =F14/'Income Statement'!F13 -> 0.69243588 | G16: =G14/'Income Statement'!G13 -> 0.78302952 | H16: =H14/'Income Statement'!H13 -> 0.81711612 | I16: =I14/'Income Statement'!I13 -> 0.84277637 | J16: =J14/'Income Statement'!J13 -> 0.88118577 | K16: =K14/'Income Statement'!K13 -> 0.86572598 | L16: =L14/'Income Statement'!L13 -> 0.83843773 | R16: =R14/'Income Statement'!R13 -> 3.7125073 | S16: =S14/'Income Statement'!S13 -> 3.3209214 | T16: =T14/'Income Statement'!T13 -> 3.4402812 | U16: =U14/'Income Statement'!U13 -> 3.3244453 | V16: =V14/'Income Statement'!V13 -> 3.1712035 | W16: =W14/'Income Statement'!W13 -> 3.2707797 | X16: =X14/'Income Statement'!X13 -> 3.1956566 | Y16: =Y14/'Income Statement'!Y13 -> 3.1217366 | Z16: =Z14/'Income Statement'!Z13 -> 3.0788558
A18: Implied Net New ARR | F18: =F14-E14 -> 54000 | G18: =G14-F14 -> 68000 | H18: =H14-G14 -> 82000 | I18: =I14-H14 -> 99000 | J18: =J14-I14 -> 101000 | K18: =K14-J14 -> 177000 | L18: =L14-K14 -> 196000 | R18: =R14-Q14 -> 770000 | S18: =S14-R14 -> 30000 | T18: =T14-S14 -> 28000 | U18: =U14-T14 -> 46000 | V18: =V14-U14 -> 44000 | W18: =W14-V14 -> 42000 | X18: =X14-W14 -> 103000 | Y18: =Y14-X14 -> 58000 | Z18: =Z14-Y14 -> 26000
A19: Net New ARR YoY Growth | F19: =IF(N(E18)=0,"",F18/E18-1) | G19: =IF(N(F18)=0,"",G18/F18-1) -> 0.25925926 | H19: =IF(N(G18)=0,"",H18/G18-1) -> 0.20588235 | I19: =IF(N(H18)=0,"",I18/H18-1) -> 0.20731707 | J19: =IF(N(I18)=0,"",J18/I18-1) -> 0.02020202 | K19: =IF(N(J18)=0,"",K18/J18-1) -> 0.75247525 | L19: =IF(N(K18)=0,"",L18/K18-1) -> 0.10734463 | V19: =IF(N(R18)=0,"",V18/R18-1) -> -0.94285714 | W19: =IF(N(S18)=0,"",W18/S18-1) -> 0.4 | X19: =IF(N(T18)=0,"",X18/T18-1) -> 2.6785714 | Y19: =IF(N(U18)=0,"",Y18/U18-1) -> 0.26086957 | Z19: =IF(N(V18)=0,"",Z18/V18-1) -> -0.40909091
A21: 2. CUSTOMERS & EMPLOYEES
A22: Customers | B22: Definition changed: includes HazardHub FY22-23 | D22: 380 | E22: 380 | F22: 340 | G22: 350 | H22: 520 | I22: 580 | J22: 470 | K22: 500 | L22: 550
A23: Customer YoY Growth | D23: =IF(N(C22)=0,"",D22/C22-1) | E23: =IF(N(D22)=0,"",E22/D22-1) -> 0 | F23: =IF(N(E22)=0,"",F22/E22-1) -> -0.10526316 | G23: =IF(N(F22)=0,"",G22/F22-1) -> 0.029411765 | H23: =IF(N(G22)=0,"",H22/G22-1) -> 0.48571429 | I23: =IF(N(H22)=0,"",I22/H22-1) -> 0.11538462 | J23: =IF(N(I22)=0,"",J22/I22-1) -> -0.18965517 | K23: =IF(N(J22)=0,"",K22/J22-1) -> 0.063829787 | L23: =IF(N(K22)=0,"",L22/K22-1) -> 0.1
A24: Total Employees | B24: As of fiscal year end | E24: 2355 | F24: 2690 | G24: 2942 | H24: 3376 | I24: 3415 | J24: 3469 | K24: 3772 | L24: 4174
A25: Employee Growth YoY | E25: =IF(N(D24)=0,"",E24/D24-1) | F25: =IF(N(E24)=0,"",F24/E24-1) -> 0.14225053 | G25: =IF(N(F24)=0,"",G24/F24-1) -> 0.093680297 | H25: =IF(N(G24)=0,"",H24/G24-1) -> 0.14751869 | I25: =IF(N(H24)=0,"",I24/H24-1) -> 0.011552133 | J25: =IF(N(I24)=0,"",J24/I24-1) -> 0.015812592 | K25: =IF(N(J24)=0,"",K24/J24-1) -> 0.087345056 | L25: =IF(N(K24)=0,"",L24/K24-1) -> 0.10657476
A27: ARR per Employee | B27: In $K | E27: =E14/E24 -> 195.32909 | F27: =F14/F24 -> 191.07807 | G27: =G14/G24 -> 197.82461 | H27: =H14/H24 -> 196.68246 | I27: =I14/I24 -> 223.42606 | J27: =J14/J24 -> 249.06313 | K27: =K14/K24 -> 275.98091 | L27: =L14/L24 -> 296.35841
A28: Revenue per Employee | B28: In $K | E28: ='Income Statement'!E13/E24 -> 305.52611 | F28: ='Income Statement'!F13/F24 -> 275.95056 | G28: ='Income Statement'!G13/G24 -> 252.64004 | H28: ='Income Statement'!H13/H24 -> 240.7032 | I28: ='Income Statement'!I13/I24 -> 265.10717 | J28: ='Income Statement'!J13/J24 -> 282.64543 | K28: ='Income Statement'!K13/K24 -> 318.78552 | L28: ='Income Statement'!L13/L24 -> 353.46502
A30: 3. BUSINESS MIX & CONCENTRATION
A31: Subscription & Support % of Revenue | C31: ='Income Statement'!C57 -> 0.13471748 | D31: ='Income Statement'!D57 -> 0.16962268 | E31: ='Income Statement'!E57 -> 0.20913283 | F31: ='Income Statement'!F57 -> 0.27410896 | G31: ='Income Statement'!G57 -> 0.33952537 | H31: ='Income Statement'!H57 -> 0.42296589 | I31: ='Income Statement'!I57 -> 0.47459134 | J31: ='Income Statement'!J57 -> 0.56000885 | ... L31: ='Income Statement'!L57 -> 0.65806517 | R31: ='Income Statement'!R57 -> 0.61534567 | S31: ='Income Statement'!S57 -> 0.54646592 | T31: ='Income Statement'!T57 -> 0.57325555 | U31: ='Income Statement'!U57 -> 0.64564988 | V31: ='Income Statement'!V57 -> 0.61433605 | W31: ='Income Statement'!W57 -> 0.61948226 | X31: ='Income Statement'!X57 -> 0.66800044 | Y31: ='Income Statement'!Y57 -> 0.6605745 | Z31: ='Income Statement'!Z57 -> 0.65694246
A32: Top 10 Customer Concentration | B32: Per 10-K risk factor disclosure | C32: 0.27 | D32: 0.31 | E32: 0.31 | F32: 0.31 | G32: 0.31 | H32: 0.27 | I32: 0.23 | J32: 0.23 | K32: 0.2 | L32: 0.21
A34: 4. SBC & EFFICIENCY
A35: Stock-Based Compensation | C35: ='Cash Flow Statement'!C12 -> 71794 | D35: ='Cash Flow Statement'!D12 -> 89614 | E35: ='Cash Flow Statement'!E12 -> 91516 | F35: ='Cash Flow Statement'!F12 -> 101817 | G35: ='Cash Flow Statement'!G12 -> 115009 | H35: ='Cash Flow Statement'!H12 -> 137011 | I35: ='Cash Flow Statement'!I12 -> 142842 | J35: ='Cash Flow Statement'!J12 -> 146460 | ... L35: ='Cash Flow Statement'!L12 -> 181799 | R35: ='Cash Flow Statement'!R12 -> 36097 | S35: ='Cash Flow Statement'!S12 -> 72524 | T35: ='Cash Flow Statement'!T12 -> 109174 | U35: ='Cash Flow Statement'!U12 -> 38060 | V35: ='Cash Flow Statement'!V12 -> 79008 | W35: ='Cash Flow Statement'!W12 -> 119365 | X35: ='Cash Flow Statement'!X12 -> 43316 | Y35: ='Cash Flow Statement'!Y12 -> 90074 | Z35: ='Cash Flow Statement'!Z12 -> 135015
A36: SBC % of Revenue | C36: ='Cash Flow Statement'!C12/'Income Statement'!C13 -> 0.14090157 | D36: ='Cash Flow Statement'!D12/'Income Statement'!D13 -> 0.13726604 | E36: ='Cash Flow Statement'!E12/'Income Statement'!E13 -> 0.12719141 | F36: ='Cash Flow Statement'!F12/'Income Statement'!F13 -> 0.13716293 | G36: ='Cash Flow Statement'!G12/'Income Statement'!G13 -> 0.15473444 | H36: ='Cash Flow Statement'!H12/'Income Statement'!H13 -> 0.16860527 | I36: ='Cash Flow Statement'!I12/'Income Statement'!I13 -> 0.15777701 | J36: ='Cash Flow Statement'!J12/'Income Statement'!J13 -> 0.14937323 | ... L36: ='Cash Flow Statement'!L12/'Income Statement'!L13 -> 0.12322323 | R36: ='Cash Flow Statement'!R12/'Income Statement'!R13 -> 0.17403945 | S36: ='Cash Flow Statement'!S12/'Income Statement'!S13 -> 0.30105813 | T36: ='Cash Flow Statement'!T12/'Income Statement'!T13 -> 0.45361022 | U36: ='Cash Flow Statement'!U12/'Income Statement'!U13 -> 0.14476932 | V36: ='Cash Flow Statement'!V12/'Income Statement'!V13 -> 0.27293077 | W36: ='Cash Flow Statement'!W12/'Income Statement'!W13 -> 0.40668397 | X36: ='Cash Flow Statement'!X12/'Income Statement'!X13 -> 0.13021925 | Y36: ='Cash Flow Statement'!Y12/'Income Statement'!Y13 -> 0.25083613 | Z36: ='Cash Flow Statement'!Z12/'Income Statement'!Z13 -> 0.36241649
A37: SBC per Employee | B37: In $K | E37: ='Cash Flow Statement'!E12/E24 -> 38.860297 | F37: ='Cash Flow Statement'!F12/F24 -> 37.850186 | G37: ='Cash Flow Statement'!G12/G24 -> 39.092114 | H37: ='Cash Flow Statement'!H12/H24 -> 40.583827 | I37: ='Cash Flow Statement'!I12/I24 -> 41.827818 | J37: ='Cash Flow Statement'!J12/J24 -> 42.21966 | K37: ='Cash Flow Statement'!K12/K24 -> 42.830329 | L37: ='Cash Flow Statement'!L12/L24 -> 43.555103

Sheet Segments
A1: Guidewire Software, Inc. — Segments
A2: $ in thousands except per-share data | USD | as of 2026-09-17
C3: FY2017 | D3: FY2018 | E3: FY2019 | F3: FY2020 | G3: FY2021 | H3: FY2022 | I3: FY2023 | J3: FY2024 | K3: FY2025 | L3: FY2026 | M3: · | N3: · | O3: · | P3: · | Q3: · | R3: 1Q2024 | S3: 2Q2024 | T3: 3Q2024 | U3: 1Q2025 | V3: 2Q2025 | W3: 3Q2025 | X3: 1Q2026 | Y3: 2Q2026 | Z3: 3Q2026
A6: 1. GEOGRAPHIC REVENUE
A7: U.S. Revenue | J7: 632568 | K7: 770859 | L7: 937854
A8: Canada Revenue | J8: 105761 | K8: 141381 | L8: 175040
A9: Other Americas Revenue | J9: 11493 | K9: 11660 | L9: 20874
A10: Total Americas Revenue | J10: 749822 | K10: 923900 | L10: 1133768
A11: Total EMEA Revenue | J11: 154434 | K11: 183584 | L11: 226885
A12: Total APAC Revenue | J12: 76241 | K12: 94975 | L12: 114710
A13: Total Revenue (Geographic) | J13: 980497 | K13: 1202459 | L13: 1475363
A15: 2. GEOGRAPHIC MIX
A16: Americas % of Revenue | C16: =C10/C13 -> #DIV/0! | D16: =D10/D13 -> #DIV/0! | E16: =E10/E13 -> #DIV/0! | F16: =F10/F13 -> #DIV/0! | G16: =G10/G13 -> #DIV/0! | H16: =H10/H13 -> #DIV/0! | I16: =I10/I13 -> #DIV/0! | J16: =J10/J13 -> 0.76473666 | ... L16: =L10/L13 -> 0.76846715 | R16: =R10/R13 -> #DIV/0! | S16: =S10/S13 -> #DIV/0! | T16: =T10/T13 -> #DIV/0! | U16: =U10/U13 -> #DIV/0! | V16: =V10/V13 -> #DIV/0! | W16: =W10/W13 -> #DIV/0! | X16: =X10/X13 -> #DIV/0! | Y16: =Y10/Y13 -> #DIV/0! | Z16: =Z10/Z13 -> #DIV/0!
A17: EMEA % of Revenue | C17: =C11/C13 -> #DIV/0! | D17: =D11/D13 -> #DIV/0! | E17: =E11/E13 -> #DIV/0! | F17: =F11/F13 -> #DIV/0! | G17: =G11/G13 -> #DIV/0! | H17: =H11/H13 -> #DIV/0! | I17: =I11/I13 -> #DIV/0! | J17: =J11/J13 -> 0.15750584 | ... L17: =L11/L13 -> 0.15378249 | R17: =R11/R13 -> #DIV/0! | S17: =S11/S13 -> #DIV/0! | T17: =T11/T13 -> #DIV/0! | U17: =U11/U13 -> #DIV/0! | V17: =V11/V13 -> #DIV/0! | W17: =W11/W13 -> #DIV/0! | X17: =X11/X13 -> #DIV/0! | Y17: =Y11/Y13 -> #DIV/0! | Z17: =Z11/Z13 -> #DIV/0!
A18: APAC % of Revenue | C18: =C12/C13 -> #DIV/0! | D18: =D12/D13 -> #DIV/0! | E18: =E12/E13 -> #DIV/0! | F18: =F12/F13 -> #DIV/0! | G18: =G12/G13 -> #DIV/0! | H18: =H12/H13 -> #DIV/0! | I18: =I12/I13 -> #DIV/0! | J18: =J12/J13 -> 0.077757505 | ... L18: =L12/L13 -> 0.077750357 | R18: =R12/R13 -> #DIV/0! | S18: =S12/S13 -> #DIV/0! | T18: =T12/T13 -> #DIV/0! | U18: =U12/U13 -> #DIV/0! | V18: =V12/V13 -> #DIV/0! | W18: =W12/W13 -> #DIV/0! | X18: =X12/X13 -> #DIV/0! | Y18: =Y12/Y13 -> #DIV/0! | Z18: =Z12/Z13 -> #DIV/0!

Sheet Note Schedules
A1: Guidewire Software, Inc. — Note Schedules
A2: $ in thousands except per-share data | USD | as of 2026-09-17
C3: FY2017 | D3: FY2018 | E3: FY2019 | F3: FY2020 | G3: FY2021 | H3: FY2022 | I3: FY2023 | J3: FY2024 | K3: FY2025 | L3: FY2026 | M3: · | N3: · | O3: · | P3: · | Q3: · | R3: 1Q2024 | S3: 2Q2024 | T3: 3Q2024 | U3: 1Q2025 | V3: 2Q2025 | W3: 3Q2025 | X3: 1Q2026 | Y3: 2Q2026 | Z3: 3Q2026
A6: 1. CONVERTIBLE SENIOR NOTES
A7: 2029 Convertible Senior Notes - Principal | K7: 690000 | L7: 690000
A8: Less: Unamortized Debt Issuance Costs | K8: -15432 | L8: -11906
A9: Net Carrying Amount | K9: 674568 | L9: 678094
A11: 2. INTANGIBLE ASSETS
A12: Acquired Technology, Net | K12: 8117 | L12: 11942
A13: Customer Contracts & Relationships, Net | K13: 3533 | L13: 4201
A14: Trademarks, Net | K14: 392 | L14: 263
A15: Total Intangible Assets, Net | K15: 12042 | L15: 16406
A17: 3. OPERATING LEASES
A18: Operating Lease Costs | J18: 12537 | K18: 13167 | L18: 14042
A19: Variable Lease Costs | J19: 2344 | K19: 2428 | L19: 3777
A20: Net Operating Lease Costs | J20: 14881 | K20: 15595 | L20: 17819
A21: Operating Lease Assets | K21: 39309 | L21: 34404
A22: Current Lease Liabilities | K22: 10438 | L22: 11687
A23: Non-current Lease Liabilities | K23: 30687 | L23: 25206
A24: Total Lease Liabilities | K24: 41125 | L24: 36893
A26: 4. REVENUE CONTRACT BALANCES
A27: Unbilled Accounts Receivable, Net | K27: 131629 | L27: 140832
A28: Contract Acquisition Costs, Net | K28: 67922 | L28: 79376
A29: Costs to Fulfill a Contract, Net | K29: 9415 | L29: 12318
A30: Deferred Revenue, Net (Total) | K30: 344786 | L30: 438814

Sheet Sources
A1: Guidewire Software, Inc. — Sources
A2: $ in thousands except per-share data | USD | as of 2026-09-17
A4: Data Sources
A6: Source Type | B6: Details
A7: Annual 10-K | B7: FY2017–FY2026 (10 filings) from SEC EDGAR
A8: Quarterly 10-Q | B8: 1Q2024–3Q2026 (9 filings) from SEC EDGAR
A9: CIK | B9: 0001528396
A11: Filing Coverage
A12: FY2017 | B12: 10-K filed September 2017 (ended Jul 31, 2017)
A13: FY2018 | B13: 10-K filed September 2018 (ended Jul 31, 2018)
A14: FY2019 | B14: 10-K filed September 2019 (ended Jul 31, 2019)
A15: FY2020 | B15: 10-K filed September 2020 (ended Jul 31, 2020)
A16: FY2021 | B16: 10-K filed September 2021 (ended Jul 31, 2021)
A17: FY2022 | B17: 10-K filed September 2022 (ended Jul 31, 2022)
A18: FY2023 | B18: 10-K filed September 2023 (ended Jul 31, 2023)
A19: FY2024 | B19: 10-K filed September 2024 (ended Jul 31, 2024)
A20: FY2025 | B20: 10-K filed September 2025 (ended Jul 31, 2025)
A21: FY2026 | B21: 10-K filed September 2026 (ended Jul 31, 2026)
A23: Notes
A24: Override policy | B24: Later filings override earlier filings for the same period
A25: Revenue labels | B25: FY2017-2018: "License and other" + "Maintenance"; FY2019+: "Subscription and support" + "License"
A26: Units | B26: All financial data in thousands USD unless noted
A27: EPS | B27: Per-share amounts in dollars
A28: Quarterly CF | B28: Cumulative YTD figures as reported in 10-Q filings
