Workbook

Sheet Cover
A1: McDonald's Corporation — Cover
A2: $ in millions except per-share data | USD | as of 2026-10-08
A4: McDonald's Corporation - Financial Model Workbook
A6: Ticker / exchange | B6: MCD / NYSE
A7: SEC registrant / CIK | B7: MCDONALDS CORP / 0000063908
A8: Reporting framework | B8: US GAAP (per SEC Form 10-K / 10-Q); consolidated
A9: Fiscal year end | B9: December 31
A10: Currency and units | B10: USD millions except per-share data and restaurant counts
A11: Annual window | B11: FY2016-FY2025 (10 Form 10-K filings; latest-filing-wins precedence for restated periods)
A12: Quarterly window | B12: 3Q2024-2Q2026 (6 Form 10-Q filings: 3Q24, 1Q25, 2Q25, 3Q25, 1Q26, 2Q26)
A13: Latest filing covered | B13: Form 10-Q for the quarter ended 2026-06-30 (filed 2026-08-07); 3Q2026 10-Q not yet filed at 2026-10-08
A14: Research as-of date | B14: 2026-10-08
A16: Colour legend
A17: Blue | B17: Hard-coded value copied from a filed statement table
A18: Black | B18: Formula / analyst calculation
A19: Green | B19: Cross-sheet link
A20: Grey italic | B20: Memo / ratio rows
A21: Amber check rows | B21: Rounding tie-outs of as-filed integers (+/-2 expected); red = strict tie-out failure
A23: Sheet directory
A24: Income Statement (IS) | B24: As-reported income statement, per-share data, tie-outs
A25: Balance Sheet (BS) | B25: As-reported balance sheet, tie-outs, debt and lease summary
A26: Cash Flow (CF) | B26: As-reported cash flow, cash walk, free cash flow analytics
A27: Segments (SEG) | B27: Reportable-segment revenue, operating income, assets, capex, D&A; revenue by type; restaurant margins by segment; SG&A by segment and incentive compensation; superseded FY2016-FY2018 structure
A28: Operating Metrics (OM) | B28: Restaurant counts (type and segment), net additions, comparable sales and guest counts, systemwide sales growth, franchised sales, franchised revenue mix, currency translation impact, non-GAAP reconciliations, capex by purpose, shareholder returns, debt statistics
A29: Note Schedules (NS) | B29: Property and equipment, income taxes, other operating and nonoperating components, goodwill by segment, debt by currency and maturity, rent and lease commitments, franchise-arrangement assets, advertising, share-based compensation, text-only operating facts
A30: Year-End Schedules | B30: Debt, lease and minimum-rent maturity ladders (Dec 2025 and Dec 2024), restructuring reserve roll-forward, equity-method investees
A31: Outlook & Text KPIs | B31: Verbatim management outlook statements FY2016-FY2025 10-Ks (FORWARD-LOOKING, not realised) and operating-KPI sentences FY2021-FY2025 with line locators
A32: Derived Metrics (DM) | B32: Margins, returns, leverage, liquidity, cash conversion, growth (formulas on the statements)
A33: Sources | B33: Filing register, extraction method, comparability and restatement notes
A35: Comparability and method notes
A36: 4Q columns marked * | B36: Income statement and cash flow 4Q = FY (10-K) less nine-month YTD (10-Q): analyst derivation, not a filed quarterly statement. Balance-sheet 4Q columns are the filed 10-K year-end balances. EPS / share counts are not derived.
A37: Revenue recast | B37: FY2018-FY2019 were recast in the FY2020 10-K (new 'Other revenues' and 'Other restaurant expenses' lines; revenue and cost both higher, operating income unchanged). FY2016-FY2017 are as originally reported and are not comparable at line level.
A38: Segment structure | B38: Current segments (U.S. / International Operated Markets / International Developmental Licensed Markets & Corporate) available from FY2017 (FY2019 10-K recast). FY2016 exists only under the superseded structure.
A39: Negative equity | B39: Shareholders' equity is a deficit in every period; ROE and debt/equity are not meaningful and are omitted.
A40: Precision | B40: FY2016-FY2019 10-K tables show one decimal; FY2018 onward as later recast are whole millions. Tie-outs therefore show +/-1-2 rounding in recent years.
A41: Systemwide sales | B41: The company does not tabulate Systemwide sales in dollars; the OM row reconstructs it as franchised sales + Company-owned and operated sales (analyst calculation). Cross-check: 2025 SG&A / reconstructed Systemwide sales = 2.2%, equal to the company's own 'about 2.2% of Systemwide sales' statement.
A42: Text-only facts | B42: Rows built from MD&A / note prose (advertising, variable rent, franchise-arrangement property, debt fair value, segment franchised %, employees, delivery / drive thru) are company statements rounded as printed; they are not audited tables.
A43: Guidance | B43: The Outlook & Text KPIs sheet quotes management guidance and targets verbatim. They are forward-looking company statements (SEC filing text), not realised data.
A44: Not loaded | B44: Official-site material and earnings-call transcripts (out of scope); 1Q/2Q 2024 quarterly flows (prior-year comparatives in the 2025 10-Qs); deferred-tax components, effective-tax-rate reconciliation, unrecognised tax benefits, derivative / fair-value tables, option and RSU activity, monthly repurchase table and the 5-year shareholder-return index (financial-reporting detail outside the operating scope of this pass); FY2016-FY2018 old-structure MD&A tables other than those shown in the superseded-structure block; 10-Q MD&A KPI tables.

Sheet Income Statement
A1: McDonald's Corporation — Income Statement
A2: $ in millions except per-share data | USD | as of 2026-10-08
C3: FY2016 | D3: FY2017 | E3: FY2018 | F3: FY2019 | G3: FY2020 | H3: FY2021 | I3: FY2022 | J3: FY2023 | K3: FY2024 | L3: FY2025 | M3: · | N3: 3Q2024 | O3: 4Q2024* | P3: 1Q2025 | Q3: 2Q2025 | R3: 3Q2025 | S3: 4Q2025* | T3: 1Q2026 | U3: 2Q2026
C4: 2016-12-31 | D4: 2017-12-31 | E4: 2018-12-31 | F4: 2019-12-31 | G4: 2020-12-31 | H4: 2021-12-31 | I4: 2022-12-31 | J4: 2023-12-31 | K4: 2024-12-31 | L4: 2025-12-31 | N4: 2024-09-30 | O4: 2024-12-31 | P4: 2025-03-31 | Q4: 2025-06-30 | R4: 2025-09-30 | S4: 2025-12-31 | T4: 2026-03-31 | U4: 2026-06-30
A6: CONTENTS
A7: =HYPERLINK("#'Income Statement'!A11","1. INCOME STATEMENT - AS REPORTED") -> 1. INCOME STATEMENT - AS REPORTED
A8: =HYPERLINK("#'Income Statement'!A43","2. PER-SHARE DATA AND SHARE COUNT") -> 2. PER-SHARE DATA AND SHARE COUNT
A9: =HYPERLINK("#'Income Statement'!A51","3. TIE-OUT CHECKS") -> 3. TIE-OUT CHECKS
A11: 1. INCOME STATEMENT - AS REPORTED
A12: Revenues from franchised restaurants | C12: 9326.9 | D12: 10101.5 | E12: 11012.5 | F12: 11655.7 | G12: 10726.1 | H12: 13085.4 | I12: 14106 | J12: 15437 | K12: 15715 | L12: 16548 | N12: 4094 | O12: 3959 | P12: 3661 | Q12: 4213 | R12: 4363 | S12: 4310 | T12: 4007 | U12: 4393
A13: YoY Growth | D13: =IF(N(C12)=0,"",D12/C12-1) -> 0.083050102 | E13: =IF(N(D12)=0,"",E12/D12-1) -> 0.090184626 | F13: =IF(N(E12)=0,"",F12/E12-1) -> 0.058406356 | G13: =IF(N(F12)=0,"",G12/F12-1) -> -0.07975497 | H13: =IF(N(G12)=0,"",H12/G12-1) -> 0.21995879 | I13: =IF(N(H12)=0,"",I12/H12-1) -> 0.077995323 | J13: =IF(N(I12)=0,"",J12/I12-1) -> 0.094357011 | K13: =IF(N(J12)=0,"",K12/J12-1) -> 0.01800868 | L13: =IF(N(K12)=0,"",L12/K12-1) -> 0.053006682 | R13: =R12/N12-1 -> 0.065705911 | S13: =S12/O12-1 -> 0.088658752 | T13: =T12/P12-1 -> 0.094509697 | U13: =U12/Q12-1 -> 0.042724899
A14: Sales by Company-owned and operated restaurants | B14: Captioned 'Sales by Company-operated restaurants' in 10-Ks through FY2023 | C14: 15295 | D14: 12718.9 | E14: 10012.7 | F14: 9420.8 | G14: 8139.2 | H14: 9787.4 | I14: 8748 | J14: 9742 | K14: 9782 | L14: 9690 | N14: 2656 | O14: 2310 | P14: 2132 | Q14: 2458 | R14: 2563 | S14: 2536 | T14: 2317 | U14: 2525
A15: YoY Growth | D15: =IF(N(C14)=0,"",D14/C14-1) -> -0.16842759 | E15: =IF(N(D14)=0,"",E14/D14-1) -> -0.21276997 | F15: =IF(N(E14)=0,"",F14/E14-1) -> -0.059114924 | G15: =IF(N(F14)=0,"",G14/F14-1) -> -0.1360394 | H15: =IF(N(G14)=0,"",H14/G14-1) -> 0.20250147 | I15: =IF(N(H14)=0,"",I14/H14-1) -> -0.10619776 | J15: =IF(N(I14)=0,"",J14/I14-1) -> 0.11362597 | K15: =IF(N(J14)=0,"",K14/J14-1) -> 0.0041059331 | L15: =IF(N(K14)=0,"",L14/K14-1) -> -0.0094050296
A16: Other revenues | B16: Line first presented in FY2020 10-K with FY2018-FY2019 recast; FY2016-FY2017 pre-date the recast (no separate line) | E16: 232.7 | F16: 287.9 | G16: 342.5 | H16: 350.1 | I16: 328 | J16: 316 | K16: 423 | L16: 647 | N16: 124 | O16: 119 | P16: 162 | Q16: 172 | R16: 151 | S16: 162 | T16: 193 | U16: 182
A17: Total revenues | C17: 24621.9 | D17: 22820.4 | E17: 21257.9 | F17: 21364.4 | G17: 19207.8 | H17: 23222.9 | I17: 23183 | J17: 25494 | K17: 25920 | L17: 26885 | N17: 6873 | O17: 6388 | P17: 5956 | Q17: 6843 | R17: 7078 | S17: 7009 | T17: 6517 | U17: 7099
A18: YoY Growth | D18: =IF(N(C17)=0,"",D17/C17-1) -> -0.073166571 | E18: =IF(N(D17)=0,"",E17/D17-1) -> -0.06846944 | F18: =IF(N(E17)=0,"",F17/E17-1) -> 0.0050099022 | G18: =IF(N(F17)=0,"",G17/F17-1) -> -0.10094363 | H18: =IF(N(G17)=0,"",H17/G17-1) -> 0.20903487 | I18: =IF(N(H17)=0,"",I17/H17-1) -> -0.0017181317 | J18: =IF(N(I17)=0,"",J17/I17-1) -> 0.099685114 | K18: =IF(N(J17)=0,"",K17/J17-1) -> 0.016709814 | L18: =IF(N(K17)=0,"",L17/K17-1) -> 0.037229938 | R18: =IF(N(N17)=0,"",R17/N17-1) -> 0.029826859 | S18: =IF(N(O17)=0,"",S17/O17-1) -> 0.097213525 | T18: =IF(N(P17)=0,"",T17/P17-1) -> 0.094190732 | U18: =IF(N(Q17)=0,"",U17/Q17-1) -> 0.037410492
A20: Franchised restaurants-occupancy expenses | C20: 1718.4 | D20: 1790 | E20: 1973.3 | F20: 2200.6 | G20: 2207.5 | H20: 2335 | I20: 2350 | J20: 2475 | K20: 2536 | L20: 2618 | N20: 646 | O20: 634 | P20: 620 | Q20: 654 | R20: 666 | S20: 678 | T20: 676 | U20: 680
A21: Company-owned and operated: Food & paper | C21: 4896.9 | D21: 4033.5 | E21: 3153.8 | F21: 2980.3 | G21: 2564.2 | H21: 3096.8 | I21: 2737 | J21: 3039 | K21: 2995 | L21: 3006
A22: Company-owned and operated: Payroll & employee benefits | C22: 4134.2 | D22: 3528.5 | E22: 2937.9 | F22: 2704.4 | G22: 2416.4 | H22: 2677.2 | I22: 2617 | J22: 2886 | K22: 2959 | L22: 2905
A23: Company-owned and operated: Occupancy & other operating expenses | C23: 3667.7 | D23: 2847.6 | E23: 2174.2 | F23: 2075.9 | G23: 2000.6 | H23: 2273.3 | I23: 2026 | J23: 2299 | K23: 2381 | L23: 2358
A24: Company-owned and operated restaurant expenses (10-Q single-line) | B24: 10-Q presents one line; 10-K presents the three components above. 4Q* = FY components less 9M YTD | N24: 2248 | O24: 1977 | P24: 1859 | Q24: 2078 | R24: 2172 | S24: 2160 | T24: 2032 | U24: 2138
A25: Company-owned and operated restaurant expenses | C25: =C21+C22+C23 -> 12698.8 | D25: =D21+D22+D23 -> 10409.6 | E25: =E21+E22+E23 -> 8265.9 | F25: =F21+F22+F23 -> 7760.6 | G25: =G21+G22+G23 -> 6981.2 | H25: =H21+H22+H23 -> 8047.3 | I25: =I21+I22+I23 -> 7380 | J25: =J21+J22+J23 -> 8224 | ... L25: =L21+L22+L23 -> 8269 | N25: =N24 -> 2248 | O25: =O24 -> 1977 | P25: =P24 -> 1859 | Q25: =Q24 -> 2078 | R25: =R24 -> 2172 | S25: =S24 -> 2160 | T25: =T24 -> 2032 | U25: =U24 -> 2138
A26: Other restaurant expenses | B26: Line first presented in FY2020 10-K with FY2018-FY2019 recast | E26: 186.1 | F26: 223.8 | G26: 267 | H26: 260.4 | I26: 245 | J26: 232 | K26: 339 | L26: 564 | N26: 104 | O26: 98 | P26: 140 | Q26: 149 | R26: 135 | S26: 140 | T26: 166 | U26: 163
A27: SG&A (single-line presentation, FY2016-FY2017) | C27: 2384.5 | D27: 2231.3
A28: SG&A: Depreciation and amortization | E28: 214.8 | F28: 262.5 | G28: 300.6 | H28: 329.7 | I28: 370 | J28: 382 | K28: 447 | L28: 457 | N28: 111 | O28: 136 | P28: 107 | Q28: 106 | R28: 121 | S28: 124 | T28: 111 | U28: 111
A29: SG&A: Other | E29: 1985.4 | F29: 1966.9 | G29: 2245 | H29: 2377.8 | I29: 2492 | J29: 2435 | K29: 2412 | L29: 2583 | N29: 536 | O29: 664 | P29: 575 | Q29: 595 | R29: 664 | S29: 749 | T29: 648 | U29: 706
A30: Selling, general & administrative expenses | B30: Analyst sum of as-filed components; filed as one line FY2016-FY2017 | C30: =C27+C28+C29 -> 2384.5 | D30: =D27+D28+D29 -> 2231.3 | E30: =E27+E28+E29 -> 2200.2 | F30: =F27+F28+F29 -> 2229.4 | G30: =G27+G28+G29 -> 2545.6 | H30: =H27+H28+H29 -> 2707.5 | I30: =I27+I28+I29 -> 2862 | J30: =J27+J28+J29 -> 2817 | ... L30: =L27+L28+L29 -> 3040 | N30: =N27+N28+N29 -> 647 | O30: =O27+O28+O29 -> 800 | P30: =P27+P28+P29 -> 682 | Q30: =Q27+Q28+Q29 -> 701 | R30: =R27+R28+R29 -> 785 | S30: =S27+S28+S29 -> 873 | T30: =T27+T28+T29 -> 759 | U30: =U27+U28+U29 -> 817
A31: Other operating (income) expense, net | C31: 75.7 | D31: -1163.2 | E31: -190.2 | F31: -119.8 | G31: -117.5 | H31: -483.3 | I31: 974 | J31: 99 | K31: 139 | L31: 2 | N31: 39 | O31: 10 | P31: 7 | Q31: 29 | R31: -37 | S31: 3 | T31: -69 | U31: -37
A32: Total operating costs and expenses | C32: 16877.4 | D32: 13267.7 | E32: 12435.3 | F32: 12294.6 | G32: 11883.8 | H32: 12866.9 | I32: 13812 | J32: 13847 | K32: 14208 | L32: 14492 | N32: 3685 | O32: 3520 | P32: 3308 | Q32: 3611 | R32: 3721 | S32: 3853 | T32: 3564 | U32: 3760
A33: Operating income | C33: 7744.5 | D33: 9552.7 | E33: 8822.6 | F33: 9069.8 | G33: 7324 | H33: 10356 | I33: 9371 | J33: 11647 | K33: 11712 | L33: 12393 | N33: 3188 | O33: 2868 | P33: 2648 | Q33: 3232 | R33: 3357 | S33: 3156 | T33: 2953 | U33: 3338
A34: Operating Margin | C34: =C33/C17 -> 0.31453706 | D34: =D33/D17 -> 0.41860353 | E34: =E33/E17 -> 0.41502688 | F34: =F33/F17 -> 0.42452866 | G34: =G33/G17 -> 0.38130343 | H34: =H33/H17 -> 0.44593914 | I34: =I33/I17 -> 0.40421861 | J34: =J33/J17 -> 0.45685259 | ... L34: =L33/L17 -> 0.46096336 | N34: =N33/N17 -> 0.46384403 | O34: =O33/O17 -> 0.44896681 | P34: =P33/P17 -> 0.44459369 | Q34: =Q33/Q17 -> 0.47230747 | R34: =R33/R17 -> 0.47428652 | S34: =S33/S17 -> 0.45027821 | T34: =T33/T17 -> 0.4531226 | U34: =U33/U17 -> 0.47020707
A35: YoY Growth | D35: =IF(N(C33)=0,"",D33/C33-1) -> 0.23348183 | E35: =IF(N(D33)=0,"",E33/D33-1) -> -0.076428654 | F35: =IF(N(E33)=0,"",F33/E33-1) -> 0.028018951 | G35: =IF(N(F33)=0,"",G33/F33-1) -> -0.19248495 | H35: =IF(N(G33)=0,"",H33/G33-1) -> 0.41398143 | I35: =IF(N(H33)=0,"",I33/H33-1) -> -0.095113944 | J35: =IF(N(I33)=0,"",J33/I33-1) -> 0.24287696 | K35: =IF(N(J33)=0,"",K33/J33-1) -> 0.0055808363 | L35: =IF(N(K33)=0,"",L33/K33-1) -> 0.058145492 | R35: =IF(N(N33)=0,"",R33/N33-1) -> 0.053011292 | S35: =IF(N(O33)=0,"",S33/O33-1) -> 0.10041841 | T35: =IF(N(P33)=0,"",T33/P33-1) -> 0.11518127 | U35: =IF(N(Q33)=0,"",U33/Q33-1) -> 0.03279703
A37: Interest expense, net of capitalized interest | C37: 884.8 | D37: 921.3 | E37: 981.2 | F37: 1121.9 | G37: 1218.1 | H37: 1185.8 | I37: 1207 | J37: 1361 | K37: 1506 | L37: 1582 | N37: 381 | O37: 380 | P37: 376 | Q37: 390 | R37: 406 | S37: 410 | T37: 400 | U37: 409
A38: Nonoperating (income) expense, net | C38: -6.3 | D38: 57.9 | E38: 25.3 | F38: -70.2 | G38: -34.8 | H38: 42.3 | I38: 339 | J38: -236 | K38: -139 | L38: -87 | N38: -36 | O38: -49 | P38: -57 | Q38: -18 | R38: 1 | S38: -12 | T38: 11 | U38: -6
A39: Income before provision for income taxes | C39: 6866 | D39: 8573.5 | E39: 7816.1 | F39: 8018.1 | G39: 6140.7 | H39: 9127.9 | I39: 7825 | J39: 10522 | K39: 10345 | L39: 10897 | N39: 2843 | O39: 2538 | P39: 2330 | Q39: 2861 | R39: 2949 | S39: 2757 | T39: 2542 | U39: 2936
A40: Provision for income taxes | C40: 2179.5 | D40: 3381.2 | E40: 1891.8 | F40: 1992.7 | G40: 1410.2 | H40: 1582.7 | I40: 1648 | J40: 2053 | K40: 2121 | L40: 2334 | N40: 588 | O40: 521 | P40: 461 | Q40: 608 | R40: 671 | S40: 594 | T40: 559 | U40: 574
A41: Net income | C41: 4686.5 | D41: 5192.3 | E41: 5924.3 | F41: 6025.4 | G41: 4730.5 | H41: 7545.2 | I41: 6177 | J41: 8469 | K41: 8223 | L41: 8563 | N41: 2255 | O41: 2016 | P41: 1868 | Q41: 2253 | R41: 2278 | S41: 2164 | T41: 1983 | U41: 2362
A42: Net Margin | C42: =C41/C17 -> 0.19033868 | D42: =D41/D17 -> 0.22752888 | E42: =E41/E17 -> 0.27868698 | F42: =F41/F17 -> 0.28202992 | G42: =G41/G17 -> 0.24628016 | H42: =H41/H17 -> 0.32490344 | I42: =I41/I17 -> 0.26644524 | J42: =J41/J17 -> 0.33219581 | ... L42: =L41/L17 -> 0.31850474 | N42: =N41/N17 -> 0.32809545 | O42: =O41/O17 -> 0.31559173 | P42: =P41/P17 -> 0.31363331 | Q42: =Q41/Q17 -> 0.32924156 | R42: =R41/R17 -> 0.32184233 | S42: =S41/S17 -> 0.3087459 | T42: =T41/T17 -> 0.30428111 | U42: =U41/U17 -> 0.33272292
A43: YoY Growth | D43: =IF(N(C41)=0,"",D41/C41-1) -> 0.10792702 | E43: =IF(N(D41)=0,"",E41/D41-1) -> 0.14097799 | F43: =IF(N(E41)=0,"",F41/E41-1) -> 0.017065307 | G43: =IF(N(F41)=0,"",G41/F41-1) -> -0.21490689 | H43: =IF(N(G41)=0,"",H41/G41-1) -> 0.5950111 | I43: =IF(N(H41)=0,"",I41/H41-1) -> -0.18133383 | J43: =IF(N(I41)=0,"",J41/I41-1) -> 0.37105391 | K43: =IF(N(J41)=0,"",K41/J41-1) -> -0.029047113 | L43: =IF(N(K41)=0,"",L41/K41-1) -> 0.04134744 | R43: =IF(N(N41)=0,"",R41/N41-1) -> 0.010199557 | S43: =IF(N(O41)=0,"",S41/O41-1) -> 0.073412698 | T43: =IF(N(P41)=0,"",T41/P41-1) -> 0.061563169 | U43: =IF(N(Q41)=0,"",U41/Q41-1) -> 0.048379938
A45: 2. PER-SHARE DATA AND SHARE COUNT
A46: Earnings per common share - basic ($) | C46: 5.49 | D46: 6.43 | E46: 7.61 | F46: 7.95 | G46: 6.35 | H46: 10.11 | I46: 8.39 | J46: 11.63 | K46: 11.45 | L46: 12 | N46: 3.15 | P46: 2.61 | Q46: 3.15 | R46: 3.2 | T46: 2.79 | U46: 3.33
A47: Earnings per common share - diluted ($) | C47: 5.44 | D47: 6.37 | E47: 7.54 | F47: 7.88 | G47: 6.31 | H47: 10.04 | I47: 8.33 | J47: 11.56 | K47: 11.39 | L47: 11.95 | N47: 3.13 | P47: 2.6 | Q47: 3.14 | R47: 3.18 | T47: 2.78 | U47: 3.32
A48: YoY Growth | D48: =IF(N(C47)=0,"",D47/C47-1) -> 0.17095588 | E48: =IF(N(D47)=0,"",E47/D47-1) -> 0.18367347 | F48: =IF(N(E47)=0,"",F47/E47-1) -> 0.045092838 | G48: =IF(N(F47)=0,"",G47/F47-1) -> -0.19923858 | H48: =IF(N(G47)=0,"",H47/G47-1) -> 0.5911252 | I48: =IF(N(H47)=0,"",I47/H47-1) -> -0.17031873 | J48: =IF(N(I47)=0,"",J47/I47-1) -> 0.3877551 | K48: =IF(N(J47)=0,"",K47/J47-1) -> -0.014705882 | L48: =IF(N(K47)=0,"",L47/K47-1) -> 0.049165935 | R48: =IF(N(N47)=0,"",R47/N47-1) -> 0.015974441 | S48: =IF(N(O47)=0,"",S47/O47-1) | T48: =IF(N(P47)=0,"",T47/P47-1) -> 0.069230769 | U48: =IF(N(Q47)=0,"",U47/Q47-1) -> 0.057324841
A49: Dividends declared per common share ($) | B49: 3Q2024 includes the declaration normally made in 4Q (timing); FY basis is the 10-K figure | C49: 3.61 | D49: 3.83 | E49: 4.19 | F49: 4.73 | G49: 5.04 | H49: 5.25 | I49: 5.66 | J49: 6.23 | K49: 6.78 | L49: 7.17 | N49: 3.44 | P49: 1.77 | Q49: 1.77 | R49: 1.77 | T49: 1.86 | U49: 1.86
A50: Weighted-average shares outstanding - basic (mm) | C50: 854.4 | D50: 807.4 | E50: 778.2 | F50: 758.1 | G50: 744.6 | H50: 746.3 | I50: 736.5 | J50: 727.9 | K50: 718.3 | L50: 713.4 | N50: 716.7 | P50: 714.9 | Q50: 714.5 | R50: 712.9 | T50: 710.7 | U50: 709.1
A51: Weighted-average shares outstanding - diluted (mm) | C51: 861.2 | D51: 815.5 | E51: 785.6 | F51: 764.9 | G51: 750.1 | H51: 751.8 | I51: 741.3 | J51: 732.3 | K51: 721.9 | L51: 716.4 | N51: 720 | P51: 718.2 | Q51: 717.6 | R51: 715.9 | T51: 713.5 | U51: 711.1
A53: 3. TIE-OUT CHECKS
A54: Revenue components vs total (filed integers; rounding +/-2 expected) | C54: =C12+C14+C16-C17 -> 0 | D54: =D12+D14+D16-D17 -> 0 | E54: =E12+E14+E16-E17 -> 0 | F54: =F12+F14+F16-F17 -> 0 | G54: =G12+G14+G16-G17 -> 0 | H54: =H12+H14+H16-H17 -> 0 | I54: =I12+I14+I16-I17 -> -1 | J54: =J12+J14+J16-J17 -> 1 | ... L54: =L12+L14+L16-L17 -> 0 | N54: =N12+N14+N16-N17 -> 1 | O54: =O12+O14+O16-O17 -> 0 | P54: =P12+P14+P16-P17 -> -1 | Q54: =Q12+Q14+Q16-Q17 -> 0 | R54: =R12+R14+R16-R17 -> -1 | S54: =S12+S14+S16-S17 -> -1 | T54: =T12+T14+T16-T17 -> 0 | U54: =U12+U14+U16-U17 -> 1
A55: Operating cost lines vs total (rounding +/-2 expected) | C55: =C20+C25+C26+C30+C31-C32 -> 0 | D55: =D20+D25+D26+D30+D31-D32 -> 0 | E55: =E20+E25+E26+E30+E31-E32 -> 0 | F55: =F20+F25+F26+F30+F31-F32 -> 0 | G55: =G20+G25+G26+G30+G31-G32 -> 0 | H55: =H20+H25+H26+H30+H31-H32 -> 0 | I55: =I20+I25+I26+I30+I31-I32 -> -1 | J55: =J20+J25+J26+J30+J31-J32 -> 0 | ... L55: =L20+L25+L26+L30+L31-L32 -> 1 | N55: =N20+N25+N26+N30+N31-N32 -> -1 | O55: =O20+O25+O26+O30+O31-O32 -> -1 | P55: =P20+P25+P26+P30+P31-P32 -> 0 | Q55: =Q20+Q25+Q26+Q30+Q31-Q32 -> 0 | R55: =R20+R25+R26+R30+R31-R32 -> 0 | S55: =S20+S25+S26+S30+S31-S32 -> 1 | T55: =T20+T25+T26+T30+T31-T32 -> 0 | U55: =U20+U25+U26+U30+U31-U32 -> 1
A56: Revenue - operating costs - operating income (rounding) | C56: =C17-C32-C33 -> 0 | D56: =D17-D32-D33 -> 0 | E56: =E17-E32-E33 -> 0 | F56: =F17-F32-F33 -> 0 | G56: =G17-G32-G33 -> 0 | H56: =H17-H32-H33 -> 0 | I56: =I17-I32-I33 -> 0 | J56: =J17-J32-J33 -> 0 | ... L56: =L17-L32-L33 -> 0 | N56: =N17-N32-N33 -> 0 | O56: =O17-O32-O33 -> 0 | P56: =P17-P32-P33 -> 0 | Q56: =Q17-Q32-Q33 -> 0 | R56: =R17-R32-R33 -> 0 | S56: =S17-S32-S33 -> 0 | T56: =T17-T32-T33 -> 0 | U56: =U17-U32-U33 -> 1
A57: Operating income - interest - nonoperating - pre-tax (rounding) | C57: =C33-C37-C38-C39 -> 0 | D57: =D33-D37-D38-D39 -> 0 | E57: =E33-E37-E38-E39 -> 0 | F57: =F33-F37-F38-F39 -> 0 | G57: =G33-G37-G38-G39 -> 0 | H57: =H33-H37-H38-H39 -> 0 | I57: =I33-I37-I38-I39 -> 0 | J57: =J33-J37-J38-J39 -> 0 | ... L57: =L33-L37-L38-L39 -> 1 | N57: =N33-N37-N38-N39 -> 0 | O57: =O33-O37-O38-O39 -> -1 | P57: =P33-P37-P38-P39 -> -1 | Q57: =Q33-Q37-Q38-Q39 -> -1 | R57: =R33-R37-R38-R39 -> 1 | S57: =S33-S37-S38-S39 -> 1 | T57: =T33-T37-T38-T39 -> 0 | U57: =U33-U37-U38-U39 -> -1
A58: Pre-tax - tax - net income (rounding) | C58: =C39-C40-C41 -> 0 | D58: =D39-D40-D41 -> 0 | E58: =E39-E40-E41 -> 0 | F58: =F39-F40-F41 -> 0 | G58: =G39-G40-G41 -> 0 | H58: =H39-H40-H41 -> 0 | I58: =I39-I40-I41 -> 0 | J58: =J39-J40-J41 -> 0 | ... L58: =L39-L40-L41 -> 0 | N58: =N39-N40-N41 -> 0 | O58: =O39-O40-O41 -> 1 | P58: =P39-P40-P41 -> 1 | Q58: =Q39-Q40-Q41 -> 0 | R58: =R39-R40-R41 -> 0 | S58: =S39-S40-S41 -> -1 | T58: =T39-T40-T41 -> 0 | U58: =U39-U40-U41 -> 0

Sheet Balance Sheet
A1: McDonald's Corporation — Balance Sheet
A2: $ in millions except per-share data | USD | as of 2026-10-08
C3: FY2016 | D3: FY2017 | E3: FY2018 | F3: FY2019 | G3: FY2020 | H3: FY2021 | I3: FY2022 | J3: FY2023 | K3: FY2024 | L3: FY2025 | M3: · | N3: 3Q2024 | O3: 4Q2024* | P3: 1Q2025 | Q3: 2Q2025 | R3: 3Q2025 | S3: 4Q2025* | T3: 1Q2026 | U3: 2Q2026
C4: 2016-12-31 | D4: 2017-12-31 | E4: 2018-12-31 | F4: 2019-12-31 | G4: 2020-12-31 | H4: 2021-12-31 | I4: 2022-12-31 | J4: 2023-12-31 | K4: 2024-12-31 | L4: 2025-12-31 | N4: 2024-09-30 | O4: 2024-12-31 | P4: 2025-03-31 | Q4: 2025-06-30 | R4: 2025-09-30 | S4: 2025-12-31 | T4: 2026-03-31 | U4: 2026-06-30
A6: CONTENTS
A7: =HYPERLINK("#'Balance Sheet'!A13","1. ASSETS") -> 1. ASSETS
A8: =HYPERLINK("#'Balance Sheet'!A31","2. LIABILITIES") -> 2. LIABILITIES
A9: =HYPERLINK("#'Balance Sheet'!A49","3. SHAREHOLDERS' EQUITY (DEFICIT)") -> 3. SHAREHOLDERS' EQUITY (DEFICIT)
A10: =HYPERLINK("#'Balance Sheet'!A60","4. TIE-OUT CHECKS") -> 4. TIE-OUT CHECKS
A11: =HYPERLINK("#'Balance Sheet'!A68","5. DEBT AND LEASE SUMMARY (ANALYST CALCULATION FROM FILED LINES)") -> 5. DEBT AND LEASE SUMMARY (ANALYST CALCULATION FROM FILED LINES)
A13: 1. ASSETS
A14: Cash and equivalents | C14: 1223.4 | D14: 2463.8 | E14: 866 | F14: 898.5 | G14: 3449.1 | H14: 4709.2 | I14: 2583.8 | J14: 4579 | K14: 1085 | L14: 774 | N14: 1221 | O14: 1085 | P14: 1238 | Q14: 1876 | R14: 2413 | S14: 774 | T14: 1170 | U14: 822
A15: Accounts and notes receivable | C15: 1474.1 | D15: 1976.2 | E15: 2441.5 | F15: 2224.2 | G15: 2110.3 | H15: 1872.4 | I15: 2115 | J15: 2488 | K15: 2383 | L15: 2466 | N15: 2460 | O15: 2383 | P15: 2387 | Q15: 2550 | R15: 2579 | S15: 2466 | T15: 2432 | U15: 2485
A16: Inventories, at cost, not in excess of market | C16: 58.9 | D16: 58.8 | E16: 51.1 | F16: 50.2 | G16: 51.1 | H16: 55.6 | I16: 52 | J16: 53 | K16: 56 | L16: 61 | N16: 54 | O16: 56 | P16: 51 | Q16: 55 | R16: 55 | S16: 61 | T16: 61 | U16: 58
A17: Prepaid expenses and other current assets | C17: 565.2 | D17: 828.4 | E17: 694.6 | F17: 385 | G17: 632.7 | H17: 511.3 | I17: 673.4 | J17: 866 | K17: 1074 | L17: 863 | N17: 1176 | O17: 1074 | P17: 1060 | Q17: 1120 | R17: 1032 | S17: 863 | T17: 1046 | U17: 980
A18: Assets of businesses held for sale | C18: 1527 | D18: 0
A19: Total current assets | C19: 4848.6 | D19: 5327.2 | E19: 4053.2 | F19: 3557.9 | G19: 6243.2 | H19: 7148.5 | I19: 5424.2 | J19: 7986 | K19: 4599 | L19: 4163 | N19: 4912 | O19: 4599 | P19: 4735 | Q19: 5601 | R19: 6079 | S19: 4163 | T19: 4709 | U19: 4345
A21: Investments in and advances to affiliates | C21: 725.9 | D21: 1085.7 | E21: 1202.8 | F21: 1270.3 | G21: 1297.2 | H21: 1201.2 | I21: 1064.5 | J21: 1080 | K21: 2710 | L21: 2820 | N21: 2960 | O21: 2710 | P21: 2751 | Q21: 2827 | R21: 2864 | S21: 2820 | T21: 2865 | U21: 2896
A22: Goodwill | C22: 2336.5 | D22: 2379.7 | E22: 2331.5 | F22: 2677.4 | G22: 2773.1 | H22: 2782.5 | I22: 2900.4 | J22: 3040 | K22: 3145 | L22: 3354 | N22: 3220 | O22: 3145 | P22: 3186 | Q22: 3308 | R22: 3306 | S22: 3354 | T22: 3349 | U22: 3347
A23: Miscellaneous other assets | C23: 1855.3 | D23: 2562.8 | E23: 2381 | F23: 2584 | G23: 3527.4 | H23: 4449.5 | I23: 4707.2 | J23: 5618 | K23: 6095 | L23: 6331 | N23: 5673 | O23: 6095 | P23: 6265 | Q23: 6492 | R23: 6588 | S23: 6331 | T23: 6357 | U23: 6393
A24: Total other assets | C24: 4917.7 | D24: 6028.2 | E24: 5915.3 | F24: 6531.7 | G24: 7597.7 | H24: 8433.2 | I24: 8672.1 | J24: 9738 | K24: 11950 | L24: 12505 | N24: 11853 | O24: 11950 | P24: 12202 | Q24: 12628 | R24: 12758 | S24: 12505 | T24: 12571 | U24: 12637
A25: Lease right-of-use asset, net | B25: Presented from FY2019 (ASC 842 adoption); no comparable line for FY2016-FY2018 | E25: 0 | F25: 13261.2 | G25: 13827.7 | H25: 13552 | I25: 12565.7 | J25: 13514 | K25: 13339 | L25: 14606 | N25: 13632 | O25: 13339 | P25: 13642 | Q25: 14286 | R25: 14285 | S25: 14606 | T25: 14513 | U25: 14459
A26: Property and equipment, at cost | C26: 34443.4 | D26: 36626.4 | E26: 37193.6 | F26: 39050.9 | G26: 41476.5 | H26: 41916.6 | I26: 41037.6 | J26: 43570 | K26: 44177 | L26: 49290 | N26: 45178 | O26: 44177 | P26: 45258 | Q26: 47609 | R26: 48215 | S26: 49290 | T26: 49477 | U26: 49943
A27: Accumulated depreciation and amortization | C27: -13185.8 | D27: -14178.1 | E27: -14350.9 | F27: -14890.9 | G27: -16518.3 | H27: -17196 | I27: -17264 | J27: -18662 | K27: -18882 | L27: -21049 | N27: -19403 | O27: -18882 | P27: -19509 | Q27: -20570 | R27: -20729 | S27: -21049 | T27: -21232 | U27: -21464
A28: Net property and equipment | C28: 21257.6 | D28: 22448.3 | E28: 22842.7 | F28: 24160 | G28: 24958.2 | H28: 24720.6 | I28: 23773.6 | J28: 24908 | K28: 25295 | L28: 28241 | N28: 25775 | O28: 25295 | P28: 25749 | Q28: 27039 | R28: 27486 | S28: 28241 | T28: 28245 | U28: 28479
A29: Total assets | C29: 31023.9 | D29: 33803.7 | E29: 32811.2 | F29: 47510.8 | G29: 52626.8 | H29: 53854.3 | I29: 50435.6 | J29: 56147 | K29: 55182 | L29: 59515 | N29: 56172 | O29: 55182 | P29: 56329 | Q29: 59555 | R29: 60608 | S29: 59515 | T29: 60037 | U29: 59920
A31: 2. LIABILITIES
A32: Accounts payable | C32: 756 | D32: 924.8 | E32: 1207.9 | F32: 988.2 | G32: 741.3 | H32: 1006.8 | I32: 980.2 | J32: 1103 | K32: 1029 | L32: 1149 | N32: 944 | O32: 1029 | P32: 882 | Q32: 838 | R32: 972 | S32: 1149 | T32: 1091 | U32: 1114
A33: Lease liability (current) | E33: 0 | F33: 621 | G33: 701.5 | H33: 705.5 | I33: 661.1 | J33: 688 | K33: 636 | L33: 694 | N33: 668 | O33: 636 | P33: 663 | Q33: 686 | R33: 698 | S33: 694 | T33: 707 | U33: 690
A34: Income taxes | C34: 267.2 | D34: 265.8 | E34: 228.3 | F34: 331.7 | G34: 741.1 | H34: 360.7 | I34: 274.9 | J34: 705 | K34: 361 | L34: 250 | N34: 786 | O34: 361 | P34: 556 | Q34: 24 | R34: 367 | S34: 250 | T34: 391 | U34: 327
A35: Other taxes | C35: 266.3 | D35: 275.4 | E35: 253.7 | F35: 247.5 | G35: 227 | H35: 236.7 | I35: 255.1 | J35: 268 | K35: 224 | L35: 247 | N35: 263 | O35: 224 | P35: 235 | Q35: 245 | R35: 242 | S35: 247 | T35: 253 | U35: 261
A36: Accrued interest | C36: 247.5 | D36: 278.4 | E36: 297 | F36: 337.8 | G36: 388.4 | H36: 363.3 | I36: 393.4 | J36: 469 | K36: 482 | L36: 533 | N36: 433 | O36: 482 | P36: 401 | Q36: 451 | R36: 471 | S36: 533 | T36: 448 | U36: 428
A37: Accrued payroll and other liabilities | C37: 1159.3 | D37: 1146.2 | E37: 986.6 | F37: 1035.7 | G37: 1138.3 | H37: 1347 | I37: 1237.4 | J37: 1434 | K37: 1129 | L37: 1488 | N37: 1353 | O37: 1129 | P37: 1191 | Q37: 1452 | R37: 1529 | S37: 1488 | T37: 1257 | U37: 1198
A38: Dividend payable | B38: Separate line only in the 3Q2024 10-Q | N38: 1265
A39: Short-term borrowings and current maturities of long-term debt | B39: Captioned 'Current maturities of long-term debt' through FY2021; line absent (nil) where blank | C39: 77.2 | D39: 0 | E39: 0 | F39: 59.1 | G39: 2243.6 | H39: 0 | I39: 0 | J39: 2192 | K39: 0 | N39: 596 | O39: 0 | P39: 80 | Q39: 602 | R39: 1800
A40: Liabilities of businesses held for sale | C40: 694.8 | D40: 0
A41: Total current liabilities | C41: 3468.3 | D41: 2890.6 | E41: 2973.5 | F41: 3621 | G41: 6181.2 | H41: 4020 | I41: 3802.1 | J41: 6859 | K41: 3861 | L41: 4361 | N41: 6308 | O41: 3861 | P41: 4008 | Q41: 4298 | R41: 6079 | S41: 4361 | T41: 4146 | U41: 4018
A42: Long-term debt | C42: 25878.5 | D42: 29536.4 | E42: 31075.3 | F42: 34118.1 | G42: 35196.8 | H42: 35622.7 | I42: 35903.5 | J42: 37153 | K42: 38424 | L42: 39973 | N42: 38990 | O42: 38424 | P42: 38845 | Q42: 40801 | R42: 39483 | S42: 39973 | T42: 40105 | U42: 39863
A43: Long-term lease liability | E43: 0 | F43: 12757.8 | G43: 13321.3 | H43: 13020.9 | I43: 12134.4 | J43: 13058 | K43: 12888 | L43: 14147 | N43: 13157 | O43: 12888 | P43: 13175 | Q43: 13778 | R43: 13837 | S43: 14147 | T43: 14069 | U43: 14039
A44: Long-term income taxes | B44: Separate line from FY2017 10-K; FY2016 amount is within Other long-term liabilities (see restatement log) | C44: 1010.6 | D44: 2370.9 | E44: 2081.2 | F44: 2265.9 | G44: 1970.7 | H44: 1896.8 | I44: 791.9 | J44: 363 | K44: 344 | L44: 139 | N44: 74 | O44: 344 | P44: 365 | Q44: 292 | R44: 285 | S44: 139 | T44: 151 | U44: 176
A45: Deferred revenues - initial franchise fees | B45: Separate line from FY2018 10-K | D45: 0 | E45: 627.8 | F45: 660.6 | G45: 702 | H45: 738.3 | I45: 757.8 | J45: 790 | K45: 778 | L45: 945 | N45: 800 | O45: 778 | P45: 914 | Q45: 933 | R45: 936 | S45: 945 | T45: 946 | U45: 946
A46: Other long-term liabilities | C46: 1053.7 | D46: 1154.4 | E46: 1096.3 | F46: 979.6 | G46: 1054.1 | H46: 1081 | I46: 1051.8 | J46: 950 | K46: 771 | L46: 704 | N46: 855 | O46: 771 | P46: 755 | Q46: 790 | R46: 694 | S46: 704 | T46: 686 | U46: 677
A47: Deferred income taxes | C47: 1817.1 | D47: 1119.4 | E47: 1215.5 | F47: 1318.1 | G47: 2025.6 | H47: 2075.6 | I47: 1997.5 | J47: 1681 | K47: 1914 | L47: 1038 | N47: 1166 | O47: 1914 | P47: 1721 | Q47: 1423 | R47: 1457 | S47: 1038 | T47: 1220 | U47: 1222
A49: 3. SHAREHOLDERS' EQUITY (DEFICIT)
A50: Preferred stock (none issued) | C50: 0 | D50: 0 | E50: 0 | F50: 0 | G50: 0 | H50: 0 | I50: 0 | J50: 0 | K50: 0 | L50: 0 | N50: 0 | O50: 0 | P50: 0 | Q50: 0 | R50: 0 | S50: 0 | T50: 0 | U50: 0
A51: Common stock, $0.01 par value | C51: 16.6 | D51: 16.6 | E51: 16.6 | F51: 16.6 | G51: 16.6 | H51: 16.6 | I51: 16.6 | J51: 17 | K51: 17 | L51: 17 | N51: 17 | O51: 17 | P51: 17 | Q51: 17 | R51: 17 | S51: 17 | T51: 17 | U51: 17
A52: Additional paid-in capital | C52: 6757.9 | D52: 7072.4 | E52: 7376 | F52: 7653.9 | G52: 7903.6 | H52: 8231.6 | I52: 8547.1 | J52: 8893 | K52: 9281 | L52: 9641 | N52: 9194 | O52: 9281 | P52: 9423 | Q52: 9500 | R52: 9560 | S52: 9641 | T52: 9792 | U52: 9841
A53: Retained earnings | C53: 46222.7 | D53: 48325.8 | E53: 50487 | F53: 52930.5 | G53: 53908.1 | H53: 57534.7 | I53: 59543.9 | J53: 63480 | K53: 66834 | L53: 70282 | N53: 64819 | O53: 66834 | P53: 67436 | Q53: 68424 | R53: 69440 | S53: 70282 | T53: 70942 | U53: 71987
A54: Accumulated other comprehensive income (loss) | C54: -3092.9 | D54: -2178.4 | E54: -2609.5 | F54: -2482.7 | G54: -2586.8 | H54: -2573.7 | I54: -2486.6 | J54: -2456 | K54: -2553 | L54: -2414 | N54: -2337 | O54: -2553 | P54: -2557 | Q54: -2430 | R54: -2414 | S54: -2414 | T54: -2363 | U54: -2340
A55: Common stock in treasury, at cost | C55: -52108.6 | D55: -56504.4 | E55: -61528.5 | F55: -66328.6 | G55: -67066.4 | H55: -67810.2 | I55: -71624.4 | J55: -74640 | K55: -77375 | L55: -79316 | N55: -76870 | O55: -77375 | P55: -77773 | Q55: -78271 | R55: -78766 | S55: -79316 | T55: -79673 | U55: -80527
A56: Total shareholders' equity (deficit) | C56: -2204.3 | D56: -3268 | E56: -6258.4 | F56: -8210.3 | G56: -7824.9 | H56: -4601 | I56: -6003.4 | J56: -4707 | K56: -3797 | L56: -1791 | N56: -5177 | O56: -3797 | P56: -3454 | Q56: -2760 | R56: -2163 | S56: -1791 | T56: -1286 | U56: -1023
A57: Total liabilities and shareholders' equity (deficit) | C57: 31023.9 | D57: 33803.7 | E57: 32811.2 | F57: 47510.8 | G57: 52626.8 | H57: 53854.3 | I57: 50435.6 | J57: 56147 | K57: 55182 | L57: 59515 | N57: 56172 | O57: 55182 | P57: 56329 | Q57: 59555 | R57: 60608 | S57: 59515 | T57: 60037 | U57: 59920
A58: Total liabilities (derived: total less equity) | C58: =C57-C56 -> 33228.2 | D58: =D57-D56 -> 37071.7 | E58: =E57-E56 -> 39069.6 | F58: =F57-F56 -> 55721.1 | G58: =G57-G56 -> 60451.7 | H58: =H57-H56 -> 58455.3 | I58: =I57-I56 -> 56439 | J58: =J57-J56 -> 60854 | ... L58: =L57-L56 -> 61306 | N58: =N57-N56 -> 61349 | O58: =O57-O56 -> 58979 | P58: =P57-P56 -> 59783 | Q58: =Q57-Q56 -> 62315 | R58: =R57-R56 -> 62771 | S58: =S57-S56 -> 61306 | T58: =T57-T56 -> 61323 | U58: =U57-U56 -> 60943
A60: 4. TIE-OUT CHECKS
A61: Balance Check: total assets - total liabilities and equity (should be ~0) | C61: =C29-C57 -> 0 | D61: =D29-D57 -> 0 | E61: =E29-E57 -> 0 | F61: =F29-F57 -> 0 | G61: =G29-G57 -> 0 | H61: =H29-H57 -> 0 | I61: =I29-I57 -> 0 | J61: =J29-J57 -> 0 | ... L61: =L29-L57 -> 0 | N61: =N29-N57 -> 0 | O61: =O29-O57 -> 0 | P61: =P29-P57 -> 0 | Q61: =Q29-Q57 -> 0 | R61: =R29-R57 -> 0 | S61: =S29-S57 -> 0 | T61: =T29-T57 -> 0 | U61: =U29-U57 -> 0
A62: Asset groups vs total assets (rounding +/-2 expected) | C62: =C19+C24+C25+C28-C29 -> 0 | D62: =D19+D24+D25+D28-D29 -> 0 | E62: =E19+E24+E25+E28-E29 -> 0 | F62: =F19+F24+F25+F28-F29 -> 0 | G62: =G19+G24+G25+G28-G29 -> 0 | H62: =H19+H24+H25+H28-H29 -> 0 | I62: =I19+I24+I25+I28-I29 -> 0 | J62: =J19+J24+J25+J28-J29 -> -1 | ... L62: =L19+L24+L25+L28-L29 -> 0 | N62: =N19+N24+N25+N28-N29 -> 0 | O62: =O19+O24+O25+O28-O29 -> 1 | P62: =P19+P24+P25+P28-P29 -> -1 | Q62: =Q19+Q24+Q25+Q28-Q29 -> -1 | R62: =R19+R24+R25+R28-R29 -> 0 | S62: =S19+S24+S25+S28-S29 -> 0 | T62: =T19+T24+T25+T28-T29 -> 1 | U62: =U19+U24+U25+U28-U29 -> 0
A63: Gross PP&E - accumulated depreciation vs net PP&E (rounding) | C63: =C26+C27-C28 -> 0 | D63: =D26+D27-D28 -> 0 | E63: =E26+E27-E28 -> 0 | F63: =F26+F27-F28 -> 0 | G63: =G26+G27-G28 -> 0 | H63: =H26+H27-H28 -> 0 | I63: =I26+I27-I28 -> 0 | J63: =J26+J27-J28 -> 0 | ... L63: =L26+L27-L28 -> 0 | N63: =N26+N27-N28 -> 0 | O63: =O26+O27-O28 -> 0 | P63: =P26+P27-P28 -> 0 | Q63: =Q26+Q27-Q28 -> 0 | R63: =R26+R27-R28 -> 0 | S63: =S26+S27-S28 -> 0 | T63: =T26+T27-T28 -> 0 | U63: =U26+U27-U28 -> 0
A64: Current liability lines vs total (rounding +/-2 expected) | C64: =C32+C33+C34+C35+C36+C37+C38+C39+C40-C41 -> 0 | D64: =D32+D33+D34+D35+D36+D37+D38+D39+D40-D41 -> 0 | E64: =E32+E33+E34+E35+E36+E37+E38+E39+E40-E41 -> 0 | F64: =F32+F33+F34+F35+F36+F37+F38+F39+F40-F41 -> 0 | G64: =G32+G33+G34+G35+G36+G37+G38+G39+G40-G41 -> 0 | H64: =H32+H33+H34+H35+H36+H37+H38+H39+H40-H41 -> 0 | I64: =I32+I33+I34+I35+I36+I37+I38+I39+I40-I41 -> 0 | J64: =J32+J33+J34+J35+J36+J37+J38+J39+J40-J41 -> 0 | ... L64: =L32+L33+L34+L35+L36+L37+L38+L39+L40-L41 -> 0 | N64: =N32+N33+N34+N35+N36+N37+N38+N39+N40-N41 -> 0 | O64: =O32+O33+O34+O35+O36+O37+O38+O39+O40-O41 -> 0 | P64: =P32+P33+P34+P35+P36+P37+P38+P39+P40-P41 -> 0 | Q64: =Q32+Q33+Q34+Q35+Q36+Q37+Q38+Q39+Q40-Q41 -> 0 | R64: =R32+R33+R34+R35+R36+R37+R38+R39+R40-R41 -> 0 | S64: =S32+S33+S34+S35+S36+S37+S38+S39+S40-S41 -> 0 | T64: =T32+T33+T34+T35+T36+T37+T38+T39+T40-T41 -> 1 | U64: =U32+U33+U34+U35+U36+U37+U38+U39+U40-U41 -> 0
A65: Equity components vs total equity (rounding +/-2 expected) | C65: =C50+C51+C52+C53+C54+C55-C56 -> 0 | D65: =D50+D51+D52+D53+D54+D55-D56 -> 0 | E65: =E50+E51+E52+E53+E54+E55-E56 -> 0 | F65: =F50+F51+F52+F53+F54+F55-F56 -> 0 | G65: =G50+G51+G52+G53+G54+G55-G56 -> 0 | H65: =H50+H51+H52+H53+H54+H55-H56 -> 0 | I65: =I50+I51+I52+I53+I54+I55-I56 -> 0 | J65: =J50+J51+J52+J53+J54+J55-J56 -> 1 | ... L65: =L50+L51+L52+L53+L54+L55-L56 -> 1 | N65: =N50+N51+N52+N53+N54+N55-N56 -> 0 | O65: =O50+O51+O52+O53+O54+O55-O56 -> 1 | P65: =P50+P51+P52+P53+P54+P55-P56 -> 0 | Q65: =Q50+Q51+Q52+Q53+Q54+Q55-Q56 -> 0 | R65: =R50+R51+R52+R53+R54+R55-R56 -> 0 | S65: =S50+S51+S52+S53+S54+S55-S56 -> 1 | T65: =T50+T51+T52+T53+T54+T55-T56 -> 1 | U65: =U50+U51+U52+U53+U54+U55-U56 -> 1
A66: Current asset lines vs total (rounding +/-2 expected) | C66: =C14+C15+C16+C17+C18-C19 -> 0 | D66: =D14+D15+D16+D17+D18-D19 -> 0 | E66: =E14+E15+E16+E17+E18-E19 -> 0 | F66: =F14+F15+F16+F17+F18-F19 -> 0 | G66: =G14+G15+G16+G17+G18-G19 -> 0 | H66: =H14+H15+H16+H17+H18-H19 -> 0 | I66: =I14+I15+I16+I17+I18-I19 -> 0 | J66: =J14+J15+J16+J17+J18-J19 -> 0 | ... L66: =L14+L15+L16+L17+L18-L19 -> 1 | N66: =N14+N15+N16+N17+N18-N19 -> -1 | O66: =O14+O15+O16+O17+O18-O19 -> -1 | P66: =P14+P15+P16+P17+P18-P19 -> 1 | Q66: =Q14+Q15+Q16+Q17+Q18-Q19 -> 0 | R66: =R14+R15+R16+R17+R18-R19 -> 0 | S66: =S14+S15+S16+S17+S18-S19 -> 1 | T66: =T14+T15+T16+T17+T18-T19 -> 0 | U66: =U14+U15+U16+U17+U18-U19 -> 0
A68: 5. DEBT AND LEASE SUMMARY (ANALYST CALCULATION FROM FILED LINES)
A69: Total debt (short-term + long-term) | C69: =C39+C42 -> 25955.7 | D69: =D39+D42 -> 29536.4 | E69: =E39+E42 -> 31075.3 | F69: =F39+F42 -> 34177.2 | G69: =G39+G42 -> 37440.4 | H69: =H39+H42 -> 35622.7 | I69: =I39+I42 -> 35903.5 | J69: =J39+J42 -> 39345 | ... L69: =L39+L42 -> 39973 | N69: =N39+N42 -> 39586 | O69: =O39+O42 -> 38424 | P69: =P39+P42 -> 38925 | Q69: =Q39+Q42 -> 41403 | R69: =R39+R42 -> 41283 | S69: =S39+S42 -> 39973 | T69: =T39+T42 -> 40105 | U69: =U39+U42 -> 39863
A70: Total lease liabilities (current + long-term) | C70: =C33+C43 -> 0 | D70: =D33+D43 -> 0 | E70: =E33+E43 -> 0 | F70: =F33+F43 -> 13378.8 | G70: =G33+G43 -> 14022.8 | H70: =H33+H43 -> 13726.4 | I70: =I33+I43 -> 12795.5 | J70: =J33+J43 -> 13746 | ... L70: =L33+L43 -> 14841 | N70: =N33+N43 -> 13825 | O70: =O33+O43 -> 13524 | P70: =P33+P43 -> 13838 | Q70: =Q33+Q43 -> 14464 | R70: =R33+R43 -> 14535 | S70: =S33+S43 -> 14841 | T70: =T33+T43 -> 14776 | U70: =U33+U43 -> 14729
A71: Net debt (total debt less cash and equivalents) | C71: =C69-C14 -> 24732.3 | D71: =D69-D14 -> 27072.6 | E71: =E69-E14 -> 30209.3 | F71: =F69-F14 -> 33278.7 | G71: =G69-G14 -> 33991.3 | H71: =H69-H14 -> 30913.5 | I71: =I69-I14 -> 33319.7 | J71: =J69-J14 -> 34766 | ... L71: =L69-L14 -> 39199 | N71: =N69-N14 -> 38365 | O71: =O69-O14 -> 37339 | P71: =P69-P14 -> 37687 | Q71: =Q69-Q14 -> 39527 | R71: =R69-R14 -> 38870 | S71: =S69-S14 -> 39199 | T71: =T69-T14 -> 38935 | U71: =U69-U14 -> 39041
A72: Net debt including lease liabilities | C72: =C71+C70 -> 24732.3 | D72: =D71+D70 -> 27072.6 | E72: =E71+E70 -> 30209.3 | F72: =F71+F70 -> 46657.5 | G72: =G71+G70 -> 48014.1 | H72: =H71+H70 -> 44639.9 | I72: =I71+I70 -> 46115.2 | J72: =J71+J70 -> 48512 | ... L72: =L71+L70 -> 54040 | N72: =N71+N70 -> 52190 | O72: =O71+O70 -> 50863 | P72: =P71+P70 -> 51525 | Q72: =Q71+Q70 -> 53991 | R72: =R71+R70 -> 53405 | S72: =S71+S70 -> 54040 | T72: =T71+T70 -> 53711 | U72: =U71+U70 -> 53770

Sheet Cash Flow
A1: McDonald's Corporation — Cash Flow
A2: $ in millions except per-share data | USD | as of 2026-10-08
C3: FY2016 | D3: FY2017 | E3: FY2018 | F3: FY2019 | G3: FY2020 | H3: FY2021 | I3: FY2022 | J3: FY2023 | K3: FY2024 | L3: FY2025 | M3: · | N3: 3Q2024 | O3: 4Q2024* | P3: 1Q2025 | Q3: 2Q2025 | R3: 3Q2025 | S3: 4Q2025* | T3: 1Q2026 | U3: 2Q2026
C4: 2016-12-31 | D4: 2017-12-31 | E4: 2018-12-31 | F4: 2019-12-31 | G4: 2020-12-31 | H4: 2021-12-31 | I4: 2022-12-31 | J4: 2023-12-31 | K4: 2024-12-31 | L4: 2025-12-31 | N4: 2024-09-30 | O4: 2024-12-31 | P4: 2025-03-31 | Q4: 2025-06-30 | R4: 2025-09-30 | S4: 2025-12-31 | T4: 2026-03-31 | U4: 2026-06-30
A6: CONTENTS
A7: =HYPERLINK("#'Cash Flow'!A14","1. OPERATING ACTIVITIES") -> 1. OPERATING ACTIVITIES
A8: =HYPERLINK("#'Cash Flow'!A30","2. INVESTING ACTIVITIES") -> 2. INVESTING ACTIVITIES
A9: =HYPERLINK("#'Cash Flow'!A40","3. FINANCING ACTIVITIES") -> 3. FINANCING ACTIVITIES
A10: =HYPERLINK("#'Cash Flow'!A51","4. CASH RECONCILIATION AND SUPPLEMENTAL") -> 4. CASH RECONCILIATION AND SUPPLEMENTAL
A11: =HYPERLINK("#'Cash Flow'!A61","5. TIE-OUT CHECKS") -> 5. TIE-OUT CHECKS
A12: =HYPERLINK("#'Cash Flow'!A70","6. FREE CASH FLOW ANALYTICS (ANALYST CALCULATION)") -> 6. FREE CASH FLOW ANALYTICS (ANALYST CALCULATION)
A14: 1. OPERATING ACTIVITIES
A15: Net income | C15: 4686.5 | D15: 5192.3 | E15: 5924.3 | F15: 6025.4 | G15: 4730.5 | H15: 7545.2 | I15: 6177 | J15: 8469 | K15: 8223 | L15: 8563 | N15: 2255 | O15: 2016 | P15: 1868 | Q15: 2253 | R15: 2278 | S15: 2164 | T15: 1983 | U15: 2362
A16: Depreciation and amortization | C16: 1516.5 | D16: 1363.4 | E16: 1482 | F16: 1617.9 | G16: 1751.4 | H16: 1868.1 | I16: 1871 | J16: 1978 | K16: 2097 | L16: 2199 | N16: 532 | O16: 553 | P16: 520 | Q16: 544 | R16: 559 | S16: 576 | T16: 566 | U16: 565
A17: Deferred income taxes | C17: -538.6 | D17: -36.4 | E17: 102.6 | F17: 149.7 | G17: 6.4 | H17: -428.3 | I17: -346 | J17: -686 | K17: -574 | L17: -126 | N17: -137 | O17: -73 | P17: -44 | Q17: -41 | R17: 35 | S17: -77 | T17: 63 | U17: -58
A18: Share-based compensation | C18: 131.3 | D18: 117.5 | E18: 125.1 | F18: 109.6 | G18: 92.4 | H18: 139.2 | I18: 167 | J18: 175 | K18: 172 | L18: 165 | N18: 40 | O18: 44 | P18: 45 | Q18: 44 | R18: 39 | S18: 37 | T18: 60 | U18: 39
A19: Net (gain) loss on sale of restaurant and other businesses | B19: Separate line FY2017+ (recast); in 10-Qs it is included in 'Other' below | C19: -310.7 | D19: -1155.8 | E19: -308.8 | F19: -128.2 | G19: -28.2 | H19: -97.8 | I19: 733 | J19: -103 | K19: -37 | L19: -149
A20: Other | B20: 10-Q 'Other' and 4Q* include the net gain/loss on sale line | C20: 407.6 | D20: 1050.7 | E20: 114.2 | F20: 49.2 | G20: -75.2 | H20: -339.1 | I20: -570 | J20: -113 | K20: 3 | L20: -207 | N20: -33 | O20: 14 | P20: -73 | Q20: -71 | R20: -53 | S20: -159 | T20: -92 | U20: -51
A21: Working capital: Accounts receivable | C21: -159 | D21: -340.7 | E21: -479.4 | F21: 27 | G21: -6.8 | H21: 309.9 | I21: -264 | J21: -161 | K21: 10 | L21: 231
A22: Working capital: Inventories, prepaid expenses and other current assets | C22: 28.1 | D22: -37.3 | E22: -1.9 | F22: 128.8 | G22: -68.6 | H22: -62.2 | I22: 6 | J22: 17 | K22: 71 | L22: -140
A23: Working capital: Accounts payable | C23: 89.8 | D23: -59.7 | E23: 129.4 | F23: -26.8 | G23: -137.5 | H23: 225 | I23: 31 | J23: 50 | K23: -10 | L23: 100
A24: Working capital: Income taxes | C24: 169.7 | D24: -396.4 | E24: -33.4 | F24: 173.4 | G24: -43.6 | H24: -302.5 | I24: -547 | J24: -220 | K24: -292 | L24: -239
A25: Working capital: Other accrued liabilities | C25: 38.4 | D25: -146.4 | E25: -87.4 | F25: -3.9 | G25: 44.4 | H25: 284 | I25: 129 | J25: 206 | K25: -217 | L25: 154
A26: Changes in working capital items (10-Q single-line) | B26: 10-Q presents one line; 4Q* = FY sum of the five lines less 9M YTD | N26: 79 | O26: 76 | P26: 111 | Q26: -731 | R26: 570 | S26: 156 | T26: -168 | U26: -50
A27: Changes in working capital items | C27: =C21+C22+C23+C24+C25 -> 167 | D27: =D21+D22+D23+D24+D25 -> -980.5 | E27: =E21+E22+E23+E24+E25 -> -472.7 | F27: =F21+F22+F23+F24+F25 -> 298.5 | G27: =G21+G22+G23+G24+G25 -> -212.1 | H27: =H21+H22+H23+H24+H25 -> 454.2 | I27: =I21+I22+I23+I24+I25 -> -645 | J27: =J21+J22+J23+J24+J25 -> -108 | ... L27: =L21+L22+L23+L24+L25 -> 106 | N27: =N26 -> 79 | O27: =O26 -> 76 | P27: =P26 -> 111 | Q27: =Q26 -> -731 | R27: =R26 -> 570 | S27: =S26 -> 156 | T27: =T26 -> -168 | U27: =U26 -> -50
A28: Cash provided by operations | C28: 6059.6 | D28: 5551.2 | E28: 6966.7 | F28: 8122.1 | G28: 6265.2 | H28: 9141.5 | I28: 7387 | J28: 9612 | K28: 9447 | L28: 10551 | N28: 2736 | O28: 2631 | P28: 2428 | Q28: 1998 | R28: 3428 | S28: 2697 | T28: 2412 | U28: 2807
A30: 2. INVESTING ACTIVITIES
A31: Capital expenditures | C31: -1821.1 | D31: -1853.7 | E31: -2741.7 | F31: -2393.7 | G31: -1640.8 | H31: -2040 | I31: -1899 | J31: -2357 | K31: -2775 | L31: -3365 | N31: -794 | O31: -807 | P31: -551 | Q31: -744 | R31: -1011 | S31: -1059 | T31: -682 | U31: -831
A32: Purchases of restaurant (and other) businesses | C32: -109.5 | D32: -77 | E32: -101.7 | F32: -540.9 | G32: -66.1 | H32: -374.2 | I32: -807 | J32: -441 | K32: -669 | L32: -354 | N32: -433 | O32: -74 | P32: -75 | Q32: -56 | R32: -109 | S32: -114 | T32: -79 | U32: -74
A33: Purchases of equity method investments | I33: 0 | J33: 0 | K33: -1837 | L33: 0 | N33: 0 | O33: 0 | P33: 0 | Q33: 0 | R33: 0 | S33: 0
A34: Sales of restaurant (and other) businesses | C34: 975.6 | D34: 974.8 | E34: 530.8 | F34: 340.8 | G34: 76.3 | H34: 196.2 | I34: 446 | J34: 195 | K34: 311 | L34: 346 | N34: 54 | O34: 155 | P34: 49 | Q34: 34 | R34: 102 | S34: 161 | T34: 72 | U34: 137
A35: Proceeds from sale of businesses in China and Hong Kong | C35: 0 | D35: 1597 | E35: 0 | F35: 0
A36: Sales of property | C36: 82.9 | D36: 166.8 | E36: 160.4 | F36: 151.2 | G36: 27.4 | H36: 106.2 | I36: 39 | J36: 95 | K36: 122 | L36: 130 | N36: 10 | O36: 90 | P36: 5 | Q36: 11 | R36: 22 | S36: 92 | T36: 34 | U36: 21
A37: Other investing | C37: -109.5 | D37: -245.9 | E37: -302.9 | F37: -628.5 | G37: 57.4 | H37: -53.9 | I37: -457 | J37: -676 | K37: -498 | L37: -579 | N37: -103 | O37: -106 | P37: -200 | Q37: -114 | R37: -116 | S37: -149 | T37: -122 | U37: -121
A38: Cash provided by (used for) investing activities | C38: -981.6 | D38: 562 | E38: -2455.1 | F38: -3071.1 | G38: -1545.8 | H38: -2165.7 | I38: -2678 | J38: -3185 | K38: -5346 | L38: -3822 | N38: -1266 | O38: -742 | P38: -771 | Q38: -869 | R38: -1112 | S38: -1069 | T38: -777 | U38: -868
A40: 3. FINANCING ACTIVITIES
A41: Net short-term borrowings (repayments) | C41: -286.2 | D41: -1050.3 | E41: 95.9 | F41: 799.2 | G41: -893.1 | H41: 15.1 | I41: 26 | J41: 213 | K41: 326 | L41: 6 | N41: 474 | O41: 193 | P41: -792 | Q41: 597 | R41: -599 | S41: 800 | T41: -791 | U41: 492
A42: Long-term financing issuances | C42: 3779.5 | D42: 4727.5 | E42: 3794.5 | F42: 4499 | G42: 5543 | H42: 1154.4 | I42: 3374 | J42: 5221 | K42: 2380 | L42: 4724 | N42: 0 | O42: 649 | P42: 1498 | Q42: 1403 | R42: 1833 | S42: -10 | T42: 1159 | U42: 0
A43: Long-term financing repayments | C43: -822.9 | D43: -1649.4 | E43: -1759.6 | F43: -2061.9 | G43: -2411.7 | H43: -2240 | I43: -2202 | J43: -2441 | K43: -2777 | L43: -4802 | N43: 0 | O43: -992 | P43: -693 | Q43: -700 | R43: -1251 | S43: -2158 | T43: -1 | U43: -580
A44: Treasury stock purchases | C44: -11171 | D44: -4685.7 | E44: -5207.7 | F44: -4976.2 | G44: -907.8 | H44: -845.5 | I44: -3896 | J44: -3054 | K44: -2824 | L44: -2056 | N44: -469 | O44: -503 | P44: -477 | Q44: -505 | R44: -501 | S44: -573 | T44: -396 | U44: -856
A45: Common stock dividends | C45: -3058.2 | D45: -3089.2 | E45: -3255.9 | F45: -3581.9 | G45: -3752.9 | H45: -3918.6 | I45: -4168 | J45: -4533 | K45: -4870 | L45: -5115 | N45: -1197 | O45: -1268 | P45: -1266 | Q45: -1265 | R45: -1262 | S45: -1323 | T45: -1323 | U45: -1317
A46: Proceeds from stock option exercises | C46: 299.4 | D46: 456.8 | E46: 403.2 | F46: 350.5 | G46: 295.5 | H46: 285.7 | I46: 248 | J46: 260 | K46: 328 | L46: 285 | N46: 132 | O46: 75 | P46: 147 | Q46: 41 | R46: 29 | S46: 69 | T46: 128 | U46: 14
A47: Excess tax benefit on share-based compensation | C47: 0 | D47: 0
A48: Other financing | C48: -3 | D48: -20.5 | E48: -20 | F48: -23.5 | G48: -122 | H48: -46.7 | I48: 38 | J48: -40 | K48: -56 | L48: -167 | N48: -27 | O48: -30 | P48: 40 | Q48: -126 | R48: -35 | S48: -46 | T48: -2 | U48: -140
A49: Cash provided by (used for) financing activities | C49: -11262.4 | D49: -5310.8 | E49: -5949.6 | F49: -4994.8 | G49: -2249 | H49: -5595.6 | I49: -6580 | J49: -4374 | K49: -7495 | L49: -7125 | N49: -1087 | O49: -1878 | P49: -1543 | Q49: -555 | R49: -1786 | S49: -3241 | T49: -1225 | U49: -2387
A51: 4. CASH RECONCILIATION AND SUPPLEMENTAL
A52: Effect of exchange rates on cash and equivalents | C52: -103.7 | D52: 264 | E52: -159.8 | F52: -23.7 | G52: 80.2 | H52: -120.1 | I52: -254 | J52: -58 | K52: -101 | L52: 86 | N52: 46 | O52: -148 | P52: 39 | Q52: 65 | R52: 6 | S52: -24 | T52: -14 | U52: 99
A53: Cash and equivalents increase (decrease) | C53: -6288.1 | D53: 1066.4 | E53: -1597.8 | F53: 32.5 | G53: 2550.6 | H53: 1260.1 | I53: -2126 | J53: 1996 | K53: -3494 | L53: -311 | N53: 429 | O53: -136 | P53: 153 | Q53: 638 | R53: 537 | S53: -1639 | T53: 396 | U53: -348
A54: Change in cash balances of businesses held for sale | B54: Captioned 'Cash balance of businesses held for sale at end of year' in the FY2016 10-K | C54: -174 | D54: 174 | E54: 0 | F54: 0
A55: Cash and equivalents at beginning of period | C55: 7685.5 | D55: 1223.4 | E55: 2463.8 | F55: 866 | G55: 898.5 | H55: 3449.1 | I55: 4709 | J55: 2584 | K55: 4579 | L55: 1085 | N55: 792 | O55: 1221 | P55: 1085 | Q55: 1238 | R55: 1876 | S55: 2413 | T55: 774 | U55: 1170
A56: Cash and equivalents at end of period | C56: 1223.4 | D56: 2463.8 | E56: 866 | F56: 898.5 | G56: 3449.1 | H56: 4709.2 | I56: 2584 | J56: 4579 | K56: 1085 | L56: 774 | N56: 1221 | O56: 1085 | P56: 1238 | Q56: 1876 | R56: 2413 | S56: 774 | T56: 1170 | U56: 822
A58: Interest paid (supplemental) | B58: Supplemental disclosure in 10-K only | C58: 873.5 | D58: 885.2 | E58: 959.6 | F58: 1066.5 | G58: 1136 | H58: 1197.3 | I58: 1184 | J58: 1287 | K58: 1523 | L58: 1555
A59: Income taxes paid, net (supplemental) | B59: Supplemental disclosure in 10-K only; FY2025 moved to the Income Tax note under ASU 2023-09 (table T840 of the FY2025 10-K) | C59: 2387.5 | D59: 2786.3 | E59: 1734.4 | F59: 1589.7 | G59: 1441.9 | H59: 2403.9 | I59: 3024 | J59: 2993 | K59: 2974 | L59: 2688
A61: 5. TIE-OUT CHECKS
A62: Cash Walk Check (annual): begin + net change + held-for-sale change - end (filed integers; rounding +/-1 in FY2022-FY2023) | C62: =C55+C53+C54-C56 -> 0 | D62: =D55+D53+D54-D56 -> 0 | E62: =E55+E53+E54-E56 -> 0 | F62: =F55+F53+F54-F56 -> 0 | G62: =G55+G53+G54-G56 -> 0 | H62: =H55+H53+H54-H56 -> 0 | I62: =I55+I53+I54-I56 -> -1 | J62: =J55+J53+J54-J56 -> 1 | ... L62: =L55+L53+L54-L56 -> 0
A63: Cash Walk Check (quarterly) | N63: =N55+N53-N56 -> 0 | O63: =O55+O53-O56 -> 0 | P63: =P55+P53-P56 -> 0 | Q63: =Q55+Q53-Q56 -> 0 | R63: =R55+R53-R56 -> 0 | S63: =S55+S53-S56 -> 0 | T63: =T55+T53-T56 -> 0 | U63: =U55+U53-U56 -> 0
A64: Operating lines vs CFO (rounding +/-2 expected) | C64: =C15+C16+C17+C18+C19+C20+C27-C28 -> 0 | D64: =D15+D16+D17+D18+D19+D20+D27-D28 -> 0 | E64: =E15+E16+E17+E18+E19+E20+E27-E28 -> 0 | F64: =F15+F16+F17+F18+F19+F20+F27-F28 -> 0 | G64: =G15+G16+G17+G18+G19+G20+G27-G28 -> 0 | H64: =H15+H16+H17+H18+H19+H20+H27-H28 -> 0 | I64: =I15+I16+I17+I18+I19+I20+I27-I28 -> 0 | J64: =J15+J16+J17+J18+J19+J20+J27-J28 -> 0 | ... L64: =L15+L16+L17+L18+L19+L20+L27-L28 -> 0 | N64: =N15+N16+N17+N18+N19+N20+N27-N28 -> 0 | O64: =O15+O16+O17+O18+O19+O20+O27-O28 -> -1 | P64: =P15+P16+P17+P18+P19+P20+P27-P28 -> -1 | Q64: =Q15+Q16+Q17+Q18+Q19+Q20+Q27-Q28 -> 0 | R64: =R15+R16+R17+R18+R19+R20+R27-R28 -> 0 | S64: =S15+S16+S17+S18+S19+S20+S27-S28 -> 0 | T64: =T15+T16+T17+T18+T19+T20+T27-T28 -> 0 | U64: =U15+U16+U17+U18+U19+U20+U27-U28 -> 0
A65: Investing lines vs CFI (rounding +/-2 expected) | C65: =C31+C32+C33+C34+C35+C36+C37-C38 -> 0 | D65: =D31+D32+D33+D34+D35+D36+D37-D38 -> 0 | E65: =E31+E32+E33+E34+E35+E36+E37-E38 -> 0 | F65: =F31+F32+F33+F34+F35+F36+F37-F38 -> 0 | G65: =G31+G32+G33+G34+G35+G36+G37-G38 -> 0 | H65: =H31+H32+H33+H34+H35+H36+H37-H38 -> 0 | I65: =I31+I32+I33+I34+I35+I36+I37-I38 -> 0 | J65: =J31+J32+J33+J34+J35+J36+J37-J38 -> 1 | ... L65: =L31+L32+L33+L34+L35+L36+L37-L38 -> 0 | N65: =N31+N32+N33+N34+N35+N36+N37-N38 -> 0 | O65: =O31+O32+O33+O34+O35+O36+O37-O38 -> 0 | P65: =P31+P32+P33+P34+P35+P36+P37-P38 -> -1 | Q65: =Q31+Q32+Q33+Q34+Q35+Q36+Q37-Q38 -> 0 | R65: =R31+R32+R33+R34+R35+R36+R37-R38 -> 0 | S65: =S31+S32+S33+S34+S35+S36+S37-S38 -> 0 | T65: =T31+T32+T33+T34+T35+T36+T37-T38 -> 0 | U65: =U31+U32+U33+U34+U35+U36+U37-U38 -> 0
A66: Financing lines vs CFF (rounding +/-2 expected) | C66: =C41+C42+C43+C44+C45+C46+C47+C48-C49 -> 0 | D66: =D41+D42+D43+D44+D45+D46+D47+D48-D49 -> 0 | E66: =E41+E42+E43+E44+E45+E46+E47+E48-E49 -> 0 | F66: =F41+F42+F43+F44+F45+F46+F47+F48-F49 -> 0 | G66: =G41+G42+G43+G44+G45+G46+G47+G48-G49 -> 0 | H66: =H41+H42+H43+H44+H45+H46+H47+H48-H49 -> 0 | I66: =I41+I42+I43+I44+I45+I46+I47+I48-I49 -> 0 | J66: =J41+J42+J43+J44+J45+J46+J47+J48-J49 -> 0 | ... L66: =L41+L42+L43+L44+L45+L46+L47+L48-L49 -> 0 | N66: =N41+N42+N43+N44+N45+N46+N47+N48-N49 -> 0 | O66: =O41+O42+O43+O44+O45+O46+O47+O48-O49 -> 2 | P66: =P41+P42+P43+P44+P45+P46+P47+P48-P49 -> 0 | Q66: =Q41+Q42+Q43+Q44+Q45+Q46+Q47+Q48-Q49 -> 0 | R66: =R41+R42+R43+R44+R45+R46+R47+R48-R49 -> 0 | S66: =S41+S42+S43+S44+S45+S46+S47+S48-S49 -> 0 | T66: =T41+T42+T43+T44+T45+T46+T47+T48-T49 -> -1 | U66: =U41+U42+U43+U44+U45+U46+U47+U48-U49 -> 0
A67: CFO + CFI + CFF + FX vs net change (rounding +/-2 expected) | C67: =C28+C38+C49+C52-C53 -> 0 | D67: =D28+D38+D49+D52-D53 -> 0 | E67: =E28+E38+E49+E52-E53 -> 0 | F67: =F28+F38+F49+F52-F53 -> -1.8474111e-13 | G67: =G28+G38+G49+G52-G53 -> 0 | H67: =H28+H38+H49+H52-H53 -> 0 | I67: =I28+I38+I49+I52-I53 -> 1 | J67: =J28+J38+J49+J52-J53 -> -1 | ... L67: =L28+L38+L49+L52-L53 -> 1 | N67: =N28+N38+N49+N52-N53 -> 0 | O67: =O28+O38+O49+O52-O53 -> -1 | P67: =P28+P38+P49+P52-P53 -> 0 | Q67: =Q28+Q38+Q49+Q52-Q53 -> 1 | R67: =R28+R38+R49+R52-R53 -> -1 | S67: =S28+S38+S49+S52-S53 -> 2 | T67: =T28+T38+T49+T52-T53 -> 0 | U67: =U28+U38+U49+U52-U53 -> -1
A68: Ending cash vs balance sheet cash (rounding) | C68: =C56-'Balance Sheet'!C14 -> 0 | D68: =D56-'Balance Sheet'!D14 -> 0 | E68: =E56-'Balance Sheet'!E14 -> 0 | F68: =F56-'Balance Sheet'!F14 -> 0 | G68: =G56-'Balance Sheet'!G14 -> 0 | H68: =H56-'Balance Sheet'!H14 -> 0 | I68: =I56-'Balance Sheet'!I14 -> 0.2 | J68: =J56-'Balance Sheet'!J14 -> 0 | ... L68: =L56-'Balance Sheet'!L14 -> 0 | N68: =N56-'Balance Sheet'!N14 -> 0 | O68: =O56-'Balance Sheet'!O14 -> 0 | P68: =P56-'Balance Sheet'!P14 -> 0 | Q68: =Q56-'Balance Sheet'!Q14 -> 0 | R68: =R56-'Balance Sheet'!R14 -> 0 | S68: =S56-'Balance Sheet'!S14 -> 0 | T68: =T56-'Balance Sheet'!T14 -> 0 | U68: =U56-'Balance Sheet'!U14 -> 0
A70: 6. FREE CASH FLOW ANALYTICS (ANALYST CALCULATION)
A71: Free cash flow (CFO + capital expenditures) | C71: =C28+C31 -> 4238.5 | D71: =D28+D31 -> 3697.5 | E71: =E28+E31 -> 4225 | F71: =F28+F31 -> 5728.4 | G71: =G28+G31 -> 4624.4 | H71: =H28+H31 -> 7101.5 | I71: =I28+I31 -> 5488 | J71: =J28+J31 -> 7255 | ... L71: =L28+L31 -> 7186 | N71: =N28+N31 -> 1942 | O71: =O28+O31 -> 1824 | P71: =P28+P31 -> 1877 | Q71: =Q28+Q31 -> 1254 | R71: =R28+R31 -> 2417 | S71: =S28+S31 -> 1638 | T71: =T28+T31 -> 1730 | U71: =U28+U31 -> 1976
A72: YoY Growth | D72: =IF(N(C71)=0,"",D71/C71-1) -> -0.1276395 | E72: =IF(N(D71)=0,"",E71/D71-1) -> 0.14266396 | F72: =IF(N(E71)=0,"",F71/E71-1) -> 0.35583432 | G72: =IF(N(F71)=0,"",G71/F71-1) -> -0.19272397 | H72: =IF(N(G71)=0,"",H71/G71-1) -> 0.53565868 | I72: =IF(N(H71)=0,"",I71/H71-1) -> -0.22720552 | J72: =IF(N(I71)=0,"",J71/I71-1) -> 0.32197522 | K72: =IF(N(J71)=0,"",K71/J71-1) -> -0.080358374 | L72: =IF(N(K71)=0,"",L71/K71-1) -> 0.077038369 | R72: =IF(N(N71)=0,"",R71/N71-1) -> 0.2445932 | S72: =IF(N(O71)=0,"",S71/O71-1) -> -0.10197368 | T72: =IF(N(P71)=0,"",T71/P71-1) -> -0.078316462 | U72: =IF(N(Q71)=0,"",U71/Q71-1) -> 0.57575758
A73: Capital expenditures % of revenue | C73: =0-C31/'Income Statement'!C17 -> 0.073962611 | D73: =0-D31/'Income Statement'!D17 -> 0.081229952 | E73: =0-E31/'Income Statement'!E17 -> 0.12897323 | F73: =0-F31/'Income Statement'!F17 -> 0.11204153 | G73: =0-G31/'Income Statement'!G17 -> 0.08542363 | H73: =0-H31/'Income Statement'!H17 -> 0.087844326 | I73: =0-I31/'Income Statement'!I17 -> 0.081913471 | J73: =0-J31/'Income Statement'!J17 -> 0.092453126 | ... L73: =0-L31/'Income Statement'!L17 -> 0.12516273 | N73: =0-N31/'Income Statement'!N17 -> 0.11552452 | O73: =0-O31/'Income Statement'!O17 -> 0.12633062 | P73: =0-P31/'Income Statement'!P17 -> 0.092511753 | Q73: =0-Q31/'Income Statement'!Q17 -> 0.10872424 | R73: =0-R31/'Income Statement'!R17 -> 0.14283696 | S73: =0-S31/'Income Statement'!S17 -> 0.15109145 | T73: =0-T31/'Income Statement'!T17 -> 0.10464938 | U73: =0-U31/'Income Statement'!U17 -> 0.11705874
A74: FCF margin | C74: =C71/'Income Statement'!C17 -> 0.1721435 | D74: =D71/'Income Statement'!D17 -> 0.16202608 | E74: =E71/'Income Statement'!E17 -> 0.19874964 | F74: =F71/'Income Statement'!F17 -> 0.26812829 | G74: =G71/'Income Statement'!G17 -> 0.24075636 | H74: =H71/'Income Statement'!H17 -> 0.30579729 | I74: =I71/'Income Statement'!I17 -> 0.23672519 | J74: =J71/'Income Statement'!J17 -> 0.28457676 | ... L74: =L71/'Income Statement'!L17 -> 0.26728659 | N74: =N71/'Income Statement'!N17 -> 0.28255493 | O74: =O71/'Income Statement'!O17 -> 0.28553538 | P74: =P71/'Income Statement'!P17 -> 0.31514439 | Q74: =Q71/'Income Statement'!Q17 -> 0.18325296 | R74: =R71/'Income Statement'!R17 -> 0.34148064 | S74: =S71/'Income Statement'!S17 -> 0.23369953 | T74: =T71/'Income Statement'!T17 -> 0.26545957 | U74: =U71/'Income Statement'!U17 -> 0.27834906
A75: FCF conversion (FCF / net income) | C75: =C71/'Income Statement'!C41 -> 0.90440627 | D75: =D71/'Income Statement'!D41 -> 0.71211217 | E75: =E71/'Income Statement'!E41 -> 0.71316442 | F75: =F71/'Income Statement'!F41 -> 0.95070867 | G75: =G71/'Income Statement'!G41 -> 0.97757108 | H75: =H71/'Income Statement'!H41 -> 0.9411944 | I75: =I71/'Income Statement'!I41 -> 0.88845718 | J75: =J71/'Income Statement'!J41 -> 0.85665368 | ... L75: =L71/'Income Statement'!L41 -> 0.83919187 | N75: =N71/'Income Statement'!N41 -> 0.86119734 | O75: =O71/'Income Statement'!O41 -> 0.9047619 | P75: =P71/'Income Statement'!P41 -> 1.004818 | Q75: =Q71/'Income Statement'!Q41 -> 0.55659121 | R75: =R71/'Income Statement'!R41 -> 1.0610184 | S75: =S71/'Income Statement'!S41 -> 0.75693161 | T75: =T71/'Income Statement'!T41 -> 0.87241553 | U75: =U71/'Income Statement'!U41 -> 0.83657917
A76: Dividends + treasury stock purchases (cash basis) | C76: =0-C45-C44 -> 14229.2 | D76: =0-D45-D44 -> 7774.9 | E76: =0-E45-E44 -> 8463.6 | F76: =0-F45-F44 -> 8558.1 | G76: =0-G45-G44 -> 4660.7 | H76: =0-H45-H44 -> 4764.1 | I76: =0-I45-I44 -> 8064 | J76: =0-J45-J44 -> 7587 | ... L76: =0-L45-L44 -> 7171 | N76: =0-N45-N44 -> 1666 | O76: =0-O45-O44 -> 1771 | P76: =0-P45-P44 -> 1743 | Q76: =0-Q45-Q44 -> 1770 | R76: =0-R45-R44 -> 1763 | S76: =0-S45-S44 -> 1896 | T76: =0-T45-T44 -> 1719 | U76: =0-U45-U44 -> 2173
A77: Shareholder returns % of FCF | C77: =C76/C71 -> 3.3571311 | D77: =D76/D71 -> 2.1027451 | E77: =E76/E71 -> 2.0032189 | F77: =F76/F71 -> 1.4939774 | G77: =G76/G71 -> 1.0078497 | H77: =H76/H71 -> 0.67085827 | I77: =I76/I71 -> 1.4693878 | J77: =J76/J71 -> 1.0457615 | ... L77: =L76/L71 -> 0.99791261 | N77: =N76/N71 -> 0.85787848 | O77: =O76/O71 -> 0.97094298 | P77: =P76/P71 -> 0.92860948 | Q77: =Q76/Q71 -> 1.4114833 | R77: =R76/R71 -> 0.72941663 | S77: =S76/S71 -> 1.1575092 | T77: =T76/T71 -> 0.99364162 | U77: =U76/U71 -> 1.0996964

Sheet Segments
A1: McDonald's Corporation — Segments
A2: $ in millions except per-share data | USD | as of 2026-10-08
C3: FY2016 | D3: FY2017 | E3: FY2018 | F3: FY2019 | G3: FY2020 | H3: FY2021 | I3: FY2022 | J3: FY2023 | K3: FY2024 | L3: FY2025 | M3: · | N3: 3Q2024 | O3: 4Q2024* | P3: 1Q2025 | Q3: 2Q2025 | R3: 3Q2025 | S3: 4Q2025* | T3: 1Q2026 | U3: 2Q2026
C4: 2016-12-31 | D4: 2017-12-31 | E4: 2018-12-31 | F4: 2019-12-31 | G4: 2020-12-31 | H4: 2021-12-31 | I4: 2022-12-31 | J4: 2023-12-31 | K4: 2024-12-31 | L4: 2025-12-31 | N4: 2024-09-30 | O4: 2024-12-31 | P4: 2025-03-31 | Q4: 2025-06-30 | R4: 2025-09-30 | S4: 2025-12-31 | T4: 2026-03-31 | U4: 2026-06-30
A6: CONTENTS
A7: =HYPERLINK("#'Segments'!A18","1. SEGMENT REVENUES (CURRENT REPORTABLE-SEGMENT STRUCTURE, FY2017-FY2025)") -> 1. SEGMENT REVENUES (CURRENT REPORTABLE-SEGMENT STRUCTURE, FY2017-FY2025)
A8: =HYPERLINK("#'Segments'!A29","2. SEGMENT OPERATING INCOME") -> 2. SEGMENT OPERATING INCOME
A9: =HYPERLINK("#'Segments'!A40","3. SEGMENT TOTAL ASSETS") -> 3. SEGMENT TOTAL ASSETS
A10: =HYPERLINK("#'Segments'!A47","4. SEGMENT CAPITAL EXPENDITURES") -> 4. SEGMENT CAPITAL EXPENDITURES
A11: =HYPERLINK("#'Segments'!A54","5. SEGMENT DEPRECIATION AND AMORTIZATION") -> 5. SEGMENT DEPRECIATION AND AMORTIZATION
A12: =HYPERLINK("#'Segments'!A61","6. SEGMENT EXPENSE DETAIL (DISCLOSED FROM FY2022 10-K, ASU 2023-07 PRESENTATION)") -> 6. SEGMENT EXPENSE DETAIL (DISCLOSED FROM FY2022 10-K, ASU 2023-07 PRESENTATION)
A13: =HYPERLINK("#'Segments'!A82","7. REVENUE BY TYPE AND SEGMENT (MD&A REVENUE TABLE)") -> 7. REVENUE BY TYPE AND SEGMENT (MD&A REVENUE TABLE)
A14: =HYPERLINK("#'Segments'!A97","8. RESTAURANT MARGINS BY SEGMENT (MD&A, FY2017-FY2025)") -> 8. RESTAURANT MARGINS BY SEGMENT (MD&A, FY2017-FY2025)
A15: =HYPERLINK("#'Segments'!A123","9. SELLING, GENERAL & ADMINISTRATIVE EXPENSES BY SEGMENT AND INCENTIVE COMPENSATION (MD&A, FY2017-FY2025)") -> 9. SELLING, GENERAL & ADMINISTRATIVE EXPENSES BY SEGMENT AND INCENTIVE COMPENSATION (MD&A, FY2017-FY2025)
A16: =HYPERLINK("#'Segments'!A137","10. SUPERSEDED SEGMENT STRUCTURE (U.S. / INT'L LEAD / HIGH GROWTH / FOUNDATIONAL), FY2016-FY2018 - NOT COMPARABLE WITH BLOCKS ABOVE") -> 10. SUPERSEDED SEGMENT STRUCTURE (U.S. / INT'L LEAD / HIGH GROWTH / FOUNDATIONAL), FY2016-FY2018 - NOT COMPARABLE WITH BLOCKS ABOVE
A18: 1. SEGMENT REVENUES (CURRENT REPORTABLE-SEGMENT STRUCTURE, FY2017-FY2025)
A19: U.S. | D19: 8006.4 | E19: 7798.7 | F19: 8002.8 | G19: 7828.5 | H19: 8865 | I19: 9588 | J19: 10568 | K19: 10631 | L19: 10825
A20: International Operated Markets | D20: 11115.9 | E20: 11578.1 | F20: 11480.1 | G20: 9570.7 | H20: 12219.8 | I20: 11297 | J20: 12382 | K20: 12628 | L20: 13633
A21: International Developmental Licensed Markets & Corporate | D21: 3698.1 | E21: 1881.1 | F21: 1881.5 | G21: 1808.6 | H21: 2138.1 | I21: 2297 | J21: 2543 | K21: 2661 | L21: 2427
A22: Total revenues | D22: =D19+D20+D21 -> 22820.4 | E22: =E19+E20+E21 -> 21257.9 | F22: =F19+F20+F21 -> 21364.4 | G22: =G19+G20+G21 -> 19207.8 | H22: =H19+H20+H21 -> 23222.9 | I22: =I19+I20+I21 -> 23182 | J22: =J19+J20+J21 -> 25493 | K22: =K19+K20+K21 -> 25920 | L22: =L19+L20+L21 -> 26885
A23: U.S. % of total | D23: =D19/D22 -> 0.35084398 | E23: =E19/E22 -> 0.36686126 | F23: =F19/F22 -> 0.37458576 | G23: =G19/G22 -> 0.4075688 | H23: =H19/H22 -> 0.38173527 | I23: =I19/I22 -> 0.41359676 | J23: =J19/J22 -> 0.41454517 | K23: =K19/K22 -> 0.4101466 | L23: =L19/L22 -> 0.40264088
A24: International Operated Markets % of total | D24: =D20/D22 -> 0.48710364 | E24: =E20/E22 -> 0.54464928 | F24: =F20/F22 -> 0.53734718 | G24: =G20/G22 -> 0.49827154 | H24: =H20/H22 -> 0.52619613 | I24: =I20/I22 -> 0.48731775 | J24: =J20/J22 -> 0.48570196 | K24: =K20/K22 -> 0.48719136 | L24: =L20/L22 -> 0.50708574
A25: International Developmental Licensed Markets & Corporate % of total | D25: =D21/D22 -> 0.16205237 | E25: =E21/E22 -> 0.088489456 | F25: =F21/F22 -> 0.088067065 | G25: =G21/G22 -> 0.094159664 | H25: =H21/H22 -> 0.092068605 | I25: =I21/I22 -> 0.099085497 | J25: =J21/J22 -> 0.099752873 | K25: =K21/K22 -> 0.10266204 | L25: =L21/L22 -> 0.090273387
A26: Segment revenue vs IS total revenues (rounding / recast timing) | D26: =D22-'Income Statement'!D17 -> 0 | E26: =E22-'Income Statement'!E17 -> 0 | F26: =F22-'Income Statement'!F17 -> 0 | G26: =G22-'Income Statement'!G17 -> 0 | H26: =H22-'Income Statement'!H17 -> 0 | I26: =I22-'Income Statement'!I17 -> -1 | J26: =J22-'Income Statement'!J17 -> -1 | K26: =K22-'Income Statement'!K17 -> 0 | L26: =L22-'Income Statement'!L17 -> 0
A27: YoY Growth | D27: =IF(N(C22)=0,"",D22/C22-1) | E27: =IF(N(D22)=0,"",E22/D22-1) -> -0.06846944 | F27: =IF(N(E22)=0,"",F22/E22-1) -> 0.0050099022 | G27: =IF(N(F22)=0,"",G22/F22-1) -> -0.10094363 | H27: =IF(N(G22)=0,"",H22/G22-1) -> 0.20903487 | I27: =IF(N(H22)=0,"",I22/H22-1) -> -0.0017611926 | J27: =IF(N(I22)=0,"",J22/I22-1) -> 0.099689414 | K27: =IF(N(J22)=0,"",K22/J22-1) -> 0.016749696 | L27: =IF(N(K22)=0,"",L22/K22-1) -> 0.037229938
A29: 2. SEGMENT OPERATING INCOME
A30: U.S. | D30: 4022.4 | E30: 4015.6 | F30: 4068.7 | G30: 3789.1 | H30: 4754.7 | I30: 5136 | J30: 5694 | K30: 5733 | L30: 5808
A31: International Operated Markets | D31: 4173.6 | E31: 4643.2 | F31: 4789 | G31: 3315.1 | H31: 5130.6 | I31: 3926 | J31: 5831 | K31: 5946 | L31: 6382
A32: International Developmental Licensed Markets & Corporate | D32: 1356.7 | E32: 163.8 | F32: 212.1 | G32: 219.8 | H32: 470.7 | I32: 309 | J32: 121 | K32: 33 | L32: 203
A33: Total operating income | D33: =D30+D31+D32 -> 9552.7 | E33: =E30+E31+E32 -> 8822.6 | F33: =F30+F31+F32 -> 9069.8 | G33: =G30+G31+G32 -> 7324 | H33: =H30+H31+H32 -> 10356 | I33: =I30+I31+I32 -> 9371 | J33: =J30+J31+J32 -> 11646 | K33: =K30+K31+K32 -> 11712 | L33: =L30+L31+L32 -> 12393
A34: U.S. margin | D34: =D30/D19 -> 0.50239808 | E34: =E30/E19 -> 0.51490633 | F34: =F30/F19 -> 0.50840956 | G34: =G30/G19 -> 0.48401354 | H34: =H30/H19 -> 0.53634518 | I34: =I30/I19 -> 0.53566959 | J34: =J30/J19 -> 0.53879637 | K34: =K30/K19 -> 0.53927194 | L34: =L30/L19 -> 0.5365358
A35: International Operated Markets margin | D35: =D31/D20 -> 0.37546218 | E35: =E31/E20 -> 0.40103298 | F35: =F31/F20 -> 0.41715664 | G35: =G31/G20 -> 0.3463801 | H35: =H31/H20 -> 0.41985957 | I35: =I31/I20 -> 0.34752589 | J35: =J31/J20 -> 0.47092554 | K35: =K31/K20 -> 0.47085841 | L35: =L31/L20 -> 0.46812881
A36: International Developmental Licensed Markets & Corporate margin | D36: =D32/D21 -> 0.36686407 | E36: =E32/E21 -> 0.08707671 | F36: =F32/F21 -> 0.11272921 | G36: =G32/G21 -> 0.12153047 | H36: =H32/H21 -> 0.22014873 | I36: =I32/I21 -> 0.13452329 | J36: =J32/J21 -> 0.047581597 | K36: =K32/K21 -> 0.012401353 | L36: =L32/L21 -> 0.083642357
A37: Total margin | D37: =D33/D22 -> 0.41860353 | E37: =E33/E22 -> 0.41502688 | F37: =F33/F22 -> 0.42452866 | G37: =G33/G22 -> 0.38130343 | H37: =H33/H22 -> 0.44593914 | I37: =I33/I22 -> 0.40423605 | J37: =J33/J22 -> 0.45683129 | K37: =K33/K22 -> 0.45185185 | L37: =L33/L22 -> 0.46096336
A38: Segment operating income vs IS operating income | D38: =D33-'Income Statement'!D33 -> 0 | E38: =E33-'Income Statement'!E33 -> 0 | F38: =F33-'Income Statement'!F33 -> 0 | G38: =G33-'Income Statement'!G33 -> 0 | H38: =H33-'Income Statement'!H33 -> 0 | I38: =I33-'Income Statement'!I33 -> 0 | J38: =J33-'Income Statement'!J33 -> -1 | K38: =K33-'Income Statement'!K33 -> 0 | L38: =L33-'Income Statement'!L33 -> 0
A40: 3. SEGMENT TOTAL ASSETS
A41: U.S. | D41: 12648.6 | E41: 14483.8 | F41: 21376.9 | G41: 21010 | H41: 21280.3 | I41: 21793 | J41: 22477 | K41: 22547 | L41: 23008
A42: International Operated Markets | D42: 16254.8 | E42: 17302.3 | F42: 22847.5 | G42: 24744 | H42: 24186.1 | I42: 21979 | J42: 23947 | K42: 23491 | L42: 27487
A43: International Developmental Licensed Markets & Corporate | D43: 4900.3 | E43: 1025.1 | F43: 3286.4 | G43: 6872.8 | H43: 8387.9 | I43: 6663 | J43: 9723 | K43: 9143 | L43: 9020
A44: Total assets | D44: =D41+D42+D43 -> 33803.7 | E44: =E41+E42+E43 -> 32811.2 | F44: =F41+F42+F43 -> 47510.8 | G44: =G41+G42+G43 -> 52626.8 | H44: =H41+H42+H43 -> 53854.3 | I44: =I41+I42+I43 -> 50435 | J44: =J41+J42+J43 -> 56147 | K44: =K41+K42+K43 -> 55181 | L44: =L41+L42+L43 -> 59515
A45: Segment assets vs BS total assets | D45: =D44-'Balance Sheet'!D29 -> 0 | E45: =E44-'Balance Sheet'!E29 -> 0 | F45: =F44-'Balance Sheet'!F29 -> 0 | G45: =G44-'Balance Sheet'!G29 -> 0 | H45: =H44-'Balance Sheet'!H29 -> 0 | I45: =I44-'Balance Sheet'!I29 -> -0.6 | J45: =J44-'Balance Sheet'!J29 -> 0 | K45: =K44-'Balance Sheet'!K29 -> -1 | L45: =L44-'Balance Sheet'!L29 -> 0
A47: 4. SEGMENT CAPITAL EXPENDITURES
A48: U.S. | D48: 861.2 | E48: 1849.8 | F48: 1480.5 | G48: 890.4 | H48: 940.7 | I48: 860 | J48: 963 | K48: 1055 | L48: 1277
A49: International Operated Markets | D49: 808 | E49: 762.4 | F49: 886.6 | G49: 731.5 | H49: 1050.6 | I49: 1015 | J49: 1340 | K49: 1661 | L49: 2048
A50: International Developmental Licensed Markets & Corporate | D50: 184.5 | E50: 129.5 | F50: 26.6 | G50: 18.9 | H50: 48.7 | I50: 24 | J50: 54 | K50: 58 | L50: 40
A51: Total capital expenditures | D51: =D48+D49+D50 -> 1853.7 | E51: =E48+E49+E50 -> 2741.7 | F51: =F48+F49+F50 -> 2393.7 | G51: =G48+G49+G50 -> 1640.8 | H51: =H48+H49+H50 -> 2040 | I51: =I48+I49+I50 -> 1899 | J51: =J48+J49+J50 -> 2357 | K51: =K48+K49+K50 -> 2774 | L51: =L48+L49+L50 -> 3365
A52: Segment capex vs CF capital expenditures (sign flipped) | D52: =D51+'Cash Flow'!D31 -> 0 | E52: =E51+'Cash Flow'!E31 -> 0 | F52: =F51+'Cash Flow'!F31 -> 0 | G52: =G51+'Cash Flow'!G31 -> 0 | H52: =H51+'Cash Flow'!H31 -> 0 | I52: =I51+'Cash Flow'!I31 -> 0 | J52: =J51+'Cash Flow'!J31 -> 0 | K52: =K51+'Cash Flow'!K31 -> -1 | L52: =L51+'Cash Flow'!L31 -> 0
A54: 5. SEGMENT DEPRECIATION AND AMORTIZATION
A55: U.S. | D55: 524.1 | E55: 598.4 | F55: 730.2 | G55: 813.8 | H55: 840.7 | I55: 912 | J55: 969 | K55: 980 | L55: 995
A56: International Operated Markets | D56: 687.1 | E56: 703.9 | F56: 669.3 | G56: 678.5 | H56: 726.4 | I56: 641 | J56: 679 | K56: 730 | L56: 789
A57: International Developmental Licensed Markets & Corporate | D57: 152.2 | E57: 179.7 | F57: 218.4 | G57: 259.1 | H57: 301 | I57: 318 | J57: 330 | K57: 387 | L57: 415
A58: Total depreciation and amortization | D58: =D55+D56+D57 -> 1363.4 | E58: =E55+E56+E57 -> 1482 | F58: =F55+F56+F57 -> 1617.9 | G58: =G55+G56+G57 -> 1751.4 | H58: =H55+H56+H57 -> 1868.1 | I58: =I55+I56+I57 -> 1871 | J58: =J55+J56+J57 -> 1978 | K58: =K55+K56+K57 -> 2097 | L58: =L55+L56+L57 -> 2199
A59: Segment D&A vs CF depreciation and amortization | D59: =D58-'Cash Flow'!D16 -> 0 | E59: =E58-'Cash Flow'!E16 -> 0 | F59: =F58-'Cash Flow'!F16 -> 0 | G59: =G58-'Cash Flow'!G16 -> 0 | H59: =H58-'Cash Flow'!H16 -> 0 | I59: =I58-'Cash Flow'!I16 -> 0 | J59: =J58-'Cash Flow'!J16 -> 0 | K59: =K58-'Cash Flow'!K16 -> 0 | L59: =L58-'Cash Flow'!L16 -> 0
A61: 6. SEGMENT EXPENSE DETAIL (DISCLOSED FROM FY2022 10-K, ASU 2023-07 PRESENTATION)
A62: U.S. | I62: 1244 | J62: 1286 | K62: 1294 | L62: 1293
A63: International Operated Markets | I63: 1086 | J63: 1170 | K63: 1231 | L63: 1324
A64: International Developmental Licensed Markets & Corporate | I64: 20 | J64: 19 | K64: 11 | L64: 1
A65: Total franchised restaurants-occupancy expenses | D65: =D62+D63+D64 -> 0 | E65: =E62+E63+E64 -> 0 | F65: =F62+F63+F64 -> 0 | G65: =G62+G63+G64 -> 0 | H65: =H62+H63+H64 -> 0 | I65: =I62+I63+I64 -> 2350 | J65: =J62+J63+J64 -> 2475 | K65: =K62+K63+K64 -> 2536 | L65: =L62+L63+L64 -> 2618
A67: U.S. | I67: 2406 | J67: 2732 | K67: 2780 | L67: 2755
A68: International Operated Markets | I68: 4266 | J68: 4707 | K68: 4765 | L68: 5101
A69: International Developmental Licensed Markets & Corporate | I69: 709 | J69: 785 | K69: 790 | L69: 413
A70: Total Company-operated restaurant expenses | D70: =D67+D68+D69 -> 0 | E70: =E67+E68+E69 -> 0 | F70: =F67+F68+F69 -> 0 | G70: =G67+G68+G69 -> 0 | H70: =H67+H68+H69 -> 0 | I70: =I67+I68+I69 -> 7381 | J70: =J67+J68+J69 -> 8224 | K70: =K67+K68+K69 -> 8335 | L70: =L67+L68+L69 -> 8269
A72: U.S. | I72: 692 | J72: 661 | K72: 654 | L72: 653
A73: International Operated Markets | I73: 629 | J73: 635 | K73: 631 | L73: 705
A74: International Developmental Licensed Markets & Corporate | I74: 1541 | J74: 1521 | K74: 1573 | L74: 1682
A75: Total selling, general & administrative expenses | D75: =D72+D73+D74 -> 0 | E75: =E72+E73+E74 -> 0 | F75: =F72+F73+F74 -> 0 | G75: =G72+G73+G74 -> 0 | H75: =H72+H73+H74 -> 0 | I75: =I72+I73+I74 -> 2862 | J75: =J72+J73+J74 -> 2817 | K75: =K72+K73+K74 -> 2858 | L75: =L72+L73+L74 -> 3040
A77: U.S. | I77: 110 | J77: 195 | K77: 170 | L77: 316
A78: International Operated Markets | I78: 1390 | J78: 39 | K78: 55 | L78: 122
A79: International Developmental Licensed Markets & Corporate | I79: -282 | J79: 97 | K79: 254 | L79: 128
A80: Total other segment items | D80: =D77+D78+D79 -> 0 | E80: =E77+E78+E79 -> 0 | F80: =F77+F78+F79 -> 0 | G80: =G77+G78+G79 -> 0 | H80: =H77+H78+H79 -> 0 | I80: =I77+I78+I79 -> 1218 | J80: =J77+J78+J79 -> 331 | K80: =K77+K78+K79 -> 479 | L80: =L77+L78+L79 -> 566
A82: 7. REVENUE BY TYPE AND SEGMENT (MD&A REVENUE TABLE)
A83: Franchised revenues: U.S. | D83: 4746 | E83: 5001 | F83: 5353 | G83: 5261 | H83: 6094 | I83: 6585 | J83: 7163 | K83: 7211 | L83: 7371
A84: Franchised revenues: International Operated Markets | D84: 4271 | E84: 4839 | F84: 5064 | G84: 4348 | H84: 5638 | I84: 5985 | J84: 6549 | K84: 6746 | L84: 7279
A85: Franchised revenues: International Developmental Licensed Markets & Corporate | D85: 1084 | E85: 1172 | F85: 1239 | G85: 1117 | H85: 1353 | I85: 1536 | J85: 1724 | K85: 1758 | L85: 1898
A86: Total franchised revenues | D86: =D83+D84+D85 -> 10101 | E86: =E83+E84+E85 -> 11012 | F86: =F83+F84+F85 -> 11656 | G86: =G83+G84+G85 -> 10726 | H86: =H83+H84+H85 -> 13085 | I86: =I83+I84+I85 -> 14106 | J86: =J83+J84+J85 -> 15436 | K86: =K83+K84+K85 -> 15715 | L86: =L83+L84+L85 -> 16548
A87: Company-owned and operated sales: U.S. | D87: 3260 | E87: 2665 | F87: 2490 | G87: 2395 | H87: 2617 | I87: 2836 | J87: 3221 | K87: 3197 | L87: 3115
A88: Company-owned and operated sales: International Operated Markets | D88: 6845 | E88: 6668 | F88: 6334 | G88: 5114 | H88: 6456 | I88: 5179 | J88: 5702 | K88: 5713 | L88: 6131
A89: Company-owned and operated sales: International Developmental Licensed Markets & Corporate | D89: 2614 | E89: 680 | F89: 597 | G89: 630 | H89: 715 | I89: 733 | J89: 819 | K89: 872 | L89: 443
A90: Total company-owned and operated sales | D90: =D87+D88+D89 -> 12719 | E90: =E87+E88+E89 -> 10013 | F90: =F87+F88+F89 -> 9421 | G90: =G87+G88+G89 -> 8139 | H90: =H87+H88+H89 -> 9788 | I90: =I87+I88+I89 -> 8748 | J90: =J87+J88+J89 -> 9742 | K90: =K87+K88+K89 -> 9782 | L90: =L87+L88+L89 -> 9689
A91: Other revenues (total) | E91: 233 | F91: 288 | G91: 343 | H91: 350 | I91: 329 | J91: 316 | K91: 423 | L91: 647
A92: Total revenues | D92: =D86+D90+D91 -> 22820 | E92: =E86+E90+E91 -> 21258 | F92: =F86+F90+F91 -> 21365 | G92: =G86+G90+G91 -> 19208 | H92: =H86+H90+H91 -> 23223 | I92: =I86+I90+I91 -> 23183 | J92: =J86+J90+J91 -> 25494 | K92: =K86+K90+K91 -> 25920 | L92: =L86+L90+L91 -> 26884
A93: Franchised revenues by segment vs IS (rounding) | D93: =D86-'Income Statement'!D12 -> -0.5 | E93: =E86-'Income Statement'!E12 -> -0.5 | F93: =F86-'Income Statement'!F12 -> 0.3 | G93: =G86-'Income Statement'!G12 -> -0.1 | H93: =H86-'Income Statement'!H12 -> -0.4 | I93: =I86-'Income Statement'!I12 -> 0 | J93: =J86-'Income Statement'!J12 -> -1 | K93: =K86-'Income Statement'!K12 -> 0 | L93: =L86-'Income Statement'!L12 -> 0
A94: Company-operated sales by segment vs IS (rounding) | D94: =D90-'Income Statement'!D14 -> 0.1 | E94: =E90-'Income Statement'!E14 -> 0.3 | F94: =F90-'Income Statement'!F14 -> 0.2 | G94: =G90-'Income Statement'!G14 -> -0.2 | H94: =H90-'Income Statement'!H14 -> 0.6 | I94: =I90-'Income Statement'!I14 -> 0 | J94: =J90-'Income Statement'!J14 -> 0 | K94: =K90-'Income Statement'!K14 -> 0 | L94: =L90-'Income Statement'!L14 -> -1
A95: Total revenues vs IS (rounding / FY2017 pre-recast) | D95: =D92-'Income Statement'!D17 -> -0.4 | E95: =E92-'Income Statement'!E17 -> 0.1 | F95: =F92-'Income Statement'!F17 -> 0.6 | G95: =G92-'Income Statement'!G17 -> 0.2 | H95: =H92-'Income Statement'!H17 -> 0.1 | I95: =I92-'Income Statement'!I17 -> 0 | J95: =J92-'Income Statement'!J17 -> 0 | K95: =K92-'Income Statement'!K17 -> 0 | L95: =L92-'Income Statement'!L17 -> -1
A97: 8. RESTAURANT MARGINS BY SEGMENT (MD&A, FY2017-FY2025)
A98: Franchised margins: U.S. | D98: 3913 | E98: 4070 | F98: 4227 | G98: 4097 | H98: 4906 | I98: 5341 | J98: 5877 | K98: 5916 | L98: 6078
A99: YoY Growth | D99: =IF(N(C98)=0,"",D98/C98-1) | E99: =IF(N(D98)=0,"",E98/D98-1) -> 0.040122668 | F99: =IF(N(E98)=0,"",F98/E98-1) -> 0.038574939 | G99: =IF(N(F98)=0,"",G98/F98-1) -> -0.030754672 | H99: =IF(N(G98)=0,"",H98/G98-1) -> 0.19746156 | I99: =IF(N(H98)=0,"",I98/H98-1) -> 0.088666938 | J99: =IF(N(I98)=0,"",J98/I98-1) -> 0.10035574 | K99: =IF(N(J98)=0,"",K98/J98-1) -> 0.0066360388 | L99: =IF(N(K98)=0,"",L98/K98-1) -> 0.027383367
A100: Franchised margins: International Operated Markets | D100: 3365 | E100: 3829 | F100: 4018 | G100: 3329 | H100: 4516 | I100: 4899 | J100: 5379 | K100: 5514 | L100: 5954
A101: YoY Growth | D101: =IF(N(C100)=0,"",D100/C100-1) | E101: =IF(N(D100)=0,"",E100/D100-1) -> 0.13789004 | F101: =IF(N(E100)=0,"",F100/E100-1) -> 0.049360146 | G101: =IF(N(F100)=0,"",G100/F100-1) -> -0.17147835 | H101: =IF(N(G100)=0,"",H100/G100-1) -> 0.35656353 | I101: =IF(N(H100)=0,"",I100/H100-1) -> 0.084809566 | J101: =IF(N(I100)=0,"",J100/I100-1) -> 0.097979179 | K101: =IF(N(J100)=0,"",K100/J100-1) -> 0.025097602 | L101: =IF(N(K100)=0,"",L100/K100-1) -> 0.079796881
A102: Franchised margins: International Developmental Licensed Markets & Corporate | D102: 1034 | E102: 1140 | F102: 1210 | G102: 1093 | H102: 1328 | I102: 1516 | J102: 1706 | K102: 1748 | L102: 1897
A103: YoY Growth | D103: =IF(N(C102)=0,"",D102/C102-1) | E103: =IF(N(D102)=0,"",E102/D102-1) -> 0.10251451 | F103: =IF(N(E102)=0,"",F102/E102-1) -> 0.061403509 | G103: =IF(N(F102)=0,"",G102/F102-1) -> -0.096694215 | H103: =IF(N(G102)=0,"",H102/G102-1) -> 0.21500457 | I103: =IF(N(H102)=0,"",I102/H102-1) -> 0.14156627 | J103: =IF(N(I102)=0,"",J102/I102-1) -> 0.12532982 | K103: =IF(N(J102)=0,"",K102/J102-1) -> 0.024618992 | L103: =IF(N(K102)=0,"",L102/K102-1) -> 0.085240275
A104: Franchised margins: total | D104: 8312 | E104: 9039 | F104: 9455 | G104: 8519 | H104: 10750 | I104: 11756 | J104: 12962 | K104: 13178 | L104: 13930
A105: YoY Growth | D105: =IF(N(C104)=0,"",D104/C104-1) | E105: =IF(N(D104)=0,"",E104/D104-1) -> 0.087463908 | F105: =IF(N(E104)=0,"",F104/E104-1) -> 0.04602279 | G105: =IF(N(F104)=0,"",G104/F104-1) -> -0.098995241 | H105: =IF(N(G104)=0,"",H104/G104-1) -> 0.2618852 | I105: =IF(N(H104)=0,"",I104/H104-1) -> 0.093581395 | J105: =IF(N(I104)=0,"",J104/I104-1) -> 0.10258591 | K105: =IF(N(J104)=0,"",K104/J104-1) -> 0.016664095 | L105: =IF(N(K104)=0,"",L104/K104-1) -> 0.057064805
A107: Company-owned and operated margins: U.S. | B107: International Developmental Licensed Markets & Corporate shown as n/m by the company | D107: 523 | E107: 397 | F107: 388 | G107: 405 | H107: 511 | I107: 429 | J107: 488 | K107: 417 | L107: 360
A108: Company-owned and operated margins: International Operated Markets | B108: International Developmental Licensed Markets & Corporate shown as n/m by the company | D108: 1336 | E108: 1327 | F108: 1266 | G108: 748 | H108: 1208 | I108: 913 | J108: 995 | K108: 948 | L108: 1031
A109: Company-owned and operated margins: total | D109: 2309 | E109: 1747 | F109: 1660 | G109: 1158 | H109: 1740 | I109: 1368 | J109: 1517 | K109: 1447 | L109: 1422
A111: Total restaurant margins: U.S. | B111: Reported from the FY2020 10-K (covers FY2018+) | E111: 4467 | F111: 4615 | G111: 4502 | H111: 5417 | I111: 5770 | J111: 6366 | K111: 6334 | L111: 6438
A112: Total restaurant margins: International Operated Markets | B112: Reported from the FY2020 10-K (covers FY2018+) | E112: 5156 | F112: 5284 | G112: 4077 | H112: 5724 | I112: 5813 | J112: 6374 | K112: 6462 | L112: 6985
A113: Total restaurant margins: total | E113: 10786 | F113: 11115 | G113: 9677 | H113: 12490 | I113: 13124 | J113: 14479 | K113: 14625 | L113: 15351
A115: Franchised margin % of franchised revenues: U.S. | D115: =D98/D83 -> 0.82448378 | E115: =E98/E83 -> 0.81383723 | F115: =F98/F83 -> 0.78965066 | G115: =G98/G83 -> 0.77874929 | H115: =H98/H83 -> 0.80505415 | I115: =I98/I83 -> 0.8110858 | J115: =J98/J83 -> 0.82046629 | K115: =K98/K83 -> 0.82041326 | L115: =L98/L83 -> 0.82458282
...

Sheet Operating Metrics
A1: McDonald's Corporation — Operating Metrics
A2: $ in millions except per-share data | USD | as of 2026-10-08
C3: FY2016 | D3: FY2017 | E3: FY2018 | F3: FY2019 | G3: FY2020 | H3: FY2021 | I3: FY2022 | J3: FY2023 | K3: FY2024 | L3: FY2025 | M3: · | N3: 3Q2024 | O3: 4Q2024* | P3: 1Q2025 | Q3: 2Q2025 | R3: 3Q2025 | S3: 4Q2025* | T3: 1Q2026 | U3: 2Q2026
C4: 2016-12-31 | D4: 2017-12-31 | E4: 2018-12-31 | F4: 2019-12-31 | G4: 2020-12-31 | H4: 2021-12-31 | I4: 2022-12-31 | J4: 2023-12-31 | K4: 2024-12-31 | L4: 2025-12-31 | N4: 2024-09-30 | O4: 2024-12-31 | P4: 2025-03-31 | Q4: 2025-06-30 | R4: 2025-09-30 | S4: 2025-12-31 | T4: 2026-03-31 | U4: 2026-06-30
A6: CONTENTS
A7: =HYPERLINK("#'Operating Metrics'!A22","1. RESTAURANT COUNT (YEAR END)") -> 1. RESTAURANT COUNT (YEAR END)
A8: =HYPERLINK("#'Operating Metrics'!A33","2. FRANCHISED SALES AND SYSTEMWIDE SALES (MD&A; FY2016 TOTAL FROM ITEM 6)") -> 2. FRANCHISED SALES AND SYSTEMWIDE SALES (MD&A; FY2016 TOTAL FROM ITEM 6)
A9: =HYPERLINK("#'Operating Metrics'!A51","3. RESTAURANTS BY SEGMENT AND NET ADDITIONS") -> 3. RESTAURANTS BY SEGMENT AND NET ADDITIONS
A10: =HYPERLINK("#'Operating Metrics'!A64","4. COMPARABLE SALES GROWTH (U.S. / TOTAL FROM FY2016; SEGMENTS FROM FY2018; SEGMENT DEFINITIONS PER FY2019+ 10-KS)") -> 4. COMPARABLE SALES GROWTH (U.S. / TOTAL FROM FY2016; SEGMENTS FROM FY2018; SEGMENT DEFINITIONS PER FY2019+ 10-KS)
A11: =HYPERLINK("#'Operating Metrics'!A75","5. SYSTEMWIDE SALES GROWTH (FY2019-FY2025)") -> 5. SYSTEMWIDE SALES GROWTH (FY2019-FY2025)
A12: =HYPERLINK("#'Operating Metrics'!A85","6. MARKET DATA (ITEM 6 SELECTED FINANCIAL DATA, FY2016-FY2021 ONLY)") -> 6. MARKET DATA (ITEM 6 SELECTED FINANCIAL DATA, FY2016-FY2021 ONLY)
A13: =HYPERLINK("#'Operating Metrics'!A89","7. FRANCHISED REVENUE COMPOSITION") -> 7. FRANCHISED REVENUE COMPOSITION
A14: =HYPERLINK("#'Operating Metrics'!A98","8. SHAREHOLDER RETURNS (MD&A TABLE)") -> 8. SHAREHOLDER RETURNS (MD&A TABLE)
A15: =HYPERLINK("#'Operating Metrics'!A108","9. DEBT STRUCTURE STATISTICS (MD&A TABLE)") -> 9. DEBT STRUCTURE STATISTICS (MD&A TABLE)
A16: =HYPERLINK("#'Operating Metrics'!A115","10. CURRENCY TRANSLATION IMPACT ON REPORTED RESULTS (COMPANY-DISCLOSED BENEFIT / (COST) VS PRIOR-YEAR RATES)") -> 10. CURRENCY TRANSLATION IMPACT ON REPORTED RESULTS (COMPANY-DISCLOSED BENEFIT / (COST) VS PRIOR-YEAR RATES)
A17: =HYPERLINK("#'Operating Metrics'!A126","11. NON-GAAP RECONCILIATION: EARNINGS PER SHARE (ADJUSTMENT LINES AS PRESENTED IN THE FILING SUPPLYING EACH NON-GAAP FIGURE)") -> 11. NON-GAAP RECONCILIATION: EARNINGS PER SHARE (ADJUSTMENT LINES AS PRESENTED IN THE FILING SUPPLYING EACH NON-GAAP FIGURE)
A18: =HYPERLINK("#'Operating Metrics'!A135","12. NON-GAAP RECONCILIATION: NET INCOME (FY2021+)") -> 12. NON-GAAP RECONCILIATION: NET INCOME (FY2021+)
A19: =HYPERLINK("#'Operating Metrics'!A144","13. NON-GAAP RECONCILIATION: OPERATING INCOME (FY2021+)") -> 13. NON-GAAP RECONCILIATION: OPERATING INCOME (FY2021+)
A20: =HYPERLINK("#'Operating Metrics'!A157","14. CAPITAL EXPENDITURES BY PURPOSE (DISCLOSED FY2016-FY2019 ONLY)") -> 14. CAPITAL EXPENDITURES BY PURPOSE (DISCLOSED FY2016-FY2019 ONLY)
A22: 1. RESTAURANT COUNT (YEAR END)
A23: Conventional franchised | D23: 21366 | E23: 21685 | F23: 21837 | G23: 21712 | H23: 21607 | I23: 21720 | J23: 21818 | K23: 22077 | L23: 22570
A24: Developmental licensed | D24: 6945 | E24: 7225 | F24: 7648 | G24: 7663 | H24: 7913 | I24: 8229 | J24: 8684 | K24: 9247 | L24: 9675
A25: Foreign affiliated | D25: 5797 | E25: 6175 | F25: 6574 | G25: 7146 | H25: 7775 | I25: 8220 | J25: 9178 | K25: 10108 | L25: 11072
A26: Total franchised restaurants | B26: FY2016 from Item 6 selected data (no type split) | C26: 31230 | D26: 34108 | E26: 35085 | F26: 36059 | G26: 36521 | H26: 37295 | I26: 38169 | J26: 39680 | K26: 41432 | L26: 43317
A27: Company-owned and operated restaurants | C27: 5669 | D27: 3133 | E27: 2770 | F27: 2636 | G27: 2677 | H27: 2736 | I27: 2106 | J27: 2142 | K27: 2045 | L27: 2039
A28: Total systemwide restaurants | C28: 36899 | D28: 37241 | E28: 37855 | F28: 38695 | G28: 39198 | H28: 40031 | I28: 40275 | J28: 41822 | K28: 43477 | L28: 45356
A29: Conventional franchised 净增 | E29: =E23-D23 -> 319 | F29: =F23-E23 -> 152 | G29: =G23-F23 -> -125 | H29: =H23-G23 -> -105 | I29: =I23-H23 -> 113 | J29: =J23-I23 -> 98 | K29: =K23-J23 -> 259 | L29: =L23-K23 -> 493
A30: Developmental licensed 净增 | E30: =E24-D24 -> 280 | F30: =F24-E24 -> 423 | G30: =G24-F24 -> 15 | H30: =H24-G24 -> 250 | I30: =I24-H24 -> 316 | J30: =J24-I24 -> 455 | K30: =K24-J24 -> 563 | L30: =L24-K24 -> 428
A31: Foreign affiliated 净增 | E31: =E25-D25 -> 378 | F31: =F25-E25 -> 399 | G31: =G25-F25 -> 572 | H31: =H25-G25 -> 629 | I31: =I25-H25 -> 445 | J31: =J25-I25 -> 958 | K31: =K25-J25 -> 930 | L31: =L25-K25 -> 964
A32: Total franchised restaurants 净增 | E32: =E26-D26 -> 977 | F32: =F26-E26 -> 974 | G32: =G26-F26 -> 462 | H32: =H26-G26 -> 774 | I32: =I26-H26 -> 874 | J32: =J26-I26 -> 1511 | K32: =K26-J26 -> 1752 | L32: =L26-K26 -> 1885
A33: Company-owned and operated restaurants 净增 | E33: =E27-D27 -> -363 | F33: =F27-E27 -> -134 | G33: =G27-F27 -> 41 | H33: =H27-G27 -> 59 | I33: =I27-H27 -> -630 | J33: =J27-I27 -> 36 | K33: =K27-J27 -> -97 | L33: =L27-K27 -> -6
A34: Total systemwide restaurants 净增 | E34: =E28-D28 -> 614 | F34: =F28-E28 -> 840 | G34: =G28-F28 -> 503 | H34: =H28-G28 -> 833 | I34: =I28-H28 -> 244 | J34: =J28-I28 -> 1547 | K34: =K28-J28 -> 1655 | L34: =L28-K28 -> 1879
A35: YoY Growth | D35: =IF(N(C28)=0,"",D28/C28-1) -> 0.0092685439 | E35: =IF(N(D28)=0,"",E28/D28-1) -> 0.016487205 | F35: =IF(N(E28)=0,"",F28/E28-1) -> 0.022189935 | G35: =IF(N(F28)=0,"",G28/F28-1) -> 0.012999095 | H35: =IF(N(G28)=0,"",H28/G28-1) -> 0.021251084 | I35: =IF(N(H28)=0,"",I28/H28-1) -> 0.0060952762 | J35: =IF(N(I28)=0,"",J28/I28-1) -> 0.038410925 | K35: =IF(N(J28)=0,"",K28/J28-1) -> 0.039572474 | L35: =IF(N(K28)=0,"",L28/K28-1) -> 0.043218253
A36: Franchised % of systemwide restaurants | C36: =C26/C28 -> 0.8463644 | D36: =D26/D28 -> 0.91587229 | E36: =E26/E28 -> 0.92682605 | F36: =F26/F28 -> 0.9318775 | G36: =G26/G28 -> 0.9317057 | H36: =H26/H28 -> 0.93165297 | I36: =I26/I28 -> 0.9477095 | J36: =J26/J28 -> 0.94878294 | ... L36: =L26/L28 -> 0.95504454
A37: Franchised + company-operated vs systemwide | C37: =C26+C27-C28 -> 0 | D37: =D26+D27-D28 -> 0 | E37: =E26+E27-E28 -> 0 | F37: =F26+F27-F28 -> 0 | G37: =G26+G27-G28 -> 0 | H37: =H26+H27-H28 -> 0 | I37: =I26+I27-I28 -> 0 | J37: =J26+J27-J28 -> 0 | ... L37: =L26+L27-L28 -> 0
A39: 2. FRANCHISED SALES AND SYSTEMWIDE SALES (MD&A; FY2016 TOTAL FROM ITEM 6)
A40: U.S. | D40: 34379 | E40: 35860 | F40: 37923 | G40: 38123 | H40: 43344 | I40: 45898 | J40: 49914 | K40: 50272 | L40: 51946
A41: International Operated Markets | D41: 24386 | E41: 27557 | F41: 28853 | G41: 25446 | H41: 33097 | I41: 34537 | J41: 38264 | K41: 39132 | L41: 42440
A42: International Developmental Licensed Markets | D42: 19426 | E42: 22717 | F42: 23981 | G42: 21609 | H42: 26234 | I42: 29038 | J42: 31573 | K42: 31529 | L42: 35289
A43: Franchised sales: total | B43: FY2016 from Item 6 selected financial data (segment split not comparable); FY2017+ from the MD&A franchised-sales table | C43: 69707 | D43: 78191 | E43: 86134 | F43: 90757 | G43: 85178 | H43: 102675 | I43: 109473 | J43: 119750 | K43: 120933 | L43: 129675
A44: YoY Growth | D44: =IF(N(C43)=0,"",D43/C43-1) -> 0.12170944 | E44: =IF(N(D43)=0,"",E43/D43-1) -> 0.10158458 | F44: =IF(N(E43)=0,"",F43/E43-1) -> 0.053672185 | G44: =IF(N(F43)=0,"",G43/F43-1) -> -0.061471842 | H44: =IF(N(G43)=0,"",H43/G43-1) -> 0.20541689 | I44: =IF(N(H43)=0,"",I43/H43-1) -> 0.066208912 | J44: =IF(N(I43)=0,"",J43/I43-1) -> 0.093877029 | K44: =IF(N(J43)=0,"",K43/J43-1) -> 0.0098789144 | L44: =IF(N(K43)=0,"",L43/K43-1) -> 0.072287961
A45: Conventional franchised | D45: 59151 | E45: 63251 | F45: 66415 | G45: 63297 | H45: 75956 | I45: 80066 | J45: 87809 | K45: 88934 | L45: 93761
A46: Developmental licensed | D46: 12546 | E46: 13519 | F46: 14392 | G46: 11781 | H46: 15151 | I46: 18444 | J46: 20045 | K46: 19736 | L46: 22451
A47: Foreign affiliated | D47: 6494 | E47: 9364 | F47: 9950 | G47: 10100 | H47: 11568 | I47: 10963 | J47: 11896 | K47: 12263 | L47: 13463
A49: Systemwide sales (analyst: franchised sales + Company-owned and operated sales) | B49: Company defines Systemwide sales as sales at all restaurants; this sum is an analyst reconstruction from two disclosed components | C49: =C43+'Income Statement'!C14 -> 85002 | D49: =D43+'Income Statement'!D14 -> 90909.9 | E49: =E43+'Income Statement'!E14 -> 96146.7 | F49: =F43+'Income Statement'!F14 -> 100177.8 | G49: =G43+'Income Statement'!G14 -> 93317.2 | H49: =H43+'Income Statement'!H14 -> 112462.4 | I49: =I43+'Income Statement'!I14 -> 118221 | J49: =J43+'Income Statement'!J14 -> 129492 | ... L49: =L43+'Income Statement'!L14 -> 139365
A50: YoY Growth | D50: =IF(N(C49)=0,"",D49/C49-1) -> 0.069503071 | E50: =IF(N(D49)=0,"",E49/D49-1) -> 0.057604287 | F50: =IF(N(E49)=0,"",F49/E49-1) -> 0.041926556 | G50: =IF(N(F49)=0,"",G49/F49-1) -> -0.068484235 | H50: =IF(N(G49)=0,"",H49/G49-1) -> 0.20516261 | I50: =IF(N(H49)=0,"",I49/H49-1) -> 0.051204669 | J50: =IF(N(I49)=0,"",J49/I49-1) -> 0.095338392 | K50: =IF(N(J49)=0,"",K49/J49-1) -> 0.0094445989 | L50: =IF(N(K49)=0,"",L49/K49-1) -> 0.066174502
A51: Franchised revenues % of franchised sales | C51: ='Income Statement'!C12/C43 -> 0.13380148 | D51: ='Income Statement'!D12/D43 -> 0.12919006 | E51: ='Income Statement'!E12/E43 -> 0.12785311 | F51: ='Income Statement'!F12/F43 -> 0.12842756 | G51: ='Income Statement'!G12/G43 -> 0.12592571 | H51: ='Income Statement'!H12/H43 -> 0.12744485 | I51: ='Income Statement'!I12/I43 -> 0.12885369 | J51: ='Income Statement'!J12/J43 -> 0.12891023 | ... L51: ='Income Statement'!L12/L43 -> 0.12761134
A52: SG&A % of Systemwide sales | C52: ='Income Statement'!C30/C49 -> 0.028052281 | D52: ='Income Statement'!D30/D49 -> 0.024544082 | E52: ='Income Statement'!E30/E49 -> 0.022883781 | F52: ='Income Statement'!F30/F49 -> 0.022254432 | G52: ='Income Statement'!G30/G49 -> 0.027279001 | H52: ='Income Statement'!H30/H49 -> 0.024074713 | I52: ='Income Statement'!I30/I49 -> 0.024208897 | J52: ='Income Statement'!J30/J49 -> 0.02175424 | ... L52: ='Income Statement'!L30/L49 -> 0.021813224
A53: Franchised sales per average franchised restaurant ($mm) | D53: =D43/((D26+C26)/2) -> 2.3934311 | E53: =E43/((E26+D26)/2) -> 2.4896738 | F53: =F43/((F26+E26)/2) -> 2.5513606 | G53: =G43/((G26+F26)/2) -> 2.347148 | H53: =H43/((H26+G26)/2) -> 2.7819172 | I53: =I43/((I26+H26)/2) -> 2.9013304 | J53: =J43/((J26+I26)/2) -> 3.0764685 | K53: =K43/((K26+J26)/2) -> 2.9818769 | L53: =L43/((L26+K26)/2) -> 3.0602131
A54: Franchised sales by segment vs total (rounding) | D54: =D40+D41+D42-D43 -> 0 | E54: =E40+E41+E42-E43 -> 0 | F54: =F40+F41+F42-F43 -> 0 | G54: =G40+G41+G42-G43 -> 0 | H54: =H40+H41+H42-H43 -> 0 | I54: =I40+I41+I42-I43 -> 0 | J54: =J40+J41+J42-J43 -> 1 | K54: =K40+K41+K42-K43 -> 0 | L54: =L40+L41+L42-L43 -> 0
A55: Franchised sales by ownership type vs total (rounding) | D55: =D45+D46+D47-D43 -> 0 | E55: =E45+E46+E47-E43 -> 0 | F55: =F45+F46+F47-F43 -> 0 | G55: =G45+G46+G47-G43 -> 0 | H55: =H45+H46+H47-H43 -> 0 | I55: =I45+I46+I47-I43 -> 0 | J55: =J45+J46+J47-J43 -> 0 | K55: =K45+K46+K47-K43 -> 0 | L55: =L45+L46+L47-L43 -> 0
A57: 3. RESTAURANTS BY SEGMENT AND NET ADDITIONS
A58: U.S. | D58: 14036 | E58: 13914 | F58: 13846 | G58: 13682 | H58: 13438 | I58: 13444 | J58: 13457 | K58: 13557 | L58: 13706
A59: International Operated Markets | D59: 10098 | E59: 10263 | F59: 10465 | G59: 10560 | H59: 10785 | I59: 10103 | J59: 10263 | K59: 10512 | L59: 10845
A60: International Developmental Licensed Markets & Corporate | D60: 13107 | E60: 13678 | F60: 14384 | G60: 14956 | H60: 15808 | I60: 16728 | J60: 18102 | K60: 19408 | L60: 20805
A61: Total systemwide restaurants | D61: 37241 | E61: 37855 | F61: 38695 | G61: 39198 | H61: 40031 | I61: 40275 | J61: 41822 | K61: 43477 | L61: 45356
A62: Conventional franchised 净增 | E62: =E58-D58 -> -122 | F62: =F58-E58 -> -68 | G62: =G58-F58 -> -164 | H62: =H58-G58 -> -244 | I62: =I58-H58 -> 6 | J62: =J58-I58 -> 13 | K62: =K58-J58 -> 100 | L62: =L58-K58 -> 149
A63: Developmental licensed 净增 | E63: =E59-D59 -> 165 | F63: =F59-E59 -> 202 | G63: =G59-F59 -> 95 | H63: =H59-G59 -> 225 | I63: =I59-H59 -> -682 | J63: =J59-I59 -> 160 | K63: =K59-J59 -> 249 | L63: =L59-K59 -> 333
A64: Foreign affiliated 净增 | E64: =E60-D60 -> 571 | F64: =F60-E60 -> 706 | G64: =G60-F60 -> 572 | H64: =H60-G60 -> 852 | I64: =I60-H60 -> 920 | J64: =J60-I60 -> 1374 | K64: =K60-J60 -> 1306 | L64: =L60-K60 -> 1397
A65: Net restaurant additions (year-over-year change) | E65: =E61-D61 -> 614 | F65: =F61-E61 -> 840 | G65: =G61-F61 -> 503 | H65: =H61-G61 -> 833 | I65: =I61-H61 -> 244 | J65: =J61-I61 -> 1547 | K65: =K61-J61 -> 1655 | L65: =L61-K61 -> 1879
A66: Net unit growth % | E66: =E65/D61 -> 0.016487205 | F66: =F65/E61 -> 0.022189935 | G66: =G65/F61 -> 0.012999095 | H66: =H65/G61 -> 0.021251084 | I66: =I65/H61 -> 0.0060952762 | J66: =J65/I61 -> 0.038410925 | K66: =K65/J61 -> 0.039572474 | L66: =L65/K61 -> 0.043218253
A67: Net additions: U.S. | E67: =E58-D58 -> -122 | F67: =F58-E58 -> -68 | G67: =G58-F58 -> -164 | H67: =H58-G58 -> -244 | I67: =I58-H58 -> 6 | J67: =J58-I58 -> 13 | K67: =K58-J58 -> 100 | L67: =L58-K58 -> 149
A68: Net additions: International Operated Markets | E68: =E59-D59 -> 165 | F68: =F59-E59 -> 202 | G68: =G59-F59 -> 95 | H68: =H59-G59 -> 225 | I68: =I59-H59 -> -682 | J68: =J59-I59 -> 160 | K68: =K59-J59 -> 249 | L68: =L59-K59 -> 333
A69: Net additions: International Developmental Licensed Markets & Corporate | E69: =E60-D60 -> 571 | F69: =F60-E60 -> 706 | G69: =G60-F60 -> 572 | H69: =H60-G60 -> 852 | I69: =I60-H60 -> 920 | J69: =J60-I60 -> 1374 | K69: =K60-J60 -> 1306 | L69: =L60-K60 -> 1397
A70: Segment restaurants vs total (rounding) | D70: =D58+D59+D60-D61 -> 0 | E70: =E58+E59+E60-E61 -> 0 | F70: =F58+F59+F60-F61 -> 0 | G70: =G58+G59+G60-G61 -> 0 | H70: =H58+H59+H60-H61 -> 0 | I70: =I58+I59+I60-I61 -> 0 | J70: =J58+J59+J60-J61 -> 0 | K70: =K58+K59+K60-K61 -> 0 | L70: =L58+L59+L60-L61 -> 0
A71: Segment restaurant total vs restaurant-count block | D71: =D61-D28 -> 0 | E71: =E61-E28 -> 0 | F71: =F61-F28 -> 0 | G71: =G61-G28 -> 0 | H71: =H61-H28 -> 0 | I71: =I61-I28 -> 0 | J71: =J61-J28 -> 0 | K71: =K61-K28 -> 0 | L71: =L61-L28 -> 0
A73: 4. COMPARABLE SALES GROWTH (U.S. / TOTAL FROM FY2016; SEGMENTS FROM FY2018; SEGMENT DEFINITIONS PER FY2019+ 10-KS)
A74: Comparable sales growth: U.S. | B74: FY2016-FY2017 from the FY2018/FY2019 10-K comparable-sales and guest-count tables (U.S. and Total Company definitions unchanged) | C74: 0.017 | D74: 0.036 | E74: 0.025 | F74: 0.05 | G74: 0.004 | H74: 0.138 | I74: 0.059 | J74: 0.087 | K74: 0.002 | L74: 0.021
A75: Comparable sales growth: International Operated Markets | E75: 0.061 | F75: 0.061 | G75: -0.15 | H75: 0.216 | I75: 0.133 | J75: 0.092 | K75: -0.002 | L75: 0.032
A76: Comparable sales growth: International Developmental Licensed Markets | E76: 0.056 | F76: 0.072 | G76: -0.105 | H76: 0.166 | I76: 0.16 | J76: 0.094 | K76: -0.003 | L76: 0.046
A77: Comparable sales growth: Total Company | B77: FY2016-FY2017 from the FY2018/FY2019 10-K comparable-sales and guest-count tables (U.S. and Total Company definitions unchanged) | C77: 0.038 | D77: 0.053 | E77: 0.045 | F77: 0.059 | G77: -0.077 | H77: 0.17 | I77: 0.109 | J77: 0.09 | K77: -0.001 | L77: 0.031
A79: Comparable guest counts growth: U.S. | B79: Guest-count tables were discontinued after the FY2019 10-K | C79: -0.021 | D79: 0.01 | E79: -0.022 | F79: -0.019
A80: Comparable guest counts growth: International Operated Markets | B80: Guest-count tables were discontinued after the FY2019 10-K | D80: 0.027 | E80: 0.028 | F80: 0.035
A81: Comparable guest counts growth: International Developmental Licensed Markets & Corporate | B81: Guest-count tables were discontinued after the FY2019 10-K | D81: 0.025 | E81: 0.01 | F81: 0.022
A82: Comparable guest counts growth: Total Company | B82: Guest-count tables were discontinued after the FY2019 10-K | C82: -0.003 | D82: 0.019 | E82: 0.002 | F82: 0.01
A84: 5. SYSTEMWIDE SALES GROWTH (FY2019-FY2025)
A85: Systemwide sales growth, as reported: U.S. | F85: 0.05 | G85: 0 | H85: 0.13 | I85: 0.06 | J85: 0.09 | K85: 0.01 | L85: 0.03
A86: Systemwide sales growth, as reported: International Operated Markets | F86: 0.03 | G86: -0.13 | H86: 0.29 | I86: 0 | J86: 0.11 | K86: 0.02 | L86: 0.08
A87: Systemwide sales growth, as reported: International Developmental Licensed Markets | F87: 0.05 | G87: -0.1 | H87: 0.21 | I87: 0.1 | J87: 0.09 | K87: 0 | L87: 0.1
A88: Systemwide sales growth, as reported: Total Company | F88: 0.04 | G88: -0.07 | H88: 0.21 | I88: 0.05 | J88: 0.1 | K88: 0.01 | L88: 0.07
A89: Systemwide sales growth, excluding currency translation: U.S. | F89: 0.05 | G89: 0 | H89: 0.13 | I89: 0.06 | J89: 0.09 | K89: 0.01 | L89: 0.03
A90: Systemwide sales growth, excluding currency translation: International Operated Markets | F90: 0.08 | G90: -0.14 | H90: 0.24 | I90: 0.11 | J90: 0.1 | K90: 0.02 | L90: 0.05
A91: Systemwide sales growth, excluding currency translation: International Developmental Licensed Markets | F91: 0.1 | G91: -0.08 | H91: 0.2 | I91: 0.21 | J91: 0.12 | K91: 0.04 | L91: 0.1
A92: Systemwide sales growth, excluding currency translation: Total Company | F92: 0.07 | G92: -0.07 | H92: 0.18 | I92: 0.11 | J92: 0.1 | K92: 0.02 | L92: 0.05
A94: 6. MARKET DATA (ITEM 6 SELECTED FINANCIAL DATA, FY2016-FY2021 ONLY)
A95: Market price at year end ($, Item 6) | B95: Item 6 table discontinued after the FY2021 10-K | C95: 121.72 | D95: 172.12 | E95: 177.57 | F95: 197.61 | G95: 214.58 | H95: 268.07
A96: Total debt ($mm, Item 6) | C96: 25956 | D96: 29536 | E96: 31075 | F96: 34177 | G96: 37440 | H96: 35623
A98: 7. FRANCHISED REVENUE COMPOSITION
A99: Rents | C99: 6107.6 | D99: 6496.3 | E99: 7082.2 | F99: 7500.2 | G99: 6844.7 | H99: 8381.1 | I99: 9046 | J99: 9840 | K99: 10017 | L99: 10442
A100: Royalties | C100: 3129.9 | D100: 3518.7 | E100: 3886.3 | F100: 4107.1 | G100: 3831.5 | H100: 4645.1 | I100: 5006 | J100: 5531 | K100: 5606 | L100: 6018
A101: Initial fees | C101: 89.4 | D101: 86.5 | E101: 44 | F101: 48.4 | G101: 49.9 | H101: 59.2 | I101: 54 | J101: 66 | K101: 92 | L101: 88
A102: Revenues from franchised restaurants | C102: =C99+C100+C101 -> 9326.9 | D102: =D99+D100+D101 -> 10101.5 | E102: =E99+E100+E101 -> 11012.5 | F102: =F99+F100+F101 -> 11655.7 | G102: =G99+G100+G101 -> 10726.1 | H102: =H99+H100+H101 -> 13085.4 | I102: =I99+I100+I101 -> 14106 | J102: =J99+J100+J101 -> 15437 | ... L102: =L99+L100+L101 -> 16548
A103: Rents % of franchised revenues | C103: =C99/C102 -> 0.65483708 | D103: =D99/D102 -> 0.64310251 | E103: =E99/E102 -> 0.64310556 | F103: =F99/F102 -> 0.64347916 | G103: =G99/G102 -> 0.63813502 | H103: =H99/H102 -> 0.64049246 | I103: =I99/I102 -> 0.6412874 | J103: =J99/J102 -> 0.63742955 | ... L103: =L99/L102 -> 0.63101281
A104: Royalties % of franchised revenues | C104: =C100/C102 -> 0.33557774 | D104: =D100/D102 -> 0.34833441 | E104: =E100/E102 -> 0.35289898 | F104: =F100/F102 -> 0.35236837 | G104: =G100/G102 -> 0.35721278 | H104: =H100/H102 -> 0.35498342 | I104: =I100/I102 -> 0.35488445 | J104: =J100/J102 -> 0.35829501 | ... L104: =L100/L102 -> 0.36366933
A105: Franchised revenue composition vs IS (rounding) | C105: =C102-'Income Statement'!C12 -> 0 | D105: =D102-'Income Statement'!D12 -> 0 | E105: =E102-'Income Statement'!E12 -> 0 | F105: =F102-'Income Statement'!F12 -> 0 | G105: =G102-'Income Statement'!G12 -> 0 | H105: =H102-'Income Statement'!H12 -> 0 | I105: =I102-'Income Statement'!I12 -> 0 | J105: =J102-'Income Statement'!J12 -> 0 | ... L105: =L102-'Income Statement'!L12 -> 0
A107: 8. SHAREHOLDER RETURNS (MD&A TABLE)
A108: Number of shares repurchased (mm) | C108: 92.3 | D108: 31.4 | E108: 32.2 | F108: 25 | G108: 4.3 | H108: 3.4 | I108: 15.8 | J108: 11.1 | K108: 10.1 | L108: 6.7
A109: Shares outstanding at year end (mm) | C109: 819 | D109: 794 | E109: 767 | F109: 746 | G109: 745 | H109: 745 | I109: 731 | J109: 723 | K109: 715 | L109: 711
A110: Dividends declared per share ($) | C110: 3.61 | D110: 3.83 | E110: 4.19 | F110: 4.73 | G110: 5.04 | H110: 5.25 | I110: 5.66 | J110: 6.23 | K110: 6.78 | L110: 7.17
A111: Treasury stock purchases (in shareholders' equity) | C111: 11142 | D111: 4651 | E111: 5247 | F111: 4980 | G111: 874 | H111: 846 | I111: 3896 | J111: 3105 | K111: 2826 | L111: 2016
...

Sheet Note Schedules
A1: McDonald's Corporation — Note Schedules
A2: $ in millions except per-share data | USD | as of 2026-10-08
C3: FY2016 | D3: FY2017 | E3: FY2018 | F3: FY2019 | G3: FY2020 | H3: FY2021 | I3: FY2022 | J3: FY2023 | K3: FY2024 | L3: FY2025 | M3: · | N3: 3Q2024 | O3: 4Q2024* | P3: 1Q2025 | Q3: 2Q2025 | R3: 3Q2025 | S3: 4Q2025* | T3: 1Q2026 | U3: 2Q2026
C4: 2016-12-31 | D4: 2017-12-31 | E4: 2018-12-31 | F4: 2019-12-31 | G4: 2020-12-31 | H4: 2021-12-31 | I4: 2022-12-31 | J4: 2023-12-31 | K4: 2024-12-31 | L4: 2025-12-31 | N4: 2024-09-30 | O4: 2024-12-31 | P4: 2025-03-31 | Q4: 2025-06-30 | R4: 2025-09-30 | S4: 2025-12-31 | T4: 2026-03-31 | U4: 2026-06-30
A6: CONTENTS
A7: =HYPERLINK("#'Note Schedules'!A17","1. PROPERTY AND EQUIPMENT (NOTE)") -> 1. PROPERTY AND EQUIPMENT (NOTE)
A8: =HYPERLINK("#'Note Schedules'!A29","2. INCOME TAXES (NOTE)") -> 2. INCOME TAXES (NOTE)
A9: =HYPERLINK("#'Note Schedules'!A47","3. OTHER OPERATING (INCOME) EXPENSE, NET - COMPONENTS (MD&A / NOTE)") -> 3. OTHER OPERATING (INCOME) EXPENSE, NET - COMPONENTS (MD&A / NOTE)
A10: =HYPERLINK("#'Note Schedules'!A56","4. NONOPERATING (INCOME) EXPENSE, NET - COMPONENTS (MD&A)") -> 4. NONOPERATING (INCOME) EXPENSE, NET - COMPONENTS (MD&A)
A11: =HYPERLINK("#'Note Schedules'!A64","5. GOODWILL BY SEGMENT (YEAR END; NOTE)") -> 5. GOODWILL BY SEGMENT (YEAR END; NOTE)
A12: =HYPERLINK("#'Note Schedules'!A71","6. DEBT BY CURRENCY, FAIR VALUE AND MATURITY (FINANCING NOTE)") -> 6. DEBT BY CURRENCY, FAIR VALUE AND MATURITY (FINANCING NOTE)
A13: =HYPERLINK("#'Note Schedules'!A92","7. RENT, LEASE COMMITMENTS AND MINIMUM RENT RECEIVABLE") -> 7. RENT, LEASE COMMITMENTS AND MINIMUM RENT RECEIVABLE
A14: =HYPERLINK("#'Note Schedules'!A106","8. FRANCHISE-ARRANGEMENT ASSETS, ADVERTISING AND SHARE-BASED COMPENSATION") -> 8. FRANCHISE-ARRANGEMENT ASSETS, ADVERTISING AND SHARE-BASED COMPENSATION
A15: =HYPERLINK("#'Note Schedules'!A121","9. OTHER OPERATING FACTS DISCLOSED IN TEXT ONLY (APPROXIMATE; NOT TABULATED BY THE COMPANY)") -> 9. OTHER OPERATING FACTS DISCLOSED IN TEXT ONLY (APPROXIMATE; NOT TABULATED BY THE COMPANY)
A17: 1. PROPERTY AND EQUIPMENT (NOTE)
A18: Land | D18: 5662.2 | E18: 5521.4 | F18: 6026.4 | G18: 6349.1 | H18: 6487.6 | I18: 6686.3 | J18: 7081 | K18: 7253 | L18: 8169
A19: Buildings and improvements on owned land | D19: 14776.9 | E19: 15377.4 | F19: 17003.7 | G19: 18218.9 | H19: 18666 | I19: 18934.2 | J19: 20059 | K19: 20487 | L19: 22202
A20: Buildings and improvements on leased land | D20: 12509.2 | E20: 12863.6 | F20: 12605.9 | G20: 13364.5 | H20: 13283.3 | I20: 12492 | J20: 13322 | K20: 13417 | L20: 15506
A21: Equipment, signs and seating | D21: 3165.7 | E21: 2942.6 | F21: 2994.5 | G21: 3119 | H21: 3032 | I21: 2498.6 | J21: 2693 | K21: 2586 | L21: 2954
A22: Other | D22: 512.4 | E22: 488.6 | F22: 420.4 | G22: 425 | H22: 447.7 | I22: 426.5 | J22: 414 | K22: 434 | L22: 459
A23: Property and equipment, at cost | D23: 36626.4 | E23: 37193.6 | F23: 39050.9 | G23: 41476.5 | H23: 41916.6 | I23: 41037.6 | J23: 43570 | K23: 44177 | L23: 49290
A24: Accumulated depreciation and amortization | D24: -14178.1 | E24: -14350.9 | F24: -14890.9 | G24: -16518.3 | H24: -17196 | I24: -17264 | J24: -18662 | K24: -18882 | L24: -21049
A25: Net property and equipment | D25: 22448.3 | E25: 22842.7 | F25: 24160 | G25: 24958.2 | H25: 24720.6 | I25: 23773.6 | J25: 24908 | K25: 25295 | L25: 28241
A26: Components vs cost (rounding) | D26: =D18+D19+D20+D21+D22-D23 -> 0 | E26: =E18+E19+E20+E21+E22-E23 -> 0 | F26: =F18+F19+F20+F21+F22-F23 -> 0 | G26: =G18+G19+G20+G21+G22-G23 -> 0 | H26: =H18+H19+H20+H21+H22-H23 -> 0 | I26: =I18+I19+I20+I21+I22-I23 -> 0 | J26: =J18+J19+J20+J21+J22-J23 -> -1 | K26: =K18+K19+K20+K21+K22-K23 -> 0 | L26: =L18+L19+L20+L21+L22-L23 -> 0
A27: Note net PP&E vs balance sheet (rounding) | D27: =D25-'Balance Sheet'!D28 -> 0 | E27: =E25-'Balance Sheet'!E28 -> 0 | F27: =F25-'Balance Sheet'!F28 -> 0 | G27: =G25-'Balance Sheet'!G28 -> 0 | H27: =H25-'Balance Sheet'!H28 -> 0 | I27: =I25-'Balance Sheet'!I28 -> 0 | J27: =J25-'Balance Sheet'!J28 -> 0 | K27: =K25-'Balance Sheet'!K28 -> 0 | L27: =L25-'Balance Sheet'!L28 -> 0
A29: 2. INCOME TAXES (NOTE)
A30: Income before taxes: U.S. | C30: 2059.4 | D30: 2242 | E30: 2218 | F30: 2159.1 | G30: 1390.4 | H30: 2413.9 | I30: 1846 | J30: 3665 | K30: 3282 | L30: 3291
A31: Income before taxes: outside the U.S. | C31: 4806.6 | D31: 6331.5 | E31: 5598.1 | F31: 5859 | G31: 4750.3 | H31: 6714 | I31: 5980 | J31: 6857 | K31: 7062 | L31: 7606
A32: Income before provision for income taxes | C32: 6866 | D32: 8573.5 | E32: 7816.1 | F32: 8018.1 | G32: 6140.7 | H32: 9127.9 | I32: 7825 | J32: 10522 | K32: 10345 | L32: 10897
A33: Current: U.S. federal | C33: 1046.6 | D33: 2030.8 | E33: 292.9 | F33: 521.8 | G33: 554.1 | H33: 887.6 | I33: 517 | J33: 1340 | K33: 1412 | L33: 1085
A34: Current: U.S. state | C34: 121.3 | D34: 169.8 | E34: 183.9 | F34: 194.7 | G34: 119.1 | H34: 228.1 | I34: 246 | J34: 263 | K34: 269 | L34: 198
A35: Current: outside the U.S. | C35: 1550.2 | D35: 1217 | E35: 1312.4 | F35: 1126.5 | G35: 730.6 | H35: 895.3 | I35: 1230 | J35: 1137 | K35: 1014 | L35: 1177
A36: Current tax provision | C36: 2718.1 | D36: 3417.6 | E36: 1789.2 | F36: 1843 | G36: 1403.8 | H36: 2011 | I36: 1994 | J36: 2740 | K36: 2695 | L36: 2460
A37: Deferred: U.S. federal | C37: -122.1 | D37: -120.1 | E37: 145.7 | F37: 38.5 | G37: 870.3 | H37: -177.4 | I37: -80 | J37: -146 | K37: -76 | L37: -349
A38: Deferred: U.S. state | C38: 14.1 | D38: 12.8 | E38: 18.7 | F38: 20 | G38: 73.3 | H38: -24.1 | I38: -46 | J38: -30 | K38: -20 | L38: -84
A39: Deferred: outside the U.S. | C39: -430.6 | D39: 70.9 | E39: -61.8 | F39: 91.2 | G39: -937.2 | H39: -226.8 | I39: -220 | J39: -511 | K39: -478 | L39: 307
A40: Deferred tax (benefit) provision | C40: -538.6 | D40: -36.4 | E40: 102.6 | F40: 149.7 | G40: 6.4 | H40: -428.3 | I40: -346 | J40: -686 | K40: -574 | L40: -126
A41: Provision for income taxes | C41: 2179.5 | D41: 3381.2 | E41: 1891.8 | F41: 1992.7 | G41: 1410.2 | H41: 1582.7 | I41: 1648 | J41: 2053 | K41: 2121 | L41: 2334
A42: U.S. share of pre-tax income | C42: =C30/C32 -> 0.29994174 | D42: =D30/D32 -> 0.26150347 | E42: =E30/E32 -> 0.28377324 | F42: =F30/F32 -> 0.26927826 | G42: =G30/G32 -> 0.2264237 | H42: =H30/H32 -> 0.26445294 | I42: =I30/I32 -> 0.23591054 | J42: =J30/J32 -> 0.34831781 | ... L42: =L30/L32 -> 0.30200973
A43: Pre-tax split vs IS (rounding) | C43: =C32-'Income Statement'!C39 -> 0 | D43: =D32-'Income Statement'!D39 -> 0 | E43: =E32-'Income Statement'!E39 -> 0 | F43: =F32-'Income Statement'!F39 -> 0 | G43: =G32-'Income Statement'!G39 -> 0 | H43: =H32-'Income Statement'!H39 -> 0 | I43: =I32-'Income Statement'!I39 -> 0 | J43: =J32-'Income Statement'!J39 -> 0 | ... L43: =L32-'Income Statement'!L39 -> 0
A44: Tax provision vs IS (rounding) | C44: =C41-'Income Statement'!C40 -> 0 | D44: =D41-'Income Statement'!D40 -> 0 | E44: =E41-'Income Statement'!E40 -> 0 | F44: =F41-'Income Statement'!F40 -> 0 | G44: =G41-'Income Statement'!G40 -> 0 | H44: =H41-'Income Statement'!H40 -> 0 | I44: =I41-'Income Statement'!I40 -> 0 | J44: =J41-'Income Statement'!J40 -> 0 | ... L44: =L41-'Income Statement'!L40 -> 0
A45: Current + deferred vs total (rounding) | C45: =C36+C40-C41 -> 0 | D45: =D36+D40-D41 -> 0 | E45: =E36+E40-E41 -> 0 | F45: =F36+F40-F41 -> 0 | G45: =G36+G40-G41 -> 0 | H45: =H36+H40-H41 -> 0 | I45: =I36+I40-I41 -> 0 | J45: =J36+J40-J41 -> 1 | ... L45: =L36+L40-L41 -> 0
A47: 3. OTHER OPERATING (INCOME) EXPENSE, NET - COMPONENTS (MD&A / NOTE)
A48: Gains on sales of restaurant businesses | C48: -283.4 | D48: -295.4 | E48: -304.1 | F48: -127.5 | G48: -23.3 | H48: -96.6 | I48: -60 | J48: -103 | K48: -94 | L48: -133
A49: Equity in earnings of unconsolidated affiliates | C49: -54.8 | D49: -183.7 | E49: -151.5 | F49: -153.8 | G49: -117.4 | H49: -176.7 | I49: -113 | J49: -153 | K49: -157 | L49: -190
A50: Asset dispositions and other (income) expense, net | C50: 72.3 | D50: 18.7 | E50: 33.7 | F50: 87.2 | G50: 290.7 | H50: 75.4 | I50: 137 | J50: -7 | K50: 100 | L50: 97
A51: Impairment and other charges (gains), net | C51: 341.6 | D51: -702.8 | E51: 231.7 | F51: 74.3 | G51: -267.5 | H51: -285.4 | I51: 1010 | J51: 362 | K51: 291 | L51: 229
A52: Other operating (income) expense, net | C52: 75.7 | D52: -1163.2 | E52: -190.2 | F52: -119.8 | G52: -117.5 | H52: -483.3 | I52: 974 | J52: 99 | K52: 139 | L52: 2
A53: Components vs total (rounding) | C53: =C48+C49+C50+C51-C52 -> 0 | D53: =D48+D49+D50+D51-D52 -> 0 | E53: =E48+E49+E50+E51-E52 -> 0 | F53: =F48+F49+F50+F51-F52 -> 0 | G53: =G48+G49+G50+G51-G52 -> 0 | H53: =H48+H49+H50+H51-H52 -> 0 | I53: =I48+I49+I50+I51-I52 -> 0 | J53: =J48+J49+J50+J51-J52 -> 0 | ... L53: =L48+L49+L50+L51-L52 -> 1
A54: Total vs income statement (rounding) | C54: =C52-'Income Statement'!C31 -> 0 | D54: =D52-'Income Statement'!D31 -> 0 | E54: =E52-'Income Statement'!E31 -> 0 | F54: =F52-'Income Statement'!F31 -> 0 | G54: =G52-'Income Statement'!G31 -> 0 | H54: =H52-'Income Statement'!H31 -> 0 | I54: =I52-'Income Statement'!I31 -> 0 | J54: =J52-'Income Statement'!J31 -> 0 | ... L54: =L52-'Income Statement'!L31 -> 0
A56: 4. NONOPERATING (INCOME) EXPENSE, NET - COMPONENTS (MD&A)
A57: Interest income | C57: -4 | D57: -7 | E57: -4 | F57: -37 | G57: -18 | H57: -9 | I57: -44 | J57: -187 | K57: -103 | L57: -82
A58: Foreign currency and hedging activity | C58: -24 | D58: 26 | E58: 5 | F58: -48 | G58: -3 | H58: 37 | I58: -134 | J58: -19 | K58: 6 | L58: 40
A59: Other (income) expense | C59: 22 | D59: 39 | E59: 25 | F59: 15 | G59: -14 | H59: 14 | I59: 517 | J59: -31 | K59: -42 | L59: -45
A60: Nonoperating (income) expense, net | C60: -6 | D60: 58 | E60: 26 | F60: -70 | G60: -35 | H60: 42 | I60: 339 | J60: -236 | K60: -139 | L60: -87
A61: Components vs total (rounding) | C61: =C57+C58+C59-C60 -> 0 | D61: =D57+D58+D59-D60 -> 0 | E61: =E57+E58+E59-E60 -> 0 | F61: =F57+F58+F59-F60 -> 0 | G61: =G57+G58+G59-G60 -> 0 | H61: =H57+H58+H59-H60 -> 0 | I61: =I57+I58+I59-I60 -> 0 | J61: =J57+J58+J59-J60 -> -1 | ... L61: =L57+L58+L59-L60 -> 0
A62: Total vs income statement (rounding) | C62: =C60-'Income Statement'!C38 -> 0.3 | D62: =D60-'Income Statement'!D38 -> 0.1 | E62: =E60-'Income Statement'!E38 -> 0.7 | F62: =F60-'Income Statement'!F38 -> 0.2 | G62: =G60-'Income Statement'!G38 -> -0.2 | H62: =H60-'Income Statement'!H38 -> -0.3 | I62: =I60-'Income Statement'!I38 -> 0 | J62: =J60-'Income Statement'!J38 -> 0 | ... L62: =L60-'Income Statement'!L38 -> 0
A64: 5. GOODWILL BY SEGMENT (YEAR END; NOTE)
A65: U.S. | F65: 1615.8 | G65: 1625.5 | H65: 1673.4 | I65: 1815.2 | J65: 1833 | K65: 1851 | L65: 1850
A66: International Operated Markets | F66: 1061.6 | G66: 1147.6 | H66: 1109.1 | I66: 1085.2 | J66: 1207 | K66: 1132 | L66: 1319
A67: International Developmental Licensed Markets & Corporate | F67: 0 | G67: 0 | H67: 0 | I67: 0 | J67: 0 | K67: 162 | L67: 185
A68: Goodwill: consolidated | C68: =C65+C66+C67 -> 0 | D68: =D65+D66+D67 -> 0 | E68: =E65+E66+E67 -> 0 | F68: =F65+F66+F67 -> 2677.4 | G68: =G65+G66+G67 -> 2773.1 | H68: =H65+H66+H67 -> 2782.5 | I68: =I65+I66+I67 -> 2900.4 | J68: =J65+J66+J67 -> 3040 | ... L68: =L65+L66+L67 -> 3354
A69: Goodwill by segment vs balance sheet (rounding) | F69: =F68-'Balance Sheet'!F22 -> 0 | G69: =G68-'Balance Sheet'!G22 -> 0 | H69: =H68-'Balance Sheet'!H22 -> 0 | I69: =I68-'Balance Sheet'!I22 -> 0 | J69: =J68-'Balance Sheet'!J22 -> 0 | K69: =K68-'Balance Sheet'!K22 -> 0 | L69: =L68-'Balance Sheet'!L22 -> 0
A71: 6. DEBT BY CURRENCY, FAIR VALUE AND MATURITY (FINANCING NOTE)
A72: Debt obligations: U.S. dollar | C72: 17139.5 | D72: 17283.3 | E72: 19425.7 | F72: 21389.5 | G72: 23884.5 | H72: 22983.7 | I72: 23132 | J72: 24480 | K72: 25424 | L72: 24531
A73: Debt obligations: Euro | C73: 7298.4 | D73: 9770 | E73: 9333.2 | F73: 9008.8 | G73: 9820.4 | H73: 9023.4 | I73: 9025.3 | J73: 11112 | K73: 9186 | L73: 11486
A74: Debt obligations: British pound sterling | C74: 921.3 | D74: 1008.9 | E74: 952.3 | F74: 1386.3 | G74: 1156.4 | H74: 1145 | I74: 1504.1 | J74: 1585 | K74: 1559 | L74: 1679
A75: Debt obligations: Canadian dollar | C75: 0 | D75: 793.8 | E75: 732 | F75: 768.6 | G75: 784.9 | H75: 790.6 | I75: 737.3 | J75: 755 | K75: 1390 | L75: 1275
A76: Debt obligations: Australian dollar | E76: 0 | F76: 981.6 | G76: 1075.9 | H76: 1015.8 | I76: 953.1 | J76: 953 | K76: 371 | L76: 400
A77: Debt obligations: Japanese yen | C77: 106.9 | D77: 110.9 | E77: 114 | F77: 115.1 | G77: 121.1 | H77: 108.6 | I77: 95.3 | J77: 89 | K77: 79 | L77: 80
A78: Debt obligations: Chinese renminbi | C78: 0
A79: Debt obligations: Other currencies | C79: 599.6 | D79: 696.2 | E79: 659.1 | F79: 655.6 | G79: 717.6 | H79: 695.3 | I79: 695.3 | J79: 593 | K79: 607 | L79: 694
A80: Debt obligations before fair value adjustments and deferred debt costs | C80: =C72+C73+C74+C75+C76+C77+C78+C79 -> 26065.7 | D80: =D72+D73+D74+D75+D76+D77+D78+D79 -> 29663.1 | E80: =E72+E73+E74+E75+E76+E77+E78+E79 -> 31216.3 | F80: =F72+F73+F74+F75+F76+F77+F78+F79 -> 34305.5 | G80: =G72+G73+G74+G75+G76+G77+G78+G79 -> 37560.8 | H80: =H72+H73+H74+H75+H76+H77+H78+H79 -> 35762.4 | I80: =I72+I73+I74+I75+I76+I77+I78+I79 -> 36142.4 | J80: =J72+J73+J74+J75+J76+J77+J78+J79 -> 39567 | ... L80: =L72+L73+L74+L75+L76+L77+L78+L79 -> 40145
A81: Fair value adjustments | C81: 0 | D81: -6.2 | E81: -12 | F81: 12.1 | G81: 35.8 | H81: 4.8 | I81: -91.5 | J81: -62 | K81: -40 | L81: -15
A82: Deferred debt costs | C82: -110 | D82: -120.5 | E82: -129 | F82: -140.4 | G82: -156.2 | H82: -144.5 | I82: -147.4 | J82: -160 | K82: -152 | L82: -157
A83: Total debt obligations (carrying amount) | C83: =C80+C81+C82 -> 25955.7 | D83: =D80+D81+D82 -> 29536.4 | E83: =E80+E81+E82 -> 31075.3 | F83: =F80+F81+F82 -> 34177.2 | G83: =G80+G81+G82 -> 37440.4 | H83: =H80+H81+H82 -> 35622.7 | I83: =I80+I81+I82 -> 35903.5 | J83: =J80+J81+J82 -> 39345 | ... L83: =L80+L81+L82 -> 39973
A84: Non-U.S.-dollar share of debt before adjustments | C84: =1-C72/C80 -> 0.34245004 | D84: =1-D72/D80 -> 0.4173468 | E84: =1-E72/E80 -> 0.37770652 | F84: =1-F72/F80 -> 0.3764994 | G84: =1-G72/G80 -> 0.36411099 | H84: =1-H72/H80 -> 0.35732222 | I84: =1-I72/I80 -> 0.35997609 | J84: =1-J72/J80 -> 0.3813026 | ... L84: =1-L72/L80 -> 0.38894009
A85: Fair value of debt obligations (debt note text; $mm, rounded to $0.1bn) | C85: 27500 | D85: 31800 | E85: 31700 | F85: 37600 | G85: 43700 | H85: 40000 | I85: 33500 | J85: 38400 | K85: 36600 | L85: 38700
A86: Fair value % of carrying amount | C86: =C85/C83 -> 1.0594975 | D86: =D85/D83 -> 1.0766376 | E86: =E85/E83 -> 1.0201028 | F86: =F85/F83 -> 1.1001486 | G86: =G85/G83 -> 1.1671884 | H86: =H85/H83 -> 1.1228795 | I86: =I85/I83 -> 0.93305667 | J86: =J85/J83 -> 0.9759817 | ... L86: =L85/L83 -> 0.9681535
A87: Aggregate debt maturities falling due in the next year | C87: 77.2 | D87: 2024.6 | E87: 0 | F87: 59.1 | G87: 2243.6 | H87: 0 | I87: 0 | J87: 2192.4 | K87: 0 | L87: 0
A88: Total debt obligations vs balance sheet total debt (rounding) | C88: =C83-'Balance Sheet'!C69 -> 0 | D88: =D83-'Balance Sheet'!D69 -> 0 | E88: =E83-'Balance Sheet'!E69 -> 0 | F88: =F83-'Balance Sheet'!F69 -> 0 | G88: =G83-'Balance Sheet'!G69 -> 0 | H88: =H83-'Balance Sheet'!H69 -> 0 | I88: =I83-'Balance Sheet'!I69 -> 0 | J88: =J83-'Balance Sheet'!J69 -> 0 | ... L88: =L83-'Balance Sheet'!L69 -> 0
A89: Aggregate debt maturities: total (sum of the maturity schedule) | C89: 26065.7 | D89: 29663.1 | E89: 31216.3 | F89: 34305.5 | G89: 37560.8 | H89: 35762.4 | I89: 36142.4 | J89: 39567.1 | K89: 38616 | L89: 40145
A90: Maturity schedule total vs debt before adjustments (rounding) | C90: =C80-C89 -> 0 | D90: =D80-D89 -> 0 | E90: =E80-E89 -> 0 | F90: =F80-F89 -> 0 | G90: =G80-G89 -> 0 | H90: =H80-H89 -> 0 | I90: =I80-I89 -> 0 | J90: =J80-J89 -> -0.1 | ... L90: =L80-L89 -> 0
A92: 7. RENT, LEASE COMMITMENTS AND MINIMUM RENT RECEIVABLE
A93: Rent expense: restaurants | B93: FY2016-FY2018 filed on a different (company-operated / franchised) basis; only the total is comparable | D93: 1562.5 | E93: 1433.9 | F93: 1530.4 | G93: 1399.5 | H93: 1486.3 | I93: 1416 | J93: 1491 | K93: 1531 | L93: 1573
A94: Rent expense: other | D94: 82 | E94: 87.9 | F94: 76.4 | G94: 79.8 | H94: 74 | I94: 60 | J94: 51 | K94: 51 | L94: 58
A95: Total rent expense | C95: 1814.2 | D95: 1644.5 | E95: 1521.8 | F95: 1606.8 | G95: 1479.3 | H95: 1560.3 | I95: 1476 | J95: 1542 | K95: 1582 | L95: 1631
A96: Variable lease payments in excess of minimum rents: Company-owned and operated restaurants | B96: Disclosed in the lease note text | C96: 135 | D96: 115.6 | E96: 82.1 | F96: 74.4 | G96: 53.7 | H96: 69.2 | I96: 40 | J96: 56 | K96: 55 | L96: 46
A97: Variable lease payments in excess of minimum rents: franchised restaurants | C97: 186.4 | D97: 204.9 | E97: 200.8 | F97: 200.7 | G97: 136.5 | H97: 160 | I97: 209 | J97: 261 | K97: 271 | L97: 285
A99: Lease payments due in the next 12 months | B99: FY2016-FY2020: operating lease commitments per the contractual-obligations table; FY2021+: total (operating + finance) lease payments from the lease note | C99: 1303 | D99: 1152 | E99: 1145 | F99: 1161.9 | G99: 1230.7 | H99: 1205.7 | I99: 1161.6 | J99: 1204.3 | K99: 1178 | L99: 1321
A100: Total remaining lease payments (undiscounted) | C100: 12253 | D100: 11857 | E100: 12266 | F100: 19022.6 | G100: 20090 | H100: 19445 | I100: 18236.8 | J100: 19879.8 | K100: 18962 | L100: 20626
A101: Minimum rent receivable under franchise arrangements in the next 12 months | C101: 2690 | D101: 2893.5 | E101: 2961.7 | F101: 3008.3 | G101: 3072.8 | H101: 3062.6 | I101: 2970.5 | J101: 2980.3 | K101: 2880 | L101: 3045
A102: Total minimum rent receivable under franchise arrangements (undiscounted) | C102: 31332 | D102: 33761.3 | E102: 34427.3 | F102: 34324 | G102: 34422.2 | H102: 33783.2 | I102: 31780.3 | J102: 31162.4 | K102: 29598 | L102: 31451
A103: Minimum rent receivable / lease payments, next 12 months | C103: =C101/C99 -> 2.0644666 | D103: =D101/D99 -> 2.5117188 | E103: =E101/E99 -> 2.5866376 | F103: =F101/F99 -> 2.5891213 | G103: =G101/G99 -> 2.4967904 | H103: =H101/H99 -> 2.5401012 | I103: =I101/I99 -> 2.5572486 | J103: =J101/J99 -> 2.4747156 | ... L103: =L101/L99 -> 2.3050719
A104: Minimum rent receivable / lease payments, total | C104: =C102/C100 -> 2.5570881 | D104: =D102/D100 -> 2.8473729 | E104: =E102/E100 -> 2.8067259 | F104: =F102/F100 -> 1.8043801 | G104: =G102/G100 -> 1.7133997 | H104: =H102/H100 -> 1.7373721 | I104: =I102/I100 -> 1.7426467 | J104: =J102/J100 -> 1.5675409 | ... L104: =L102/L100 -> 1.524823
A106: 8. FRANCHISE-ARRANGEMENT ASSETS, ADVERTISING AND SHARE-BASED COMPENSATION
A107: Net property and equipment under franchise arrangements | B107: Disclosed in $bn to one decimal; converted to $mm | C107: 16300 | D107: 16500 | E107: 17800 | F107: 19200 | G107: 20000 | H107: 19900 | I107: 20200 | J107: 20100 | K107: 20600 | L107: 22800
A108: of which land | C108: 4500 | D108: 4800 | E108: 4900 | F108: 5400 | G108: 5700 | H108: 5800 | I108: 5900 | J108: 6200 | K108: 6400 | L108: 7100
A109: Accumulated depreciation and amortization on franchise-arrangement property | C109: 7600 | D109: 9800 | E109: 10400 | F109: 10900 | G109: 12100 | H109: 12700 | I109: 14300 | J109: 14500 | K109: 14900 | L109: 16900
A110: Franchise-arrangement property % of balance sheet net PP&E | C110: =C107/'Balance Sheet'!C28 -> 0.76678459 | D110: =D107/'Balance Sheet'!D28 -> 0.73502225 | E110: =E107/'Balance Sheet'!E28 -> 0.77924238 | F110: =F107/'Balance Sheet'!F28 -> 0.79470199 | G110: =G107/'Balance Sheet'!G28 -> 0.80133984 | H110: =H107/'Balance Sheet'!H28 -> 0.80499664 | I110: =I107/'Balance Sheet'!I28 -> 0.849682 | J110: =J107/'Balance Sheet'!J28 -> 0.80696965 | ... L110: =L107/'Balance Sheet'!L28 -> 0.80733685
...

Sheet Derived Metrics
A1: McDonald's Corporation — Derived Metrics
A2: $ in millions except per-share data | USD | as of 2026-10-08
C3: FY2016 | D3: FY2017 | E3: FY2018 | F3: FY2019 | G3: FY2020 | H3: FY2021 | I3: FY2022 | J3: FY2023 | K3: FY2024 | L3: FY2025 | M3: · | N3: 3Q2024 | O3: 4Q2024* | P3: 1Q2025 | Q3: 2Q2025 | R3: 3Q2025 | S3: 4Q2025* | T3: 1Q2026 | U3: 2Q2026
C4: 2016-12-31 | D4: 2017-12-31 | E4: 2018-12-31 | F4: 2019-12-31 | G4: 2020-12-31 | H4: 2021-12-31 | I4: 2022-12-31 | J4: 2023-12-31 | K4: 2024-12-31 | L4: 2025-12-31 | N4: 2024-09-30 | O4: 2024-12-31 | P4: 2025-03-31 | Q4: 2025-06-30 | R4: 2025-09-30 | S4: 2025-12-31 | T4: 2026-03-31 | U4: 2026-06-30
A6: CONTENTS
A7: =HYPERLINK("#'Derived Metrics'!A16","1. PROFITABILITY") -> 1. PROFITABILITY
A8: =HYPERLINK("#'Derived Metrics'!A29","2. RETURNS AND EFFICIENCY (ANNUAL; AVERAGE BALANCES)") -> 2. RETURNS AND EFFICIENCY (ANNUAL; AVERAGE BALANCES)
A9: =HYPERLINK("#'Derived Metrics'!A37","3. LEVERAGE AND COVERAGE (ANNUAL)") -> 3. LEVERAGE AND COVERAGE (ANNUAL)
A10: =HYPERLINK("#'Derived Metrics'!A45","4. LIQUIDITY (PERIOD-END)") -> 4. LIQUIDITY (PERIOD-END)
A11: =HYPERLINK("#'Derived Metrics'!A50","5. CASH CONVERSION AND CAPITAL ALLOCATION") -> 5. CASH CONVERSION AND CAPITAL ALLOCATION
A12: =HYPERLINK("#'Derived Metrics'!A62","6. SYSTEMWIDE AND FRANCHISE ECONOMICS") -> 6. SYSTEMWIDE AND FRANCHISE ECONOMICS
A13: =HYPERLINK("#'Derived Metrics'!A73","7. EARNINGS QUALITY") -> 7. EARNINGS QUALITY
A14: =HYPERLINK("#'Derived Metrics'!A77","8. GROWTH") -> 8. GROWTH
A16: 1. PROFITABILITY
A17: Franchised margin ($mm) | C17: ='Income Statement'!C12-'Income Statement'!C20 -> 7608.5 | D17: ='Income Statement'!D12-'Income Statement'!D20 -> 8311.5 | E17: ='Income Statement'!E12-'Income Statement'!E20 -> 9039.2 | F17: ='Income Statement'!F12-'Income Statement'!F20 -> 9455.1 | G17: ='Income Statement'!G12-'Income Statement'!G20 -> 8518.6 | H17: ='Income Statement'!H12-'Income Statement'!H20 -> 10750.4 | I17: ='Income Statement'!I12-'Income Statement'!I20 -> 11756 | J17: ='Income Statement'!J12-'Income Statement'!J20 -> 12962 | ... L17: ='Income Statement'!L12-'Income Statement'!L20 -> 13930 | N17: ='Income Statement'!N12-'Income Statement'!N20 -> 3448 | O17: ='Income Statement'!O12-'Income Statement'!O20 -> 3325 | P17: ='Income Statement'!P12-'Income Statement'!P20 -> 3041 | Q17: ='Income Statement'!Q12-'Income Statement'!Q20 -> 3559 | R17: ='Income Statement'!R12-'Income Statement'!R20 -> 3697 | S17: ='Income Statement'!S12-'Income Statement'!S20 -> 3632 | T17: ='Income Statement'!T12-'Income Statement'!T20 -> 3331 | U17: ='Income Statement'!U12-'Income Statement'!U20 -> 3713
A18: Franchised margin % of franchised revenues | C18: =('Income Statement'!C12-'Income Statement'!C20)/'Income Statement'!C12 -> 0.81575872 | D18: =('Income Statement'!D12-'Income Statement'!D20)/'Income Statement'!D12 -> 0.82279859 | E18: =('Income Statement'!E12-'Income Statement'!E20)/'Income Statement'!E12 -> 0.82081271 | F18: =('Income Statement'!F12-'Income Statement'!F20)/'Income Statement'!F12 -> 0.81119967 | G18: =('Income Statement'!G12-'Income Statement'!G20)/'Income Statement'!G12 -> 0.7941936 | H18: =('Income Statement'!H12-'Income Statement'!H20)/'Income Statement'!H12 -> 0.82155685 | I18: =('Income Statement'!I12-'Income Statement'!I20)/'Income Statement'!I12 -> 0.83340423 | J18: =('Income Statement'!J12-'Income Statement'!J20)/'Income Statement'!J12 -> 0.83967092 | ... L18: =('Income Statement'!L12-'Income Statement'!L20)/'Income Statement'!L12 -> 0.84179357 | N18: =('Income Statement'!N12-'Income Statement'!N20)/'Income Statement'!N12 -> 0.84220811 | O18: =('Income Statement'!O12-'Income Statement'!O20)/'Income Statement'!O12 -> 0.83985855 | P18: =('Income Statement'!P12-'Income Statement'!P20)/'Income Statement'!P12 -> 0.83064736 | Q18: =('Income Statement'!Q12-'Income Statement'!Q20)/'Income Statement'!Q12 -> 0.8447662 | R18: =('Income Statement'!R12-'Income Statement'!R20)/'Income Statement'!R12 -> 0.84735274 | S18: =('Income Statement'!S12-'Income Statement'!S20)/'Income Statement'!S12 -> 0.84269142 | T18: =('Income Statement'!T12-'Income Statement'!T20)/'Income Statement'!T12 -> 0.83129523 | U18: =('Income Statement'!U12-'Income Statement'!U20)/'Income Statement'!U12 -> 0.84520829
A19: Company-operated margin ($mm) | C19: ='Income Statement'!C14-'Income Statement'!C25 -> 2596.2 | D19: ='Income Statement'!D14-'Income Statement'!D25 -> 2309.3 | E19: ='Income Statement'!E14-'Income Statement'!E25 -> 1746.8 | F19: ='Income Statement'!F14-'Income Statement'!F25 -> 1660.2 | G19: ='Income Statement'!G14-'Income Statement'!G25 -> 1158 | H19: ='Income Statement'!H14-'Income Statement'!H25 -> 1740.1 | I19: ='Income Statement'!I14-'Income Statement'!I25 -> 1368 | J19: ='Income Statement'!J14-'Income Statement'!J25 -> 1518 | ... L19: ='Income Statement'!L14-'Income Statement'!L25 -> 1421 | N19: ='Income Statement'!N14-'Income Statement'!N25 -> 408 | O19: ='Income Statement'!O14-'Income Statement'!O25 -> 333 | P19: ='Income Statement'!P14-'Income Statement'!P25 -> 273 | Q19: ='Income Statement'!Q14-'Income Statement'!Q25 -> 380 | R19: ='Income Statement'!R14-'Income Statement'!R25 -> 391 | S19: ='Income Statement'!S14-'Income Statement'!S25 -> 376 | T19: ='Income Statement'!T14-'Income Statement'!T25 -> 285 | U19: ='Income Statement'!U14-'Income Statement'!U25 -> 387
A20: Company-operated margin % of company-operated sales | C20: =('Income Statement'!C14-'Income Statement'!C25)/'Income Statement'!C14 -> 0.16974175 | D20: =('Income Statement'!D14-'Income Statement'!D25)/'Income Statement'!D14 -> 0.18156444 | E20: =('Income Statement'!E14-'Income Statement'!E25)/'Income Statement'!E14 -> 0.17445844 | F20: =('Income Statement'!F14-'Income Statement'!F25)/'Income Statement'!F14 -> 0.17622707 | G20: =('Income Statement'!G14-'Income Statement'!G25)/'Income Statement'!G14 -> 0.14227443 | H20: =('Income Statement'!H14-'Income Statement'!H25)/'Income Statement'!H14 -> 0.17778981 | I20: =('Income Statement'!I14-'Income Statement'!I25)/'Income Statement'!I14 -> 0.1563786 | J20: =('Income Statement'!J14-'Income Statement'!J25)/'Income Statement'!J14 -> 0.15582016 | ... L20: =('Income Statement'!L14-'Income Statement'!L25)/'Income Statement'!L14 -> 0.14664603 | N20: =('Income Statement'!N14-'Income Statement'!N25)/'Income Statement'!N14 -> 0.15361446 | O20: =('Income Statement'!O14-'Income Statement'!O25)/'Income Statement'!O14 -> 0.14415584 | P20: =('Income Statement'!P14-'Income Statement'!P25)/'Income Statement'!P14 -> 0.12804878 | Q20: =('Income Statement'!Q14-'Income Statement'!Q25)/'Income Statement'!Q14 -> 0.15459723 | R20: =('Income Statement'!R14-'Income Statement'!R25)/'Income Statement'!R14 -> 0.1525556 | S20: =('Income Statement'!S14-'Income Statement'!S25)/'Income Statement'!S14 -> 0.14826498 | T20: =('Income Statement'!T14-'Income Statement'!T25)/'Income Statement'!T14 -> 0.12300388 | U20: =('Income Statement'!U14-'Income Statement'!U25)/'Income Statement'!U14 -> 0.15326733
A21: SG&A % of revenues | C21: ='Income Statement'!C30/'Income Statement'!C17 -> 0.096844679 | D21: ='Income Statement'!D30/'Income Statement'!D17 -> 0.097776551 | E21: ='Income Statement'!E30/'Income Statement'!E17 -> 0.10350035 | F21: ='Income Statement'!F30/'Income Statement'!F17 -> 0.10435116 | G21: ='Income Statement'!G30/'Income Statement'!G17 -> 0.13252949 | H21: ='Income Statement'!H30/'Income Statement'!H17 -> 0.11658751 | I21: ='Income Statement'!I30/'Income Statement'!I17 -> 0.12345253 | J21: ='Income Statement'!J30/'Income Statement'!J17 -> 0.11049659 | ... L21: ='Income Statement'!L30/'Income Statement'!L17 -> 0.1130742 | N21: ='Income Statement'!N30/'Income Statement'!N17 -> 0.094136476 | O21: ='Income Statement'!O30/'Income Statement'!O17 -> 0.12523482 | P21: ='Income Statement'!P30/'Income Statement'!P17 -> 0.11450638 | Q21: ='Income Statement'!Q30/'Income Statement'!Q17 -> 0.10244045 | R21: ='Income Statement'!R30/'Income Statement'!R17 -> 0.11090704 | S21: ='Income Statement'!S30/'Income Statement'!S17 -> 0.12455414 | T21: ='Income Statement'!T30/'Income Statement'!T17 -> 0.11646463 | U21: ='Income Statement'!U30/'Income Statement'!U17 -> 0.11508663
A22: Operating margin | C22: ='Income Statement'!C33/'Income Statement'!C17 -> 0.31453706 | D22: ='Income Statement'!D33/'Income Statement'!D17 -> 0.41860353 | E22: ='Income Statement'!E33/'Income Statement'!E17 -> 0.41502688 | F22: ='Income Statement'!F33/'Income Statement'!F17 -> 0.42452866 | G22: ='Income Statement'!G33/'Income Statement'!G17 -> 0.38130343 | H22: ='Income Statement'!H33/'Income Statement'!H17 -> 0.44593914 | I22: ='Income Statement'!I33/'Income Statement'!I17 -> 0.40421861 | J22: ='Income Statement'!J33/'Income Statement'!J17 -> 0.45685259 | ... L22: ='Income Statement'!L33/'Income Statement'!L17 -> 0.46096336 | N22: ='Income Statement'!N33/'Income Statement'!N17 -> 0.46384403 | O22: ='Income Statement'!O33/'Income Statement'!O17 -> 0.44896681 | P22: ='Income Statement'!P33/'Income Statement'!P17 -> 0.44459369 | Q22: ='Income Statement'!Q33/'Income Statement'!Q17 -> 0.47230747 | R22: ='Income Statement'!R33/'Income Statement'!R17 -> 0.47428652 | S22: ='Income Statement'!S33/'Income Statement'!S17 -> 0.45027821 | T22: ='Income Statement'!T33/'Income Statement'!T17 -> 0.4531226 | U22: ='Income Statement'!U33/'Income Statement'!U17 -> 0.47020707
A23: EBITDA ($mm; operating income + cash-flow D&A) | C23: ='Income Statement'!C33+'Cash Flow'!C16 -> 9261 | D23: ='Income Statement'!D33+'Cash Flow'!D16 -> 10916.1 | E23: ='Income Statement'!E33+'Cash Flow'!E16 -> 10304.6 | F23: ='Income Statement'!F33+'Cash Flow'!F16 -> 10687.7 | G23: ='Income Statement'!G33+'Cash Flow'!G16 -> 9075.4 | H23: ='Income Statement'!H33+'Cash Flow'!H16 -> 12224.1 | I23: ='Income Statement'!I33+'Cash Flow'!I16 -> 11242 | J23: ='Income Statement'!J33+'Cash Flow'!J16 -> 13625 | ... L23: ='Income Statement'!L33+'Cash Flow'!L16 -> 14592 | N23: ='Income Statement'!N33+'Cash Flow'!N16 -> 3720 | O23: ='Income Statement'!O33+'Cash Flow'!O16 -> 3421 | P23: ='Income Statement'!P33+'Cash Flow'!P16 -> 3168 | Q23: ='Income Statement'!Q33+'Cash Flow'!Q16 -> 3776 | R23: ='Income Statement'!R33+'Cash Flow'!R16 -> 3916 | S23: ='Income Statement'!S33+'Cash Flow'!S16 -> 3732 | T23: ='Income Statement'!T33+'Cash Flow'!T16 -> 3519 | U23: ='Income Statement'!U33+'Cash Flow'!U16 -> 3903
A24: EBITDA margin | C24: =C23/'Income Statement'!C17 -> 0.37612857 | D24: =D23/'Income Statement'!D17 -> 0.47834832 | E24: =E23/'Income Statement'!E17 -> 0.48474214 | F24: =F23/'Income Statement'!F17 -> 0.50025744 | G24: =G23/'Income Statement'!G17 -> 0.47248514 | H24: =H23/'Income Statement'!H17 -> 0.52638129 | I24: =I23/'Income Statement'!I17 -> 0.4849243 | J24: =J23/'Income Statement'!J17 -> 0.53443948 | ... L24: =L23/'Income Statement'!L17 -> 0.54275618 | N24: =N23/'Income Statement'!N17 -> 0.54124836 | O24: =O23/'Income Statement'!O17 -> 0.53553538 | P24: =P23/'Income Statement'!P17 -> 0.5319006 | Q24: =Q23/'Income Statement'!Q17 -> 0.55180476 | R24: =R23/'Income Statement'!R17 -> 0.55326363 | S24: =S23/'Income Statement'!S17 -> 0.53245827 | T24: =T23/'Income Statement'!T17 -> 0.53997238 | U24: =U23/'Income Statement'!U17 -> 0.54979575
A25: Net margin | C25: ='Income Statement'!C41/'Income Statement'!C17 -> 0.19033868 | D25: ='Income Statement'!D41/'Income Statement'!D17 -> 0.22752888 | E25: ='Income Statement'!E41/'Income Statement'!E17 -> 0.27868698 | F25: ='Income Statement'!F41/'Income Statement'!F17 -> 0.28202992 | G25: ='Income Statement'!G41/'Income Statement'!G17 -> 0.24628016 | H25: ='Income Statement'!H41/'Income Statement'!H17 -> 0.32490344 | I25: ='Income Statement'!I41/'Income Statement'!I17 -> 0.26644524 | J25: ='Income Statement'!J41/'Income Statement'!J17 -> 0.33219581 | ... L25: ='Income Statement'!L41/'Income Statement'!L17 -> 0.31850474 | N25: ='Income Statement'!N41/'Income Statement'!N17 -> 0.32809545 | O25: ='Income Statement'!O41/'Income Statement'!O17 -> 0.31559173 | P25: ='Income Statement'!P41/'Income Statement'!P17 -> 0.31363331 | Q25: ='Income Statement'!Q41/'Income Statement'!Q17 -> 0.32924156 | R25: ='Income Statement'!R41/'Income Statement'!R17 -> 0.32184233 | S25: ='Income Statement'!S41/'Income Statement'!S17 -> 0.3087459 | T25: ='Income Statement'!T41/'Income Statement'!T17 -> 0.30428111 | U25: ='Income Statement'!U41/'Income Statement'!U17 -> 0.33272292
A26: Effective tax rate | C26: ='Income Statement'!C40/'Income Statement'!C39 -> 0.31743373 | D26: ='Income Statement'!D40/'Income Statement'!D39 -> 0.39437803 | E26: ='Income Statement'!E40/'Income Statement'!E39 -> 0.24203887 | F26: ='Income Statement'!F40/'Income Statement'!F39 -> 0.24852521 | G26: ='Income Statement'!G40/'Income Statement'!G39 -> 0.22964809 | H26: ='Income Statement'!H40/'Income Statement'!H39 -> 0.17339147 | I26: ='Income Statement'!I40/'Income Statement'!I39 -> 0.21060703 | J26: ='Income Statement'!J40/'Income Statement'!J39 -> 0.195115 | ... L26: ='Income Statement'!L40/'Income Statement'!L39 -> 0.21418739 | N26: ='Income Statement'!N40/'Income Statement'!N39 -> 0.20682378 | O26: ='Income Statement'!O40/'Income Statement'!O39 -> 0.20527975 | P26: ='Income Statement'!P40/'Income Statement'!P39 -> 0.19785408 | Q26: ='Income Statement'!Q40/'Income Statement'!Q39 -> 0.21251311 | R26: ='Income Statement'!R40/'Income Statement'!R39 -> 0.22753476 | S26: ='Income Statement'!S40/'Income Statement'!S39 -> 0.21545158 | T26: ='Income Statement'!T40/'Income Statement'!T39 -> 0.21990559 | U26: ='Income Statement'!U40/'Income Statement'!U39 -> 0.19550409
A27: D&A % of revenues | C27: ='Cash Flow'!C16/'Income Statement'!C17 -> 0.06159151 | D27: ='Cash Flow'!D16/'Income Statement'!D17 -> 0.05974479 | E27: ='Cash Flow'!E16/'Income Statement'!E17 -> 0.069715259 | F27: ='Cash Flow'!F16/'Income Statement'!F17 -> 0.075728782 | G27: ='Cash Flow'!G16/'Income Statement'!G17 -> 0.091181707 | H27: ='Cash Flow'!H16/'Income Statement'!H17 -> 0.08044215 | I27: ='Cash Flow'!I16/'Income Statement'!I17 -> 0.08070569 | J27: ='Cash Flow'!J16/'Income Statement'!J17 -> 0.077586883 | ... L27: ='Cash Flow'!L16/'Income Statement'!L17 -> 0.081792821 | N27: ='Cash Flow'!N16/'Income Statement'!N17 -> 0.077404336 | O27: ='Cash Flow'!O16/'Income Statement'!O17 -> 0.086568566 | P27: ='Cash Flow'!P16/'Income Statement'!P17 -> 0.087306917 | Q27: ='Cash Flow'!Q16/'Income Statement'!Q17 -> 0.079497297 | R27: ='Cash Flow'!R16/'Income Statement'!R17 -> 0.078977112 | S27: ='Cash Flow'!S16/'Income Statement'!S17 -> 0.082180054 | T27: ='Cash Flow'!T16/'Income Statement'!T17 -> 0.086849778 | U27: ='Cash Flow'!U16/'Income Statement'!U17 -> 0.079588674
A29: 2. RETURNS AND EFFICIENCY (ANNUAL; AVERAGE BALANCES)
A30: Average total assets ($mm) | D30: =('Balance Sheet'!D29+'Balance Sheet'!C29)/2 -> 32413.8 | E30: =('Balance Sheet'!E29+'Balance Sheet'!D29)/2 -> 33307.45 | F30: =('Balance Sheet'!F29+'Balance Sheet'!E29)/2 -> 40161 | G30: =('Balance Sheet'!G29+'Balance Sheet'!F29)/2 -> 50068.8 | H30: =('Balance Sheet'!H29+'Balance Sheet'!G29)/2 -> 53240.55 | I30: =('Balance Sheet'!I29+'Balance Sheet'!H29)/2 -> 52144.95 | J30: =('Balance Sheet'!J29+'Balance Sheet'!I29)/2 -> 53291.3 | K30: =('Balance Sheet'!K29+'Balance Sheet'!J29)/2 -> 55664.5 | L30: =('Balance Sheet'!L29+'Balance Sheet'!K29)/2 -> 57348.5
A31: Return on average assets | D31: ='Income Statement'!D41/D30 -> 0.16018794 | E31: ='Income Statement'!E41/E30 -> 0.17786711 | F31: ='Income Statement'!F41/F30 -> 0.15003112 | G31: ='Income Statement'!G41/G30 -> 0.094479996 | H31: ='Income Statement'!H41/H30 -> 0.14171905 | I31: ='Income Statement'!I41/I30 -> 0.11845826 | J31: ='Income Statement'!J41/J30 -> 0.158919 | K31: ='Income Statement'!K41/K30 -> 0.14772431 | L31: ='Income Statement'!L41/L30 -> 0.14931515
A32: Asset turnover | D32: ='Income Statement'!D17/D30 -> 0.70403347 | E32: ='Income Statement'!E17/E30 -> 0.63823259 | F32: ='Income Statement'!F17/F30 -> 0.53196883 | G32: ='Income Statement'!G17/G30 -> 0.38362813 | H32: ='Income Statement'!H17/H30 -> 0.43618821 | I32: ='Income Statement'!I17/I30 -> 0.44458764 | J32: ='Income Statement'!J17/J30 -> 0.47838953 | K32: ='Income Statement'!K17/K30 -> 0.46564687 | L32: ='Income Statement'!L17/L30 -> 0.4688004
A33: Invested capital ($mm; total debt + lease liabilities + equity) | B33: Lease liabilities are on the balance sheet from FY2019 (ASC 842); FY2016-FY2018 exclude them - not comparable across the FY2018/FY2019 boundary | C33: ='Balance Sheet'!C69+'Balance Sheet'!C70+'Balance Sheet'!C56 -> 23751.4 | D33: ='Balance Sheet'!D69+'Balance Sheet'!D70+'Balance Sheet'!D56 -> 26268.4 | E33: ='Balance Sheet'!E69+'Balance Sheet'!E70+'Balance Sheet'!E56 -> 24816.9 | F33: ='Balance Sheet'!F69+'Balance Sheet'!F70+'Balance Sheet'!F56 -> 39345.7 | G33: ='Balance Sheet'!G69+'Balance Sheet'!G70+'Balance Sheet'!G56 -> 43638.3 | H33: ='Balance Sheet'!H69+'Balance Sheet'!H70+'Balance Sheet'!H56 -> 44748.1 | I33: ='Balance Sheet'!I69+'Balance Sheet'!I70+'Balance Sheet'!I56 -> 42695.6 | J33: ='Balance Sheet'!J69+'Balance Sheet'!J70+'Balance Sheet'!J56 -> 48384 | ... L33: ='Balance Sheet'!L69+'Balance Sheet'!L70+'Balance Sheet'!L56 -> 53023
A34: NOPAT ($mm; operating income x (1 - effective tax rate)) | C34: ='Income Statement'!C33*(1-C26) -> 5286.1345 | D34: ='Income Statement'!D33*(1-D26) -> 5785.325 | E34: ='Income Statement'!E33*(1-E26) -> 6687.1879 | F34: ='Income Statement'!F33*(1-F26) -> 6815.726 | G34: ='Income Statement'!G33*(1-G26) -> 5642.0574 | H34: ='Income Statement'!H33*(1-H26) -> 8560.3579 | I34: ='Income Statement'!I33*(1-I26) -> 7397.4015 | J34: ='Income Statement'!J33*(1-J26) -> 9374.4956 | ... L34: ='Income Statement'!L33*(1-L26) -> 9738.5757
A35: ROIC (NOPAT / average invested capital) | D35: =D34/((D33+C33)/2) -> 0.2313214 | E35: =E34/((E33+D33)/2) -> 0.26180478 | F35: =F34/((F33+E33)/2) -> 0.21245168 | G35: =G34/((G33+F33)/2) -> 0.1359794 | H35: =H34/((H33+G33)/2) -> 0.19370306 | I35: =I34/((I33+H33)/2) -> 0.16919233 | J35: =J34/((J33+I33)/2) -> 0.20585281 | K35: =K34/((K33+J33)/2) -> 0.19289851 | L35: =L34/((L33+K33)/2) -> 0.19251143
A37: 3. LEVERAGE AND COVERAGE (ANNUAL)
A38: Net debt / EBITDA | C38: ='Balance Sheet'!C71/C23 -> 2.6705863 | D38: ='Balance Sheet'!D71/D23 -> 2.4800616 | E38: ='Balance Sheet'!E71/E23 -> 2.9316325 | F38: ='Balance Sheet'!F71/F23 -> 3.1137382 | G38: ='Balance Sheet'!G71/G23 -> 3.7454327 | H38: ='Balance Sheet'!H71/H23 -> 2.5288978 | I38: ='Balance Sheet'!I71/I23 -> 2.9638587 | J38: ='Balance Sheet'!J71/J23 -> 2.551633 | ... L38: ='Balance Sheet'!L71/L23 -> 2.686335
A39: Net debt incl. lease liabilities / EBITDA (EBITDA not rent-adjusted) | B39: Lease liabilities on balance sheet from FY2019 only (ASC 842) | C39: ='Balance Sheet'!C72/C23 -> 2.6705863 | D39: ='Balance Sheet'!D72/D23 -> 2.4800616 | E39: ='Balance Sheet'!E72/E23 -> 2.9316325 | F39: ='Balance Sheet'!F72/F23 -> 4.3655323 | G39: ='Balance Sheet'!G72/G23 -> 5.2905767 | H39: ='Balance Sheet'!H72/H23 -> 3.6517944 | I39: ='Balance Sheet'!I72/I23 -> 4.1020459 | J39: ='Balance Sheet'!J72/J23 -> 3.5605138 | ... L39: ='Balance Sheet'!L72/L23 -> 3.7033991
A40: Total debt / total assets | C40: ='Balance Sheet'!C69/'Balance Sheet'!C29 -> 0.83663563 | D40: ='Balance Sheet'!D69/'Balance Sheet'!D29 -> 0.87376234 | E40: ='Balance Sheet'!E69/'Balance Sheet'!E29 -> 0.94709428 | F40: ='Balance Sheet'!F69/'Balance Sheet'!F29 -> 0.71935644 | G40: ='Balance Sheet'!G69/'Balance Sheet'!G29 -> 0.7114322 | H40: ='Balance Sheet'!H69/'Balance Sheet'!H29 -> 0.66146436 | I40: ='Balance Sheet'!I69/'Balance Sheet'!I29 -> 0.7118682 | J40: ='Balance Sheet'!J69/'Balance Sheet'!J29 -> 0.70074982 | ... L40: ='Balance Sheet'!L69/'Balance Sheet'!L29 -> 0.6716458
A41: Interest coverage (operating income / interest expense) | C41: ='Income Statement'!C33/'Income Statement'!C37 -> 8.7528255 | D41: ='Income Statement'!D33/'Income Statement'!D37 -> 10.368718 | E41: ='Income Statement'!E33/'Income Statement'!E37 -> 8.9916429 | F41: ='Income Statement'!F33/'Income Statement'!F37 -> 8.0843212 | G41: ='Income Statement'!G33/'Income Statement'!G37 -> 6.0126426 | H41: ='Income Statement'!H33/'Income Statement'!H37 -> 8.7333446 | I41: ='Income Statement'!I33/'Income Statement'!I37 -> 7.7638774 | J41: ='Income Statement'!J33/'Income Statement'!J37 -> 8.5576782 | ... L41: ='Income Statement'!L33/'Income Statement'!L37 -> 7.8337547
A42: EBITDA / interest expense | C42: =C23/'Income Statement'!C37 -> 10.466772 | D42: =D23/'Income Statement'!D37 -> 11.848584 | E42: =E23/'Income Statement'!E37 -> 10.502038 | F42: =F23/'Income Statement'!F37 -> 9.5264284 | G42: =G23/'Income Statement'!G37 -> 7.4504556 | H42: =H23/'Income Statement'!H37 -> 10.308737 | I42: =I23/'Income Statement'!I37 -> 9.3140017 | J42: =J23/'Income Statement'!J37 -> 10.011021 | ... L42: =L23/'Income Statement'!L37 -> 9.2237674
A43: Cash provided by operations / total debt | C43: ='Cash Flow'!C28/'Balance Sheet'!C69 -> 0.23345932 | D43: ='Cash Flow'!D28/'Balance Sheet'!D69 -> 0.18794437 | E43: ='Cash Flow'!E28/'Balance Sheet'!E69 -> 0.2241877 | F43: ='Cash Flow'!F28/'Balance Sheet'!F69 -> 0.23764674 | G43: ='Cash Flow'!G28/'Balance Sheet'!G69 -> 0.16733796 | H43: ='Cash Flow'!H28/'Balance Sheet'!H69 -> 0.25662008 | I43: ='Cash Flow'!I28/'Balance Sheet'!I69 -> 0.20574596 | J43: ='Cash Flow'!J28/'Balance Sheet'!J69 -> 0.24430042 | ... L43: ='Cash Flow'!L28/'Balance Sheet'!L69 -> 0.26395317
A45: 4. LIQUIDITY (PERIOD-END)
A46: Current ratio | C46: ='Balance Sheet'!C19/'Balance Sheet'!C41 -> 1.397976 | D46: ='Balance Sheet'!D19/'Balance Sheet'!D41 -> 1.8429392 | E46: ='Balance Sheet'!E19/'Balance Sheet'!E41 -> 1.3631074 | F46: ='Balance Sheet'!F19/'Balance Sheet'!F41 -> 0.98257387 | G46: ='Balance Sheet'!G19/'Balance Sheet'!G41 -> 1.0100304 | H46: ='Balance Sheet'!H19/'Balance Sheet'!H41 -> 1.7782338 | I46: ='Balance Sheet'!I19/'Balance Sheet'!I41 -> 1.4266327 | J46: ='Balance Sheet'!J19/'Balance Sheet'!J41 -> 1.1643097 | ... L46: ='Balance Sheet'!L19/'Balance Sheet'!L41 -> 0.95459757 | N46: ='Balance Sheet'!N19/'Balance Sheet'!N41 -> 0.77869372 | O46: ='Balance Sheet'!O19/'Balance Sheet'!O41 -> 1.1911422 | P46: ='Balance Sheet'!P19/'Balance Sheet'!P41 -> 1.1813872 | Q46: ='Balance Sheet'!Q19/'Balance Sheet'!Q41 -> 1.3031643 | R46: ='Balance Sheet'!R19/'Balance Sheet'!R41 -> 1 | S46: ='Balance Sheet'!S19/'Balance Sheet'!S41 -> 0.95459757 | T46: ='Balance Sheet'!T19/'Balance Sheet'!T41 -> 1.1357935 | U46: ='Balance Sheet'!U19/'Balance Sheet'!U41 -> 1.0813838
A47: Quick ratio ((cash + receivables) / current liabilities) | C47: =('Balance Sheet'!C14+'Balance Sheet'!C15)/'Balance Sheet'!C41 -> 0.77775856 | D47: =('Balance Sheet'!D14+'Balance Sheet'!D15)/'Balance Sheet'!D41 -> 1.5360133 | E47: =('Balance Sheet'!E14+'Balance Sheet'!E15)/'Balance Sheet'!E41 -> 1.1123255 | F47: =('Balance Sheet'!F14+'Balance Sheet'!F15)/'Balance Sheet'!F41 -> 0.86238608 | G47: =('Balance Sheet'!G14+'Balance Sheet'!G15)/'Balance Sheet'!G41 -> 0.89940465 | H47: =('Balance Sheet'!H14+'Balance Sheet'!H15)/'Balance Sheet'!H41 -> 1.6372139 | I47: =('Balance Sheet'!I14+'Balance Sheet'!I15)/'Balance Sheet'!I41 -> 1.2358433 | J47: =('Balance Sheet'!J14+'Balance Sheet'!J15)/'Balance Sheet'!J41 -> 1.0303251 | ... L47: =('Balance Sheet'!L14+'Balance Sheet'!L15)/'Balance Sheet'!L41 -> 0.74294886 | N47: =('Balance Sheet'!N14+'Balance Sheet'!N15)/'Balance Sheet'!N41 -> 0.58354471 | O47: =('Balance Sheet'!O14+'Balance Sheet'!O15)/'Balance Sheet'!O41 -> 0.8982129 | P47: =('Balance Sheet'!P14+'Balance Sheet'!P15)/'Balance Sheet'!P41 -> 0.90444112 | Q47: =('Balance Sheet'!Q14+'Balance Sheet'!Q15)/'Balance Sheet'!Q41 -> 1.0297813 | R47: =('Balance Sheet'!R14+'Balance Sheet'!R15)/'Balance Sheet'!R41 -> 0.8211877 | S47: =('Balance Sheet'!S14+'Balance Sheet'!S15)/'Balance Sheet'!S41 -> 0.74294886 | T47: =('Balance Sheet'!T14+'Balance Sheet'!T15)/'Balance Sheet'!T41 -> 0.86878919 | U47: =('Balance Sheet'!U14+'Balance Sheet'!U15)/'Balance Sheet'!U41 -> 0.82304629
A48: Cash ratio | C48: ='Balance Sheet'!C14/'Balance Sheet'!C41 -> 0.35273765 | D48: ='Balance Sheet'!D14/'Balance Sheet'!D41 -> 0.85234899 | E48: ='Balance Sheet'!E14/'Balance Sheet'!E41 -> 0.29123928 | F48: ='Balance Sheet'!F14/'Balance Sheet'!F41 -> 0.24813587 | G48: ='Balance Sheet'!G14/'Balance Sheet'!G41 -> 0.55799845 | H48: ='Balance Sheet'!H14/'Balance Sheet'!H41 -> 1.1714428 | I48: ='Balance Sheet'!I14/'Balance Sheet'!I41 -> 0.67957182 | J48: ='Balance Sheet'!J14/'Balance Sheet'!J41 -> 0.66759003 | ... L48: ='Balance Sheet'!L14/'Balance Sheet'!L41 -> 0.17748223 | N48: ='Balance Sheet'!N14/'Balance Sheet'!N41 -> 0.19356373 | O48: ='Balance Sheet'!O14/'Balance Sheet'!O41 -> 0.28101528 | P48: ='Balance Sheet'!P14/'Balance Sheet'!P41 -> 0.30888224 | Q48: ='Balance Sheet'!Q14/'Balance Sheet'!Q41 -> 0.43648208 | R48: ='Balance Sheet'!R14/'Balance Sheet'!R41 -> 0.39694029 | S48: ='Balance Sheet'!S14/'Balance Sheet'!S41 -> 0.17748223 | T48: ='Balance Sheet'!T14/'Balance Sheet'!T41 -> 0.28219971 | U48: ='Balance Sheet'!U14/'Balance Sheet'!U41 -> 0.20457939
A50: 5. CASH CONVERSION AND CAPITAL ALLOCATION
A51: CFO margin | C51: ='Cash Flow'!C28/'Income Statement'!C17 -> 0.24610611 | D51: ='Cash Flow'!D28/'Income Statement'!D17 -> 0.24325603 | E51: ='Cash Flow'!E28/'Income Statement'!E17 -> 0.32772287 | F51: ='Cash Flow'!F28/'Income Statement'!F17 -> 0.38016982 | G51: ='Cash Flow'!G28/'Income Statement'!G17 -> 0.32617999 | H51: ='Cash Flow'!H28/'Income Statement'!H17 -> 0.39364162 | I51: ='Cash Flow'!I28/'Income Statement'!I17 -> 0.31863866 | J51: ='Cash Flow'!J28/'Income Statement'!J17 -> 0.37702989 | ... L51: ='Cash Flow'!L28/'Income Statement'!L17 -> 0.39244932 | N51: ='Cash Flow'!N28/'Income Statement'!N17 -> 0.39807944 | O51: ='Cash Flow'!O28/'Income Statement'!O17 -> 0.411866 | P51: ='Cash Flow'!P28/'Income Statement'!P17 -> 0.40765615 | Q51: ='Cash Flow'!Q28/'Income Statement'!Q17 -> 0.2919772 | R51: ='Cash Flow'!R28/'Income Statement'!R17 -> 0.4843176 | S51: ='Cash Flow'!S28/'Income Statement'!S17 -> 0.38479098 | T51: ='Cash Flow'!T28/'Income Statement'!T17 -> 0.37010895 | U51: ='Cash Flow'!U28/'Income Statement'!U17 -> 0.3954078
A52: CFO / EBITDA | C52: ='Cash Flow'!C28/C23 -> 0.65431379 | D52: ='Cash Flow'!D28/D23 -> 0.50853327 | E52: ='Cash Flow'!E28/E23 -> 0.6760767 | F52: ='Cash Flow'!F28/F23 -> 0.75994835 | G52: ='Cash Flow'!G28/G23 -> 0.69034974 | H52: ='Cash Flow'!H28/H23 -> 0.74782602 | I52: ='Cash Flow'!I28/I23 -> 0.65708949 | J52: ='Cash Flow'!J28/J23 -> 0.70546789 | ... L52: ='Cash Flow'!L28/L23 -> 0.72306743 | N52: ='Cash Flow'!N28/N23 -> 0.73548387 | O52: ='Cash Flow'!O28/O23 -> 0.76907337 | P52: ='Cash Flow'!P28/P23 -> 0.76641414 | Q52: ='Cash Flow'!Q28/Q23 -> 0.52913136 | R52: ='Cash Flow'!R28/R23 -> 0.87538304 | S52: ='Cash Flow'!S28/S23 -> 0.72266881 | T52: ='Cash Flow'!T28/T23 -> 0.68542199 | U52: ='Cash Flow'!U28/U23 -> 0.71919037
A53: Capital expenditures % of revenues | C53: =0-'Cash Flow'!C31/'Income Statement'!C17 -> 0.073962611 | D53: =0-'Cash Flow'!D31/'Income Statement'!D17 -> 0.081229952 | E53: =0-'Cash Flow'!E31/'Income Statement'!E17 -> 0.12897323 | F53: =0-'Cash Flow'!F31/'Income Statement'!F17 -> 0.11204153 | G53: =0-'Cash Flow'!G31/'Income Statement'!G17 -> 0.08542363 | H53: =0-'Cash Flow'!H31/'Income Statement'!H17 -> 0.087844326 | I53: =0-'Cash Flow'!I31/'Income Statement'!I17 -> 0.081913471 | J53: =0-'Cash Flow'!J31/'Income Statement'!J17 -> 0.092453126 | ... L53: =0-'Cash Flow'!L31/'Income Statement'!L17 -> 0.12516273 | N53: =0-'Cash Flow'!N31/'Income Statement'!N17 -> 0.11552452 | O53: =0-'Cash Flow'!O31/'Income Statement'!O17 -> 0.12633062 | P53: =0-'Cash Flow'!P31/'Income Statement'!P17 -> 0.092511753 | Q53: =0-'Cash Flow'!Q31/'Income Statement'!Q17 -> 0.10872424 | R53: =0-'Cash Flow'!R31/'Income Statement'!R17 -> 0.14283696 | S53: =0-'Cash Flow'!S31/'Income Statement'!S17 -> 0.15109145 | T53: =0-'Cash Flow'!T31/'Income Statement'!T17 -> 0.10464938 | U53: =0-'Cash Flow'!U31/'Income Statement'!U17 -> 0.11705874
A54: Capital expenditures / D&A | C54: =0-'Cash Flow'!C31/'Cash Flow'!C16 -> 1.2008572 | D54: =0-'Cash Flow'!D31/'Cash Flow'!D16 -> 1.3596157 | E54: =0-'Cash Flow'!E31/'Cash Flow'!E16 -> 1.85 | F54: =0-'Cash Flow'!F31/'Cash Flow'!F16 -> 1.4795105 | G54: =0-'Cash Flow'!G31/'Cash Flow'!G16 -> 0.93685052 | H54: =0-'Cash Flow'!H31/'Cash Flow'!H16 -> 1.0920186 | I54: =0-'Cash Flow'!I31/'Cash Flow'!I16 -> 1.0149653 | J54: =0-'Cash Flow'!J31/'Cash Flow'!J16 -> 1.1916077 | ... L54: =0-'Cash Flow'!L31/'Cash Flow'!L16 -> 1.530241 | N54: =0-'Cash Flow'!N31/'Cash Flow'!N16 -> 1.4924812 | O54: =0-'Cash Flow'!O31/'Cash Flow'!O16 -> 1.4593128 | P54: =0-'Cash Flow'!P31/'Cash Flow'!P16 -> 1.0596154 | Q54: =0-'Cash Flow'!Q31/'Cash Flow'!Q16 -> 1.3676471 | R54: =0-'Cash Flow'!R31/'Cash Flow'!R16 -> 1.8085868 | S54: =0-'Cash Flow'!S31/'Cash Flow'!S16 -> 1.8385417 | T54: =0-'Cash Flow'!T31/'Cash Flow'!T16 -> 1.204947 | U54: =0-'Cash Flow'!U31/'Cash Flow'!U16 -> 1.4707965
A55: FCF margin | C55: ='Cash Flow'!C71/'Income Statement'!C17 -> 0.1721435 | D55: ='Cash Flow'!D71/'Income Statement'!D17 -> 0.16202608 | E55: ='Cash Flow'!E71/'Income Statement'!E17 -> 0.19874964 | F55: ='Cash Flow'!F71/'Income Statement'!F17 -> 0.26812829 | G55: ='Cash Flow'!G71/'Income Statement'!G17 -> 0.24075636 | H55: ='Cash Flow'!H71/'Income Statement'!H17 -> 0.30579729 | I55: ='Cash Flow'!I71/'Income Statement'!I17 -> 0.23672519 | J55: ='Cash Flow'!J71/'Income Statement'!J17 -> 0.28457676 | ... L55: ='Cash Flow'!L71/'Income Statement'!L17 -> 0.26728659 | N55: ='Cash Flow'!N71/'Income Statement'!N17 -> 0.28255493 | O55: ='Cash Flow'!O71/'Income Statement'!O17 -> 0.28553538 | P55: ='Cash Flow'!P71/'Income Statement'!P17 -> 0.31514439 | Q55: ='Cash Flow'!Q71/'Income Statement'!Q17 -> 0.18325296 | R55: ='Cash Flow'!R71/'Income Statement'!R17 -> 0.34148064 | S55: ='Cash Flow'!S71/'Income Statement'!S17 -> 0.23369953 | T55: ='Cash Flow'!T71/'Income Statement'!T17 -> 0.26545957 | U55: ='Cash Flow'!U71/'Income Statement'!U17 -> 0.27834906
A56: FCF / net income | C56: ='Cash Flow'!C71/'Income Statement'!C41 -> 0.90440627 | D56: ='Cash Flow'!D71/'Income Statement'!D41 -> 0.71211217 | E56: ='Cash Flow'!E71/'Income Statement'!E41 -> 0.71316442 | F56: ='Cash Flow'!F71/'Income Statement'!F41 -> 0.95070867 | G56: ='Cash Flow'!G71/'Income Statement'!G41 -> 0.97757108 | H56: ='Cash Flow'!H71/'Income Statement'!H41 -> 0.9411944 | I56: ='Cash Flow'!I71/'Income Statement'!I41 -> 0.88845718 | J56: ='Cash Flow'!J71/'Income Statement'!J41 -> 0.85665368 | ... L56: ='Cash Flow'!L71/'Income Statement'!L41 -> 0.83919187 | N56: ='Cash Flow'!N71/'Income Statement'!N41 -> 0.86119734 | O56: ='Cash Flow'!O71/'Income Statement'!O41 -> 0.9047619 | P56: ='Cash Flow'!P71/'Income Statement'!P41 -> 1.004818 | Q56: ='Cash Flow'!Q71/'Income Statement'!Q41 -> 0.55659121 | R56: ='Cash Flow'!R71/'Income Statement'!R41 -> 1.0610184 | S56: ='Cash Flow'!S71/'Income Statement'!S41 -> 0.75693161 | T56: ='Cash Flow'!T71/'Income Statement'!T41 -> 0.87241553 | U56: ='Cash Flow'!U71/'Income Statement'!U41 -> 0.83657917
A57: Dividends paid % of net income | C57: =(0-'Cash Flow'!C45)/'Income Statement'!C41 -> 0.65255521 | D57: =(0-'Cash Flow'!D45)/'Income Statement'!D41 -> 0.59495792 | E57: =(0-'Cash Flow'!E45)/'Income Statement'!E41 -> 0.54958392 | F57: =(0-'Cash Flow'!F45)/'Income Statement'!F41 -> 0.59446676 | G57: =(0-'Cash Flow'!G45)/'Income Statement'!G41 -> 0.79334108 | H57: =(0-'Cash Flow'!H45)/'Income Statement'!H41 -> 0.51935005 | I57: =(0-'Cash Flow'!I45)/'Income Statement'!I41 -> 0.67476121 | J57: =(0-'Cash Flow'!J45)/'Income Statement'!J41 -> 0.53524619 | ... L57: =(0-'Cash Flow'!L45)/'Income Statement'!L41 -> 0.59733738 | N57: =(0-'Cash Flow'!N45)/'Income Statement'!N41 -> 0.5308204 | O57: =(0-'Cash Flow'!O45)/'Income Statement'!O41 -> 0.62896825 | P57: =(0-'Cash Flow'!P45)/'Income Statement'!P41 -> 0.67773019 | Q57: =(0-'Cash Flow'!Q45)/'Income Statement'!Q41 -> 0.56147359 | R57: =(0-'Cash Flow'!R45)/'Income Statement'!R41 -> 0.55399473 | S57: =(0-'Cash Flow'!S45)/'Income Statement'!S41 -> 0.61136784 | T57: =(0-'Cash Flow'!T45)/'Income Statement'!T41 -> 0.66717095 | U57: =(0-'Cash Flow'!U45)/'Income Statement'!U41 -> 0.55757832
A58: Dividends paid % of FCF | C58: =(0-'Cash Flow'!C45)/'Cash Flow'!C71 -> 0.72152884 | D58: =(0-'Cash Flow'!D45)/'Cash Flow'!D71 -> 0.83548343 | E58: =(0-'Cash Flow'!E45)/'Cash Flow'!E71 -> 0.77062722 | F58: =(0-'Cash Flow'!F45)/'Cash Flow'!F71 -> 0.62528804 | G58: =(0-'Cash Flow'!G45)/'Cash Flow'!G71 -> 0.81154312 | H58: =(0-'Cash Flow'!H45)/'Cash Flow'!H71 -> 0.55179892 | I58: =(0-'Cash Flow'!I45)/'Cash Flow'!I71 -> 0.75947522 | J58: =(0-'Cash Flow'!J45)/'Cash Flow'!J71 -> 0.62481048 | ... L58: =(0-'Cash Flow'!L45)/'Cash Flow'!L71 -> 0.71180072 | N58: =(0-'Cash Flow'!N45)/'Cash Flow'!N71 -> 0.61637487 | O58: =(0-'Cash Flow'!O45)/'Cash Flow'!O71 -> 0.69517544 | P58: =(0-'Cash Flow'!P45)/'Cash Flow'!P71 -> 0.67448055 | Q58: =(0-'Cash Flow'!Q45)/'Cash Flow'!Q71 -> 1.0087719 | R58: =(0-'Cash Flow'!R45)/'Cash Flow'!R71 -> 0.52213488 | S58: =(0-'Cash Flow'!S45)/'Cash Flow'!S71 -> 0.80769231 | T58: =(0-'Cash Flow'!T45)/'Cash Flow'!T71 -> 0.76473988 | U58: =(0-'Cash Flow'!U45)/'Cash Flow'!U71 -> 0.66649798
A59: Treasury stock purchases % of FCF | C59: =(0-'Cash Flow'!C44)/'Cash Flow'!C71 -> 2.6356022 | D59: =(0-'Cash Flow'!D44)/'Cash Flow'!D71 -> 1.2672617 | E59: =(0-'Cash Flow'!E44)/'Cash Flow'!E71 -> 1.2325917 | F59: =(0-'Cash Flow'!F44)/'Cash Flow'!F71 -> 0.86868934 | G59: =(0-'Cash Flow'!G44)/'Cash Flow'!G71 -> 0.19630655 | H59: =(0-'Cash Flow'!H44)/'Cash Flow'!H71 -> 0.11905935 | I59: =(0-'Cash Flow'!I44)/'Cash Flow'!I71 -> 0.70991254 | J59: =(0-'Cash Flow'!J44)/'Cash Flow'!J71 -> 0.42095107 | ... L59: =(0-'Cash Flow'!L44)/'Cash Flow'!L71 -> 0.28611188 | N59: =(0-'Cash Flow'!N44)/'Cash Flow'!N71 -> 0.2415036 | O59: =(0-'Cash Flow'!O44)/'Cash Flow'!O71 -> 0.27576754 | P59: =(0-'Cash Flow'!P44)/'Cash Flow'!P71 -> 0.25412893 | Q59: =(0-'Cash Flow'!Q44)/'Cash Flow'!Q71 -> 0.40271132 | R59: =(0-'Cash Flow'!R44)/'Cash Flow'!R71 -> 0.20728175 | S59: =(0-'Cash Flow'!S44)/'Cash Flow'!S71 -> 0.34981685 | T59: =(0-'Cash Flow'!T44)/'Cash Flow'!T71 -> 0.22890173 | U59: =(0-'Cash Flow'!U44)/'Cash Flow'!U71 -> 0.43319838
A60: Dividends + buybacks % of FCF | C60: ='Cash Flow'!C76/'Cash Flow'!C71 -> 3.3571311 | D60: ='Cash Flow'!D76/'Cash Flow'!D71 -> 2.1027451 | E60: ='Cash Flow'!E76/'Cash Flow'!E71 -> 2.0032189 | F60: ='Cash Flow'!F76/'Cash Flow'!F71 -> 1.4939774 | G60: ='Cash Flow'!G76/'Cash Flow'!G71 -> 1.0078497 | H60: ='Cash Flow'!H76/'Cash Flow'!H71 -> 0.67085827 | I60: ='Cash Flow'!I76/'Cash Flow'!I71 -> 1.4693878 | J60: ='Cash Flow'!J76/'Cash Flow'!J71 -> 1.0457615 | ... L60: ='Cash Flow'!L76/'Cash Flow'!L71 -> 0.99791261 | N60: ='Cash Flow'!N76/'Cash Flow'!N71 -> 0.85787848 | O60: ='Cash Flow'!O76/'Cash Flow'!O71 -> 0.97094298 | P60: ='Cash Flow'!P76/'Cash Flow'!P71 -> 0.92860948 | Q60: ='Cash Flow'!Q76/'Cash Flow'!Q71 -> 1.4114833 | R60: ='Cash Flow'!R76/'Cash Flow'!R71 -> 0.72941663 | S60: ='Cash Flow'!S76/'Cash Flow'!S71 -> 1.1575092 | T60: ='Cash Flow'!T76/'Cash Flow'!T71 -> 0.99364162 | U60: ='Cash Flow'!U76/'Cash Flow'!U71 -> 1.0996964
A62: 6. SYSTEMWIDE AND FRANCHISE ECONOMICS
A63: Systemwide sales ($mm; franchised sales + Company-operated sales) | C63: ='Operating Metrics'!C49 -> 85002 | D63: ='Operating Metrics'!D49 -> 90909.9 | E63: ='Operating Metrics'!E49 -> 96146.7 | F63: ='Operating Metrics'!F49 -> 100177.8 | G63: ='Operating Metrics'!G49 -> 93317.2 | H63: ='Operating Metrics'!H49 -> 112462.4 | I63: ='Operating Metrics'!I49 -> 118221 | J63: ='Operating Metrics'!J49 -> 129492 | ... L63: ='Operating Metrics'!L49 -> 139365
A64: Systemwide sales growth (reported currency) | D64: ='Operating Metrics'!D49/'Operating Metrics'!C49-1 -> 0.069503071 | E64: ='Operating Metrics'!E49/'Operating Metrics'!D49-1 -> 0.057604287 | F64: ='Operating Metrics'!F49/'Operating Metrics'!E49-1 -> 0.041926556 | G64: ='Operating Metrics'!G49/'Operating Metrics'!F49-1 -> -0.068484235 | H64: ='Operating Metrics'!H49/'Operating Metrics'!G49-1 -> 0.20516261 | I64: ='Operating Metrics'!I49/'Operating Metrics'!H49-1 -> 0.051204669 | J64: ='Operating Metrics'!J49/'Operating Metrics'!I49-1 -> 0.095338392 | K64: ='Operating Metrics'!K49/'Operating Metrics'!J49-1 -> 0.0094445989 | L64: ='Operating Metrics'!L49/'Operating Metrics'!K49-1 -> 0.066174502
A65: Franchised revenues % of franchised sales | C65: ='Income Statement'!C12/'Operating Metrics'!C43 -> 0.13380148 | D65: ='Income Statement'!D12/'Operating Metrics'!D43 -> 0.12919006 | E65: ='Income Statement'!E12/'Operating Metrics'!E43 -> 0.12785311 | F65: ='Income Statement'!F12/'Operating Metrics'!F43 -> 0.12842756 | G65: ='Income Statement'!G12/'Operating Metrics'!G43 -> 0.12592571 | H65: ='Income Statement'!H12/'Operating Metrics'!H43 -> 0.12744485 | I65: ='Income Statement'!I12/'Operating Metrics'!I43 -> 0.12885369 | J65: ='Income Statement'!J12/'Operating Metrics'!J43 -> 0.12891023 | ... L65: ='Income Statement'!L12/'Operating Metrics'!L43 -> 0.12761134
A66: Franchised margins % of franchised sales | C66: =('Income Statement'!C12-'Income Statement'!C20)/'Operating Metrics'!C43 -> 0.10914973 | D66: =('Income Statement'!D12-'Income Statement'!D20)/'Operating Metrics'!D43 -> 0.1062974 | E66: =('Income Statement'!E12-'Income Statement'!E20)/'Operating Metrics'!E43 -> 0.10494346 | F66: =('Income Statement'!F12-'Income Statement'!F20)/'Operating Metrics'!F43 -> 0.10418039 | G66: =('Income Statement'!G12-'Income Statement'!G20)/'Operating Metrics'!G43 -> 0.10000939 | H66: =('Income Statement'!H12-'Income Statement'!H20)/'Operating Metrics'!H43 -> 0.10470319 | I66: =('Income Statement'!I12-'Income Statement'!I20)/'Operating Metrics'!I43 -> 0.10738721 | J66: =('Income Statement'!J12-'Income Statement'!J20)/'Operating Metrics'!J43 -> 0.10824217 | ... L66: =('Income Statement'!L12-'Income Statement'!L20)/'Operating Metrics'!L43 -> 0.1074224
A67: SG&A % of Systemwide sales | C67: ='Income Statement'!C30/'Operating Metrics'!C49 -> 0.028052281 | D67: ='Income Statement'!D30/'Operating Metrics'!D49 -> 0.024544082 | E67: ='Income Statement'!E30/'Operating Metrics'!E49 -> 0.022883781 | F67: ='Income Statement'!F30/'Operating Metrics'!F49 -> 0.022254432 | G67: ='Income Statement'!G30/'Operating Metrics'!G49 -> 0.027279001 | H67: ='Income Statement'!H30/'Operating Metrics'!H49 -> 0.024074713 | I67: ='Income Statement'!I30/'Operating Metrics'!I49 -> 0.024208897 | J67: ='Income Statement'!J30/'Operating Metrics'!J49 -> 0.02175424 | ... L67: ='Income Statement'!L30/'Operating Metrics'!L49 -> 0.021813224
A68: Operating income % of Systemwide sales | C68: ='Income Statement'!C33/'Operating Metrics'!C49 -> 0.091109621 | D68: ='Income Statement'!D33/'Operating Metrics'!D49 -> 0.10507876 | E68: ='Income Statement'!E33/'Operating Metrics'!E49 -> 0.09176186 | F68: ='Income Statement'!F33/'Operating Metrics'!F49 -> 0.090537025 | G68: ='Income Statement'!G33/'Operating Metrics'!G49 -> 0.078484995 | H68: ='Income Statement'!H33/'Operating Metrics'!H49 -> 0.09208411 | I68: ='Income Statement'!I33/'Operating Metrics'!I49 -> 0.079266797 | J68: ='Income Statement'!J33/'Operating Metrics'!J49 -> 0.08994378 | ... L68: ='Income Statement'!L33/'Operating Metrics'!L49 -> 0.088924766
A69: Total revenues per average systemwide restaurant ($mm) | D69: ='Income Statement'!D17/(('Operating Metrics'!D28+'Operating Metrics'!C28)/2) -> 0.61560291 | E69: ='Income Statement'!E17/(('Operating Metrics'!E28+'Operating Metrics'!D28)/2) -> 0.56615266 | F69: ='Income Statement'!F17/(('Operating Metrics'!F28+'Operating Metrics'!E28)/2) -> 0.55818158 | G69: ='Income Statement'!G17/(('Operating Metrics'!G28+'Operating Metrics'!F28)/2) -> 0.49318424 | H69: ='Income Statement'!H17/(('Operating Metrics'!H28+'Operating Metrics'!G28)/2) -> 0.58622222 | I69: ='Income Statement'!I17/(('Operating Metrics'!I28+'Operating Metrics'!H28)/2) -> 0.57736657 | J69: ='Income Statement'!J17/(('Operating Metrics'!J28+'Operating Metrics'!I28)/2) -> 0.6210702 | K69: ='Income Statement'!K17/(('Operating Metrics'!K28+'Operating Metrics'!J28)/2) -> 0.60774452 | L69: ='Income Statement'!L17/(('Operating Metrics'!L28+'Operating Metrics'!K28)/2) -> 0.60529308
A70: Interest expense / average total debt | D70: ='Income Statement'!D37/(('Balance Sheet'!D69+'Balance Sheet'!C69)/2) -> 0.033204726 | E70: ='Income Statement'!E37/(('Balance Sheet'!E69+'Balance Sheet'!D69)/2) -> 0.032376587 | F70: ='Income Statement'!F37/(('Balance Sheet'!F69+'Balance Sheet'!E69)/2) -> 0.034386422 | G70: ='Income Statement'!G37/(('Balance Sheet'!G69+'Balance Sheet'!F69)/2) -> 0.034016778 | H70: ='Income Statement'!H37/(('Balance Sheet'!H69+'Balance Sheet'!G69)/2) -> 0.032459614 | I70: ='Income Statement'!I37/(('Balance Sheet'!I69+'Balance Sheet'!H69)/2) -> 0.033749871 | J70: ='Income Statement'!J37/(('Balance Sheet'!J69+'Balance Sheet'!I69)/2) -> 0.036173479 | K70: ='Income Statement'!K37/(('Balance Sheet'!K69+'Balance Sheet'!J69)/2) -> 0.038730085 | L70: ='Income Statement'!L37/(('Balance Sheet'!L69+'Balance Sheet'!K69)/2) -> 0.040358687
A71: Capital expenditures per net restaurant addition ($mm; net additions can be small or negative) | E71: =(0-'Cash Flow'!E31)/'Operating Metrics'!E65 -> 4.4653094 | F71: =(0-'Cash Flow'!F31)/'Operating Metrics'!F65 -> 2.8496429 | G71: =(0-'Cash Flow'!G31)/'Operating Metrics'!G65 -> 3.2620278 | H71: =(0-'Cash Flow'!H31)/'Operating Metrics'!H65 -> 2.4489796 | I71: =(0-'Cash Flow'!I31)/'Operating Metrics'!I65 -> 7.7827869 | J71: =(0-'Cash Flow'!J31)/'Operating Metrics'!J65 -> 1.5235941 | K71: =(0-'Cash Flow'!K31)/'Operating Metrics'!K65 -> 1.6767372 | L71: =(0-'Cash Flow'!L31)/'Operating Metrics'!L65 -> 1.7908462
A73: 7. EARNINGS QUALITY
A74: CFO / net income | C74: ='Cash Flow'!C28/'Income Statement'!C41 -> 1.2929905 | D74: ='Cash Flow'!D28/'Income Statement'!D41 -> 1.0691216 | E74: ='Cash Flow'!E28/'Income Statement'!E41 -> 1.1759533 | F74: ='Cash Flow'!F28/'Income Statement'!F41 -> 1.3479769 | G74: ='Cash Flow'!G28/'Income Statement'!G41 -> 1.3244266 | H74: ='Cash Flow'!H28/'Income Statement'!H41 -> 1.211565 | I74: ='Cash Flow'!I28/'Income Statement'!I41 -> 1.195888 | J74: ='Cash Flow'!J28/'Income Statement'!J41 -> 1.1349628 | ... L74: ='Cash Flow'!L28/'Income Statement'!L41 -> 1.2321616 | N74: ='Cash Flow'!N28/'Income Statement'!N41 -> 1.2133038 | O74: ='Cash Flow'!O28/'Income Statement'!O41 -> 1.3050595 | P74: ='Cash Flow'!P28/'Income Statement'!P41 -> 1.2997859 | Q74: ='Cash Flow'!Q28/'Income Statement'!Q41 -> 0.88681758 | R74: ='Cash Flow'!R28/'Income Statement'!R41 -> 1.5048288 | S74: ='Cash Flow'!S28/'Income Statement'!S41 -> 1.2463031 | T74: ='Cash Flow'!T28/'Income Statement'!T41 -> 1.2163389 | U74: ='Cash Flow'!U28/'Income Statement'!U41 -> 1.1883997
A75: Accrual ratio ((net income - CFO) / average assets) | D75: =('Income Statement'!D41-'Cash Flow'!D28)/D30 -> -0.011072444 | E75: =('Income Statement'!E41-'Cash Flow'!E28)/E30 -> -0.031296302 | F75: =('Income Statement'!F41-'Cash Flow'!F28)/F30 -> -0.052207365 | G75: =('Income Statement'!G41-'Cash Flow'!G28)/G30 -> -0.030651823 | H75: =('Income Statement'!H41-'Cash Flow'!H28)/H30 -> -0.029982786 | I75: =('Income Statement'!I41-'Cash Flow'!I28)/I30 -> -0.023204548 | J75: =('Income Statement'!J41-'Cash Flow'!J28)/J30 -> -0.021448154 | K75: =('Income Statement'!K41-'Cash Flow'!K28)/K30 -> -0.02198888 | L75: =('Income Statement'!L41-'Cash Flow'!L28)/L30 -> -0.034665248
A77: 8. GROWTH
A78: Total revenues | C78: ='Income Statement'!C17 -> 24621.9 | D78: ='Income Statement'!D17 -> 22820.4 | E78: ='Income Statement'!E17 -> 21257.9 | F78: ='Income Statement'!F17 -> 21364.4 | G78: ='Income Statement'!G17 -> 19207.8 | H78: ='Income Statement'!H17 -> 23222.9 | I78: ='Income Statement'!I17 -> 23183 | J78: ='Income Statement'!J17 -> 25494 | ... L78: ='Income Statement'!L17 -> 26885 | N78: ='Income Statement'!N17 -> 6873 | O78: ='Income Statement'!O17 -> 6388 | P78: ='Income Statement'!P17 -> 5956 | Q78: ='Income Statement'!Q17 -> 6843 | R78: ='Income Statement'!R17 -> 7078 | S78: ='Income Statement'!S17 -> 7009 | T78: ='Income Statement'!T17 -> 6517 | U78: ='Income Statement'!U17 -> 7099
A79: YoY Growth | D79: =IF(N(C78)=0,"",D78/C78-1) -> -0.073166571 | E79: =IF(N(D78)=0,"",E78/D78-1) -> -0.06846944 | F79: =IF(N(E78)=0,"",F78/E78-1) -> 0.0050099022 | G79: =IF(N(F78)=0,"",G78/F78-1) -> -0.10094363 | H79: =IF(N(G78)=0,"",H78/G78-1) -> 0.20903487 | I79: =IF(N(H78)=0,"",I78/H78-1) -> -0.0017181317 | J79: =IF(N(I78)=0,"",J78/I78-1) -> 0.099685114 | K79: =IF(N(J78)=0,"",K78/J78-1) -> 0.016709814 | L79: =IF(N(K78)=0,"",L78/K78-1) -> 0.037229938 | R79: =IF(N(N78)=0,"",R78/N78-1) -> 0.029826859 | S79: =IF(N(O78)=0,"",S78/O78-1) -> 0.097213525 | T79: =IF(N(P78)=0,"",T78/P78-1) -> 0.094190732 | U79: =IF(N(Q78)=0,"",U78/Q78-1) -> 0.037410492
A80: Operating income | C80: ='Income Statement'!C33 -> 7744.5 | D80: ='Income Statement'!D33 -> 9552.7 | E80: ='Income Statement'!E33 -> 8822.6 | F80: ='Income Statement'!F33 -> 9069.8 | G80: ='Income Statement'!G33 -> 7324 | H80: ='Income Statement'!H33 -> 10356 | I80: ='Income Statement'!I33 -> 9371 | J80: ='Income Statement'!J33 -> 11647 | ... L80: ='Income Statement'!L33 -> 12393 | N80: ='Income Statement'!N33 -> 3188 | O80: ='Income Statement'!O33 -> 2868 | P80: ='Income Statement'!P33 -> 2648 | Q80: ='Income Statement'!Q33 -> 3232 | R80: ='Income Statement'!R33 -> 3357 | S80: ='Income Statement'!S33 -> 3156 | T80: ='Income Statement'!T33 -> 2953 | U80: ='Income Statement'!U33 -> 3338
A81: YoY Growth | D81: =IF(N(C80)=0,"",D80/C80-1) -> 0.23348183 | E81: =IF(N(D80)=0,"",E80/D80-1) -> -0.076428654 | F81: =IF(N(E80)=0,"",F80/E80-1) -> 0.028018951 | G81: =IF(N(F80)=0,"",G80/F80-1) -> -0.19248495 | H81: =IF(N(G80)=0,"",H80/G80-1) -> 0.41398143 | I81: =IF(N(H80)=0,"",I80/H80-1) -> -0.095113944 | J81: =IF(N(I80)=0,"",J80/I80-1) -> 0.24287696 | K81: =IF(N(J80)=0,"",K80/J80-1) -> 0.0055808363 | L81: =IF(N(K80)=0,"",L80/K80-1) -> 0.058145492 | R81: =IF(N(N80)=0,"",R80/N80-1) -> 0.053011292 | S81: =IF(N(O80)=0,"",S80/O80-1) -> 0.10041841 | T81: =IF(N(P80)=0,"",T80/P80-1) -> 0.11518127 | U81: =IF(N(Q80)=0,"",U80/Q80-1) -> 0.03279703
A82: Net income | C82: ='Income Statement'!C41 -> 4686.5 | D82: ='Income Statement'!D41 -> 5192.3 | E82: ='Income Statement'!E41 -> 5924.3 | F82: ='Income Statement'!F41 -> 6025.4 | G82: ='Income Statement'!G41 -> 4730.5 | H82: ='Income Statement'!H41 -> 7545.2 | I82: ='Income Statement'!I41 -> 6177 | J82: ='Income Statement'!J41 -> 8469 | ... L82: ='Income Statement'!L41 -> 8563 | N82: ='Income Statement'!N41 -> 2255 | O82: ='Income Statement'!O41 -> 2016 | P82: ='Income Statement'!P41 -> 1868 | Q82: ='Income Statement'!Q41 -> 2253 | R82: ='Income Statement'!R41 -> 2278 | S82: ='Income Statement'!S41 -> 2164 | T82: ='Income Statement'!T41 -> 1983 | U82: ='Income Statement'!U41 -> 2362
A83: YoY Growth | D83: =IF(N(C82)=0,"",D82/C82-1) -> 0.10792702 | E83: =IF(N(D82)=0,"",E82/D82-1) -> 0.14097799 | F83: =IF(N(E82)=0,"",F82/E82-1) -> 0.017065307 | G83: =IF(N(F82)=0,"",G82/F82-1) -> -0.21490689 | H83: =IF(N(G82)=0,"",H82/G82-1) -> 0.5950111 | I83: =IF(N(H82)=0,"",I82/H82-1) -> -0.18133383 | J83: =IF(N(I82)=0,"",J82/I82-1) -> 0.37105391 | K83: =IF(N(J82)=0,"",K82/J82-1) -> -0.029047113 | L83: =IF(N(K82)=0,"",L82/K82-1) -> 0.04134744 | R83: =IF(N(N82)=0,"",R82/N82-1) -> 0.010199557 | S83: =IF(N(O82)=0,"",S82/O82-1) -> 0.073412698 | T83: =IF(N(P82)=0,"",T82/P82-1) -> 0.061563169 | U83: =IF(N(Q82)=0,"",U82/Q82-1) -> 0.048379938
A84: Diluted EPS ($) | C84: ='Income Statement'!C47 -> 5.44 | D84: ='Income Statement'!D47 -> 6.37 | E84: ='Income Statement'!E47 -> 7.54 | F84: ='Income Statement'!F47 -> 7.88 | G84: ='Income Statement'!G47 -> 6.31 | H84: ='Income Statement'!H47 -> 10.04 | I84: ='Income Statement'!I47 -> 8.33 | J84: ='Income Statement'!J47 -> 11.56 | ... L84: ='Income Statement'!L47 -> 11.95 | N84: ='Income Statement'!N47 -> 3.13 | O84: ='Income Statement'!O47 -> 0 | P84: ='Income Statement'!P47 -> 2.6 | Q84: ='Income Statement'!Q47 -> 3.14 | R84: ='Income Statement'!R47 -> 3.18 | S84: ='Income Statement'!S47 -> 0 | T84: ='Income Statement'!T47 -> 2.78 | U84: ='Income Statement'!U47 -> 3.32
A85: YoY Growth | D85: =IF(N(C84)=0,"",D84/C84-1) -> 0.17095588 | E85: =IF(N(D84)=0,"",E84/D84-1) -> 0.18367347 | F85: =IF(N(E84)=0,"",F84/E84-1) -> 0.045092838 | G85: =IF(N(F84)=0,"",G84/F84-1) -> -0.19923858 | H85: =IF(N(G84)=0,"",H84/G84-1) -> 0.5911252 | I85: =IF(N(H84)=0,"",I84/H84-1) -> -0.17031873 | J85: =IF(N(I84)=0,"",J84/I84-1) -> 0.3877551 | K85: =IF(N(J84)=0,"",K84/J84-1) -> -0.014705882 | L85: =IF(N(K84)=0,"",L84/K84-1) -> 0.049165935 | R85: =IF(N(N84)=0,"",R84/N84-1) -> 0.015974441 | S85: =IF(N(O84)=0,"",S84/O84-1) | T85: =IF(N(P84)=0,"",T84/P84-1) -> 0.069230769 | U85: =IF(N(Q84)=0,"",U84/Q84-1) -> 0.057324841
A86: Cash provided by operations | C86: ='Cash Flow'!C28 -> 6059.6 | D86: ='Cash Flow'!D28 -> 5551.2 | E86: ='Cash Flow'!E28 -> 6966.7 | F86: ='Cash Flow'!F28 -> 8122.1 | G86: ='Cash Flow'!G28 -> 6265.2 | H86: ='Cash Flow'!H28 -> 9141.5 | I86: ='Cash Flow'!I28 -> 7387 | J86: ='Cash Flow'!J28 -> 9612 | ... L86: ='Cash Flow'!L28 -> 10551 | N86: ='Cash Flow'!N28 -> 2736 | O86: ='Cash Flow'!O28 -> 2631 | P86: ='Cash Flow'!P28 -> 2428 | Q86: ='Cash Flow'!Q28 -> 1998 | R86: ='Cash Flow'!R28 -> 3428 | S86: ='Cash Flow'!S28 -> 2697 | T86: ='Cash Flow'!T28 -> 2412 | U86: ='Cash Flow'!U28 -> 2807
A87: YoY Growth | D87: =IF(N(C86)=0,"",D86/C86-1) -> -0.083899927 | E87: =IF(N(D86)=0,"",E86/D86-1) -> 0.25498991 | F87: =IF(N(E86)=0,"",F86/E86-1) -> 0.1658461 | G87: =IF(N(F86)=0,"",G86/F86-1) -> -0.22862314 | H87: =IF(N(G86)=0,"",H86/G86-1) -> 0.45909149 | I87: =IF(N(H86)=0,"",I86/H86-1) -> -0.19192693 | J87: =IF(N(I86)=0,"",J86/I86-1) -> 0.30120482 | K87: =IF(N(J86)=0,"",K86/J86-1) -> -0.017166042 | L87: =IF(N(K86)=0,"",L86/K86-1) -> 0.1168625 | R87: =IF(N(N86)=0,"",R86/N86-1) -> 0.25292398 | S87: =IF(N(O86)=0,"",S86/O86-1) -> 0.025085519 | T87: =IF(N(P86)=0,"",T86/P86-1) -> -0.0065897858 | U87: =IF(N(Q86)=0,"",U86/Q86-1) -> 0.4049049
A88: Free cash flow | C88: ='Cash Flow'!C71 -> 4238.5 | D88: ='Cash Flow'!D71 -> 3697.5 | E88: ='Cash Flow'!E71 -> 4225 | F88: ='Cash Flow'!F71 -> 5728.4 | G88: ='Cash Flow'!G71 -> 4624.4 | H88: ='Cash Flow'!H71 -> 7101.5 | I88: ='Cash Flow'!I71 -> 5488 | J88: ='Cash Flow'!J71 -> 7255 | ... L88: ='Cash Flow'!L71 -> 7186 | N88: ='Cash Flow'!N71 -> 1942 | O88: ='Cash Flow'!O71 -> 1824 | P88: ='Cash Flow'!P71 -> 1877 | Q88: ='Cash Flow'!Q71 -> 1254 | R88: ='Cash Flow'!R71 -> 2417 | S88: ='Cash Flow'!S71 -> 1638 | T88: ='Cash Flow'!T71 -> 1730 | U88: ='Cash Flow'!U71 -> 1976
A89: YoY Growth | D89: =IF(N(C88)=0,"",D88/C88-1) -> -0.1276395 | E89: =IF(N(D88)=0,"",E88/D88-1) -> 0.14266396 | F89: =IF(N(E88)=0,"",F88/E88-1) -> 0.35583432 | G89: =IF(N(F88)=0,"",G88/F88-1) -> -0.19272397 | H89: =IF(N(G88)=0,"",H88/G88-1) -> 0.53565868 | I89: =IF(N(H88)=0,"",I88/H88-1) -> -0.22720552 | J89: =IF(N(I88)=0,"",J88/I88-1) -> 0.32197522 | K89: =IF(N(J88)=0,"",K88/J88-1) -> -0.080358374 | L89: =IF(N(K88)=0,"",L88/K88-1) -> 0.077038369 | R89: =IF(N(N88)=0,"",R88/N88-1) -> 0.2445932 | S89: =IF(N(O88)=0,"",S88/O88-1) -> -0.10197368 | T89: =IF(N(P88)=0,"",T88/P88-1) -> -0.078316462 | U89: =IF(N(Q88)=0,"",U88/Q88-1) -> 0.57575758

Sheet Year-End Schedules
A1: McDonald's Corporation — Year-End Schedules
A2: $ in millions except per-share data | USD | as of 2026-10-08
A4: Year-end schedules disclosed in the notes (USD millions). Source: Form 10-K notes; table IDs refer to tables.json in this output folder.
A6: Aggregate debt maturities at December 31, 2025 (before fair value adjustments and deferred debt costs)
A7: Year | B7: Amount
A8: 2026 | B8: 0
A9: 2027 | B9: 3201
A10: 2028 | B10: 5166
A11: 2029 | B11: 3637
A12: 2030 | B12: 3011
A13: Thereafter | B13: 25130
A15: Aggregate debt maturities at December 31, 2024 (before fair value adjustments and deferred debt costs)
A16: Year | B16: Amount
A17: 2025 | B17: 0
A18: 2026 | B18: 2392
A19: 2027 | B19: 3036
A20: 2028 | B20: 7221
A21: 2029 | B21: 3394
A22: Thereafter | B22: 22573
A24: Minimum rent payments due to the Company under franchise arrangements at December 31, 2025 (table T828)
A25: Year | B25: Owned sites | C25: Leased sites | D25: Total
A26: 2026 | B26: 1509 | C26: 1536 | D26: 3045
A27: 2027 | B27: 1465 | C27: 1478 | D27: 2943
A28: 2028 | B28: 1409 | C28: 1403 | D28: 2812
A29: 2029 | B29: 1334 | C29: 1325 | D29: 2659
A30: 2030 | B30: 1271 | C30: 1256 | D30: 2527
A31: Thereafter | B31: 8855 | C31: 8610 | D31: 17465
A32: Total minimum payments | B32: 15843 | C32: 15608 | D32: 31451
A34: Minimum rent payments due to the Company under franchise arrangements at December 31, 2024 (table T763)
A35: Year | B35: Owned sites | C35: Leased sites | D35: Total
A36: 2025 | B36: 1455 | C36: 1425 | D36: 2880
A37: 2026 | B37: 1401 | C37: 1361 | D37: 2762
A38: 2027 | B38: 1353 | C38: 1301 | D38: 2654
A39: 2028 | B39: 1298 | C39: 1236 | D39: 2534
A40: 2029 | B40: 1227 | C40: 1166 | D40: 2393
A41: Thereafter | B41: 8462 | C41: 7913 | D41: 16375
A42: Total minimum payments | B42: 15196 | C42: 14402 | D42: 29598
A44: Lease payment maturities at December 31, 2025 (table T833)
A45: Year | B45: Operating | C45: Finance | D45: Total (as filed)
A46: 2026 | B46: 1200 | C46: 120 | D46: 1321
A47: 2027 | B47: 1166 | C47: 123 | D47: 1289
A48: 2028 | B48: 1115 | C48: 124 | D48: 1239
A49: 2029 | B49: 1076 | C49: 125 | D49: 1201
A50: 2030 | B50: 1029 | C50: 127 | D50: 1156
A51: Thereafter | B51: 10977 | C51: 3443 | D51: 14420
A52: Total lease payments | B52: 16564 | C52: 4062 | D52: 20626
A53: Less: imputed interest | B53: 4075 | C53: 1710 | D53: 5785
A54: Present value of lease liability | B54: 12488 | C54: 2352 | D54: 14840
A56: Lease payment maturities at December 31, 2024 (table T768)
A57: Year | B57: Operating | C57: Finance | D57: Total (as filed)
A58: 2025 | B58: 1087 | C58: 91 | D58: 1178
A59: 2026 | B59: 1042 | C59: 93 | D59: 1135
A60: 2027 | B60: 1013 | C60: 94 | D60: 1107
A61: 2028 | B61: 972 | C61: 95 | D61: 1067
A62: 2029 | B62: 939 | C62: 96 | D62: 1035
A63: Thereafter | B63: 10897 | C63: 2543 | D63: 13440
A64: Total lease payments | B64: 15950 | C64: 3012 | D64: 18962
A65: Less: imputed interest | B65: 4206 | C65: 1232 | D65: 5438
A66: Present value of lease liability | B66: 11744 | C66: 1780 | D66: 13524
A68: Restructuring reserve roll-forward - Accelerating the Organization (table T835)
A69: Line | B69: Employee termination benefits | C69: Costs to terminate contracts | D69: Professional services and other | E69: Total
A70: 2023
A71: Accrued Balance at Beginning of Year | B71: 0 | C71: 0 | D71: 0 | E71: 0
A72: Restructuring Costs Incurred | B72: 96 | C72: 32 | D72: 122 | E72: 250
A73: Cash Payments | B73: -52 | C73: -21 | D73: -99 | E73: -172
A74: Other Non-Cash Items | B74: -3 | C74: 0 | D74: -16 | E74: -19
A75: Accrued Balance at December 31, 2023 | B75: 41 | C75: 11 | D75: 7 | E75: 59
A76: 2024
A77: Accrued Balance at Beginning of Year | B77: 41 | C77: 11 | D77: 7 | E77: 59
A78: Restructuring Costs Incurred | B78: 6 | C78: 1 | D78: 214 | E78: 221
A79: Cash Payments | B79: -24 | C79: -8 | D79: -205 | E79: -237
A80: Other Non-Cash Items | B80: 0 | C80: 0 | D80: -1 | E80: -1
A81: Accrued Balance at December 31, 2024 | B81: 23 | C81: 4 | D81: 15 | E81: 42
A82: 2025
A83: Accrued Balance at Beginning of Year | B83: 23 | C83: 4 | D83: 15 | E83: 42
A84: Restructuring Costs Incurred | B84: 32 | C84: 1 | D84: 193 | E84: 226
A85: Cash Payments | B85: -21 | C85: -1 | D85: -197 | E85: -219
A86: Other Non-Cash Items | B86: 0 | C86: 0 | D86: 4 | E86: 4
A87: Accrued Balance at December 31, 2025 | B87: 34 | C87: 4 | D87: 15 | E87: 53
A89: Equity-method investees (table T836); company-reported, Level 1 fair value where listed
A90: Investee | B90: Ownership 2025 | C90: Fair value 2025 | D90: Carrying 2025 | E90: Ownership 2024 | F90: Fair value 2024 | G90: Carrying 2024
A91: Grand Foods Holding | B91: 48 | C91: N/A | D91: 2048 | E91: 48 | F91: N/A | G91: 1973
A92: McDonald's Japan Holdings Co., Ltd | B92: 35 | C92: 1915 | D92: 657 | E92: 35 | F92: 1849 | G92: 590
A94: Summarised financial data of the equity-method investees (table T837)
A95: Line | B95: 2025 | C95: 2024
A96: Revenue | B96: 579 | C96: 538
A97: Equity in Earnings | B97: 146 | C97: 113
A98: Accounts Receivable | B98: 89 | C98: 157
A99: Dividends Received | B99: 15 | C99: 157

Sheet Outlook & Text KPIs
A1: McDonald's Corporation — Outlook & Text KPIs
A2: $ in millions except per-share data | USD | as of 2026-10-08
A4: Management outlook and operating-KPI statements quoted verbatim from Form 10-K MD&A text. Source tier: SEC filing (company statement). Nature: FORWARD-LOOKING guidance / targets or company-stated facts - not realised results, not audited, not verified independently.
A5: Locator = line number in the prepared document.md of the cited 10-K (sources/companies/US/MCD-mcdonalds/artifacts/ten_k/MCD-mcdonalds/FY<year>/psp_*/prepared/document.md). Management-stated conditions are preserved in the quoted text.
A7: 10-K fiscal year | B7: Guided year | C7: Item | D7: Verbatim statement | E7: Line
A8: FY2016 | B8: 2017 | C8: Net restaurant additions contribution to Systemwide sales growth | D8: Changes in Systemwide sales are driven by comparable sales and net restaurant unit expansion. The Company expects net restaurant additions to add approximately 1 percentage point to 2017 Systemwide sales growth (in constant currencies). | E8: 836
A9: FY2016 | B9: 2017 | C9: SG&A | D9: The Company expects full-year 2017 selling, general and administrative expenses to decrease about 7-8%, in constant currencies with fluctuations expected between the quarters. This includes incentive-based compensation costs of less than $ 300 million. | E9: 845
A10: FY2016 | B10: 2017 | C10: Interest expense | D10: Based on current interest and foreign currency exchange rates, the Company expects interest expense for the full-year 2017 to increase about 5-10% compared with 2016 due to higher average debt balances. | E10: 848
A11: FY2016 | B11: 2017 | C11: Effective tax rate | D11: The Company expects the effective income tax rate for the full-year 2017 to be in the 31-33% range. Some volatility may result in a quarterly tax rate outside of the annual range. | E11: 854
A12: FY2016 | B12: 2017 | C12: Capital expenditures / restaurant openings | D12: The Company expects capital expenditures for 2017 to be approximately $ 1.7 billion, about one-third of which will be used to open new restaurants. The Company expects to open about 900 restaurants, including about 500 restaurants in affiliated and developmental licensee markets where the Company generally does not fund any capital expenditures. The Company expects net additions of about 400 restaurants. The remaining two-thirds of capital will be used to reinvest in existing locations, including about 650 reimages | E12: 857
A13: FY2017 | B13: 2018 | C13: Net restaurant additions contribution to Systemwide sales growth | D13: Changes in Systemwide sales are driven by comparable sales, net restaurant unit expansion, and the potential impacts of hyper-inflation. The Company expects net restaurant additions to add approximately 1 percentage point to 2018 Systemwide sales growth (in constant currencies). | E13: 842
A14: FY2017 | B14: 2018 | C14: SG&A | D14: The Company expects full-year 2018 selling, general and administrative expenses to decrease about 1% in constant currencies. | E14: 854
A15: FY2017 | B15: 2018 | C15: Interest expense | D15: Based on current interest and foreign currency exchange rates, the Company expects interest expense for the full-year 2018 to increase about 5% to 7% compared with 2017 due primarily to higher average debt balances. | E15: 857
A16: FY2017 | B16: 2018 | C16: Effective tax rate | D16: The Company expects the effective income tax rate for the full-year 2018 to be in the 25-27% range, with volatility between the quarters. Certain aspects of the Tax Act are expected to be clarified, and as such, could impact the Company's tax rate. | E16: 863
A17: FY2017 | B17: 2018 | C17: Capital expenditures / restaurant openings | D17: The Company expects capital expenditures for 2018 to be approximately $ 2.4 billion. About $ 1.5 billion will be dedicated to our U.S. business, primarily focused on accelerating the pace of EOTF. We expect to complete EOTF at nearly 4,000 additional U.S. restaurants in 2018, | E17: 866
A18: FY2018 | B18: 2019 | C18: Net restaurant additions contribution to Systemwide sales growth | D18: Changes in Systemwide sales are driven by comparable sales, net restaurant unit expansion and the potential impacts of hyper-inflation. The Company expects net restaurant additions to add approximately 1 percentage point to 2019 Systemwide sales growth (in constant currencies). | E18: 796
A19: FY2018 | B19: 2019 | C19: SG&A | D19: The Company expects full year 2019 selling, general and administrative expenses to decrease about 4% in constant currencies. | E19: 805
... A69: FY2025 | B69: 2026 | C69: Free cash flow conversion | D69: The Company expects to achieve a free cash flow conversion rate in the low-to-mid 80% range for 2026. | E69: 378
A71: Operating KPI and strategy statements (FY2021-FY2025 10-Ks)
A72: 10-K fiscal year | B72: Topic | D72: Verbatim statement | E72: Line
A73: FY2021 | B73: Loyalty / digital | D73: • Comparable sales in the U.S. increased 13.8%, benefiting primarily from strong average check growth, successful menu and marketing promotions and growth in digital channels, which benefited from the launch of the Company's loyalty program. | E73: 321
A74: FY2021 | B74: Restaurant development | D74: • Capital expenditures of $ 2.0 billion were allocated mainly to reinvestment in existing restaurants and, to a lesser extent, to new restaurant openings. | E74: 343
A75: FY2021 | B75: Restaurant development | D75: • Across the System, nearly 1,500 new restaurants (including those in developmental licensee and affiliate markets) were opened. | E75: 347
A76: FY2021 | B76: Loyalty / digital | D76: The Company has successful loyalty programs in over 40 markets around the world, including “MyMcDonald’s Rewards” in the U.S., Germany and Canada, each of which launched in 2021. | E76: 365
A77: FY2021 | B77: Loyalty / digital | D77: Just six months after its launch, MyMcDonald’s Rewards in the U.S. has enrolled 30 million members, with over 21 million active loyalty members earning rewards. | E77: 365
A78: FY2021 | B78: Delivery | D78: ◦ Delivery: The Company has expanded the number of restaurants offering delivery to over 33,000, representing over 80% of McDonald's restaurants, and delivery sales have grown significantly over the past few years. | E78: 367
A79: FY2021 | B79: Drive thru | D79: ◦ Drive Thru: The Company has drive thru locations in over 25,000 restaurants globally, including nearly 95% of the 13,000+ locations in the U.S. | E79: 369
A80: FY2021 | B80: Restaurant development | D80: The Company will open over 500 restaurants in the U.S. and International Operated Markets segments, and developmental licensees and affiliates will contribute capital towards over 1,300 restaurant openings in their respective markets. | E80: 389
A81: FY2022 | B81: Restaurant development | D81: • Capital expenditures of $ 1.9 billion were allocated approximately 50% to each of reinvestment in existing restaurants and new restaurant openings. | E81: 333
A82: FY2022 | B82: Restaurant development | D82: • Across the System, over 1,500 new restaurants (including those in our developmental licensee and affiliated markets) were opened. | E82: 337
A83: FY2022 | B83: Loyalty / digital | D83: The Company has successful loyalty programs in over 50 markets around the world, including its top six markets. | E83: 355
A84: FY2022 | B84: Loyalty / digital | D84: As of December 31, 2022, the Company’s loyalty customers have proven to be highly engaged, with nearly 50 million active loyalty members across the top six markets in the last 90 days, including 28 million in the U.S. | E84: 355
... A122: FY2025 | B122: Restaurant development | D122: Globally, the Company expects to open approximately 2,600 restaurants in 2026, with about 750 restaurants opening in the U.S. and International Operated Markets, and developmental licensees and affiliates contributing capital towards more than 1,800 restaurant openings in their respective markets. | E122: 376

Sheet Sources
A1: McDonald's Corporation — Sources
A2: $ in millions except per-share data | USD | as of 2026-10-08
A4: Source ID | B4: Form / period | C4: Period end | D4: SEC URL (accession folder) | E4: Local path | F4: Raw source.html SHA-256 | G4: Notes
A5: S001 | B5: SEC 10-K - McDonald's Corporation FY2016 10-K | C5: 2016-12-31 | D5: https://www.sec.gov/Archives/edgar/data/63908/000006390817000017/ | E5: sources/companies/US/MCD-mcdonalds/artifacts/ten_k/MCD-mcdonalds/FY2016/ | F5: 3850e57247214dacb2d6707f5d14d5cb94e0861e1f1e9eaf43a973ad3d18f21b | G5: Accession 0000063908-17-000017; filed 2017-03-01; package psp_7eec6fd72710477497d5550d77be8305; raw/source.html SHA-256 shown; prepared/docu
A6: S002 | B6: SEC 10-K - McDonald's Corporation FY2017 10-K | C6: 2017-12-31 | D6: https://www.sec.gov/Archives/edgar/data/63908/000006390818000010/ | E6: sources/companies/US/MCD-mcdonalds/artifacts/ten_k/MCD-mcdonalds/FY2017/ | F6: 0febf160f7c305eb50f271545fad1dad0615747544caf0fe455543b7c054de26 | G6: Accession 0000063908-18-000010; filed 2018-02-23; package psp_70e820a9eb774ac39e1e7a22fffb2910; raw/source.html SHA-256 shown; prepared/docu
A7: S003 | B7: SEC 10-K - McDonald's Corporation FY2018 10-K | C7: 2018-12-31 | D7: https://www.sec.gov/Archives/edgar/data/63908/000006390819000010/ | E7: sources/companies/US/MCD-mcdonalds/artifacts/ten_k/MCD-mcdonalds/FY2018/ | F7: e64dbaa45bfadd7815ce167b97a5c1fd178f4e4e5673586010fcde0a766fa75a | G7: Accession 0000063908-19-000010; filed 2019-02-22; package psp_54de7e747d424a1eb6b58080627b8671; raw/source.html SHA-256 shown; prepared/docu
A8: S004 | B8: SEC 10-K - McDonald's Corporation FY2019 10-K | C8: 2019-12-31 | D8: https://www.sec.gov/Archives/edgar/data/63908/000006390820000022/ | E8: sources/companies/US/MCD-mcdonalds/artifacts/ten_k/MCD-mcdonalds/FY2019/ | F8: b4fe586c36906c1c31ed8389cd288bda28364810fe5bb5d6b59f015fd0d34b6c | G8: Accession 0000063908-20-000022; filed 2020-02-26; package psp_6a6839c598fb44cf84637ef78c8cca77; raw/source.html SHA-256 shown; prepared/docu
A9: S005 | B9: SEC 10-K - McDonald's Corporation FY2020 10-K | C9: 2020-12-31 | D9: https://www.sec.gov/Archives/edgar/data/63908/000006390821000013/ | E9: sources/companies/US/MCD-mcdonalds/artifacts/ten_k/MCD-mcdonalds/FY2020/ | F9: 81e96230b4bed3bb40e3b190c2ef68952261c449940ce498c511546764ecf5dd | G9: Accession 0000063908-21-000013; filed 2021-02-23; package psp_5aea50748dad4c96af9a2e472c4ee0ca; raw/source.html SHA-256 shown; prepared/docu
A10: S006 | B10: SEC 10-K - McDonald's Corporation FY2021 10-K | C10: 2021-12-31 | D10: https://www.sec.gov/Archives/edgar/data/63908/000006390822000011/ | E10: sources/companies/US/MCD-mcdonalds/artifacts/ten_k/MCD-mcdonalds/FY2021/ | F10: dfa470c0ef8b9e08dd2da7d69463eb907ecd79afdeb840481a3d7854ec9a2d40 | G10: Accession 0000063908-22-000011; filed 2022-02-24; package psp_f17120d116dd4836a7cf87a9a4d1eea5; raw/source.html SHA-256 shown; prepared/docu
A11: S007 | B11: SEC 10-K - McDonald's Corporation FY2022 10-K | C11: 2022-12-31 | D11: https://www.sec.gov/Archives/edgar/data/63908/000006390823000012/ | E11: sources/companies/US/MCD-mcdonalds/artifacts/ten_k/MCD-mcdonalds/FY2022/ | F11: 584b17313492be687b5266b463bd34aa218953607a877ed94a3566dbf8daed9a | G11: Accession 0000063908-23-000012; filed 2023-02-24; package psp_5c02e34023f4489ca3bd31125a064c4f; raw/source.html SHA-256 shown; prepared/docu
A12: S008 | B12: SEC 10-K - McDonald's Corporation FY2023 10-K | C12: 2023-12-31 | D12: https://www.sec.gov/Archives/edgar/data/63908/000006390824000072/ | E12: sources/companies/US/MCD-mcdonalds/artifacts/ten_k/MCD-mcdonalds/FY2023/ | F12: 3c88e1f965e57e2b3c6c0149e8c47a112c91bf6a58648ac069b17b16b10a0362 | G12: Accession 0000063908-24-000072; filed 2024-02-22; package psp_ef1ae541a2824f9686a1c1fc99a30117; raw/source.html SHA-256 shown; prepared/docu
A13: S009 | B13: SEC 10-Q - McDonald's Corporation 2024 Q3 10-Q | C13: 2024-09-30 | D13: https://www.sec.gov/Archives/edgar/data/63908/000006390824000156/ | E13: sources/companies/US/MCD-mcdonalds/artifacts/ten_k/MCD-mcdonalds-10Q-Q3/FY2024/ | F13: 492598e17026b9e60d883c0722b3f6a0a1b610d1a67cb5234f4ff68fd5d5bc47 | G13: Accession 0000063908-24-000156; filed 2024-11-07; package psp_9bb891694811468dafd1c2ff04bd55d5; raw/source.html SHA-256 shown; prepared/docu
A14: S010 | B14: SEC 10-K - McDonald's Corporation FY2024 10-K | C14: 2024-12-31 | D14: https://www.sec.gov/Archives/edgar/data/63908/000006390825000012/ | E14: sources/companies/US/MCD-mcdonalds/artifacts/ten_k/MCD-mcdonalds/FY2024/ | F14: 35b47dfeae166963f5c97d3a43ac61851ef6dae752b2e85a3849268d300e9564 | G14: Accession 0000063908-25-000012; filed 2025-02-25; package psp_3dcad7a1d4024ad5afd45edf2d6ab8fa; raw/source.html SHA-256 shown; prepared/docu
A15: S011 | B15: SEC 10-Q - McDonald's Corporation 2025 Q1 10-Q | C15: 2025-03-31 | D15: https://www.sec.gov/Archives/edgar/data/63908/000006390825000025/ | E15: sources/companies/US/MCD-mcdonalds/artifacts/ten_k/MCD-mcdonalds-10Q-Q1/FY2025/ | F15: a244127f7d114bf3b90c1cd2403b77857961c8d2d81e27c7945f55a9e030b0d4 | G15: Accession 0000063908-25-000025; filed 2025-05-12; package psp_52b253d4e7c24d1a8d9ce36afc225215; raw/source.html SHA-256 shown; prepared/docu
... A20: S016 | B20: SEC 10-Q - McDonald's Corporation 2026 Q2 10-Q | C20: 2026-06-30 | D20: https://www.sec.gov/Archives/edgar/data/63908/000006390826000073/ | E20: sources/companies/US/MCD-mcdonalds/artifacts/ten_k/MCD-mcdonalds-10Q-Q2/FY2026/ | F20: 1f4c9ed2518b2a004ce1289ecf7e3e31f3852580482a24aa96203817914e52d2 | G20: Accession 0000063908-26-000073; filed 2026-08-07; package psp_7f085b8ce86148ada0a6134bd63f3a28; raw/source.html SHA-256 shown; prepared/docu
A22: Extraction method
A23: Collector | B23: collect_tables.py over the 16 raw source.html files -> tables.json (858 tables)
A24: Parser | B24: mcd_extract.py / mcd_extract2.py (statements, segments, KPIs) and mcd_extract3.py / mcd_extract4.py (MD&A operating tables, note schedules, prose series, outlook text) map rows by caption and compact SEC split-cell negatives; no value is typed by hand
A25: Precedence | B25: For a period reported in several filings the latest filing is used; superseded differences > 1.0 are listed in restatement_log.json
A26: Tier discipline | B26: Tier 2 per company-research-to-excel: SEC filing HTML only; no press releases, third-party data or research reports
A28: Restatement / reclassification log (differences > 1.0 between filings)
A29: IS:total_revenues FY2018 | B29: 10-K FY2018: 21,025.2; 10-K FY2019: 21,025.2; 10-K FY2020: 21,257.9 | C29: latest filing used
A30: IS:total_revenues FY2019 | B30: 10-K FY2019: 21,076.5; 10-K FY2020: 21,364.4; 10-K FY2021: 21,364.4 | C30: latest filing used
A31: IS:other_operating FY2018 | B31: 10-K FY2018: -236.8; 10-K FY2019: -236.8; 10-K FY2020: -190.2 | C31: latest filing used
A32: IS:other_operating FY2019 | B32: 10-K FY2019: -183.9; 10-K FY2020: -119.8; 10-K FY2021: -119.8 | C32: latest filing used
A33: IS:total_opex FY2018 | B33: 10-K FY2018: 12,202.6; 10-K FY2019: 12,202.6; 10-K FY2020: 12,435.3 | C33: latest filing used
A34: IS:total_opex FY2019 | B34: 10-K FY2019: 12,006.7; 10-K FY2020: 12,294.6; 10-K FY2021: 12,294.6 | C34: latest filing used
A35: BS:other_lt_liabilities FY2016 | B35: 10-K FY2016: 2,064.3; 10-K FY2017: 1,053.7 | C35: latest filing used
A36: CF:cf_other_charges FY2016 | B36: 10-K FY2016: 96.9; 10-K FY2017: 407.6; 10-K FY2018: 407.6 | C36: latest filing used

Sheet Valuation
A1: 麦当劳估值
A2: 单位：百万美元；预测期间为估值起点之后的完整年度；黄色区域可编辑。
A3: 估值结果 | C3: 两年 | D3: 五年 | F3: 当前情景 | H3: =CHOOSE($C$15,"低情景","基准情景","高情景") -> 基准情景
A4: 年化股东回报率 IRR | C4: =IF(C45="可计算",IFERROR(IRR(C68:E68,0.1),"IRR求解失败"),"待填参数") -> 0.090540718 | D4: =IF(D45="可计算",IFERROR(IRR(C69:H69,0.1),"IRR求解失败"),"待填参数") -> 0.093654283
A5: 目标买入市值（按当前股份） | C5: =IF(AND(C45="可计算",ISNUMBER(C14),C14>-1),SUM(D70:E70)+E71,"待填参数") -> 149971.94 | D5: =IF(AND(D45="可计算",ISNUMBER(C14),C14>-1),SUM(D70:H70)+H71,"待填参数") -> 131493.22 | F5: 现金分红与回购分别处理
A6: 退出价值（按当前持有股份） | C6: =IF(C45="可计算",E65,"待填参数") -> 186497.15 | D6: =IF(D45="可计算",H65,"待填参数") -> 225611.97 | F6: 回购仅通过净缩股提高每股价值
A7: 持有期现金分红（按当前股份） | C7: =IF(C43="可计算",SUM(D61:E61),"待填参数") -> 11026.075 | D7: =IF(D43="可计算",SUM(D61:H61),"待填参数") -> 29153.99 | F7: 基准参数初始化为历史参考，尚非预测
A8: 退出市盈率 PE | C8: =IF(ISNUMBER(C38),C38,"待填退出PE") -> 20 | D8: =IF(ISNUMBER(D38),D38,"待填退出PE") -> 20 | F8: 退出PE直接输入，缩股另行计算
A9: 回购调整后的每股盈利 CAGR | C9: =IF(C43="可计算",(E59/C59)^(1/2)-1,"待填参数") -> 0.030150754 | D9: =IF(D43="可计算",(H59/C59)^(1/5)-1,"待填参数") -> 0.051231347 | F9: 结果按年度末收款与缩股近似
A11: 估值起点与控制项
A12: 当前总市值 | C12: 166500 | E12: 必填：输入估值日总市值，单位百万美元
A13: 基期净利润 | C13: 8787 | E13: 已链接2026Q2 TTM净利润；可替换为正常化基期利润
A14: 要求年化回报率 | C14: 0.15 | E14: 用于目标买入市值；10%为可调整的演示要求
A15: 情景选择（1低 / 2基准 / 3高） | C15: 2 | E15: 修改此选择，使用同一套逐年计算切换情景
A16: 估值日期 | C16: 46305 | E16: 市值与日期需同步更新；不自动联网更新行情
A18: 参数假设：前两年与第三至第五年分别设置
A19: 基准初始化采用历史锚点；请将其替换为研究预测。低/高情景留空，未填情景不会影响已填情景。
A21: 参数与情景 | C21: 前两年 | D21: 第三至第五年 | E21: 单位 | F21: 历史参考 | G21: 参数定义
A22: 公司总净利润增速 g | C22: =IF(ISNUMBER(CHOOSE($C$15,C23,C24,C25)),CHOOSE($C$15,C23,C24,C25),"待填参数") -> 0.025 | D22: =IF(ISNUMBER(CHOOSE($C$15,D23,D24,D25)),CHOOSE($C$15,D23,D24,D25),"待填参数") -> 0.057 | E22: % | F22: =('Income Statement'!L41/'Income Statement'!F41)^(1/6)-1 -> 0.060327463
A23: 低情景
A24: 基准情景 | C24: 0.025 | D24: 0.057
A25: 高情景
A26: 净缩股速率 s | C26: =IF(ISNUMBER(CHOOSE($C$15,C27,C28,C29)),CHOOSE($C$15,C27,C28,C29),"待填参数") -> 0.005 | D26: =IF(ISNUMBER(CHOOSE($C$15,D27,D28,D29)),CHOOSE($C$15,D27,D28,D29),"待填参数") -> 0.008 | E26: % | F26: =1-C90/C89 -> 0.0084033613
A27: 低情景
A28: 基准情景 | C28: 0.005 | D28: 0.008 | G28: 正值为缩股；负值为净摊薄
A29: 高情景 | G29: 已包含股权激励等净影响；数据取整
A30: FCF转换率 c | C30: =IF(ISNUMBER(CHOOSE($C$15,C31,C32,C33)),CHOOSE($C$15,C31,C32,C33),"待填参数") -> 0.82 | D30: =IF(ISNUMBER(CHOOSE($C$15,D31,D32,D33)),CHOOSE($C$15,D31,D32,D33),"待填参数") -> 0.86 | E30: % | F30: =(SUM('Cash Flow'!J28:L28)+SUM('Cash Flow'!J31:L31))/SUM('Income Statement'!J41:L41) -> 0.83599287
A31: 低情景
A32: 基准情景 | C32: 0.82 | D32: 0.86
A33: 高情景
A34: 现金分红支付率 p | C34: =IF(ISNUMBER(CHOOSE($C$15,C35,C36,C37)),CHOOSE($C$15,C35,C36,C37),"待填参数") -> 0.6 | D34: =IF(ISNUMBER(CHOOSE($C$15,D35,D36,D37)),CHOOSE($C$15,D35,D36,D37),"待填参数") -> 0.57 | E34: % | F34: =-SUM('Cash Flow'!J45:L45)/SUM('Income Statement'!J41:L41) -> 0.57485646
A35: 低情景
A36: 基准情景 | C36: 0.6 | D36: 0.57 | G36: 只含现金分红；不含回购
A37: 高情景
A38: 退出市盈率 PE | C38: =IF(ISNUMBER(CHOOSE($C$15,C39,C40,C41)),CHOOSE($C$15,C39,C40,C41),"待填参数") -> 20 | D38: =IF(ISNUMBER(CHOOSE($C$15,D39,D40,D41)),CHOOSE($C$15,D39,D40,D41),"待填参数") -> 20 | E38: 倍 | F38: 待提供
A39: 低情景
A40: 基准情景 | C40: 20 | D40: 20 | G40: 输入25，即按25倍退出PE估值
A41: 高情景 | G41: 净缩股速率自动调整每股价值
A43: 利润与股数计算状态 | C43: =IF(COUNT(C13,C22,C26,C34)<4,"待填经营参数",IF(AND(C13>0,C22>-1,C26<1,C34>=0),"可计算","参数无效")) -> 可计算 | D43: =IF(OR(C43<>"可计算",COUNT(D22,D26,D34)<3),"待填经营参数",IF(AND(D22>-1,D26<1,D34>=0),"可计算","参数无效")) -> 可计算
A45: 估值计算状态 | C45: =IF(C43<>"可计算",C43,IF(COUNT(C12,C38)<2,"待填市值/退出PE",IF(AND(C12>0,C38>0),"可计算","参数无效"))) -> 可计算 | D45: =IF(D43<>"可计算",D43,IF(COUNT(C12,D38)<2,"待填市值/退出PE",IF(AND(C12>0,D38>0),"可计算","参数无效"))) -> 可计算
A47: 逐年计算：公司利润、流通股数与当前股东权益
C49: 基期 | D49: 第1年 | E49: 第2年 | F49: 第3年 | G49: 第4年 | H49: 第5年
A50: 年度序号 | C50: 0 | D50: 1 | E50: 2 | F50: 3 | G50: 4 | H50: 5
A51: 公司净利润增速 | D51: =C22 -> 0.025 | E51: =C22 -> 0.025 | F51: =D22 -> 0.057 | G51: =D22 -> 0.057 | H51: =D22 -> 0.057
A52: 净缩股速率 | D52: =C26 -> 0.005 | E52: =C26 -> 0.005 | F52: =D26 -> 0.008 | G52: =D26 -> 0.008 | H52: =D26 -> 0.008
A53: 现金分红支付率 | D53: =C34 -> 0.6 | E53: =C34 -> 0.6 | F53: =D34 -> 0.57 | G53: =D34 -> 0.57 | H53: =D34 -> 0.57
A54: FCF转换率 | D54: =C30 -> 0.82 | E54: =C30 -> 0.82 | F54: =D30 -> 0.86 | G54: =D30 -> 0.86 | H54: =D30 -> 0.86
A55: 退出市盈率 PE | D55: =C38 -> 20 | E55: =C38 -> 20 | F55: =D38 -> 20 | G55: =D38 -> 20 | H55: =D38 -> 20
A57: 公司总净利润 | C57: =C13 -> 8787 | D57: =IF($C$43="可计算",C57*(1+D51),"待填参数") -> 9006.675 | E57: =IF($C$43="可计算",D57*(1+E51),"待填参数") -> 9231.8419 | F57: =IF($D$43="可计算",E57*(1+F51),"待填参数") -> 9758.0569 | G57: =IF($D$43="可计算",F57*(1+G51),"待填参数") -> 10314.266 | H57: =IF($D$43="可计算",G57*(1+H51),"待填参数") -> 10902.179
A58: 流通股数指数（基期=100） | C58: 100 | D58: =IF($C$43="可计算",C58*(1-D52),"待填参数") -> 99.5 | E58: =IF($C$43="可计算",D58*(1-E52),"待填参数") -> 99.0025 | F58: =IF($D$43="可计算",E58*(1-F52),"待填参数") -> 98.21048 | G58: =IF($D$43="可计算",F58*(1-G52),"待填参数") -> 97.424796 | H58: =IF($D$43="可计算",G58*(1-H52),"待填参数") -> 96.645398
A59: 净利润（按当前股份折算） | C59: =C57 -> 8787 | D59: =IF($C$43="可计算",D57/(D58/$C$58),"待填参数") -> 9051.9347 | E59: =IF($C$43="可计算",E57/(E58/$C$58),"待填参数") -> 9324.8573 | F59: =IF($D$43="可计算",F57/(F58/$C$58),"待填参数") -> 9935.8611 | G59: =IF($D$43="可计算",G57/(G58/$C$58),"待填参数") -> 10586.9 | H59: =IF($D$43="可计算",H57/(H58/$C$58),"待填参数") -> 11280.598
A60: 公司现金分红总额 | D60: =IF($C$43="可计算",D57*D53,"待填参数") -> 5404.005 | E60: =IF($C$43="可计算",E57*E53,"待填参数") -> 5539.1051 | F60: =IF($D$43="可计算",F57*F53,"待填参数") -> 5562.0924 | G60: =IF($D$43="可计算",G57*G53,"待填参数") -> 5879.1317 | H60: =IF($D$43="可计算",H57*H53,"待填参数") -> 6214.2422
A61: 现金分红（按当前股份折算） | D61: =IF($C$43="可计算",D60/(D58/$C$58),"待填参数") -> 5431.1608 | E61: =IF($C$43="可计算",E60/(E58/$C$58),"待填参数") -> 5594.9144 | F61: =IF($D$43="可计算",F60/(F58/$C$58),"待填参数") -> 5663.4408 | G61: =IF($D$43="可计算",G60/(G58/$C$58),"待填参数") -> 6034.5332 | H61: =IF($D$43="可计算",H60/(H58/$C$58),"待填参数") -> 6429.9411
A62: 公司FCF参考 | D62: =IF(AND($C$43="可计算",ISNUMBER(D54),D54>0),D57*D54,"待填转换率") -> 7385.4735 | E62: =IF(AND($C$43="可计算",ISNUMBER(E54),E54>0),E57*E54,"待填转换率") -> 7570.1103 | F62: =IF(AND($D$43="可计算",ISNUMBER(F54),F54>0),F57*F54,"待填转换率") -> 8391.9289 | G62: =IF(AND($D$43="可计算",ISNUMBER(G54),G54>0),G57*G54,"待填转换率") -> 8870.2688 | H62: =IF(AND($D$43="可计算",ISNUMBER(H54),H54>0),H57*H54,"待填转换率") -> 9375.8742
A63: 公司FCF扣除分红后余额 | D63: =IF(ISNUMBER(D62),D62-D60,"待填参数") -> 1981.4685 | E63: =IF(ISNUMBER(E62),E62-E60,"待填参数") -> 2031.0052 | F63: =IF(ISNUMBER(F62),F62-F60,"待填参数") -> 2829.8365 | G63: =IF(ISNUMBER(G62),G62-G60,"待填参数") -> 2991.1372 | H63: =IF(ISNUMBER(H62),H62-H60,"待填参数") -> 3161.632
A64: 公司整体退出市值 | D64: =IF(AND($C$43="可计算",ISNUMBER(D55),D55>0),D57*D55,"待填参数") -> 180133.5 | E64: =IF(AND($C$43="可计算",ISNUMBER(E55),E55>0),E57*E55,"待填参数") -> 184636.84 | F64: =IF(AND($D$43="可计算",ISNUMBER(F55),F55>0),F57*F55,"待填参数") -> 195161.14 | G64: =IF(AND($D$43="可计算",ISNUMBER(G55),G55>0),G57*G55,"待填参数") -> 206285.32 | H64: =IF(AND($D$43="可计算",ISNUMBER(H55),H55>0),H57*H55,"待填参数") -> 218043.59
A65: 退出价值（按当前股份折算） | D65: =IF(ISNUMBER(D64),D64/(D58/$C$58),"待填参数") -> 181038.69 | E65: =IF(ISNUMBER(E64),E64/(E58/$C$58),"待填参数") -> 186497.15 | F65: =IF(ISNUMBER(F64),F64/(F58/$C$58),"待填参数") -> 198717.22 | G65: =IF(ISNUMBER(G64),G64/(G58/$C$58),"待填参数") -> 211738.01 | H65: =IF(ISNUMBER(H64),H64/(H58/$C$58),"待填参数") -> 225611.97
A68: 两年：投资现金流 | C68: =IF(C45="可计算",-C12,"待填参数") -> -166500 | D68: =IF($C$45="可计算",D61,"待填参数") -> 5431.1608 | E68: =IF($C$45="可计算",E61+E65,"待填参数") -> 192092.06 | F68: =0 -> 0 | G68: =0 -> 0 | H68: =0 -> 0
A69: 五年：投资现金流 | C69: =IF(D45="可计算",-C12,"待填参数") -> -166500 | D69: =IF($D$45="可计算",D61,"待填参数") -> 5431.1608 | E69: =IF($D$45="可计算",E61,"待填参数") -> 5594.9144 | F69: =IF($D$45="可计算",F61,"待填参数") -> 5663.4408 | G69: =IF($D$45="可计算",G61,"待填参数") -> 6034.5332 | H69: =IF($D$45="可计算",H61+H65,"待填参数") -> 232041.91
