Workbook

Sheet Cover
A1: The Coca-Cola Company — Cover
A2: $ in millions except per-share data | USD | as of 2026-10-14
A4: The Coca-Cola Company (NYSE: KO)
A6: Ticker / exchange | B6: KO / NYSE
A7: CIK | B7: 0000021344
A8: Reporting framework | B8: US GAAP, consolidated
A9: Currency / units | B9: USD; $ in millions except per-share data
A10: Fiscal year end | B10: December 31 (10-Q quarters end on the Friday nearest the calendar quarter end)
A11: Annual window | B11: FY2016-FY2025 (ten 10-Ks)
A12: Quarterly window | B12: 3Q2024, 1Q2025, 2Q2025, 3Q2025, 1Q2026, 2Q2026 (six 10-Qs; no 4Q columns because a 10-K is not a quarterly filing)
A13: Latest covered period | B13: 2Q2026 (quarter ended July 3, 2026; 10-Q filed 2026-07-29)
A14: Workbook date | B14: 2026-10-14 (reviewed; original export 2026-10-13)
A16: Sheet directory
A17: Income Statement (IS) | B17: As-reported income statement, growth/margin rows, six tie-out checks
A18: Balance Sheet (BS) | B18: As-reported balance sheet, eight tie-out checks, working-capital days
A19: Cash Flow (CF) | B19: As-reported cash flow statement (quarterly columns are fiscal year-to-date), four checks, FCF and shareowner-return analytics
A20: Segments (SEG) | B20: Three segment bases kept separate (A: FY2016-FY2018, B: FY2017-FY2024, C: FY2023-FY2025), each tied to consolidated totals
A21: Geography (GEO) | B21: US / International net operating revenues and PP&E
A22: Derived Metrics (DM) | B22: Live formulas from verified IS/BS/CF and segment D&A; annual and selected discrete-quarter ratios. Cash-flow ratios retain annual coverage where quarterly inputs are cumulative.
A23: Sources | B23: Filing accessions, file paths, SHA-256, annual-column provenance, restatement log
A25: Colour legend
A26: Blue font | B26: Hard-coded value copied from a filing
A27: Black font | B27: Formula
A28: Green font | B28: Cross-sheet link
A29: Grey italic | B29: Memo / analytic row
A31: How annual columns were sourced
A32: Income statement and cash flow | B32: Each fiscal year is taken from the 10-K filed two years later (or the FY2025 10-K for FY2024 and FY2025), so later reclassifications are reflected. The first-filed value is compared with the value used in the Sources sheet.
A33: Balance sheet | B33: Each year-end is taken from the 10-K for the following year (the FY2025 10-K for FY2025), i.e. the later comparative column.
A34: Quarterly | B34: IS: three-month column of each 10-Q. BS: period-end balance of each 10-Q. CF: fiscal year-to-date column of each 10-Q (Q1 = 3 months, Q2 = 6 months, Q3 = 9 months).
A36: Comparability notes
A37: Sign convention | B37: Income-statement expenses are shown positive as filed (cost of goods sold, SG&A, interest expense, income taxes). Cash-flow outflows are negative as filed.
A38: Discontinued operations | B38: FY2016-FY2018 filings present a discontinued-operations line (FY2017-FY2018). The latest filing presenting each year is used, so FY2017 and FY2018 follow the FY2019 and FY2020 10-K presentation.
A39: Recast years | B39: Later 10-Ks recast earlier years: FY2016 operating income (FY2018 10-K), FY2017 and FY2018 net operating revenues and operating income (FY2019 and FY2020 10-Ks), and operating cash flow for FY2016-FY2018. FY2016 is on the older pre-recast basis because no later 10-K presents it; FY2016-to-FY2017 growth rates therefore mix bases. The differences are listed in the Sources sheet; the cause is not analysed here.
A40: Caption changes | B40: FY2021 onward: 'prepaid expenses and other current assets', 'other noncurrent assets/liabilities' replace earlier captions; debt issuance/payment captions were renamed in the FY2023 10-K with identical values. Equivalent lines share one row.
A41: Segments | B41: KO re-segmented in the FY2019 10-K (Global Ventures added) and again in the FY2025 10-K (Global Ventures dissolved). Segment series are not stitched across bases. The FY2025 10-K recast covers FY2023-FY2025 only.
A42: Fiscal 2025 events | B42: Large FY2024 'Other operating charges' and FY2024-FY2025 cash-flow movements relate to the IRS tax litigation deposit and the settlement of the fairlife contingent consideration (see 10-K notes). The workbook does not adjust them.
A44: Not built in this pass
A45: Valuation / forecast sheets | B45: Excluded by instruction.
A46: Operating Metrics and Note Schedules coverage | B46: Built and verified: volume, revenue factors, line of business, debt, income taxes, equity-method investees, and assets/liabilities held for sale. Standalone BS Detail remains absent.
A47: Non-GAAP bridge | B47: Not built: KO's comparable (non-GAAP) measures are in the 8-K earnings releases and IR schedules acquired in the research package; they are not included here.
A48: Quarterly gaps | B48: 4Q2024/4Q2025 are not separately derived. Quarterly YoY growth is shown only for matching periods present in the workbook. Undisclosed inputs remain blank; explicit N/A remains N/A.
A50: Scope
B51: Data-preparation workbook only. No investment thesis, valuation, target price or recommendation.
A53: Review 2026-10-14 | B53: See Audit 2026-10-14 for source-cell checks and change log. Original workbook preserved; source numbers verified against SEC raw HTML after excluding superscript footnotes.
A54: Operating Metrics | B54: FY2016-FY2025 volume growth and six disclosed quarters; omitted Asia Pacific / Global Ventures concentrate-sales rows restored. Global Ventures comparative FY2018 follows FY2019 disclosure basis.
A55: Note Schedules | B55: FY2025 equity-investment carrying values / differences / totals restored as a supplement; original fair values retained.

Sheet Income Statement
A1: The Coca-Cola Company — Income Statement
A2: $ in millions except per-share data | USD | as of 2026-10-14
C3: FY2016 | D3: FY2017 | E3: FY2018 | F3: FY2019 | G3: FY2020 | H3: FY2021 | I3: FY2022 | J3: FY2023 | K3: FY2024 | L3: FY2025 | M3: · | N3: · | O3: · | P3: 3Q2024 | Q3: 1Q2025 | R3: 2Q2025 | S3: 3Q2025 | T3: 1Q2026 | U3: 2Q2026
C4: 2016-12-31 | D4: 2017-12-31 | E4: 2018-12-31 | F4: 2019-12-31 | G4: 2020-12-31 | H4: 2021-12-31 | I4: 2022-12-31 | J4: 2023-12-31 | K4: 2024-12-31 | L4: 2025-12-31 | P4: 2024-09-27 | Q4: 2025-03-28 | R4: 2025-06-27 | S4: 2025-09-26 | T4: 2026-04-03 | U4: 2026-07-03
A6: CONTENTS
A7: =HYPERLINK("#'Income Statement'!A10","1. INCOME STATEMENT — AS REPORTED (expenses shown positive, as filed)") -> 1. INCOME STATEMENT — AS REPORTED (expenses shown positive, as filed)
A8: =HYPERLINK("#'Income Statement'!A47","2. CHECKS") -> 2. CHECKS
A10: 1. INCOME STATEMENT — AS REPORTED (expenses shown positive, as filed)
A11: Net Operating Revenues | C11: 41863 | D11: 36212 | E11: 34300 | F11: 37266 | G11: 33014 | H11: 38655 | I11: 43004 | J11: 45754 | K11: 47061 | L11: 47941 | P11: 11854 | Q11: 11129 | R11: 12535 | S11: 12455 | T11: 12472 | U11: 13380
A12: YoY Growth | D12: =IF(N(C11)=0,"",D11/C11-1) -> -0.13498794 | E12: =IF(N(D11)=0,"",E11/D11-1) -> -0.052800177 | F12: =IF(N(E11)=0,"",F11/E11-1) -> 0.086472303 | G12: =IF(N(F11)=0,"",G11/F11-1) -> -0.11409864 | H12: =IF(N(G11)=0,"",H11/G11-1) -> 0.1708669 | I12: =IF(N(H11)=0,"",I11/H11-1) -> 0.11250808 | J12: =IF(N(I11)=0,"",J11/I11-1) -> 0.06394754 | K12: =IF(N(J11)=0,"",K11/J11-1) -> 0.028565808 | L12: =IF(N(K11)=0,"",L11/K11-1) -> 0.018699135
A13: Cost of goods sold | C13: 16465 | D13: 13721 | E13: 13067 | F13: 14619 | G13: 13433 | H13: 15357 | I13: 18000 | J13: 18520 | K13: 18324 | L13: 18397 | P13: 4664 | Q13: 4163 | R13: 4714 | S13: 4797 | T13: 4620 | U13: 4965
A14: Gross Profit | C14: 25398 | D14: 22491 | E14: 21233 | F14: 22647 | G14: 19581 | H14: 23298 | I14: 25004 | J14: 27234 | K14: 28737 | L14: 29544 | P14: 7190 | Q14: 6966 | R14: 7821 | S14: 7658 | T14: 7852 | U14: 8415
A15: Gross Margin | C15: =C14/C11 -> 0.60669326 | D15: =D14/D11 -> 0.62109246 | E15: =E14/E11 -> 0.6190379 | F15: =F14/F11 -> 0.60771212 | G15: =G14/G11 -> 0.59311201 | H15: =H14/H11 -> 0.60271634 | I15: =I14/I11 -> 0.58143429 | J15: =J14/J11 -> 0.59522665 | ... L15: =L14/L11 -> 0.61625748 | P15: =P14/P11 -> 0.60654631 | Q15: =Q14/Q11 -> 0.62593225 | R15: =R14/R11 -> 0.62393299 | S15: =S14/S11 -> 0.61485347 | T15: =T14/T11 -> 0.62957024 | U15: =U14/U11 -> 0.62892377
A16: Selling, general and administrative expenses | C16: 15370 | D16: 12834 | E16: 11002 | F16: 12103 | G16: 9731 | H16: 12144 | I16: 12880 | J16: 13972 | K16: 14582 | L16: 14521 | P16: 3636 | Q16: 3234 | R16: 3470 | S16: 3618 | T16: 3472 | U16: 3720
A17: Other operating charges | C17: 1371 | D17: 1902 | E17: 1079 | F17: 458 | G17: 853 | H17: 846 | I17: 1215 | J17: 1951 | K17: 4163 | L17: 1261 | P17: 1044 | Q17: 73 | R17: 71 | S17: 58 | T17: 21 | U17: 23
A18: Operating Income | C18: 8657 | D18: 7755 | E18: 9152 | F18: 10086 | G18: 8997 | H18: 10308 | I18: 10909 | J18: 11311 | K18: 9992 | L18: 13762 | P18: 2510 | Q18: 3659 | R18: 4280 | S18: 3982 | T18: 4359 | U18: 4672
A19: Operating Margin | C19: =C18/C11 -> 0.20679359 | D19: =D18/D11 -> 0.21415553 | E19: =E18/E11 -> 0.26682216 | F19: =F18/F11 -> 0.27064885 | G19: =G18/G11 -> 0.27252075 | H19: =H18/H11 -> 0.26666667 | I19: =I18/I11 -> 0.25367408 | J19: =J18/J11 -> 0.24721336 | ... L19: =L18/L11 -> 0.28706118 | P19: =P18/P11 -> 0.21174287 | Q19: =Q18/Q11 -> 0.32878066 | R19: =R18/R11 -> 0.34144396 | S19: =S18/S11 -> 0.31971096 | T19: =T18/T11 -> 0.34950289 | U19: =U18/U11 -> 0.34917788
A20: YoY Growth | D20: =IF(N(C18)=0,"",D18/C18-1) -> -0.10419314 | E20: =IF(N(D18)=0,"",E18/D18-1) -> 0.18014184 | F20: =IF(N(E18)=0,"",F18/E18-1) -> 0.1020542 | G20: =IF(N(F18)=0,"",G18/F18-1) -> -0.10797145 | H20: =IF(N(G18)=0,"",H18/G18-1) -> 0.14571524 | I20: =IF(N(H18)=0,"",I18/H18-1) -> 0.05830423 | J20: =IF(N(I18)=0,"",J18/I18-1) -> 0.036850307 | K20: =IF(N(J18)=0,"",K18/J18-1) -> -0.11661215 | L20: =IF(N(K18)=0,"",L18/K18-1) -> 0.37730184
A21: Interest income | C21: 642 | D21: 679 | E21: 689 | F21: 563 | G21: 370 | H21: 276 | I21: 449 | J21: 907 | K21: 988 | L21: 786 | P21: 263 | Q21: 180 | R21: 188 | S21: 185 | T21: 222 | U21: 198
A22: Interest expense | C22: 733 | D22: 853 | E22: 950 | F22: 946 | G22: 1437 | H22: 1597 | I22: 882 | J22: 1527 | K22: 1656 | L22: 1654 | P22: 425 | Q22: 387 | R22: 445 | S22: 391 | T22: 375 | U22: 369
A23: Equity income (loss) — net | C23: 835 | D23: 1072 | E23: 1008 | F23: 1049 | G23: 978 | H23: 1438 | I23: 1472 | J23: 1691 | K23: 1770 | L23: 2031 | P23: 541 | Q23: 351 | R23: 561 | S23: 644 | T23: 384 | U23: 604
A24: Other income (loss) — net | C24: -1265 | D24: -1763 | E24: -1674 | F24: 34 | G24: 841 | H24: 2000 | I24: -262 | J24: 570 | K24: 1992 | L24: 1073 | P24: 491 | Q24: 254 | R24: 212 | S24: -237 | T24: 21 | U24: 370
A25: Income Before Income Taxes | B25: FY2016 from the FY2018 10-K: income from continuing operations before income taxes. | C25: 8136 | D25: 6890 | E25: 8225 | F25: 10786 | G25: 9749 | H25: 12425 | I25: 11686 | J25: 12952 | K25: 13086 | L25: 15998 | P25: 3380 | Q25: 4057 | R25: 4796 | S25: 4183 | T25: 4611 | U25: 5475
A26: Income taxes | C26: 1586 | D26: 5607 | E26: 1749 | F26: 1801 | G26: 1981 | H26: 2621 | I26: 2115 | J26: 2249 | K26: 2437 | L26: 2861 | P26: 530 | Q26: 722 | R26: 993 | S26: 500 | T26: 645 | U26: 1037
A27: Effective Tax Rate | C27: =C26/C25 -> 0.19493609 | D27: =D26/D25 -> 0.8137881 | E27: =E26/E25 -> 0.21264438 | F27: =F26/F25 -> 0.16697571 | G27: =G26/G25 -> 0.20320033 | H27: =H26/H25 -> 0.21094567 | I27: =I26/I25 -> 0.18098579 | J27: =J26/J25 -> 0.17364114 | ... L27: =L26/L25 -> 0.17883485 | P27: =P26/P25 -> 0.15680473 | Q27: =Q26/Q25 -> 0.17796401 | R27: =R26/R25 -> 0.20704754 | S27: =S26/S25 -> 0.11953144 | T27: =T26/T25 -> 0.13988289 | U27: =U26/U25 -> 0.18940639
A28: Net income from continuing operations | C28: 6550
A29: Income (loss) from discontinued operations, net of income taxes | B29: Shown only where the latest filing presenting the year reports it. | C29: 0
A30: Consolidated Net Income | C30: 6550 | D30: 1283 | E30: 6476 | F30: 8985 | G30: 7768 | H30: 9804 | I30: 9571 | J30: 10703 | K30: 10649 | L30: 13137 | P30: 2850 | Q30: 3335 | R30: 3803 | S30: 3683 | T30: 3966 | U30: 4438
A31: Less: Net income (loss) attributable to noncontrolling interests | C31: 23 | D31: 35 | E31: 42 | F31: 65 | G31: 21 | H31: 33 | I31: 29 | J31: -11 | K31: 18 | L31: 30 | P31: 2 | Q31: 5 | R31: -7 | S31: -13 | T31: 42 | U31: 13
A32: Net Income Attributable to Shareowners of The Coca-Cola Company | C32: 6527 | D32: 1248 | E32: 6434 | F32: 8920 | G32: 7747 | H32: 9771 | I32: 9542 | J32: 10714 | K32: 10631 | L32: 13107 | P32: 2848 | Q32: 3330 | R32: 3810 | S32: 3696 | T32: 3924 | U32: 4425
A33: Net Margin (attributable) | C33: =C32/C11 -> 0.15591334 | D33: =D32/D11 -> 0.034463714 | E33: =E32/E11 -> 0.18758017 | F33: =F32/F11 -> 0.23936027 | G33: =G32/G11 -> 0.23465802 | H33: =H32/H11 -> 0.25277454 | I33: =I32/I11 -> 0.22188634 | J33: =J32/J11 -> 0.23416532 | ... L33: =L32/L11 -> 0.27339855 | P33: =P32/P11 -> 0.24025645 | Q33: =Q32/Q11 -> 0.29921826 | R33: =R32/R11 -> 0.30394894 | S33: =S32/S11 -> 0.29674829 | T33: =T32/T11 -> 0.31462476 | U33: =U32/U11 -> 0.33071749
A34: YoY Growth | D34: =IF(N(C32)=0,"",D32/C32-1) -> -0.80879424 | E34: =IF(N(D32)=0,"",E32/D32-1) -> 4.1554487 | F34: =IF(N(E32)=0,"",F32/E32-1) -> 0.38638483 | G34: =IF(N(F32)=0,"",G32/F32-1) -> -0.13150224 | H34: =IF(N(G32)=0,"",H32/G32-1) -> 0.26126242 | I34: =IF(N(H32)=0,"",I32/H32-1) -> -0.0234367 | J34: =IF(N(I32)=0,"",J32/I32-1) -> 0.1228254 | K34: =IF(N(J32)=0,"",K32/J32-1) -> -0.0077468732 | L34: =IF(N(K32)=0,"",L32/K32-1) -> 0.23290377
A35: Basic net income per share from continuing operations | C35: 1.51
A36: Basic net income per share from discontinued operations
A37: Basic net income (loss) per share from discontinued operations | C37: 0
A38: Basic Net Income Per Share | C38: 1.51 | D38: 0.29 | E38: 1.51 | F38: 2.09 | G38: 1.8 | H38: 2.26 | I38: 2.2 | J38: 2.48 | K38: 2.47 | L38: 3.05 | P38: 0.66 | Q38: 0.77 | R38: 0.89 | S38: 0.86 | T38: 0.91 | U38: 1.03
A39: Diluted net income per share from continuing operations | C39: 1.49
A40: Diluted net income per share from discontinued operations
A41: Diluted net income (loss) per share from discontinued operations | C41: 0
A42: Diluted Net Income Per Share | C42: 1.49 | D42: 0.29 | E42: 1.5 | F42: 2.07 | G42: 1.79 | H42: 2.25 | I42: 2.19 | J42: 2.47 | K42: 2.46 | L42: 3.04 | P42: 0.66 | Q42: 0.77 | R42: 0.88 | S42: 0.86 | T42: 0.91 | U42: 1.03
A43: Average Shares Outstanding — Basic | C43: 4317 | D43: 4272 | E43: 4259 | F43: 4276 | G43: 4295 | H43: 4315 | I43: 4328 | J43: 4323 | K43: 4309 | L43: 4303 | P43: 4311 | Q43: 4302 | R43: 4304 | S43: 4303 | T43: 4302 | U43: 4303
A44: Effect of dilutive securities | C44: 50 | D44: 52 | E44: 40 | F44: 38 | G44: 28 | H44: 25 | I44: 22 | J44: 16 | K44: 11 | L44: 10 | P44: 12 | Q44: 11 | R44: 11 | S44: 10 | T44: 12 | U44: 10
A45: Average Shares Outstanding — Diluted | C45: 4367 | D45: 4324 | E45: 4299 | F45: 4314 | G45: 4323 | H45: 4340 | I45: 4350 | J45: 4339 | K45: 4320 | L45: 4313 | P45: 4323 | Q45: 4313 | R45: 4315 | S45: 4313 | T45: 4314 | U45: 4313
A47: 2. CHECKS
A48: Check: Revenue - COGS - Gross profit (≈0) | C48: =C11-C13-C14 -> 0 | D48: =D11-D13-D14 -> 0 | E48: =E11-E13-E14 -> 0 | F48: =F11-F13-F14 -> 0 | G48: =G11-G13-G14 -> 0 | H48: =H11-H13-H14 -> 0 | I48: =I11-I13-I14 -> 0 | J48: =J11-J13-J14 -> 0 | ... L48: =L11-L13-L14 -> 0 | P48: =P11-P13-P14 -> 0 | Q48: =Q11-Q13-Q14 -> 0 | R48: =R11-R13-R14 -> 0 | S48: =S11-S13-S14 -> 0 | T48: =T11-T13-T14 -> 0 | U48: =U11-U13-U14 -> 0
A49: Check: Gross profit - SG&A - other charges - Op. income (≈0) | C49: =C14-C16-C17-C18 -> 0 | D49: =D14-D16-D17-D18 -> 0 | E49: =E14-E16-E17-E18 -> 0 | F49: =F14-F16-F17-F18 -> 0 | G49: =G14-G16-G17-G18 -> 0 | H49: =H14-H16-H17-H18 -> 0 | I49: =I14-I16-I17-I18 -> 0 | J49: =J14-J16-J17-J18 -> 0 | ... L49: =L14-L16-L17-L18 -> 0 | P49: =P14-P16-P17-P18 -> 0 | Q49: =Q14-Q16-Q17-Q18 -> 0 | R49: =R14-R16-R17-R18 -> 0 | S49: =S14-S16-S17-S18 -> 0 | T49: =T14-T16-T17-T18 -> 0 | U49: =U14-U16-U17-U18 -> 0
A50: Check: Operating income to pre-tax income bridge (≈0) | C50: =C18+C21-C22+C23+C24-C25 -> 0 | D50: =D18+D21-D22+D23+D24-D25 -> 0 | E50: =E18+E21-E22+E23+E24-E25 -> 0 | F50: =F18+F21-F22+F23+F24-F25 -> 0 | G50: =G18+G21-G22+G23+G24-G25 -> 0 | H50: =H18+H21-H22+H23+H24-H25 -> 0 | I50: =I18+I21-I22+I23+I24-I25 -> 0 | J50: =J18+J21-J22+J23+J24-J25 -> 0 | ... L50: =L18+L21-L22+L23+L24-L25 -> 0 | P50: =P18+P21-P22+P23+P24-P25 -> 0 | Q50: =Q18+Q21-Q22+Q23+Q24-Q25 -> 0 | R50: =R18+R21-R22+R23+R24-R25 -> 0 | S50: =S18+S21-S22+S23+S24-S25 -> 0 | T50: =T18+T21-T22+T23+T24-T25 -> 0 | U50: =U18+U21-U22+U23+U24-U25 -> 0
A51: Check: EBT - income taxes - consolidated net income (≈0) | C51: =C25-C26-C30 -> 0 | D51: =D25-D26-D30 -> 0 | E51: =E25-E26-E30 -> 0 | F51: =F25-F26-F30 -> 0 | G51: =G25-G26-G30 -> 0 | H51: =H25-H26-H30 -> 0 | I51: =I25-I26-I30 -> 0 | J51: =J25-J26-J30 -> 0 | ... L51: =L25-L26-L30 -> 0 | P51: =P25-P26-P30 -> 0 | Q51: =Q25-Q26-Q30 -> 0 | R51: =R25-R26-R30 -> 0 | S51: =S25-S26-S30 -> 0 | T51: =T25-T26-T30 -> 0 | U51: =U25-U26-U30 -> 0
A52: Check: Consolidated NI - NCI - NI attributable (≈0) | C52: =C30-C31-C32 -> 0 | D52: =D30-D31-D32 -> 0 | E52: =E30-E31-E32 -> 0 | F52: =F30-F31-F32 -> 0 | G52: =G30-G31-G32 -> 0 | H52: =H30-H31-H32 -> 0 | I52: =I30-I31-I32 -> 0 | J52: =J30-J31-J32 -> 0 | ... L52: =L30-L31-L32 -> 0 | P52: =P30-P31-P32 -> 0 | Q52: =Q30-Q31-Q32 -> 0 | R52: =R30-R31-R32 -> 0 | S52: =S30-S31-S32 -> 0 | T52: =T30-T31-T32 -> 0 | U52: =U30-U31-U32 -> 0
A53: Check: NI attributable / diluted shares - diluted EPS (rounding, ≈0) | C53: =C32/C45-C42 -> 0.0046187314 | D53: =D32/D45-D42 -> -0.0013783534 | E53: =E32/E45-E42 -> -0.0033728774 | F53: =F32/F45-F42 -> -0.0023133982 | G53: =G32/G45-G42 -> 0.002042563 | H53: =H32/H45-H42 -> 0.0013824885 | I53: =I32/I45-I42 -> 0.0035632184 | J53: =J32/J45-J42 -> -0.00076745794 | ... L53: =L32/L45-L42 -> -0.0010479944 | P53: =P32/P45-P42 -> -0.001198242 | Q53: =Q32/Q45-Q42 -> 0.002084396 | R53: =R32/R45-R42 -> 0.0029663963 | S53: =S32/S45-S42 -> -0.0030558776 | T53: =T32/T45-T42 -> -0.00040333797 | U53: =U32/U45-U42 -> -0.0040319963

Sheet Balance Sheet
A1: The Coca-Cola Company — Balance Sheet
A2: $ in millions except per-share data | USD | as of 2026-10-14
C3: FY2016 | D3: FY2017 | E3: FY2018 | F3: FY2019 | G3: FY2020 | H3: FY2021 | I3: FY2022 | J3: FY2023 | K3: FY2024 | L3: FY2025 | M3: · | N3: · | O3: · | P3: 3Q2024 | Q3: 1Q2025 | R3: 2Q2025 | S3: 3Q2025 | T3: 1Q2026 | U3: 2Q2026
C4: 2016-12-31 | D4: 2017-12-31 | E4: 2018-12-31 | F4: 2019-12-31 | G4: 2020-12-31 | H4: 2021-12-31 | I4: 2022-12-31 | J4: 2023-12-31 | K4: 2024-12-31 | L4: 2025-12-31 | P4: 2024-09-27 | Q4: 2025-03-28 | R4: 2025-06-27 | S4: 2025-09-26 | T4: 2026-04-03 | U4: 2026-07-03
A6: CONTENTS
A7: =HYPERLINK("#'Balance Sheet'!A11","1. BALANCE SHEET — AS REPORTED (year-end values from the first 10-K after the year-end; quarterly columns are 10-Q period-end)") -> 1. BALANCE SHEET — AS REPORTED (year-end values from the first 10-K after the year-end; quarterly columns are 10-Q period-end)
A8: =HYPERLINK("#'Balance Sheet'!A58","2. CHECKS") -> 2. CHECKS
A9: =HYPERLINK("#'Balance Sheet'!A68","3. WORKING CAPITAL ANALYTICS (quarterly uses 91 days; the 10-Q IS is a three-month column)") -> 3. WORKING CAPITAL ANALYTICS (quarterly uses 91 days; the 10-Q IS is a three-month column)
A11: 1. BALANCE SHEET — AS REPORTED (year-end values from the first 10-K after the year-end; quarterly columns are 10-Q period-end)
A12: Assets
A13: Current Assets
A14: Cash and cash equivalents | C14: 8555 | D14: 6006 | E14: 9077 | F14: 6480 | G14: 6795 | H14: 9684 | I14: 9519 | J14: 9366 | K14: 10828 | L14: 10270 | P14: 13938 | Q14: 8417 | R14: 9590 | S14: 12732 | T14: 10574 | U14: 12907
A15: Short-term investments | C15: 9595 | D15: 9352 | E15: 2025 | F15: 1467 | G15: 1771 | H15: 1242 | I15: 1043 | J15: 2997 | K15: 2020 | L15: 3602 | P15: 2439 | Q15: 3579 | R15: 2658 | S15: 1142 | T15: 509 | U15: 622
A16: Total Cash, Cash Equivalents and Short-Term Investments | C16: 18150 | D16: 15358 | E16: 11102 | F16: 7947 | G16: 8566 | H16: 10926 | I16: 10562 | J16: 12363 | K16: 12848 | L16: 13872 | P16: 16377 | Q16: 11996 | R16: 12248 | S16: 13874 | T16: 11083 | U16: 13529
A17: Marketable securities | C17: 4051 | D17: 5317 | E17: 5013 | F17: 3228 | G17: 2348 | H17: 1699 | I17: 1069 | J17: 1300 | K17: 1723 | L17: 1934 | P17: 1787 | Q17: 1791 | R17: 2049 | S17: 1907 | T17: 2737 | U17: 2842
A18: Trade accounts receivable, less allowances | C18: 3856 | D18: 3667 | E18: 3685 | F18: 3971 | G18: 3144 | H18: 3512 | I18: 3487 | J18: 3410 | K18: 3569 | L18: 3038 | P18: 4233 | Q18: 4091 | R18: 4168 | S18: 3946 | T18: 3675 | U18: 3732
A19: Inventories | C19: 2675 | D19: 2655 | E19: 3071 | F19: 3379 | G19: 3266 | H19: 3414 | I19: 4233 | J19: 4424 | K19: 4728 | L19: 4425 | P19: 4714 | Q19: 5102 | R19: 5082 | S19: 4802 | T19: 4730 | U19: 4647
A20: Prepaid expenses and other current assets | C20: 2481 | D20: 2000 | E20: 2059 | F20: 1886 | G20: 1916 | H20: 2994 | I20: 3240 | J20: 5235 | K20: 2998 | L20: 2433 | P20: 3177 | Q20: 3198 | R20: 3062 | S20: 2718 | T20: 2953 | U20: 2688
A21: Assets held for sale | C21: 2797 | D21: 219 | K21: 131 | L21: 5342 | T21: 5212 | U21: 5438
A22: Assets held for sale — discontinued operations | C22: 0 | D22: 7329
A23: Total Current Assets | C23: 34010 | D23: 36545 | E23: 24930 | F23: 20411 | G23: 19240 | H23: 22545 | I23: 22591 | J23: 26732 | K23: 25997 | L23: 31044 | P23: 30288 | Q23: 26178 | R23: 26609 | S23: 27247 | T23: 30390 | U23: 32876
A24: Equity method investments | C24: 16260 | D24: 20856 | E24: 19412 | F24: 19025 | G24: 19273 | H24: 17598 | I24: 18264 | J24: 19671 | K24: 18087 | L24: 20235 | P24: 18993 | Q24: 18369 | R24: 19379 | S24: 20323 | T24: 20403 | U24: 20782
A25: Other investments | C25: 989 | D25: 1096 | E25: 867 | F25: 854 | G25: 812 | H25: 818 | I25: 501 | P25: 44
A26: Deferred income tax assets | D26: 330 | E26: 2674 | F26: 2412 | G26: 2460 | H26: 2129 | I26: 1746 | J26: 1561 | K26: 1319 | L26: 1206 | P26: 1428 | Q26: 1311 | R26: 1325 | S26: 1267 | T26: 1141 | U26: 1090
A27: Property, plant and equipment — net | C27: 10635 | D27: 8203 | E27: 9598 | F27: 10838 | G27: 10777 | H27: 9920 | I27: 9841 | J27: 9236 | K27: 10303 | L27: 9613 | P27: 9864 | Q27: 10431 | R27: 10784 | S27: 10902 | T27: 9522 | U27: 9636
A28: Trademarks with indefinite lives | C28: 6097 | D28: 6729 | E28: 6682 | F28: 9266 | G28: 10395 | H28: 14465 | I28: 14214 | J28: 14349 | K28: 13301 | L28: 12531 | P28: 13598 | Q28: 13425 | R28: 13615 | S28: 13515 | T28: 12463 | U28: 12500
A29: Bottlers' franchise rights with indefinite lives | C29: 3676 | D29: 138 | E29: 51
A30: Goodwill | C30: 10629 | D30: 9401 | E30: 14109 | F30: 16764 | G30: 17506 | H30: 19363 | I30: 18782 | J30: 18358 | K30: 18139 | L30: 15491 | P30: 18686 | Q30: 18333 | R30: 18663 | S30: 18662 | T30: 15411 | U30: 15456
A31: Other intangible assets | C31: 726 | D31: 368 | E31: 745 | F31: 736 | G31: 649 | H31: 785 | I31: 635 | P31: 461
A32: Other noncurrent assets | C32: 4248 | D32: 4230 | E32: 4148 | F32: 6075 | G32: 6184 | H32: 6731 | I32: 6189 | J32: 7796 | K32: 13403 | L32: 14696 | P32: 12904 | Q32: 13669 | R32: 13958 | S32: 14129 | T32: 14887 | U32: 15582
A33: Total Assets | C33: 87270 | D33: 87896 | E33: 83216 | F33: 86381 | G33: 87296 | H33: 94354 | I33: 92763 | J33: 97703 | K33: 100549 | L33: 104816 | P33: 106266 | Q33: 101716 | R33: 104333 | S33: 106045 | T33: 104217 | U33: 107922
A34: Liabilities and equity
A35: Current Liabilities
A36: Accounts payable and accrued expenses | C36: 9490 | D36: 8748 | E36: 9533 | F36: 11312 | G36: 11145 | H36: 14619 | I36: 15749 | J36: 15485 | K36: 21712 | L36: 14813 | P36: 23820 | Q36: 16499 | R36: 17030 | S36: 17692 | T36: 14409 | U36: 15434
A37: Loans and notes payable | C37: 12498 | D37: 13205 | E37: 13835 | F37: 10994 | G37: 2183 | H37: 3307 | I37: 2373 | J37: 4557 | K37: 1499 | L37: 1551 | P37: 2203 | Q37: 5418 | R37: 4379 | S37: 2319 | T37: 332 | U37: 48
A38: Current maturities of long-term debt | C38: 3527 | D38: 3298 | E38: 5003 | F38: 4253 | G38: 485 | H38: 1338 | I38: 399 | J38: 1960 | K38: 648 | L38: 1822 | P38: 1067 | Q38: 163 | R38: 91 | S38: 1920 | T38: 4493 | U38: 6494
A39: Accrued income taxes | C39: 307 | D39: 410 | E39: 411 | F39: 414 | G39: 788 | H39: 686 | I39: 1203 | J39: 1569 | K39: 1387 | L39: 525 | P39: 1479 | Q39: 1728 | R39: 444 | S39: 568 | T39: 717 | U39: 782
A40: Liabilities held for sale | C40: 710 | D40: 37 | K40: 3 | L40: 2570 | T40: 2427 | U40: 2442
A41: Liabilities held for sale — discontinued operations | C41: 0 | D41: 1496
A42: Total Current Liabilities | C42: 26532 | D42: 27194 | E42: 28782 | F42: 26973 | G42: 14601 | H42: 19950 | I42: 19724 | J42: 23571 | K42: 25249 | L42: 21281 | P42: 28569 | Q42: 23808 | R42: 21944 | S42: 22499 | T42: 22378 | U42: 25200
A43: Long-term debt | C43: 29684 | D43: 31182 | E43: 25376 | F43: 27516 | G43: 40125 | H43: 38116 | I43: 36377 | J43: 35547 | K43: 42375 | L43: 42119 | P43: 42994 | Q43: 43530 | R43: 44976 | S43: 43177 | T43: 39065 | U43: 37001
A44: Other noncurrent liabilities | C44: 4081 | D44: 8021 | E44: 7646 | F44: 8510 | G44: 9453 | H44: 8607 | I44: 7922 | J44: 8466 | K44: 4084 | L44: 4735 | P44: 4257 | Q44: 4313 | R44: 4856 | S44: 4667 | T44: 4425 | U44: 4627
A45: Deferred income tax liabilities | C45: 3753 | D45: 2522 | E45: 2354 | F45: 2284 | G45: 1833 | H45: 2821 | I45: 2914 | J45: 2639 | K45: 2469 | L45: 2406 | P45: 2292 | Q45: 2311 | R45: 2375 | S45: 2435 | T45: 2615 | U45: 2779
A46: The Coca-Cola Company Shareowners' Equity
A47: The Coca-Cola Company Shareowners'Equity
A48: Common stock, $0.25 par value | C48: 1760 | D48: 1760 | E48: 1760 | F48: 1760 | G48: 1760 | H48: 1760 | I48: 1760 | J48: 1760 | K48: 1760 | L48: 1760 | P48: 1760 | Q48: 1760 | R48: 1760 | S48: 1760 | T48: 1760 | U48: 1760
A49: Capital surplus | C49: 14993 | D49: 15864 | E49: 16520 | F49: 17154 | G49: 17601 | H49: 18116 | I49: 18822 | J49: 19209 | K49: 19801 | L49: 20581 | P49: 19710 | Q49: 19873 | R49: 19970 | S49: 20489 | T49: 20634 | U49: 20741
A50: Reinvested earnings | C50: 65502 | D50: 60430 | E50: 63234 | F50: 65855 | G50: 66555 | H50: 69094 | I50: 71019 | J50: 73782 | K50: 76054 | L50: 80382 | P50: 75946 | Q50: 77189 | R50: 78803 | S50: 80305 | T50: 82026 | U50: 84169
A51: Accumulated other comprehensive income (loss) | C51: -11205 | D51: -10305 | E51: -12814 | F51: -13544 | G51: -14601 | H51: -14330 | I51: -14895 | J51: -14275 | K51: -16843 | L51: -14131 | P51: -15536 | Q51: -16482 | R51: -15758 | S51: -14952 | T51: -14040 | U51: -13626
A52: Treasury stock, at cost | C52: -47988 | D52: -50677 | E52: -51719 | F52: -52244 | G52: -52016 | H52: -51641 | I52: -52601 | J52: -54535 | K52: -55916 | L52: -56423 | P52: -55362 | Q52: -56138 | R52: -56190 | S52: -56355 | T52: -56747 | U52: -56894
A53: Equity Attributable to Shareowners of The Coca-Cola Company | C53: 23062 | D53: 17072 | E53: 16981 | F53: 18981 | G53: 19299 | H53: 22999 | I53: 24105 | J53: 25941 | K53: 24856 | L53: 32169 | P53: 26518 | Q53: 26202 | R53: 28585 | S53: 31247 | T53: 33633 | U53: 36150
A54: Equity attributable to noncontrolling interests | C54: 158 | D54: 1905 | E54: 2077 | F54: 2117 | G54: 1985 | H54: 1861 | I54: 1721 | J54: 1539 | K54: 1516 | L54: 2106 | P54: 1636 | Q54: 1552 | R54: 1597 | S54: 2020 | T54: 2101 | U54: 2165
A55: Total Equity | C55: 23220 | D55: 18977 | E55: 19058 | F55: 21098 | G55: 21284 | H55: 24860 | I55: 25826 | J55: 27480 | K55: 26372 | L55: 34275 | P55: 28154 | Q55: 27754 | R55: 30182 | S55: 33267 | T55: 35734 | U55: 38315
A56: Total Liabilities and Equity | C56: 87270 | D56: 87896 | E56: 83216 | F56: 86381 | G56: 87296 | H56: 94354 | I56: 92763 | J56: 97703 | K56: 100549 | L56: 104816 | P56: 106266 | Q56: 101716 | R56: 104333 | S56: 106045 | T56: 104217 | U56: 107922
A58: 2. CHECKS
A59: Check: Cash + short-term investments - subtotal (≈0) | C59: =C14+C15-C16 -> 0 | D59: =D14+D15-D16 -> 0 | E59: =E14+E15-E16 -> 0 | F59: =F14+F15-F16 -> 0 | G59: =G14+G15-G16 -> 0 | H59: =H14+H15-H16 -> 0 | I59: =I14+I15-I16 -> 0 | J59: =J14+J15-J16 -> 0 | ... L59: =L14+L15-L16 -> 0 | P59: =P14+P15-P16 -> 0 | Q59: =Q14+Q15-Q16 -> 0 | R59: =R14+R15-R16 -> 0 | S59: =S14+S15-S16 -> 0 | T59: =T14+T15-T16 -> 0 | U59: =U14+U15-U16 -> 0
A60: Check: Current asset lines - Total current assets (≈0) | C60: =C16+C17+C18+C19+C20+C21+C22-C23 -> 0 | D60: =D16+D17+D18+D19+D20+D21+D22-D23 -> 0 | E60: =E16+E17+E18+E19+E20+E21+E22-E23 -> 0 | F60: =F16+F17+F18+F19+F20+F21+F22-F23 -> 0 | G60: =G16+G17+G18+G19+G20+G21+G22-G23 -> 0 | H60: =H16+H17+H18+H19+H20+H21+H22-H23 -> 0 | I60: =I16+I17+I18+I19+I20+I21+I22-I23 -> 0 | J60: =J16+J17+J18+J19+J20+J21+J22-J23 -> 0 | ... L60: =L16+L17+L18+L19+L20+L21+L22-L23 -> 0 | P60: =P16+P17+P18+P19+P20+P21+P22-P23 -> 0 | Q60: =Q16+Q17+Q18+Q19+Q20+Q21+Q22-Q23 -> 0 | R60: =R16+R17+R18+R19+R20+R21+R22-R23 -> 0 | S60: =S16+S17+S18+S19+S20+S21+S22-S23 -> 0 | T60: =T16+T17+T18+T19+T20+T21+T22-T23 -> 0 | U60: =U16+U17+U18+U19+U20+U21+U22-U23 -> 0
A61: Check: Current + non-current assets - Total assets (≈0) | C61: =C23+C24+C25+C32+C26+C27+C28+C29+C30+C31-C33 -> 0 | D61: =D23+D24+D25+D32+D26+D27+D28+D29+D30+D31-D33 -> 0 | E61: =E23+E24+E25+E32+E26+E27+E28+E29+E30+E31-E33 -> 0 | F61: =F23+F24+F25+F32+F26+F27+F28+F29+F30+F31-F33 -> 0 | G61: =G23+G24+G25+G32+G26+G27+G28+G29+G30+G31-G33 -> 0 | H61: =H23+H24+H25+H32+H26+H27+H28+H29+H30+H31-H33 -> 0 | I61: =I23+I24+I25+I32+I26+I27+I28+I29+I30+I31-I33 -> 0 | J61: =J23+J24+J25+J32+J26+J27+J28+J29+J30+J31-J33 -> 0 | ... L61: =L23+L24+L25+L32+L26+L27+L28+L29+L30+L31-L33 -> 0 | P61: =P23+P24+P25+P32+P26+P27+P28+P29+P30+P31-P33 -> 0 | Q61: =Q23+Q24+Q25+Q32+Q26+Q27+Q28+Q29+Q30+Q31-Q33 -> 0 | R61: =R23+R24+R25+R32+R26+R27+R28+R29+R30+R31-R33 -> 0 | S61: =S23+S24+S25+S32+S26+S27+S28+S29+S30+S31-S33 -> 0 | T61: =T23+T24+T25+T32+T26+T27+T28+T29+T30+T31-T33 -> 0 | U61: =U23+U24+U25+U32+U26+U27+U28+U29+U30+U31-U33 -> 0
A62: Check: Current liability lines - Total current liabilities (≈0) | C62: =C36+C37+C38+C39+C40+C41-C42 -> 0 | D62: =D36+D37+D38+D39+D40+D41-D42 -> 0 | E62: =E36+E37+E38+E39+E40+E41-E42 -> 0 | F62: =F36+F37+F38+F39+F40+F41-F42 -> 0 | G62: =G36+G37+G38+G39+G40+G41-G42 -> 0 | H62: =H36+H37+H38+H39+H40+H41-H42 -> 0 | I62: =I36+I37+I38+I39+I40+I41-I42 -> 0 | J62: =J36+J37+J38+J39+J40+J41-J42 -> 0 | ... L62: =L36+L37+L38+L39+L40+L41-L42 -> 0 | P62: =P36+P37+P38+P39+P40+P41-P42 -> 0 | Q62: =Q36+Q37+Q38+Q39+Q40+Q41-Q42 -> 0 | R62: =R36+R37+R38+R39+R40+R41-R42 -> 0 | S62: =S36+S37+S38+S39+S40+S41-S42 -> 0 | T62: =T36+T37+T38+T39+T40+T41-T42 -> 0 | U62: =U36+U37+U38+U39+U40+U41-U42 -> 0
A63: Check: Equity components - Equity attributable to shareowners (≈0) | C63: =C48+C49+C50+C51+C52-C53 -> 0 | D63: =D48+D49+D50+D51+D52-D53 -> 0 | E63: =E48+E49+E50+E51+E52-E53 -> 0 | F63: =F48+F49+F50+F51+F52-F53 -> 0 | G63: =G48+G49+G50+G51+G52-G53 -> 0 | H63: =H48+H49+H50+H51+H52-H53 -> 0 | I63: =I48+I49+I50+I51+I52-I53 -> 0 | J63: =J48+J49+J50+J51+J52-J53 -> 0 | ... L63: =L48+L49+L50+L51+L52-L53 -> 0 | P63: =P48+P49+P50+P51+P52-P53 -> 0 | Q63: =Q48+Q49+Q50+Q51+Q52-Q53 -> 0 | R63: =R48+R49+R50+R51+R52-R53 -> 0 | S63: =S48+S49+S50+S51+S52-S53 -> 0 | T63: =T48+T49+T50+T51+T52-T53 -> 0 | U63: =U48+U49+U50+U51+U52-U53 -> 0
A64: Check: Equity attributable + NCI - Total equity (≈0) | C64: =C53+C54-C55 -> 0 | D64: =D53+D54-D55 -> 0 | E64: =E53+E54-E55 -> 0 | F64: =F53+F54-F55 -> 0 | G64: =G53+G54-G55 -> 0 | H64: =H53+H54-H55 -> 0 | I64: =I53+I54-I55 -> 0 | J64: =J53+J54-J55 -> 0 | ... L64: =L53+L54-L55 -> 0 | P64: =P53+P54-P55 -> 0 | Q64: =Q53+Q54-Q55 -> 0 | R64: =R53+R54-R55 -> 0 | S64: =S53+S54-S55 -> 0 | T64: =T53+T54-T55 -> 0 | U64: =U53+U54-U55 -> 0
A65: Check: Liabilities + equity components - Total L&E (≈0) | C65: =C42+C43+C44+C45+C55-C56 -> 0 | D65: =D42+D43+D44+D45+D55-D56 -> 0 | E65: =E42+E43+E44+E45+E55-E56 -> 0 | F65: =F42+F43+F44+F45+F55-F56 -> 0 | G65: =G42+G43+G44+G45+G55-G56 -> 0 | H65: =H42+H43+H44+H45+H55-H56 -> 0 | I65: =I42+I43+I44+I45+I55-I56 -> 0 | J65: =J42+J43+J44+J45+J55-J56 -> 0 | ... L65: =L42+L43+L44+L45+L55-L56 -> 0 | P65: =P42+P43+P44+P45+P55-P56 -> 0 | Q65: =Q42+Q43+Q44+Q45+Q55-Q56 -> 0 | R65: =R42+R43+R44+R45+R55-R56 -> 0 | S65: =S42+S43+S44+S45+S55-S56 -> 0 | T65: =T42+T43+T44+T45+T55-T56 -> 0 | U65: =U42+U43+U44+U45+U55-U56 -> 0
A66: Balance Check: Total assets - Total liabilities and equity (≈0) | C66: =C33-C56 -> 0 | D66: =D33-D56 -> 0 | E66: =E33-E56 -> 0 | F66: =F33-F56 -> 0 | G66: =G33-G56 -> 0 | H66: =H33-H56 -> 0 | I66: =I33-I56 -> 0 | J66: =J33-J56 -> 0 | ... L66: =L33-L56 -> 0 | P66: =P33-P56 -> 0 | Q66: =Q33-Q56 -> 0 | R66: =R33-R56 -> 0 | S66: =S33-S56 -> 0 | T66: =T33-T56 -> 0 | U66: =U33-U56 -> 0
A68: 3. WORKING CAPITAL ANALYTICS (quarterly uses 91 days; the 10-Q IS is a three-month column)
A69: Days Sales Outstanding | C69: =C18/'Income Statement'!C11*365 -> 33.620142 | D69: =D18/'Income Statement'!D11*365 -> 36.961643 | E69: =E18/'Income Statement'!E11*365 -> 39.213557 | F69: =F18/'Income Statement'!F11*365 -> 38.893764 | G69: =G18/'Income Statement'!G11*365 -> 34.759799 | H69: =H18/'Income Statement'!H11*365 -> 33.162075 | I69: =I18/'Income Statement'!I11*365 -> 29.5962 | J69: =J18/'Income Statement'!J11*365 -> 27.203086 | ... L69: =L18/'Income Statement'!L11*365 -> 23.129889 | P69: =P18/'Income Statement'!P11*91 -> 32.495613 | Q69: =Q18/'Income Statement'!Q11*91 -> 33.451433 | R69: =R18/'Income Statement'!R11*91 -> 30.258317 | S69: =S18/'Income Statement'!S11*91 -> 28.83067 | T69: =T18/'Income Statement'!T11*91 -> 26.814064 | U69: =U18/'Income Statement'!U11*91 -> 25.382063
A70: Days Inventory Outstanding | C70: =C19/'Income Statement'!C13*365 -> 59.30003 | D70: =D19/'Income Statement'!D13*365 -> 70.627141 | E70: =E19/'Income Statement'!E13*365 -> 85.782123 | F70: =F19/'Income Statement'!F13*365 -> 84.36521 | G70: =G19/'Income Statement'!G13*365 -> 88.743393 | H70: =H19/'Income Statement'!H13*365 -> 81.142801 | I70: =I19/'Income Statement'!I13*365 -> 85.835833 | J70: =J19/'Income Statement'!J13*365 -> 87.190065 | ... L70: =L19/'Income Statement'!L13*365 -> 87.792847 | P70: =P19/'Income Statement'!P13*91 -> 91.975557 | Q70: =Q19/'Income Statement'!Q13*91 -> 111.52582 | R70: =R19/'Income Statement'!R13*91 -> 98.103946 | S70: =S19/'Income Statement'!S13*91 -> 91.094851 | T70: =T19/'Income Statement'!T13*91 -> 93.166667 | U70: =U19/'Income Statement'!U13*91 -> 85.171601
A71: Days Payable Outstanding (AP and accrued expenses) | C71: =C36/'Income Statement'!C13*365 -> 210.37656 | D71: =D36/'Income Statement'!D13*365 -> 232.71044 | E71: =E36/'Income Statement'!E13*365 -> 266.28492 | F71: =F36/'Income Statement'!F13*365 -> 282.43245 | G71: =G36/'Income Statement'!G13*365 -> 302.83072 | H71: =H36/'Income Statement'!H13*365 -> 347.45946 | I71: =I36/'Income Statement'!I13*365 -> 319.35472 | J71: =J36/'Income Statement'!J13*365 -> 305.18494 | ... L71: =L36/'Income Statement'!L13*365 -> 293.89275 | P71: =P36/'Income Statement'!P13*91 -> 464.75557 | Q71: =Q36/'Income Statement'!Q13*91 -> 360.65554 | R71: =R36/'Income Statement'!R13*91 -> 328.75053 | S71: =S36/'Income Statement'!S13*91 -> 335.6206 | T71: =T36/'Income Statement'!T13*91 -> 283.81364 | U71: =U36/'Income Statement'!U13*91 -> 282.87895
A72: Cash Conversion Cycle | C72: =C69+C70-C71 -> -117.45638 | D72: =D69+D70-D71 -> -125.12166 | E72: =E69+E70-E71 -> -141.28924 | F72: =F69+F70-F71 -> -159.17348 | G72: =G69+G70-G71 -> -179.32752 | H72: =H69+H70-H71 -> -233.15459 | I72: =I69+I70-I71 -> -203.92269 | J72: =J69+J70-J71 -> -190.79178 | ... L72: =L69+L70-L71 -> -182.97002 | P72: =P69+P70-P71 -> -340.2844 | Q72: =Q69+Q70-Q71 -> -215.67828 | R72: =R69+R70-R71 -> -200.38827 | S72: =S69+S70-S71 -> -215.69507 | T72: =T69+T70-T71 -> -163.83291 | U72: =U69+U70-U71 -> -172.32529

Sheet Cash Flow
A1: The Coca-Cola Company — Cash Flow
A2: $ in millions except per-share data | USD | as of 2026-10-14
C3: FY2016 | D3: FY2017 | E3: FY2018 | F3: FY2019 | G3: FY2020 | H3: FY2021 | I3: FY2022 | J3: FY2023 | K3: FY2024 | L3: FY2025 | M3: · | N3: · | O3: · | P3: 3Q2024 | Q3: 1Q2025 | R3: 2Q2025 | S3: 3Q2025 | T3: 1Q2026 | U3: 2Q2026
C4: 2016-12-31 | D4: 2017-12-31 | E4: 2018-12-31 | F4: 2019-12-31 | G4: 2020-12-31 | H4: 2021-12-31 | I4: 2022-12-31 | J4: 2023-12-31 | K4: 2024-12-31 | L4: 2025-12-31 | P4: 2024-09-27 | Q4: 2025-03-28 | R4: 2025-06-27 | S4: 2025-09-26 | T4: 2026-04-03 | U4: 2026-07-03
A6: CONTENTS
A7: =HYPERLINK("#'Cash Flow'!A11","1. CASH FLOW STATEMENT — AS REPORTED (quarterly columns are fiscal year-to-date)") -> 1. CASH FLOW STATEMENT — AS REPORTED (quarterly columns are fiscal year-to-date)
A8: =HYPERLINK("#'Cash Flow'!A64","2. CHECKS") -> 2. CHECKS
A9: =HYPERLINK("#'Cash Flow'!A70","3. FREE CASH FLOW AND SHAREOWNER RETURN ANALYTICS (annual; quarterly shown where inputs are YTD)") -> 3. FREE CASH FLOW AND SHAREOWNER RETURN ANALYTICS (annual; quarterly shown where inputs are YTD)
A11: 1. CASH FLOW STATEMENT — AS REPORTED (quarterly columns are fiscal year-to-date)
A12: Operating Activities
A13: Consolidated net income | C13: 6550 | D13: 1283 | E13: 6476 | F13: 8985 | G13: 7768 | H13: 9804 | I13: 9571 | J13: 10703 | K13: 10649 | L13: 13137 | P13: 8436 | Q13: 3335 | R13: 7138 | S13: 10821 | T13: 3966 | U13: 8404
A14: (Income) loss from discontinued operations | C14: 0
A15: Net income from continuing operations | C15: 6550
A16: Adjustments to reconcile net income to operating cash flow: | B16: Filed caption: Adjustments to reconcile consolidated net income to net cash provided by operating activities:
A17: Depreciation and amortization | C17: 1787 | D17: 1260 | E17: 1086 | F17: 1365 | G17: 1536 | H17: 1452 | I17: 1260 | J17: 1128 | K17: 1075 | L17: 1050 | P17: 799 | Q17: 267 | R17: 546 | S17: 814 | T17: 264 | U17: 530
A18: Stock-based compensation expense | C18: 258 | D18: 219 | E18: 225 | F18: 201 | G18: 126 | H18: 337 | I18: 356 | J18: 254 | K18: 286 | L18: 279 | P18: 207 | Q18: 63 | R18: 130 | S18: 204 | T18: 56 | U18: 117
A19: Deferred income taxes | C19: -856 | D19: -1252 | E19: -413 | F19: -280 | G19: -18 | H19: 894 | I19: -122 | J19: -2 | K19: -11 | L19: 517 | P19: 0 | Q19: 95 | R19: 459 | S19: 496 | T19: 205 | U19: 353
A20: Equity (income) loss — net of dividends | C20: -449 | D20: -628 | E20: -457 | F20: -421 | G20: -511 | H20: -615 | I20: -838 | J20: -1019 | K20: -802 | L20: -1038 | P20: -693 | Q20: -264 | R20: -387 | S20: -859 | T20: -375 | U20: -520
A21: Foreign currency adjustments | C21: 158 | D21: 292 | E21: -50 | F21: 91 | G21: -88 | H21: 86 | I21: 203 | J21: 175 | K21: -110 | L21: 191 | P21: -61 | Q21: 50 | R21: 111 | S21: 127 | T21: 33 | U21: 107
A22: Significant (gains) losses — net | C22: 1146 | D22: 1459 | E22: 743 | F22: -467 | G22: -914 | H22: -1365 | I22: -129 | J22: -492 | K22: -1737 | L22: -713 | P22: -1722 | Q22: -331 | R22: -433 | S22: -396 | T22: 10 | U22: -56
A23: Other operating charges | C23: 647 | D23: 1218 | E23: 558 | F23: 127 | G23: 556 | H23: 506 | I23: 1086 | J23: 1741 | K23: 4000 | L23: 1052 | P23: 3874 | Q23: 0 | R23: 38 | S23: 38 | T23: 10 | U23: 0
A24: Other items | C24: -224 | D24: -252 | E24: 699 | F24: 504 | G24: 699 | H24: 201 | I24: 236 | J24: -43 | K24: -311 | L24: 141 | P24: -143 | Q24: 104 | R24: 238 | S24: 447 | T24: 115 | U24: -125
A25: Net change in operating assets and liabilities | C25: -225 | D25: 3442 | E25: -1240 | F25: 366 | G25: 690 | H25: 1325 | I25: -605 | J25: -846 | K25: -6234 | L25: -7208 | P25: -7843 | Q25: -8521 | R25: -9231 | S25: -8040 | T25: -2263 | U25: -1267
A26: Net Cash Provided by Operating Activities | C26: 8792 | D26: 7041 | E26: 7627 | F26: 10471 | G26: 9844 | H26: 12625 | I26: 11018 | J26: 11599 | K26: 6805 | L26: 7408 | P26: 2854 | Q26: -5202 | R26: -1391 | S26: 3652 | T26: 2021 | U26: 7543
A27: Investing Activities
A28: Purchases of investments | C28: -16626 | D28: -17296 | E28: -7789 | F28: -4704 | G28: -13583 | H28: -6030 | I28: -3751 | J28: -6698 | K28: -5640 | L28: -6160 | P28: -4398 | Q28: -2507 | R28: -2865 | S28: -3292 | T28: -1459 | U28: -2799
A29: Proceeds from disposals of investments | C29: 17842 | D29: 16694 | E29: 14977 | F29: 6973 | G29: 13835 | H29: 7059 | I29: 4771 | J29: 4354 | K29: 6589 | L29: 4665 | P29: 5125 | Q29: 1005 | R29: 2201 | S29: 4300 | T29: 3503 | U29: 4574
A30: Acquisitions of businesses, equity method inv. & nonmkt. securities | B30: Filed caption: Acquisitions of businesses, equity method investments and nonmarketable securities | C30: -838 | D30: -3809 | E30: -1263 | F30: -5542 | G30: -1052 | H30: -4766 | I30: -73 | J30: -62 | K30: -315 | L30: -461 | P30: -153 | Q30: -42 | R30: -179 | S30: -356 | T30: -37 | U30: -199
A31: Proceeds from disposals of businesses, equity method inv. & nonmkt… | B31: Filed caption: Proceeds from disposals of businesses, equity method investments and nonmarketable securities Full label: Proceeds from disposals of businesses, equity method inv. & nonmkt. securities | C31: 1035 | D31: 3821 | E31: 1362 | F31: 429 | G31: 189 | H31: 2180 | I31: 458 | J31: 430 | K31: 3485 | L31: 3567 | P31: 3468 | Q31: 748 | R31: 973 | S31: 1020 | T31: 0 | U31: 1
A32: Purchases of property, plant and equipment | C32: -2262 | D32: -1750 | E32: -1548 | F32: -2054 | G32: -1177 | H32: -1367 | I32: -1484 | J32: -1852 | K32: -2064 | L32: -2112 | P32: -1261 | Q32: -309 | R32: -751 | S32: -1230 | T32: -266 | U32: -684
A33: Proceeds from disposals of property, plant and equipment | C33: 150 | D33: 108 | E33: 248 | F33: 978 | G33: 189 | H33: 108 | I33: 75 | J33: 74 | K33: 40 | L33: 13 | P33: 33 | Q33: 8 | R33: 13 | S33: 21 | T33: 2 | U33: 7
A34: Collateral (paid) received associated with hedging activities — net | G34: 0 | H34: 0 | I34: -1465 | J34: 366 | K34: 235 | L34: 330 | P34: 299 | Q34: -15 | R34: 206 | S34: 300 | T34: -20 | U34: -37
A35: Other investing activities | C35: -305 | D35: -80 | E35: -60 | F35: -56 | G35: 122 | H35: 51 | I35: 706 | J35: 39 | K35: 194 | L35: 91 | P35: 194 | Q35: 45 | R35: 124 | S35: 214 | T35: 23 | U35: 241
A36: Net Cash Provided by (Used in) Investing Activities | C36: -1004 | D36: -2312 | E36: 5927 | F36: -3976 | G36: -1477 | H36: -2765 | I36: -763 | J36: -3349 | K36: 2524 | L36: -67 | P36: 3307 | Q36: -1067 | R36: -278 | S36: 977 | T36: 1746 | U36: 1104
A37: Financing Activities
A38: Issuances of loans, notes payable and long-term debt | C38: 27281 | D38: 29926 | E38: 27605 | F38: 23009 | G38: 26934 | H38: 13094 | I38: 3972 | J38: 6891 | K38: 12061 | L38: 4980 | P38: 11298 | Q38: 5436 | R38: 5320 | S38: 4854 | T38: 0 | U38: 9
A39: Payments of loans, notes payable and long-term debt | C39: -25615 | D39: -28871 | E39: -30600 | F39: -24850 | G39: -28796 | H39: -12866 | I39: -4930 | J39: -5034 | K39: -9533 | L39: -4967 | P39: -7925 | Q39: -1599 | R39: -2630 | S39: -4166 | T39: -1262 | U39: -1559
A40: Issuances of stock | C40: 1434 | D40: 1595 | E40: 1476 | F40: 1012 | G40: 647 | H40: 702 | I40: 837 | J40: 539 | K40: 747 | L40: 313 | P40: 717 | Q40: 159 | R40: 223 | S40: 243 | T40: 155 | U40: 251
A41: Purchases of stock for treasury | C41: -3681 | D41: -3682 | E41: -1912 | F41: -1103 | G41: -118 | H41: -111 | I41: -1418 | J41: -2289 | K41: -1795 | L41: -746 | P41: -1228 | Q41: -370 | R41: -472 | S41: -644 | T41: -477 | U41: -663
A42: Dividends | C42: -6043 | D42: -6320 | E42: -6644 | F42: -6845 | G42: -7047 | H42: -7252 | I42: -7616 | J42: -7952 | K42: -8359 | L42: -8779 | P42: -4274 | Q42: -89 | R42: -2283 | S42: -4391 | T42: -2281 | U42: -4562
A43: Proceeds from sale of a noncontrolling interest | J43: 0 | K43: 0 | L43: 1338 | S43: 1277
A44: Other financing activities | C44: 79 | D44: -95 | E44: -272 | F44: -227 | G44: 310 | H44: -353 | I44: -1095 | J44: -465 | K44: -31 | L44: -279 | P44: -14 | Q44: -105 | R44: -106 | S44: -261 | T44: -3 | U44: -11
A45: Net Cash Provided by (Used in) Financing Activities | C45: -6545 | D45: -7447 | E45: -10347 | F45: -9004 | G45: -8070 | H45: -6786 | I45: -10250 | J45: -8310 | K45: -6910 | L45: -8140 | P45: -1426 | Q45: 3432 | R45: 52 | S45: -3088 | T45: -3868 | U45: -6535
A46: Cash flows from discontinued operations
A47: Net cash from operating activities - discontinued operations | B47: Filed caption: Net cash provided by (used in) operating activities from discontinued operations | C47: 0
A48: Net cash from investing activities - discontinued operations | B48: Filed caption: Net cash provided by (used in) investing activities from discontinued operations | C48: 0
A49: Net cash from financing activities - discontinued operations | B49: Filed caption: Net cash provided by (used in) financing activities from discontinued operations | C49: 0
A50: Net cash provided by (used in) discontinued operations | C50: 0
A51: Effect of exchange rate changes on cash and cash equivalents
A52: Cash and cash equivalents
A53: Net increase (decrease) during the year
A54: Balance at beginning of year
A55: Balance at end of year
A56: Effect of exchange rate changes on cash and restricted cash | B56: Filed caption: Effect of Exchange Rate Changes on Cash, Cash Equivalents, Restricted Cash and Restricted Cash Equivalents | C56: -5 | D56: 241 | E56: -262 | F56: -72 | G56: 76 | H56: -159 | I56: -205 | J56: -73 | K56: -623 | L56: 321 | P56: -266 | Q56: 163 | R56: 332 | S56: 335 | T56: 86 | U56: 85
A57: Cash and restricted cash | B57: Filed caption: Cash, Cash Equivalents, Restricted Cash and Restricted Cash Equivalents
A58: Net increase (decrease) in cash and restricted cash | B58: Filed caption: Net increase (decrease) in cash, cash equivalents, restricted cash and restricted cash equivalents during the year | C58: 1238 | D58: -2477 | E58: 2945 | F58: -2581 | G58: 373 | H58: 2915 | I58: -200 | J58: -133 | K58: 1796 | L58: -478 | P58: 4469 | Q58: -2674 | R58: -1285 | S58: 1876 | T58: -15 | U58: 2197
A59: Cash and restricted cash at beginning of year | B59: Filed caption: Cash, cash equivalents, restricted cash and restricted cash equivalents at beginning of year | C59: 7612 | D59: 8850 | E59: 6373 | F59: 9318 | G59: 6737 | H59: 7110 | I59: 10025 | J59: 9825 | K59: 9692 | L59: 11488 | P59: 9692 | Q59: 11488 | R59: 11488 | S59: 11488 | T59: 11010 | U59: 11010
A60: Cash and restricted cash at end of year | B60: Filed caption: Cash, Cash Equivalents, Restricted Cash and Restricted Cash Equivalents at End of Year | C60: 8850 | D60: 6373 | E60: 9318 | F60: 6737 | G60: 7110 | H60: 10025 | I60: 9825 | J60: 9692 | K60: 11488 | L60: 11010 | P60: 14161 | Q60: 8814 | R60: 10203 | S60: 13364 | T60: 10995 | U60: 13207
A61: Less: Restricted cash and restricted cash equivalents at end of ye… | B61: Full label: Less: Restricted cash and restricted cash equivalents at end of year | C61: 295 | D61: 271 | E61: 241 | F61: 257 | G61: 315 | H61: 341 | I61: 306 | J61: 326 | K61: 660 | L61: 740 | P61: 223 | Q61: 397 | R61: 613 | S61: 632 | T61: 421 | U61: 300
A62: Cash and Cash Equivalents at End of Year | C62: 8555 | D62: 6102 | E62: 9077 | F62: 6480 | G62: 6795 | H62: 9684 | I62: 9519 | J62: 9366 | K62: 10828 | L62: 10270 | P62: 13938 | Q62: 8417 | R62: 9590 | S62: 12732 | T62: 10574 | U62: 12907
A64: 2. CHECKS
A65: Check: Operating lines - Net cash from operations (≈0) | C65: =C13+C17+C18+C19+C20+C21+C22+C23+C24+C25-C26 -> 0 | D65: =D13+D17+D18+D19+D20+D21+D22+D23+D24+D25-D26 -> 0 | E65: =E13+E17+E18+E19+E20+E21+E22+E23+E24+E25-E26 -> 0 | F65: =F13+F17+F18+F19+F20+F21+F22+F23+F24+F25-F26 -> 0 | G65: =G13+G17+G18+G19+G20+G21+G22+G23+G24+G25-G26 -> 0 | H65: =H13+H17+H18+H19+H20+H21+H22+H23+H24+H25-H26 -> 0 | I65: =I13+I17+I18+I19+I20+I21+I22+I23+I24+I25-I26 -> 0 | J65: =J13+J17+J18+J19+J20+J21+J22+J23+J24+J25-J26 -> 0 | ... L65: =L13+L17+L18+L19+L20+L21+L22+L23+L24+L25-L26 -> 0 | P65: =P13+P17+P18+P19+P20+P21+P22+P23+P24+P25-P26 -> 0 | Q65: =Q13+Q17+Q18+Q19+Q20+Q21+Q22+Q23+Q24+Q25-Q26 -> 0 | R65: =R13+R17+R18+R19+R20+R21+R22+R23+R24+R25-R26 -> 0 | S65: =S13+S17+S18+S19+S20+S21+S22+S23+S24+S25-S26 -> 0 | T65: =T13+T17+T18+T19+T20+T21+T22+T23+T24+T25-T26 -> 0 | U65: =U13+U17+U18+U19+U20+U21+U22+U23+U24+U25-U26 -> 0
A66: Check: Investing lines - Net cash from investing activities (≈0) | C66: =C28+C29+C30+C31+C32+C33+C34+C35-C36 -> 0 | D66: =D28+D29+D30+D31+D32+D33+D34+D35-D36 -> 0 | E66: =E28+E29+E30+E31+E32+E33+E34+E35-E36 -> 0 | F66: =F28+F29+F30+F31+F32+F33+F34+F35-F36 -> 0 | G66: =G28+G29+G30+G31+G32+G33+G34+G35-G36 -> 0 | H66: =H28+H29+H30+H31+H32+H33+H34+H35-H36 -> 0 | I66: =I28+I29+I30+I31+I32+I33+I34+I35-I36 -> 0 | J66: =J28+J29+J30+J31+J32+J33+J34+J35-J36 -> 0 | ... L66: =L28+L29+L30+L31+L32+L33+L34+L35-L36 -> 0 | P66: =P28+P29+P30+P31+P32+P33+P34+P35-P36 -> 0 | Q66: =Q28+Q29+Q30+Q31+Q32+Q33+Q34+Q35-Q36 -> 0 | R66: =R28+R29+R30+R31+R32+R33+R34+R35-R36 -> 0 | S66: =S28+S29+S30+S31+S32+S33+S34+S35-S36 -> 0 | T66: =T28+T29+T30+T31+T32+T33+T34+T35-T36 -> 0 | U66: =U28+U29+U30+U31+U32+U33+U34+U35-U36 -> 0
A67: Check: Financing lines - Net cash from financing activities (≈0) | C67: =C38+C39+C40+C41+C42+C43+C44-C45 -> 0 | D67: =D38+D39+D40+D41+D42+D43+D44-D45 -> 0 | E67: =E38+E39+E40+E41+E42+E43+E44-E45 -> 0 | F67: =F38+F39+F40+F41+F42+F43+F44-F45 -> 0 | G67: =G38+G39+G40+G41+G42+G43+G44-G45 -> 0 | H67: =H38+H39+H40+H41+H42+H43+H44-H45 -> 0 | I67: =I38+I39+I40+I41+I42+I43+I44-I45 -> 0 | J67: =J38+J39+J40+J41+J42+J43+J44-J45 -> 0 | ... L67: =L38+L39+L40+L41+L42+L43+L44-L45 -> 0 | P67: =P38+P39+P40+P41+P42+P43+P44-P45 -> 0 | Q67: =Q38+Q39+Q40+Q41+Q42+Q43+Q44-Q45 -> 0 | R67: =R38+R39+R40+R41+R42+R43+R44-R45 -> 0 | S67: =S38+S39+S40+S41+S42+S43+S44-S45 -> 0 | T67: =T38+T39+T40+T41+T42+T43+T44-T45 -> 0 | U67: =U38+U39+U40+U41+U42+U43+U44-U45 -> 0
A68: Cash walk check: CFO+CFI+CFF(+disc.)+FX - net change (≈0) | C68: =C26+C36+C45+C50+C56-C58 -> 0 | D68: =D26+D36+D45+D50+D56-D58 -> 0 | E68: =E26+E36+E45+E50+E56-E58 -> 0 | F68: =F26+F36+F45+F50+F56-F58 -> 0 | G68: =G26+G36+G45+G50+G56-G58 -> 0 | H68: =H26+H36+H45+H50+H56-H58 -> 0 | I68: =I26+I36+I45+I50+I56-I58 -> 0 | J68: =J26+J36+J45+J50+J56-J58 -> 0 | ... L68: =L26+L36+L45+L50+L56-L58 -> 0 | P68: =P26+P36+P45+P50+P56-P58 -> 0 | Q68: =Q26+Q36+Q45+Q50+Q56-Q58 -> 0 | R68: =R26+R36+R45+R50+R56-R58 -> 0 | S68: =S26+S36+S45+S50+S56-S58 -> 0 | T68: =T26+T36+T45+T50+T56-T58 -> 0 | U68: =U26+U36+U45+U50+U56-U58 -> 0
A70: 3. FREE CASH FLOW AND SHAREOWNER RETURN ANALYTICS (annual; quarterly shown where inputs are YTD)
A71: Free cash flow (CFO + PP&E purchases; analyst calc.) | C71: =C26+C32 -> 6530 | D71: =D26+D32 -> 5291 | E71: =E26+E32 -> 6079 | F71: =F26+F32 -> 8417 | G71: =G26+G32 -> 8667 | H71: =H26+H32 -> 11258 | I71: =I26+I32 -> 9534 | J71: =J26+J32 -> 9747 | ... L71: =L26+L32 -> 5296 | P71: =P26+P32 -> 1593 | Q71: =Q26+Q32 -> -5511 | R71: =R26+R32 -> -2142 | S71: =S26+S32 -> 2422 | T71: =T26+T32 -> 1755 | U71: =U26+U32 -> 6859
A72: YoY Growth | D72: =IF(N(C71)=0,"",D71/C71-1) -> -0.18973966 | E72: =IF(N(D71)=0,"",E71/D71-1) -> 0.14893215 | F72: =IF(N(E71)=0,"",F71/E71-1) -> 0.38460273 | G72: =IF(N(F71)=0,"",G71/F71-1) -> 0.029701794 | H72: =IF(N(G71)=0,"",H71/G71-1) -> 0.29895004 | I72: =IF(N(H71)=0,"",I71/H71-1) -> -0.15313555 | J72: =IF(N(I71)=0,"",J71/I71-1) -> 0.022341095 | K72: =IF(N(J71)=0,"",K71/J71-1) -> -0.51359393 | L72: =IF(N(K71)=0,"",L71/K71-1) -> 0.11706391
A73: Capex % of Revenue | C73: =0-C32/'Income Statement'!C11 -> 0.054033395 | D73: =0-D32/'Income Statement'!D11 -> 0.048326522 | E73: =0-E32/'Income Statement'!E11 -> 0.045131195 | F73: =0-F32/'Income Statement'!F11 -> 0.055117265 | G73: =0-G32/'Income Statement'!G11 -> 0.035651542 | H73: =0-H32/'Income Statement'!H11 -> 0.035364118 | I73: =0-I32/'Income Statement'!I11 -> 0.034508418 | J73: =0-J32/'Income Statement'!J11 -> 0.040477335 | ... L73: =0-L32/'Income Statement'!L11 -> 0.04405415
A74: FCF Margin | C74: =C71/'Income Statement'!C11 -> 0.155985 | D74: =D71/'Income Statement'!D11 -> 0.14611179 | E74: =E71/'Income Statement'!E11 -> 0.17723032 | F74: =F71/'Income Statement'!F11 -> 0.22586272 | G74: =G71/'Income Statement'!G11 -> 0.26252499 | H74: =H71/'Income Statement'!H11 -> 0.29124305 | I74: =I71/'Income Statement'!I11 -> 0.22170031 | J74: =J71/'Income Statement'!J11 -> 0.21303055 | ... L74: =L71/'Income Statement'!L11 -> 0.11046912
A75: FCF / Net income attributable | C75: =C71/'Income Statement'!C32 -> 1.0004596 | D75: =D71/'Income Statement'!D32 -> 4.2395833 | E75: =E71/'Income Statement'!E32 -> 0.94482437 | F75: =F71/'Income Statement'!F32 -> 0.94360987 | G75: =G71/'Income Statement'!G32 -> 1.1187556 | H75: =H71/'Income Statement'!H32 -> 1.152185 | I75: =I71/'Income Statement'!I32 -> 0.9991616 | J75: =J71/'Income Statement'!J32 -> 0.90974426 | ... L75: =L71/'Income Statement'!L32 -> 0.4040589
A76: Cash returned to shareowners (dividends + buybacks, positive) | C76: =0-C42-C41 -> 9724 | D76: =0-D42-D41 -> 10002 | E76: =0-E42-E41 -> 8556 | F76: =0-F42-F41 -> 7948 | G76: =0-G42-G41 -> 7165 | H76: =0-H42-H41 -> 7363 | I76: =0-I42-I41 -> 9034 | J76: =0-J42-J41 -> 10241 | ... L76: =0-L42-L41 -> 9525 | P76: =0-P42-P41 -> 5502 | Q76: =0-Q42-Q41 -> 459 | R76: =0-R42-R41 -> 2755 | S76: =0-S42-S41 -> 5035 | T76: =0-T42-T41 -> 2758 | U76: =0-U42-U41 -> 5225
A77: % of Free Cash Flow | C77: =C76/C71 -> 1.4891271 | D77: =D76/D71 -> 1.8903799 | E77: =E76/E71 -> 1.4074683 | F77: =F76/F71 -> 0.94427943 | G77: =G76/G71 -> 0.82669897 | H77: =H76/H71 -> 0.65402381 | I77: =I76/I71 -> 0.94755611 | J77: =J76/J71 -> 1.0506823 | ... L77: =L76/L71 -> 1.7985272 | P77: =P76/P71 -> 3.4538606 | Q77: =Q76/Q71 -> -0.08328797 | R77: =R76/R71 -> -1.2861811 | S77: =S76/S71 -> 2.0788604 | T77: =T76/T71 -> 1.57151 | U77: =U76/U71 -> 0.76177285

Sheet Segments
A1: The Coca-Cola Company — Segments
A2: $ in millions except per-share data | USD | as of 2026-10-14
C3: FY2016 | D3: FY2017 | E3: FY2018 | F3: FY2019 | G3: FY2020 | H3: FY2021 | I3: FY2022 | J3: FY2023 | K3: FY2024 | L3: FY2025 | M3: · | N3: · | O3: · | P3: 3Q2024 | Q3: 1Q2025 | R3: 2Q2025 | S3: 3Q2025 | T3: 1Q2026 | U3: 2Q2026
C4: 2016-12-31 | D4: 2017-12-31 | E4: 2018-12-31 | F4: 2019-12-31 | G4: 2020-12-31 | H4: 2021-12-31 | I4: 2022-12-31 | J4: 2023-12-31 | K4: 2024-12-31 | L4: 2025-12-31 | P4: 2024-09-27 | Q4: 2025-03-28 | R4: 2025-06-27 | S4: 2025-09-26 | T4: 2026-04-03 | U4: 2026-07-03
A6: CONTENTS
A7: =HYPERLINK("#'Segments'!A11","1. SEGMENTS — BASIS C (FY2025 10-K recast: Global Ventures dissolved into the geographic segments; FY2023-FY2025 only)") -> 1. SEGMENTS — BASIS C (FY2025 10-K recast: Global Ventures dissolved into the geographic segments; FY2023-FY2025 only)
A8: =HYPERLINK("#'Segments'!A86","2. SEGMENTS — BASIS B (FY2019-FY2024 10-K presentation incl. Global Ventures; FY2017-FY2024, each year from the latest 10-K presenting it on this basis)") -> 2. SEGMENTS — BASIS B (FY2019-FY2024 10-K presentation incl. Global Ventures; FY2017-FY2024, each year from the latest 10-K presenting it on this basis)
A9: =HYPERLINK("#'Segments'!A168","3. SEGMENTS — BASIS A (FY2018 10-K presentation: no Global Ventures; FY2016-FY2018)") -> 3. SEGMENTS — BASIS A (FY2018 10-K presentation: no Global Ventures; FY2016-FY2018)
A11: 1. SEGMENTS — BASIS C (FY2025 10-K recast: Global Ventures dissolved into the geographic segments; FY2023-FY2025 only)
A12: Third-party net operating revenues
A13: EMEA | J13: 10152 | K13: 10278 | L13: 10833 | Q13: 2481 | R13: 3008 | S13: 2818 | T13: 2807 | U13: 3087
A14: Latin America | J14: 5834 | K14: 6471 | L14: 6331 | Q14: 1477 | R14: 1587 | S14: 1572 | T14: 1678 | U14: 1839
A15: North America | J15: 16965 | K15: 18860 | L15: 19579 | Q15: 4359 | R15: 5028 | S15: 5249 | T15: 4891 | U15: 5405
A16: Asia Pacific | J16: 4811 | K16: 5127 | L16: 5328 | Q16: 1325 | R16: 1464 | S16: 1438 | T16: 1426 | U16: 1487
A17: Bottling Investments | J17: 7852 | K17: 6215 | L17: 5726 | Q17: 1461 | R17: 1409 | S17: 1344 | T17: 1638 | U17: 1525
A18: Corporate | J18: 140 | K18: 110 | L18: 144 | Q18: 26 | R18: 39 | S18: 34 | T18: 32 | U18: 37
A19: Consolidated (as reported) | J19: 45754 | K19: 47061 | L19: 47941 | Q19: 11129 | R19: 12535 | S19: 12455 | T19: 12472 | U19: 13380
A20: Check: segments + Corporate - Consolidated (≈0) | J20: =J13+J14+J15+J16+J17+J18-J19 -> 0 | K20: =K13+K14+K15+K16+K17+K18-K19 -> 0 | L20: =L13+L14+L15+L16+L17+L18-L19 -> 0
A22: Intersegment net operating revenues
A23: EMEA | J23: 686 | K23: 680 | L23: 680 | Q23: 176 | R23: 168 | S23: 178 | T23: 205 | U23: 153
A24: Latin America | J24: 0 | K24: 0 | L24: 3 | Q24: 0 | R24: 0 | S24: 1 | T24: 0 | U24: 0
A25: North America | J25: 8 | K25: 9 | L25: 7 | Q25: 2 | R25: 1 | S25: 4 | T25: 2 | U25: 3
A26: Asia Pacific | J26: 731 | K26: 467 | L26: 310 | Q26: 96 | R26: 108 | S26: 68 | T26: 82 | U26: 94
A27: Bottling Investments | J27: 8 | K27: 8 | L27: 9 | Q27: 2 | R27: 2 | S27: 2 | T27: 2 | U27: 2
A28: Corporate | J28: 0 | K28: 0 | L28: 0 | Q28: 0 | R28: 0 | S28: 0 | T28: 0 | U28: 0
A29: Eliminations | J29: -1433 | K29: -1164 | L29: -1009 | Q29: -276 | R29: -279 | S29: -253 | T29: -291 | U29: -252
A30: Consolidated (as reported) | J30: 0 | K30: 0 | L30: 0 | Q30: =Q23+Q24+Q25+Q26+Q27+Q28+Q29 -> 0 | R30: =R23+R24+R25+R26+R27+R28+R29 -> 0 | S30: =S23+S24+S25+S26+S27+S28+S29 -> 0 | T30: =T23+T24+T25+T26+T27+T28+T29 -> 0 | U30: =U23+U24+U25+U26+U27+U28+U29 -> 0
A31: Check: segments + Corporate - Consolidated (≈0) | J31: =J23+J24+J25+J26+J27+J28+J29-J30 -> 0 | K31: =K23+K24+K25+K26+K27+K28+K29-K30 -> 0 | L31: =L23+L24+L25+L26+L27+L28+L29-L30 -> 0
A33: Total net operating revenues (third-party + intersegment)
A34: EMEA | J34: 10838 | K34: 10958 | L34: 11513 | Q34: 2657 | R34: 3176 | S34: 2996 | T34: 3012 | U34: 3240
A35: Latin America | J35: 5834 | K35: 6471 | L35: 6334 | Q35: 1477 | R35: 1587 | S35: 1573 | T35: 1678 | U35: 1839
A36: North America | J36: 16973 | K36: 18869 | L36: 19586 | Q36: 4361 | R36: 5029 | S36: 5253 | T36: 4893 | U36: 5408
A37: Asia Pacific | J37: 5542 | K37: 5594 | L37: 5638 | Q37: 1421 | R37: 1572 | S37: 1506 | T37: 1508 | U37: 1581
A38: Bottling Investments | J38: 7860 | K38: 6223 | L38: 5735 | Q38: 1463 | R38: 1411 | S38: 1346 | T38: 1640 | U38: 1527
A39: Corporate | J39: 140 | K39: 110 | L39: 144 | Q39: 26 | R39: 39 | S39: 34 | T39: 32 | U39: 37
A40: Eliminations | J40: -1433 | K40: -1164 | L40: -1009 | Q40: -276 | R40: -279 | S40: -253 | T40: -291 | U40: -252
A41: Consolidated (as reported) | J41: 45754 | K41: 47061 | L41: 47941 | Q41: ='Income Statement'!Q11 -> 11129 | R41: ='Income Statement'!R11 -> 12535 | S41: ='Income Statement'!S11 -> 12455 | T41: ='Income Statement'!T11 -> 12472 | U41: ='Income Statement'!U11 -> 13380
A42: Check: segments + Corporate - Consolidated (≈0) | J42: =J34+J35+J36+J37+J38+J39+J40-J41 -> 0 | K42: =K34+K35+K36+K37+K38+K39+K40-K41 -> 0 | L42: =L34+L35+L36+L37+L38+L39+L40-L41 -> 0
A44: Operating income (loss)
A45: EMEA | J45: 4323 | K45: 4255 | L45: 4298 | Q45: 1065 | R45: 1325 | S45: 1097 | T45: 1259 | U45: 1309
A46: Latin America | J46: 3436 | K46: 3792 | L46: 3742 | Q46: 904 | R46: 957 | S46: 897 | T46: 1038 | U46: 1177
A47: North America | J47: 4634 | K47: 4556 | L47: 5070 | Q47: 1341 | R47: 1621 | S47: 1681 | T47: 1606 | U47: 1695
A48: Asia Pacific | J48: 2057 | K48: 2156 | L48: 2042 | Q48: 624 | R48: 647 | S48: 521 | T48: 536 | U48: 656
A49: Bottling Investments | J49: 578 | K49: 496 | L49: 426 | Q49: 119 | R49: 59 | S49: 57 | T49: 191 | U49: 91
A50: Corporate | J50: -3717 | K50: -5263 | L50: -1816 | Q50: -394 | R50: -329 | S50: -271 | T50: -271 | U50: -256
A51: Consolidated (as reported) | J51: 11311 | K51: 9992 | L51: 13762 | Q51: 3659 | R51: 4280 | S51: 3982 | T51: 4359 | U51: 4672
A52: Check: segments + Corporate - Consolidated (≈0) | J52: =J45+J46+J47+J48+J49+J50-J51 -> 0 | K52: =K45+K46+K47+K48+K49+K50-K51 -> 0 | L52: =L45+L46+L47+L48+L49+L50-L51 -> 0
A54: Depreciation and amortization
A55: EMEA | J55: 187 | K55: 181 | L55: 173 | Q55: 44 | R55: 55 | S55: 40 | T55: 48 | U55: 51
A56: Latin America | J56: 48 | K56: 29 | L56: 32 | Q56: 7 | R56: 8 | S56: 8 | T56: 8 | U56: 9
A57: North America | J57: 310 | K57: 325 | L57: 326 | Q57: 81 | R57: 81 | S57: 83 | T57: 99 | U57: 92
A58: Asia Pacific | J58: 50 | K58: 45 | L58: 47 | Q58: 12 | R58: 10 | S58: 12 | T58: 11 | U58: 12
A59: Bottling Investments | J59: 389 | K59: 319 | L59: 313 | Q59: 76 | R59: 76 | S59: 78 | T59: 83 | U59: 86
A60: Corporate | J60: 144 | K60: 176 | L60: 159 | Q60: 47 | R60: 49 | S60: 47 | T60: 15 | U60: 16
A61: Consolidated (as reported) | J61: 1128 | K61: 1075 | L61: 1050 | Q61: 267 | R61: 279 | S61: 268 | T61: 264 | U61: 266
A62: Check: segments + Corporate - Consolidated (≈0) | J62: =J55+J56+J57+J58+J59+J60-J61 -> 0 | K62: =K55+K56+K57+K58+K59+K60-K61 -> 0 | L62: =L55+L56+L57+L58+L59+L60-L61 -> 0
A64: Capital expenditures
A65: EMEA | J65: 235 | K65: 222 | L65: 237 | Q65: 41 | R65: 49 | S65: 66 | T65: 53 | U65: 47
A66: Latin America | J66: 1 | K66: 1 | L66: 2 | Q66: 0 | R66: 1 | S66: 0 | T66: 0 | U66: 0
A67: North America | J67: 412 | K67: 602 | L67: 669 | Q67: 115 | R67: 154 | S67: 176 | T67: 83 | U67: 179
A68: Asia Pacific | J68: 23 | K68: 18 | L68: 72 | Q68: 1 | R68: 4 | S68: 12 | T68: 1 | U68: 0
A69: Bottling Investments | J69: 843 | K69: 734 | L69: 547 | Q69: 105 | R69: 119 | S69: 105 | T69: 74 | U69: 91
A70: Corporate | J70: 338 | K70: 487 | L70: 585 | Q70: 47 | R70: 115 | S70: 120 | T70: 55 | U70: 101
A71: Consolidated (as reported) | J71: 1852 | K71: 2064 | L71: 2112 | Q71: 309 | R71: 442 | S71: 479 | T71: 266 | U71: 418
A72: Check: segments + Corporate - Consolidated (≈0) | J72: =J65+J66+J67+J68+J69+J70-J71 -> 0 | K72: =K65+K66+K67+K68+K69+K70-K71 -> 0 | L72: =L65+L66+L67+L68+L69+L70-L71 -> 0
A74: Info: third-party total - IS net operating revenues (differences = in… | B74: Full label: Info: third-party total - IS net operating revenues (differences = intersegment revenue and later restatements) | J74: =J19-'Income Statement'!J11 -> 0 | K74: =K19-'Income Statement'!K11 -> 0 | L74: =L19-'Income Statement'!L11 -> 0 | Q74: =Q19-'Income Statement'!Q11 -> 0 | R74: =R19-'Income Statement'!R11 -> 0 | S74: =S19-'Income Statement'!S11 -> 0 | T74: =T19-'Income Statement'!T11 -> 0 | U74: =U19-'Income Statement'!U11 -> 0
A75: Info: total net operating revenues - IS net operating revenues (diffe… | B75: Full label: Info: total net operating revenues - IS net operating revenues (differences = later restatements only) | J75: =J41-'Income Statement'!J11 -> 0 | K75: =K41-'Income Statement'!K11 -> 0 | L75: =L41-'Income Statement'!L11 -> 0 | Q75: =Q41-'Income Statement'!Q11 -> 0 | R75: =R41-'Income Statement'!R11 -> 0 | S75: =S41-'Income Statement'!S11 -> 0 | T75: =T41-'Income Statement'!T11 -> 0 | U75: =U41-'Income Statement'!U11 -> 0
A76: Check: segment third-party revenue vs IS net operating revenues (≈0) | J76: =J19-'Income Statement'!J11 -> 0 | K76: =K19-'Income Statement'!K11 -> 0 | L76: =L19-'Income Statement'!L11 -> 0 | Q76: =Q13+Q14+Q15+Q16+Q17+Q18-Q19 -> 0 | R76: =R13+R14+R15+R16+R17+R18-R19 -> 0 | S76: =S13+S14+S15+S16+S17+S18-S19 -> 0 | T76: =T13+T14+T15+T16+T17+T18-T19 -> 0 | U76: =U13+U14+U15+U16+U17+U18-U19 -> 0
A77: Check: segment operating income vs IS operating income (≈0) | J77: =J51-'Income Statement'!J18 -> 0 | K77: =K51-'Income Statement'!K18 -> 0 | L77: =L51-'Income Statement'!L18 -> 0 | Q77: =Q45+Q46+Q47+Q48+Q49+Q50-Q51 -> 0 | R77: =R45+R46+R47+R48+R49+R50-R51 -> 0 | S77: =S45+S46+S47+S48+S49+S50-S51 -> 0 | T77: =T45+T46+T47+T48+T49+T50-T51 -> 0 | U77: =U45+U46+U47+U48+U49+U50-U51 -> 0
A78: Check: segment D&A vs CF depreciation and amortization (≈0) | J78: =J61-'Cash Flow'!J17 -> 0 | K78: =K61-'Cash Flow'!K17 -> 0 | L78: =L61-'Cash Flow'!L17 -> 0 | Q78: =Q55+Q56+Q57+Q58+Q59+Q60-Q61 -> 0 | R78: =R55+R56+R57+R58+R59+R60-R61 -> 0 | S78: =S55+S56+S57+S58+S59+S60-S61 -> 0 | T78: =T55+T56+T57+T58+T59+T60-T61 -> 0 | U78: =U55+U56+U57+U58+U59+U60-U61 -> 0
A79: Info: segment capex + CF purchases of PP&E (definitions differ) | J79: =J71+'Cash Flow'!J32 -> 0 | K79: =K71+'Cash Flow'!K32 -> 0 | L79: =L71+'Cash Flow'!L32 -> 0 | Q79: =Q65+Q66+Q67+Q68+Q69+Q70-Q71 -> 0 | R79: =R65+R66+R67+R68+R69+R70-R71 -> 0 | S79: =S65+S66+S67+S68+S69+S70-S71 -> 0 | T79: =T65+T66+T67+T68+T69+T70-T71 -> 0 | U79: =U65+U66+U67+U68+U69+U70-U71 -> 0
A80: EMEA operating margin (op. income / third-party revenue) | J80: =J45/J13 -> 0.42582742 | K80: =K45/K13 -> 0.41399105 | L80: =L45/L13 -> 0.39675067 | Q80: =IFERROR(Q45/Q13,"") -> 0.42926239 | R80: =IFERROR(R45/R13,"") -> 0.44049202 | S80: =IFERROR(S45/S13,"") -> 0.38928318 | T80: =IFERROR(T45/T13,"") -> 0.44852155 | U80: =IFERROR(U45/U13,"") -> 0.42403628
A81: Latin America operating margin (op. income / third-party revenue) | J81: =J46/J14 -> 0.58896126 | K81: =K46/K14 -> 0.58599907 | L81: =L46/L14 -> 0.59105986 | Q81: =IFERROR(Q46/Q14,"") -> 0.61205146 | R81: =IFERROR(R46/R14,"") -> 0.60302457 | S81: =IFERROR(S46/S14,"") -> 0.57061069 | T81: =IFERROR(T46/T14,"") -> 0.61859356 | U81: =IFERROR(U46/U14,"") -> 0.64002175
A82: North America operating margin (op. income / third-party revenue) | J82: =J47/J15 -> 0.2731506 | K82: =K47/K15 -> 0.24156946 | L82: =L47/L15 -> 0.25895092 | Q82: =IFERROR(Q47/Q15,"") -> 0.30763937 | R82: =IFERROR(R47/R15,"") -> 0.32239459 | S82: =IFERROR(S47/S15,"") -> 0.32025148 | T82: =IFERROR(T47/T15,"") -> 0.32835821 | U82: =IFERROR(U47/U15,"") -> 0.31359852
A83: Asia Pacific operating margin (op. income / third-party revenue) | J83: =J48/J16 -> 0.42756184 | K83: =K48/K16 -> 0.42051882 | L83: =L48/L16 -> 0.38325826 | Q83: =IFERROR(Q48/Q16,"") -> 0.4709434 | R83: =IFERROR(R48/R16,"") -> 0.44193989 | S83: =IFERROR(S48/S16,"") -> 0.36230876 | T83: =IFERROR(T48/T16,"") -> 0.37587658 | U83: =IFERROR(U48/U16,"") -> 0.44115669
A84: Bottling Investments operating margin (op. income / third-party reven… | B84: Full label: Bottling Investments operating margin (op. income / third-party revenue) | J84: =J49/J17 -> 0.073611819 | K84: =K49/K17 -> 0.079806919 | L84: =L49/L17 -> 0.074397485 | Q84: =IFERROR(Q49/Q17,"") -> 0.081451061 | R84: =IFERROR(R49/R17,"") -> 0.041873669 | S84: =IFERROR(S49/S17,"") -> 0.042410714 | T84: =IFERROR(T49/T17,"") -> 0.11660562 | U84: =IFERROR(U49/U17,"") -> 0.059672131
A86: 2. SEGMENTS — BASIS B (FY2019-FY2024 10-K presentation incl. Global Ventures; FY2017-FY2024, each year from the latest 10-K presenting it on this basis)
A87: Third-party net operating revenues
A88: EMEA | D88: 6780 | E88: 6535 | F88: 6434 | G88: 5534 | H88: 6564 | I88: 6896 | J88: 7392 | K88: 7442 | P88: 1847
A89: Latin America | D89: 3953 | E89: 3971 | F89: 4118 | G89: 3499 | H89: 4143 | I89: 4910 | J89: 5830 | K89: 6459 | P89: 1639
A90: North America | D90: 8678 | E90: 11370 | F90: 11906 | G90: 11473 | H90: 13184 | I90: 15667 | J90: 16766 | K90: 18640 | P90: 4983
A91: Asia Pacific | D91: 4753 | E91: 4797 | F91: 4723 | G91: 4213 | H91: 4682 | I91: 4711 | J91: 4724 | K91: 5079 | P91: 1272
A92: Global Ventures | D92: 712 | E92: 767 | F92: 2560 | G92: 1991 | H92: 2805 | I92: 2843 | J92: 3064 | K92: 3129 | P92: 781
A93: Bottling Investments | D93: 11223 | E93: 6768 | F93: 7431 | G93: 6258 | H93: 7194 | I93: 7883 | J93: 7852 | K93: 6215 | P93: 1314
A94: Corporate | D94: 113 | E94: 92 | F94: 94 | G94: 46 | H94: 83 | I94: 94 | J94: 126 | K94: 97 | P94: 18
A95: Consolidated (as reported) | D95: 36212 | E95: 34300 | F95: 37266 | G95: 33014 | H95: 38655 | I95: 43004 | J95: 45754 | K95: 47061 | P95: 11854
A96: Check: segments + Corporate - Consolidated (≈0) | D96: =D88+D89+D90+D91+D92+D93+D94-D95 -> 0 | E96: =E88+E89+E90+E91+E92+E93+E94-E95 -> 0 | F96: =F88+F89+F90+F91+F92+F93+F94-F95 -> 0 | G96: =G88+G89+G90+G91+G92+G93+G94-G95 -> 0 | H96: =H88+H89+H90+H91+H92+H93+H94-H95 -> 0 | I96: =I88+I89+I90+I91+I92+I93+I94-I95 -> 0 | J96: =J88+J89+J90+J91+J92+J93+J94-J95 -> 0 | K96: =K88+K89+K90+K91+K92+K93+K94-K95 -> 0
A98: Intersegment net operating revenues
A99: EMEA | D99: 42 | E99: 564 | F99: 624 | G99: 523 | H99: 629 | I99: 627 | J99: 686 | K99: 680 | P99: 172
A100: Latin America | D100: 73 | E100: 39 | F100: 0 | G100: 0 | H100: 0 | I100: 0 | J100: 0 | K100: 0 | P100: 0
A101: North America | D101: 1951 | E101: 260 | F101: 9 | G101: 4 | H101: 6 | I101: 7 | J101: 8 | K101: 9 | P101: 1
A102: Asia Pacific | D102: 409 | E102: 388 | F102: 604 | G102: 509 | H102: 609 | I102: 734 | J102: 731 | K102: 467 | P102: 77
A103: Global Ventures | D103: 3 | E103: 3 | F103: 2 | G103: 0 | H103: 0 | I103: 0 | J103: 0 | K103: 0 | P103: 0
A104: Bottling Investments | D104: 83 | E104: 19 | F104: 9 | G104: 7 | H104: 9 | I104: 8 | J104: 8 | K104: 8 | P104: 2
A105: Corporate | D105: 0 | E105: 0 | F105: 0 | G105: 0 | H105: 2 | I105: 0 | J105: 0 | K105: 0 | P105: 0
A106: Eliminations | D106: -2561 | E106: -1273 | F106: -1248 | G106: -1043 | H106: -1255 | I106: -1376 | J106: -1433 | K106: -1164 | P106: -252
A107: Consolidated (as reported) | D107: 0 | E107: 0 | F107: 0 | G107: 0 | H107: 0 | I107: 0 | J107: 0 | K107: 0 | P107: =P99+P100+P101+P102+P103+P104+P105+P106 -> 0
A108: Check: segments + Corporate - Consolidated (≈0) | D108: =D99+D100+D101+D102+D103+D104+D105+D106-D107 -> 0 | E108: =E99+E100+E101+E102+E103+E104+E105+E106-E107 -> 0 | F108: =F99+F100+F101+F102+F103+F104+F105+F106-F107 -> 0 | G108: =G99+G100+G101+G102+G103+G104+G105+G106-G107 -> 0 | H108: =H99+H100+H101+H102+H103+H104+H105+H106-H107 -> 0 | I108: =I99+I100+I101+I102+I103+I104+I105+I106-I107 -> 0 | J108: =J99+J100+J101+J102+J103+J104+J105+J106-J107 -> 0 | K108: =K99+K100+K101+K102+K103+K104+K105+K106-K107 -> 0
A110: Total net operating revenues (third-party + intersegment)
A111: EMEA | D111: 6822 | E111: 7099 | F111: 7058 | G111: 6057 | H111: 7193 | I111: 7523 | J111: 8078 | K111: 8122 | P111: 2019
...

Sheet Geography
A1: The Coca-Cola Company — Geography
A2: $ in millions except per-share data | USD | as of 2026-10-14
C3: FY2016 | D3: FY2017 | E3: FY2018 | F3: FY2019 | G3: FY2020 | H3: FY2021 | I3: FY2022 | J3: FY2023 | K3: FY2024 | L3: FY2025 | M3: · | N3: · | O3: · | P3: 3Q2024 | Q3: 1Q2025 | R3: 2Q2025 | S3: 3Q2025 | T3: 1Q2026 | U3: 2Q2026
C4: 2016-12-31 | D4: 2017-12-31 | E4: 2018-12-31 | F4: 2019-12-31 | G4: 2020-12-31 | H4: 2021-12-31 | I4: 2022-12-31 | J4: 2023-12-31 | K4: 2024-12-31 | L4: 2025-12-31 | P4: 2024-09-27 | Q4: 2025-03-28 | R4: 2025-06-27 | S4: 2025-09-26 | T4: 2026-04-03 | U4: 2026-07-03
A6: CONTENTS
A7: =HYPERLINK("#'Geography'!A10","1. NET OPERATING REVENUES BY GEOGRAPHY (Note: Operating Segments — Geographic and Customer Data)") -> 1. NET OPERATING REVENUES BY GEOGRAPHY (Note: Operating Segments — Geographic and Customer Data)
A8: =HYPERLINK("#'Geography'!A20","2. PROPERTY, PLANT AND EQUIPMENT — NET BY GEOGRAPHY") -> 2. PROPERTY, PLANT AND EQUIPMENT — NET BY GEOGRAPHY
A10: 1. NET OPERATING REVENUES BY GEOGRAPHY (Note: Operating Segments — Geographic and Customer Data)
A11: United States | C11: 19899 | D11: 14727 | E11: 11344 | F11: 11715 | G11: 11281 | H11: 13010 | I11: 15413 | J11: 16550 | K11: 18362 | L11: 19127 | P11: 4903 | Q11: 4253 | R11: 4935 | S11: 5118 | T11: 4745 | U11: 5260
A12: International | C12: 21964 | D12: 21485 | E12: 22956 | F12: 25551 | G12: 21733 | H12: 25645 | I12: 27591 | J12: 29204 | K12: 28699 | L12: 28814 | P12: 6951 | Q12: 6876 | R12: 7600 | S12: 7337 | T12: 7727 | U12: 8120
A13: Net operating revenues (as reported) | C13: 41863 | D13: 36212 | E13: 34300 | F13: 37266 | G13: 33014 | H13: 38655 | I13: 43004 | J13: 45754 | K13: 47061 | L13: 47941 | P13: 11854 | Q13: 11129 | R13: 12535 | S13: 12455 | T13: 12472 | U13: 13380
A14: United States % of revenue | C14: =C11/C13 -> 0.47533622 | D14: =D11/D13 -> 0.40668839 | E14: =E11/E13 -> 0.33072886 | F14: =F11/F13 -> 0.31436162 | G14: =G11/G13 -> 0.34170352 | H14: =H11/H13 -> 0.33656707 | I14: =I11/I13 -> 0.35840852 | J14: =J11/J13 -> 0.36171701 | ... L14: =L11/L13 -> 0.39896957 | P14: =IFERROR(P11/P13,"") -> 0.41361566 | Q14: =IFERROR(Q11/Q13,"") -> 0.38215473 | R14: =IFERROR(R11/R13,"") -> 0.39369765 | S14: =IFERROR(S11/S13,"") -> 0.41091931 | T14: =IFERROR(T11/T13,"") -> 0.38045221 | U14: =IFERROR(U11/U13,"") -> 0.39312407
A15: International YoY Growth | D15: =IF(N(C12)=0,"",D12/C12-1) -> -0.021808414 | E15: =IF(N(D12)=0,"",E12/D12-1) -> 0.068466372 | F15: =IF(N(E12)=0,"",F12/E12-1) -> 0.11304234 | G15: =IF(N(F12)=0,"",G12/F12-1) -> -0.14942664 | H15: =IF(N(G12)=0,"",H12/G12-1) -> 0.18000276 | I15: =IF(N(H12)=0,"",I12/H12-1) -> 0.075882238 | J15: =IF(N(I12)=0,"",J12/I12-1) -> 0.058461092 | K15: =IF(N(J12)=0,"",K12/J12-1) -> -0.017292152 | L15: =IF(N(K12)=0,"",L12/K12-1) -> 0.0040071083 | S15: =IFERROR(S12/P12-1,"") -> 0.055531578 | T15: =IFERROR(T12/Q12-1,"") -> 0.12376382 | U15: =IFERROR(U12/R12-1,"") -> 0.068421053
A16: United States YoY Growth | D16: =IF(N(C11)=0,"",D11/C11-1) -> -0.25991256 | E16: =IF(N(D11)=0,"",E11/D11-1) -> -0.22971413 | F16: =IF(N(E11)=0,"",F11/E11-1) -> 0.032704513 | G16: =IF(N(F11)=0,"",G11/F11-1) -> -0.037046522 | H16: =IF(N(G11)=0,"",H11/G11-1) -> 0.15326655 | I16: =IF(N(H11)=0,"",I11/H11-1) -> 0.18470407 | J16: =IF(N(I11)=0,"",J11/I11-1) -> 0.073768896 | K16: =IF(N(J11)=0,"",K11/J11-1) -> 0.1094864 | L16: =IF(N(K11)=0,"",L11/K11-1) -> 0.041662128 | S16: =IFERROR(S11/P11-1,"") -> 0.043850704 | T16: =IFERROR(T11/Q11-1,"") -> 0.11568305 | U16: =IFERROR(U11/R11-1,"") -> 0.06585613
A17: Check: US + International - reported total (≈0) | C17: =C11+C12-C13 -> 0 | D17: =D11+D12-D13 -> 0 | E17: =E11+E12-E13 -> 0 | F17: =F11+F12-F13 -> 0 | G17: =G11+G12-G13 -> 0 | H17: =H11+H12-H13 -> 0 | I17: =I11+I12-I13 -> 0 | J17: =J11+J12-J13 -> 0 | ... L17: =L11+L12-L13 -> 0 | P17: =P11+P12-P13 -> 0 | Q17: =Q11+Q12-Q13 -> 0 | R17: =R11+R12-R13 -> 0 | S17: =S11+S12-S13 -> 0 | T17: =T11+T12-T13 -> 0 | U17: =U11+U12-U13 -> 0
A18: Check: geography total vs IS net operating revenues (≈0) | C18: =C13-'Income Statement'!C11 -> 0 | D18: =D13-'Income Statement'!D11 -> 0 | E18: =E13-'Income Statement'!E11 -> 0 | F18: =F13-'Income Statement'!F11 -> 0 | G18: =G13-'Income Statement'!G11 -> 0 | H18: =H13-'Income Statement'!H11 -> 0 | I18: =I13-'Income Statement'!I11 -> 0 | J18: =J13-'Income Statement'!J11 -> 0 | ... L18: =L13-'Income Statement'!L11 -> 0 | P18: =P13-'Income Statement'!P11 -> 0 | Q18: =Q13-'Income Statement'!Q11 -> 0 | R18: =R13-'Income Statement'!R11 -> 0 | S18: =S13-'Income Statement'!S11 -> 0 | T18: =T13-'Income Statement'!T11 -> 0 | U18: =U13-'Income Statement'!U11 -> 0
A20: 2. PROPERTY, PLANT AND EQUIPMENT — NET BY GEOGRAPHY
A21: United States | C21: 6784 | D21: 4163 | E21: 4154 | F21: 4062 | G21: 3988 | H21: 3420 | I21: 3494 | J21: 3682 | K21: 4364 | L21: 4825
A22: International | C22: 3851 | D22: 4040 | E22: 5444 | F22: 6776 | G22: 6789 | H22: 6500 | I22: 6347 | J22: 5554 | K22: 5939 | L22: 4788
A23: Property, plant and equipment — net (as reported) | C23: 10635 | D23: 8203 | E23: 9598 | F23: 10838 | G23: 10777 | H23: 9920 | I23: 9841 | J23: 9236 | K23: 10303 | L23: 9613
A24: Check: US + International - reported total (≈0) | C24: =C21+C22-C23 -> 0 | D24: =D21+D22-D23 -> 0 | E24: =E21+E22-E23 -> 0 | F24: =F21+F22-F23 -> 0 | G24: =G21+G22-G23 -> 0 | H24: =H21+H22-H23 -> 0 | I24: =I21+I22-I23 -> 0 | J24: =J21+J22-J23 -> 0 | ... L24: =L21+L22-L23 -> 0
A25: Check: geography total vs BS property, plant and equipment - net (≈0) | C25: =C23-'Balance Sheet'!C27 -> 0 | D25: =D23-'Balance Sheet'!D27 -> 0 | E25: =E23-'Balance Sheet'!E27 -> 0 | F25: =F23-'Balance Sheet'!F27 -> 0 | G25: =G23-'Balance Sheet'!G27 -> 0 | H25: =H23-'Balance Sheet'!H27 -> 0 | I25: =I23-'Balance Sheet'!I27 -> 0 | J25: =J23-'Balance Sheet'!J27 -> 0 | ... L25: =L23-'Balance Sheet'!L27 -> 0

Sheet Operating Metrics
A1: The Coca-Cola Company — Operating Metrics
A2: $ in millions except per-share data | USD | as of 2026-10-14
C3: FY2016 | D3: FY2017 | E3: FY2018 | F3: FY2019 | G3: FY2020 | H3: FY2021 | I3: FY2022 | J3: FY2023 | K3: FY2024 | L3: FY2025 | M3: · | N3: · | O3: · | P3: 3Q2024 | Q3: 1Q2025 | R3: 2Q2025 | S3: 3Q2025 | T3: 1Q2026 | U3: 2Q2026
C4: 2016-12-31 | D4: 2017-12-31 | E4: 2018-12-31 | F4: 2019-12-31 | G4: 2020-12-31 | H4: 2021-12-31 | I4: 2022-12-31 | J4: 2023-12-31 | K4: 2024-12-31 | L4: 2025-12-31 | P4: 2024-09-27 | Q4: 2025-03-28 | R4: 2025-06-27 | S4: 2025-09-26 | T4: 2026-04-03 | U4: 2026-07-03
A6: CONTENTS
A7: =HYPERLINK("#'Operating Metrics'!A13","1. BEVERAGE VOLUME — SYSTEM UNIT CASE VOLUME (Company disclosure, not from the financial statements)") -> 1. BEVERAGE VOLUME — SYSTEM UNIT CASE VOLUME (Company disclosure, not from the financial statements)
A8: =HYPERLINK("#'Operating Metrics'!A33","2. NET OPERATING REVENUE FACTORS — VOLUME / PRICE-MIX / FX / ACQUISITIONS & DIVESTITURES (% impact, as reported)") -> 2. NET OPERATING REVENUE FACTORS — VOLUME / PRICE-MIX / FX / ACQUISITIONS & DIVESTITURES (% impact, as reported)
A9: =HYPERLINK("#'Operating Metrics'!A87","3. NET OPERATING REVENUES BY LINE OF BUSINESS — CONCENTRATE VS FINISHED PRODUCT OPERATIONS (Note 3)") -> 3. NET OPERATING REVENUES BY LINE OF BUSINESS — CONCENTRATE VS FINISHED PRODUCT OPERATIONS (Note 3)
A10: =HYPERLINK("#'Operating Metrics'!A108","4. REVENUE MIX — OPERATING SEGMENT % OF COMPANY NET OPERATING REVENUES (as reported; Global Ventures exists FY2019-FY2024 only)") -> 4. REVENUE MIX — OPERATING SEGMENT % OF COMPANY NET OPERATING REVENUES (as reported; Global Ventures exists FY2019-FY2024 only)
A11: =HYPERLINK("#'Operating Metrics'!A118","5. CUSTOMER CONCENTRATION") -> 5. CUSTOMER CONCENTRATION
A13: 1. BEVERAGE VOLUME — SYSTEM UNIT CASE VOLUME (Company disclosure, not from the financial statements)
A14: Unit case volume (billion unit cases) | B14: Company-reported Coca-Cola system unit case volume; the sentence in each 10-K lists that year and the two prior years. Values are in billion unit cases as printed. | C14: 29.3 | D14: 29.2 | E14: 29.6 | F14: 30.3 | G14: 29 | H14: 31.3 | I14: 32.7 | J14: 33.3 | K14: 33.7 | L14: 33.8
A15: YoY Growth | B15: Growth calculated from rounded billion-case totals; may differ from issuer-reported comparable volume growth below (calendar and structural adjustments). | D15: =IF(N(C14)=0,"",D14/C14-1) -> -0.0034129693 | E15: =IF(N(D14)=0,"",E14/D14-1) -> 0.01369863 | F15: =IF(N(E14)=0,"",F14/E14-1) -> 0.023648649 | G15: =IF(N(F14)=0,"",G14/F14-1) -> -0.04290429 | H15: =IF(N(G14)=0,"",H14/G14-1) -> 0.079310345 | I15: =IF(N(H14)=0,"",I14/H14-1) -> 0.044728435 | J15: =IF(N(I14)=0,"",J14/I14-1) -> 0.018348624 | K15: =IF(N(J14)=0,"",K14/J14-1) -> 0.012012012 | L15: =IF(N(K14)=0,"",L14/K14-1) -> 0.0029673591
A17: Unit case volume growth by operating segment (as reported)
A18: Worldwide | C18: 0.01 | D18: 0 | E18: 0.02 | F18: 0.02 | G18: -0.06 | H18: 0.08 | I18: 0.05 | J18: 0.02 | K18: 0.01 | L18: 0 | P18: -0.01 | Q18: 0.02 | R18: -0.01 | S18: 0.01 | T18: 0.03 | U18: 0.05
A19: EMEA | C19: 0.01 | D19: 0.01 | E19: 0.02 | F19: 0.02 | G19: -0.06 | H19: 0.09 | I19: 0.03 | J19: -0.02 | K19: 0 | L19: 0.03 | P19: -0.02 | Q19: 0.03 | R19: 0.03 | S19: 0.04 | T19: 0.02 | U19: 0.04
A20: Latin America | C20: -0.01 | D20: -0.02 | E20: 0 | F20: 0.01 | G20: -0.02 | H20: 0.06 | I20: 0.06 | J20: 0.05 | K20: 0.03 | L20: 0 | P20: 0 | Q20: 0 | R20: -0.02 | S20: 0 | T20: 0.01 | U20: 0.03
A21: North America | C21: 0.01 | D21: 0 | E21: 0 | F21: 0 | G21: -0.07 | H21: 0.05 | I21: 0.02 | J21: -0.01 | K21: 0 | L21: -0.01 | P21: 0 | Q21: -0.03 | R21: -0.01 | S21: 0 | T21: 0.04 | U21: 0.03
A22: Bottling Investments | C22: -0.16 | D22: -0.41 | E22: -0.15 | F22: 0.24 | G22: -0.15 | H22: 0.11 | I22: 0.12 | J22: -0.01 | K22: -0.23 | L22: -0.08 | P22: -0.31 | Q22: -0.17 | R22: -0.05 | S22: 0.02 | T22: 0.01 | U22: 0.05
A23: Asia Pacific | C23: 0.02 | D23: 0.01 | E23: 0.04 | F23: 0.05 | G23: -0.09 | H23: 0.1 | I23: 0.06 | J23: 0.03 | K23: 0.01 | L23: 0 | P23: -0.02 | Q23: 0.06 | R23: -0.03 | S23: -0.01 | T23: 0.05 | U23: 0.08
A24: Global Ventures | B24: Global Ventures FY2018 is the comparative disclosed in FY2019 10-K, including acquired-business history; FY2019 excludes Costa non-ready-to-drink volume. See the volume footnotes; segment dissolved in FY2025. | E24: 0.08 | F24: 0.07 | G24: -0.13 | H24: 0.17 | I24: 0.13 | J24: 0.04 | K24: 0.02 | P24: 0.01
A26: Concentrate sales volume growth by operating segment (as reported)
A27: Worldwide | C27: 0 | D27: 0 | E27: 0.03 | F27: 0.02 | G27: -0.07 | H27: 0.09 | I27: 0.05 | J27: 0.02 | K27: 0.01 | L27: 0.01 | P27: -0.01 | Q27: 0.01 | R27: -0.01 | S27: 0 | T27: 0.08 | U27: 0.04
A28: EMEA | C28: 0 | D28: 0.01 | E28: 0.06 | F28: 0.01 | G28: -0.08 | H28: 0.12 | I28: 0.02 | J28: 0 | K28: -0.01 | L28: 0.03 | P28: -0.07 | Q28: 0.01 | R28: 0.02 | S28: 0.03 | T28: 0.05 | U28: 0.01
A29: Latin America | C29: -0.01 | D29: -0.03 | E29: 0.01 | F29: 0.01 | G29: -0.02 | H29: 0.06 | I29: 0.07 | J29: 0.06 | K29: 0.03 | L29: -0.01 | P29: 0.02 | Q29: -0.03 | R29: -0.01 | S29: -0.03 | T29: 0.07 | U29: 0.01
A30: Bottling Investments | B30: Company explicitly reports concentrate sales for Bottling Investments as N/A; N/A is neither zero nor the adjacent footnote number. | C30: N/A | D30: N/A | E30: N/A | F30: N/A | G30: N/A | H30: N/A | I30: N/A | J30: N/A | K30: N/A | L30: N/A | P30: N/A | Q30: N/A | R30: N/A | S30: N/A | T30: N/A | U30: N/A
A31: North America | C31: 0.02 | D31: 0.02 | E31: -0.02 | F31: -0.01 | G31: -0.07 | H31: 0.07 | I31: 0.01 | J31: -0.01 | K31: 0.01 | L31: -0.01 | P31: 0.01 | Q31: -0.04 | R31: 0 | S31: -0.02 | T31: 0.11 | U31: 0.03
A32: Asia Pacific | C32: 0.03 | D32: 0.04 | E32: 0.04 | F32: 0.04 | G32: -0.09 | H32: 0.11 | I32: 0.08 | J32: 0 | K32: 0.03 | L32: 0 | P32: -0.03 | Q32: 0.02 | R32: -0.05 | S32: -0.01 | T32: 0.1 | U32: 0.1
A33: 2. NET OPERATING REVENUE FACTORS — VOLUME / PRICE-MIX / FX / ACQUISITIONS & DIVESTITURES (% impact, as reported)
A34: Net operating revenue impact — Volume
A35: Consolidated | F35: 0.01 | G35: -0.07 | H35: 0.09 | I35: 0.05 | J35: 0.02 | K35: 0.02 | L35: 0.01 | P35: -0.02 | Q35: 0.01 | R35: -0.01 | S35: 0 | T35: 0.08 | U35: 0.04
A36: Asia Pacific | F36: 0.05 | G36: -0.1 | H36: 0.11 | I36: 0.08 | J36: 0 | K36: 0.02 | L36: 0.01 | P36: -0.04 | Q36: 0.08 | R36: -0.05 | S36: -0.01 | T36: 0.1 | U36: 0.11
A37: Bottling Investments | F37: 0.06 | G37: -0.13 | H37: 0.11 | I37: 0.12 | J37: 0.06 | K37: 0.05 | L37: 0 | P37: -0.01 | Q37: -0.01 | R37: -0.02 | S37: 0.05 | T37: 0.11 | U37: 0.08
A38: EMEA | F38: 0.01 | G38: -0.08 | H38: 0.12 | I38: 0.02 | J38: 0 | K38: -0.01 | L38: 0.04 | P38: -0.07 | Q38: 0.01 | R38: 0.02 | S38: 0.03 | T38: 0.05 | U38: 0.01
A39: Global Ventures | F39: 0.08 | G39: -0.13 | H39: 0.2 | I39: 0.13 | J39: 0.05 | K39: 0.04 | P39: 0.01
A40: Latin America | F40: 0.01 | G40: -0.02 | H40: 0.06 | I40: 0.07 | J40: 0.06 | K40: 0.03 | L40: -0.01 | P40: 0.02 | Q40: -0.03 | R40: -0.01 | S40: -0.03 | T40: 0.07 | U40: 0.01
A41: North America | F41: 0 | G41: -0.07 | H41: 0.07 | I41: 0.01 | J41: -0.01 | K41: 0.01 | L41: -0.01 | P41: 0.01 | Q41: -0.04 | R41: 0 | S41: -0.02 | T41: 0.11 | U41: 0.03
A43: Net operating revenue impact — Price/Mix
A44: Consolidated | F44: 0.05 | G44: -0.02 | H44: 0.06 | I44: 0.11 | J44: 0.1 | K44: 0.11 | L44: 0.04 | P44: 0.1 | Q44: 0.05 | R44: 0.06 | S44: 0.06 | T44: 0.02 | U44: 0.02
A45: Asia Pacific | F45: 0 | G45: -0.02 | H45: -0.02 | I45: 0.03 | J45: 0.05 | K45: 0.02 | L45: 0.04 | P45: 0.07 | Q45: -0.01 | R45: 0.1 | S45: 0.08 | T45: -0.06 | U45: -0.09
A46: Bottling Investments | F46: 0.03 | G46: 0.02 | H46: 0.02 | I46: 0.07 | J46: 0.08 | K46: 0.05 | L46: 0.02 | P46: 0.04 | Q46: 0.03 | R46: 0 | S46: 0.01 | T46: -0.01 | U46: 0.02
A47: EMEA | F47: 0.04 | G47: -0.05 | H47: 0.06 | I47: 0.16 | J47: 0.19 | K47: 0.17 | L47: 0.02 | P47: 0.09 | Q47: 0.06 | R47: 0.03 | S47: 0.04 | T47: 0.05 | U47: 0.01
A48: Global Ventures | F48: -0.01 | G48: -0.09 | H48: 0.13 | I48: 0 | J48: 0.02 | K48: -0.03 | P48: -0.03
A49: Latin America | F49: 0.13 | G49: 0.02 | H49: 0.12 | I49: 0.17 | J49: 0.16 | K49: 0.21 | L49: 0.11 | P49: 0.21 | Q49: 0.16 | R49: 0.15 | S49: 0.07 | T49: 0.01 | U49: 0.03
A50: North America | F50: 0.03 | G50: 0.02 | H50: 0.07 | I50: 0.12 | J50: 0.08 | K50: 0.1 | L50: 0.05 | P50: 0.11 | Q50: 0.08 | R50: 0.03 | S50: 0.06 | T50: 0.01 | U50: 0.04
A52: Net operating revenue impact — FX
A53: Consolidated | F53: -0.04 | G53: -0.02 | H53: 0.01 | I53: -0.07 | J53: -0.04 | K53: -0.05 | L53: -0.02 | P53: -0.05 | Q53: -0.05 | R53: -0.03 | S53: 0 | T53: 0.03 | U53: 0.02
A54: Asia Pacific | F54: -0.01 | G54: 0 | H54: 0.03 | I54: -0.09 | J54: -0.05 | K54: -0.03 | L54: -0.03 | P54: -0.07 | Q54: -0.06 | R54: -0.02 | S54: 0.04 | T54: 0.02 | U54: -0.01
A55: Bottling Investments | F55: -0.05 | G55: -0.04 | H55: 0.02 | I55: -0.09 | J55: -0.07 | K55: -0.02 | L55: -0.02 | P55: -0.01 | Q55: -0.03 | R55: -0.04 | S55: -0.02 | T55: 0.04 | U55: 0
A56: EMEA | F56: -0.09 | G56: -0.02 | H56: 0.01 | I56: -0.14 | J56: -0.12 | K56: -0.16 | L56: 0 | P56: -0.1 | Q56: -0.06 | R56: 0.01 | S56: 0.03 | T56: 0.06 | U56: 0.02
A57: Global Ventures | F57: -0.16 | G57: 0.01 | H57: 0.07 | I57: -0.11 | J57: 0 | K57: 0.02 | P57: 0.02
A58: Latin America | F58: -0.1 | G58: -0.14 | H58: 0 | I58: -0.05 | J58: -0.03 | K58: -0.14 | L58: -0.12 | P58: -0.2 | Q58: -0.16 | R58: -0.17 | S58: -0.08 | T58: 0.05 | U58: 0.11
A59: North America | F59: 0 | G59: 0 | H59: 0 | I59: 0 | J59: 0 | K59: 0 | L59: 0 | P59: 0 | Q59: 0 | R59: 0 | S59: 0 | T59: 0 | U59: 0
A61: Net operating revenue impact — Acquisitions & Divestitures
A62: Consolidated | F62: 0.07 | G62: 0 | H62: 0 | I62: 0.02 | J62: -0.01 | K62: -0.04 | L62: -0.01 | P62: -0.04 | Q62: -0.03 | R62: 0 | S62: 0 | T62: -0.01 | U62: -0.01
A63: Asia Pacific | F63: -0.01 | G63: 0 | H63: 0 | I63: 0 | J63: 0.01 | K63: 0 | L63: -0.01 | P63: 0 | Q63: -0.05 | R63: 0 | S63: 0 | T63: 0 | U63: 0
A64: Bottling Investments | F64: 0.05 | G64: -0.02 | H64: 0 | I64: 0 | J64: -0.08 | K64: -0.28 | L64: -0.07 | P64: -0.32 | Q64: -0.18 | R64: -0.03 | S64: -0.02 | T64: -0.02 | U64: -0.02
A65: EMEA | F65: 0.03 | G65: 0 | H65: 0 | I65: 0 | J65: 0 | K65: 0 | L65: -0.01 | P65: 0 | Q65: 0 | R65: 0 | S65: 0 | T65: -0.03 | U65: -0.03
A66: Global Ventures | F66: 2.42 | G66: 0 | H66: 0 | I66: 0 | J66: 0 | K66: 0 | P66: 0
A67: Latin America | F67: 0 | G67: 0 | H67: 0 | I67: 0 | J67: 0 | K67: 0 | L67: 0 | P67: 0 | Q67: 0 | R67: 0 | S67: 0 | T67: 0 | U67: 0
A68: North America | F68: 0 | G68: 0.02 | H68: 0 | I68: 0.06 | J68: 0 | K68: 0 | L68: 0 | P68: 0 | Q68: 0 | R68: 0 | S68: 0 | T68: 0 | U68: 0
A70: Net operating revenue impact — Total
A71: Consolidated | F71: 0.09 | G71: -0.11 | H71: 0.17 | I71: 0.11 | J71: 0.06 | K71: 0.03 | L71: 0.02 | P71: -0.01 | Q71: -0.02 | R71: 0.01 | S71: 0.05 | T71: 0.12 | U71: 0.07
A72: Asia Pacific | F72: 0.03 | G72: -0.11 | H72: 0.12 | I72: 0.03 | J72: 0 | K72: 0.02 | L72: 0.01 | P72: -0.04 | Q72: -0.04 | R72: 0.03 | S72: 0.11 | T72: 0.06 | U72: 0.01
A73: Bottling Investments | F73: 0.1 | G73: -0.16 | H73: 0.15 | I73: 0.1 | J73: 0 | K73: -0.21 | L73: -0.08 | P73: -0.29 | Q73: -0.2 | R73: -0.08 | S73: 0.02 | T73: 0.12 | U73: 0.08
A74: EMEA | F74: -0.01 | G74: -0.14 | H74: 0.19 | I74: 0.05 | J74: 0.07 | K74: 0.01 | L74: 0.05 | P74: -0.07 | Q74: 0.01 | R74: 0.05 | S74: 0.1 | T74: 0.13 | U74: 0.02
A75: Global Ventures | F75: 2.33 | G75: -0.22 | H75: 0.41 | I75: 0.01 | J75: 0.08 | K75: 0.02 | P75: 0
A76: Latin America | F76: 0.03 | G76: -0.15 | H76: 0.18 | I76: 0.19 | J76: 0.19 | K76: 0.11 | L76: -0.02 | P76: 0.04 | Q76: -0.03 | R76: -0.04 | S76: -0.04 | T76: 0.14 | U76: 0.16
A77: North America | F77: 0.02 | G77: -0.04 | H77: 0.15 | I77: 0.19 | J77: 0.07 | K77: 0.11 | L77: 0.04 | P77: 0.12 | Q77: 0.03 | R77: 0.03 | S77: 0.04 | T77: 0.12 | U77: 0.07
A79: Check: Consolidated revenue factors sum to Total (≈0) | F79: =F35+F44+F53+F62-F71 -> 0 | G79: =G35+G44+G53+G62-G71 -> 0 | H79: =H35+H44+H53+H62-H71 -> -0.01 | I79: =I35+I44+I53+I62-I71 -> 0 | J79: =J35+J44+J53+J62-J71 -> 0.01 | K79: =K35+K44+K53+K62-K71 -> 0.01 | L79: =L35+L44+L53+L62-L71 -> 0 | P79: =P35+P44+P53+P62-P71 -> 0 | Q79: =Q35+Q44+Q53+Q62-Q71 -> 0 | R79: =R35+R44+R53+R62-R71 -> 0.01 | S79: =S35+S44+S53+S62-S71 -> 0.01 | T79: =T35+T44+T53+T62-T71 -> 0 | U79: =U35+U44+U53+U62-U71 -> 0
A80: Check: Asia Pacific revenue factors sum to Total (≈0) | F80: =F36+F45+F54+F63-F72 -> 0 | G80: =G36+G45+G54+G63-G72 -> -0.01 | H80: =H36+H45+H54+H63-H72 -> 0 | I80: =I36+I45+I54+I63-I72 -> -0.01 | J80: =J36+J45+J54+J63-J72 -> 0.01 | K80: =K36+K45+K54+K63-K72 -> -0.01 | L80: =L36+L45+L54+L63-L72 -> 0 | P80: =P36+P45+P54+P63-P72 -> 0 | Q80: =Q36+Q45+Q54+Q63-Q72 -> 0 | R80: =R36+R45+R54+R63-R72 -> 0 | S80: =S36+S45+S54+S63-S72 -> 0 | T80: =T36+T45+T54+T63-T72 -> 0 | U80: =U36+U45+U54+U63-U72 -> 0
A81: Check: Bottling Investments revenue factors sum to Total (≈0) | F81: =F37+F46+F55+F64-F73 -> -0.01 | G81: =G37+G46+G55+G64-G73 -> -0.01 | H81: =H37+H46+H55+H64-H73 -> 0 | I81: =I37+I46+I55+I64-I73 -> 0 | J81: =J37+J46+J55+J64-J73 -> -0.01 | K81: =K37+K46+K55+K64-K73 -> 0.01 | L81: =L37+L46+L55+L64-L73 -> 0.01 | P81: =P37+P46+P55+P64-P73 -> -0.01 | Q81: =Q37+Q46+Q55+Q64-Q73 -> 0.01 | R81: =R37+R46+R55+R64-R73 -> -0.01 | S81: =S37+S46+S55+S64-S73 -> 0 | T81: =T37+T46+T55+T64-T73 -> 0 | U81: =U37+U46+U55+U64-U73 -> 0
A82: Check: EMEA revenue factors sum to Total (≈0) | F82: =F38+F47+F56+F65-F74 -> 0 | G82: =G38+G47+G56+G65-G74 -> -0.01 | H82: =H38+H47+H56+H65-H74 -> 0 | I82: =I38+I47+I56+I65-I74 -> -0.01 | J82: =J38+J47+J56+J65-J74 -> 0 | K82: =K38+K47+K56+K65-K74 -> -0.01 | L82: =L38+L47+L56+L65-L74 -> 0 | P82: =P38+P47+P56+P65-P74 -> -0.01 | Q82: =Q38+Q47+Q56+Q65-Q74 -> 0 | R82: =R38+R47+R56+R65-R74 -> 0.01 | S82: =S38+S47+S56+S65-S74 -> 0 | T82: =T38+T47+T56+T65-T74 -> 0 | U82: =U38+U47+U56+U65-U74 -> -0.01
A83: Check: Global Ventures revenue factors sum to Total (≈0) | F83: =F39+F48+F57+F66-F75 -> 0 | G83: =G39+G48+G57+G66-G75 -> 0.01 | H83: =H39+H48+H57+H66-H75 -> -0.01 | I83: =I39+I48+I57+I66-I75 -> 0.01 | J83: =J39+J48+J57+J66-J75 -> -0.01 | K83: =K39+K48+K57+K66-K75 -> 0.01 | L83: =L39+L48+L57+L66-L75 -> 0 | P83: =P39+P48+P57+P66-P75 -> 3.469447e-18 | Q83: =Q39+Q48+Q57+Q66-Q75 -> 0 | R83: =R39+R48+R57+R66-R75 -> 0 | S83: =S39+S48+S57+S66-S75 -> 0 | T83: =T39+T48+T57+T66-T75 -> 0 | U83: =U39+U48+U57+U66-U75 -> 0
A84: Check: Latin America revenue factors sum to Total (≈0) | F84: =F40+F49+F58+F67-F76 -> 0.01 | G84: =G40+G49+G58+G67-G76 -> 0.01 | H84: =H40+H49+H58+H67-H76 -> 0 | I84: =I40+I49+I58+I67-I76 -> 0 | J84: =J40+J49+J58+J67-J76 -> 0 | K84: =K40+K49+K58+K67-K76 -> -0.01 | L84: =L40+L49+L58+L67-L76 -> 0 | P84: =P40+P49+P58+P67-P76 -> -0.01 | Q84: =Q40+Q49+Q58+Q67-Q76 -> 0 | R84: =R40+R49+R58+R67-R76 -> 0.01 | S84: =S40+S49+S58+S67-S76 -> 0 | T84: =T40+T49+T58+T67-T76 -> -0.01 | U84: =U40+U49+U58+U67-U76 -> -0.01
A85: Check: North America revenue factors sum to Total (≈0) | F85: =F41+F50+F59+F68-F77 -> 0.01 | G85: =G41+G50+G59+G68-G77 -> 0.01 | H85: =H41+H50+H59+H68-H77 -> -0.01 | I85: =I41+I50+I59+I68-I77 -> 0 | J85: =J41+J50+J59+J68-J77 -> 0 | K85: =K41+K50+K59+K68-K77 -> 0 | L85: =L41+L50+L59+L68-L77 -> 0 | P85: =P41+P50+P59+P68-P77 -> 0 | Q85: =Q41+Q50+Q59+Q68-Q77 -> 0.01 | R85: =R41+R50+R59+R68-R77 -> 0 | S85: =S41+S50+S59+S68-S77 -> 0 | T85: =T41+T50+T59+T68-T77 -> 0 | U85: =U41+U50+U59+U68-U77 -> 0
A87: 3. NET OPERATING REVENUES BY LINE OF BUSINESS — CONCENTRATE VS FINISHED PRODUCT OPERATIONS (Note 3)
A88: Concentrate operations | B88: Note 3: Business and Revenue Disclosures — net operating revenues disaggregated by line of business.
A89: United States | B89: Note 3: Business and Revenue Disclosures — net operating revenues disaggregated by line of business. | E89: 4571 | F89: 5252 | G89: 5443 | H89: 6551 | I89: 7702 | J89: 8780 | K89: 8813 | L89: 8956 | P89: 2283 | Q89: 1927 | R89: 2268 | S89: 2375 | T89: 2188 | U89: 2426
A90: International | B90: Note 3: Business and Revenue Disclosures — net operating revenues disaggregated by line of business. | E90: 15323 | F90: 15247 | G90: 13139 | H90: 15248 | I90: 16369 | J90: 17759 | K90: 18912 | L90: 19506 | P90: 4775 | Q90: 5256 | R90: 6021 | S90: 5823 | T90: 5197 | U90: 5720
A91: Total | B91: Note 3: Business and Revenue Disclosures — net operating revenues disaggregated by line of business. | E91: 19894 | F91: 20499 | G91: 18582 | H91: 21799 | I91: 24071 | J91: 26539 | K91: 27725 | L91: 28462 | P91: 7058 | Q91: 7183 | R91: 8289 | S91: 8198 | T91: 7385 | U91: 8146
A92: Check: Concentrate operations US + International - Total (≈0) | B92: Note 3: Business and Revenue Disclosures — net operating revenues disaggregated by line of business. | E92: =E89+E90-E91 -> 0 | F92: =F89+F90-F91 -> 0 | G92: =G89+G90-G91 -> 0 | H92: =H89+H90-H91 -> 0 | I92: =I89+I90-I91 -> 0 | J92: =J89+J90-J91 -> 0 | K92: =K89+K90-K91 -> 0 | L92: =L89+L90-L91 -> 0 | P92: =P89+P90-P91 -> 0 | Q92: =Q89+Q90-Q91 -> 0 | R92: =R89+R90-R91 -> 0 | S92: =S89+S90-S91 -> 0 | T92: =T89+T90-T91 -> 0 | U92: =U89+U90-U91 -> 0
A94: Finished product operations | B94: Note 3: Business and Revenue Disclosures — net operating revenues disaggregated by line of business.
A95: United States | B95: Note 3: Business and Revenue Disclosures — net operating revenues disaggregated by line of business. | E95: 6773 | F95: 6463 | G95: 5838 | H95: 6459 | I95: 7711 | J95: 7770 | K95: 9549 | L95: 10171 | P95: 2620 | Q95: 2326 | R95: 2667 | S95: 2743 | T95: 2557 | U95: 2834
A96: International | B96: Note 3: Business and Revenue Disclosures — net operating revenues disaggregated by line of business. | E96: 7633 | F96: 10304 | G96: 8594 | H96: 10397 | I96: 11222 | J96: 11445 | K96: 9787 | L96: 9308 | P96: 2176 | Q96: 1620 | R96: 1579 | S96: 1514 | T96: 2530 | U96: 2400
A97: Total | B97: Note 3: Business and Revenue Disclosures — net operating revenues disaggregated by line of business. | E97: 14406 | F97: 16767 | G97: 14432 | H97: 16856 | I97: 18933 | J97: 19215 | K97: 19336 | L97: 19479 | P97: 4796 | Q97: 3946 | R97: 4246 | S97: 4257 | T97: 5087 | U97: 5234
A98: Check: Finished product operations US + International - Total (≈0) | B98: Note 3: Business and Revenue Disclosures — net operating revenues disaggregated by line of business. | E98: =E95+E96-E97 -> 0 | F98: =F95+F96-F97 -> 0 | G98: =G95+G96-G97 -> 0 | H98: =H95+H96-H97 -> 0 | I98: =I95+I96-I97 -> 0 | J98: =J95+J96-J97 -> 0 | K98: =K95+K96-K97 -> 0 | L98: =L95+L96-L97 -> 0 | P98: =P95+P96-P97 -> 0 | Q98: =Q95+Q96-Q97 -> 0 | R98: =R95+R96-R97 -> 0 | S98: =S95+S96-S97 -> 0 | T98: =T95+T96-T97 -> 0 | U98: =U95+U96-U97 -> 0
A100: Total | B100: Note 3: Business and Revenue Disclosures — net operating revenues disaggregated by line of business.
A101: United States | B101: Note 3: Business and Revenue Disclosures — net operating revenues disaggregated by line of business. | E101: 11344 | F101: 11715 | G101: 11281 | H101: 13010 | I101: 15413 | J101: 16550 | K101: 18362 | L101: 19127 | P101: 4903 | Q101: 4253 | R101: 4935 | S101: 5118 | T101: 4745 | U101: 5260
A102: International | B102: Note 3: Business and Revenue Disclosures — net operating revenues disaggregated by line of business. | E102: 22956 | F102: 25551 | G102: 21733 | H102: 25645 | I102: 27591 | J102: 29204 | K102: 28699 | L102: 28814 | P102: 6951 | Q102: 6876 | R102: 7600 | S102: 7337 | T102: 7727 | U102: 8120
A103: Total | B103: Note 3: Business and Revenue Disclosures — net operating revenues disaggregated by line of business. | E103: 34300 | F103: 37266 | G103: 33014 | H103: 38655 | I103: 43004 | J103: 45754 | K103: 47061 | L103: 47941 | P103: 11854 | Q103: 11129 | R103: 12535 | S103: 12455 | T103: 12472 | U103: 13380
A104: Check: Total US + International - Total (≈0) | B104: Note 3: Business and Revenue Disclosures — net operating revenues disaggregated by line of business. | E104: =E101+E102-E103 -> 0 | F104: =F101+F102-F103 -> 0 | G104: =G101+G102-G103 -> 0 | H104: =H101+H102-H103 -> 0 | I104: =I101+I102-I103 -> 0 | J104: =J101+J102-J103 -> 0 | K104: =K101+K102-K103 -> 0 | L104: =L101+L102-L103 -> 0 | P104: =P101+P102-P103 -> 0 | Q104: =Q101+Q102-Q103 -> 0 | R104: =R101+R102-R103 -> 0 | S104: =S101+S102-S103 -> 0 | T104: =T101+T102-T103 -> 0 | U104: =U101+U102-U103 -> 0
A106: Check: line of business total vs IS net operating revenues (≈0) | B106: Note 3: Business and Revenue Disclosures — net operating revenues disaggregated by line of business. | E106: =E103-'Income Statement'!E11 -> 0 | F106: =F103-'Income Statement'!F11 -> 0 | G106: =G103-'Income Statement'!G11 -> 0 | H106: =H103-'Income Statement'!H11 -> 0 | I106: =I103-'Income Statement'!I11 -> 0 | J106: =J103-'Income Statement'!J11 -> 0 | K106: =K103-'Income Statement'!K11 -> 0 | L106: =L103-'Income Statement'!L11 -> 0 | P106: =P103-'Income Statement'!P11 -> 0 | Q106: =Q103-'Income Statement'!Q11 -> 0 | R106: =R103-'Income Statement'!R11 -> 0 | S106: =S103-'Income Statement'!S11 -> 0 | T106: =T103-'Income Statement'!T11 -> 0 | U106: =U103-'Income Statement'!U11 -> 0
A108: 4. REVENUE MIX — OPERATING SEGMENT % OF COMPANY NET OPERATING REVENUES (as reported; Global Ventures exists FY2019-FY2024 only)
A109: EMEA | E109: 0.191 | F109: 0.173 | G109: 0.168 | H109: 0.17 | I109: 0.16 | J109: 0.162 | K109: 0.218 | L109: 0.226 | P109: =IFERROR(Segments!P88/Segments!P95,"") -> 0.15581238 | Q109: =IFERROR(Segments!Q13/Segments!Q19,"") -> 0.22293108 | R109: =IFERROR(Segments!R13/Segments!R19,"") -> 0.23996809 | S109: =IFERROR(Segments!S13/Segments!S19,"") -> 0.22625452 | T109: =IFERROR(Segments!T13/Segments!T19,"") -> 0.22506414 | U109: =IFERROR(Segments!U13/Segments!U19,"") -> 0.23071749
A110: Latin America | E110: 0.116 | F110: 0.11 | G110: 0.106 | H110: 0.107 | I110: 0.114 | J110: 0.127 | K110: 0.138 | L110: 0.132 | P110: =IFERROR(Segments!P89/Segments!P95,"") -> 0.13826556 | Q110: =IFERROR(Segments!Q14/Segments!Q19,"") -> 0.13271633 | R110: =IFERROR(Segments!R14/Segments!R19,"") -> 0.1266055 | S110: =IFERROR(Segments!S14/Segments!S19,"") -> 0.12621437 | T110: =IFERROR(Segments!T14/Segments!T19,"") -> 0.13454137 | U110: =IFERROR(Segments!U14/Segments!U19,"") -> 0.13744395
A111: North America | E111: 0.331 | F111: 0.319 | G111: 0.347 | H111: 0.341 | I111: 0.365 | J111: 0.366 | K111: 0.401 | L111: 0.408 | P111: =IFERROR(Segments!P90/Segments!P95,"") -> 0.42036443 | Q111: =IFERROR(Segments!Q15/Segments!Q19,"") -> 0.3916794 | R111: =IFERROR(Segments!R15/Segments!R19,"") -> 0.40111687 | S111: =IFERROR(Segments!S15/Segments!S19,"") -> 0.42143717 | T111: =IFERROR(Segments!T15/Segments!T19,"") -> 0.39215843 | U111: =IFERROR(Segments!U15/Segments!U19,"") -> 0.40396114
A112: Asia Pacific | E112: 0.14 | F112: 0.127 | G112: 0.128 | H112: 0.121 | I112: 0.11 | J112: 0.103 | K112: 0.109 | L112: 0.111 | P112: =IFERROR(Segments!P91/Segments!P95,"") -> 0.10730555 | Q112: =IFERROR(Segments!Q16/Segments!Q19,"") -> 0.11905832 | R112: =IFERROR(Segments!R16/Segments!R19,"") -> 0.11679298 | S112: =IFERROR(Segments!S16/Segments!S19,"") -> 0.11545564 | T112: =IFERROR(Segments!T16/Segments!T19,"") -> 0.11433611 | U112: =IFERROR(Segments!U16/Segments!U19,"") -> 0.11113602
A113: Global Ventures | E113: 0.022 | F113: 0.069 | G113: 0.06 | H113: 0.073 | I113: 0.066 | J113: 0.067 | K113: 0.067 | P113: =IFERROR(Segments!P92/Segments!P95,"") -> 0.065884933
A114: Bottling Investments | E114: 0.197 | F114: 0.199 | G114: 0.19 | H114: 0.186 | I114: 0.183 | J114: 0.172 | K114: 0.132 | L114: 0.12 | P114: =IFERROR(Segments!P93/Segments!P95,"") -> 0.11084866 | Q114: =IFERROR(Segments!Q17/Segments!Q19,"") -> 0.13127864 | R114: =IFERROR(Segments!R17/Segments!R19,"") -> 0.11240527 | S114: =IFERROR(Segments!S17/Segments!S19,"") -> 0.10790847 | T114: =IFERROR(Segments!T17/Segments!T19,"") -> 0.13133419 | U114: =IFERROR(Segments!U17/Segments!U19,"") -> 0.11397608
...

Sheet 产品销量
A1: 可口可乐产品销量
A2: 截至2026-10-14。年度数据覆盖FY2016—FY2025。单位、估算和口径变更在各表旁说明。
C3: FY2016 | D3: FY2017 | E3: FY2018 | F3: FY2019 | G3: FY2020 | H3: FY2021 | I3: FY2022 | J3: FY2023 | K3: FY2024 | L3: FY2025
A4: 0.0%表示公司披露持平。双位数保留定性表述。估算绝对量使用四舍五入的销量和占比。
A6: 1. 体系销量与销量结构
A7: 体系销量（十亿单位箱） | C7: ='Operating Metrics'!C14 -> 29.3 | D7: ='Operating Metrics'!D14 -> 29.2 | E7: ='Operating Metrics'!E14 -> 29.6 | F7: ='Operating Metrics'!F14 -> 30.3 | G7: ='Operating Metrics'!G14 -> 29 | H7: ='Operating Metrics'!H14 -> 31.3 | I7: ='Operating Metrics'!I14 -> 32.7 | J7: ='Operating Metrics'!J14 -> 33.3 | ... L7: ='Operating Metrics'!L14 -> 33.8
A8: 体系销量（亿单位箱） | C8: =C7*10 -> 293 | D8: =D7*10 -> 292 | E8: =E7*10 -> 296 | F8: =F7*10 -> 303 | G8: =G7*10 -> 290 | H8: =H7*10 -> 313 | I8: =I7*10 -> 327 | J8: =J7*10 -> 333 | ... L8: =L7*10 -> 338
A9: 全球销量同比（公司披露） | C9: ='Operating Metrics'!C18 -> 0.01 | D9: ='Operating Metrics'!D18 -> 0 | E9: ='Operating Metrics'!E18 -> 0.02 | F9: ='Operating Metrics'!F18 -> 0.02 | G9: ='Operating Metrics'!G18 -> -0.06 | H9: ='Operating Metrics'!H18 -> 0.08 | I9: ='Operating Metrics'!I18 -> 0.05 | J9: ='Operating Metrics'!J18 -> 0.02 | ... L9: ='Operating Metrics'!L18 -> 0
A10: 全球销量同比（绝对量计算） | C10: ="n.a." -> n.a. | D10: ='Operating Metrics'!D15 -> -0.0034129693 | E10: ='Operating Metrics'!E15 -> 0.01369863 | F10: ='Operating Metrics'!F15 -> 0.023648649 | G10: ='Operating Metrics'!G15 -> -0.04290429 | H10: ='Operating Metrics'!H15 -> 0.079310345 | I10: ='Operating Metrics'!I15 -> 0.044728435 | J10: ='Operating Metrics'!J15 -> 0.018348624 | K10: ='Operating Metrics'!K15 -> 0.012012012 | L10: ='Operating Metrics'!L15 -> 0.0029673591
A12: 碳酸软饮占全球销量 | C12: 0.69 | D12: 0.69 | E12: 0.69 | F12: 0.69 | G12: 0.69 | H12: 0.69 | I12: 0.69 | J12: 0.69 | K12: 0.69 | L12: 0.69
A13: 可口可乐商标系列占全球销量 | C13: 0.45 | D13: 0.45 | E13: 0.45 | F13: 0.45 | G13: 0.47 | H13: 0.47 | I13: 0.46 | J13: 0.47 | K13: 0.47 | L13: 0.47
A14: 美国占全球销量 | C14: 0.19 | D14: 0.19 | E14: 0.18 | F14: 0.18 | G14: 0.18 | H14: 0.17 | I14: 0.17 | J14: 0.16 | K14: 0.16 | L14: 0.16
A15: 国际占全球销量 | C15: =1-C14 -> 0.81 | D15: =1-D14 -> 0.81 | E15: =1-E14 -> 0.82 | F15: =1-F14 -> 0.82 | G15: =1-G14 -> 0.82 | H15: =1-H14 -> 0.83 | I15: =1-I14 -> 0.83 | J15: =1-J14 -> 0.84 | ... L15: =1-L14 -> 0.84
A16: 品类结构来源 | C16: S003 | D16: S003 | E16: S003 | F16: S004 | G16: S005 | H16: S006 | I16: S007 | J16: S008 | K16: S009 | L16: S010
A17: 美国占比来源 | C17: S001 | D17: S002 | E17: S003 | F17: S004 | G17: S005 | H17: S006 | I17: S007 | J17: S008 | K17: S009 | L17: S010
A19: 2. 根据销量占比推算绝对量（亿单位箱）
A20: 碳酸软饮（估算） | C20: =C8*C12 -> 202.17 | D20: =D8*D12 -> 201.48 | E20: =E8*E12 -> 204.24 | F20: =F8*F12 -> 209.07 | G20: =G8*G12 -> 200.1 | H20: =H8*H12 -> 215.97 | I20: =I8*I12 -> 225.63 | J20: =J8*J12 -> 229.77 | ... L20: =L8*L12 -> 233.22
A21: 可口可乐商标系列（估算） | C21: =C8*C13 -> 131.85 | D21: =D8*D13 -> 131.4 | E21: =E8*E13 -> 133.2 | F21: =F8*F13 -> 136.35 | G21: =G8*G13 -> 136.3 | H21: =H8*H13 -> 147.11 | I21: =I8*I13 -> 150.42 | J21: =J8*J13 -> 156.51 | ... L21: =L8*L13 -> 158.86
A22: 其他品类（估算） | C22: =C8-C20 -> 90.83 | D22: =D8-D20 -> 90.52 | E22: =E8-E20 -> 91.76 | F22: =F8-F20 -> 93.93 | G22: =G8-G20 -> 89.9 | H22: =H8-H20 -> 97.03 | I22: =I8-I20 -> 101.37 | J22: =J8-J20 -> 103.23 | ... L22: =L8-L20 -> 104.78
A23: 碳酸软饮中其他商标（估算） | C23: =C20-C21 -> 70.32 | D23: =D20-D21 -> 70.08 | E23: =E20-E21 -> 71.04 | F23: =F20-F21 -> 72.72 | G23: =G20-G21 -> 63.8 | H23: =H20-H21 -> 68.86 | I23: =I20-I21 -> 75.21 | J23: =J20-J21 -> 73.26 | ... L23: =L20-L21 -> 74.36
A24: 美国体系销量（估算） | C24: =C8*C14 -> 55.67 | D24: =D8*D14 -> 55.48 | E24: =E8*E14 -> 53.28 | F24: =F8*F14 -> 54.54 | G24: =G8*G14 -> 52.2 | H24: =H8*H14 -> 53.21 | I24: =I8*I14 -> 55.59 | J24: =J8*J14 -> 53.28 | ... L24: =L8*L14 -> 54.08
A25: 国际体系销量（估算） | C25: =C8-C24 -> 237.33 | D25: =D8-D24 -> 236.52 | E25: =E8-E24 -> 242.72 | F25: =F8-F24 -> 248.46 | G25: =G8-G24 -> 237.8 | H25: =H8-H24 -> 259.79 | I25: =I8-I24 -> 271.41 | J25: =J8-J24 -> 279.72 | ... L25: =L8-L24 -> 283.92
A26: 商标系列包含在碳酸软饮中，两行不能相加。上述绝对量为估算，不能替代公司披露的可比同比。
A28: 3. 全年品类增长（FY2017—FY2020原分类）
A29: 碳酸软饮 | D29: -0.01 | E29: 0.02 | F29: 0.02 | G29: -0.04
A30: 果汁、乳制品和植物基饮料 | D30: 0 | E30: -0.01 | F30: 0 | G30: -0.09
A31: 水、增值水和运动饮料 | D31: 0.01 | E31: 0.03 | F31: 0.03 | G31: -0.11
A32: 茶和咖啡 | D32: 0.02 | E32: 0.01 | F32: 0.01 | G32: -0.17
A33: 可口可乐商标系列 | D33: 未披露 | E33: 未披露 | F33: 未披露 | G33: -0.01
A34: Coca-Cola Zero Sugar | D34: 未披露 | E34: 双位数 | F34: 双位数 | G34: 0.04
A35: 全年增长来源 | D35: VOL-FY2017 | E35: VOL-FY2018 | F35: VOL-FY2019 | G35: VOL-FY2020
A36: FY2016公告使用Sparkling beverages等旧分类，未填入同名新口径。2021年起分类调整，旧表与新表分开。
A38: 4. 全年品类及品牌增长（FY2021—FY2025）
A39: 碳酸软饮 | H39: 0.07 | I39: 0.04 | J39: 0.02 | K39: 0.02 | L39: 0
A40: 可口可乐商标系列 | H40: 0.07 | I40: 0.04 | J40: 0.02 | K40: 0.02 | L40: 0
A41: Coca-Cola Zero Sugar | H41: 双位数 | I41: 0.11 | J41: 0.05 | K41: 0.09 | L41: 0.14
A42: Diet Coke / Coca-Cola Light | H42: 未披露 | I42: 未披露 | J42: 未披露 | K42: 未披露 | L42: 0
A43: 风味碳酸饮料 | H43: 0.09 | I43: 0.05 | J43: 0.01 | K43: 0.01 | L43: -0.01
A44: 果汁、增值乳制品和植物基饮料 | H44: 0.12 | I44: 0.03 | J44: 0.02 | K44: 0 | L44: -0.03
A45: 水、运动饮料、咖啡和茶 | H45: 0.07 | I45: 0.06 | J45: 0.01 | K45: -0.01 | L45: 0.02
A46: 水 / 补水 | H46: 0.05 | I46: 0.05 | J46: 0.02 | K46: -0.02 | L46: 0.02
A47: 运动饮料 | H47: 0.13 | I47: 0.08 | J47: 0 | K47: -0.01 | L47: 0.01
A48: 咖啡 | H48: 0.15 | I48: 0.13 | J48: 0.03 | K48: -0.03 | L48: 0
A49: 茶 | H49: 0.06 | I49: 0.01 | J49: -0.01 | K49: 0.04 | L49: 0.02
A50: 全年增长来源 | H50: VOL-FY2021 | I50: VOL-FY2022 | J50: VOL-FY2023 | K50: VOL-FY2024 | L50: VOL-FY2025
A52: 5. 近期单季销量增长
C53: 3Q2024 | D53: 4Q2024 | E53: 1Q2025 | F53: 2Q2025 | G53: 3Q2025 | H53: 4Q2025 | I53: 1Q2026 | J53: 2Q2026
A54: 全球体系销量 | C54: -0.01 | D54: 0.02 | E54: 0.02 | F54: -0.01 | G54: 0.01 | H54: 0.01 | I54: 0.03 | J54: 0.05
A55: 碳酸软饮 | C55: 0 | D55: 0.02 | E55: 0.02 | F55: -0.01 | G55: 0 | H55: 0 | I55: 0.02 | J55: 0.04
A56: 可口可乐商标系列 | C56: 0 | D56: 0.02 | E56: 0.01 | F56: -0.01 | G56: 0.01 | H56: 0.01 | I56: 0.02 | J56: 0.05
A57: Coca-Cola Zero Sugar | C57: 0.11 | D57: 0.13 | E57: 0.14 | F57: 0.14 | G57: 0.14 | H57: 0.13 | I57: 0.13 | J57: 0.16
A58: Diet Coke / Coca-Cola Light | C58: 未披露 | D58: 未披露 | E58: 未披露 | F58: 未披露 | G58: 0.02 | H58: 0.02 | I58: 0.06 | J58: 0.07
A59: 风味碳酸饮料 | C59: -0.01 | D59: 0.02 | E59: 0.02 | F59: -0.02 | G59: -0.01 | H59: -0.01 | I59: 0.03 | J59: 0.04
A60: 果汁、增值乳制品和植物基饮料 | C60: -0.03 | D60: -0.01 | E60: 0.01 | F60: -0.04 | G60: -0.03 | H60: -0.03 | I60: -0.01 | J60: 0.02
A61: 水、运动饮料、咖啡和茶 | C61: -0.04 | D61: 0.02 | E61: 0.02 | F61: 0 | G61: 0.03 | H61: 0.03 | I61: 0.05 | J61: 0.06
A62: 水 / 补水 | C62: -0.06 | D62: 0.02 | E62: 0.03 | F62: 0 | G62: 0.03 | H62: 0.04 | I62: 0.05 | J62: 0.06
A63: 运动饮料 | C63: -0.03 | D63: -0.02 | E63: -0.01 | F63: -0.03 | G63: 0.03 | H63: 0.05 | I63: 0.03 | J63: 0.05
A64: 咖啡 | C64: -0.06 | D64: -0.01 | E64: -0.02 | F64: 0.01 | G64: 0.02 | H64: 0 | I64: 0 | J64: -0.02
A65: 茶 | C65: 0.07 | D65: 0.05 | E65: 0 | F65: 0 | G65: 0.02 | H65: 0.05 | I65: 0.08 | J65: 0.06
A66: 单季增长来源 | C66: Q32024公告 | D66: FY2024单季 | E66: Q12025公告 | F66: Q22025公告 | G66: Q32025公告 | H66: FY2025单季 | I66: Q12026公告 | J66: Q22026公告
A68: 季度绝对箱量没有完整披露，仅补入单季同比，不从全年箱量倒推季度箱量。
A69: 增长率来自公司业绩公告。品牌未披露的单项数据保留“未披露”，不能按零处理。
A71: 6. 重点品牌补充（业绩会纪要）
A72: 品牌 | C72: 期间 | D72: 范围 | E72: 销量同比 | F72: 来源与口径
A73: fairlife | C73: 2Q2025 | D73: 业务整体 | E73: 双位数 | F73: 2025Q2业绩会纪要，第25行。管理层称销量增长受产能约束。
A74: Santa Clara | C74: 3Q2025 | D74: 墨西哥 | E74: 0.13 | F74: 2025Q3业绩会纪要，第97行。墨西哥品牌销量同比增长。
A75: 纪要数据属于管理层表述。fairlife只披露双位数增速，未填入具体百分比。两项均不用于推算品牌单价。
A78: 7. 数据来源
A80: VOL-FY2016 FY2016 | C80: https://investors.coca-colacompany.com/news-events/press-releases/detail/871/the-coca-cola-company-reports-fourth-quarter-and-full-year-2016-results
A81: VOL-FY2017 FY2017 | C81: https://investors.coca-colacompany.com/news-events/press-releases/detail/929/the-coca-cola-company-reports-strong-operating-results-for-fourth-quarter-and-full-year-2017-achieves-or-exceeds-the-companys-full-year-guidance
A82: VOL-FY2018 FY2018 | C82: https://investors.coca-colacompany.com/news-events/press-releases/detail/962/coca-cola-reports-strong-results-for-fourth-quarter-and-full-year-2018
A83: VOL-FY2019 FY2019 | C83: https://investors.coca-colacompany.com/news-events/press-releases/detail/981/coca-cola-reports-strong-growth-in-fourth-quarter-and-full-year-2019-company-achieves-or-exceeds-all-full-year-guidance
A84: VOL-FY2020 FY2020 | C84: https://investors.coca-colacompany.com/news-events/press-releases/detail/1012/coca-cola-reports-fourth-quarter-and-full-year-2020-results
A85: VOL-FY2021 FY2021 | C85: https://investors.coca-colacompany.com/news-events/press-releases/detail/1046/coca-cola-reports-fourth-quarter-and-full-year-2021-results
A86: VOL-FY2022 FY2022 | C86: https://investors.coca-colacompany.com/news-events/press-releases/detail/1076/coca-cola-reports-fourth-quarter-and-full-year-2022-results
A87: VOL-FY2023 FY2023 | C87: https://investors.coca-colacompany.com/news-events/press-releases/detail/1101/coca-cola-reports-fourth-quarter-and-full-year-2023-results
A88: S001 2016-12-31 | C88: https://www.sec.gov/Archives/edgar/data/21344/000002134417000009/a2016123110-k.htm
A89: S002 2017-12-31 | C89: https://www.sec.gov/Archives/edgar/data/21344/000002134418000008/a2017123110-k.htm
A90: S003 2018-12-31 | C90: https://www.sec.gov/Archives/edgar/data/21344/000002134419000014/a2018123110-k.htm
A91: S004 2019-12-31 | C91: https://www.sec.gov/Archives/edgar/data/21344/000002134420000006/a2019123110-k.htm
... A105: VOL-FY2025 FY2025 | C105: https://investors.coca-colacompany.com/_assets/_58ca73310d2ced796ebc757917b74f04/cocacolacompany/db/880/11088/earnings_release/Coca-Cola+Q4+2025+Earnings+Release_Full+Release_2.10.26.pdf

Sheet Derived Metrics
A1: The Coca-Cola Company — Derived Metrics
A2: $ in millions except per-share data | USD | as of 2026-10-14
C3: FY2016 | D3: FY2017 | E3: FY2018 | F3: FY2019 | G3: FY2020 | H3: FY2021 | I3: FY2022 | J3: FY2023 | K3: FY2024 | L3: FY2025 | M3: · | N3: · | O3: · | P3: 3Q2024 | Q3: 1Q2025 | R3: 2Q2025 | S3: 3Q2025 | T3: 1Q2026 | U3: 2Q2026
C4: 2016-12-31 | D4: 2017-12-31 | E4: 2018-12-31 | F4: 2019-12-31 | G4: 2020-12-31 | H4: 2021-12-31 | I4: 2022-12-31 | J4: 2023-12-31 | K4: 2024-12-31 | L4: 2025-12-31 | P4: 2024-09-27 | Q4: 2025-03-28 | R4: 2025-06-27 | S4: 2025-09-26 | T4: 2026-04-03 | U4: 2026-07-03
A6: CONTENTS
A7: =HYPERLINK("#'Derived Metrics'!A19","1. PROFITABILITY") -> 1. PROFITABILITY
A8: =HYPERLINK("#'Derived Metrics'!A29","2. RETURNS (average of opening and closing balances)") -> 2. RETURNS (average of opening and closing balances)
A9: =HYPERLINK("#'Derived Metrics'!A35","3. LEVERAGE") -> 3. LEVERAGE
A10: =HYPERLINK("#'Derived Metrics'!A42","4. SOLVENCY") -> 4. SOLVENCY
A11: =HYPERLINK("#'Derived Metrics'!A46","5. LIQUIDITY") -> 5. LIQUIDITY
A12: =HYPERLINK("#'Derived Metrics'!A51","6. COVERAGE") -> 6. COVERAGE
A13: =HYPERLINK("#'Derived Metrics'!A55","7. CASH CONVERSION") -> 7. CASH CONVERSION
A14: =HYPERLINK("#'Derived Metrics'!A64","8. EARNINGS QUALITY") -> 8. EARNINGS QUALITY
A15: =HYPERLINK("#'Derived Metrics'!A68","9. GROWTH") -> 9. GROWTH
A16: =HYPERLINK("#'Derived Metrics'!A76","10. SHAREOWNER RETURNS") -> 10. SHAREOWNER RETURNS
A17: =HYPERLINK("#'Derived Metrics'!A84","11. WORKING CAPITAL") -> 11. WORKING CAPITAL
A19: 1. PROFITABILITY
A20: Gross Margin | C20: ='Income Statement'!C14/'Income Statement'!C11 -> 0.60669326 | D20: ='Income Statement'!D14/'Income Statement'!D11 -> 0.62109246 | E20: ='Income Statement'!E14/'Income Statement'!E11 -> 0.6190379 | F20: ='Income Statement'!F14/'Income Statement'!F11 -> 0.60771212 | G20: ='Income Statement'!G14/'Income Statement'!G11 -> 0.59311201 | H20: ='Income Statement'!H14/'Income Statement'!H11 -> 0.60271634 | I20: ='Income Statement'!I14/'Income Statement'!I11 -> 0.58143429 | J20: ='Income Statement'!J14/'Income Statement'!J11 -> 0.59522665 | ... L20: ='Income Statement'!L14/'Income Statement'!L11 -> 0.61625748 | P20: =IFERROR('Income Statement'!P14/'Income Statement'!P11,"") -> 0.60654631 | Q20: =IFERROR('Income Statement'!Q14/'Income Statement'!Q11,"") -> 0.62593225 | R20: =IFERROR('Income Statement'!R14/'Income Statement'!R11,"") -> 0.62393299 | S20: =IFERROR('Income Statement'!S14/'Income Statement'!S11,"") -> 0.61485347 | T20: =IFERROR('Income Statement'!T14/'Income Statement'!T11,"") -> 0.62957024 | U20: =IFERROR('Income Statement'!U14/'Income Statement'!U11,"") -> 0.62892377
A21: SG&A % of Revenue | C21: ='Income Statement'!C16/'Income Statement'!C11 -> 0.36714999 | D21: ='Income Statement'!D16/'Income Statement'!D11 -> 0.3544129 | E21: ='Income Statement'!E16/'Income Statement'!E11 -> 0.32075802 | F21: ='Income Statement'!F16/'Income Statement'!F11 -> 0.32477325 | G21: ='Income Statement'!G16/'Income Statement'!G11 -> 0.29475374 | H21: ='Income Statement'!H16/'Income Statement'!H11 -> 0.31416376 | I21: ='Income Statement'!I16/'Income Statement'!I11 -> 0.29950702 | J21: ='Income Statement'!J16/'Income Statement'!J11 -> 0.30537221 | ... L21: ='Income Statement'!L16/'Income Statement'!L11 -> 0.30289314 | P21: =IFERROR('Income Statement'!P16/'Income Statement'!P11,"") -> 0.3067319 | Q21: =IFERROR('Income Statement'!Q16/'Income Statement'!Q11,"") -> 0.29059215 | R21: =IFERROR('Income Statement'!R16/'Income Statement'!R11,"") -> 0.27682489 | S21: =IFERROR('Income Statement'!S16/'Income Statement'!S11,"") -> 0.29048575 | T21: =IFERROR('Income Statement'!T16/'Income Statement'!T11,"") -> 0.27838358 | U21: =IFERROR('Income Statement'!U16/'Income Statement'!U11,"") -> 0.27802691
A22: Operating Margin | C22: ='Income Statement'!C18/'Income Statement'!C11 -> 0.20679359 | D22: ='Income Statement'!D18/'Income Statement'!D11 -> 0.21415553 | E22: ='Income Statement'!E18/'Income Statement'!E11 -> 0.26682216 | F22: ='Income Statement'!F18/'Income Statement'!F11 -> 0.27064885 | G22: ='Income Statement'!G18/'Income Statement'!G11 -> 0.27252075 | H22: ='Income Statement'!H18/'Income Statement'!H11 -> 0.26666667 | I22: ='Income Statement'!I18/'Income Statement'!I11 -> 0.25367408 | J22: ='Income Statement'!J18/'Income Statement'!J11 -> 0.24721336 | ... L22: ='Income Statement'!L18/'Income Statement'!L11 -> 0.28706118 | P22: =IFERROR('Income Statement'!P18/'Income Statement'!P11,"") -> 0.21174287 | Q22: =IFERROR('Income Statement'!Q18/'Income Statement'!Q11,"") -> 0.32878066 | R22: =IFERROR('Income Statement'!R18/'Income Statement'!R11,"") -> 0.34144396 | S22: =IFERROR('Income Statement'!S18/'Income Statement'!S11,"") -> 0.31971096 | T22: =IFERROR('Income Statement'!T18/'Income Statement'!T11,"") -> 0.34950289 | U22: =IFERROR('Income Statement'!U18/'Income Statement'!U11,"") -> 0.34917788
A23: EBITDA (operating income + D&A; analyst calculation) | C23: =('Income Statement'!C18+'Cash Flow'!C17) -> 10444 | D23: =('Income Statement'!D18+'Cash Flow'!D17) -> 9015 | E23: =('Income Statement'!E18+'Cash Flow'!E17) -> 10238 | F23: =('Income Statement'!F18+'Cash Flow'!F17) -> 11451 | G23: =('Income Statement'!G18+'Cash Flow'!G17) -> 10533 | H23: =('Income Statement'!H18+'Cash Flow'!H17) -> 11760 | I23: =('Income Statement'!I18+'Cash Flow'!I17) -> 12169 | J23: =('Income Statement'!J18+'Cash Flow'!J17) -> 12439 | ... L23: =('Income Statement'!L18+'Cash Flow'!L17) -> 14812 | Q23: ='Income Statement'!Q18+Segments!Q61 -> 3926 | R23: ='Income Statement'!R18+Segments!R61 -> 4559 | S23: ='Income Statement'!S18+Segments!S61 -> 4250 | T23: ='Income Statement'!T18+Segments!T61 -> 4623 | U23: ='Income Statement'!U18+Segments!U61 -> 4938
A24: EBITDA Margin | C24: =('Income Statement'!C18+'Cash Flow'!C17)/'Income Statement'!C11 -> 0.24948045 | D24: =('Income Statement'!D18+'Cash Flow'!D17)/'Income Statement'!D11 -> 0.24895062 | E24: =('Income Statement'!E18+'Cash Flow'!E17)/'Income Statement'!E11 -> 0.29848397 | F24: =('Income Statement'!F18+'Cash Flow'!F17)/'Income Statement'!F11 -> 0.30727741 | G24: =('Income Statement'!G18+'Cash Flow'!G17)/'Income Statement'!G11 -> 0.31904647 | H24: =('Income Statement'!H18+'Cash Flow'!H17)/'Income Statement'!H11 -> 0.30422972 | I24: =('Income Statement'!I18+'Cash Flow'!I17)/'Income Statement'!I11 -> 0.28297368 | J24: =('Income Statement'!J18+'Cash Flow'!J17)/'Income Statement'!J11 -> 0.27186694 | ... L24: =('Income Statement'!L18+'Cash Flow'!L17)/'Income Statement'!L11 -> 0.3089631 | Q24: =IFERROR(Q23/'Income Statement'!Q11,"") -> 0.35277204 | R24: =IFERROR(R23/'Income Statement'!R11,"") -> 0.36370164 | S24: =IFERROR(S23/'Income Statement'!S11,"") -> 0.34122842 | T24: =IFERROR(T23/'Income Statement'!T11,"") -> 0.3706703 | U24: =IFERROR(U23/'Income Statement'!U11,"") -> 0.3690583
A25: Net Margin (attributable) | C25: ='Income Statement'!C32/'Income Statement'!C11 -> 0.15591334 | D25: ='Income Statement'!D32/'Income Statement'!D11 -> 0.034463714 | E25: ='Income Statement'!E32/'Income Statement'!E11 -> 0.18758017 | F25: ='Income Statement'!F32/'Income Statement'!F11 -> 0.23936027 | G25: ='Income Statement'!G32/'Income Statement'!G11 -> 0.23465802 | H25: ='Income Statement'!H32/'Income Statement'!H11 -> 0.25277454 | I25: ='Income Statement'!I32/'Income Statement'!I11 -> 0.22188634 | J25: ='Income Statement'!J32/'Income Statement'!J11 -> 0.23416532 | ... L25: ='Income Statement'!L32/'Income Statement'!L11 -> 0.27339855 | P25: =IFERROR('Income Statement'!P32/'Income Statement'!P11,"") -> 0.24025645 | Q25: =IFERROR('Income Statement'!Q32/'Income Statement'!Q11,"") -> 0.29921826 | R25: =IFERROR('Income Statement'!R32/'Income Statement'!R11,"") -> 0.30394894 | S25: =IFERROR('Income Statement'!S32/'Income Statement'!S11,"") -> 0.29674829 | T25: =IFERROR('Income Statement'!T32/'Income Statement'!T11,"") -> 0.31462476 | U25: =IFERROR('Income Statement'!U32/'Income Statement'!U11,"") -> 0.33071749
A26: Effective Tax Rate | C26: ='Income Statement'!C26/'Income Statement'!C25 -> 0.19493609 | D26: ='Income Statement'!D26/'Income Statement'!D25 -> 0.8137881 | E26: ='Income Statement'!E26/'Income Statement'!E25 -> 0.21264438 | F26: ='Income Statement'!F26/'Income Statement'!F25 -> 0.16697571 | G26: ='Income Statement'!G26/'Income Statement'!G25 -> 0.20320033 | H26: ='Income Statement'!H26/'Income Statement'!H25 -> 0.21094567 | I26: ='Income Statement'!I26/'Income Statement'!I25 -> 0.18098579 | J26: ='Income Statement'!J26/'Income Statement'!J25 -> 0.17364114 | ... L26: ='Income Statement'!L26/'Income Statement'!L25 -> 0.17883485 | P26: =IFERROR('Income Statement'!P26/'Income Statement'!P25,"") -> 0.15680473 | Q26: =IFERROR('Income Statement'!Q26/'Income Statement'!Q25,"") -> 0.17796401 | R26: =IFERROR('Income Statement'!R26/'Income Statement'!R25,"") -> 0.20704754 | S26: =IFERROR('Income Statement'!S26/'Income Statement'!S25,"") -> 0.11953144 | T26: =IFERROR('Income Statement'!T26/'Income Statement'!T25,"") -> 0.13988289 | U26: =IFERROR('Income Statement'!U26/'Income Statement'!U25,"") -> 0.18940639
A27: Equity income % of pre-tax income | C27: ='Income Statement'!C23/'Income Statement'!C25 -> 0.10263029 | D27: ='Income Statement'!D23/'Income Statement'!D25 -> 0.15558781 | E27: ='Income Statement'!E23/'Income Statement'!E25 -> 0.12255319 | F27: ='Income Statement'!F23/'Income Statement'!F25 -> 0.097255702 | G27: ='Income Statement'!G23/'Income Statement'!G25 -> 0.10031798 | H27: ='Income Statement'!H23/'Income Statement'!H25 -> 0.11573441 | I27: ='Income Statement'!I23/'Income Statement'!I25 -> 0.12596269 | J27: ='Income Statement'!J23/'Income Statement'!J25 -> 0.13055899 | ... L27: ='Income Statement'!L23/'Income Statement'!L25 -> 0.12695337 | P27: =IFERROR('Income Statement'!P23/'Income Statement'!P25,"") -> 0.16005917 | Q27: =IFERROR('Income Statement'!Q23/'Income Statement'!Q25,"") -> 0.086517131 | R27: =IFERROR('Income Statement'!R23/'Income Statement'!R25,"") -> 0.11697248 | S27: =IFERROR('Income Statement'!S23/'Income Statement'!S25,"") -> 0.15395649 | T27: =IFERROR('Income Statement'!T23/'Income Statement'!T25,"") -> 0.083279115 | U27: =IFERROR('Income Statement'!U23/'Income Statement'!U25,"") -> 0.11031963
A29: 2. RETURNS (average of opening and closing balances)
A30: ROA (NI attributable / average total assets) | D30: ='Income Statement'!D32/('Balance Sheet'!D33+'Balance Sheet'!C33)*2 -> 0.014249341 | E30: ='Income Statement'!E32/('Balance Sheet'!E33+'Balance Sheet'!D33)*2 -> 0.075202207 | F30: ='Income Statement'!F32/('Balance Sheet'!F33+'Balance Sheet'!E33)*2 -> 0.10519054 | G30: ='Income Statement'!G32/('Balance Sheet'!G33+'Balance Sheet'!F33)*2 -> 0.089211582 | H30: ='Income Statement'!H32/('Balance Sheet'!H33+'Balance Sheet'!G33)*2 -> 0.10758051 | I30: ='Income Statement'!I32/('Balance Sheet'!I33+'Balance Sheet'!H33)*2 -> 0.10198966 | J30: ='Income Statement'!J32/('Balance Sheet'!J33+'Balance Sheet'!I33)*2 -> 0.11250302 | K30: ='Income Statement'!K32/('Balance Sheet'!K33+'Balance Sheet'!J33)*2 -> 0.10724734 | L30: ='Income Statement'!L32/('Balance Sheet'!L33+'Balance Sheet'!K33)*2 -> 0.1276459
A31: ROE (NI attributable / average equity attributable) | D31: ='Income Statement'!D32/('Balance Sheet'!D53+'Balance Sheet'!C53)*2 -> 0.062191658 | E31: ='Income Statement'!E32/('Balance Sheet'!E53+'Balance Sheet'!D53)*2 -> 0.37788154 | F31: ='Income Statement'!F32/('Balance Sheet'!F53+'Balance Sheet'!E53)*2 -> 0.49607919 | G31: ='Income Statement'!G32/('Balance Sheet'!G53+'Balance Sheet'!F53)*2 -> 0.40475444 | H31: ='Income Statement'!H32/('Balance Sheet'!H53+'Balance Sheet'!G53)*2 -> 0.46200766 | I31: ='Income Statement'!I32/('Balance Sheet'!I53+'Balance Sheet'!H53)*2 -> 0.40514606 | J31: ='Income Statement'!J32/('Balance Sheet'!J53+'Balance Sheet'!I53)*2 -> 0.42816609 | K31: ='Income Statement'!K32/('Balance Sheet'!K53+'Balance Sheet'!J53)*2 -> 0.41856803 | L31: ='Income Statement'!L32/('Balance Sheet'!L53+'Balance Sheet'!K53)*2 -> 0.45969312
A32: ROIC (operating income x (1 - tax rate) / average equity + debt) | D32: ='Income Statement'!D18*(1-D26)/(('Balance Sheet'!D55+'Balance Sheet'!C55+('Balance Sheet'!D37+'Balance Sheet'!D38+'Balance Sheet'!D43)+('Balance Sheet'!C37+'Balance Sheet'!C38+'Balance Sheet'!C43))/2) -> 0.02130043 | E32: ='Income Statement'!E18*(1-E26)/(('Balance Sheet'!E55+'Balance Sheet'!D55+('Balance Sheet'!E37+'Balance Sheet'!E38+'Balance Sheet'!E43)+('Balance Sheet'!D37+'Balance Sheet'!D38+'Balance Sheet'!D43))/2) -> 0.11091598 | F32: ='Income Statement'!F18*(1-F26)/(('Balance Sheet'!F55+'Balance Sheet'!E55+('Balance Sheet'!F37+'Balance Sheet'!F38+'Balance Sheet'!F43)+('Balance Sheet'!E37+'Balance Sheet'!E38+'Balance Sheet'!E43))/2) -> 0.1321747 | G32: ='Income Statement'!G18*(1-G26)/(('Balance Sheet'!G55+'Balance Sheet'!F55+('Balance Sheet'!G37+'Balance Sheet'!G38+'Balance Sheet'!G43)+('Balance Sheet'!F37+'Balance Sheet'!F38+'Balance Sheet'!F43))/2) -> 0.11206689 | H32: ='Income Statement'!H18*(1-H26)/(('Balance Sheet'!H55+'Balance Sheet'!G55+('Balance Sheet'!H37+'Balance Sheet'!H38+'Balance Sheet'!H43)+('Balance Sheet'!G37+'Balance Sheet'!G38+'Balance Sheet'!G43))/2) -> 0.12351853 | I32: ='Income Statement'!I18*(1-I26)/(('Balance Sheet'!I55+'Balance Sheet'!H55+('Balance Sheet'!I37+'Balance Sheet'!I38+'Balance Sheet'!I43)+('Balance Sheet'!H37+'Balance Sheet'!H38+'Balance Sheet'!H43))/2) -> 0.13476464 | J32: ='Income Statement'!J18*(1-J26)/(('Balance Sheet'!J55+'Balance Sheet'!I55+('Balance Sheet'!J37+'Balance Sheet'!J38+'Balance Sheet'!J43)+('Balance Sheet'!I37+'Balance Sheet'!I38+'Balance Sheet'!I43))/2) -> 0.1389684 | K32: ='Income Statement'!K18*(1-K26)/(('Balance Sheet'!K55+'Balance Sheet'!J55+('Balance Sheet'!K37+'Balance Sheet'!K38+'Balance Sheet'!K43)+('Balance Sheet'!J37+'Balance Sheet'!J38+'Balance Sheet'!J43))/2) -> 0.11579764 | L32: ='Income Statement'!L18*(1-L26)/(('Balance Sheet'!L55+'Balance Sheet'!K55+('Balance Sheet'!L37+'Balance Sheet'!L38+'Balance Sheet'!L43)+('Balance Sheet'!K37+'Balance Sheet'!K38+'Balance Sheet'!K43))/2) -> 0.15001725
A33: Asset Turnover | D33: ='Income Statement'!D11/('Balance Sheet'!D33+'Balance Sheet'!C33)*2 -> 0.41345923 | E33: ='Income Statement'!E11/('Balance Sheet'!E33+'Balance Sheet'!D33)*2 -> 0.40090701 | F33: ='Income Statement'!F11/('Balance Sheet'!F33+'Balance Sheet'!E33)*2 -> 0.43946532 | G33: ='Income Statement'!G11/('Balance Sheet'!G33+'Balance Sheet'!F33)*2 -> 0.380177 | H33: ='Income Statement'!H11/('Balance Sheet'!H33+'Balance Sheet'!G33)*2 -> 0.42559868 | I33: ='Income Statement'!I11/('Balance Sheet'!I33+'Balance Sheet'!H33)*2 -> 0.45964824 | J33: ='Income Statement'!J11/('Balance Sheet'!J33+'Balance Sheet'!I33)*2 -> 0.4804427 | K33: ='Income Statement'!K11/('Balance Sheet'!K33+'Balance Sheet'!J33)*2 -> 0.4747594 | L33: ='Income Statement'!L11/('Balance Sheet'!L33+'Balance Sheet'!K33)*2 -> 0.46688579
A35: 3. LEVERAGE
A36: Total debt (loans and notes payable + current maturities + long-term… | B36: Full label: Total debt (loans and notes payable + current maturities + long-term debt) | C36: =('Balance Sheet'!C37+'Balance Sheet'!C38+'Balance Sheet'!C43) -> 45709 | D36: =('Balance Sheet'!D37+'Balance Sheet'!D38+'Balance Sheet'!D43) -> 47685 | E36: =('Balance Sheet'!E37+'Balance Sheet'!E38+'Balance Sheet'!E43) -> 44214 | F36: =('Balance Sheet'!F37+'Balance Sheet'!F38+'Balance Sheet'!F43) -> 42763 | G36: =('Balance Sheet'!G37+'Balance Sheet'!G38+'Balance Sheet'!G43) -> 42793 | H36: =('Balance Sheet'!H37+'Balance Sheet'!H38+'Balance Sheet'!H43) -> 42761 | I36: =('Balance Sheet'!I37+'Balance Sheet'!I38+'Balance Sheet'!I43) -> 39149 | J36: =('Balance Sheet'!J37+'Balance Sheet'!J38+'Balance Sheet'!J43) -> 42064 | ... L36: =('Balance Sheet'!L37+'Balance Sheet'!L38+'Balance Sheet'!L43) -> 45492 | P36: ='Balance Sheet'!P37+'Balance Sheet'!P38+'Balance Sheet'!P43 -> 46264 | Q36: ='Balance Sheet'!Q37+'Balance Sheet'!Q38+'Balance Sheet'!Q43 -> 49111 | R36: ='Balance Sheet'!R37+'Balance Sheet'!R38+'Balance Sheet'!R43 -> 49446 | S36: ='Balance Sheet'!S37+'Balance Sheet'!S38+'Balance Sheet'!S43 -> 47416 | T36: ='Balance Sheet'!T37+'Balance Sheet'!T38+'Balance Sheet'!T43 -> 43890 | U36: ='Balance Sheet'!U37+'Balance Sheet'!U38+'Balance Sheet'!U43 -> 43543
A37: Cash, short-term investments and marketable securities | C37: =('Balance Sheet'!C14+'Balance Sheet'!C15+'Balance Sheet'!C17) -> 22201 | D37: =('Balance Sheet'!D14+'Balance Sheet'!D15+'Balance Sheet'!D17) -> 20675 | E37: =('Balance Sheet'!E14+'Balance Sheet'!E15+'Balance Sheet'!E17) -> 16115 | F37: =('Balance Sheet'!F14+'Balance Sheet'!F15+'Balance Sheet'!F17) -> 11175 | G37: =('Balance Sheet'!G14+'Balance Sheet'!G15+'Balance Sheet'!G17) -> 10914 | H37: =('Balance Sheet'!H14+'Balance Sheet'!H15+'Balance Sheet'!H17) -> 12625 | I37: =('Balance Sheet'!I14+'Balance Sheet'!I15+'Balance Sheet'!I17) -> 11631 | J37: =('Balance Sheet'!J14+'Balance Sheet'!J15+'Balance Sheet'!J17) -> 13663 | ... L37: =('Balance Sheet'!L14+'Balance Sheet'!L15+'Balance Sheet'!L17) -> 15806 | P37: ='Balance Sheet'!P14+'Balance Sheet'!P15+'Balance Sheet'!P17 -> 18164 | Q37: ='Balance Sheet'!Q14+'Balance Sheet'!Q15+'Balance Sheet'!Q17 -> 13787 | R37: ='Balance Sheet'!R14+'Balance Sheet'!R15+'Balance Sheet'!R17 -> 14297 | S37: ='Balance Sheet'!S14+'Balance Sheet'!S15+'Balance Sheet'!S17 -> 15781 | T37: ='Balance Sheet'!T14+'Balance Sheet'!T15+'Balance Sheet'!T17 -> 13820 | U37: ='Balance Sheet'!U14+'Balance Sheet'!U15+'Balance Sheet'!U17 -> 16371
A38: Net debt | C38: =C36-C37 -> 23508 | D38: =D36-D37 -> 27010 | E38: =E36-E37 -> 28099 | F38: =F36-F37 -> 31588 | G38: =G36-G37 -> 31879 | H38: =H36-H37 -> 30136 | I38: =I36-I37 -> 27518 | J38: =J36-J37 -> 28401 | ... L38: =L36-L37 -> 29686 | P38: =P36-P37 -> 28100 | Q38: =Q36-Q37 -> 35324 | R38: =R36-R37 -> 35149 | S38: =S36-S37 -> 31635 | T38: =T36-T37 -> 30070 | U38: =U36-U37 -> 27172
A39: Net Debt / EBITDA | B39: Annual columns: annual EBITDA denominator. Quarterly columns: discrete three-month EBITDA denominator, without annualization; these multiples are not directly comparable to annual multiples. | C39: =C38/C23 -> 2.2508617 | D39: =D38/D23 -> 2.9961176 | E39: =E38/E23 -> 2.744579 | F39: =F38/F23 -> 2.7585364 | G39: =G38/G23 -> 3.0265831 | H39: =H38/H23 -> 2.562585 | I39: =I38/I23 -> 2.2613197 | J39: =J38/J23 -> 2.2832221 | ... L39: =L38/L23 -> 2.0041858 | Q39: =IFERROR(Q38/Q23,"") -> 8.9974529 | R39: =IFERROR(R38/R23,"") -> 7.7098048 | S39: =IFERROR(S38/S23,"") -> 7.4435294 | T39: =IFERROR(T38/T23,"") -> 6.5044343 | U39: =IFERROR(U38/U23,"") -> 5.5026326
A40: Debt / Total Equity | C40: =C36/'Balance Sheet'!C55 -> 1.9685185 | D40: =D36/'Balance Sheet'!D55 -> 2.5127786 | E40: =E36/'Balance Sheet'!E55 -> 2.3199706 | F40: =F36/'Balance Sheet'!F55 -> 2.0268746 | G40: =G36/'Balance Sheet'!G55 -> 2.0105713 | H40: =H36/'Balance Sheet'!H55 -> 1.7200724 | I40: =I36/'Balance Sheet'!I55 -> 1.5158755 | J40: =J36/'Balance Sheet'!J55 -> 1.5307132 | ... L40: =L36/'Balance Sheet'!L55 -> 1.3272648 | P40: =IFERROR(P36/'Balance Sheet'!P55,"") -> 1.6432479 | Q40: =IFERROR(Q36/'Balance Sheet'!Q55,"") -> 1.7695107 | R40: =IFERROR(R36/'Balance Sheet'!R55,"") -> 1.6382612 | S40: =IFERROR(S36/'Balance Sheet'!S55,"") -> 1.4253164 | T40: =IFERROR(T36/'Balance Sheet'!T55,"") -> 1.228242 | U40: =IFERROR(U36/'Balance Sheet'!U55,"") -> 1.1364479
A42: 4. SOLVENCY
A43: Equity Ratio (total equity / total assets) | C43: ='Balance Sheet'!C55/'Balance Sheet'!C33 -> 0.26607081 | D43: ='Balance Sheet'!D55/'Balance Sheet'!D33 -> 0.21590289 | E43: ='Balance Sheet'!E55/'Balance Sheet'!E33 -> 0.22901846 | F43: ='Balance Sheet'!F55/'Balance Sheet'!F33 -> 0.24424353 | G43: ='Balance Sheet'!G55/'Balance Sheet'!G33 -> 0.24381415 | H43: ='Balance Sheet'!H55/'Balance Sheet'!H33 -> 0.26347585 | I43: ='Balance Sheet'!I55/'Balance Sheet'!I33 -> 0.27840842 | J43: ='Balance Sheet'!J55/'Balance Sheet'!J33 -> 0.28126055 | ... L43: ='Balance Sheet'!L55/'Balance Sheet'!L33 -> 0.3270016 | P43: =IFERROR('Balance Sheet'!P55/'Balance Sheet'!P33,"") -> 0.26493893 | Q43: =IFERROR('Balance Sheet'!Q55/'Balance Sheet'!Q33,"") -> 0.27285776 | R43: =IFERROR('Balance Sheet'!R55/'Balance Sheet'!R33,"") -> 0.28928527 | S43: =IFERROR('Balance Sheet'!S55/'Balance Sheet'!S33,"") -> 0.31370645 | T43: =IFERROR('Balance Sheet'!T55/'Balance Sheet'!T33,"") -> 0.34288072 | U43: =IFERROR('Balance Sheet'!U55/'Balance Sheet'!U33,"") -> 0.35502493
A44: Debt / Total Assets | C44: =C36/'Balance Sheet'!C33 -> 0.52376533 | D44: =D36/'Balance Sheet'!D33 -> 0.54251616 | E44: =E36/'Balance Sheet'!E33 -> 0.53131609 | F44: =F36/'Balance Sheet'!F33 -> 0.495051 | G44: =G36/'Balance Sheet'!G33 -> 0.49020574 | H44: =H36/'Balance Sheet'!H33 -> 0.45319753 | I44: =I36/'Balance Sheet'!I33 -> 0.42203249 | J44: =J36/'Balance Sheet'!J33 -> 0.43052926 | ... L44: =L36/'Balance Sheet'!L33 -> 0.43401771 | P44: =IFERROR(P36/'Balance Sheet'!P33,"") -> 0.43536032 | Q44: =IFERROR(Q36/'Balance Sheet'!Q33,"") -> 0.48282473 | R44: =IFERROR(R36/'Balance Sheet'!R33,"") -> 0.47392484 | S44: =IFERROR(S36/'Balance Sheet'!S33,"") -> 0.44713093 | T44: =IFERROR(T36/'Balance Sheet'!T33,"") -> 0.4211405 | U44: =IFERROR(U36/'Balance Sheet'!U33,"") -> 0.40346732
A46: 5. LIQUIDITY
A47: Current Ratio | C47: ='Balance Sheet'!C23/'Balance Sheet'!C42 -> 1.2818483 | D47: ='Balance Sheet'!D23/'Balance Sheet'!D42 -> 1.3438626 | E47: ='Balance Sheet'!E23/'Balance Sheet'!E42 -> 0.86616635 | F47: ='Balance Sheet'!F23/'Balance Sheet'!F42 -> 0.75671968 | G47: ='Balance Sheet'!G23/'Balance Sheet'!G42 -> 1.317718 | H47: ='Balance Sheet'!H23/'Balance Sheet'!H42 -> 1.1300752 | I47: ='Balance Sheet'!I23/'Balance Sheet'!I42 -> 1.1453559 | J47: ='Balance Sheet'!J23/'Balance Sheet'!J42 -> 1.1341055 | ... L47: ='Balance Sheet'!L23/'Balance Sheet'!L42 -> 1.458766 | P47: =IFERROR('Balance Sheet'!P23/'Balance Sheet'!P42,"") -> 1.0601701 | Q47: =IFERROR('Balance Sheet'!Q23/'Balance Sheet'!Q42,"") -> 1.0995464 | R47: =IFERROR('Balance Sheet'!R23/'Balance Sheet'!R42,"") -> 1.2125866 | S47: =IFERROR('Balance Sheet'!S23/'Balance Sheet'!S42,"") -> 1.2110316 | T47: =IFERROR('Balance Sheet'!T23/'Balance Sheet'!T42,"") -> 1.3580302 | U47: =IFERROR('Balance Sheet'!U23/'Balance Sheet'!U42,"") -> 1.3046032
A48: Quick Ratio ((current assets - inventories) / current liabilities) | C48: =('Balance Sheet'!C23-'Balance Sheet'!C19)/'Balance Sheet'!C42 -> 1.1810267 | D48: =('Balance Sheet'!D23-'Balance Sheet'!D19)/'Balance Sheet'!D42 -> 1.2462308 | E48: =('Balance Sheet'!E23-'Balance Sheet'!E19)/'Balance Sheet'!E42 -> 0.75946772 | F48: =('Balance Sheet'!F23-'Balance Sheet'!F19)/'Balance Sheet'!F42 -> 0.63144626 | G48: =('Balance Sheet'!G23-'Balance Sheet'!G19)/'Balance Sheet'!G42 -> 1.0940347 | H48: =('Balance Sheet'!H23-'Balance Sheet'!H19)/'Balance Sheet'!H42 -> 0.95894737 | I48: =('Balance Sheet'!I23-'Balance Sheet'!I19)/'Balance Sheet'!I42 -> 0.93074427 | J48: =('Balance Sheet'!J23-'Balance Sheet'!J19)/'Balance Sheet'!J42 -> 0.94641721 | ... L48: =('Balance Sheet'!L23-'Balance Sheet'!L19)/'Balance Sheet'!L42 -> 1.2508341 | P48: =IFERROR(('Balance Sheet'!P23-'Balance Sheet'!P19)/'Balance Sheet'!P42,"") -> 0.89516609 | Q48: =IFERROR(('Balance Sheet'!Q23-'Balance Sheet'!Q19)/'Balance Sheet'!Q42,"") -> 0.88524866 | R48: =IFERROR(('Balance Sheet'!R23-'Balance Sheet'!R19)/'Balance Sheet'!R42,"") -> 0.98099708 | S48: =IFERROR(('Balance Sheet'!S23-'Balance Sheet'!S19)/'Balance Sheet'!S42,"") -> 0.99759989 | T48: =IFERROR(('Balance Sheet'!T23-'Balance Sheet'!T19)/'Balance Sheet'!T42,"") -> 1.1466619 | U48: =IFERROR(('Balance Sheet'!U23-'Balance Sheet'!U19)/'Balance Sheet'!U42,"") -> 1.1201984
A49: Cash Ratio ((cash + short-term investments + marketable securities) /… | B49: Full label: Cash Ratio ((cash + short-term investments + marketable securities) / current liabilities) | C49: =C37/'Balance Sheet'!C42 -> 0.83676315 | D49: =D37/'Balance Sheet'!D42 -> 0.760278 | E49: =E37/'Balance Sheet'!E42 -> 0.55989855 | F49: =F37/'Balance Sheet'!F42 -> 0.41430319 | G49: =G37/'Balance Sheet'!G42 -> 0.74748305 | H49: =H37/'Balance Sheet'!H42 -> 0.63283208 | I49: =I37/'Balance Sheet'!I42 -> 0.58968769 | J49: =J37/'Balance Sheet'!J42 -> 0.57965296 | ... L49: =L37/'Balance Sheet'!L42 -> 0.74272826 | P49: =IFERROR(P37/'Balance Sheet'!P42,"") -> 0.63579404 | Q49: =IFERROR(Q37/'Balance Sheet'!Q42,"") -> 0.57909106 | R49: =IFERROR(R37/'Balance Sheet'!R42,"") -> 0.65152206 | S49: =IFERROR(S37/'Balance Sheet'!S42,"") -> 0.70140895 | T49: =IFERROR(T37/'Balance Sheet'!T42,"") -> 0.61757083 | U49: =IFERROR(U37/'Balance Sheet'!U42,"") -> 0.64964286
A51: 6. COVERAGE
A52: Interest Coverage (operating income / interest expense) | C52: ='Income Statement'!C18/'Income Statement'!C22 -> 11.810368 | D52: ='Income Statement'!D18/'Income Statement'!D22 -> 9.091442 | E52: ='Income Statement'!E18/'Income Statement'!E22 -> 9.6336842 | F52: ='Income Statement'!F18/'Income Statement'!F22 -> 10.661734 | G52: ='Income Statement'!G18/'Income Statement'!G22 -> 6.2609603 | H52: ='Income Statement'!H18/'Income Statement'!H22 -> 6.4546024 | I52: ='Income Statement'!I18/'Income Statement'!I22 -> 12.368481 | J52: ='Income Statement'!J18/'Income Statement'!J22 -> 7.4073346 | ... L52: ='Income Statement'!L18/'Income Statement'!L22 -> 8.3204353 | P52: =IFERROR('Income Statement'!P18/'Income Statement'!P22,"") -> 5.9058824 | Q52: =IFERROR('Income Statement'!Q18/'Income Statement'!Q22,"") -> 9.4547804 | R52: =IFERROR('Income Statement'!R18/'Income Statement'!R22,"") -> 9.6179775 | S52: =IFERROR('Income Statement'!S18/'Income Statement'!S22,"") -> 10.184143 | T52: =IFERROR('Income Statement'!T18/'Income Statement'!T22,"") -> 11.624 | U52: =IFERROR('Income Statement'!U18/'Income Statement'!U22,"") -> 12.661247
A53: CFO / Interest Expense | C53: ='Cash Flow'!C26/'Income Statement'!C22 -> 11.994543 | D53: ='Cash Flow'!D26/'Income Statement'!D22 -> 8.2543962 | E53: ='Cash Flow'!E26/'Income Statement'!E22 -> 8.0284211 | F53: ='Cash Flow'!F26/'Income Statement'!F22 -> 11.06871 | G53: ='Cash Flow'!G26/'Income Statement'!G22 -> 6.8503827 | H53: ='Cash Flow'!H26/'Income Statement'!H22 -> 7.9054477 | I53: ='Cash Flow'!I26/'Income Statement'!I22 -> 12.492063 | J53: ='Cash Flow'!J26/'Income Statement'!J22 -> 7.5959398 | ... L53: ='Cash Flow'!L26/'Income Statement'!L22 -> 4.4788392
A55: 7. CASH CONVERSION
A56: CFO Margin | C56: ='Cash Flow'!C26/'Income Statement'!C11 -> 0.21001839 | D56: ='Cash Flow'!D26/'Income Statement'!D11 -> 0.19443831 | E56: ='Cash Flow'!E26/'Income Statement'!E11 -> 0.22236152 | F56: ='Cash Flow'!F26/'Income Statement'!F11 -> 0.28097998 | G56: ='Cash Flow'!G26/'Income Statement'!G11 -> 0.29817653 | H56: ='Cash Flow'!H26/'Income Statement'!H11 -> 0.32660717 | I56: ='Cash Flow'!I26/'Income Statement'!I11 -> 0.25620872 | J56: ='Cash Flow'!J26/'Income Statement'!J11 -> 0.25350789 | ... L56: ='Cash Flow'!L26/'Income Statement'!L11 -> 0.15452327
A57: CFO / EBITDA | C57: ='Cash Flow'!C26/('Income Statement'!C18+'Cash Flow'!C17) -> 0.84182306 | D57: ='Cash Flow'!D26/('Income Statement'!D18+'Cash Flow'!D17) -> 0.78103161 | E57: ='Cash Flow'!E26/('Income Statement'!E18+'Cash Flow'!E17) -> 0.74496972 | F57: ='Cash Flow'!F26/('Income Statement'!F18+'Cash Flow'!F17) -> 0.91441795 | G57: ='Cash Flow'!G26/('Income Statement'!G18+'Cash Flow'!G17) -> 0.93458654 | H57: ='Cash Flow'!H26/('Income Statement'!H18+'Cash Flow'!H17) -> 1.0735544 | I57: ='Cash Flow'!I26/('Income Statement'!I18+'Cash Flow'!I17) -> 0.9054154 | J57: ='Cash Flow'!J26/('Income Statement'!J18+'Cash Flow'!J17) -> 0.93247046 | ... L57: ='Cash Flow'!L26/('Income Statement'!L18+'Cash Flow'!L17) -> 0.50013503
A58: Capex Intensity (purchases of PP&E / revenue) | C58: =0-'Cash Flow'!C32/'Income Statement'!C11 -> 0.054033395 | D58: =0-'Cash Flow'!D32/'Income Statement'!D11 -> 0.048326522 | E58: =0-'Cash Flow'!E32/'Income Statement'!E11 -> 0.045131195 | F58: =0-'Cash Flow'!F32/'Income Statement'!F11 -> 0.055117265 | G58: =0-'Cash Flow'!G32/'Income Statement'!G11 -> 0.035651542 | H58: =0-'Cash Flow'!H32/'Income Statement'!H11 -> 0.035364118 | I58: =0-'Cash Flow'!I32/'Income Statement'!I11 -> 0.034508418 | J58: =0-'Cash Flow'!J32/'Income Statement'!J11 -> 0.040477335 | ... L58: =0-'Cash Flow'!L32/'Income Statement'!L11 -> 0.04405415
A59: Free Cash Flow (CFO + purchases of PP&E) | C59: ='Cash Flow'!C71 -> 6530 | D59: ='Cash Flow'!D71 -> 5291 | E59: ='Cash Flow'!E71 -> 6079 | F59: ='Cash Flow'!F71 -> 8417 | G59: ='Cash Flow'!G71 -> 8667 | H59: ='Cash Flow'!H71 -> 11258 | I59: ='Cash Flow'!I71 -> 9534 | J59: ='Cash Flow'!J71 -> 9747 | ... L59: ='Cash Flow'!L71 -> 5296
A60: FCF Margin | C60: ='Cash Flow'!C71/'Income Statement'!C11 -> 0.155985 | D60: ='Cash Flow'!D71/'Income Statement'!D11 -> 0.14611179 | E60: ='Cash Flow'!E71/'Income Statement'!E11 -> 0.17723032 | F60: ='Cash Flow'!F71/'Income Statement'!F11 -> 0.22586272 | G60: ='Cash Flow'!G71/'Income Statement'!G11 -> 0.26252499 | H60: ='Cash Flow'!H71/'Income Statement'!H11 -> 0.29124305 | I60: ='Cash Flow'!I71/'Income Statement'!I11 -> 0.22170031 | J60: ='Cash Flow'!J71/'Income Statement'!J11 -> 0.21303055 | ... L60: ='Cash Flow'!L71/'Income Statement'!L11 -> 0.11046912
A61: FCF / Net income attributable | C61: ='Cash Flow'!C71/'Income Statement'!C32 -> 1.0004596 | D61: ='Cash Flow'!D71/'Income Statement'!D32 -> 4.2395833 | E61: ='Cash Flow'!E71/'Income Statement'!E32 -> 0.94482437 | F61: ='Cash Flow'!F71/'Income Statement'!F32 -> 0.94360987 | G61: ='Cash Flow'!G71/'Income Statement'!G32 -> 1.1187556 | H61: ='Cash Flow'!H71/'Income Statement'!H32 -> 1.152185 | I61: ='Cash Flow'!I71/'Income Statement'!I32 -> 0.9991616 | J61: ='Cash Flow'!J71/'Income Statement'!J32 -> 0.90974426 | ... L61: ='Cash Flow'!L71/'Income Statement'!L32 -> 0.4040589
A62: D&A / Capex | C62: =0-'Cash Flow'!C17/'Cash Flow'!C32 -> 0.79000884 | D62: =0-'Cash Flow'!D17/'Cash Flow'!D32 -> 0.72 | E62: =0-'Cash Flow'!E17/'Cash Flow'!E32 -> 0.70155039 | F62: =0-'Cash Flow'!F17/'Cash Flow'!F32 -> 0.66455696 | G62: =0-'Cash Flow'!G17/'Cash Flow'!G32 -> 1.3050127 | H62: =0-'Cash Flow'!H17/'Cash Flow'!H32 -> 1.06218 | I62: =0-'Cash Flow'!I17/'Cash Flow'!I32 -> 0.8490566 | J62: =0-'Cash Flow'!J17/'Cash Flow'!J32 -> 0.60907127 | ... L62: =0-'Cash Flow'!L17/'Cash Flow'!L32 -> 0.49715909
A64: 8. EARNINGS QUALITY
A65: CFO / Net income attributable | C65: ='Cash Flow'!C26/'Income Statement'!C32 -> 1.3470201 | D65: ='Cash Flow'!D26/'Income Statement'!D32 -> 5.6418269 | E65: ='Cash Flow'!E26/'Income Statement'!E32 -> 1.1854212 | F65: ='Cash Flow'!F26/'Income Statement'!F32 -> 1.1738789 | G65: ='Cash Flow'!G26/'Income Statement'!G32 -> 1.2706854 | H65: ='Cash Flow'!H26/'Income Statement'!H32 -> 1.2920888 | I65: ='Cash Flow'!I26/'Income Statement'!I32 -> 1.1546846 | J65: ='Cash Flow'!J26/'Income Statement'!J32 -> 1.0826022 | ... L65: ='Cash Flow'!L26/'Income Statement'!L32 -> 0.56519417
A66: Accrual Ratio ((NI attributable - CFO) / average total assets) | D66: =('Income Statement'!D32-'Cash Flow'!D26)/('Balance Sheet'!D33+'Balance Sheet'!C33)*2 -> -0.066142973 | E66: =('Income Statement'!E32-'Cash Flow'!E26)/('Balance Sheet'!E33+'Balance Sheet'!D33)*2 -> -0.013944083 | F66: =('Income Statement'!F32-'Cash Flow'!F26)/('Balance Sheet'!F33+'Balance Sheet'!E33)*2 -> -0.018290418 | G66: =('Income Statement'!G32-'Cash Flow'!G26)/('Balance Sheet'!G33+'Balance Sheet'!F33)*2 -> -0.024148275 | H66: =('Income Statement'!H32-'Cash Flow'!H26)/('Balance Sheet'!H33+'Balance Sheet'!G33)*2 -> -0.031423066 | I66: =('Income Statement'!I32-'Cash Flow'!I26)/('Balance Sheet'!I33+'Balance Sheet'!H33)*2 -> -0.015776226 | J66: =('Income Statement'!J32-'Cash Flow'!J26)/('Balance Sheet'!J33+'Balance Sheet'!I33)*2 -> -0.0092929972 | K66: =('Income Statement'!K32-'Cash Flow'!K26)/('Balance Sheet'!K33+'Balance Sheet'!J33)*2 -> 0.038597341 | L66: =('Income Statement'!L32-'Cash Flow'!L26)/('Balance Sheet'!L33+'Balance Sheet'!K33)*2 -> 0.055501181
A68: 9. GROWTH
A69: Revenue Growth | D69: ='Income Statement'!D11/'Income Statement'!C11-1 -> -0.13498794 | E69: ='Income Statement'!E11/'Income Statement'!D11-1 -> -0.052800177 | F69: ='Income Statement'!F11/'Income Statement'!E11-1 -> 0.086472303 | G69: ='Income Statement'!G11/'Income Statement'!F11-1 -> -0.11409864 | H69: ='Income Statement'!H11/'Income Statement'!G11-1 -> 0.1708669 | I69: ='Income Statement'!I11/'Income Statement'!H11-1 -> 0.11250808 | J69: ='Income Statement'!J11/'Income Statement'!I11-1 -> 0.06394754 | K69: ='Income Statement'!K11/'Income Statement'!J11-1 -> 0.028565808 | L69: ='Income Statement'!L11/'Income Statement'!K11-1 -> 0.018699135 | S69: =IFERROR('Income Statement'!S11/'Income Statement'!P11-1,"") -> 0.050700186 | T69: =IFERROR('Income Statement'!T11/'Income Statement'!Q11-1,"") -> 0.12067571 | U69: =IFERROR('Income Statement'!U11/'Income Statement'!R11-1,"") -> 0.067411249
A70: Operating Income Growth | D70: ='Income Statement'!D18/'Income Statement'!C18-1 -> -0.10419314 | E70: ='Income Statement'!E18/'Income Statement'!D18-1 -> 0.18014184 | F70: ='Income Statement'!F18/'Income Statement'!E18-1 -> 0.1020542 | G70: ='Income Statement'!G18/'Income Statement'!F18-1 -> -0.10797145 | H70: ='Income Statement'!H18/'Income Statement'!G18-1 -> 0.14571524 | I70: ='Income Statement'!I18/'Income Statement'!H18-1 -> 0.05830423 | J70: ='Income Statement'!J18/'Income Statement'!I18-1 -> 0.036850307 | K70: ='Income Statement'!K18/'Income Statement'!J18-1 -> -0.11661215 | L70: ='Income Statement'!L18/'Income Statement'!K18-1 -> 0.37730184 | S70: =IFERROR('Income Statement'!S18/'Income Statement'!P18-1,"") -> 0.58645418 | T70: =IFERROR('Income Statement'!T18/'Income Statement'!Q18-1,"") -> 0.1913091 | U70: =IFERROR('Income Statement'!U18/'Income Statement'!R18-1,"") -> 0.091588785
A71: Net Income (attributable) Growth | D71: ='Income Statement'!D32/'Income Statement'!C32-1 -> -0.80879424 | E71: ='Income Statement'!E32/'Income Statement'!D32-1 -> 4.1554487 | F71: ='Income Statement'!F32/'Income Statement'!E32-1 -> 0.38638483 | G71: ='Income Statement'!G32/'Income Statement'!F32-1 -> -0.13150224 | H71: ='Income Statement'!H32/'Income Statement'!G32-1 -> 0.26126242 | I71: ='Income Statement'!I32/'Income Statement'!H32-1 -> -0.0234367 | J71: ='Income Statement'!J32/'Income Statement'!I32-1 -> 0.1228254 | K71: ='Income Statement'!K32/'Income Statement'!J32-1 -> -0.0077468732 | L71: ='Income Statement'!L32/'Income Statement'!K32-1 -> 0.23290377 | S71: =IFERROR('Income Statement'!S32/'Income Statement'!P32-1,"") -> 0.29775281 | T71: =IFERROR('Income Statement'!T32/'Income Statement'!Q32-1,"") -> 0.17837838 | U71: =IFERROR('Income Statement'!U32/'Income Statement'!R32-1,"") -> 0.16141732
A72: Diluted EPS Growth | D72: ='Income Statement'!D42/'Income Statement'!C42-1 -> -0.80536913 | E72: ='Income Statement'!E42/'Income Statement'!D42-1 -> 4.1724138 | F72: ='Income Statement'!F42/'Income Statement'!E42-1 -> 0.38 | G72: ='Income Statement'!G42/'Income Statement'!F42-1 -> -0.1352657 | H72: ='Income Statement'!H42/'Income Statement'!G42-1 -> 0.25698324 | I72: ='Income Statement'!I42/'Income Statement'!H42-1 -> -0.026666667 | J72: ='Income Statement'!J42/'Income Statement'!I42-1 -> 0.12785388 | K72: ='Income Statement'!K42/'Income Statement'!J42-1 -> -0.004048583 | L72: ='Income Statement'!L42/'Income Statement'!K42-1 -> 0.23577236 | S72: =IFERROR('Income Statement'!S42/'Income Statement'!P42-1,"") -> 0.3030303 | T72: =IFERROR('Income Statement'!T42/'Income Statement'!Q42-1,"") -> 0.18181818 | U72: =IFERROR('Income Statement'!U42/'Income Statement'!R42-1,"") -> 0.17045455
A73: CFO Growth | D73: ='Cash Flow'!D26/'Cash Flow'!C26-1 -> -0.19915833 | E73: ='Cash Flow'!E26/'Cash Flow'!D26-1 -> 0.083226814 | F73: ='Cash Flow'!F26/'Cash Flow'!E26-1 -> 0.3728858 | G73: ='Cash Flow'!G26/'Cash Flow'!F26-1 -> -0.059879668 | H73: ='Cash Flow'!H26/'Cash Flow'!G26-1 -> 0.28250711 | I73: ='Cash Flow'!I26/'Cash Flow'!H26-1 -> -0.12728713 | J73: ='Cash Flow'!J26/'Cash Flow'!I26-1 -> 0.052731893 | K73: ='Cash Flow'!K26/'Cash Flow'!J26-1 -> -0.41331149 | L73: ='Cash Flow'!L26/'Cash Flow'!K26-1 -> 0.088611315
A74: Diluted weighted-average shares change | D74: ='Income Statement'!D45/'Income Statement'!C45-1 -> -0.0098465766 | E74: ='Income Statement'!E45/'Income Statement'!D45-1 -> -0.0057816836 | F74: ='Income Statement'!F45/'Income Statement'!E45-1 -> 0.0034891835 | G74: ='Income Statement'!G45/'Income Statement'!F45-1 -> 0.0020862309 | H74: ='Income Statement'!H45/'Income Statement'!G45-1 -> 0.0039324543 | I74: ='Income Statement'!I45/'Income Statement'!H45-1 -> 0.0023041475 | J74: ='Income Statement'!J45/'Income Statement'!I45-1 -> -0.0025287356 | K74: ='Income Statement'!K45/'Income Statement'!J45-1 -> -0.0043788891 | L74: ='Income Statement'!L45/'Income Statement'!K45-1 -> -0.0016203704 | S74: =IFERROR('Income Statement'!S45/'Income Statement'!P45-1,"") -> -0.0023132084 | T74: =IFERROR('Income Statement'!T45/'Income Statement'!Q45-1,"") -> 0.00023185718 | U74: =IFERROR('Income Statement'!U45/'Income Statement'!R45-1,"") -> -0.00046349942
A76: 10. SHAREOWNER RETURNS
A77: Cash dividends paid (shown positive) | C77: =0-'Cash Flow'!C42 -> 6043 | D77: =0-'Cash Flow'!D42 -> 6320 | E77: =0-'Cash Flow'!E42 -> 6644 | F77: =0-'Cash Flow'!F42 -> 6845 | G77: =0-'Cash Flow'!G42 -> 7047 | H77: =0-'Cash Flow'!H42 -> 7252 | I77: =0-'Cash Flow'!I42 -> 7616 | J77: =0-'Cash Flow'!J42 -> 7952 | ... L77: =0-'Cash Flow'!L42 -> 8779
A78: Purchases of stock for treasury (shown positive) | C78: =0-'Cash Flow'!C41 -> 3681 | D78: =0-'Cash Flow'!D41 -> 3682 | E78: =0-'Cash Flow'!E41 -> 1912 | F78: =0-'Cash Flow'!F41 -> 1103 | G78: =0-'Cash Flow'!G41 -> 118 | H78: =0-'Cash Flow'!H41 -> 111 | I78: =0-'Cash Flow'!I41 -> 1418 | J78: =0-'Cash Flow'!J41 -> 2289 | ... L78: =0-'Cash Flow'!L41 -> 746
A79: Issuances of stock | C79: ='Cash Flow'!C40 -> 1434 | D79: ='Cash Flow'!D40 -> 1595 | E79: ='Cash Flow'!E40 -> 1476 | F79: ='Cash Flow'!F40 -> 1012 | G79: ='Cash Flow'!G40 -> 647 | H79: ='Cash Flow'!H40 -> 702 | I79: ='Cash Flow'!I40 -> 837 | J79: ='Cash Flow'!J40 -> 539 | ... L79: ='Cash Flow'!L40 -> 313
A80: Dividend payout (dividends / NI attributable) | C80: =C77/'Income Statement'!C32 -> 0.92584648 | D80: =D77/'Income Statement'!D32 -> 5.0641026 | E80: =E77/'Income Statement'!E32 -> 1.0326391 | F80: =F77/'Income Statement'!F32 -> 0.76737668 | G80: =G77/'Income Statement'!G32 -> 0.90964244 | H80: =H77/'Income Statement'!H32 -> 0.7421963 | I80: =I77/'Income Statement'!I32 -> 0.79815552 | J80: =J77/'Income Statement'!J32 -> 0.74220646 | ... L80: =L77/'Income Statement'!L32 -> 0.66979477
A81: Total payout ((dividends + treasury purchases) / NI attributable) | C81: =(C77+C78)/'Income Statement'!C32 -> 1.4898116 | D81: =(D77+D78)/'Income Statement'!D32 -> 8.0144231 | E81: =(E77+E78)/'Income Statement'!E32 -> 1.3298104 | F81: =(F77+F78)/'Income Statement'!F32 -> 0.89103139 | G81: =(G77+G78)/'Income Statement'!G32 -> 0.92487414 | H81: =(H77+H78)/'Income Statement'!H32 -> 0.75355644 | I81: =(I77+I78)/'Income Statement'!I32 -> 0.94676169 | J81: =(J77+J78)/'Income Statement'!J32 -> 0.95585216 | ... L81: =(L77+L78)/'Income Statement'!L32 -> 0.72671092
A82: Dividends % of FCF | C82: =C77/C59 -> 0.92542113 | D82: =D77/D59 -> 1.1944812 | E82: =E77/E59 -> 1.0929429 | F82: =F77/F59 -> 0.81323512 | G82: =G77/G59 -> 0.81308411 | H82: =H77/H59 -> 0.64416415 | I82: =I77/I59 -> 0.79882526 | J82: =J77/J59 -> 0.81584077 | ... L82: =L77/L59 -> 1.6576662
A84: 11. WORKING CAPITAL
A85: Days Sales Outstanding | C85: ='Balance Sheet'!C18/'Income Statement'!C11*365 -> 33.620142 | D85: ='Balance Sheet'!D18/'Income Statement'!D11*365 -> 36.961643 | E85: ='Balance Sheet'!E18/'Income Statement'!E11*365 -> 39.213557 | F85: ='Balance Sheet'!F18/'Income Statement'!F11*365 -> 38.893764 | G85: ='Balance Sheet'!G18/'Income Statement'!G11*365 -> 34.759799 | H85: ='Balance Sheet'!H18/'Income Statement'!H11*365 -> 33.162075 | I85: ='Balance Sheet'!I18/'Income Statement'!I11*365 -> 29.5962 | J85: ='Balance Sheet'!J18/'Income Statement'!J11*365 -> 27.203086 | ... L85: ='Balance Sheet'!L18/'Income Statement'!L11*365 -> 23.129889 | P85: =IFERROR('Balance Sheet'!P18/'Income Statement'!P11*91,"") -> 32.495613 | Q85: =IFERROR('Balance Sheet'!Q18/'Income Statement'!Q11*91,"") -> 33.451433 | R85: =IFERROR('Balance Sheet'!R18/'Income Statement'!R11*91,"") -> 30.258317 | S85: =IFERROR('Balance Sheet'!S18/'Income Statement'!S11*91,"") -> 28.83067 | T85: =IFERROR('Balance Sheet'!T18/'Income Statement'!T11*91,"") -> 26.814064 | U85: =IFERROR('Balance Sheet'!U18/'Income Statement'!U11*91,"") -> 25.382063
A86: Days Inventory Outstanding | C86: ='Balance Sheet'!C19/'Income Statement'!C13*365 -> 59.30003 | D86: ='Balance Sheet'!D19/'Income Statement'!D13*365 -> 70.627141 | E86: ='Balance Sheet'!E19/'Income Statement'!E13*365 -> 85.782123 | F86: ='Balance Sheet'!F19/'Income Statement'!F13*365 -> 84.36521 | G86: ='Balance Sheet'!G19/'Income Statement'!G13*365 -> 88.743393 | H86: ='Balance Sheet'!H19/'Income Statement'!H13*365 -> 81.142801 | I86: ='Balance Sheet'!I19/'Income Statement'!I13*365 -> 85.835833 | J86: ='Balance Sheet'!J19/'Income Statement'!J13*365 -> 87.190065 | ... L86: ='Balance Sheet'!L19/'Income Statement'!L13*365 -> 87.792847 | P86: =IFERROR('Balance Sheet'!P19/'Income Statement'!P13*91,"") -> 91.975557 | Q86: =IFERROR('Balance Sheet'!Q19/'Income Statement'!Q13*91,"") -> 111.52582 | R86: =IFERROR('Balance Sheet'!R19/'Income Statement'!R13*91,"") -> 98.103946 | S86: =IFERROR('Balance Sheet'!S19/'Income Statement'!S13*91,"") -> 91.094851 | T86: =IFERROR('Balance Sheet'!T19/'Income Statement'!T13*91,"") -> 93.166667 | U86: =IFERROR('Balance Sheet'!U19/'Income Statement'!U13*91,"") -> 85.171601
A87: Days Payable Outstanding (AP and accrued expenses) | C87: ='Balance Sheet'!C36/'Income Statement'!C13*365 -> 210.37656 | D87: ='Balance Sheet'!D36/'Income Statement'!D13*365 -> 232.71044 | E87: ='Balance Sheet'!E36/'Income Statement'!E13*365 -> 266.28492 | F87: ='Balance Sheet'!F36/'Income Statement'!F13*365 -> 282.43245 | G87: ='Balance Sheet'!G36/'Income Statement'!G13*365 -> 302.83072 | H87: ='Balance Sheet'!H36/'Income Statement'!H13*365 -> 347.45946 | I87: ='Balance Sheet'!I36/'Income Statement'!I13*365 -> 319.35472 | J87: ='Balance Sheet'!J36/'Income Statement'!J13*365 -> 305.18494 | ... L87: ='Balance Sheet'!L36/'Income Statement'!L13*365 -> 293.89275 | P87: =IFERROR('Balance Sheet'!P36/'Income Statement'!P13*91,"") -> 464.75557 | Q87: =IFERROR('Balance Sheet'!Q36/'Income Statement'!Q13*91,"") -> 360.65554 | R87: =IFERROR('Balance Sheet'!R36/'Income Statement'!R13*91,"") -> 328.75053 | S87: =IFERROR('Balance Sheet'!S36/'Income Statement'!S13*91,"") -> 335.6206 | T87: =IFERROR('Balance Sheet'!T36/'Income Statement'!T13*91,"") -> 283.81364 | U87: =IFERROR('Balance Sheet'!U36/'Income Statement'!U13*91,"") -> 282.87895
A88: Cash Conversion Cycle | C88: =C85+C86-C87 -> -117.45638 | D88: =D85+D86-D87 -> -125.12166 | E88: =E85+E86-E87 -> -141.28924 | F88: =F85+F86-F87 -> -159.17348 | G88: =G85+G86-G87 -> -179.32752 | H88: =H85+H86-H87 -> -233.15459 | I88: =I85+I86-I87 -> -203.92269 | J88: =J85+J86-J87 -> -190.79178 | ... L88: =L85+L86-L87 -> -182.97002 | P88: =P85+P86-P87 -> -340.2844 | Q88: =Q85+Q86-Q87 -> -215.67828 | R88: =R85+R86-R87 -> -200.38827 | S88: =S85+S86-S87 -> -215.69507 | T88: =T85+T86-T87 -> -163.83291 | U88: =U85+U86-U87 -> -172.32529

Sheet Note Schedules
A1: The Coca-Cola Company — Note Schedules
A2: $ in millions except per-share data | USD | as of 2026-10-14
C3: FY2016 | D3: FY2017 | E3: FY2018 | F3: FY2019 | G3: FY2020 | H3: FY2021 | I3: FY2022 | J3: FY2023 | K3: FY2024 | L3: FY2025 | M3: · | N3: · | O3: · | P3: 3Q2024 | Q3: 1Q2025 | R3: 2Q2025 | S3: 3Q2025 | T3: 1Q2026 | U3: 2Q2026
C4: 2016-12-31 | D4: 2017-12-31 | E4: 2018-12-31 | F4: 2019-12-31 | G4: 2020-12-31 | H4: 2021-12-31 | I4: 2022-12-31 | J4: 2023-12-31 | K4: 2024-12-31 | L4: 2025-12-31 | P4: 2024-09-27 | Q4: 2025-03-28 | R4: 2025-06-27 | S4: 2025-09-26 | T4: 2026-04-03 | U4: 2026-07-03
A6: CONTENTS
A7: =HYPERLINK("#'Note Schedules'!A15","1. EQUITY METHOD INVESTEES — AGGREGATE FINANCIAL INFORMATION AND THE COMPANY'S SHARE OF NET INCOME (Note 6)") -> 1. EQUITY METHOD INVESTEES — AGGREGATE FINANCIAL INFORMATION AND THE COMPANY'S SHARE OF NET INCOME (Note 6)
A8: =HYPERLINK("#'Note Schedules'!A26","2. QUOTED FAIR VALUES — see carrying-value supplement below") -> 2. QUOTED FAIR VALUES — see carrying-value supplement below
A9: =HYPERLINK("#'Note Schedules'!A35","3. INCOME BEFORE INCOME TAXES BY JURISDICTION (Note 15)") -> 3. INCOME BEFORE INCOME TAXES BY JURISDICTION (Note 15)
A10: =HYPERLINK("#'Note Schedules'!A40","4. INCOME TAXES — CURRENT AND DEFERRED BY JURISDICTION (Note 15)") -> 4. INCOME TAXES — CURRENT AND DEFERRED BY JURISDICTION (Note 15)
A11: =HYPERLINK("#'Note Schedules'!A54","5. UNRECOGNIZED TAX BENEFITS — ROLL-FORWARD (Note 15)") -> 5. UNRECOGNIZED TAX BENEFITS — ROLL-FORWARD (Note 15)
A12: =HYPERLINK("#'Note Schedules'!A67","6. LONG-TERM DEBT BY TYPE (2025 10-K, Note 11)") -> 6. LONG-TERM DEBT BY TYPE (2025 10-K, Note 11)
A13: =HYPERLINK("#'Note Schedules'!A78","7. ASSETS AND LIABILITIES HELD FOR SALE (2025 10-K, Note 2)") -> 7. ASSETS AND LIABILITIES HELD FOR SALE (2025 10-K, Note 2)
A15: 1. EQUITY METHOD INVESTEES — AGGREGATE FINANCIAL INFORMATION AND THE COMPANY'S SHARE OF NET INCOME (Note 6)
A16: Net operating revenues | B16: Note 6 Equity Method Investments — aggregate financial information of the investees, and the Company's share of their net income. | C16: 58054 | D16: 73343 | E16: 75482 | F16: 75980 | G16: 69384 | H16: 79934 | I16: 85116 | J16: 93862 | K16: 99043 | L16: 102800
A17: Cost of goods sold | B17: Note 6 Equity Method Investments — aggregate financial information of the investees, and the Company's share of their net income. | C17: 34338 | D17: 42871 | E17: 44933 | F17: 44881 | G17: 41139 | H17: 47847 | I17: 52051 | J17: 55780 | K17: 58527 | L17: 60622
A18: Gross profit | B18: Note 6 Equity Method Investments — aggregate financial information of the investees, and the Company's share of their net income. | C18: 23716 | D18: 30472 | E18: 30549 | F18: 31099 | G18: 28245 | H18: 32087 | I18: 33065 | J18: 38082 | K18: 40516 | L18: 42178
A19: Operating income | B19: Note 6 Equity Method Investments — aggregate financial information of the investees, and the Company's share of their net income. | C19: 5652 | D19: 7577 | E19: 7511 | F19: 7748 | G19: 7056 | H19: 9089 | I19: 9719 | J19: 11868 | K19: 12536 | L19: 13426
A20: Consolidated net income | B20: Note 6 Equity Method Investments — aggregate financial information of the investees, and the Company's share of their net income. | C20: 2967 | D20: 4545 | E20: 4646 | F20: 4597 | G20: 4176 | H20: 6050 | I20: 6373 | J20: 7657 | K20: 8439 | L20: 9355
A21: Less: Net income attributable to noncontrolling interests | B21: Note 6 Equity Method Investments — aggregate financial information of the investees, and the Company's share of their net income. | C21: 78 | D21: 120 | E21: 101 | F21: 63 | G21: 54 | H21: 91 | I21: 102 | J21: 75 | K21: 98 | L21: 153
A22: Net income attributable to common shareowners | B22: Note 6 Equity Method Investments — aggregate financial information of the investees, and the Company's share of their net income. | C22: 2889 | D22: 4425 | E22: 4545 | F22: 4534 | G22: 4122 | H22: 5959 | I22: 6271 | J22: 7582 | K22: 8341 | L22: 9202
A23: Equity income (loss) — net | B23: Note 6 Equity Method Investments — aggregate financial information of the investees, and the Company's share of their net income. | C23: 835 | D23: 1072 | E23: 1008 | F23: 1049 | G23: 978 | H23: 1438 | I23: 1472 | J23: 1691 | K23: 1770 | L23: 2031
A24: Check: investees' equity income - IS equity income (loss) — net (≈0) | C24: =C23-'Income Statement'!C23 -> 0 | D24: =D23-'Income Statement'!D23 -> 0 | E24: =E23-'Income Statement'!E23 -> 0 | F24: =F23-'Income Statement'!F23 -> 0 | G24: =G23-'Income Statement'!G23 -> 0 | H24: =H23-'Income Statement'!H23 -> 0 | I24: =I23-'Income Statement'!I23 -> 0 | J24: =J23-'Income Statement'!J23 -> 0 | ... L24: =L23-'Income Statement'!L23 -> 0
A26: 2. EQUITY METHOD INVESTMENTS — QUOTED FAIR VALUES (FY2025, Note 6; carrying-value bridge below)
A27: Monster Beverage Corporation | L27: 15659
A28: Coca-Cola Europacific Partners plc | L28: 7163
A29: Coca-Cola FEMSA, S.A.B. de C.V. | L29: 5543
A30: Coca-Cola HBC AG | L30: 4051
A31: Coca-Cola Bottlers Japan Holdings Inc. | L31: 822
A32: Coca-Cola İ ç ecek A. Ş. | L32: 770
A33: Embotelladora Andina S.A. | L33: 278
A35: 3. INCOME BEFORE INCOME TAXES BY JURISDICTION (Note 15)
A36: United States | B36: Note 15 Income Taxes — income before income taxes by jurisdiction. FY2024-FY2023 Puerto Rico amounts were reclassified from United States to International on adoption of ASU 2023-09. | C36: 113 | D36: -690 | E36: 888 | F36: 3249 | G36: 3149 | H36: 3538 | I36: 3452 | J36: 1991 | K36: 2499 | L36: 5678
A37: International | B37: Note 15 Income Taxes — income before income taxes by jurisdiction. FY2024-FY2023 Puerto Rico amounts were reclassified from United States to International on adoption of ASU 2023-09. | C37: 8023 | D37: 7580 | E37: 7337 | F37: 7537 | G37: 6600 | H37: 8887 | I37: 8234 | J37: 10961 | K37: 10587 | L37: 10320
A38: Total | B38: Note 15 Income Taxes — income before income taxes by jurisdiction. FY2024-FY2023 Puerto Rico amounts were reclassified from United States to International on adoption of ASU 2023-09. | C38: 8136 | D38: 6890 | E38: 8225 | F38: 10786 | G38: 9749 | H38: 12425 | I38: 11686 | J38: 12952 | K38: 13086 | L38: 15998
A40: 4. INCOME TAXES — CURRENT AND DEFERRED BY JURISDICTION (Note 15)
A41: Current
A42: United States | B42: Note 15 Income Taxes — current and deferred tax expense by jurisdiction. | F42: 508 | G42: 296 | H42: 243 | I42: 468 | J42: 83 | K42: 324 | L42: 86
A43: State and Local | B43: Note 15 Income Taxes — current and deferred tax expense by jurisdiction. | F43: 94 | G43: 396 | H43: 106 | I43: 118 | J43: 129 | K43: 143 | L43: 178
A44: International | B44: Note 15 Income Taxes — current and deferred tax expense by jurisdiction. | F44: 1479 | G44: 1307 | H44: 1378 | I44: 1651 | J44: 2039 | K44: 1981 | L44: 2080
A45: Total | B45: Note 15 Income Taxes — current and deferred tax expense by jurisdiction. | F45: 2081 | G45: 1999 | H45: 1727 | I45: 2237 | J45: 2251 | K45: 2448 | L45: 2344
A47: Deferred
A48: United States | B48: Note 15 Income Taxes — current and deferred tax expense by jurisdiction. | F48: -65 | G48: -220 | H48: 229 | I48: -121 | J48: -135 | K48: -254 | L48: 220
A49: State and Local | B49: Note 15 Income Taxes — current and deferred tax expense by jurisdiction. | F49: 52 | G49: 21 | H49: -10 | I49: -4 | J49: -78 | K49: -134 | L49: 123
A50: International | B50: Note 15 Income Taxes — current and deferred tax expense by jurisdiction. | F50: -267 | G50: 181 | H50: 675 | I50: 3 | J50: 211 | K50: 377 | L50: 174
A51: Total | B51: Note 15 Income Taxes — current and deferred tax expense by jurisdiction. | F51: -280 | G51: -18 | H51: 894 | I51: -122 | J51: -2 | K51: -11 | L51: 517
A54: 5. UNRECOGNIZED TAX BENEFITS — ROLL-FORWARD (Note 15)
A55: Beginning balance of unrecognized tax benefits | B55: Note 15 Income Taxes — reconciliation of the gross unrecognized tax benefits. | C55: 168 | D55: 302 | E55: 331
A56: Increase related to prior period tax positions | B56: Note 15 Income Taxes — reconciliation of the gross unrecognized tax benefits. | C56: 163 | D56: 18 | E56: 11 | F56: 204 | G56: 528 | H56: 9 | I56: 6 | J56: 2 | K56: 33 | L56: 19
A57: Decrease related to prior period tax positions | B57: Note 15 Income Taxes — reconciliation of the gross unrecognized tax benefits. | C57: 0 | D57: -13 | E57: -2 | F57: 0 | G57: -1 | H57: -50 | I57: 0 | J57: -25 | K57: -52 | L57: -46
A58: Increase related to current period tax positions | B58: Note 15 Income Taxes — reconciliation of the gross unrecognized tax benefits. | C58: 17 | D58: 13 | E58: 17 | F58: 29 | G58: 26 | H58: 37 | I58: 38 | J58: 32 | K58: 30 | L58: 31
A59: Decrease related to settlements with taxing authorities | B59: Note 15 Income Taxes — reconciliation of the gross unrecognized tax benefits. | C59: -40 | D59: 0 | E59: -4 | F59: -174 | G59: -19 | H59: -4 | I59: -2 | J59: 0 | K59: -57 | L59: 0
A60: Decrease due to lapse of the applicable statute of limitations | B60: Note 15 Income Taxes — reconciliation of the gross unrecognized tax benefits. | C60: 0 | D60: 0 | E60: 0 | I60: 0 | J60: -2 | K60: 0 | L60: -13
A61: Increase (decrease) due to effect of foreign currency exchange rate changes | B61: Note 15 Income Taxes — reconciliation of the gross unrecognized tax benefits. | C61: -6 | D61: 11 | E61: -17 | F61: -3 | G61: -11
A62: Ending balance of unrecognized tax benefits | B62: Note 15 Income Taxes — reconciliation of the gross unrecognized tax benefits. | C62: 302 | D62: 331 | E62: 336
A63: Balance of unrecognized tax benefits at beginning of year | B63: Note 15 Income Taxes — reconciliation of the gross unrecognized tax benefits. | D63: 302 | E63: 331 | F63: 336 | G63: 392 | H63: 915 | I63: 906 | J63: 926 | K63: 929 | L63: 880
A64: Balance of unrecognized tax benefits at end of year | B64: Note 15 Income Taxes — reconciliation of the gross unrecognized tax benefits. | D64: 331 | E64: 336 | F64: 392 | G64: 915 | H64: 906 | I64: 926 | J64: 929 | K64: 880 | L64: 857
A65: Effect of foreign currency translation | B65: Note 15 Income Taxes — reconciliation of the gross unrecognized tax benefits. | G65: -11 | H65: -1 | I65: -22 | J65: -4 | K65: -3 | L65: -14
A67: 6. LONG-TERM DEBT BY TYPE (2025 10-K, Note 11)
A68: U.S. dollar notes due 2027-2093 | B68: Note 11 Debt and Borrowing Arrangements — long-term debt by type, as filed (amounts only; weighted-average rates are in the filing). | K68: 26931 | L68: 26945
A69: U.S. dollar debentures due 2026-2098 | B69: Note 11 Debt and Borrowing Arrangements — long-term debt by type, as filed (amounts only; weighted-average rates are in the filing). | K69: 778 | L69: 767
A70: Euro notes due 2026-2053 | B70: Note 11 Debt and Borrowing Arrangements — long-term debt by type, as filed (amounts only; weighted-average rates are in the filing). | K70: 13619 | L70: 15470
A71: Swiss franc notes due 2028 | B71: Note 11 Debt and Borrowing Arrangements — long-term debt by type, as filed (amounts only; weighted-average rates are in the filing). | K71: 635 | L71: 726
A72: Other, due through 2098 2 | B72: Note 11 Debt and Borrowing Arrangements — long-term debt by type, as filed (amounts only; weighted-average rates are in the filing). | K72: 1845 | L72: 651
A73: Fair value adjustments 3 | B73: Note 11 Debt and Borrowing Arrangements — long-term debt by type, as filed (amounts only; weighted-average rates are in the filing). | K73: -785 | L73: -618
A74: Total 4,5 | B74: Note 11 Debt and Borrowing Arrangements — long-term debt by type, as filed (amounts only; weighted-average rates are in the filing). | K74: 43023 | L74: 43941
A75: Less: Current portion | B75: Note 11 Debt and Borrowing Arrangements — long-term debt by type, as filed (amounts only; weighted-average rates are in the filing). | K75: 648 | L75: 1822
A76: Long-term debt | B76: Note 11 Debt and Borrowing Arrangements — long-term debt by type, as filed (amounts only; weighted-average rates are in the filing). | K76: 42375 | L76: 42119
A78: 7. ASSETS AND LIABILITIES HELD FOR SALE (2025 10-K, Note 2)
A79: Cash, cash equivalents and short-term investments | B79: Note 2 Acquisitions and Divestitures — major classes of assets and liabilities classified as held for sale. | K79: 0 | L79: 178
A80: Trade accounts receivable, less allowances | B80: Note 2 Acquisitions and Divestitures — major classes of assets and liabilities classified as held for sale. | K80: 0 | L80: 389
A81: Inventories | B81: Note 2 Acquisitions and Divestitures — major classes of assets and liabilities classified as held for sale. | K81: 23 | L81: 466
A82: Prepaid expenses and other current assets | B82: Note 2 Acquisitions and Divestitures — major classes of assets and liabilities classified as held for sale. | K82: 0 | L82: 147
A83: Equity method investments | B83: Note 2 Acquisitions and Divestitures — major classes of assets and liabilities classified as held for sale. | K83: 0 | L83: 5
A84: Deferred income tax assets | B84: Note 2 Acquisitions and Divestitures — major classes of assets and liabilities classified as held for sale. | K84: 0 | L84: 46
A85: Property, plant and equipment — net | B85: Note 2 Acquisitions and Divestitures — major classes of assets and liabilities classified as held for sale. | K85: 108 | L85: 1964
A86: Trademarks with indefinite lives | B86: Note 2 Acquisitions and Divestitures — major classes of assets and liabilities classified as held for sale. | K86: 0 | L86: 2
A87: Goodwill | B87: Note 2 Acquisitions and Divestitures — major classes of assets and liabilities classified as held for sale. | K87: 0 | L87: 3350
A88: Other noncurrent assets | B88: Note 2 Acquisitions and Divestitures — major classes of assets and liabilities classified as held for sale. | K88: 0 | L88: 60
A89: Allowance for reduction of assets held for sale | B89: Note 2 Acquisitions and Divestitures — major classes of assets and liabilities classified as held for sale. | K89: 0 | L89: -1265
A90: Assets held for sale | B90: Note 2 Acquisitions and Divestitures — major classes of assets and liabilities classified as held for sale. | K90: 131 | L90: 5342
... A98: Liabilities held for sale | B98: Note 2 Acquisitions and Divestitures — major classes of assets and liabilities classified as held for sale. | K98: 3 | L98: 2570
A102: =HYPERLINK("#'Note Schedules'!A104","Supplement: equity investment carrying values and differences") -> Supplement: equity investment carrying values and differences
A104: EQUITY METHOD INVESTMENTS — CARRYING VALUES AND FAIR-VALUE DIFFERENCES (FY2025 supplement) | B104: sources/companies/US/KO-coca-cola/artifacts/ten_k/KO-coca-cola/FY2025/psp_49eb40deba72424d91379bb74482f553/raw/source.html
A106: Monster Beverage Corporation — carrying value | L106: 5593
A107: Monster Beverage Corporation — fair value less carrying value | L107: =L27-L106 -> 10066
A108: Coca-Cola Europacific Partners plc — carrying value | L108: 3926
A109: Coca-Cola Europacific Partners plc — fair value less carrying value | L109: =L28-L108 -> 3237
A110: Coca-Cola FEMSA, S.A.B. de C.V. — carrying value | L110: 2236
A111: Coca-Cola FEMSA, S.A.B. de C.V. — fair value less carrying value | L111: =L29-L110 -> 3307
A112: Coca-Cola HBC AG — carrying value | L112: 1391
A113: Coca-Cola HBC AG — fair value less carrying value | L113: =L30-L112 -> 2660
A114: Coca-Cola Bottlers Japan Holdings Inc. — carrying value | L114: 459
A115: Coca-Cola Bottlers Japan Holdings Inc. — fair value less carrying value | L115: =L31-L114 -> 363
A116: Coca-Cola İ ç ecek A. Ş. — carrying value | L116: 288
A117: Coca-Cola İ ç ecek A. Ş. — fair value less carrying value | L117: =L32-L116 -> 482
A118: Embotelladora Andina S.A. — carrying value | L118: 106
A119: Embotelladora Andina S.A. — fair value less carrying value | L119: =L33-L118 -> 172
A123: Total quoted fair value | L123: =L27+L28+L29+L30+L31+L32+L33 -> 34286
A124: Total carrying value | L124: =L106+L108+L110+L112+L114+L116+L118 -> 13999
A125: Total fair value less carrying value | L125: =L107+L109+L111+L113+L115+L117+L119 -> 20287
...

Sheet Sources
A1: The Coca-Cola Company — Sources
A2: $ in millions except per-share data | USD | as of 2026-10-14
A4: Filing | B4: Accession | C4: Prepared Markdown (repository-relative) | D4: SHA-256 of prepared Markdown | E4: IS / BS / CF statement start lines
A5: 10K-FY2016 | B5: 0000021344-17-000009 | C5: sources/companies/US/KO-coca-cola/artifacts/ten_k/KO-coca-cola/FY2016/psp_0ed5b72f27fe4226b9b05bf29fe7e76c/prepared/document.md | D5: dd856b55749506be22a42092697ce960e3bb89f1644895528b4d89878acfa0b6 | E5: IS L2154 / BS L2210 / CF L2263
A6: 10K-FY2017 | B6: 0000021344-18-000008 | C6: sources/companies/US/KO-coca-cola/artifacts/ten_k/KO-coca-cola/FY2017/psp_64d67d2812744e7eb64a5759a5b0d2cc/prepared/document.md | D6: dc150bf678b61eeb1b1e9ddf1375ac80fc71dd85ed04cf22ab057adb4ea7fee8 | E6: IS L2196 / BS L2264 / CF L2319
A7: 10K-FY2018 | B7: 0000021344-19-000014 | C7: sources/companies/US/KO-coca-cola/artifacts/ten_k/KO-coca-cola/FY2018/psp_cd9dabfed2e24fdf9f06fd9f8d8cc6c7/prepared/document.md | D7: 584f3fa2e7adcc78e0f94495f59f9385ed8951036efa48435c6050f1efa063aa | E7: IS L2144 / BS L2212 / CF L2268
A8: 10K-FY2019 | B8: 0000021344-20-000006 | C8: sources/companies/US/KO-coca-cola/artifacts/ten_k/KO-coca-cola/FY2019/psp_405c783f553d43c9b2011bba81319d93/prepared/document.md | D8: a42953329137d2b4c2be953cd5bff7344db28ba5cbfcfb917a6ee95306f2d91e | E8: IS L1982 / BS L2039 / CF L2092
A9: 10K-FY2020 | B9: 0000021344-21-000008 | C9: sources/companies/US/KO-coca-cola/artifacts/ten_k/KO-coca-cola/FY2020/psp_b79ab798eb324e1d912ca3860d0fc698/prepared/document.md | D9: 3735da399257180897b06689ba0633b114bce949856078d78d796376d4e852f6 | E9: IS L1763 / BS L1820 / CF L1872
A10: 10K-FY2021 | B10: 0000021344-22-000009 | C10: sources/companies/US/KO-coca-cola/artifacts/ten_k/KO-coca-cola/FY2021/psp_4fff57be228c498ea65921f9a13be0aa/prepared/document.md | D10: a27f4441fd01ed474bb6fcefa3d01001cc9676979ae5b25ce77e27bdbd249667 | E10: IS L1677 / BS L1734 / CF L1786
A11: 10K-FY2022 | B11: 0000021344-23-000011 | C11: sources/companies/US/KO-coca-cola/artifacts/ten_k/KO-coca-cola/FY2022/psp_6bf10915d7ef409c929d7a30212965c0/prepared/document.md | D11: 56895f3b80b4aed74aeb05817034df0cdea44c2a3917712011b54f6050a12dce | E11: IS L1670 / BS L1727 / CF L1779
A12: 10K-FY2023 | B12: 0000021344-24-000009 | C12: sources/companies/US/KO-coca-cola/artifacts/ten_k/KO-coca-cola/FY2023/psp_db84d64043d94eb59996e93ad7e18711/prepared/document.md | D12: 20fcd94c8a0f645efcbe6e8290bd5d21de4c34ecf2ac8b8a31d1ec324f56116d | E12: IS L1676 / BS L1733 / CF L1785
A13: 10K-FY2024 | B13: 0000021344-25-000011 | C13: sources/companies/US/KO-coca-cola/artifacts/ten_k/KO-coca-cola/FY2024/psp_96ebc5b07f714c29808ae5a23d0ea839/prepared/document.md | D13: ac683e64461625a79275d07c966cb632c987af4bfe9968b08888eb9e3aed66a9 | E13: IS L1661 / BS L1718 / CF L1768
A14: 10K-FY2025 | B14: 0001628280-26-010047 | C14: sources/companies/US/KO-coca-cola/artifacts/ten_k/KO-coca-cola/FY2025/psp_49eb40deba72424d91379bb74482f553/prepared/document.md | D14: a01e1f2db6cfb973bc23ce22ceaa07cbdb26f4e71e70807ee9de161836c77a97 | E14: IS L1613 / BS L1670 / CF L1722
A15: 10Q-Q3/FY2024 | B15: 0000021344-24-000060 | C15: sources/companies/US/KO-coca-cola/artifacts/ten_k/KO-coca-cola-10Q-Q3/FY2024/psp_b0f46569dc0a4627b57065521111d109/prepared/document.md | D15: bcf42679a3ea84a3b4769cadeefc9147633f93e8cf6d25d83c5aa848b1b7bbc0 | E15: IS L118 / BS L177 / CF L229
... A20: 10Q-Q2/FY2026 | B20: 0001628280-26-050503 | C20: sources/companies/US/KO-coca-cola/artifacts/ten_k/KO-coca-cola-10Q-Q2/FY2026/psp_97ecfba950d14cbea07200e07838e85b/prepared/document.md | D20: 22efdfea6165f42b095082d18c4b7cca4c226c6ba5142877afad62c6b77c3085 | E20: IS L118 / BS L177 / CF L229
A22: Annual column provenance (which 10-K supplies each fiscal-year column)
A23: Column | B23: IS and CF source | C23: BS source | D23: Segments source | E23: Geography source
A24: FY2016 | B24: FY2018 10-K | C24: FY2017 10-K | D24: A: FY2018 10-K | E24: FY2018 10-K
A25: FY2017 | B25: FY2019 10-K | C25: FY2018 10-K | D25: A: FY2018 10-K; B: FY2019 10-K | E25: FY2019 10-K
A26: FY2018 | B26: FY2020 10-K | C26: FY2019 10-K | D26: A: FY2018 10-K; B: FY2020 10-K | E26: FY2020 10-K
A27: FY2019 | B27: FY2021 10-K | C27: FY2020 10-K | D27: B: FY2021 10-K | E27: FY2021 10-K
A28: FY2020 | B28: FY2022 10-K | C28: FY2021 10-K | D28: B: FY2022 10-K | E28: FY2022 10-K
A29: FY2021 | B29: FY2023 10-K | C29: FY2022 10-K | D29: B: FY2023 10-K | E29: FY2023 10-K
A30: FY2022 | B30: FY2024 10-K | C30: FY2023 10-K | D30: B: FY2024 10-K | E30: FY2024 10-K
A31: FY2023 | B31: FY2025 10-K | C31: FY2024 10-K | D31: B: FY2024 10-K; C: FY2025 10-K | E31: FY2025 10-K
A32: FY2024 | B32: FY2025 10-K | C32: FY2025 10-K | D32: B: FY2024 10-K; C: FY2025 10-K | E32: FY2025 10-K
A33: FY2025 | B33: FY2025 10-K | C33: FY2025 10-K | D33: C: FY2025 10-K | E33: FY2025 10-K
A35: Quarterly column provenance
A36: 3Q2024 | B36: 10Q-Q3/FY2024 | C36: period end 2024-09-27
A37: 1Q2025 | B37: 10Q-Q1/FY2025 | C37: period end 2025-03-28
A38: 2Q2025 | B38: 10Q-Q2/FY2025 | C38: period end 2025-06-27
A39: 3Q2025 | B39: 10Q-Q3/FY2025 | C39: period end 2025-09-26
A40: 1Q2026 | B40: 10Q-Q1/FY2026 | C40: period end 2026-04-03
A41: 2Q2026 | B41: 10Q-Q2/FY2026 | C41: period end 2026-07-03
A43: Restatement log: first-filed value vs value used in the workbook (differences only)
A44: Column | B44: Line | C44: As first filed | D44: Used in workbook | E44: First-filed / used filing
A45: FY2016 | B45: Operating income | C45: 8626 | D45: 8657 | E45: 10K-FY2016 -> 10K-FY2018
A46: FY2017 | B46: Net operating revenues | C46: 35410 | D46: 36212 | E46: 10K-FY2017 -> 10K-FY2019
A47: FY2017 | B47: Operating income | C47: 7501 | D47: 7755 | E47: 10K-FY2017 -> 10K-FY2019
A48: FY2018 | B48: Net operating revenues | C48: 31856 | D48: 34300 | E48: 10K-FY2018 -> 10K-FY2020
A49: FY2018 | B49: Operating income | C49: 8700 | D49: 9152 | E49: 10K-FY2018 -> 10K-FY2020
A50: FY2016 | B50: Net cash provided by operating activities | C50: 8796 | D50: 8792 | E50: 10K-FY2016 -> 10K-FY2018
A51: FY2017 | B51: Net cash provided by operating activities | C51: 6995 | D51: 7041 | E51: 10K-FY2017 -> 10K-FY2019
A52: FY2018 | B52: Net cash provided by operating activities | C52: 7320 | D52: 7627 | E52: 10K-FY2018 -> 10K-FY2020
A54: Parsing notes
B55: Statements were parsed from the prepared Markdown produced by the bundled ResearchFoundry SEC-HTML flow (research package S001-S016). Numbers are copied, not re-keyed. Totals are stored as reported and verified by the check rows.
A57: Quarterly detail provenance (10-Q) | B57: Source path (repository-relative) | C57: Scope / method | D57: Quarterly columns | E57: Notes
A58: Segments | B58: sources/companies/US/KO-coca-cola/artifacts/ten_k/KO-coca-cola-10Q-Q3/FY2024/psp_b0f46569dc0a4627b57065521111d109/prepared/document.md | C58: Note 17; Q3 2024 as filed. D&A and capex are not disclosed in this 10-Q. | D58: 3Q2024 | E58: Basis B / Global Ventures presentation
A59: Segments | B59: sources/companies/US/KO-coca-cola/artifacts/ten_k/KO-coca-cola-10Q-Q1/FY2025/psp_c15006a1bc8448fe86ec22586b3298f9/prepared/document.md | C59: Note 17; three-month rows as filed. | D59: 1Q2025 | E59: Basis C / recast presentation
A60: Segments | B60: sources/companies/US/KO-coca-cola/artifacts/ten_k/KO-coca-cola-10Q-Q2/FY2025/psp_cc43d923d87f4db78f1374bdb216dc8a/prepared/document.md | C60: Note 17; three-month rows as filed. | D60: 2Q2025 | E60: Basis C / recast presentation
A61: Segments | B61: sources/companies/US/KO-coca-cola/artifacts/ten_k/KO-coca-cola-10Q-Q3/FY2025/psp_f597d41b18c94f9188267b47ac69f2c8/prepared/document.md | C61: Note 17; three-month rows as filed. | D61: 3Q2025 | E61: Basis C / recast presentation
A62: Segments | B62: sources/companies/US/KO-coca-cola/artifacts/ten_k/KO-coca-cola-10Q-Q1/FY2026/psp_61215a140e4d47a4b2bf9438434839bb/prepared/document.md | C62: Note 16; three-month rows as filed. | D62: 1Q2026 | E62: Basis C
A63: Segments | B63: sources/companies/US/KO-coca-cola/artifacts/ten_k/KO-coca-cola-10Q-Q2/FY2026/psp_97ecfba950d14cbea07200e07838e85b/prepared/document.md | C63: Note 16; six-month rows less 1Q2026 Note 16 to derive Q2 discrete. | D63: 2Q2026 | E63: Derived single-quarter values; check rows tie to IS
A64: Geography / line of business | B64: 10-Q Note 3 | C64: United States / International × concentrate / finished product; first three-month table used. | D64: 3Q2024–2Q2026 | E64: Quarterly PP&E by geography is not disclosed in the 10-Qs; annual PP&E rows remain annual-only
A65: Operating Metrics | B65: 10-Q MD&A, Beverage Volume / Net Operating Revenues | C65: Volume growth and revenue factor tables; first three-month table used. | D65: 3Q2024–2Q2026 | E65: Unit case absolute volume is not disclosed quarterly; growth rates are reported as filed
A67: Review 2026-10-14 | B67: Raw SEC HTML exact-caption / exact-period checks; 10 annual filings and six interim filings. Superscript / raised-position footnotes excluded before numeric extraction.
A68: Audit evidence | B68: data/derived/companies/US/KO-coca-cola/workbook-audit-20261014/source-cell-audit.json
A69: Formula evaluation | B69: Independent arithmetic evaluation and Excel full rebuild/recalculation; formula results checked against disclosed source inputs and existing tie-outs.
A70: Source-basis caution | B70: Growth from rounded unit-case totals differs from reported comparable growth; quarterly CF is cumulative; quarterly net-debt/EBITDA uses discrete-quarter EBITDA without annualization.

Sheet Audit 2026-10-14
A1: KO workbook review — 2026-10-14
A2: Coverage | B2: FY2016-FY2025; 3Q2024, 1Q/2Q/3Q2025, 1Q/2Q2026
A3: Method | B3: SEC original HTML; caption and period-column matching; superscripts removed
A4: Source-cell checks | B4: 3565
A5: Unresolved source matches | B5: 0
A6: Data cells revised or completed | B6: 131
A7: Formula verification | B7: All numeric formulas evaluated; no errors or off-tolerance tie-outs. See formula-audit.json.
A8: Preservation | B8: Original workbook retained. All original numeric formulas and unrelated worksheet data preserved.
A9: Interpretation | B9: N/A = explicitly not applicable. Blank = undisclosed / out of scope. Dash zero = explicitly disclosed zero.
A10: Workbook source | B10: research/companies/US/KO-coca-cola/outputs/company-research-to-excel-20261013/KO_model.xlsx
A11: Audit evidence | B11: data/derived/companies/US/KO-coca-cola/workbook-audit-20261014/source-cell-audit.json
A13: Sheet | B13: Source checks | C13: Data changes
A14: Income Statement | B14: 326 | C14: 3
A15: Balance Sheet | B15: 546 | C15: 2
A16: Cash Flow | B16: 534 | C16: 14
A17: Operating Metrics | B17: 833 | C17: 81
A18: Note Schedules | B18: 330 | C18: 31
A19: Segments | B19: 918 | C19: 0
A20: Geography | B20: 78 | C20: 0
A22: Sheet | B22: Cell | C22: Period | D22: Metric | E22: Before | F22: After | G22: Filing | H22: Original source URL | I22: Workspace-relative source | J22: Reason
A23: Income Statement | B23: C29 | C23: FY2016 | D23: Income (loss) from discontinued operations, net of income taxes | E23: (blank) | F23: 0 | G23: 10K-FY2018 | H23: https://www.sec.gov/Archives/edgar/data/21344/000002134419000014/ | I23: sources/companies/US/KO-coca-cola/artifacts/ten_k/KO-coca-cola/FY2018/psp_cd9dabfed2e24fdf9f06fd9f8d8cc6c7/raw/source.html | J23: SEC HTML statement, exact caption and period column
A24: Income Statement | B24: C37 | C24: FY2016 | D24: Basic net income (loss) per share from discontinued operations | E24: (blank) | F24: 0 | G24: 10K-FY2018 | H24: https://www.sec.gov/Archives/edgar/data/21344/000002134419000014/ | I24: sources/companies/US/KO-coca-cola/artifacts/ten_k/KO-coca-cola/FY2018/psp_cd9dabfed2e24fdf9f06fd9f8d8cc6c7/raw/source.html | J24: SEC HTML statement, exact caption and period column
A25: Income Statement | B25: C41 | C25: FY2016 | D25: Diluted net income (loss) per share from discontinued operations | E25: (blank) | F25: 0 | G25: 10K-FY2018 | H25: https://www.sec.gov/Archives/edgar/data/21344/000002134419000014/ | I25: sources/companies/US/KO-coca-cola/artifacts/ten_k/KO-coca-cola/FY2018/psp_cd9dabfed2e24fdf9f06fd9f8d8cc6c7/raw/source.html | J25: SEC HTML statement, exact caption and period column
A26: Balance Sheet | B26: C22 | C26: FY2016 | D26: Assets held for sale — discontinued operations | E26: (blank) | F26: 0 | G26: 10K-FY2017 | H26: https://www.sec.gov/Archives/edgar/data/21344/000002134418000008/ | I26: sources/companies/US/KO-coca-cola/artifacts/ten_k/KO-coca-cola/FY2017/psp_64d67d2812744e7eb64a5759a5b0d2cc/raw/source.html | J26: SEC HTML statement, exact caption and period column
A27: Balance Sheet | B27: C41 | C27: FY2016 | D27: Liabilities held for sale — discontinued operations | E27: (blank) | F27: 0 | G27: 10K-FY2017 | H27: https://www.sec.gov/Archives/edgar/data/21344/000002134418000008/ | I27: sources/companies/US/KO-coca-cola/artifacts/ten_k/KO-coca-cola/FY2017/psp_64d67d2812744e7eb64a5759a5b0d2cc/raw/source.html | J27: SEC HTML statement, exact caption and period column
A28: Cash Flow | B28: C14 | C28: FY2016 | D28: (Income) loss from discontinued operations | E28: (blank) | F28: 0 | G28: 10K-FY2018 | H28: https://www.sec.gov/Archives/edgar/data/21344/000002134419000014/ | I28: sources/companies/US/KO-coca-cola/artifacts/ten_k/KO-coca-cola/FY2018/psp_cd9dabfed2e24fdf9f06fd9f8d8cc6c7/raw/source.html | J28: SEC HTML statement, exact caption and period column
A29: Cash Flow | B29: C47 | C29: FY2016 | D29: Net cash from operating activities - discontinued operations | E29: (blank) | F29: 0 | G29: 10K-FY2018 | H29: https://www.sec.gov/Archives/edgar/data/21344/000002134419000014/ | I29: sources/companies/US/KO-coca-cola/artifacts/ten_k/KO-coca-cola/FY2018/psp_cd9dabfed2e24fdf9f06fd9f8d8cc6c7/raw/source.html | J29: SEC HTML statement, exact caption and period column
A30: Cash Flow | B30: C48 | C30: FY2016 | D30: Net cash from investing activities - discontinued operations | E30: (blank) | F30: 0 | G30: 10K-FY2018 | H30: https://www.sec.gov/Archives/edgar/data/21344/000002134419000014/ | I30: sources/companies/US/KO-coca-cola/artifacts/ten_k/KO-coca-cola/FY2018/psp_cd9dabfed2e24fdf9f06fd9f8d8cc6c7/raw/source.html | J30: SEC HTML statement, exact caption and period column
A31: Cash Flow | B31: C49 | C31: FY2016 | D31: Net cash from financing activities - discontinued operations | E31: (blank) | F31: 0 | G31: 10K-FY2018 | H31: https://www.sec.gov/Archives/edgar/data/21344/000002134419000014/ | I31: sources/companies/US/KO-coca-cola/artifacts/ten_k/KO-coca-cola/FY2018/psp_cd9dabfed2e24fdf9f06fd9f8d8cc6c7/raw/source.html | J31: SEC HTML statement, exact caption and period column
A32: Cash Flow | B32: C50 | C32: FY2016 | D32: Net cash provided by (used in) discontinued operations | E32: (blank) | F32: 0 | G32: 10K-FY2018 | H32: https://www.sec.gov/Archives/edgar/data/21344/000002134419000014/ | I32: sources/companies/US/KO-coca-cola/artifacts/ten_k/KO-coca-cola/FY2018/psp_cd9dabfed2e24fdf9f06fd9f8d8cc6c7/raw/source.html | J32: SEC HTML statement, exact caption and period column
A33: Cash Flow | B33: G34 | C33: FY2020 | D33: Collateral (paid) received associated with hedging activities — net | E33: (blank) | F33: 0 | G33: 10K-FY2022 | H33: https://www.sec.gov/Archives/edgar/data/21344/000002134423000011/ | I33: sources/companies/US/KO-coca-cola/artifacts/ten_k/KO-coca-cola/FY2022/psp_6bf10915d7ef409c929d7a30212965c0/raw/source.html | J33: SEC HTML statement, exact caption and period column
... A153: Note Schedules | B153: L125 | C153: FY2025 | D153: Total fair value less carrying value | E153: (blank) | F153: =L107+L109+L111+L113+L115+L117+L119 | G153: 10K-FY2025 | H153: https://www.sec.gov/Archives/edgar/data/21344/000162828026010047/ | I153: sources/companies/US/KO-coca-cola/artifacts/ten_k/KO-coca-cola/FY2025/psp_49eb40deba72424d91379bb74482f553/raw/source.html | J153: Restore total from the same disclosure, linked to components

Sheet Valuation Driver Build
A1: 可口可乐：DCF参数推导
A2: 研究日：2026-10-16。金额为百万美元，比例为百分比。
A3: 黄色蓝字＝预测建议；绿色＝原底稿链接；“待定”＝缺少必要输入。
A4: 参数已完成；估值、日期回报及敏感性见Valuation。
A5: 情景控制移至Valuation!C7；本表C43只读链接，所有经营预测及现金股数桥随其切换。
A7: 一、2026年基期：实际、指引与剩余季度
A8: 指标 | B8: 单位 | C8: 2026Q1A | D8: 2026Q2A | E8: 2026Q3E | F8: 2026Q4E | G8: 2026H1A | H8: FY2026E | J8: FY2021 | K8: FY2022 | L8: FY2023 | M8: FY2024 | N8: FY2025 | P8: 2024Q3A | Q8: 2024Q4A | R8: 2025Q1A | S8: 2025Q2A | T8: 2025Q3A | U8: 2025Q4A | V8: 2026Q1A | W8: 2026Q2A | Y8: 判断依据 / 待讨论事项
A10: 报告收入（GAAP） | B10: 百万美元 | C10: ='Income Statement'!T11 -> 12472 | D10: ='Income Statement'!U11 -> 13380 | E10: 待GAAP桥 | F10: 待GAAP桥 | G10: =SUM(C10:D10) -> 25852 | H10: 待GAAP桥 | J10: ='Income Statement'!H11 -> 38655 | K10: ='Income Statement'!I11 -> 43004 | L10: ='Income Statement'!J11 -> 45754 | M10: ='Income Statement'!K11 -> 47061 | N10: ='Income Statement'!L11 -> 47941 | P10: ='Income Statement'!P11 -> 11854 | Q10: =$E$204 -> 11544 | R10: ='Income Statement'!Q11 -> 11129 | S10: ='Income Statement'!R11 -> 12535 | T10: ='Income Statement'!S11 -> 12455 | U10: ='Income Statement'!L11-SUM('Income Statement'!Q11:S11) -> 11822 | V10: ='Income Statement'!T11 -> 12472 | W10: ='Income Statement'!U11 -> 13380
A11: 报告收入同比 | B11: % | C11: =C10/R10-1 -> 0.12067571 | D11: =D10/S10-1 -> 0.067411249 | E11: 待GAAP桥 | F11: 待GAAP桥 | G11: =G10/SUM(R10:S10)-1 -> 0.092461122 | H11: 待GAAP桥 | J11: ='Income Statement'!H11/'Income Statement'!G11-1 -> 0.1708669 | K11: ='Income Statement'!I11/'Income Statement'!H11-1 -> 0.11250808 | L11: ='Income Statement'!J11/'Income Statement'!I11-1 -> 0.06394754 | M11: ='Income Statement'!K11/'Income Statement'!J11-1 -> 0.028565808 | N11: ='Income Statement'!L11/'Income Statement'!K11-1 -> 0.018699135 | P11: =P10/$C$264-1 -> -0.0082824396 | Q11: =Q10/$C$265-1 -> 0.064061204 | R11: =R10/$C$266-1 -> -0.015132743 | S11: =S10/$C$267-1 -> 0.013912481 | T11: =T10/P10-1 -> 0.050700186 | U11: =U10/Q10-1 -> 0.024081774 | V11: =V10/R10-1 -> 0.12067571 | W11: =W10/S10-1 -> 0.067411249
A12: 公司可比收入 | B12: 百万美元 | C12: =$C$209 -> 12471 | D12: =$C$210 -> 13373 | E12: =T12*(1+E17) -> 12908.48 | F12: =H12-SUM(C12:E12) -> 10991.69 | G12: =SUM(C12:D12) -> 25844 | H12: =N12*(1+H17) -> 49744.17 | J12: =$C$565 -> 38658 | K12: =$C$566 -> 43046 | L12: =$C$200 -> 45784 | M12: =$C$201 -> 46897 | N12: =$C$202 -> 48062 | P12: =$C$203 -> 11949 | Q12: =$C$204 -> 11404 | R12: =$C$205 -> 11216 | S12: =$C$206 -> 12617 | T12: =$C$207 -> 12412 | U12: =$C$208 -> 11817 | V12: =$C$209 -> 12471 | W12: =$C$210 -> 13373
A13: 可比收入同比 | B13: % | C13: =C12/R12-1 -> 0.11189372 | D13: =D12/S12-1 -> 0.059919157 | E13: =E12/T12-1 -> 0.04 | F13: =F12/U12-1 -> -0.069840907 | G13: =G12/SUM(R12:S12)-1 -> 0.084378803 | H13: =H12/N12-1 -> 0.035 | J13: n.a. | K13: =K12/J12-1 -> 0.1135082 | L13: =L12/K12-1 -> 0.063606375 | M13: =IF(COUNT(M12,L12)=2,M12/L12-1,"未补充") -> 0.024309803 | N13: =IF(COUNT(N12,M12)=2,N12/M12-1,"未补充") -> 0.024841674 | P13: =P12/$D$264-1 -> 0.0031903283 | Q13: =Q12/$D$265-1 -> 0.041651443 | R13: =R12/$D$266-1 -> -0.001335589 | S13: =S12/$D$267-1 -> 0.024689353 | T13: =T12/P12-1 -> 0.038748012 | U13: =U12/Q12-1 -> 0.036215363 | V13: =V12/R12-1 -> 0.11189372 | W13: =W12/S12-1 -> 0.059919157
A14: 有机收入增长 | B14: % | C14: 0.1 | D14: 0.06 | E14: =IF(ISNUMBER('Valuation Inputs'!C89),'Valuation Inputs'!C89,"待定") -> 0.04 | F14: 待拆解 | G14: 0.08 | H14: =E223 -> 0.05 | J14: =$F$565 -> 0.16 | K14: =$F$566 -> 0.16 | L14: =$F$567 -> 0.12 | M14: 0.12 | N14: 0.05 | P14: 0.09 | Q14: 0.14 | R14: 0.06 | S14: 0.05 | T14: 0.06 | U14: 0.05 | V14: 0.1 | W14: 0.06 | Y14: 完整指引先约束全年，季度需核验销量与价格／组合。
A15: 汇率收入贡献（见口径说明） | B15: 百分点 | C15: =C316 -> 0.02 | D15: =D316 -> 0.01 | E15: =E230 -> 0.01 | F15: 待拆解 | G15: 0.02 | H15: =E224 -> 0.01 | J15: ='Operating Metrics'!H53 -> 0.01 | K15: ='Operating Metrics'!I53 -> -0.07 | L15: ='Operating Metrics'!J53 -> -0.04 | M15: ='Operating Metrics'!K53 -> -0.05 | N15: ='Operating Metrics'!L53 -> -0.02 | P15: ='Operating Metrics'!P53 -> -0.05 | Q15: 未补充 | R15: ='Operating Metrics'!Q53 -> -0.05 | S15: ='Operating Metrics'!R53 -> -0.03 | T15: ='Operating Metrics'!S53 -> 0 | U15: 未补充 | V15: =C316 -> 0.02 | W15: =D316 -> 0.01 | Y15: 2026实际/预测采用可比口径；较早年度历史仍为原底稿GAAP贡献，勿直接混比。
A16: 收购与处置贡献 | B16: 百分点 | C16: ='Operating Metrics'!T62 -> -0.01 | D16: ='Operating Metrics'!U62 -> -0.01 | E16: =E231 -> -0.01 | F16: 待拆解 | G16: -0.01 | H16: =E225 -> -0.025 | J16: ='Operating Metrics'!H62 -> 0 | K16: ='Operating Metrics'!I62 -> 0.02 | L16: ='Operating Metrics'!J62 -> -0.01 | M16: ='Operating Metrics'!K62 -> -0.04 | N16: ='Operating Metrics'!L62 -> -0.01 | P16: ='Operating Metrics'!P62 -> -0.04 | Q16: 未补充 | R16: ='Operating Metrics'!Q62 -> -0.03 | S16: ='Operating Metrics'!R62 -> 0 | T16: ='Operating Metrics'!S62 -> 0 | U16: 未补充 | V16: ='Operating Metrics'!T62 -> -0.01 | W16: ='Operating Metrics'!U62 -> -0.01
A17: 归因合计（舍入近似） | B17: % | C17: =SUM(C14:C16) -> 0.11 | D17: =SUM(D14:D16) -> 0.06 | E17: =SUM(E14:E16) -> 0.04 | F17: n.a. | H17: =SUM(H14:H16) -> 0.035
A18: 公司可比营业利润率 | B18: % | C18: =C19/C12 -> 0.34479994 | D18: =D19/D12 -> 0.35579152 | E18: =E301 -> 0.32696596 | F18: =F301 -> 0.26187465 | G18: =G19/G12 -> 0.35048754 | H18: =H19/H12 -> 0.32480346 | J18: =J19/J12 -> 0.28736613 | K18: =K19/K12 -> 0.28678623 | L18: =IF(COUNT(L19,L12)=2,L19/L12,"未补充") -> 0.2912808 | M18: =IF(COUNT(M19,M12)=2,M19/M12,"未补充") -> 0.30033904 | N18: =IF(COUNT(N19,N12)=2,N19/N12,"未补充") -> 0.31236736 | P18: =IF(COUNT(P19,P12)=2,P19/P12,"未补充") -> 0.30722236 | Q18: =IF(COUNT(Q19,Q12)=2,Q19/Q12,"未补充") -> 0.23974044 | R18: =IF(COUNT(R19,R12)=2,R19/R12,"未补充") -> 0.33764265 | S18: =IF(COUNT(S19,S12)=2,S19/S12,"未补充") -> 0.34722993 | T18: =IF(COUNT(T19,T12)=2,T19/T12,"未补充") -> 0.31880438 | U18: =IF(COUNT(U19,U12)=2,U19/U12,"未补充") -> 0.24439367 | V18: =IF(COUNT(V19,V12)=2,V19/V12,"未补充") -> 0.34479994 | W18: =IF(COUNT(W19,W12)=2,W19/W12,"未补充") -> 0.35579152 | Y18: 按2026-10-16确认的利润桥计算，约32.7%/26.2%；不是公司利润率指引。
A19: 公司可比营业利润 | B19: 百万美元 | C19: =$D$209 -> 4300 | D19: =$D$210 -> 4758 | E19: =E300 -> 4220.6336 | F19: =F300 -> 2878.4449 | G19: =SUM(C19:D19) -> 9058 | H19: =SUM(C19:F19) -> 16157.079 | J19: =$D$565 -> 11109 | K19: =$D$566 -> 12345 | L19: =$D$200 -> 13336 | M19: =$D$201 -> 14085 | N19: =$D$202 -> 15013 | P19: =$D$203 -> 3671 | Q19: =$D$204 -> 2734 | R19: =$D$205 -> 3787 | S19: =$D$206 -> 4381 | T19: =$D$207 -> 3957 | U19: =$D$208 -> 2888 | V19: =$D$209 -> 4300 | W19: =$D$210 -> 4758
A20: 可比营业利润同比 | B20: % | C20: =C19/R19-1 -> 0.13546343 | D20: =D19/S19-1 -> 0.086053412 | E20: =E19/T19-1 -> 0.066624615 | F20: =F19/U19-1 -> -0.0033085427 | G20: =G19/SUM(R19:S19)-1 -> 0.1089618 | H20: =H19/N19-1 -> 0.076205857 | K20: =IF(COUNT(K19,J19)=2,K19/J19-1,"未补充") -> 0.11126114 | L20: =IF(COUNT(L19,K19)=2,L19/K19-1,"未补充") -> 0.080275415 | M20: =IF(COUNT(M19,L19)=2,M19/L19-1,"未补充") -> 0.056163767 | N20: =IF(COUNT(N19,M19)=2,N19/M19-1,"未补充") -> 0.065885694 | P20: =P19/$F$264-1 -> 0.038178733 | Q20: =Q19/$F$265-1 -> 0.079778831 | R20: =R19/$F$266-1 -> 0.039527862 | S20: =S19/$F$267-1 -> 0.085211791 | T20: =T19/P19-1 -> 0.077907927 | U20: =U19/Q19-1 -> 0.056327725 | V20: =V19/R19-1 -> 0.13546343 | W20: =W19/S19-1 -> 0.086053412
A21: 报告营业利润（GAAP） | B21: 百万美元 | C21: ='Income Statement'!T18 -> 4359 | D21: ='Income Statement'!U18 -> 4672 | E21: 待GAAP桥 | F21: 待GAAP桥 | G21: =SUM(C21:D21) -> 9031 | H21: 待GAAP桥 | J21: ='Income Statement'!H18 -> 10308 | K21: ='Income Statement'!I18 -> 10909 | L21: ='Income Statement'!J18 -> 11311 | M21: ='Income Statement'!K18 -> 9992 | N21: ='Income Statement'!L18 -> 13762 | P21: ='Income Statement'!P18 -> 2510 | Q21: =$F$204 -> 2709 | R21: ='Income Statement'!Q18 -> 3659 | S21: ='Income Statement'!R18 -> 4280 | T21: ='Income Statement'!S18 -> 3982 | U21: ='Income Statement'!L18-SUM('Income Statement'!Q18:S18) -> 1841 | V21: ='Income Statement'!T18 -> 4359 | W21: ='Income Statement'!U18 -> 4672
A22: 报告营业利润率 | B22: % | C22: =C21/C10 -> 0.34950289 | D22: =D21/D10 -> 0.34917788 | E22: 待GAAP桥 | F22: 待GAAP桥 | G22: =G21/G10 -> 0.34933467 | H22: 待GAAP桥 | J22: =IF(COUNT(J21,J10)=2,J21/J10,"未补充") -> 0.26666667 | K22: =IF(COUNT(K21,K10)=2,K21/K10,"未补充") -> 0.25367408 | L22: =IF(COUNT(L21,L10)=2,L21/L10,"未补充") -> 0.24721336 | M22: =IF(COUNT(M21,M10)=2,M21/M10,"未补充") -> 0.21232018 | N22: =IF(COUNT(N21,N10)=2,N21/N10,"未补充") -> 0.28706118 | P22: =IF(COUNT(P21,P10)=2,P21/P10,"未补充") -> 0.21174287 | Q22: =IF(COUNT(Q21,Q10)=2,Q21/Q10,"未补充") -> 0.23466736 | R22: =IF(COUNT(R21,R10)=2,R21/R10,"未补充") -> 0.32878066 | S22: =IF(COUNT(S21,S10)=2,S21/S10,"未补充") -> 0.34144396 | T22: =IF(COUNT(T21,T10)=2,T21/T10,"未补充") -> 0.31971096 | U22: =IF(COUNT(U21,U10)=2,U21/U10,"未补充") -> 0.15572661 | V22: =IF(COUNT(V21,V10)=2,V21/V10,"未补充") -> 0.34950289 | W22: =IF(COUNT(W21,W10)=2,W21/W10,"未补充") -> 0.34917788
A23: 公司可比调整净额 | B23: 百万美元 | C23: =C19-C21 -> -59 | D23: =D19-D21 -> 86 | E23: 待GAAP桥 | F23: 待GAAP桥 | G23: =SUM(C23:D23) -> 27 | H23: 待GAAP桥 | J23: =IF(COUNT(J19,J21)=2,J19-J21,"未补充") -> 801 | K23: =IF(COUNT(K19,K21)=2,K19-K21,"未补充") -> 1436 | L23: =IF(COUNT(L19,L21)=2,L19-L21,"未补充") -> 2025 | M23: =IF(COUNT(M19,M21)=2,M19-M21,"未补充") -> 4093 | N23: =IF(COUNT(N19,N21)=2,N19-N21,"未补充") -> 1251 | P23: =IF(COUNT(P19,P21)=2,P19-P21,"未补充") -> 1161 | Q23: =IF(COUNT(Q19,Q21)=2,Q19-Q21,"未补充") -> 25 | R23: =IF(COUNT(R19,R21)=2,R19-R21,"未补充") -> 128 | S23: =IF(COUNT(S19,S21)=2,S19-S21,"未补充") -> 101 | T23: =IF(COUNT(T19,T21)=2,T19-T21,"未补充") -> -25 | U23: =IF(COUNT(U19,U21)=2,U19-U21,"未补充") -> 1047 | V23: =IF(COUNT(V19,V21)=2,V19-V21,"未补充") -> -59 | W23: =IF(COUNT(W19,W21)=2,W19-W21,"未补充") -> 86
A24: 减：分析师保留的经常成本 | B24: 百万美元 | H24: =IF(ISNUMBER('Valuation Inputs'!C101),'Valuation Inputs'!C101,"待定") -> 100 | Y24: 建议全年保留100，待逐项审议；不等于公司调整均合理。
A25: 分析师正常化营业利润 | B25: 百万美元 | H25: =H19-H24 -> 16057.079 | Y25: 计算建议，税负与全部调整项目尚待讨论。
A27: 折旧摊销 | B27: 百万美元 | C27: ='Cash Flow'!T17 -> 264 | D27: =('Cash Flow'!U17-'Cash Flow'!T17) -> 266 | E27: =(H27-SUM(C27:D27))*T27/(T27+U27) -> 303.09524 | F27: =H27-SUM(C27:E27) -> 266.90476 | G27: =SUM(C27:D27) -> 530 | H27: =IF(ISNUMBER('Valuation Inputs'!C102),'Valuation Inputs'!C102,"待定") -> 1100 | J27: ='Cash Flow'!H17 -> 1452 | K27: ='Cash Flow'!I17 -> 1260 | L27: ='Cash Flow'!J17 -> 1128 | M27: ='Cash Flow'!K17 -> 1075 | N27: ='Cash Flow'!L17 -> 1050 | P27: ='Cash Flow'!P17-$C$218 -> 268 | Q27: =('Cash Flow'!K17-'Cash Flow'!P17) -> 276 | R27: ='Cash Flow'!Q17 -> 267 | S27: =('Cash Flow'!R17-'Cash Flow'!Q17) -> 279 | T27: =('Cash Flow'!S17-'Cash Flow'!R17) -> 268 | U27: =('Cash Flow'!L17-'Cash Flow'!S17) -> 236 | V27: ='Cash Flow'!T17 -> 264 | W27: =('Cash Flow'!U17-'Cash Flow'!T17) -> 266
A28: 资本开支 | B28: 百万美元 | C28: =-'Cash Flow'!T32 -> 266 | D28: =-('Cash Flow'!U32-'Cash Flow'!T32) -> 418 | E28: =(H28-SUM(C28:D28))*T28/(T28+U28) -> 533.5518 | F28: =H28-SUM(C28:E28) -> 982.4482 | G28: =SUM(C28:D28) -> 684 | H28: =E227 -> 2200 | J28: =-'Cash Flow'!H32 -> 1367 | K28: =-'Cash Flow'!I32 -> 1484 | L28: =-'Cash Flow'!J32 -> 1852 | M28: =-'Cash Flow'!K32 -> 2064 | N28: =-'Cash Flow'!L32 -> 2112 | P28: =-'Cash Flow'!P32-$C$217 -> 469 | Q28: =-('Cash Flow'!K32-'Cash Flow'!P32) -> 803 | R28: =-'Cash Flow'!Q32 -> 309 | S28: =-('Cash Flow'!R32-'Cash Flow'!Q32) -> 442 | T28: =-('Cash Flow'!S32-'Cash Flow'!R32) -> 479 | U28: =-('Cash Flow'!L32-'Cash Flow'!S32) -> 882 | V28: =-'Cash Flow'!T32 -> 266 | W28: =-('Cash Flow'!U32-'Cash Flow'!T32) -> 418
A29: 经营现金流（报告／指引） | B29: 百万美元 | C29: ='Cash Flow'!T26 -> 2021 | D29: =('Cash Flow'!U26-'Cash Flow'!T26) -> 5522 | E29: 待分配 | F29: 待分配 | G29: =SUM(C29:D29) -> 7543 | H29: =E226 -> 14600 | J29: ='Cash Flow'!H26 -> 12625 | K29: ='Cash Flow'!I26 -> 11018 | L29: ='Cash Flow'!J26 -> 11599 | M29: ='Cash Flow'!K26 -> 6805 | N29: ='Cash Flow'!L26 -> 7408 | P29: ='Cash Flow'!P26-$C$216 -> -1259 | Q29: =('Cash Flow'!K26-'Cash Flow'!P26) -> 3951 | R29: ='Cash Flow'!Q26 -> -5202 | S29: =('Cash Flow'!R26-'Cash Flow'!Q26) -> 3811 | T29: =('Cash Flow'!S26-'Cash Flow'!R26) -> 5043 | U29: =('Cash Flow'!L26-'Cash Flow'!S26) -> 3756 | V29: ='Cash Flow'!T26 -> 2021 | W29: =('Cash Flow'!U26-'Cash Flow'!T26) -> 5522 | Y29: 2026全年取公司指引，尚未完成独立现金流预测。
A30: 公司FCF：经营现金流－资本开支 | B30: 百万美元 | C30: =C29-C28 -> 1755 | D30: =D29-D28 -> 5104 | E30: 待分配 | F30: 待分配 | G30: =SUM(C30:D30) -> 6859 | H30: =H29-H28 -> 12400 | J30: =J29-J28 -> 11258 | K30: =K29-K28 -> 9534 | L30: =L29-L28 -> 9747 | M30: =M29-M28 -> 4741 | N30: =N29-N28 -> 5296 | P30: =P29-P28 -> -1728 | Q30: =Q29-Q28 -> 3148 | R30: =R29-R28 -> -5511 | S30: =S29-S28 -> 3369 | T30: =T29-T28 -> 4564 | U30: =U29-U28 -> 2874 | V30: =V29-V28 -> 1755 | W30: =W29-W28 -> 5104
A31: 集团税率指引 | B31: % | H31: =E229 -> 0.199 | Y31: 19.9%为集团基础税率，不能直接等同DCF经营税率。
A33: 下半年尚需产生的经营现金流 | B33: 百万美元 | H33: =H29-G29 -> 7057
A34: 下半年尚需投入的资本开支 | B34: 百万美元 | H34: =H28-G28 -> 1516
A35: 下半年公司FCF预算 | B35: 百万美元 | H35: =H33-H34 -> 5541
A37: Q4收入由全年指引与前3季度推算；它是待讨论的残余预测，不代表公司单独给出的Q4指引。
A38: 资本开支和折旧的季度分配暂沿用2025年下半年比例；后续以项目投产和处置时间修订。
A41: 二、未来年度：经营驱动与FCFF衔接
A42: 指标 | B42: 单位 | C42: FY2026E | D42: FY2027E | E42: FY2028E | F42: FY2029E | G42: FY2030E | H42: FY2031E | J42: FY2021 | K42: FY2022 | L42: FY2023 | M42: FY2024 | N42: FY2025 | P42: 2024Q3A | Q42: 2024Q4A | R42: 2025Q1A | S42: 2025Q2A | T42: 2025Q3A | U42: 2025Q4A | V42: 2026Q1A | W42: 2026Q2A | Y42: 判断依据 / 待讨论事项
A43: 情景选择（链接Valuation!C7） | C43: =Valuation!C7 -> 2 | D43: =CHOOSE(C43,"保守","基准","乐观") -> 基准 | E43: 1保守／2基准／3乐观 | Y43: 选择器切换同一套收入和利润公式；三种假设为分析建议。
A44: 期初公司可比收入 | B44: 百万美元 | C44: =N12 -> 48062 | D44: =C49 -> 49744.17 | E44: =D49 -> 49921.378 | F44: =E49 -> 52417.447 | G44: =F49 -> 54776.233 | H44: =G49 -> 57241.163
A45: 有机收入增长 | B45: % | C45: =H14 -> 0.05 | D45: =D513 -> 0.05 | E45: =E513 -> 0.05 | F45: =F513 -> 0.045 | G45: =G513 -> 0.045 | H45: =H513 -> 0.04 | J45: =J14 -> 0.16 | K45: =K14 -> 0.16 | L45: =L14 -> 0.12 | M45: =M14 -> 0.12 | N45: =N14 -> 0.05 | P45: =P14 -> 0.09 | Q45: =Q14 -> 0.14 | R45: =R14 -> 0.06 | S45: =S14 -> 0.05 | T45: =T14 -> 0.06 | U45: =U14 -> 0.05 | V45: =V14 -> 0.1 | W45: =W14 -> 0.06 | Y45: 三种情景由销量和价格／组合相加；详见503—513行。
A46: 汇率贡献 | B46: % | C46: =H15 -> 0.01 | D46: =D520 -> 0 | E46: =E520 -> 0 | F46: =F520 -> 0 | G46: =G520 -> 0 | H46: =H520 -> 0 | J46: =J15 -> 0.01 | K46: =K15 -> -0.07 | L46: =L15 -> -0.04 | M46: =M15 -> -0.05 | N46: =N15 -> -0.02 | P46: =P15 -> -0.05 | Q46: =Q15 -> 未补充 | R46: =R15 -> -0.05 | S46: =S15 -> -0.03 | T46: =T15 -> 0 | U46: =U15 -> 未补充 | V46: =V15 -> 0.02 | W46: =W15 -> 0.01 | Y46: 2027年起暂用中性汇率0%，仅为分析假设。
A47: 结构变化对收入的净影响 | B47: 百万美元 | C47: =N12*H16 -> -1201.55 | D47: =-$C$490 -> -2200 | E47: =0 -> 0 | F47: =0 -> 0 | G47: =0 -> 0 | H47: =0 -> 0 | J47: 待同口径桥 | K47: 待同口径桥 | L47: 待同口径桥 | M47: 待同口径桥 | N47: 待同口径桥 | P47: 待同口径桥 | Q47: 待同口径桥 | R47: 待同口径桥 | S47: 待同口径桥 | T47: 待同口径桥 | U47: 待同口径桥 | V47: 待同口径桥 | W47: 待同口径桥 | Y47: 2027从2026基期扣净退出收入22亿美元，再计算持续经营增长；2028起不假设新增并购处置。
A48: 持续经营及汇率收入增量 | B48: 百万美元 | C48: =C44*(C45+C46) -> 2883.72 | D48: =IF(COUNT(D44:D47)=4,(D44+D47)*(D45+D46),"待定") -> 2377.2085 | E48: =IF(COUNT(E44:E47)=4,(E44+E47)*(E45+E46),"待定") -> 2496.0689 | F48: =IF(COUNT(F44:F47)=4,(F44+F47)*(F45+F46),"待定") -> 2358.7851 | G48: =IF(COUNT(G44:G47)=4,(G44+G47)*(G45+G46),"待定") -> 2464.9305 | H48: =IF(COUNT(H44:H47)=4,(H44+H47)*(H45+H46),"待定") -> 2289.6465 | Y48: 2027先剔除CCBA净退出部分，避免对已退出收入继续计提有机增长。
