Workbook

Sheet Cover
A1: Uber Technologies, Inc. — Cover
A2: USD in million except per-share data | USD | as of 2026-09-08
A4: Uber Technologies, Inc. — Financial Model
A6: Ticker | B6: UBER
A7: Currency / Units | B7: USD in million except per-share data
A8: Reporting Framework | B8: US GAAP
A9: Fiscal Year End | B9: December 31
A10: Periods Covered | B10: FY2016 – FY2025 (annual only; no quarterly columns — see note below)
A11: Model Date | B11: 2026-09-08
A13: Sheet Guide
A14: Income Statement (IS) | B14: As-reported P&L, EPS/share count, Adjusted EBITDA bridge
A15: Balance Sheet (BS) | B15: As-reported balance sheet, balance check, working-capital analytics
A16: Cash Flow (CF) | B16: As-reported CFO/CFI/CFF detail, cash walk check, FCF analytics
A17: Segments (SEG) | B17: Mobility / Delivery / Freight (and legacy ATG / All Other) revenue and Adjusted EBITDA, tied to IS revenue
A18: Geography (GEO) | B18: Revenue by region and by country, tied to IS revenue
A19: Operating Metrics (OP) | B19: Gross Bookings, MAPCs, Trips and derived KPIs
A20: Derived Metrics (DM) | B20: Ratio and common-size analytics computed from metrics.md
A22: Key Comparability Notes
A23: 1. Revenue restatement | B23: FY2018-2019 revenue and cost of revenue were restated in the FY2020 10-K to reclassify certain Driver/Restaurant incentives as a reduction of revenue. This model uses the restated basis throughout.
A24: 2. Segment re-definition | B24: Reportable segments changed from 5 (2018-2020, incl. ATG and All Other) to 4 (2019-2021, ATG divested) to 3 (Mobility/Delivery/Freight only, from FY2021 10-K onward, All Other phased out).
A25: 3. Geography granularity | B25: Country-level revenue disclosure added a separate United Kingdom line starting the FY2023 10-K; prior years' 'All other countries' figure includes the UK.
A26: 4. ASC 842 adoption | B26: Operating lease right-of-use assets/liabilities first appear in FY2019 upon adoption of the new lease standard — not a data gap for FY2016-2018.
A27: 5. Interest presentation | B27: Uber began separately disclosing Interest income (previously netted within Other income (expense)) starting the FY2025 10-K, with FY2023 restated on a comparable basis.
A28: 6. Quarterly columns | B28: Omitted — the curated Tier-1 source (financial_input.json) contains only annual data; no quarterly time series was available to build a consistent quarterly block.
A30: Source Tiers | B30: Tier 1: data/curated financial_input.json (curated aggregates). Tier 2: SEC 10-K/10-Q source HTML (as-reported detail). Tier 3: sec-cleaned S-1/press releases (supplementary). Tier 4: metrics.md (derived ratios). See Sources sheet for the full table-level bibliography.

Sheet Income Statement
A1: Uber Technologies, Inc. — Income Statement
A2: USD in million except per-share data | USD | as of 2026-09-08
C3: FY2016 | D3: FY2017 | E3: FY2018 | F3: FY2019 | G3: FY2020 | H3: FY2021 | I3: FY2022 | J3: FY2023 | K3: FY2024 | L3: FY2025
A6: CONTENTS
A7: =HYPERLINK("#'Income Statement'!A11","1. INCOME STATEMENT")
A8: =HYPERLINK("#'Income Statement'!A44","2. EPS & SHARE COUNT")
A9: =HYPERLINK("#'Income Statement'!A51","3. NON-GAAP RECONCILIATION (ADJUSTED EBITDA)")
A11: 1. INCOME STATEMENT
A12: Revenue | C12: 3845 | D12: 7932 | E12: 10433 | F12: 13000 | G12: 11139 | H12: 17455 | I12: 31877 | J12: 37281 | K12: 43978 | L12: 52017
A13: YoY Growth | D13: =IF(N(C12)=0,"",D12/C12-1) | E13: =IF(N(D12)=0,"",E12/D12-1) | F13: =IF(N(E12)=0,"",F12/E12-1) | G13: =IF(N(F12)=0,"",G12/F12-1) | H13: =IF(N(G12)=0,"",H12/G12-1) | I13: =IF(N(H12)=0,"",I12/H12-1) | J13: =IF(N(I12)=0,"",J12/I12-1) | K13: =IF(N(J12)=0,"",K12/J12-1) | L13: =IF(N(K12)=0,"",L12/K12-1)
A14: Cost of revenue, exclusive of D&A shown separately below | C14: 2228 | D14: 4160 | E14: 4786 | F14: 6061 | G14: 5154 | H14: 9351 | I14: 19659 | J14: 22457 | K14: 26651 | L14: 31338
A15: Gross Profit | C15: =C12-C14 | D15: =D12-D14 | E15: =E12-E14 | F15: =F12-F14 | G15: =G12-G14 | H15: =H12-H14 | I15: =I12-I14 | J15: =J12-J14 | ... L15: =L12-L14
A16: Gross Margin | C16: =C15/C12 | D16: =D15/D12 | E16: =E15/E12 | F16: =F15/F12 | G16: =G15/G12 | H16: =H15/H12 | I16: =I15/I12 | J16: =J15/J12 | ... L16: =L15/L12
A18: Operations and support | E18: 1516 | F18: 2302 | G18: 1819 | H18: 1877 | I18: 2413 | J18: 2689 | K18: 2732 | L18: 2854
A19: Sales and marketing | E19: 3151 | F19: 4626 | G19: 3583 | H19: 4789 | I19: 4756 | J19: 4356 | K19: 4337 | L19: 4898
A20: Research and development | E20: 1505 | F20: 4836 | G20: 2205 | H20: 2054 | I20: 2798 | J20: 3164 | K20: 3109 | L20: 3402
A21: General and administrative | E21: 2082 | F21: 3299 | G21: 2666 | H21: 2316 | I21: 3136 | J21: 2682 | K21: 3639 | L21: 3241
A22: Depreciation and amortization | C22: 320 | D22: 510 | E22: 426 | F22: 472 | G22: 575 | H22: 902 | I22: 947 | J22: 823 | K22: 711 | L22: 719
A23: Total costs and expenses | B23: Full opex detail only disclosed from FY2018 (post-IPO 10-K comparatives) | E23: =E14+E18+E19+E20+E21+E22 | F23: =F14+F18+F19+F20+F21+F22 | G23: =G14+G18+G19+G20+G21+G22 | H23: =H14+H18+H19+H20+H21+H22 | I23: =I14+I18+I19+I20+I21+I22 | J23: =J14+J18+J19+J20+J21+J22 | K23: =K14+K18+K19+K20+K21+K22 | L23: =L14+L18+L19+L20+L21+L22
A24: Income (loss) from operations | C24: -3023 | D24: -4080 | E24: -3033 | F24: -8596 | G24: -4863 | H24: -3834 | I24: -1832 | J24: 1110 | K24: 2799 | L24: 5565
A25: Operating Margin | C25: =C24/C12 | D25: =D24/D12 | E25: =E24/E12 | F25: =F24/F12 | G25: =G24/G12 | H25: =H24/H12 | I25: =I24/I12 | J25: =J24/J12 | ... L25: =L24/L12
A26: YoY Growth | D26: =IF(N(C24)=0,"",D24/C24-1) | E26: =IF(N(D24)=0,"",E24/D24-1) | F26: =IF(N(E24)=0,"",F24/E24-1) | G26: =IF(N(F24)=0,"",G24/F24-1) | H26: =IF(N(G24)=0,"",H24/G24-1) | I26: =IF(N(H24)=0,"",I24/H24-1) | J26: =IF(N(I24)=0,"",J24/I24-1) | K26: =IF(N(J24)=0,"",K24/J24-1) | L26: =IF(N(K24)=0,"",L24/K24-1)
A27: Check: Revenue - Total Costs & Exp - Op. Income (should be ~0) | E27: =E12-E23-E24 | F27: =F12-F23-F24 | G27: =G12-G23-G24 | H27: =H12-H23-H24 | I27: =I12-I23-I24 | J27: =J12-J23-J24 | K27: =K12-K23-K24 | L27: =L12-L23-L24
A29: Net interest expense (pre-IPO presentation) | B29: FY2016-2017 filings did not separately break out interest expense/income; Tier-1 net figure used | C29: 334 | D29: 479
A30: Interest expense | E30: -648 | F30: -559 | G30: -458 | H30: -483 | I30: -565 | J30: -633 | K30: -523 | L30: -440
A31: Interest income | B31: Separately disclosed starting with the FY2025 10-K (FY2023 restated comparative); previously netted within Other income (expense) | J31: 484 | K31: 721 | L31: 743
A32: Other income (expense), net | E32: 4993 | F32: 722 | G32: -1625 | H32: 3292 | I32: -7029 | J32: 1360 | K32: 1128 | L32: -68
A33: Income (loss) before income taxes | C33: -3218 | D33: -4575 | E33: 1312 | F33: -8433 | G33: -6946 | H33: -1025 | I33: -9426 | J33: 2321 | K33: 4125 | L33: 5800
A34: Provision for (benefit from) income taxes | C34: 28 | D34: -542 | E34: 283 | F34: 45 | G34: -192 | H34: -492 | I34: -181 | J34: 213 | K34: -5758 | L34: -4346
A35: Income (loss) from equity method investments | E35: -42 | F35: -34 | G35: -34 | H35: -37 | I35: 107 | J35: 48 | K35: -38 | L35: -53
A36: Check: Income before tax - Tax + Equity Method - NI (should be ~0) | E36: =E33-E34+E35-E37 | F36: =F33-F34+F35-F37 | G36: =G33-G34+G35-G37 | H36: =H33-H34+H35-H37 | I36: =I33-I34+I35-I37 | J36: =J33-J34+J35-J37 | K36: =K33-K34+K35-K37 | L36: =L33-L34+L35-L37
A37: Net income (loss) including non-controlling interests | C37: -370 | D37: -4033 | E37: 987 | F37: -8512 | G37: -6788 | H37: -570 | I37: -9138 | J37: 2156 | K37: 9845 | L37: 10093
A38: Less: net income (loss) attributable to non-controlling interests, net of tax | C38: 0 | D38: 0 | E38: -10 | F38: -6 | G38: -20 | H38: -74 | I38: 3 | J38: 269 | K38: -11 | L38: 40
A39: Net income (loss) attributable to Uber Technologies, Inc. | C39: -370 | D39: -4033 | E39: 997 | F39: -8506 | G39: -6768 | H39: -496 | I39: -9141 | J39: 1887 | K39: 9856 | L39: 10053
A40: Check: NI incl. NCI - NCI - NI to Uber (should be ~0) | C40: =C37-C38-C39 | D40: =D37-D38-D39 | E40: =E37-E38-E39 | F40: =F37-F38-F39 | G40: =G37-G38-G39 | H40: =H37-H38-H39 | I40: =I37-I38-I39 | J40: =J37-J38-J39 | ... L40: =L37-L38-L39
A41: Net Margin | C41: =C39/C12 | D41: =D39/D12 | E41: =E39/E12 | F41: =F39/F12 | G41: =G39/G12 | H41: =H39/H12 | I41: =I39/I12 | J41: =J39/J12 | ... L41: =L39/L12
A42: YoY Growth | D42: =IF(N(C39)=0,"",D39/C39-1) | E42: =IF(N(D39)=0,"",E39/D39-1) | F42: =IF(N(E39)=0,"",F39/E39-1) | G42: =IF(N(F39)=0,"",G39/F39-1) | H42: =IF(N(G39)=0,"",H39/G39-1) | I42: =IF(N(H39)=0,"",I39/H39-1) | J42: =IF(N(I39)=0,"",J39/I39-1) | K42: =IF(N(J39)=0,"",K39/J39-1) | L42: =IF(N(K39)=0,"",L39/K39-1)
A44: 2. EPS & SHARE COUNT
A45: Basic EPS | B45: FY2016-2018: no meaningful per-share amounts presented pre-IPO | F45: -6.81 | G45: -3.86 | H45: -0.26 | I45: -4.64 | J45: 0.93 | K45: 4.71 | L45: 4.82
A46: Diluted EPS | F46: -6.81 | G46: -3.86 | H46: -0.29 | I46: -4.65 | J46: 0.87 | K46: 4.56 | L46: 4.73
A47: YoY Growth | D47: =IF(N(C46)=0,"",D46/C46-1) | E47: =IF(N(D46)=0,"",E46/D46-1) | F47: =IF(N(E46)=0,"",F46/E46-1) | G47: =IF(N(F46)=0,"",G46/F46-1) | H47: =IF(N(G46)=0,"",H46/G46-1) | I47: =IF(N(H46)=0,"",I46/H46-1) | J47: =IF(N(I46)=0,"",J46/I46-1) | K47: =IF(N(J46)=0,"",K46/J46-1) | L47: =IF(N(K46)=0,"",L46/K46-1)
A48: Weighted Avg Shares — Basic (millions) | E48: 443.368 | F48: 1248.353 | G48: 1752.96 | H48: 1892.546 | I48: 1972.131 | J48: 2035.651 | K48: 2094.602 | L48: 2085.253
A49: Weighted Avg Shares — Diluted (millions) | E49: 478.999 | F49: 1248.353 | G49: 1752.96 | H49: 1895.519 | I49: 1974.928 | J49: 2091.782 | K49: 2150.508 | L49: 2119.689
A51: 3. NON-GAAP RECONCILIATION (ADJUSTED EBITDA)
A52: Net income (loss) attributable to Uber (from above) | C52: =C39 | D52: =D39 | E52: =E39 | F52: =F39 | G52: =G39 | H52: =H39 | I52: =I39 | J52: =J39 | ... L52: =L39
A53: Add: Net income (loss) attributable to non-controlling interests, net of tax | E53: =E38 | F53: =F38 | G53: =G38 | H53: =H38 | I53: =I38 | J53: =J38 | K53: =K38 | L53: =L38
A54: Add: Loss (income) from equity method investments | E54: 42 | F54: 34 | G54: 34 | H54: 37 | I54: -107 | J54: -48 | K54: 38 | L54: 53
A55: Add: Provision for (benefit from) income taxes | E55: =E34 | F55: =F34 | G55: =G34 | H55: =H34 | I55: =I34 | J55: =J34 | K55: =K34 | L55: =L34
A56: Add (deduct): Other (income) expense, net | E56: =0-E32 | F56: =0-F32 | G56: =0-G32 | H56: =0-H32 | I56: =0-I32 | J56: =0-J32 | K56: =0-K32 | L56: =0-L32
A57: Add: Interest expense | E57: =0-E30 | F57: =0-F30 | G57: =0-G30 | H57: =0-H30 | I57: =0-I30 | J57: =0-J30 | K57: =0-K30 | L57: =0-L30
A58: Deduct: Interest income | J58: =0-J31 | K58: =0-K31 | L58: =0-L31
A59: =Income (loss) from operations | E59: =E24 | F59: =F24 | G59: =G24 | H59: =H24 | I59: =I24 | J59: =J24 | K59: =K24 | L59: =L24
A61: Add: Depreciation and amortization | E61: =E22 | F61: =F22 | G61: =G22 | H61: =H22 | I61: =I22 | J61: =J22 | K61: =K22 | L61: =L22
A62: Add: Stock-based compensation expense | E62: 172 | F62: 4596 | G62: 827 | H62: 1168 | I62: 1793 | J62: 1935 | K62: 1796 | L62: 1826
A63: Add: Legal, tax, and regulatory reserve changes and settlements | E63: 340 | F63: 353 | G63: -35 | H63: 526 | I63: 732 | J63: 9 | K63: 1123 | L63: 564
A64: Add: Driver appreciation award | F64: 299
A65: Add: Payroll tax on IPO stock-based compensation | F65: 86
A66: Add: Goodwill and asset impairments/loss on sale of assets, net | E66: 237 | F66: 8 | G66: 317 | H66: 157 | I66: 25 | J66: 84 | K66: 3 | L66: 2
A67: Add: Acquisition, financing and divestiture related expenses | E67: 15 | F67: 0 | G67: 86 | H67: 102 | I67: 46 | J67: 36 | K67: 25 | L67: 43
A68: Add: Accelerated lease costs related to cease-use of ROU assets | G68: 102 | H68: 5
A69: Add: COVID-19 response initiatives | G69: 106 | H69: 54
A70: Add (deduct): (Gain) loss on lease arrangement, net | E70: -4 | G70: -5 | I70: 7 | J70: 4 | K70: 2 | L70: 2
A71: Add: Restructuring and related charges, net | F71: 57 | G71: 362 | J71: 51 | K71: 25 | L71: 9
A72: Add: Legacy auto insurance transfer | H72: 103
A73: Add (deduct): Mass arbitration fees, net | H73: 43 | I73: -14
A74: Adjusted EBITDA | C74: -2517 | D74: -2642 | E74: -1847 | F74: -2725 | G74: -2528 | H74: -774 | I74: 1713 | J74: 4052 | K74: 6484 | L74: 8730
A75: Adjusted EBITDA Margin | C75: =C74/C12 | D75: =D74/D12 | E75: =E74/E12 | F75: =F74/F12 | G75: =G74/G12 | H75: =H74/H12 | I75: =I74/I12 | J75: =J74/J12 | ... L75: =L74/L12
A76: YoY Growth | D76: =IF(N(C74)=0,"",D74/C74-1) | E76: =IF(N(D74)=0,"",E74/D74-1) | F76: =IF(N(E74)=0,"",F74/E74-1) | G76: =IF(N(F74)=0,"",G74/F74-1) | H76: =IF(N(G74)=0,"",H74/G74-1) | I76: =IF(N(H74)=0,"",I74/H74-1) | J76: =IF(N(I74)=0,"",J74/I74-1) | K76: =IF(N(J74)=0,"",K74/J74-1) | L76: =IF(N(K74)=0,"",L74/K74-1)
A77: Bridge Check vs. Adjusted EBITDA (should be ~0) | E77: =E52+E53+E54+E55+E56+E57+E58+E61+E62+E63+E64+E65+E66+E67+E68+E69+E70+E71+E72+E73-E74 | F77: =F52+F53+F54+F55+F56+F57+F58+F61+F62+F63+F64+F65+F66+F67+F68+F69+F70+F71+F72+F73-F74 | G77: =G52+G53+G54+G55+G56+G57+G58+G61+G62+G63+G64+G65+G66+G67+G68+G69+G70+G71+G72+G73-G74 | H77: =H52+H53+H54+H55+H56+H57+H58+H61+H62+H63+H64+H65+H66+H67+H68+H69+H70+H71+H72+H73-H74 | I77: =I52+I53+I54+I55+I56+I57+I58+I61+I62+I63+I64+I65+I66+I67+I68+I69+I70+I71+I72+I73-I74 | J77: =J52+J53+J54+J55+J56+J57+J58+J61+J62+J63+J64+J65+J66+J67+J68+J69+J70+J71+J72+J73-J74 | K77: =K52+K53+K54+K55+K56+K57+K58+K61+K62+K63+K64+K65+K66+K67+K68+K69+K70+K71+K72+K73-K74 | L77: =L52+L53+L54+L55+L56+L57+L58+L61+L62+L63+L64+L65+L66+L67+L68+L69+L70+L71+L72+L73-L74

Sheet Balance Sheet
A1: Uber Technologies, Inc. — Balance Sheet
A2: USD in million except per-share data | USD | as of 2026-09-08
C3: FY2016 | D3: FY2017 | E3: FY2018 | F3: FY2019 | G3: FY2020 | H3: FY2021 | I3: FY2022 | J3: FY2023 | K3: FY2024 | L3: FY2025
A6: CONTENTS
A7: =HYPERLINK("#'Balance Sheet'!A12","1. ASSETS")
A8: =HYPERLINK("#'Balance Sheet'!A35","2. LIABILITIES")
A9: =HYPERLINK("#'Balance Sheet'!A50","3. EQUITY")
A10: =HYPERLINK("#'Balance Sheet'!A60","4. WORKING CAPITAL ANALYTICS")
A12: 1. ASSETS
A13: Cash and cash equivalents | C13: 6241 | D13: 4393 | E13: 6406 | F13: 10873 | G13: 5647 | H13: 4295 | I13: 4208 | J13: 4680 | K13: 5893 | L13: 7105
A14: Short-term investments | F14: 440 | G14: 1180 | I14: 103 | J14: 727 | K14: 1084 | L14: 528
A15: Restricted cash and cash equivalents, current | F15: 99 | G15: 250 | H15: 631 | I15: 680 | J15: 805 | K15: 545 | L15: 631
A16: Accounts receivable, net | D16: 739 | E16: 919 | F16: 1214 | G16: 1073 | H16: 2439 | I16: 2779 | J16: 3404 | K16: 3333 | L16: 3827
A17: Prepaid expenses and other current assets | F17: 1299 | G17: 1215 | H17: 1454 | I17: 1479 | J17: 1681 | K17: 1390 | L17: 1902
A18: Assets held for sale | G18: 517
A19: Total current assets | D19: 6837 | E19: 8658 | F19: 13925 | G19: 9882 | H19: 8819 | I19: 9249 | J19: 11297 | K19: 12245 | L19: 13993
A20: Check: Sum of current asset detail vs. Total current assets (should be ~0) | F20: =F13+F14+F15+F16+F17+F18-F19 | G20: =G13+G14+G15+G16+G17+G18-G19 | H20: =H13+H14+H15+H16+H17+H18-H19 | I20: =I13+I14+I15+I16+I17+I18-I19 | J20: =J13+J14+J15+J16+J17+J18-J19 | K20: =K13+K14+K15+K16+K17+K18-K19 | L20: =L13+L14+L15+L16+L17+L18-L19
A22: Restricted cash and cash equivalents, non-current | F22: 1095 | G22: 1494 | H22: 2879 | I22: 1789 | J22: 1519 | K22: 2172 | L22: 1911
A23: Collateral held by insurer | G23: 860
A24: Investments | F24: 10527 | G24: 9052 | H24: 11806 | I24: 4401 | J24: 6101 | K24: 8460 | L24: 9178
A25: Restricted investments | B25: New face line starting FY2022 | I25: 1614 | J25: 4779 | K25: 7019 | L25: 8874
A26: Equity method investments | F26: 1364 | G26: 1079 | H26: 800 | I26: 870 | J26: 353 | K26: 302 | L26: 287
A27: Property and equipment, net | D27: 1192 | E27: 1641 | F27: 1731 | G27: 1814 | H27: 1853 | I27: 2082 | J27: 2073 | K27: 1952 | L27: 1897
A28: Operating lease right-of-use assets | B28: ASC 842 adopted effective Jan 1, 2019; no ROU assets reported before FY2019 | F28: 1594 | G28: 1274 | H28: 1388 | I28: 1449 | J28: 1241 | K28: 1158 | L28: 1114
A29: Intangible assets, net | D29: 54 | E29: 82 | F29: 71 | G29: 1564 | H29: 2412 | I29: 1874 | J29: 1425 | K29: 1125 | L29: 1048
A30: Goodwill | D30: 39 | E30: 153 | F30: 167 | G30: 6109 | H30: 8420 | I30: 8263 | J30: 8151 | K30: 8066 | L30: 8931
A31: Deferred tax assets | B31: Became material after release of U.S. valuation allowance in FY2023 | K31: 6171 | L31: 10951
A32: Other assets | F32: 88 | G32: 124 | H32: 397 | I32: 518 | J32: 1760 | K32: 2574 | L32: 3618
A33: Total assets | C33: 15713 | D33: 15426 | E33: 23988 | F33: 31761 | G33: 33252 | H33: 38774 | I33: 32109 | J33: 38699 | K33: 51244 | L33: 61802
A35: 2. LIABILITIES
A36: Accounts payable | D36: 213 | E36: 150 | F36: 272 | G36: 235 | H36: 860 | I36: 728 | J36: 790 | K36: 858 | L36: 1013
A37: Short-term insurance reserves | F37: 1121 | G37: 1243 | H37: 1442 | I37: 1692 | J37: 2016 | K37: 2754 | L37: 3387
A38: Operating lease liabilities, current | F38: 196 | G38: 175 | H38: 185 | I38: 201 | J38: 190 | K38: 175 | L38: 169
A39: Accrued and other current liabilities | F39: 4050 | G39: 5112 | H39: 6537 | I39: 6232 | J39: 6458 | K39: 7689 | L39: 7751
A40: Liabilities held for sale | G40: 100
A41: Total current liabilities | D41: 3847 | E41: 4259 | F41: 5639 | G41: 6865 | H41: 9024 | I41: 8853 | J41: 9454 | K41: 11476 | L41: 12320
A42: Check: Sum of current liability detail vs. Total current liabilities (should be ~0) | F42: =F36+F37+F38+F39+F40-F41 | G42: =G36+G37+G38+G39+G40-G41 | H42: =H36+H37+H38+H39+H40-H41 | I42: =I36+I37+I38+I39+I40-I41 | J42: =J36+J37+J38+J39+J40-J41 | K42: =K36+K37+K38+K39+K40-K41 | L42: =L36+L37+L38+L39+L40-L41
A44: Long-term insurance reserves | F44: 2297 | G44: 2223 | H44: 2546 | I44: 3028 | J44: 4722 | K44: 7042 | L44: 9076
A45: Long-term debt, net of current portion | C45: 3087 | D45: 3048 | E45: 6869 | F45: 5707 | G45: 7560 | H45: 9276 | I45: 9265 | J45: 9459 | K45: 8347 | L45: 10521
A46: Operating lease liabilities, non-current | F46: 1523 | G46: 1544 | H46: 1644 | I46: 1673 | J46: 1550 | K46: 1454 | L46: 1390
A47: Other long-term liabilities | F47: 1412 | G47: 1306 | H47: 935 | I47: 786 | J47: 832 | K47: 449 | L47: 412
A48: Total liabilities | C48: 9198 | D48: 11773 | E48: 17196 | F48: 16578 | G48: 19498 | H48: 23425 | I48: 23605 | J48: 26017 | K48: 28768 | L48: 33719
A50: 3. EQUITY
A51: Redeemable non-controlling interests (mezzanine) | C51: 11111 | D51: 12210 | E51: 14177 | F51: 311 | G51: 787 | H51: 204 | I51: 430 | J51: 654 | K51: 93 | L51: 165
A52: Additional paid-in capital | F52: 30739 | G52: 35931 | H52: 38608 | I52: 40550 | J52: 42264 | K52: 42801 | L52: 38101
A53: Accumulated other comprehensive income (loss) | F53: -187 | G53: -535 | H53: -524 | I53: -443 | J53: -421 | K53: -517 | L53: -432
A54: Accumulated deficit | F54: -16362 | G54: -23130 | H54: -23626 | I54: -32767 | J54: -30594 | K54: -20726 | L54: -10628
A55: Total Uber Technologies, Inc. stockholders' equity (deficit) | C55: -4596 | D55: -8557 | E55: -7385 | F55: 14190 | G55: 12266 | H55: 14458 | I55: 7340 | J55: 11249 | K55: 21558 | L55: 27041
A56: Non-redeemable non-controlling interests | C56: 0 | D56: 0 | E56: 0 | F56: 682 | G56: 701 | H56: 687 | I56: 734 | J56: 779 | K56: 825 | L56: 877
A57: Total equity (deficit) | C57: -4596 | D57: -8557 | E57: -7385 | F57: 14872 | G57: 12967 | H57: 15145 | I57: 8074 | J57: 12028 | K57: 22383 | L57: 27918
A58: Balance Check: Assets - Liabilities - Redeemable NCI - Equity (should be ~0) | C58: =C33-C48-C51-C57 | D58: =D33-D48-D51-D57 | E58: =E33-E48-E51-E57 | F58: =F33-F48-F51-F57 | G58: =G33-G48-G51-G57 | H58: =H33-H48-H51-H57 | I58: =I33-I48-I51-I57 | J58: =J33-J48-J51-J57 | ... L58: =L33-L48-L51-L57
A60: 4. WORKING CAPITAL ANALYTICS
A61: Days Sales Outstanding (AR) | D61: =D16/'Income Statement'!D12*365 | E61: =E16/'Income Statement'!E12*365 | F61: =F16/'Income Statement'!F12*365 | G61: =G16/'Income Statement'!G12*365 | H61: =H16/'Income Statement'!H12*365 | I61: =I16/'Income Statement'!I12*365 | J61: =J16/'Income Statement'!J12*365 | K61: =K16/'Income Statement'!K12*365 | L61: =L16/'Income Statement'!L12*365
A62: Days Payable Outstanding (AP) | D62: =D36/'Income Statement'!D14*365 | E62: =E36/'Income Statement'!E14*365 | F62: =F36/'Income Statement'!F14*365 | G62: =G36/'Income Statement'!G14*365 | H62: =H36/'Income Statement'!H14*365 | I62: =I36/'Income Statement'!I14*365 | J62: =J36/'Income Statement'!J14*365 | K62: =K36/'Income Statement'!K14*365 | L62: =L36/'Income Statement'!L14*365
A63: Net Trade Cycle (DSO - DPO) | B63: Uber carries no inventory (asset-light platform business); DIO is not applicable and is omitted | D63: =D61-D62 | E63: =E61-E62 | F63: =F61-F62 | G63: =G61-G62 | H63: =H61-H62 | I63: =I61-I62 | J63: =J61-J62 | K63: =K61-K62 | L63: =L61-L62

Sheet Cash Flow
A1: Uber Technologies, Inc. — Cash Flow
A2: USD in million except per-share data | USD | as of 2026-09-08
C3: FY2016 | D3: FY2017 | E3: FY2018 | F3: FY2019 | G3: FY2020 | H3: FY2021 | I3: FY2022 | J3: FY2023 | K3: FY2024 | L3: FY2025
A6: CONTENTS
A7: =HYPERLINK("#'Cash Flow'!A12","1. OPERATING ACTIVITIES")
A8: =HYPERLINK("#'Cash Flow'!A47","2. INVESTING ACTIVITIES")
A9: =HYPERLINK("#'Cash Flow'!A65","3. FINANCING ACTIVITIES")
A10: =HYPERLINK("#'Cash Flow'!A86","4. CASH WALK & FCF ANALYTICS")
A12: 1. OPERATING ACTIVITIES
A13: Net income (loss) including non-controlling interests | C13: -370 | D13: -4033 | E13: 987 | F13: -8512 | G13: -6788 | H13: -570 | I13: -9138 | J13: 2156 | K13: 9845 | L13: 10093
A14: Depreciation and amortization | E14: 426 | F14: 472 | G14: 575 | H14: 902 | I14: 947 | J14: 823 | K14: 737 | L14: 747
A15: Bad debt expense | B15: Folded into Other starting the FY2025 10-K presentation | E15: 71 | F15: 92 | G15: 76 | H15: 109 | I15: 114 | J15: 92
A16: Stock-based compensation | C16: 107 | D16: 124 | E16: 170 | F16: 4596 | G16: 827 | H16: 1168 | I16: 1793 | J16: 1935 | K16: 1796 | L16: 1826
A17: Loss (gain) from sale of investments | H17: -413 | I17: 0 | J17: 74
A18: Gain on business divestitures, net | E18: -3214 | F18: 0 | G18: -204 | H18: -1684 | I18: -14 | J18: -204
A19: Deferred income taxes | E19: 35 | F19: -88 | G19: -266 | H19: -692 | I19: -441 | J19: 26 | K19: -6027 | L19: -4779
A20: Gain on extinguishment of convertible notes and settlement of derivatives | F20: -444
A21: Revaluation of derivative liabilities | E21: 501 | F21: -58
A22: Accretion of discount on long-term debt | E22: 318 | F22: 82 | G22: 45
A23: Payment-in-kind interest | E23: 71 | F23: 10
A24: Impairment of debt and equity securities | G24: 1690
A25: Impairments of goodwill, long-lived and other assets | E25: 197 | G25: 404 | H25: 116 | I25: 28 | J25: 86
A26: Impairment of equity method investment | I26: 182
A27: Loss (income) from equity method investments, net | E27: 42 | F27: 34 | G27: 34 | H27: 37 | I27: -107 | J27: -48
A28: Unrealized (gain) loss on debt and equity securities, net | E28: -1996 | F28: -2 | G28: 125 | H28: -1142 | I28: 7045 | J28: -1610 | K28: -1832 | L28: 97
A29: Accretion of discounts on marketable debt securities, net | B29: Separately broken out starting the FY2025 10-K; previously embedded in unrealized gain/loss line | J29: -154 | K29: -251 | L29: -158
A30: Revaluation of MLU B.V. call option | I30: -191
A31: Gain on forfeiture of unvested warrants and related share repurchases | E31: -152
A32: Unrealized foreign currency transactions | E32: 53 | F32: 16 | G32: 48 | H32: 38 | I32: 96 | J32: 138 | K32: 308 | L32: -120
A33: Other | E33: 60 | F33: -19 | G33: -43 | H33: 4 | I33: -7 | J33: 106 | K33: 187 | L33: 166
A35: Change in accounts receivable | E35: -279 | F35: -407 | G35: 142 | H35: -597 | I35: -542 | J35: -758 | K35: -142 | L35: -466
A36: Change in prepaid expenses and other assets | E36: -473 | F36: -478 | G36: 94 | H36: -236 | I36: -196 | J36: -1462 | K36: -694 | L36: -1028
A37: Change in collateral held by insurer | F37: -1199 | G37: 339 | H37: 860
A38: Change in operating lease right-of-use assets | F38: 201 | G38: 341 | H38: 165 | I38: 193 | J38: 191 | K38: 196 | L38: 177
A39: Change in accounts payable | E39: -39 | F39: 95 | G39: -133 | H39: 90 | I39: -133 | J39: 64 | K39: 86 | L39: 126
A40: Change in accrued insurance reserves | E40: 943 | F40: 481 | G40: -3 | H40: 516 | I40: 736 | J40: 2230 | K40: 2819 | L40: 2660
A41: Change in accrued expenses and other liabilities | E41: 738 | F41: 960 | G41: 83 | H41: 1068 | I41: 492 | J41: 80 | K41: 330 | L41: 967
A42: Change in operating lease liabilities | F42: -153 | G42: -131 | H42: -184 | I42: -215 | J42: -180 | K42: -221 | L42: -209
A43: Net cash provided by (used in) operating activities | C43: =C13+C14+C15+C16+C17+C18+C19+C20+C21+C22+C23+C24+C25+C26+C27+C28+C29+C30+C31+C32+C33+C35+C36+C37+C38+C39+C40+C41+C42 | D43: =D13+D14+D15+D16+D17+D18+D19+D20+D21+D22+D23+D24+D25+D26+D27+D28+D29+D30+D31+D32+D33+D35+D36+D37+D38+D39+D40+D41+D42 | E43: =E13+E14+E15+E16+E17+E18+E19+E20+E21+E22+E23+E24+E25+E26+E27+E28+E29+E30+E31+E32+E33+E35+E36+E37+E38+E39+E40+E41+E42 | F43: =F13+F14+F15+F16+F17+F18+F19+F20+F21+F22+F23+F24+F25+F26+F27+F28+F29+F30+F31+F32+F33+F35+F36+F37+F38+F39+F40+F41+F42 | G43: =G13+G14+G15+G16+G17+G18+G19+G20+G21+G22+G23+G24+G25+G26+G27+G28+G29+G30+G31+G32+G33+G35+G36+G37+G38+G39+G40+G41+G42 | H43: =H13+H14+H15+H16+H17+H18+H19+H20+H21+H22+H23+H24+H25+H26+H27+H28+H29+H30+H31+H32+H33+H35+H36+H37+H38+H39+H40+H41+H42 | I43: =I13+I14+I15+I16+I17+I18+I19+I20+I21+I22+I23+I24+I25+I26+I27+I28+I29+I30+I31+I32+I33+I35+I36+I37+I38+I39+I40+I41+I42 | J43: =J13+J14+J15+J16+J17+J18+J19+J20+J21+J22+J23+J24+J25+J26+J27+J28+J29+J30+J31+J32+J33+J35+J36+J37+J38+J39+J40+J41+J42 | ... L43: =L13+L14+L15+L16+L17+L18+L19+L20+L21+L22+L23+L24+L25+L26+L27+L28+L29+L30+L31+L32+L33+L35+L36+L37+L38+L39+L40+L41+L42
A44: Net cash provided by (used in) operating activities (as reported) | B44: As-reported figure (used for FY2016-2017 where full add-back detail is unavailable, and for cross-check FY2018-2025) | C44: -2913 | D44: -1418 | E44: -1541 | F44: -4321 | G44: -2745 | H44: -445 | I44: 642 | J44: 3585 | K44: 7137 | L44: 10099
A45: Check: Calculated CFO vs. As-Reported CFO (should be ~0) | E45: =E43-E44 | F45: =F43-F44 | G45: =G43-G44 | H45: =H43-H44 | I45: =I43-I44 | J45: =J43-J44 | K45: =K43-K44 | L45: =L43-L44
A47: 2. INVESTING ACTIVITIES
A48: Proceeds from sale and disposal of property and equipment | E48: 369 | F48: 51 | G48: 3
A49: Purchases of property and equipment | C49: -1629 | D49: -821 | E49: -558 | F49: -588 | G49: -616 | H49: -298 | I49: -252 | J49: -223 | K49: -242 | L49: -336
A50: Purchases of equity method investments | E50: -412
A51: Purchases of non-marketable equity securities | F51: -100 | G51: -10 | H51: -982 | I51: -14 | J51: -52 | K51: -289 | L51: -676
A52: Purchases of marketable securities | F52: -441 | G52: -2101 | H52: -1113 | I52: -1708 | J52: -8774 | K52: -12765 | L52: -21447
A53: Proceeds from maturities and sales of marketable securities | F53: 2 | G53: 1360 | H53: 2291 | I53: 376 | J53: 5069 | K53: 10204 | L53: 20046
A54: Proceeds from sale of non-marketable equity securities | H54: 500
A55: Proceeds from business disposal, net of cash divested | F55: 293 | I55: 26
A56: Proceeds from sale of equity method investments | H56: 1000 | J56: 721 | K56: 17
A57: Acquisition of businesses, net of cash acquired | E57: -64 | F57: -7 | G57: -1471 | H57: -2314 | I57: -59 | L57: -815
A58: Purchase of notes receivable | G58: -185 | H58: -297
A59: Return of capital from equity method investee | G59: 91
A60: Other investing activities | E60: -30 | G60: 60 | H60: 12 | I60: -6 | J60: 33 | K60: -102 | L60: -336
A61: Net cash used in investing activities | E61: =E48+E49+E50+E51+E52+E53+E54+E55+E56+E57+E58+E59+E60 | F61: =F48+F49+F50+F51+F52+F53+F54+F55+F56+F57+F58+F59+F60 | G61: =G48+G49+G50+G51+G52+G53+G54+G55+G56+G57+G58+G59+G60 | H61: =H48+H49+H50+H51+H52+H53+H54+H55+H56+H57+H58+H59+H60 | I61: =I48+I49+I50+I51+I52+I53+I54+I55+I56+I57+I58+I59+I60 | J61: =J48+J49+J50+J51+J52+J53+J54+J55+J56+J57+J58+J59+J60 | K61: =K48+K49+K50+K51+K52+K53+K54+K55+K56+K57+K58+K59+K60 | L61: =L48+L49+L50+L51+L52+L53+L54+L55+L56+L57+L58+L59+L60
A62: Net cash used in investing activities (as reported) | C62: -1858 | D62: -487 | E62: -695 | F62: -790 | G62: -2869 | H62: -1201 | I62: -1637 | J62: -3226 | K62: -3177 | L62: -3564
A63: Check: Calculated CFI vs. As-Reported CFI (should be ~0) | E63: =E61-E62 | F63: =F61-F62 | G63: =G61-G62 | H63: =H61-H62 | I63: =I61-I62 | J63: =J61-J62 | K63: =K61-K62 | L63: =L61-L62
A65: 3. FINANCING ACTIVITIES
A66: Proceeds from issuance of common stock upon IPO, net of offering costs | F66: 7973
A67: Taxes paid related to net share settlement of equity awards | F67: -1573 | G67: -17
A68: Proceeds from issuance of common stock, private placement | F68: 500
A69: Proceeds from issuance of subsidiary preferred stock units | F69: 1000 | G69: 247
A70: Proceeds from issuance of common stock under ESPP | F70: 49 | G70: 125 | H70: 107 | I70: 92 | J70: 130 | K70: 156 | L70: 183
A71: Proceeds from issuance and sale of subsidiary stock units | H71: 675 | I71: 255
A72: Issuance of term loan and notes, net of issuance costs | E72: 3466 | F72: 1189 | G72: 2628 | H72: 1766 | J72: 2824 | K72: 3972 | L72: 3359
A73: Principal repayment on term loan and notes | E73: -19 | F73: -27 | G73: -527 | H73: -309 | J73: -2675 | K73: -3986 | L73: -2350
A74: Principal repayment on Careem Notes | B74: Folded into Other financing activities from the FY2025 10-K presentation onward | G74: -891 | H74: -307 | I74: -80
A75: Principal repayment on revolving lines of credit | E75: -491
A76: Principal payments on capital and finance leases | E76: -89 | F76: -138 | G76: -224 | H76: -226 | I76: -184 | J76: -171 | K76: -172 | L76: -157
A77: Proceeds from issuance of redeemable convertible preferred stock | E77: 1750
A78: Repurchase of stock subject to put options related to Yandex | F78: -74
A79: Repurchases of common stock | K79: -1252 | L79: -6523
A80: Redemption of non-controlling interests | K80: -851 | L80: -109
A81: Other financing activities | E81: 23 | F81: 40 | G81: 38 | H81: 74 | I81: -68 | J81: -203 | K81: 46 | L81: -116
A82: Net cash provided by (used in) financing activities | E82: =E66+E67+E68+E69+E70+E71+E72+E73+E74+E75+E76+E77+E78+E79+E80+E81 | F82: =F66+F67+F68+F69+F70+F71+F72+F73+F74+F75+F76+F77+F78+F79+F80+F81 | G82: =G66+G67+G68+G69+G70+G71+G72+G73+G74+G75+G76+G77+G78+G79+G80+G81 | H82: =H66+H67+H68+H69+H70+H71+H72+H73+H74+H75+H76+H77+H78+H79+H80+H81 | I82: =I66+I67+I68+I69+I70+I71+I72+I73+I74+I75+I76+I77+I78+I79+I80+I81 | J82: =J66+J67+J68+J69+J70+J71+J72+J73+J74+J75+J76+J77+J78+J79+J80+J81 | K82: =K66+K67+K68+K69+K70+K71+K72+K73+K74+K75+K76+K77+K78+K79+K80+K81 | L82: =L66+L67+L68+L69+L70+L71+L72+L73+L74+L75+L76+L77+L78+L79+L80+L81
A83: Net cash provided by (used in) financing activities (as reported) | C83: 6194 | D83: 1015 | E83: 4640 | F83: 8939 | G83: 1379 | H83: 1780 | I83: 15 | J83: -95 | K83: -2087 | L83: -5713
A84: Check: Calculated CFF vs. As-Reported CFF (should be ~0) | E84: =E82-E83 | F84: =F82-F83 | G84: =G82-G83 | H84: =H82-H83 | I84: =I82-I83 | J84: =J82-J83 | K84: =K82-K83 | L84: =L82-L83
A86: 4. CASH WALK & FCF ANALYTICS
A87: Effect of exchange rate changes on cash | C87: -25 | D87: 22 | E87: -119 | F87: -4 | G87: -92 | H87: -69 | I87: -148 | J87: 63 | K87: -267 | L87: 215
A88: Net increase (decrease) in cash, cash equivalents and restricted cash | E88: 2285 | F88: 3824 | G88: -4327 | H88: 65 | I88: -1128 | J88: 327 | K88: 1606 | L88: 1037
A89: Cash Walk Check: CFO+CFI+CFF+FX - Net Change in Cash (should be ~0) | E89: =E44+E62+E83+E87-E88 | F89: =F44+F62+F83+F87-F88 | G89: =G44+G62+G83+G87-G88 | H89: =H44+H62+H83+H87-H88 | I89: =I44+I62+I83+I87-I88 | J89: =J44+J62+J83+J87-J88 | K89: =K44+K62+K83+K87-K88 | L89: =L44+L62+L83+L87-L88
A91: Free Cash Flow (CFO - Capex) | C91: =C44+C49 | D91: =D44+D49 | E91: =E44+E49 | F91: =F44+F49 | G91: =G44+G49 | H91: =H44+H49 | I91: =I44+I49 | J91: =J44+J49 | ... L91: =L44+L49
A92: YoY Growth | D92: =IF(N(C91)=0,"",D91/C91-1) | E92: =IF(N(D91)=0,"",E91/D91-1) | F92: =IF(N(E91)=0,"",F91/E91-1) | G92: =IF(N(F91)=0,"",G91/F91-1) | H92: =IF(N(G91)=0,"",H91/G91-1) | I92: =IF(N(H91)=0,"",I91/H91-1) | J92: =IF(N(I91)=0,"",J91/I91-1) | K92: =IF(N(J91)=0,"",K91/J91-1) | L92: =IF(N(K91)=0,"",L91/K91-1)
A93: Capex % of Revenue | C93: =0-C49/'Income Statement'!C12 | D93: =0-D49/'Income Statement'!D12 | E93: =0-E49/'Income Statement'!E12 | F93: =0-F49/'Income Statement'!F12 | G93: =0-G49/'Income Statement'!G12 | H93: =0-H49/'Income Statement'!H12 | I93: =0-I49/'Income Statement'!I12 | J93: =0-J49/'Income Statement'!J12 | ... L93: =0-L49/'Income Statement'!L12
A94: FCF Margin | C94: =C91/'Income Statement'!C12 | D94: =D91/'Income Statement'!D12 | E94: =E91/'Income Statement'!E12 | F94: =F91/'Income Statement'!F12 | G94: =G91/'Income Statement'!G12 | H94: =H91/'Income Statement'!H12 | I94: =I91/'Income Statement'!I12 | J94: =J91/'Income Statement'!J12 | ... L94: =L91/'Income Statement'!L12
A96: Supplemental: Cash paid for interest | E96: 124 | F96: 332 | G96: 412 | H96: 449 | I96: 513 | J96: 629 | K96: 475 | L96: 386
A97: Supplemental: Cash paid for income taxes | E97: 289 | F97: 133 | G97: 82 | H97: 87 | I97: 175 | J97: 234

Sheet Segments
A1: Uber Technologies, Inc. — Segments
A2: USD in million except per-share data | USD | as of 2026-09-08
C3: FY2016 | D3: FY2017 | E3: FY2018 | F3: FY2019 | G3: FY2020 | H3: FY2021 | I3: FY2022 | J3: FY2023 | K3: FY2024 | L3: FY2025
A6: CONTENTS
A7: =HYPERLINK("#'Segments'!A10","1. SEGMENT REVENUE")
A8: =HYPERLINK("#'Segments'!A19","2. SEGMENT ADJUSTED EBITDA & RECONCILIATION TO OPERATING INCOME")
A10: 1. SEGMENT REVENUE
A11: Mobility | E11: 9288 | F11: 10707 | G11: 6089 | H11: 6953 | I11: 14029 | J11: 19832 | K11: 25087 | L11: 29670
A12: Delivery | E12: 772 | F12: 1401 | G12: 3904 | H12: 8362 | I12: 10901 | J12: 12204 | K12: 13750 | L12: 17248
A13: Freight | E13: 356 | F13: 731 | G13: 1011 | H13: 2132 | I13: 6947 | J13: 5245 | K13: 5141 | L13: 5099
A14: ATG and Other Technology Programs | B14: Divested; segment discontinued after FY2020 | F14: 42 | G14: 100
A15: All Other | B15: Phased out; not reported as a separate segment from FY2021 10-K onward | E15: 17 | F15: 119 | G15: 35 | H15: 8
A16: Total Segment Revenue | E16: =E11+E12+E13+E14+E15 | F16: =F11+F12+F13+F14+F15 | G16: =G11+G12+G13+G14+G15 | H16: =H11+H12+H13+H14+H15 | I16: =I11+I12+I13+I14+I15 | J16: =J11+J12+J13+J14+J15 | K16: =K11+K12+K13+K14+K15 | L16: =L11+L12+L13+L14+L15
A17: Check: Total Segment Revenue vs. IS Revenue (should be ~0) | E17: =E16-'Income Statement'!E12 | F17: =F16-'Income Statement'!F12 | G17: =G16-'Income Statement'!G12 | H17: =H16-'Income Statement'!H12 | I17: =I16-'Income Statement'!I12 | J17: =J16-'Income Statement'!J12 | K17: =K16-'Income Statement'!K12 | L17: =L16-'Income Statement'!L12
A19: 2. SEGMENT ADJUSTED EBITDA & RECONCILIATION TO OPERATING INCOME
A20: Mobility Adjusted EBITDA | E20: 1541 | F20: 2071 | G20: 1169 | H20: 1596 | I20: 3299 | J20: 4963 | K20: 6497 | L20: 7899
A21: Delivery Adjusted EBITDA | E21: -601 | F21: -1372 | G21: -873 | H21: -348 | I21: 551 | J21: 1506 | K21: 2471 | L21: 3572
A22: Freight Adjusted EBITDA | E22: -102 | F22: -217 | G22: -227 | H22: -130 | I22: 0 | J22: -64 | K22: -74 | L22: -33
A23: ATG and Other Technology Programs Adjusted EBITDA | E23: -537 | F23: -499 | G23: -375
A24: All Other Adjusted EBITDA | E24: -50 | F24: -251 | G24: -86 | H24: -11
A25: Total Segment Adjusted EBITDA | E25: =E20+E21+E22+E23+E24 | F25: =F20+F21+F22+F23+F24 | G25: =G20+G21+G22+G23+G24 | H25: =H20+H21+H22+H23+H24 | I25: =I20+I21+I22+I23+I24 | J25: =J20+J21+J22+J23+J24 | K25: =K20+K21+K22+K23+K24 | L25: =L20+L21+L22+L23+L24
A27: Less: Corporate G&A and Platform R&D | E27: -1971 | F27: -2457 | G27: -2136 | H27: -1881 | I27: -2137 | J27: -2353 | K27: -2410 | L27: -2708
A28: Less: Depreciation and amortization | E28: -426 | F28: -472 | G28: -575 | H28: -902 | I28: -947 | J28: -823
A29: Less: Stock-based compensation | E29: -172 | F29: -4596 | G29: -827 | H29: -1168 | I29: -1793 | J29: -1935
A30: Less: Legal, tax, and regulatory reserve changes and settlements | E30: -340 | F30: -353 | G30: 35 | H30: -526 | I30: -732 | J30: -9
A31: Less: Driver appreciation award | F31: -299
A32: Less: Payroll tax on IPO stock-based compensation | F32: -86
A33: Less: Goodwill/asset impairments, loss on sale of assets, net | E33: -237 | F33: -8 | G33: -317 | H33: -157 | I33: -25 | J33: -84
A34: Less: Acquisition, financing and divestiture related expenses | E34: -15 | G34: -86 | H34: -102 | I34: -46 | J34: -36
A35: Less: Accelerated lease costs related to cease-use of ROU assets | G35: -102 | H35: -5
A36: Less: COVID-19 response initiatives | G36: -106 | H36: -54
A37: Add (less): Gain (loss) on lease arrangement, net | E37: 4 | G37: 5 | H37: 0 | I37: -7 | J37: -4
A38: Less: Impact of 2018 Divested Operations | E38: -127
A39: Less: Restructuring and related charges | F39: -57 | G39: -362 | H39: 0 | I39: -2 | J39: -51
A40: Less: Legacy auto insurance transfer | H40: -103
A41: Add (less): Mass arbitration fees, net | H41: 43 | I41: 14
A42: Income (loss) from operations | E42: =E25+E27+E28+E29+E30+E31+E32+E33+E34+E35+E36+E37+E38+E39+E40+E41 | F42: =F25+F27+F28+F29+F30+F31+F32+F33+F34+F35+F36+F37+F38+F39+F40+F41 | G42: =G25+G27+G28+G29+G30+G31+G32+G33+G34+G35+G36+G37+G38+G39+G40+G41 | H42: =H25+H27+H28+H29+H30+H31+H32+H33+H34+H35+H36+H37+H38+H39+H40+H41 | I42: =I25+I27+I28+I29+I30+I31+I32+I33+I34+I35+I36+I37+I38+I39+I40+I41 | J42: =J25+J27+J28+J29+J30+J31+J32+J33+J34+J35+J36+J37+J38+J39+J40+J41 | K42: =K25+K27+K28+K29+K30+K31+K32+K33+K34+K35+K36+K37+K38+K39+K40+K41 | L42: =L25+L27+L28+L29+L30+L31+L32+L33+L34+L35+L36+L37+L38+L39+L40+L41
A43: Check: Segment-derived Op. Income vs. IS Op. Income (should be ~0) | B43: From FY2024 (10-K-2025 vintage), the reconciliation bridge starts from Net income and no longer isolates a segment-EBITDA-to-operating-income subtotal in the same structure; see IS Non-GAAP Reconciliation block for FY2024-2025 bridge detail. Small residuals in FY2021-FY2022 (<3% of operating income) reflect de minimis reconciling items not separately itemized in the filings. | E43: =E42-'Income Statement'!E24 | F43: =F42-'Income Statement'!F24 | G43: =G42-'Income Statement'!G24 | H43: =H42-'Income Statement'!H24 | I43: =I42-'Income Statement'!I24 | J43: =J42-'Income Statement'!J24

Sheet Geography
A1: Uber Technologies, Inc. — Geography
A2: USD in million except per-share data | USD | as of 2026-09-08
C3: FY2016 | D3: FY2017 | E3: FY2018 | F3: FY2019 | G3: FY2020 | H3: FY2021 | I3: FY2022 | J3: FY2023 | K3: FY2024 | L3: FY2025
A6: CONTENTS
A7: =HYPERLINK("#'Geography'!A10","1. REVENUE BY REGION")
A8: =HYPERLINK("#'Geography'!A18","2. REVENUE BY COUNTRY")
A10: 1. REVENUE BY REGION
A11: United States and Canada | E11: 6226 | F11: 8465 | G11: 6611 | H11: 10094 | I11: 19474 | J11: 20436 | K11: 23618 | L11: 26469
A12: Latin America | E12: 1963 | F12: 1862 | G12: 1295 | H12: 1417 | I12: 1978 | J12: 2512 | K12: 2795 | L12: 3327
A13: Europe, Middle East and Africa | E13: 1495 | F13: 1852 | G13: 2086 | H13: 3213 | I13: 6944 | J13: 9904 | K13: 12529 | L13: 16364
A14: Asia Pacific | E14: 749 | F14: 821 | G14: 1147 | H14: 2731 | I14: 3481 | J14: 4429 | K14: 5036 | L14: 5857
A15: Total Revenue by Region | E15: =E11+E12+E13+E14 | F15: =F11+F12+F13+F14 | G15: =G11+G12+G13+G14 | H15: =H11+H12+H13+H14 | I15: =I11+I12+I13+I14 | J15: =J11+J12+J13+J14 | K15: =K11+K12+K13+K14 | L15: =L11+L12+L13+L14
A16: Check: Total by Region vs. IS Revenue (should be ~0) | E16: =E15-'Income Statement'!E12 | F16: =F15-'Income Statement'!F12 | G16: =G15-'Income Statement'!G12 | H16: =H15-'Income Statement'!H12 | I16: =I15-'Income Statement'!I12 | J16: =J15-'Income Statement'!J12 | K16: =K15-'Income Statement'!K12 | L16: =L15-'Income Statement'!L12
A18: 2. REVENUE BY COUNTRY
A19: United States | E19: 5824 | F19: 7968 | G19: 6082 | H19: 9058 | I19: 17953 | J19: 18620 | K19: 21429 | L19: 23771
A20: United Kingdom | B20: Separately disclosed as a distinct country line starting the FY2023 10-K; previously included within All other countries | J20: 6522 | K20: 8373 | L20: 10609
A21: All other countries | B21: FY2018-2022 figure includes United Kingdom (not yet broken out separately) | E21: 4609 | F21: 5032 | G21: 5057 | H21: 8397 | I21: 13924 | J21: 12139 | K21: 14176 | L21: 17637
A22: Total Revenue by Country | E22: =E19+E20+E21 | F22: =F19+F20+F21 | G22: =G19+G20+G21 | H22: =H19+H20+H21 | I22: =I19+I20+I21 | J22: =J19+J20+J21 | K22: =K19+K20+K21 | L22: =L19+L20+L21
A23: Check: Total by Country vs. IS Revenue (should be ~0) | E23: =E22-'Income Statement'!E12 | F23: =F22-'Income Statement'!F12 | G23: =G22-'Income Statement'!G12 | H23: =H22-'Income Statement'!H12 | I23: =I22-'Income Statement'!I12 | J23: =J22-'Income Statement'!J12 | K23: =K22-'Income Statement'!K12 | L23: =L22-'Income Statement'!L12

Sheet Operating Metrics
A1: Uber Technologies, Inc. — Operating Metrics
A2: USD in million except per-share data | USD | as of 2026-09-08
C3: FY2016 | D3: FY2017 | E3: FY2018 | F3: FY2019 | G3: FY2020 | H3: FY2021 | I3: FY2022 | J3: FY2023 | K3: FY2024 | L3: FY2025
A6: CONTENTS
A7: =HYPERLINK("#'Operating Metrics'!A9","1. OPERATING METRICS")
A9: 1. OPERATING METRICS
A10: Gross Bookings | C10: 19236 | D10: 34409 | E10: 49799 | F10: 65001 | G10: 57897 | H10: 90415 | I10: 115395 | J10: 137865 | K10: 162773 | L10: 193454
A11: YoY Growth | D11: =IF(N(C10)=0,"",D10/C10-1) | E11: =IF(N(D10)=0,"",E10/D10-1) | F11: =IF(N(E10)=0,"",F10/E10-1) | G11: =IF(N(F10)=0,"",G10/F10-1) | H11: =IF(N(G10)=0,"",H10/G10-1) | I11: =IF(N(H10)=0,"",I10/H10-1) | J11: =IF(N(I10)=0,"",J10/I10-1) | K11: =IF(N(J10)=0,"",K10/J10-1) | L11: =IF(N(K10)=0,"",L10/K10-1)
A12: Monthly Active Platform Consumers (millions) | C12: 45 | D12: 68 | E12: 91 | F12: 111 | G12: 93 | H12: 118 | I12: 131 | J12: 150 | K12: 171 | L12: 202
A13: YoY Growth | D13: =IF(N(C12)=0,"",D12/C12-1) | E13: =IF(N(D12)=0,"",E12/D12-1) | F13: =IF(N(E12)=0,"",F12/E12-1) | G13: =IF(N(F12)=0,"",G12/F12-1) | H13: =IF(N(G12)=0,"",H12/G12-1) | I13: =IF(N(H12)=0,"",I12/H12-1) | J13: =IF(N(I12)=0,"",J12/I12-1) | K13: =IF(N(J12)=0,"",K12/J12-1) | L13: =IF(N(K12)=0,"",L12/K12-1)
A14: Trips (millions) | C14: 1818 | D14: 3736 | E14: 5220 | F14: 6904 | G14: 5025 | H14: 6368 | I14: 7642 | J14: 9448 | K14: 11273 | L14: 13567
A15: YoY Growth | D15: =IF(N(C14)=0,"",D14/C14-1) | E15: =IF(N(D14)=0,"",E14/D14-1) | F15: =IF(N(E14)=0,"",F14/E14-1) | G15: =IF(N(F14)=0,"",G14/F14-1) | H15: =IF(N(G14)=0,"",H14/G14-1) | I15: =IF(N(H14)=0,"",I14/H14-1) | J15: =IF(N(I14)=0,"",J14/I14-1) | K15: =IF(N(J14)=0,"",K14/J14-1) | L15: =IF(N(K14)=0,"",L14/K14-1)
A17: Platform Take Rate (Revenue / Gross Bookings) | C17: ='Income Statement'!C12/C10 | D17: ='Income Statement'!D12/D10 | E17: ='Income Statement'!E12/E10 | F17: ='Income Statement'!F12/F10 | G17: ='Income Statement'!G12/G10 | H17: ='Income Statement'!H12/H10 | I17: ='Income Statement'!I12/I10 | J17: ='Income Statement'!J12/J10 | ... L17: ='Income Statement'!L12/L10
A18: Gross Bookings per MAPC ($) | C18: =C10/C12*1000 | D18: =D10/D12*1000 | E18: =E10/E12*1000 | F18: =F10/F12*1000 | G18: =G10/G12*1000 | H18: =H10/H12*1000 | I18: =I10/I12*1000 | J18: =J10/J12*1000 | ... L18: =L10/L12*1000
A19: Trips per MAPC | C19: =C14/C12 | D19: =D14/D12 | E19: =E14/E12 | F19: =F14/F12 | G19: =G14/G12 | H19: =H14/H12 | I19: =I14/I12 | J19: =J14/J12 | ... L19: =L14/L12

Sheet Derived Metrics
A1: Uber Technologies, Inc. — Derived Metrics
A2: USD in million except per-share data | USD | as of 2026-09-08
C3: FY2016 | D3: FY2017 | E3: FY2018 | F3: FY2019 | G3: FY2020 | H3: FY2021 | I3: FY2022 | J3: FY2023 | K3: FY2024 | L3: FY2025
A6: 1. CASH CONVERSION
A7: CFO margin | C7: -0.7576 | D7: -0.1788 | E7: -0.1477 | F7: -0.3324 | G7: -0.2464 | H7: -0.0255 | I7: 0.0201 | J7: 0.0962 | K7: 0.1623 | L7: 0.1941
A8: CFO / EBITDA | J8: 1.85 | K8: 2.03 | L8: 1.61
A9: Capex intensity | C9: 0.4252 | D9: 0.1045 | E9: 0.0535 | F9: 0.0452 | G9: 0.0553 | H9: 0.0171 | I9: 0.0079 | J9: 0.006 | K9: 0.0055 | L9: 0.0065
A10: CFO / capex | C10: -1.78 | D10: -1.71 | E10: -2.76 | F10: -7.35 | G10: -4.46 | H10: -1.49 | I10: 2.55 | J10: 16.08 | K10: 29.49 | L10: 30.06
A11: Cash flow after capex margin | C11: -1.1828 | D11: -0.2833 | E11: -0.2012 | F11: -0.3776 | G11: -0.3017 | H11: -0.0426 | I11: 0.0122 | J11: 0.0902 | K11: 0.1568 | L11: 0.1877
A12: Cash flow after capex | C12: -4548 | D12: -2247 | E12: -2099 | F12: -4909 | G12: -3361 | H12: -743 | I12: 390 | J12: 3362 | K12: 6895 | L12: 9763
A13: D&A / capex | C13: 0.2 | D13: 0.62 | E13: 0.76 | F13: 0.8 | G13: 0.93 | H13: 3.03 | I13: 3.76 | J13: 3.69 | K13: 2.94 | L13: 2.14
A15: 2. COMMON SIZE
A16: Cash / total assets | C16: 0.3972 | D16: 0.2848 | E16: 0.2671 | F16: 0.3423 | G16: 0.1698 | H16: 0.1108 | I16: 0.1311 | J16: 0.1209 | K16: 0.115 | L16: 0.115
A17: Receivables / total assets | D17: 0.0479 | E17: 0.0383 | F17: 0.0382 | G17: 0.0323 | H17: 0.0629 | I17: 0.0865 | J17: 0.088 | K17: 0.065 | L17: 0.0619
A18: PP&E / total assets | D18: 0.0773 | E18: 0.0684 | F18: 0.0545 | G18: 0.0546 | H18: 0.0478 | I18: 0.0648 | J18: 0.0536 | K18: 0.0381 | L18: 0.0307
A19: Right-of-use assets / total assets | F19: 0.0502 | G19: 0.0383 | H19: 0.0358 | I19: 0.0451 | J19: 0.0321 | K19: 0.0226 | L19: 0.018
A20: Goodwill / total assets | D20: 0.0025 | E20: 0.0064 | F20: 0.0053 | G20: 0.1837 | H20: 0.2172 | I20: 0.2573 | J20: 0.2106 | K20: 0.1574 | L20: 0.1445
A21: Intangible assets / total assets | D21: 0.0035 | E21: 0.0034 | F21: 0.0022 | G21: 0.047 | H21: 0.0622 | I21: 0.0584 | J21: 0.0368 | K21: 0.022 | L21: 0.017
A22: Cost of revenue / revenue | C22: 0.5795 | D22: 0.5245 | E22: 0.4587 | F22: 0.4662 | G22: 0.4627 | H22: 0.5357 | I22: 0.6167 | J22: 0.6024 | K22: 0.606 | L22: 0.6025
A24: 3. COVERAGE
A25: EBIT interest coverage | C25: -9.05 | D25: -8.52 | E25: -4.68 | F25: -15.38 | G25: -10.62 | H25: -7.94 | I25: -3.24 | J25: 7.45
A26: CFO cash-interest coverage | G26: -6.66 | H26: -0.99 | I26: 1.25 | J26: 5.7 | K26: 15.03 | L26: 26.16
A28: 4. DEBT BRIDGE
A29: Gross debt excluding leases | F29: 5791 | G29: 7914 | H29: 9388 | I29: 9361 | J29: 9560 | K29: 9575 | L29: 10600
A30: Lease liabilities | F30: 1719 | G30: 1719 | H30: 1829 | I30: 1874 | J30: 1740 | K30: 1629 | L30: 1559
A31: Net debt excluding leases | F31: -5522 | G31: 1087 | H31: 5093 | I31: 5050 | J31: 4153 | K31: 2598 | L31: 2967
A32: Net debt including leases | F32: -3803 | G32: 2806 | H32: 6922 | I32: 6924 | J32: 5893 | K32: 4227 | L32: 4526
A34: 5. EARNINGS QUALITY
A35: CFO / consolidated net income | E35: -1.56 | J35: 1.66 | K35: 0.72 | L35: 1
A36: Accrual ratio | D36: -0.168 | E36: 0.1283 | F36: -0.1504 | G36: -0.1244 | H36: -0.0035 | I36: -0.2759 | J36: -0.0404 | K36: 0.0602 | L36: -0.0001
A38: 6. GROWTH
A39: Revenue growth | D39: 1.0629 | E39: 0.3153 | F39: 0.246 | G39: -0.1432 | H39: 0.567 | I39: 0.8262 | J39: 0.1695 | K39: 0.1796 | L39: 0.1828
A40: Consolidated profit growth | F40: -9.6241 | K40: 3.5663 | L40: 0.0252
A41: Parent profit growth | F41: -9.5316 | K41: 4.2231 | L41: 0.02
A42: Revenue CAGR since first supplied period | L42: 0.3357
A44: 7. ISSUER APM
A45: Company-reported FCF margin | H45: -0.0426 | I45: 0.0122 | J45: 0.0902 | K45: 0.1568 | L45: 0.1877
A47: 8. LEVERAGE
A48: Net debt ex leases / EBITDA | J48: 2.15 | K48: 0.74 | L48: 0.47
A50: 9. LIQUIDITY
A51: Current ratio | D51: 1.78 | E51: 2.03 | F51: 2.47 | G51: 1.44 | H51: 0.98 | I51: 1.04 | J51: 1.19 | K51: 1.07 | L51: 1.14
A52: Quick ratio | D52: 1.33 | E52: 1.72 | F52: 2.22 | G52: 1.15 | H52: 0.75 | I52: 0.8 | J52: 0.93 | K52: 0.9 | L52: 0.93
A53: Cash-only ratio | D53: 1.14 | E53: 1.5 | F53: 1.93 | G53: 0.82 | H53: 0.48 | I53: 0.48 | J53: 0.5 | K53: 0.51 | L53: 0.58
A54: CFO / average current liabilities | E54: -0.3802 | F54: -0.8731 | G54: -0.4391 | H54: -0.056 | I54: 0.0718 | J54: 0.3917 | K54: 0.682 | L54: 0.8488
A56: 10. PROFITABILITY
A57: Gross margin | C57: 0.4205 | D57: 0.4755 | E57: 0.5413 | F57: 0.5338 | G57: 0.5373 | H57: 0.4643 | I57: 0.3833 | J57: 0.3976 | K57: 0.394 | L57: 0.3975
A58: Operating margin | C58: -0.7862 | D58: -0.5144 | E58: -0.2907 | F58: -0.6612 | G58: -0.4366 | H58: -0.2197 | I58: -0.0575 | J58: 0.0298 | K58: 0.0636 | L58: 0.107
A59: EBITDA margin | C59: -0.703 | D59: -0.4501 | E59: -0.2499 | F59: -0.6249 | G59: -0.385 | H59: -0.168 | I59: -0.0278 | J59: 0.0518 | K59: 0.0798 | L59: 0.1208
A60: Consolidated net margin | C60: -0.0962 | D60: -0.5084 | E60: 0.0946 | F60: -0.6548 | G60: -0.6094 | H60: -0.0327 | I60: -0.2867 | J60: 0.0578 | K60: 0.2239 | L60: 0.194
A61: Parent net margin | C61: -0.0962 | D61: -0.5084 | E61: 0.0956 | F61: -0.6543 | G61: -0.6076 | H61: -0.0284 | I61: -0.2868 | J61: 0.0506 | K61: 0.2241 | L61: 0.1933
A62: Effective tax rate | C62: -0.0087 | D62: 0.1185 | E62: 0.2157 | F62: -0.0053 | G62: 0.0276 | H62: 0.48 | I62: 0.0192 | J62: 0.0918 | K62: -1.3959 | L62: -0.7493
A64: 11. RETURNS
A65: ROA | D65: -0.259 | E65: 0.0501 | F65: -0.3054 | G65: -0.2088 | H65: -0.0158 | I65: -0.2578 | J65: 0.0609 | K65: 0.2189 | L65: 0.1786
A66: Parent ROE | D66: 0.6132 | E66: -0.1251 | F66: -2.4999 | G66: -0.5116 | H66: -0.0371 | I66: -0.8387 | J66: 0.203 | K66: 0.6008 | L66: 0.4137
A67: Consolidated ROE | D67: 0.6132 | E67: -0.1238 | F67: -2.2738 | G67: -0.4877 | H67: -0.0406 | I67: -0.7871 | J67: 0.2145 | K67: 0.5722 | L67: 0.4013
A68: Asset turnover | D68: 0.51 | E68: 0.53 | F68: 0.47 | G68: 0.34 | H68: 0.48 | I68: 0.9 | J68: 1.05 | K68: 0.98 | L68: 0.92
A69: Invested capital turnover | G69: 0.82 | H69: 0.89 | I69: 1.72 | J69: 2.26 | K69: 1.94 | L69: 1.73
A71: 12. SOLVENCY
A72: Equity ratio | C72: -0.2925 | D72: -0.5547 | E72: -0.3079 | F72: 0.4682 | G72: 0.39 | H72: 0.3906 | I72: 0.2515 | J72: 0.3108 | K72: 0.4368 | L72: 0.4517
A73: Gross debt ex leases / assets | F73: 0.1823 | G73: 0.238 | H73: 0.2421 | I73: 0.2915 | J73: 0.247 | K73: 0.1869 | L73: 0.1715
A74: Gross debt incl leases / assets | F74: 0.2365 | G74: 0.2897 | H74: 0.2893 | I74: 0.3499 | J74: 0.292 | K74: 0.2186 | L74: 0.1967
A75: Debt / equity ex leases | F75: 0.39 | G75: 0.61 | H75: 0.62 | I75: 1.16 | J75: 0.79 | K75: 0.43 | L75: 0.38
A76: Debt / equity incl leases | F76: 0.5 | G76: 0.74 | H76: 0.74 | I76: 1.39 | J76: 0.94 | K76: 0.5 | L76: 0.44
A78: 13. WORKING CAPITAL
A79: Days sales outstanding | E79: 29 | F79: 29.9 | G79: 37.5 | H79: 36.7 | I79: 29.9 | J79: 30.3 | K79: 28 | L79: 25.1
A80: Days payables outstanding | E80: 13.8 | F80: 12.7 | G80: 18 | H80: 21.4 | I80: 14.7 | J80: 12.3 | K80: 11.3 | L80: 10.9

Sheet Sources
A1: Uber Technologies, Inc. — Sources
A2: USD in million except per-share data | USD | as of 2026-09-08
A4: Source ID | B4: Filing / Document | C4: Path | D4: Tier
A5: S106 | B5: Uber Technologies, Inc. curated financial_input.json (FY2016-2025 annual aggregates) | C5: data/curated/companies/US/UBER-uber/financial_input.json | D5: 1
A6: S081 | B6: Uber 10-K for FY2018 (restated FY2018 comparatives) | C6: data/curated/companies/US/UBER-uber/financial_input.json (source ref) | D6: 1
A7: 10-K-2025 | B7: Uber 10-K for fiscal year 2025 (filed 2026) | C7: sources/companies/US/UBER-uber/sec/10-k-2025/source.html | D7: 2
A8: 10-K-2023 | B8: Uber 10-K for fiscal year 2023 (filed 2024) | C8: sources/companies/US/UBER-uber/sec/10-k-2023/source.html | D8: 2
A9: 10-K-2021 | B9: Uber 10-K for fiscal year 2021 (filed 2022) | C9: sources/companies/US/UBER-uber/sec/10-k-2021/source.html | D9: 2
A10: 10-K-2020 | B10: Uber 10-K for fiscal year 2020 (filed 2021) — restated FY2018-2019 comparatives | C10: sources/companies/US/UBER-uber/sec/10-k-2020/source.html | D10: 2
A11: 10-K-2019 | B11: Uber 10-K for fiscal year 2019 (filed 2020) | C11: sources/companies/US/UBER-uber/sec/10-k-2019/source.html | D11: 2
A12: 10-K-2022 | B12: Uber 10-K for fiscal year 2022 (filed 2023) | C12: sources/companies/US/UBER-uber/sec/10-k-2022/source.html | D12: 2
A13: 10-K-2024 | B13: Uber 10-K for fiscal year 2024 (filed 2025) | C13: sources/companies/US/UBER-uber/sec/10-k-2024/source.html | D13: 2
A14: 10-Q-2026Q2 | B14: Uber 10-Q for Q2 2026 | C14: sources/companies/US/UBER-uber/sec/10-q-2026q2/source.html | D14: 2
A15: sec-cleaned | B15: S-1 / 424B4 prospectus and 2026 Q1/Q2 earnings press releases (cleaned markdown) | C15: research/companies/US/UBER-uber/data/sec-cleaned/ | D15: 3
A16: metrics.md | B16: Curated derived-metrics workbook (ratios for Derived Metrics sheet) | C16: data/curated/companies/US/UBER-uber/metrics.md | D16: 4
